Workbook
Name BdgtNo: #REF!
Name BdgtNo: #REF!
Name BdgtNo: [1]index!$L$9
Name BdgtNo: #REF!
Name BdgtNo: #REF!
Name BdgtYear: #REF!
Name BdgtYear: #REF!
Name BdgtYear: [1]index!$L$8
Name BdgtYear: #REF!
Name BdgtYear: #REF!
Name BdgtYrFrom: #REF!
Name BdgtYrFrom: #REF!
Name BdgtYrFrom: [1]index!$L$13
Name BdgtYrFrom: #REF!
Name BdgtYrFrom: #REF!
Name BdgtYrTo: #REF!
Name BdgtYrTo: #REF!
Name BdgtYrTo: [1]index!$L$14
Name BdgtYrTo: #REF!
Name BdgtYrTo: #REF!
Name Description: "P_A_C_Ex"
Name FinYrFrom: #REF!
Name FinYrFrom: #REF!
Name FinYrFrom: [1]index!$L$11
Name FinYrFrom: #REF!
Name FinYrFrom: #REF!
Name FinYrTo: #REF!
Name FinYrTo: #REF!
Name FinYrTo: [1]index!$L$12
Name FinYrTo: #REF!
Name FinYrTo: #REF!
Name Head: #REF!
Name Head: #REF!
Name Head: '[1]a|ex|smry'!$B$1:$L$1
Name Head: #REF!
Name Head: #REF!
Name Last2Yr: #REF!
Name Last2Yr: #REF!
Name Last2Yr: [1]index!$L$7
Name Last2Yr: #REF!
Name Last2Yr: #REF!
Name Last3Yr: #REF!
Name Last3Yr: #REF!
Name Last3Yr: [1]index!$L$6
Name Last3Yr: #REF!
Name Last3Yr: #REF!
Name Last4Yr: #REF!
Name Last4Yr: #REF!
Name Last4Yr: [1]index!$L$5
Name Last4Yr: #REF!
Name Last4Yr: #REF!
Name Last5Yr: #REF!
Name Last5Yr: #REF!
Name Last5Yr: [1]index!$L$4
Name Last5Yr: #REF!
Name Last5Yr: #REF!
Name List_Smry_0: A_Capital_List!#REF!
Name List_Smry_0: A_Revenue_List!#REF!
Name List_Smry_0: C_Capital_List!#REF!
Name List_Smry_0: C_Revenue_List!#REF!

Sheet A_Revenue_Income
A1: जमेचा | G1: तपशील
A2: विवरण | C2: नक्की आकडा | H2: 2017-18 वर्षाचा अंदाज | J2: 2018-19 वर्षाचा अंदाज | M2: 2017-18 वर्षाच्या मान्य अंदाजाशी तुलना केलेला 2018-19 वर्षाचा मा. महा. आयुक्त यांनी सुचविलेला अंदाज
C3: 2014-15 | D3: 2015-16 | E3: 2016-17 | F3: 2016-17 शेवटची सहामाही | G3: 2017-18 पहिली सहामाही | H3: मान्य अंदाज | I3: दुरूस्त अंदाज | J3: मा. महापालिका आयुक्त यांनी सुचविलेला | K3: मा. स्थायी समितीने मान्यता दिलेला | L3: मा. महानगर- पालिकेने संमत केलेला
M5: अधिक | N5: कमी
A7: अधिनियमाप्रमाणे कमीत कमी रोख शिल्लक ठेवण्याची रक्कम जमेस धरून वर्षारंभीची शिल्लक | B7: 0 | C7: 100000 | D7: 100000 | E7: 100000 | F7: 100000 | G7: 0 | H7: 100000 | I7: 100000 | J7: 100000 | K7: 0 | L7: 0 | M7: 0 | N7: 0
C8: 0 | D8: 0 | E8: 0 | F8: 0 | G8: 0 | H8: 0 | I8: 0 | J8: 0 | K8: 0 | L8: 0 | M8: 0 | N8: 0
A9: १. सर्वसाधारण कर, अप्रत्यक्ष कर व इतर जमा | C9: 0 | D9: 0 | F9: 0 | G9: 0 | H9: 0 | I9: 0 | J9: 0 | K9: 0 | L9: 0 | M9: 0 | N9: 0
A10: क. सर्वसाधारण पट्टी | C10: 0 | D10: 0 | E10: 0 | F10: 0 | G10: 0 | H10: 0 | I10: 0 | J10: 0 | K10: 0 | L10: 0 | M10: 0 | N10: 0
A11: १. नागरिकांकडून (कआकसंप्र) | B11: RI11A101 | C11: 2428110703 | D11: 3224088721 | E11: 3579419675 | F11: 1562913282 | G11: 2149789191 | H11: 6690000000 | I11: 6690000000 | J11: 6000000000 | K11: 0 | L11: 0 | M11: 0 | N11: 690000000
A12: लोहगाव (उर्वरित) | B12: RI11AA101 | C12: 0 | D12: 0 | E12: 0 | F12: 0 | G12: 0 | H12: 0 | I12: 0 | J12: 66600000 | K12: 0 | L12: 0 | M12: 66600000 | N12: 0
A13: मुंढवा (उर्वरित केशवनगर) | B13: RI11AB101 | C13: 0 | D13: 0 | E13: 0 | F13: 0 | G13: 0 | H13: 0 | I13: 0 | J13: 31000000 | K13: 0 | L13: 0 | M13: 31000000 | N13: 0
A14: हडपसर (संपूर्ण साडेसतरानळी) | B14: RI11AC101 | C14: 0 | D14: 0 | E14: 0 | F14: 0 | G14: 0 | H14: 0 | I14: 0 | J14: 120800000 | K14: 0 | L14: 0 | M14: 120800000 | N14: 0
A15: शिवणे (संपूर्ण उत्तमनगर) | B15: RI11AD101 | C15: 0 | D15: 0 | E15: 0 | F15: 0 | G15: 0 | H15: 0 | I15: 0 | J15: 5600000 | K15: 0 | L15: 0 | M15: 5600000 | N15: 0
A16: शिवणे | B16: RI11AE101 | C16: 0 | D16: 0 | E16: 0 | F16: 0 | G16: 0 | H16: 0 | I16: 0 | J16: 40000000 | K16: 0 | L16: 0 | M16: 40000000 | N16: 0
A17: आंबेगाव खुर्द | B17: RI11AF101 | C17: 0 | D17: 0 | E17: 0 | F17: 0 | G17: 0 | H17: 0 | I17: 0 | J17: 28500000 | K17: 0 | L17: 0 | M17: 28500000 | N17: 0
A18: उंड्री | B18: RI11AG101 | C18: 0 | D18: 0 | E18: 0 | F18: 0 | G18: 0 | H18: 0 | I18: 0 | J18: 33100000 | K18: 0 | L18: 0 | M18: 33100000 | N18: 0
A19: धायरी | B19: RI11AH101 | C19: 0 | D19: 0 | E19: 0 | F19: 0 | G19: 0 | H19: 0 | I19: 0 | J19: 47600000 | K19: 0 | L19: 0 | M19: 47600000 | N19: 0
A20: आंबेगाव बुद्रुक | B20: RI11AJ101 | C20: 0 | D20: 0 | E20: 0 | F20: 0 | G20: 0 | H20: 0 | I20: 0 | J20: 73000000 | K20: 0 | L20: 0 | M20: 73000000 | N20: 0
A21: फुरसुंगी | B21: RI11AK101 | C21: 0 | D21: 0 | E21: 0 | F21: 0 | G21: 0 | H21: 0 | I21: 0 | J21: 85000000 | K21: 0 | L21: 0 | M21: 85000000 | N21: 0
A22: उरुळी देवाची | B22: RI11AL101 | C22: 0 | D22: 0 | E22: 0 | F22: 0 | G22: 0 | H22: 0 | I22: 0 | J22: 30200000 | K22: 0 | L22: 0 | M22: 30200000 | N22: 0
... A25: ४. पुणे वाहन व्यवहार खात्याकडील मिळकतींवरील कर (कआकसंप्र) | B25: RI11A104 | C25: 8123432 | D25: 26466145 | E25: 14042374 | F25: 4782935 | G25: 9081253 | H25: 20000000 | I25: 20000000 | J25: 10000000 | K25: 0 | L25: 0 | M25: 0 | N25: 10000000
C26: 0 | D26: 0 | E26: 0 | F26: 0 | G26: 0 | H26: 0 | I26: 0 | J26: 0 | K26: 0 | L26: 0 | M26: 0 | N26: 0
A27: क. सर्वसाधारण कर बेरीज | C27: 2521171745 | D27: 3485431565 | E27: 3814921689 | F27: 1680350959 | G27: 2253244415 | H27: 6910000000 | I27: 6910000000 | J27: 6711400000 | K27: 0 | L27: 0 | M27: 0 | N27: 198600000
C28: 0 | D28: 0 | E28: 0 | F28: 0 | G28: 0 | H28: 0 | I28: 0 | J28: 0 | K28: 0 | L28: 0 | M28: 0 | N28: 0
A29: ख. आयातकर | C29: 0 | D29: 0 | E29: 0 | F29: 0 | G29: 0 | H29: 0 | I29: 0 | J29: 0 | K29: 0 | L29: 0 | M29: 0 | N29: 0
A30: १. पक्की जमा (आ.क.प्र.) | B30: RI11B101 | C30: 87959085 | D30: 134378501 | E30: -10809081 | F30: -10809081 | G30: 235776 | H30: 0 | I30: 0 | J30: 0 | K30: 0 | L30: 0 | M30: 0 | N30: 0
C31: 0 | D31: 0 | E31: 0 | F31: 0 | G31: 0 | H31: 0 | I31: 0 | J31: 0 | K31: 0 | L31: 0 | M31: 0 | N31: 0
A32: निव्वळ जमा | C32: 87959085 | D32: 134378501 | E32: -10809081 | F32: -10809081 | G32: 235776 | H32: 0 | I32: 0 | J32: 0 | K32: 0 | L32: 0 | M32: 0 | N32: 0
C33: 0 | D33: 0 | E33: 0 | F33: 0 | G33: 0 | H33: 0 | I33: 0 | J33: 0 | K33: 0 | L33: 0 | M33: 0 | N33: 0
A34: ट्रॅन्झिट फी (रहदारी फी) (आ.क.प्र.) | B34: RI11B105 | C34: 136555000 | D34: 0 | E34: 0 | F34: 0 | G34: 0 | H34: 0 | I34: 0 | J34: 0 | K34: 0 | L34: 0 | M34: 0 | N34: 0
C35: 0 | D35: 0 | E35: 0 | F35: 0 | G35: 0 | H35: 0 | I35: 0 | J35: 0 | K35: 0 | L35: 0 | M35: 0 | N35: 0
A36: बेरीज | C36: 224514085 | D36: 134378501 | E36: -10809081 | F36: -10809081 | G36: 235776 | H36: 0 | I36: 0 | J36: 0 | K36: 0 | L36: 0 | M36: 0 | N36: 0
C37: 0 | D37: 0 | E37: 0 | F37: 0 | G37: 0 | H37: 0 | I37: 0 | J37: 0 | K37: 0 | L37: 0 | M37: 0 | N37: 0
A38: ख. निव्वळ आयातकर एकूण बेरीज | C38: 224514085 | D38: 134378501 | E38: -10809081 | F38: -10809081 | G38: 235776 | H38: 0 | I38: 0 | J38: 0 | K38: 0 | L38: 0 | M38: 0 | N38: 0
C39: 0 | D39: 0 | E39: 0 | F39: 0 | G39: 0 | H39: 0 | I39: 0 | J39: 0 | K39: 0 | L39: 0 | M39: 0 | N39: 0
A40: ख-१. स्थानिक संस्था कर | C40: 0 | D40: 0 | E40: 0 | F40: 0 | G40: 0 | H40: 0 | I40: 0 | J40: 0 | K40: 0 | L40: 0 | M40: 0 | N40: 0
A41: स्थानिक संस्था कर नोंदणी शुल्क | B41: RI11B201 | C41: 275729 | D41: 65050 | E41: -3033323 | F41: -3034348 | G41: 375 | H41: 0 | I41: 0 | J41: 0 | K41: 0 | L41: 0 | M41: 0 | N41: 0
A42: स्थानिक संस्था कर | B42: RI11B202 | C42: 9885567929 | D42: 6697263834 | E42: 3919870123 | F42: 2193581335 | G42: 1486050555 | H42: 5000000000 | I42: 5000000000 | J42: 10000000 | K42: 0 | L42: 0 | M42: 0 | N42: 4990000000
A43: चौरस मीटर बांधकामाप्रमाणे भरावयाची ठोक रक्कम | B43: RI11B202B | C43: 326733396 | D43: 218475764 | E43: 152493815 | F43: 101269415 | G43: 73722887 | H43: 170000000 | I43: 170000000 | J43: 0 | K43: 0 | L43: 0 | M43: 0 | N43: 170000000
A44: कंत्राटदाराने एकूण उलाढाल / करारानुसार ०.२५ % भरावयाची रक्कम | B44: RI11B202C | C44: 3925 | D44: 1153 | E44: 0 | F44: 0 | G44: 0 | H44: 0 | I44: 0 | J44: 0 | K44: 0 | L44: 0 | M44: 0 | N44: 0
A45: निर्गत मालापोटी १० % हिस्सा | B45: RI11B202D | C45: 16776728 | D45: 13727522 | E45: 6045544 | F45: 2704100 | G45: 1498056 | H45: 5000000 | I45: 5000000 | J45: 0 | K45: 0 | L45: 0 | M45: 0 | N45: 5000000
A46: इतर जमा - स्थानिक संस्था कर | B46: RI11B202E | C46: 886 | D46: 968005 | E46: 76000 | F46: 0 | G46: 0 | H46: 1000 | I46: 1000 | J46: 1000 | K46: 0 | L46: 0 | M46: 0 | N46: 0
A47: स्थानिक संस्था करापोटी व्याज | B47: RI11B203 | C47: 68901237 | D47: 28119768 | E47: 17179218 | F47: 10143086 | G47: 9762551 | H47: 1000 | I47: 1000 | J47: 500000 | K47: 0 | L47: 0 | M47: 499000 | N47: 0
A48: स्थानिक संस्था कर शास्ती (दंड) | B48: RI11B204 | C48: 13940851 | D48: 8211906 | E48: 2020670 | F48: 565000 | G48: 100000 | H48: 1000 | I48: 1000 | J48: 0 | K48: 0 | L48: 0 | M48: 0 | N48: 1000
A49: राज्य शासनाकडून मुद्रांक शुल्क अधिभारापोटी मिळालेली रक्कम (१%) | B49: RI11B206 | C49: 2483821000 | D49: 1756629960 | E49: 2194142347 | F49: 1538856234 | G49: 477309178 | H49: 1800000000 | I49: 1800000000 | J49: 0 | K49: 0 | L49: 0 | M49: 0 | N49: 1800000000
A50: मनपा ठेकेदारांच्या बिलांमधून एल.बी.टी. वसुली | B50: RI11B207 | C50: 30434564 | D50: 19452052 | E50: 11186427 | F50: 8099239 | G50: 2679137 | H50: 5000000 | I50: 5000000 | J50: 0 | K50: 0 | L50: 0 | M50: 0 | N50: 5000000
A51: राज्यशासनाकडून एल.बी.टी.साठी सहाय्यक अनुदान | B51: RI11B208 | C51: 0 | D51: 5774000000 | E51: 7646900000 | F51: 2969900000 | G51: 4285500000 | H51: 10353997000 | I51: 10353997000 | J51: 0 | K51: 0 | L51: 0 | M51: 0 | N51: 10353997000
C52: 0 | D52: 0 | E52: 0 | F52: 0 | G52: 0 | H52: 0 | I52: 0 | J52: 0 | K52: 0 | L52: 0 | M52: 0 | N52: 0
A53: ख-१. स्थानिक संस्था कर बेरीज | C53: 12826456245 | D53: 14516915014 | E53: 13946880821 | F53: 6822084061 | G53: 6336622739 | H53: 17334000000 | I53: 17334000000 | J53: 10501000 | K53: 0 | L53: 0 | M53: 0 | N53: 17323499000
C54: 0 | D54: 0 | E54: 0 | F54: 0 | G54: 0 | H54: 0 | I54: 0 | J54: 0 | K54: 0 | L54: 0 | M54: 0 | N54: 0
A55: वजा :- स्थानिक संस्था कर रिफंड | B55: RI11B251 | C55: 17626981 | D55: 16761083 | E55: 0 | F55: 0 | G55: 0 | H55: 30000000 | I55: 30000000 | J55: 40000000 | K55: 0 | L55: 0 | M55: 10000000 | N55: 0
C56: 0 | D56: 0 | E56: 0 | F56: 0 | G56: 0 | H56: 0 | I56: 0 | J56: 0 | K56: 0 | L56: 0 | M56: 0 | N56: 0
A57: ख-१. स्थानिक संस्था कर एकूण बेरीज | C57: 12808829264 | D57: 14500153931 | E57: 13946880821 | F57: 6822084061 | G57: 6336622739 | H57: 17304000000 | I57: 17304000000 | J57: -29499000 | K57: 0 | L57: 0 | M57: 0 | N57: 17333499000
C58: 0 | D58: 0 | E58: 0 | F58: 0 | G58: 0 | H58: 0 | I58: 0 | J58: 0 | K58: 0 | L58: 0 | M58: 0 | N58: 0
A59: राज्यशासनाकडून महाराष्ट्र वस्तू व सेवा कर अंतर्गत अनुदान (GST) | B59: RI11B209 | C59: 0 | D59: 0 | E59: 0 | F59: 0 | G59: 4119000000 | H59: 0 | I59: 0 | J59: 18820000000 | K59: 0 | L59: 0 | M59: 18820000000 | N59: 0
A60: ग. इतर कर | C60: 0 | D60: 0 | E60: 0 | F60: 0 | G60: 0 | H60: 0 | I60: 0 | J60: 0 | K60: 0 | L60: 0 | M60: 0 | N60: 0
A61: १. करमणूककर (कआकसंप्र) | B61: RI11C101 | C61: 13944890 | D61: 13464060 | E61: 14975320 | F61: 7695750 | G61: 7455400 | H61: 20000000 | I61: 20000000 | J61: 22500000 | K61: 0 | L61: 0 | M61: 2500000 | N61: 0
A62: २. व्यवसायकर (कआकसंप्र) शासनाकडून व्यवसाय करापोटी मिळणारी नुकसान भरपाई | B62: RI11C102 | C62: 2042874 | D62: 1929231 | E62: 0 | F62: 0 | G62: 0 | H62: 2300000 | I62: 2300000 | J62: 2300000 | K62: 0 | L62: 0 | M62: 0 | N62: 0
A63: ३. राज्य शासनाने बसविलेल्या करमणूककरापोटी मिळणारा हिस्सा (शासनाकडून) (कआकसंप्र) | B63: RI11C103 | C63: 0 | D63: 36848702 | E63: 0 | F63: 0 | G63: 0 | H63: 20000000 | I63: 20000000 | J63: 20000000 | K63: 0 | L63: 0 | M63: 0 | N63: 0
C64: 0 | D64: 0 | E64: 0 | F64: 0 | G64: 0 | H64: 0 | I64: 0 | J64: 0 | K64: 0 | L64: 0 | M64: 0 | N64: 0
A65: ग. बेरीज | C65: 15987764 | D65: 52241993 | E65: 14975320 | F65: 7695750 | G65: 7455400 | H65: 42300000 | I65: 42300000 | J65: 44800000 | K65: 0 | L65: 0 | M65: 2500000 | N65: 0
C66: 0 | D66: 0 | E66: 0 | F66: 0 | G66: 0 | H66: 0 | I66: 0 | J66: 0 | K66: 0 | L66: 0 | M66: 0 | N66: 0
A67: घ. महानगरपालिका अधिनियमाखाली दंडाबाबत शासकीय सहाय्य (वि. सल्लागार) | B67: RI11D101 | C67: 1399556 | D67: 1754405 | E67: 1398273 | F67: 1398273 | G67: 0 | H67: 0 | I67: 0 | J67: 0 | K67: 0 | L67: 0 | M67: 0 | N67: 0
C68: 0 | D68: 0 | E68: 0 | F68: 0 | G68: 0 | H68: 0 | I68: 0 | J68: 0 | K68: 0 | L68: 0 | M68: 0 | N68: 0
A69: ड-१ गुंतविलेल्या रकमांवरील व्याज (मु.ले.) | B69: RI11E101 | C69: 957978190 | D69: 695705904 | E69: 1136681699 | F69: 702490910 | G69: 417313706 | H69: 900000000 | I69: 900000000 | J69: 1050000000 | K69: 0 | L69: 0 | M69: 150000000 | N69: 0
A70: ड-३ विविध खात्यांच्या ऑडिट अहवालातून वसुली | B70: RI11E107 | C70: 1257401 | D70: 581701 | E70: 769540 | F70: 289704 | G70: 1420677 | H70: 1000000 | I70: 1000000 | J70: 1000000 | K70: 0 | L70: 0 | M70: 0 | N70: 0
A71: पुणे महानगरपालिकेस बक्षिसापोटी मिळालेल्या रकमा | B71: RI11E122 | C71: 0 | D71: 250000 | E71: 0 | F71: 0 | G71: 0 | H71: 250000 | I71: 250000 | J71: 602000 | K71: 0 | L71: 0 | M71: 352000 | N71: 0
A72: सेवकांसाठी सेवापुस्तक शुल्क | B72: RI11E123 | C72: 47380 | D72: 7565 | E72: 1860 | F72: 1860 | G72: 0 | H72: 0 | I72: 0 | J72: 0 | K72: 0 | L72: 0 | M72: 0 | N72: 0
C73: 0 | D73: 0 | E73: 0 | F73: 0 | G73: 0 | H73: 0 | I73: 0 | J73: 0 | K73: 0 | L73: 0 | M73: 0 | N73: 0
A74: ज. इतर जमा | C74: 0 | D74: 0 | E74: 0 | F74: 0 | G74: 0 | H74: 0 | I74: 0 | J74: 0 | K74: 0 | L74: 0 | M74: 0 | N74: 0
A75: १. जुनी रद्दी विक्री (मसआ.जिंघ.) | B75: RI11H101 | C75: 508451 | D75: 351589 | E75: 336827 | F75: 200494 | G75: 0 | H75: 200000 | I75: 200000 | J75: 400000 | K75: 0 | L75: 0 | M75: 200000 | N75: 0
A76: २. शुल्काचे उत्पन्न | C76: 0 | D76: 0 | E76: 0 | F76: 0 | G76: 0 | H76: 0 | I76: 0 | J76: 0 | K76: 0 | L76: 0 | M76: 0 | N76: 0
A77: अ. मसुदा शुल्क (वि. सल्लागार) | B77: RI11H102A | C77: 3892377 | D77: 4258800 | E77: 4911565 | F77: 2964023 | G77: 1092926 | H77: 7500000 | I77: 7500000 | J77: 7500000 | K77: 0 | L77: 0 | M77: 0 | N77: 0
A78: ब. दाव्याचा खर्च व प्रोसेस शुल्क (वि. सल्लागार) | B78: RI11H102B | C78: 2585571 | D78: 0 | E78: 0 | F78: -3000 | G78: 0 | H78: 200000 | I78: 200000 | J78: 200000 | K78: 0 | L78: 0 | M78: 0 | N78: 0
A79: क. नक्कल शुल्क (झोनिपु) | B79: RI11H102C | C79: 181683 | D79: 214772 | E79: 176631 | F79: 78290 | G79: 72632 | H79: 300000 | I79: 300000 | J79: 300000 | K79: 0 | L79: 0 | M79: 0 | N79: 0
A80: ड. अधिपत्र (Warrant) शुल्क (कआकसंप्र) | B80: RI11H102D | C80: 9973908 | D80: 29660663 | E80: 14083529 | F80: 11215829 | G80: 1899577 | H80: 20000000 | I80: 20000000 | J80: 20000000 | K80: 0 | L80: 0 | M80: 0 | N80: 0
A81: ई. सूचनापत्र (Notice) शुल्क (कआकसंप्र) | B81: RI11H102E | C81: 4430230 | D81: 5970368 | E81: 4355036 | F81: 3542390 | G81: 365818 | H81: 0 | I81: 0 | J81: 0 | K81: 0 | L81: 0 | M81: 0 | N81: 0
A82: फ. मिळकतीच्या मालकी हक्काबद्दल शुल्क (कआकसंप्र) | B82: RI11H102F | C82: 31562036 | D82: 73259763 | E82: 69135530 | F82: 31219619 | G82: 37733595 | H82: 70000000 | I82: 70000000 | J82: 80000000 | K82: 0 | L82: 0 | M82: 10000000 | N82: 0
A83: ग. मिळकतकर थकबाकी शास्ती (२%) (कआकसंप्र) | B83: RI11H102G | C83: 281401747 | D83: 388434483 | E83: 712193608 | F83: 538062240 | G83: 163068503 | H83: 1300000000 | I83: 1300000000 | J83: 950000000 | K83: 0 | L83: 0 | M83: 0 | N83: 350000000
C84: 0 | D84: 0 | E84: 0 | F84: 0 | G84: 0 | H84: 0 | I84: 0 | J84: 0 | K84: 0 | L84: 0 | M84: 0 | N84: 0
A85: ज२. बेरीज | C85: 334027552 | D85: 501798849 | E85: 804855899 | F85: 587079391 | G85: 204233051 | H85: 1398000000 | I85: 1398000000 | J85: 1058000000 | K85: 0 | L85: 0 | M85: 0 | N85: 340000000
C86: 0 | D86: 0 | E86: 0 | F86: 0 | G86: 0 | H86: 0 | I86: 0 | J86: 0 | K86: 0 | L86: 0 | M86: 0 | N86: 0
A87: ३. किरकोळ जमा | C87: 0 | D87: 0 | E87: 0 | F87: 0 | G87: 0 | H87: 0 | I87: 0 | J87: 0 | K87: 0 | L87: 0 | M87: 0 | N87: 0
A88: अ. न नेलेली व जप्त केलेली अनामत पक्की जमा (मु.ले.) | B88: RI11H103A | C88: 2344292 | D88: 846143 | E88: 554926 | F88: 31440 | G88: 0 | H88: 2000000 | I88: 2000000 | J88: 1000000 | K88: 0 | L88: 0 | M88: 0 | N88: 1000000
A89: ब. काटा भाडे (आ.क.प्र.) | B89: RI11H103B | C89: 120 | D89: 0 | E89: 0 | F89: 0 | G89: 0 | H89: 0 | I89: 0 | J89: 0 | K89: 0 | L89: 0 | M89: 0 | N89: 0
A90: क.१ मतदार याद्या विक्री (म.स.आ.) | B90: RI11H103C | C90: 87431 | D90: 27997 | E90: 1458419 | F90: 1442033 | G90: 0 | H90: 200000 | I90: 200000 | J90: 200000 | K90: 0 | L90: 0 | M90: 0 | N90: 0
A91: क.२ इतर किरकोळ जमा | B91: RI11H103D | C91: 597643 | D91: 11767 | E91: 45344 | F91: 27074 | G91: 0 | H91: 15000 | I91: 15000 | J91: 15000 | K91: 0 | L91: 0 | M91: 0 | N91: 0
A92: ड. इतर खात्यांकडील पुस्तके, मॅन्युअल्स्‌, नकाशे इ. (मसआ.जिंघ.) | B92: RI11H103E | C92: 86862 | D92: 194460 | E92: 29362 | F92: 15262 | G92: 2200 | H92: 100000 | I92: 100000 | J92: 100000 | K92: 0 | L92: 0 | M92: 0 | N92: 0
A93: ई. भांडार खात्याकडील जुने साहित्य विक्री (म.स.आ.) | B93: RI11H103F | C93: 2321725 | D93: 0 | E93: 11910838 | F93: 11910838 | G93: 0 | H93: 20000000 | I93: 20000000 | J93: 30000000 | K93: 0 | L93: 0 | M93: 10000000 | N93: 0
A94: ड. परत माल नोंद लेखनिकी खर्च (आ.क.प्र.) | B94: RI11H103I | C94: 400 | D94: 0 | E94: 0 | F94: 0 | G94: 0 | H94: 0 | I94: 0 | J94: 0 | K94: 0 | L94: 0 | M94: 0 | N94: 0
A95: छ. घरबांधणी कर्ज फॉर्म विक्री (मसआ.जिंघ.) | B95: RI11H103K | C95: 7420 | D95: 1200 | E95: 1500 | F95: 1200 | G95: 0 | H95: 1000 | I95: 1000 | J95: 0 | K95: 0 | L95: 0 | M95: 0 | N95: 1000
A96: सेवकवर्ग विभाग इतर जमा | B96: RI11H103N | C96: 4941 | D96: 7734 | E96: 2486592 | F96: 2466984 | G96: 1206 | H96: 0 | I96: 0 | J96: 2500000 | K96: 0 | L96: 0 | M96: 2500000 | N96: 0
A97: सुरक्षा विभाग इतर जमा | B97: RI11H103P | C97: 39483 | D97: 367664 | E97: 30869 | F97: 18824 | G97: 0 | H97: 0 | I97: 0 | J97: 0 | K97: 0 | L97: 0 | M97: 0 | N97: 0
A98: जकात फॉर्म विक्री (आ.क.प्र.) | B98: RI11H103Q | C98: 3424140 | D98: 0 | E98: 0 | F98: 0 | G98: 0 | H98: 0 | I98: 0 | J98: 0 | K98: 0 | L98: 0 | M98: 0 | N98: 0
A99: महाराष्ट्र माहितीचा अधिकार अधिनियम | B99: RI11H103R | C99: 393965 | D99: 514666 | E99: 662909 | F99: 389228 | G99: 313418 | H99: 300000 | I99: 300000 | J99: 450000 | K99: 0 | L99: 0 | M99: 150000 | N99: 0
... A102: जकात नाक्यांवरील उपहारगृह भाडेपोटी जमा | B102: RI11H103U | C102: 365491 | D102: 0 | E102: 0 | F102: 0 | G102: 0 | H102: 0 | I102: 0 | J102: 0 | K102: 0 | L102: 0 | M102: 0 | N102: 0
C103: 0 | D103: 0 | E103: 0 | F103: 0 | G103: 0 | H103: 0 | I103: 0 | J103: 0 | K103: 0 | L103: 0 | M103: 0 | N103: 0
A104: ज३. बेरीज | C104: 10624977 | D104: 3077464 | E104: 18284134 | F104: 16769418 | G104: 804640 | H104: 25116000 | I104: 25116000 | J104: 34265000 | K104: 0 | L104: 0 | M104: 9149000 | N104: 0
C105: 0 | D105: 0 | E105: 0 | F105: 0 | G105: 0 | H105: 0 | I105: 0 | J105: 0 | K105: 0 | L105: 0 | M105: 0 | N105: 0
A106: ज. इतर जमा एकूण बेरीज | C106: 345160980 | D106: 505227902 | E106: 823476860 | F106: 604049303 | G106: 205037691 | H106: 1423316000 | I106: 1423316000 | J106: 1092665000 | K106: 0 | L106: 0 | M106: 0 | N106: 330651000
...

Sheet A_Revenue_Expenditure
A1: योजनेतर खर्च तपशील
A2: विवरण | D2: नक्‍की आकडा | G2: मान्य अंदाज 2017-18 | H2: नवीन अंदाज 2018-19
D3: 2014-15 | E3: 2015-16 | F3: 2016-17
A5: १. मुख्य देखरेख, वसुली वगैरे | D5: 0 | E5: 0 | F5: 0 | G5: 0 | H5: 0
A6: क. महानगरपालिका व स्थायी समिती | D6: 0 | E6: 0 | F6: 0 | G6: 0 | H6: 0
A7: १ नगरसचिव यांचे कार्यालय | D7: 0 | E7: 0 | F7: 0 | G7: 0 | H7: 0
A8: १. नगरसचिव (म्युनिसिपल सेक्रेटरी) (मुं.प्रां. मनपा अधिनियम, कलम४५(३) प्रमाणे) वेतन | B8: RE11A101A | D8: 1101057 | E8: 1191964 | F8: 1345488 | G8: 2000000 | H8: 1500000
A9: २. कायम सेवकवर्ग वेतन | B9: RE11A102A | D9: 33475150 | E9: 35806543 | F9: 38012640 | G9: 45000000 | H9: 45000000
A10: ३. संकीर्ण (न.स.) | B10: RE11A103 | D10: 5578556 | E10: 5089168 | F10: 5914622 | G10: 10000000 | H10: 10000000
A11: ३अ. मागील बिले देण्यासाठी (न.स.) | B11: RE11A103A | D11: 643043 | E11: 713127 | F11: 2128349 | G11: 4000000 | H11: 4000000
A12: ४. प्रवास खर्च (न.स.) | B12: RE11A104 | D12: 3362 | E12: 35220 | F12: 12586 | G12: 1600000 | H12: 1800000
A13: ५. ग्रंथालय व वाचनालय | B13: RE11A105 | D13: 148487 | E13: 189830 | F13: 179955 | G13: 200000 | H13: 200000
A14: ६. समारंभ खर्च (न.स. व वि.अ.) | B14: RE11A106 | D14: 253700 | E14: 158700 | F14: 0 | G14: 500000 | H14: 500000
A15: १०. अखिल भारतीय/महाराष्ट्र महापौर परिषद व अखिल भारतीय स्थानिक स्वराज्य संस्था प्रतिनिधी अधिवेशन | B15: RE11A110 | D15: 1800 | E15: 0 | F15: 0 | G15: 160000 | H15: 200000
A16: ११. मनपा व शासकीय निवृत्त सेवकांना द्यावयाचा चहापान खर्च | B16: RE11A111 | D16: 73480 | E16: 46400 | F16: 780 | G16: 300000 | H16: 300000
A17: १३. महाराष्ट्र राज्य महानगरपालिका स्थायी समिती अध्यक्ष परिषद वर्गणी व तद्‌नुषंगिक खर्च | B17: RE11A113 | D17: 0 | E17: 0 | F17: 0 | G17: 800 | H17: 1000
A18: १४. मा. महापौर यांचा व्ययनियमन (सम्प्च्युअरी) भत्ता | B18: RE11A114 | D18: 0 | E18: 0 | F18: 0 | G18: 4000 | H18: 5000
A19: १५. मा. महापौर यांचा ऐच्छिक खर्च | B19: RE11A115 | D19: 260496 | E19: 290981 | F19: 159775 | G19: 200000 | H19: 200000
... A51: देशी खेळांना प्रोत्साहन देण्याकरिता शिबिरे व स्पर्धा आयोजित करणे. | B51: RE11A279 | D51: 0 | E51: 0 | F51: 0 | G51: 1000000 | H51: 0
D52: 0 | E52: 0 | F52: 0 | G52: 0 | H52: 0
A53: क. मनपा व स्थायी समिती बेरीज | D53: 69785307 | E53: 88248698 | F53: 111232206 | G53: 163519600 | H53: 150104000
D54: 0 | E54: 0 | F54: 0 | G54: 0 | H54: 0
A55: ख. मुख्य लेखापरिक्षक यांचे कार्यालय | D55: 0 | E55: 0 | F55: 0 | G55: 0 | H55: 0
A56: १. मुख्य लेखापरिक्षक (म्युनिसिपल चीफ ऑडिटर) (मु.प्रां. मनपा अधिनियम, कलम ४५ (३) प्रमाणे) यांचे वेतन | B56: RE11B101A | D56: 1626729 | E56: 1755460 | F56: 1610523 | G56: 2500000 | H56: 2500000
A57: २. कायम सेवकवर्ग वेतन | B57: RE11B102A | D57: 24303637 | E57: 28145211 | F57: 27837708 | G57: 32500000 | H57: 32500000
A58: ३. संकीर्ण | B58: RE11B103 | D58: 56982 | E58: 96249 | F58: 53529 | G58: 270000 | H58: 300000
D59: 0 | E59: 0 | F59: 0 | G59: 0 | H59: 0
A60: ख. मुख्यलेखापरिक्षक यांचे कार्या. बेरीज | D60: 25987348 | E60: 29996920 | F60: 29501760 | G60: 35270000 | H60: 35300000
D61: 0 | E61: 0 | F61: 0 | G61: 0 | H61: 0
A62: ग१. महापालिका आयुक्त यांचे कार्यालय | D62: 0 | E62: 0 | F62: 0 | G62: 0 | H62: 0
A63: १. महापालिका आयुक्त (म्युनिसिपल कमिशनर) (मु. प्रां. मनपा अधिनियम, कलम ३७ (१) प्रमाणे) यांचे वेतन | B63: RE11C101A | D63: 2711973 | E63: 1744095 | F63: 2174568 | G63: 3000000 | H63: 3000000
A64: २. उपआयुक्त (जनरल) (मुं. प्रां. मनपा अधिनियम, कलम ४५(३) प्रमाणे) यांचे वेतन | B64: RE11C102A | D64: 1139336 | E64: 1051185 | F64: 558905 | G64: 2000000 | H64: 2200000
A65: ३. कायम सेवकवर्ग वेतन | B65: RE11C103A | D65: 16474467 | E65: 15941845 | F65: 25487531 | G65: 25000000 | H65: 30000000
A66: ४. संकीर्ण | B66: RE11C104 | D66: 666868 | E66: 1929754 | F66: 1172964 | G66: 1350000 | H66: 1500000
A67: ६. मा. महापालिका आयुक्त यांचा ऐच्छिक खर्च (म.स.आ.) | B67: RE11C106 | D67: 0 | E67: 0 | F67: 0 | G67: 504000 | H67: 800000
D68: 0 | E68: 0 | F68: 0 | G68: 0 | H68: 0
A69: ग१. महापालिका आयुक्त कार्यालय बेरीज | D69: 20992644 | E69: 20666879 | F69: 29393968 | G69: 31854000 | H69: 37500000
D70: 0 | E70: 0 | F70: 0 | G70: 0 | H70: 0
A71: ग२. अतिरिक्त महापालिका आयुक्त (विशेष) यांचे कार्यालय | D71: 0 | E71: 0 | F71: 0 | G71: 0 | H71: 0
A72: १. अतिरिक्त महापालिका आयुक्त (विशेष) यांचे वेतन | B72: RE11C126A | D72: 756064 | E72: 945856 | F72: 1172527 | G72: 3000000 | H72: 3000000
A73: २. कायम सेवकवर्ग वेतन | B73: RE11C127A | D73: 11116883 | E73: 11788340 | F73: 12260312 | G73: 15000000 | H73: 15000000
A74: ३. संकीर्ण | B74: RE11C128 | D74: 129848 | E74: 108214 | F74: 187547 | G74: 630000 | H74: 700000
A75: ४. मनपा सेवकांस विविध सेमिनर, कॉन्फरन्स, प्रशिक्षण इ. साठी हजर राहण्यासाठी खर्च | B75: RE11C129 | D75: 63204 | E75: 54607 | F75: 17191 | G75: 216000 | H75: 300000
A76: 5. अतिरिक्त महापालिका आयुक्त (विशेष) यांचेकडे येणार्‍या पाहुण्यांचा आतिथ्याकरिता होणारा खर्च | B76: RE11C129C | D76: 15844 | E76: 11680 | F76: 14310 | G76: 144000 | H76: 200000
D77: 0 | E77: 0 | F77: 0 | G77: 0 | H77: 0
A78: ग२. अतिरिक्त महापालिका आयुक्त (विशेष) यांचे कार्यालय बेरीज | D78: 12081843 | E78: 12908697 | F78: 13651887 | G78: 18990000 | H78: 19200000
D79: 0 | E79: 0 | F79: 0 | G79: 0 | H79: 0
A80: ग३. अतिरिक्त महापालिका आयुक्त (जनरल) यांचे कार्यालय | D80: 0 | E80: 0 | F80: 0 | G80: 0 | H80: 0
A81: १. मा. अतिरिक्त महापालिका आयुक्त (जनरल) यांचे वेतन | B81: RE11C131A | D81: 0 | E81: 156177 | F81: 1017661 | G81: 3000000 | H81: 3000000
A82: २. कायम सेवकवर्ग वेतन | B82: RE11C132A | D82: 5670265 | E82: 8237117 | F82: 9750326 | G82: 10000000 | H82: 14700000
A83: ३. संकीर्ण | B83: RE11C133 | D83: 101416 | E83: 124563 | F83: 109248 | G83: 630000 | H83: 700000
A84: ४.अतिरिक्त महापालिका आयुक्त (जनरल) यांचेकडे येणार्‍या पाहुण्यांचा आतिथ्याकरिता होणारा खर्च | B84: RE11C134 | D84: 0 | E84: 1400 | F84: 14516 | G84: 144000 | H84: 200000
A85: ५. अधिकारी / सेवक प्रशिक्षण वर्ग / कार्यशाळेस उपस्थित राहण्याचा प्रवासखर्च, कार्यशाळा शुल्क, प्रशिक्षण शुल्क वगैरे | B85: RE11C135 | D85: 0 | E85: 0 | F85: 0 | G85: 216000 | H85: 300000
D86: 0 | E86: 0 | F86: 0 | G86: 0 | H86: 0
A87: ग३. अतिरिक्त महापालिका आयुक्त (जनरल) यांचे कार्यालय बेरीज | D87: 5771681 | E87: 8519257 | F87: 10891751 | G87: 13990000 | H87: 18900000
D88: 0 | E88: 0 | F88: 0 | G88: 0 | H88: 0
A89: ग४. अतिरिक्त महापालिका आयुक्त (इस्टेट) यांचे कार्यालय | D89: 0 | E89: 0 | F89: 0 | G89: 0 | H89: 0
A90: १. मा. अतिरिक्त महापालिका आयुक्त (इस्टेट) यांचे वेतन | B90: RE11C141 | D90: 836451 | E90: 1029923 | F90: 1303409 | G90: 3000000 | H90: 3000000
A91: २. कायम सेवकवर्ग वेतन | B91: RE11C142 | D91: 0 | E91: 7790663 | F91: 11057473 | G91: 10000000 | H91: 12500000
A92: ३. संकीर्ण | B92: RE11C143 | D92: 167836 | E92: 174390 | F92: 194543 | G92: 630000 | H92: 700000
A93: ४.अतिरिक्त महापालिका आयुक्त (इस्टेट) यांचेकडे येणार्‍या पाहुण्यांचा आतिथ्याकरिता होणारा खर्च | B93: RE11C144 | D93: 1400 | E93: 3560 | F93: 4300 | G93: 144000 | H93: 200000
A94: 6. प्रशिक्षण वर्ग / कार्यशाळेस उपस्थित राहण्याचा प्रवासखर्च | B94: RE11C146 | D94: 0 | E94: 0 | F94: 0 | G94: 0 | H94: 300000
A95: ग४. अतिरिक्त महापालिका आयुक्त (इस्टेट) यांचे कार्यालय बेरीज | D95: 1005687 | E95: 8998536 | F95: 12559725 | G95: 13774000 | H95: 16700000
A96: ग५. दक्षता विभाग | D96: 0 | E96: 0 | F96: 0 | G96: 0 | H96: 0
A97: १. कायम सेवकवर्ग वेतन | B97: RE11C151 | D97: 0 | E97: 6811234 | F97: 9876040 | G97: 10000000 | H97: 12300000
A98: २. संकीर्ण | B98: RE11C152 | D98: 28049 | E98: 35660 | F98: 69450 | G98: 180000 | H98: 200000
D99: 0 | E99: 0 | F99: 0 | G99: 0 | H99: 0
A100: ग५. दक्षता विभाग बेरीज | D100: 28049 | E100: 6846894 | F100: 9945490 | G100: 10180000 | H100: 12500000
D101: 0 | E101: 0 | F101: 0 | G101: 0 | H101: 0
A102: ग१+ग२+ग३+ग४+ग५ एकूण बेरीज | D102: 39879904 | E102: 57940263 | F102: 76442821 | G102: 88788000 | H102: 104800000
D103: 0 | E103: 0 | F103: 0 | G103: 0 | H103: 0
A104: घ१. उपआयुक्त (विशेष) यांचे कार्यालय | D104: 0 | E104: 0 | F104: 0 | G104: 0 | H104: 0
A105: १. उपआयुक्त (विशेष) (मुं. प्रां. मनपा अधिनियम, कलम ४५(३) प्रमाणे) यांचे वेतन | B105: RE11D101A | D105: 1031779 | E105: 1081781 | F105: 487765 | G105: 2000000 | H105: 2200000
A106: २. कायम सेवकवर्ग वेतन | B106: RE11D102A | D106: 4695065 | E106: 5128703 | F106: 6473172 | G106: 10000000 | H106: 12000000
A107: ३. संकीर्ण | B107: RE11D103 | D107: 67522 | E107: 106810 | F107: 99567 | G107: 135000 | H107: 150000
D108: 0 | E108: 0 | F108: 0 | G108: 0 | H108: 0
A109: घ१. उपआयुक्त (विशेष) कार्यालय बेरीज | D109: 5794366 | E109: 6317294 | F109: 7060504 | G109: 12135000 | H109: 14350000
D110: 0 | E110: 0 | F110: 0 | G110: 0 | H110: 0
A111: मुख्य समन्वयक कार्यालय (Smart City व AMRUT योजना) | D111: 0 | E111: 0 | F111: 0 | G111: 0 | H111: 0
A112: 1. संकीर्ण | B112: RE11D111 | D112: 0 | E112: 0 | F112: 1332134 | G112: 1350000 | H112: 1500000
D113: 0 | E113: 0 | F113: 0 | G113: 0 | H113: 0
A114: मुख्य समन्वयक कार्यालय (Smart City व AMRUT योजना) कार्यालय बेरीज | D114: 0 | E114: 0 | F114: 1332134 | G114: 1350000 | H114: 1500000
D115: 0 | E115: 0 | F115: 0 | G115: 0 | H115: 0
A116: घ२. सेवकवर्ग विभाग | D116: 0 | E116: 0 | F116: 0 | G116: 0 | H116: 0
A117: १. कायम सेवकवर्ग वेतन | B117: RE11D126A | D117: 14462421 | E117: 23459179 | F117: 24996357 | G117: 25000000 | H117: 30000000
A118: २. संकीर्ण | B118: RE11D127 | D118: 287881 | E118: 343005 | F118: 352110 | G118: 450000 | H118: 500000
A119: ४. विविध रिक्त पदे भरण्यासाठी आयोजित करण्यात येणार्‍या परीक्षांसाठी खर्च | B119: RE11D127B | D119: 105074 | E119: 0 | F119: 0 | G119: 3600000 | H119: 0
A120: ५. प्रशिक्षण प्रबोधिनीसाठी फर्निचर व तद्‌नुषंगिक कामे करणे व साहित्य घेणे | B120: RE11D127C | D120: 0 | E120: 0 | F120: 0 | G120: 720000 | H120: 900000
A121: ६. अधिकारी / कर्मचार्‍यांसाठी प्रशिक्षण आयोजन करणेसाठी खर्च | B121: RE11D127D | D121: 304943 | E121: 551627 | F121: 762802 | G121: 3000000 | H121: 3000000
A122: ७. पुणे मनपामध्ये बायोमॅट्रिक अटेंडन्स प्रणाली कार्यान्वीत करणे | B122: RE11D127E | D122: 0 | E122: 1388036 | F122: 0 | G122: 7200000 | H122: 9000000
A123: ८. सेवकवर्ग विभागासाठी फर्निचर करणे | B123: RE11D127F | D123: 0 | E123: 0 | F123: 0 | G123: 720000 | H123: 1000000
A124: नगरसेवकांसाठी नागरिक समस्या सोडविण्यासाठी प्रशिक्षण वर्ग | B124: RE11D127G | D124: 0 | E124: 0 | F124: 0 | G124: 0 | H124: 1000000
A125: समाविष्ट गावांतील सेवकांच्या वेतनासाठी | B125: RE11D127H | D125: 0 | E125: 0 | F125: 0 | G125: 0 | H125: 180000000
D126: 0 | E126: 0 | F126: 0 | G126: 0 | H126: 0
A127: घ२. सेवकवर्ग विभाग बेरीज | D127: 15160319 | E127: 25741847 | F127: 26111269 | G127: 40690000 | H127: 225400000
D128: 0 | E128: 0 | F128: 0 | G128: 0 | H128: 0
A129: घ२अ. सेवाभरती व परीक्षा नियंत्रण विभाग | D129: 0 | E129: 0 | F129: 0 | G129: 0 | H129: 0
A130: १. कायम सेवकवर्ग वेतन | B130: RE11D151 | D130: 0 | E130: 0 | F130: 0 | G130: 7000000 | H130: 7000000
A131: 3. विविध रिक्त पदे भरण्यासाठी आयोजित करण्यात येणार्‍या परीक्षांसाठी खर्च | B131: RE11D153 | D131: 0 | E131: 0 | F131: 160799 | G131: 0 | H131: 2500000
D132: 0 | E132: 0 | F132: 0 | G132: 0 | H132: 0
...

Sheet A_Revenue_List
F1: प्रकल्पीय रक्कम | G1: 1819 आयुक्त
A3: यादी क्र. R1
A4: थोर व्यक्तींच्या जयंती / पुण्यतिथी साजरी करणे
A5: RE11A274/R1-
A7: क्र. | B7: code | C7: ward | E7: कामाचे नाव | F7: प्रकल्पीय रक्कम | G7: तरतूद
A9: 1 | B9: RE11A274/R1-1 | E9: महात्मा फुले जयंती | G9: 100000
A10: 2 | B10: RE11A274/R1-2 | E10: डॉ. बाबासाहेब आंबेडकर जयंती | G10: 150000
A11: 3 | B11: RE11A274/R1-3 | E11: लोकशाहीर अण्णाभाऊ साठे जयंती | G11: 200000
A12: 4 | B12: RE11A274/R1-4 | E12: ईद-ए-मिलाद (पैगंबर जयंती) | G12: 150000
A13: 5 | B13: RE11A274/R1-5 | E13: शहरातील शिवजयंती साजरी करणे, रोषणाई करणे | G13: 200000
A14: 6 | B14: RE11A274/R1-6 | E14: महात्मा फुले यांची पुण्यतिथी साजरी करणे (दि. 28 नोव्हेंबर) | G14: 500000
A15: 7 | B15: RE11A274/R1-7 | E15: मौलाना अब्दुल कलाम आझाद जयंती व पुण्यतिथी साजरी करणे | G15: 600000
A16: 8 | B16: RE11A274/R1-8 | E16: लहुजी वस्ताद साळवे जयंती महोत्सव गंज पेठ व संगमवाडी येथे साजरा करणे | G16: 500000
A17: 9 | B17: RE11A274/R1-9 | E17: नेताजी सुभाषचंद्र बोस यांची जयंती साजरी करणे | G17: 10000
A18: 10 | B18: RE11A274/R1-10 | E18: येरवडा येथे लोकशाहिर अण्णाभाऊ साठे जयंती महोत्सव साजरा करणे | G18: 100000
A19: 11 | B19: RE11A274/R1-11 | E19: श्री संत रोहिदास महाराज जयंती, पुण्यतिथी साजरी करणे | G19: 50000
A20: 13 | B20: RE11A274/R1-13 | E20: मौलाना अबुल कलाम आझाद जयंती महोत्सव | G20: 500000
A21: 14 | B21: RE11A274/R1-14 | E21: महावीर जयंती | G21: 100000
E23: यादी क्र. R1 एकूण | F23: 0 | G23: 3160000
A26: यादी क्र. R2
A27: शहरामध्ये विविध कार्यक्रम, उत्सव, महोत्सव, संमेलन/ सहप्रायोजक तत्वावर कार्यक्रम साजरे करणे
A28: RE11A275/R2-
A30: क्र. | B30: code | C30: ward | E30: कामाचे नाव | F30: प्रकल्पीय रक्कम | G30: तरतूद
A32: 1 | B32: RE11A275/R2-1 | E32: महानगरपालिका वर्धापन दिन / सुवर्ण महोत्सव साजरा करणे | G32: 700000
A33: 2 | B33: RE11A275/R2-2 | E33: वर्षातील महत्त्वपूर्ण दिन | G33: 600000
A34: 3 | B34: RE11A275/R2-3 | E34: शिवाजीमहाराज आग्र्‍याहून सुटून परत आले तो स्मृती दिन साजरा करणे | G34: 515000
A35: 4 | B35: RE11A275/R2-4 | E35: शनिवारवाडा सांस्कृतिक महोत्सव | G35: 2000000
A36: 5 | B36: RE11A275/R2-5 | E36: भारतरत्न डॉ. बाबासाहेब आंबेडकर सांस्कृतिक महोत्सव साजरा करणे/ भिम फेस्टिवल (शनिवारवाडा पटांगण) / फुले आंबेडकर फेस्टिवल (समताभूमी) | G36: 2000000
A37: 6 | B37: RE11A275/R2-6 | E37: शिवमहोत्सव साजरा करणे (१४ ते २० फेब्रुवारी) | G37: 2000000
A38: 7 | B38: RE11A275/R2-7 | E38: अण्णाभाऊ साठे महोत्सव | G38: 2000000
A39: 8 | B39: RE11A275/R2-8 | E39: जागतिक आदिवासी दिन | G39: 500000
E41: यादी क्र. R2 एकूण | F41: 0 | G41: 10315000
A44: यादी क्र. R3
A45: सत्कार, अभिनंदन, पुरस्कार, बक्षिसे यासारखे कार्यक्रम साजरे करणे
A46: RE11A276/R3-
A48: क्र. | B48: code | C48: ward | E48: कामाचे नाव | F48: प्रकल्पीय रक्कम | G48: तरतूद
A50: 1 | B50: RE11A276/R3-1 | E50: गणेशोत्सव प्रशस्तिपत्रके वितरण | G50: 1000000
A51: 2 | B51: RE11A276/R3-2 | E51: श्री. संत ज्ञानेश्वर व तुकाराम महाराज पालखी स्वागत व दिंडी प्रमुखांचा स्मृतीचिन्ह देऊन सत्कार | G51: 1000000
A52: 3 | B52: RE11A276/R3-3 | E52: प्रतिवर्षी पुणे शहरातील इयत्ता १० वी, १२ वी परिक्षेत गुणवत्ता यादीत येणार्‍या विद्यार्थ्यांचे अभिनंदन | G52: 60000
A53: 4 | B53: RE11A276/R3-4 | E53: बालगंधर्व पुरस्कार प्रदानकरिता | G53: 500000
A54: 5 | B54: RE11A276/R3-5 | E54: पठ्ठे बापूराव पुरस्कारकरिता | G54: 500000
A55: 6 | B55: RE11A276/R3-6 | E55: आचार्य अत्रे पुरस्कारकरिता | G55: 300000
A56: 7 | B56: RE11A276/R3-7 | E56: पुणे आंतरराष्ट्रीय मॅरेथॉन स्पर्धेसाठी पारितोषिके | G56: 3000000
A57: 8 | B57: RE11A276/R3-8 | E57: महर्षि वाल्मिकी पुरस्कार | G57: 500000
A58: 9 | B58: RE11A276/R3-9 | E58: सावित्रीबाई फुले पुरस्कार | G58: 500000
A59: 10 | B59: RE11A276/R3-10 | E59: मौलाना अब्दुल कलाम आझाद पुरस्कार | G59: 500000
A60: 11 | B60: RE11A276/R3-11 | E60: जयंतराव टिळक पुरस्कार | G60: 500000
A61: 12 | B61: RE11A276/R3-12 | E61: १ ऑक्टोंबर - जागतिक ज्येष्ठ नागरिक दिनाच्या मेळाव्याकरता आच्छादित मंडप टाकणे व स्मृतिचिन्हे देणे | G61: 100000
... A75: 26 | B75: RE11A276/R3-29 | E75: गुरू गोविंदसिंगजी साहेब यांचे नावे पुरस्कार | G75: 300000
E77: यादी क्र. R3 एकूण | F77: 0 | G77: 14435000
A79: यादी क्र. R4
A80: शहरातील विविध स्मशानभूमी/ दफनभूमीमध्ये देखभाल दुरुस्ती कामे करणे
A81: RE17F169/R4-
A83: क्र. | B83: code | C83: ward | E83: कामाचे नाव | F83: प्रकल्पीय रक्कम | G83: तरतूद
A85: 1 | B85: RE17F169/R4-1 | E85: वैकुंठ स्मशानभूमी येथे सुधारणा कामे करणे | G85: 3500000
A86: 2 | B86: RE17F169/R4-2 | E86: शहरातील हिंदू स्मशानभूमीत सुधारणा कामे करणे | G86: 12500000
A87: 3 | B87: RE17F169/R4-3 | E87: शहरातील मुस्लिम कब्रस्तानात सुधारणा कामे करणे | G87: 11000000
A88: 4 | B88: RE17F169/R4-4 | E88: शहरातील ख्रिश्चन दफनभूमी येथे सुधारणा कामे करणे | G88: 7500000
A89: 5 | B89: RE17F169/R4-5 | E89: लिंगायत स्मशानभूमीत विविध सुधारणा कामे करणे | G89: 4000000
A90: 6 | B90: RE17F169/R4-6 | E90: लिंगायत ख्रिश्चन मुस्लिम स्मशानभूमीमध्ये माती टाकणे | G90: 2500000
E92: यादी क्र. R4 एकूण | F92: 0 | G92: 41000000
A94: यादी क्र. R7
A95: पुणे शहरातील हेरिटेज्‌ स्ट्रक्चरबाबत अनुषंगिक कामे करणे
A96: RE23H103/R7-
A98: क्र. | B98: code | C98: ward | E98: कामाचे नाव | F98: प्रकल्पीय रक्कम | G98: तरतूद
A100: 1 | B100: RE23H103/R7-1 | E100: पुणे शहरातील हेरिटेज्‌ स्ट्रक्चरबाबत अनुषगिक कामे करणे | G100: 12500000
A101: 2 | B101: RE23H103/R7-2 | E101: लाल महाल येथील मास्टर प्लिनिंगनुसार विविधविकास व दुरूस्तीची कामे करणे | G101: 5000000
A102: 3 | B102: RE23H103/R7-3 | E102: ऐतिहिसिक जुनी महात्मा फुले मंडई येथे मंडई दुरूस्ती करणे (गाळयांची डेव्हलपेमेंट +विदयुत व्यवस्था) | G102: 7500000
A103: 4 | B103: RE23H103/R7-4 | E103: विश्रामबागवाडा येथे दुरूस्ती, जतन व संवर्धनाची उर्वरित टप्प्यातील कामे करणे. | G103: 10000000
A104: 5 | B104: RE23H103/R7-5 | E104: नानावाडा येथे दुरूस्ती, जतन व संवर्धनाची उर्वरित टप्प्यातील कामे करणे. (दर्शनी व दगडी इमारत) | G104: 10000000
A105: 6 | B105: RE23H103/R7-7 | E105: शनिवारवाडा येथील देखभाल दुरूस्तीची कामे करणे | G105: 10000000
A106: 7 | B106: RE23H103/R7-8 | E106: पुणे शहरातील हेरिटेज स्ट्रक्चरल ऑडिट करणे | G106: 1500000
A107: 8 | B107: RE23H103/R7-9 | E107: आर्किटेक्ट फी अदा करणे | G107: 3000000
A108: 9 | B108: RE23H103/R7-10 | E108: भिडेवाडा येथे पहिली मुलांची शाळा/राषट्रीय स्मारक उभारणे. | G108: 2500000
A109: 10 | B109: RE23H103/R7-11 | E109: पुणे शहरातील प्राचिन कालीन ऐतिहासिक वास्तुंची विदयुत व्यवस्था, दुरूस्ती व सुशोभिकरण इ. कामे करणे. | G109: 5000000
A110: 11 | B110: RE23H103/R7-12 | E110: पुणे शहरातील 245 ऐतिहासिक वास्तुंपैकी धोकादायक वास्तुंची अत्यावशयक डागडुजी, दुरूस्ती करणे. | G110: 2500000
E111: टुरिस्ट हब अंतर्गत खालील कामे करणे (पुणे टुरिझम) :-
A112: 12 | B112: RE23H103/R7-13 | E112: पर्यटनवाढीसाठी विविध ब्रॉशर्स, पोस्टर्स, नकाशे, हेरिटेज पुस्तिका इ. तयार करणे | G112: 1000000
A113: 13 | B113: RE23H103/R7-14 | E113: पुणे शहरात विविध प्रकारचे वॉक, ट्रेल, मिनी बस टुर विकसित करणे. | G113: 2500000
A114: 14 | B114: RE23H103/R7-15 | E114: पर्यटकांसाठी विविध ठिकाणी माहिती फलक, दिशादशक साईनेज, होर्डिंग्ज, इ. उभारणे. | G114: 2000000
A115: 15 | B115: RE23H103/R7-16 | E115: पुणे टुरिस्ट डेस्टिनेशन करिता टुरिझम करीता मास्टर प्लॅन तयार करणे व त्या अनुषंगाने विकास कामे करणे | G115: 2500000
A116: 16 | B116: RE23H103/R7-17 | E116: पुणे ब्रँडिंग, मार्केटिंगच्या अनुषंगाने विविध कामे करणे | G116: 2500000
A117: 17 | B117: RE23H103/R7-18 | E117: पर्वती पायथा येथे चित्रकला, शिल्पकला सराव व प्रात्यक्षिकासाठी बैठक व्यवस्था करणे | G117: 1000000
A118: 18 | B118: RE23H103/R7-19 | E118: हेरीटेजविषयक ट्रेनिंग कार्यशाळा इ. साठी | G118: 500000
A119: 19 | B119: RE23H103/R7-21 | E119: प्रेक्षणीय स्थळांसाठीचे नियोजन पार्कींगसह | G119: 500000
A120: 20 | B120: RE23H103/R7-22 | E120: ऐतिहासिक वास्तूमध्ये फायर ऑडीट करणे व अग्निशमन यंत्रणा पुरविणे | G120: 2500000
E122: यादी क्र. R7 एकूण | F122: 0 | G122: 84500000
A124: यादी क्र. R8
A125: उद्यान विभागाकडील देखभाल दुरूस्तीची कामे
A126: RE26A120/R8-
A128: क्र. | B128: code | C128: ward | E128: कामाचे नाव | F128: प्रकल्पीय रक्कम | G128: तरतूद
A130: 1 | B130: RE26A120/R8-11 | E130: निरनिराळ्या उद्यानात बोअरवेल व पर्यायी पाण्याची व्यवस्था करणे | G130: 6000000
A131: 2 | B131: RE26A120/R8-12 | E131: उपआयुक्‍त क्र 1 मधील उद्यानात नावाच्या पाट्या बसविणे | G131: 500000
A132: 3 | B132: RE26A120/R8-13 | E132: उपआयुक्‍त क्र 2 मधील उद्यानात नावाच्या पाट्या बसविणे | G132: 500000
A133: 4 | B133: RE26A120/R8-14 | E133: उपआयुक्‍त क्र 3 मधील उद्यानात नावाच्या पाट्या बसविणे | G133: 500000
A134: 5 | B134: RE26A120/R8-15 | E134: उपआयुक्‍त क्र 4 मधील उद्यानात नावाच्या पाट्या बसविणे | G134: 500000
A135: 6 | B135: RE26A120/R8-21 | E135: उपआयुक्‍त क्र 5 मधील उद्यानात नावाच्या पाट्या बसविणे | G135: 500000
A136: 7 | B136: RE26A120/R8-16 | E136: विविध उद्यानातील तुषार ठिबक सिंचन योजना राबवणे व देखभाल दुरुस्ती इ | G136: 8000000
A137: 8 | B137: RE26A120/R8-17 | E137: विविध उद्यानातील विद्युत मोटार पंप देखभाल दुरुस्ती इ | G137: 4000000
A138: 9 | B138: RE26A120/R8-18 | E138: पुणे शहरातील उद्यानातील तलांवामध्ये पाणी स्वच्छ राहण्यासाठी एरिएटर बसविणे | G138: 2000000
...

Sheet A_Capital_Expenditure
A1: सन 2018-19 चे योजनांतर्गत | I1: खर्चाबाबतचे अंदाजपत्रक
A2: अनुक्रमांक | B2: मान्यतेचा ठराव क्र. दिनांक (कोड) | C2: प्रभाग क्रमांक | D2: BPL | E2: कामाचे नाव अगर वर्णन | F2: दि. 31 मार्च 2018 अखेरपर्यंत केलेली तरतूद | I2: दि. 31 मार्च 2017 पर्यंतचा खर्चाचा नक्‍की आकडा | J2: 2017-18 मधील खर्चाची अंदाजी रक्कम | L2: 2018-19 साठी अधिक तरतूद | N2: 2018-19 साठी एकूण तरतूद | O2: प्रकल्पीय रक्कम
F3: कर्जातून | G3: महसूल निधीतून | H3: एकूण | J3: प्रत्यक्ष उपलब्ध तरतूद | K3: कर्जातून तरतूद | L3: कर्जातून | M3: महसूल निधी व इतर निधी
E8: १. मनपा भवन व मनपा इमारती | F8: 0 | G8: 0 | H8: 0 | I8: 0 | J8: 0 | M8: 0 | N8: 0
A9: 1 | B9: CE11A122 | C9: G | E9: मनपा भवन येथे विस्तारित इमारत बांधणे व पुणे मनपा मिळकतीमध्ये क्षेत्रिय कार्यालय/ प्रशासकिय इमारतीचे विस्तारीकरण करणे | F9: 0 | G9: 110042095 | H9: 110042095 | I9: 110042095 | J9: 0 | M9: 0 | N9: 0 | O9: 200000000
A10: 2 | B10: CE11A129# | C10: J1- | D10: _ | E10: शहरात विविध ठिकाणी मनपासाठी इमारती बांधणे व विकास कामे करणे | F10: 0 | G10: 619391500 | H10: 619391500 | I10: 213494607 | J10: 405896893 | M10: 67500000 | N10: 67500000
F11: 0 | G11: 0 | H11: 0 | I11: 0 | J11: 0 | M11: 0 | N11: 0
E12: १. मनपा भवन व मनपा इमारती एकूण बेरीज | F12: 0 | G12: 729433595 | H12: 729433595 | I12: 323536702 | J12: 405896893 | M12: 67500000 | N12: 67500000
F13: 0 | G13: 0 | H13: 0 | I13: 0 | J13: 0 | M13: 0 | N13: 0
E14: २. प्राथमिक शिक्षण | F14: 0 | G14: 0 | H14: 0 | I14: 0 | J14: 0 | M14: 0 | N14: 0
A15: 1 | B15: CE12A264 | C15: G | D15: P | E15: पुणे शहरातील प्राथमिक शाळांमध्ये वर्गखोल्या, सिमाभिंत, स्वच्छतागृह, वॉचमन क्वॉर्टर, वॉटर प्रुफिंग, पाण्याची व्यवस्था व इतर तद्‌नुषंगिक कामे व देखभाल दुरूस्तीची कामे करणे | F15: 0 | G15: 99322156 | H15: 99322156 | I15: 99322156 | J15: 0 | M15: 0 | N15: 0 | O15: 37500000
A16: 2 | B16: CE12A381# | C16: J11- | D16: _ | E16: प्राथमिक शाळेमध्ये मुलभूत सोयी सुविधांसाठी विविध विकासकामे करणे | F16: 0 | G16: 1086115286 | H16: 1086115286 | I16: 962003220 | J16: 124112066 | M16: 292800000 | N16: 292800000
A17: 3 | B17: CE12A400 | C17: 67 | D17: P | E17: वि.स.खांडेकर शाळा दुसर्‍या मजल्यावर नविन ६ वर्ग खोल्या बांधणे | F17: 0 | G17: 5464342 | H17: 5464342 | I17: 5464342 | J17: 0 | M17: 0 | N17: 0
A18: 4 | B18: CE12A411 | C18: 67 | D18: P | E18: वॉर्ड क्र.११६ फायनल प्लॉट क्र.४७८ पर्वती येथील राजीव गांधी प्रायमरी शाळेचे उर्वरित काम पुर्ण करणे | F18: 0 | G18: 49557496 | H18: 49557496 | I18: 49557496 | J18: 0 | M18: 0 | N18: 0
A19: 5 | B19: CE12A412 | C19: 53 | D19: P | E19: वॉर्ड क्र. १२७ मधील हिंगणे खुर्द शाळा क्र. १६८ शाळेचा हॉल व वर्गखोल्या बांधणे व नुतनीकरण करणे | F19: 0 | G19: 4248634 | H19: 4248634 | I19: 4248634 | J19: 0 | M19: 0 | N19: 0
A20: 6 | B20: CE12A413 | C20: 43 | E20: वॉ.क्रं.९३ साधना विद्यालय येथे शाळा बांधणे | F20: 0 | G20: 19135330 | H20: 19135330 | I20: 19135330 | J20: 0 | M20: 0 | N20: 0
A21: 7 | B21: CE12A414 | C21: 36 | E21: एरंडवणा येथील मनपा च्या ताब्यात आलेल्या सन-डयु अपार्टमेंट या ठिकाणी इमारतीत प्राथमिक शाळेसाठी विविध विकासाची कामे करणे | F21: 0 | G21: 16701860 | H21: 16701860 | I21: 16701860 | J21: 0 | M21: 0 | N21: 0
A22: 9 | B22: CE12A417 | E22: मनपाच्या अस्तित्वात असलेल्या शाळा इमारतींमध्ये मुलींसाठी नवीन स्वच्छतागृहे बांधणे | F22: 0 | G22: 21655528 | H22: 21655528 | I22: 21655528 | J22: 0 | M22: 0 | N22: 0
A23: 12 | B23: CE12A420 | C23: 62 | E23: प्र.क्र.६२ कोंढवा बु. येथे शाळा इमारत बांधणे. | F23: 0 | G23: 5118234 | H23: 5118234 | I23: 5118234 | J23: 0 | M23: 0 | N23: 0
A24: 13 | B24: CE12A421 | E24: पुणे शहरातील मध्यवर्ती भागाच्या मनपा शाळांमध्ये विविध दुरूस्त्या व विकासकामे करणे | F24: 0 | G24: 5658310 | H24: 5658310 | I24: 5658310 | J24: 0 | M24: 0 | N24: 0
A25: 14 | B25: CE12A422# | C25: J2- | D25: _ | E25: प्राथमिक शाळेसाठी नवीन इमारत बांधणे | F25: 0 | G25: 432045500 | H25: 432045500 | I25: 61570297 | J25: 370475203 | M25: 21000000 | N25: 21000000
A26: 15 | B26: CE12A423# | C26: _ | D26: _ | E26: प्राथमिक शाळेसाठी वर्गखोल्या बांधणे | F26: 0 | G26: 61484000 | H26: 61484000 | I26: 48906901 | J26: 12577099 | M26: 0 | N26: 0
A27: 16 | B27: CE12A424# | C27: _ | D27: _ | E27: प्राथमिक शाळांची मैदाने विकसित करणे | F27: 0 | G27: 30727500 | H27: 30727500 | I27: 10533916 | J27: 20193584 | M27: 0 | N27: 0
A28: 18 | B28: #+ | E28: सन २०१४-१५ मधील अपूर्ण कामांसाठी सन २०१५-१६ मध्ये उपलब्ध केलेली तरतूद | F28: 0 | G28: 65921767 | H28: 65921767 | I28: 65921767 | J28: 0 | M28: 0 | N28: 0
F29: 0 | G29: 0 | H29: 0 | I29: 0 | J29: 0 | M29: 0 | N29: 0
E30: २. प्राथमिक शिक्षण एकूण बेरीज | F30: 0 | G30: 2002792660 | H30: 2002792660 | I30: 1475434708 | J30: 527357952 | M30: 313800000 | N30: 313800000
F31: 0 | G31: 0 | H31: 0 | I31: 0 | J31: 0 | M31: 0 | N31: 0
E32: ३. दुय्यम शिक्षण | F32: 0 | G32: 0 | H32: 0 | I32: 0 | J32: 0 | M32: 0 | N32: 0
A33: 1 | B33: CE13A128# | C33: J5- | E33: माध्यमिक शाळांमध्ये मुलभूत सोयी सुविधांसाठी विविध विकासकामे करणे | F33: 0 | G33: 17145412 | H33: 17145412 | I33: 14931759 | J33: 2213653 | M33: 2500000 | N33: 2500000
A34: 2 | B34: CE13A215 | D34: PL | E34: मनपा शाळांमध्ये मुलींसाठी स्वच्छतागृहे बांधणे | F34: 0 | G34: 27758288 | H34: 27758288 | I34: 27758288 | J34: 0 | M34: 0 | N34: 0
F35: 0 | G35: 0 | H35: 0 | I35: 0 | J35: 0 | M35: 0 | N35: 0
E36: ३. दुय्यम शिक्षण एकूण बेरीज | F36: 0 | G36: 44903700 | H36: 44903700 | I36: 42690047 | J36: 2213653 | M36: 2500000 | N36: 2500000
F37: 0 | G37: 0 | H37: 0 | I37: 0 | J37: 0 | M37: 0 | N37: 0
E38: ७. आरोग्य विभाग | F38: 0 | G38: 0 | H38: 0 | I38: 0 | J38: 0 | M38: 0 | N38: 0
A39: 2 | B39: CE17A192# | C39: J13- | D39: _ | E39: दवाखान्यातील मुलभूत सोयी सुविधांसाठी विविध विकासकामे करणे | F39: 0 | G39: 570695045 | H39: 570695045 | I39: 530104452 | J39: 40590593 | M39: 29500000 | N39: 29500000
A40: 3 | B40: CE17A205 | C40: 28 | D40: L | E40: सुतार रुग्णालय (कोथरूड) येथे विस्तारीकरण व इतर सुविधा पुरविणे | F40: 0 | G40: 30242691 | H40: 30242691 | I40: 30242691 | J40: 0 | M40: 0 | N40: 0
A41: 4 | B41: CE17A206 | C41: 23 | D41: L | E41: कमला नेहरू रुग्णालय प्रोजेक्ट अंतर्गत विविध उपकरणे खरेदी व तद्‌नुषंगिक कामे करणे | F41: 0 | G41: 258881822 | H41: 258881822 | I41: 258881822 | J41: 0 | M41: 0 | N41: 0
A42: 5 | B42: CE17A217 | D42: PL | E42: शहरातील इतर सर्व दवाखाने, प्रसुतिगृहे व रुग्णालये यांचेकरिता विविध शस्त्रे व उपकरणे खरेदी करणे | F42: 0 | G42: 201470861 | H42: 201470861 | I42: 201470861 | J42: 0 | M42: 0 | N42: 0
A43: 6 | B43: CE17A218 | D43: PL | E43: डॉ. नायडू हॉस्पिटल प्रोजेक्ट | F43: 0 | G43: 4409032 | H43: 4409032 | I43: 4409032 | J43: 0 | M43: 0 | N43: 0
A44: 7 | B44: CE17A227# | C44: J12- | D44: _ | E44: शहरातील विविध स्मशानभूमी / दफनभूमी साठी विविध विकासकामे करणे | F44: 0 | G44: 403698045 | H44: 403698045 | I44: 269818495 | J44: 133879550 | M44: 50000000 | N44: 50000000
A45: 8 | B45: CE17A230 | E45: कमला नेहरू रुग्णालयासाठी प्रयोगशाळा विकसित करणे | F45: 0 | G45: 15973740 | H45: 15973740 | I45: 15973740 | J45: 0 | M45: 0 | N45: 0
A46: 12 | B46: CE17A235 | C46: 9 | E46: बाणेर स.नं. १६४ मधील आरक्षित जागेमध्ये अद्ययावत सार्वजनिक रुग्णालयासह आरोग्य सुविधा उभारणे | F46: 0 | G46: 16779511 | H46: 16779511 | I46: 16779511 | J46: 0 | M46: 0 | N46: 0
A47: 13 | B47: CE17A236 | C47: 15 | E47: येरवडा मुस्लीम दफन भूमी येथे सिमाभिंत बांधणे. | F47: 0 | G47: 7593458 | H47: 7593458 | I47: 7593458 | J47: 0 | M47: 0 | N47: 0
A48: 15 | B48: CE17A238 | C48: 52 | E48: वैकुंठ स्मशानभूमीत संथारा मरण व्यक्तिस अग्री देण्यासाठी स्वतंत्र चौथरा व शेड बांधणे. | F48: 0 | G48: 3250600 | H48: 3250600 | I48: 3250600 | J48: 0 | M48: 0 | N48: 0
A49: 17 | B49: CE17A240 | E49: पुणे मनपाच्या बाबू गेनू दवाखाना (रविवार पेठ), आनंदीबाई नरहरी गाडगीळ दवाखाना, कलावती मावळे दवाखाना येथील विविध विकास कामे करणे व दर्जा वाढ करणे | F49: 0 | G49: 762849 | H49: 762849 | I49: 762849 | J49: 0 | M49: 0 | N49: 0
A50: 18 | B50: CE17A241 | C50: 18 | E50: प्रभाग क्र. १८ व वडगाव शेरी परिसरामध्ये विविध मनपा शाळांमध्ये विविध सुधारणा विषयक कामे करणे | F50: 0 | G50: 1432758 | H50: 1432758 | I50: 1432758 | J50: 0 | M50: 0 | N50: 0
A51: 19 | B51: CE17A242# | C51: J6- | D51: _ | E51: शहरामध्ये नव्याने प्रसुतिगृह / विविध सोयीसुविधा असलेले दवाखाने बांधणे | F51: 0 | G51: 505991093 | H51: 505991093 | I51: 84707425 | J51: 421283668 | M51: 79500000 | N51: 79500000
A52: 20 | B52: CE17A243# | C52: J7- | D52: _ | E52: प्राथमिक आरोग्य केंद्र उभारणे | F52: 0 | G52: 22263242 | H52: 22263242 | I52: 16972373 | J52: 5290869 | M52: 500000 | N52: 500000
A53: 21 | B53: CE17A244# | C53: J8- | D53: _ | E53: शहरातील दवाखान्यांसाठी विविध उपकरणे खरेदी करणे | F53: 0 | G53: 140367500 | H53: 140367500 | I53: 107216604 | J53: 33150896 | M53: 1000000 | N53: 1000000
A54: 22 | B54: CE17A246# | C54: _ | D54: _ | E54: शहरातील दशक्रीया विधीसाठी घाट बांधणे, विविध विकास कामे करणे | F54: 0 | G54: 6646177 | H54: 6646177 | I54: 6384646 | J54: 261531 | M54: 0 | N54: 0
A55: 24 | B55: #+ | E55: सन २०१४-१५ मधील अपूर्ण कामांसाठी सन २०१५-१६ मध्ये उपलब्ध केलेली तरतूद | F55: 0 | G55: 82697047 | H55: 82697047 | I55: 82697047 | J55: 0 | M55: 0 | N55: 0
F56: 0 | G56: 0 | H56: 0 | I56: 0 | J56: 0 | M56: 0 | N56: 0
E57: ७. आरोग्य विभाग एकूण बेरीज | F57: 0 | G57: 2395516248 | H57: 2395516248 | I57: 1761059141 | J57: 634457107 | M57: 160500000 | N57: 160500000
F58: 0 | G58: 0 | H58: 0 | I58: 0 | J58: 0 | M58: 0 | N58: 0
E59: ९. पथांची झाडलोट / घनकचरा व्यवस्थापन विभाग | F59: 0 | G59: 0 | H59: 0 | I59: 0 | J59: 0 | M59: 0 | N59: 0
A60: 2 | B60: CE19A112 | E60: घरोघरी जावुन कचरा गोळा करणे, कंटेनर मुक्त शहर करणे | F60: 0 | G60: 4627174 | H60: 4627174 | I60: 4627174 | J60: 0 | M60: 0 | N60: 0
A61: 3 | B61: CE19A116 | E61: उरूळी देवाची/फुरसंगी डेपो परिसर कचरा डेपोवरील उर्वरित कचर्‍याचे नॉर्म्सप्रमाणे कॅपिंग करणे व तद्‌नुषंगिक कामे करणे | F61: 0 | G61: 792825974 | H61: 792825974 | I61: 752200135 | J61: 40625839 | M61: 20000000 | N61: 20000000
A62: 4 | B62: CE19A117 | E62: उरुळी देवाची/फुरसुंगी येथील कचरा डेपोच्या भोवती सिमाभिंत बांधणे. | F62: 0 | G62: 44341239 | H62: 44341239 | I62: 39341239 | J62: 5000000 | M62: 5000000 | N62: 5000000
A63: 5 | B63: CE19A120 | E63: व्हर्मीकंपोस्ट पध्दतीचे प्रक्रिया प्रकल्प उभारणे. | F63: 0 | G63: 168337022 | H63: 168337022 | I63: 148337022 | J63: 20000000 | M63: 10000000 | N63: 10000000
A64: 6 | B64: CE19A121 | E64: विकेंद्रित पध्दतीने कचरा प्रक्रिया प्रकल्प उभारणे व तदनुषंगिक कामे करणे. | F64: 0 | G64: 35821084 | H64: 35821084 | I64: 35821084 | J64: 0 | M64: 0 | N64: 0
A65: 7 | B65: CE19A122 | E65: कचरा प्रक्रिया प्रकल्पासाठी जागा ताब्यात घेणे, कंपाउंड करणे, रस्ते करणे व तदनुषंगिक कामे करणे. | F65: 0 | G65: 61024585 | H65: 61024585 | I65: 50703610 | J65: 10320975 | M65: 10000000 | N65: 10000000
A66: 8 | B66: CE19A123 | E66: ताब्यात येणार्‍या जागांवर प्रक्रिया प्रकल्प उभारणे, प्रकल्पांसाठी आवश्यक सुविधा विषयक कामे करणे इत्यादी. | F66: 0 | G66: 156270431 | H66: 156270431 | I66: 135793686 | J66: 20476745 | M66: 20000000 | N66: 20000000
A67: 9 | B67: CE19A139 | E67: उरुळी देवाची/फुरसंगी येथील गावांमध्ये विविध विकास कामे करणे | F67: 0 | G67: 434788172 | H67: 434788172 | I67: 414599443 | J67: 20188729 | M67: 90000000 | N67: 90000000
A68: 10 | B68: CE19A140 | E68: कचरा गोळा करणेसाठी घंटागाडया खरेदी करणे. | F68: 0 | G68: 55139399 | H68: 55139399 | I68: 55139399 | J68: 0 | M68: 0 | N68: 0
A69: 11 | B69: CE19A141 | E69: घनकचरा व्यवस्थापनकडील कचरागाडया, बंदिस्त करणे विविध रॅम्प बंदिस्त करणे व कॉक्रीट करणे. | F69: 0 | G69: 108427180 | H69: 108427180 | I69: 97840596 | J69: 10586584 | M69: 10000000 | N69: 10000000
A70: 12 | B70: CE19A142 | E70: विकेंद्रीत पध्दतीने विविध ठीकाणी बायोगॅस प्रकल्प / मेकॅनिकल कंपोस्टींग पध्दतीचे ५ टन क्षमते पर्यंतचे प्रकल्प उभारणे | F70: 0 | G70: 161324923 | H70: 161324923 | I70: 161324923 | J70: 0 | M70: 0 | N70: 0
A71: 13 | B71: CE19A143 | E71: गार्डन वेस्टसाठी विविध ठिकाणी पुणे मनपा हद्दीत श्रेडर मशिन बसविणे | F71: 0 | G71: 4225378 | H71: 4225378 | I71: 3965378 | J71: 260000 | M71: 2500000 | N71: 2500000
... A74: 18 | B74: CE19A153 | E74: प्लास्टिक व इलेक्ट्रॉनिक वस्तू विभाजीत करणेकरीता शेड बांधणे | F74: 0 | G74: 16630595 | H74: 16630595 | I74: 6529978 | J74: 10100617 | M74: 5000000 | N74: 5000000
A75: 19 | B75: CE19A154# | D75: _ | E75: घनकचरा संदर्भात शहरात विविध विकास कामे करणे | F75: 0 | G75: 258584628 | H75: 258584628 | I75: 176366169 | J75: 82218459 | M75: 0 | N75: 0
A76: 20 | B76: CE19A155 | E76: e-waste जमा करणे व प्रक्रिया करणे | F76: 0 | G76: 850000 | H76: 850000 | I76: 850000 | J76: 0 | M76: 5000000 | N76: 5000000
A77: 21 | B77: CE19A156 | E77: कचरा वाहतुकीसाठी नव्याने उपनगरांमध्ये रॅम्प उभारणी व विकासकामे करणे | F77: 0 | G77: 26675378 | H77: 26675378 | I77: 6675378 | J77: 20000000 | M77: 20000000 | N77: 20000000
A78: 22 | B78: CE19A157 | E78: उरळी देवाची / फुरसुगी येथे इनर्ट /रिजेक्ट मटेरीयल साठी नव्याने शास्त्रोक्त लॅण्डफील विकसीत करणे व त्याची देखभाल दुरुस्ती करणे | F78: 0 | G78: 155810578 | H78: 155810578 | I78: 83310578 | J78: 72500000 | M78: 150000000 | N78: 150000000
A79: 23 | B79: CE19A158 | E79: पुणे महानगरपालिकाच्या नव्याने समाविष्ट होणाऱ्या गावामध्ये घनकचरा व्यवस्थापनाशी संबधीत कामे करणे | F79: 0 | G79: 11353767 | H79: 11353767 | I79: 11353767 | J79: 0 | M79: 50000000 | N79: 50000000
A80: 26 | B80: CE19A162 | E80: पुणे शहराच्या घनकचर्‍यासाठी ताब्यात येणार्‍या जागांवर नव्याने शास्त्रीय पध्दतीने भूभराव विकसित करणे व त्याची देखभाल दुरूस्ती करणे | F80: 0 | G80: 19958051 | H80: 19958051 | I80: 2108051 | J80: 17850000 | M80: 0 | N80: 0
A81: 27 | B81: CE19A163 | E81: घनकचरा व्यवस्थापनाअंतर्गत विकेंद्रीत पध्दतीने प्रभाग व वॉर्डनिहाय कचरा प्रकिया केंद्र उभारणे व तद्‌नुषंगिक कामे करणे | F81: 0 | G81: 202609808 | H81: 202609808 | I81: 202501380 | J81: 108428 | M81: 80000000 | N81: 80000000
A82: 28 | B82: CE19A165 | C82: 18 | E82: प्रभाग क्र. १८ व वडगाव शेरी परिसरामध्ये विविध ठिकाणी कचरा साठवणुकीसाठी बकेट्‌स पुरविणे | F82: 0 | G82: 1520000 | H82: 1520000 | I82: 1520000 | J82: 0 | M82: 0 | N82: 0
A83: 29 | B83: CE19A168 | E83: पुणे मनपाच्या अस्तित्वातील कचरा हस्तांतर केंद्र व हजेरीकोठ्‌या व विविध प्रकल्प याठिकाणी सेवकांसाठी सुविधा पुरविणे व बांधकामासाठी देखभाल दुरूस्ती करणे | F83: 0 | G83: 10950000 | H83: 10950000 | I83: 2146684 | J83: 8803316 | M83: 5000000 | N83: 5000000
A84: 30 | B84: CE19A169 | E84: स्वच्छ भारत अभियान अंतर्गत मनपाचा हिस्सा | F84: 0 | G84: 259500000 | H84: 259500000 | I84: 15928877 | J84: 243571123 | M84: 10000000 | N84: 10000000
A85: 32 | B85: CE19A171 | E85: समग्रसाठी मनपाचा हिस्सा | F85: 0 | G85: 162500000 | H85: 162500000 | I85: 0 | J85: 162500000 | M85: 60000000 | N85: 60000000
A86: 33 | B86: CE19A172 | E86: शहरातील विविध कचरा प्रकल्पावरून देवाची उरुळी येथे कचरा / रिजेक्ट वाहतूक करणे व शास्त्रोक्त पद्धतीने विल्हेवाट लावण्यासाठी मशिनरी पुरवणे व तदनुषंगिक कामे करणे | F86: 0 | G86: 25000000 | H86: 25000000 | I86: 0 | J86: 25000000 | M86: 0 | N86: 0
A87: 34 | B87: CE19A173 | E87: सार्वजनीक स्वच्छतागृह बांधणे | F87: 0 | G87: 25000000 | H87: 25000000 | I87: 0 | J87: 25000000 | M87: 87500000 | N87: 87500000
A88: 35 | B88: CE19A174 | E88: e-toilet करणे, जुन्या बसचे स्वच्छतागृहामध्ये रूपांतर करणे | F88: 0 | G88: 10000000 | H88: 10000000 | I88: 0 | J88: 10000000 | M88: 30000000 | N88: 30000000
A89: 36 | B89: CE19A175 | E89: Waste Park उभारणे | F89: 0 | G89: 10000000 | H89: 10000000 | I89: 0 | J89: 10000000 | M89: 0 | N89: 0
A90: 37 | B90: CE19A176 | E90: मायक्रो ऑरगॅनिझम कम्पोस्टिंग प्रकल्प राबविणे | F90: 0 | G90: 50000000 | H90: 50000000 | I90: 0 | J90: 50000000 | M90: 0 | N90: 0
A91: 1 | B91: CE19A178 | E91: उरूळी देवाची/फुरसंगी डेपो येथील साठलेल्या कचऱ्यावर बायोमायनिंग प्रक्रिया करणे | F91: 0 | G91: 0 | H91: 0 | I91: 0 | J91: 0 | M91: 160000000 | N91: 160000000
A92: 1 | B92: CE19A179 | E92: उरूळी देवाची/फुरसंगी डेपो येथील साठलेल्या कचऱ्यावर बायोमायनिंग प्रक्रिया करण्यासाठीच्या ठिकाणी रस्ता करणे, R.O. Plant बसविणे | F92: 0 | G92: 0 | H92: 0 | I92: 0 | J92: 0 | M92: 40000000 | N92: 40000000
F93: 0 | G93: 0 | H93: 0 | I93: 0 | J93: 0 | M93: 0 | N93: 0
E94: ९. पथांची झाडलोट / घनकचरा व्यवस्थापन विभाग एकूण बेरीज | F94: 0 | G94: 3417904136 | H94: 3417904136 | I94: 2487793321 | J94: 930110815 | M94: 870000000 | N94: 870000000
F95: 0 | G95: 0 | H95: 0 | I95: 0 | J95: 0 | M95: 0 | N95: 0
E96: १०क. पथ सुधारणा | F96: 0 | G96: 0 | H96: 0 | I96: 0 | J96: 0 | M96: 0 | N96: 0
A97: 1 | B97: CE20A102# | C97: A2- | D97: _ | E97: शहरातील रस्ते डांबरीकरणाने विकसित करणे | F97: 11538000 | G97: 6290001849 | H97: 6301539849 | I97: 4556139375 | J97: 1745400474 | M97: 780000000 | N97: 780000000
A98: 2 | B98: CE20A103# | C98: A13- | D98: _ | E98: Pedestrian Policy नुसार शहरातील फूटपाथ विकसित करणे | F98: 0 | G98: 2295928348 | H98: 2295928348 | I98: 1412184146 | J98: 883744202 | M98: 431500000 | N98: 431500000
A99: 3 | B99: CE20A819# | E99: शहरात निरनिराळ्या ठिकाणी रस्ते डांबरी करणे व तद्‌नुषंगिक कामे करणे | F99: 0 | G99: 4325582564 | H99: 4325582564 | I99: 4325582564 | J99: 0 | M99: 0 | N99: 0
A100: 4 | B100: CE20A883# | E100: शहरात विविध ठिकाणी गल्लीबोळ सिमेंट काँक्रीट करणे | F100: 0 | G100: 2895844637 | H100: 2895844637 | I100: 2895844637 | J100: 0 | M100: 0 | N100: 0
A101: 5 | B101: CE20A884# | D101: _ | E101: शहरात विविध विकासाची कामे करणे | F101: 0 | G101: 1263626342 | H101: 1263626342 | I101: 998188288 | J101: 265438054 | M101: 0 | N101: 0
A102: 6 | B102: CE20A1195# | C102: _ | E102: पावसाळी लाईन टाकणे | F102: 0 | G102: 621343906 | H102: 621343906 | I102: 621343906 | J102: 0 | M102: 0 | N102: 0
A103: 9 | B103: CE20A1249# | C103: A6- | D103: _ | E103: शहरामधील रस्ते विकसित करणे | F103: 0 | G103: 1446053004 | H103: 1446053004 | I103: 715345642 | J103: 730707362 | M103: 643000000 | N103: 643000000
A104: 10 | B104: CE20A1250# | C104: _ | D104: _ | E104: पुणे शहरात सी.एम.पी. आराखड्यानुसार (PPP / Development TDR / Deffered payment / Premium charges) अन्वये प्रशासकीय मुल्यमापनानुसार प्रत्यक्ष अंमलबजावणी करून कामे करणे | F104: 0 | G104: 311306136 | H104: 311306136 | I104: 310594176 | J104: 711960 | M104: 0 | N104: 0
A105: 12 | B105: CE20A1258# | C105: _ | E105: पुणे शहरातील अस्तित्वातील मुख्य रस्ते ओव्हरले पध्दतीने कॉक्रिटीकरण करणेचे काम डिफर्ड पेमेंट पध्दतीने करणे | F105: 0 | G105: 11261243 | H105: 11261243 | I105: 11261243 | J105: 0 | M105: 0 | N105: 0
A106: 13 | B106: CE20A1259# | C106: A9- | E106: शहरातील रस्ते पुनर्डांबरीकरण करणे | F106: 0 | G106: 743024682 | H106: 743024682 | I106: 422846527 | J106: 320178155 | M106: 170000000 | N106: 170000000
...

Sheet A_Land_Acquisition
A1: सन 2018-19 चे अंदाजपत्रक - खास निधीतून करावयाची योजनांतर्गत कामे
A2: अनुक्रमांक | C2: कामाचे नाव | D2: मान्य अंदाज 2017-18 | E2: नवीन अंदाज 2018-19
A7: (अ) | C7: भूमी संपादन निधीतून करावयाचा खर्च | D7: 0 | E7: 0
D8: 0 | E8: 0
A9: 1 | B9: FE11A101 | C9: भूमी संपादन विशेष अधिकारी यांचा कार्यालयीन खर्च - | D9: 30000000 | E9: 30000000
A10: 2 | C10: कोर्टाच्या निकालानुसार वाढीव नुकसानभरपाई कोर्ट खर्च, वकील फी, जॉइन्ट जज्ज यांचा खर्च वगैरे | D10: 0 | E10: 0
A11: 3 | C11: भूमी संपादन अधिनियमात नव्याने केलेल्या दुरुस्तीमुळे यापूर्वी जाहीर झालेल्या योजनापोटी ावयाच्या वाढीव रकमेचा खर्च | D11: 0 | E11: 0
A12: 4 | C12: परचेस नोटीसांमुळे (नवीन) पाठवावयाच्या भूमी संपादन योजनांसाठी तरतूद | D12: 0 | E12: 0
A13: 5 | C13: ताब्यात घेतलेल्या मिळकती पाडणे, ड्रेनेज, वॉटर, इलेक्ट्रीक टेलिफोन वगैरे कनेक्शन्स हलविणे, जोडणे व इतर तद्‌नुषंगिक कामे करणे. | D13: 0 | E13: 0
A14: 6 | C14: कार्यालयीन कामासाठी साधने, डेडस्टॉक वस्तू खरेदी करणे, हत्यारे खरेदी करणे, कार्यालय व कोठीची दुरुस्ती करणे, आवश्यक सुधारणा करणे, प्रकटन खर्च, प्रवास खर्च वगैर | D14: 0 | E14: 0
A15: 7 | C15: मुंबई प्रांतिक मनपा अधिनियम १९४९ च्या कलम २१३ अन्वये रस्तारूंदीसाठी ताब्यात घेतलेल्या मोकळ्या जागा व त्याप्रित्यर्थ ावयाची नुकसानभरपाईची रक्कम | D15: 0 | E15: 0
A16: 8 | C16: इतर योजनांमधील मोजणी फी व इतर तद्‌नुषंगिक रक्कम | D16: 0 | E16: 0
A17: 9 | C17: भूमी संपादन अधिकारी ह्यांचेकडील खालील नमूद केलेल्या ज्या जागांचे निवाडे जाहीर करतील त्यासाठी रक्कम | D17: 0 | E17: 0
A18: 10 | C18: संगणक दुरूस्ती व आवश्यक साहित्य | D18: 0 | E18: 0
D19: 0 | E19: 0
C20: (अ) बेरीज | D20: 30000000 | E20: 30000000
D21: 0 | E21: 0
D22: 0 | E22: 0
B23: FE11A102 | C23: भूसंपादनासाठी आवश्यक जागांची यादी :- | D23: 470000000 | E23: 470000000
D24: 0 | E24: 0
C25: सी.वाय.जी अंतर्गत रस्ते : | D25: 0 | E25: 0
C26: बाणेर मुख्य रस्ता २६१ ते १०५ | D26: 0 | E26: 0
C27: बाणेर स.क्र. १३३ ते बालेवाडी स.क्र. १० बालेवाडीकडे जाणारा रस्ता मुख्य रस्ता (बालेवाडी) | D27: 0 | E27: 0
C28: बालेवाडी स.क्र. ३४, ३५ जी१ गार्डनचे आरक्षण | D28: 0 | E28: 0
C29: बाणेर स.क्र. २८, २९० जी२ गार्डनचे आरक्षण व बाणेर स.क्र. ३५ जी३ गार्डनचे आरक्षण | D29: 0 | E29: 0
C30: कल्याणीनगर जंक्शन ते आळंदी रोड | D30: 0 | E30: 0
C31: बाणेर स.क्र. १०५, १०६, ११०, १११ पीएमटी१ | D31: 0 | E31: 0
C32: बाणेर स.क्र. ३३ पी.३ | D32: 0 | E32: 0
C33: बाणेर स.क्र. १०० पी.४ | D33: 0 | E33: 0
C34: बाणेर स.क्र. १७४ पी.४ | D34: 0 | E34: 0
C35: बाणेर स.क्र. ७९ पी.६ | D35: 0 | E35: 0
C36: बाणेर स.क्र. १०५, १०६ पी.७ पार्किंगचे आरक्षण | D36: 0 | E36: 0
... C42: एअरपोर्ट रोड ते डेक्कन कॉलेज व्हाया हॉटमिक्स प्लँट | D42: 0 | E42: 0
D43: 0 | E43: 0
C44: जेएनएनयुआरएम / बीआरटी अंतर्गत रस्ते : | D44: 0 | E44: 0
C45: बाणेर स.क्र. १०७, १०८ व ११० मधून जाणारा १८ मी. रस्ता. | D45: 0 | E45: 0
C46: मौजे खराडी ता. हवेली, संगमवाडी ते खराडी २४ मी. नदीकाठचा डी.पी. रस्ता | D46: 0 | E46: 0
C47: मौजे वडगांव शेरी ता. हवेली, संगमवाडी ते खराडी २४ मी. नदीकाठचा डी.पी. रस्ता | D47: 0 | E47: 0
C48: सिंहगड रस्ता महानगरपालिका हद्द दरम्यान नियोजनाते विकसीत करणे (वडगांव बुद्रुक) | D48: 0 | E48: 0
C49: सिंहगड रस्ता महानगरपालिका हद्द दरम्यान नियोजनाते विकसीत करणे (वडगांव खुर्द) | D49: 0 | E49: 0
C50: विश्रांतवाडी ते धानोरी | D50: 0 | E50: 0
C51: संचेती हॉस्पिटल ते गव्हर्नमेंट पोल्ट्री फार्म | D51: 0 | E51: 0
C52: पुणे स्टेशन ते मनपा रोड (कॅनॉट रोड) | D52: 0 | E52: 0
D53: 0 | E53: 0
C54: आरआरडीपी अंतर्गत रस्ते : | D54: 0 | E54: 0
C55: मुळा नदिवरील पिंपळे निलेख यांना जोडणारा पुल रस्त्याचे भुसंपाद (बाणेर) | D55: 0 | E55: 0
C56: सुतारवाडी रस्ता २४ मी. (जुना) | D56: 0 | E56: 0
C57: कोथरूड एकलव्य कॉलेज ते हायवेपर्यंत मुख्य रस्ता (१५ मी. नवीन) | D57: 0 | E57: 0
C58: कोथरूड महात्मा सोसायटी एकलव्य कॉलेज ते हायवे परिसरातील डी.पी. रस्ते (१५ मी.) व ( १८ मी.) | D58: 0 | E58: 0
C59: बालभारती ते पौड फाटा रस्ता | D59: 0 | E59: 0
C60: वारजे जकातनाका ते नवीन अहिरे हद्द एन.डी.ए. रोड जुना जकातनाका ते हायवे व वारजे माळवाडी टेकडीपर्यंत | D60: 0 | E60: 0
C61: जे.पी. नाईक इन्स्टिटयुट ते गणंजय सोसायटी | D61: 0 | E61: 0
C62: अलंकार पोलीस चौकी गिरीजा शंकर सोसायटी पश्चिमानगरी ते नाईक पूल डी.पी. रस्ता | D62: 0 | E62: 0
C63: चांदणी चौक ते सुस चौक | D63: 0 | E63: 0
C64: सिंहगड रोड दोन्ही कॅनॉलवरील प्रस्तावित पुलासह (वडगांव बुद्रुक) | D64: 0 | E64: 0
C65: सुस रस्ता ते बाणेर रस्ता रामनदी कडेचा रस्ता (बाणेर) | D65: 0 | E65: 0
... C67: सुस रस्ता ते बाणेर रस्ता रामनदी कडेचा रस्ता या रस्त्याचे भूसंपादन करणेबाबत (पाषाण) | D67: 0 | E67: 0
D68: 0 | E68: 0
C69: भूसंपादनाची इतर प्रकरणे : | D69: 0 | E69: 0
C70: पुणेमुंबई रस्ता हॅरीस ब्रिज ते खडकी कॅन्टोन्मेंट | D70: 0 | E70: 0
C71: हडपसर स.नं. २२६, २२४, २६६, २११, २१०, २०९, २०८, २०७ पोस्ट ऑफीस बाजूने जाणारा १८ मी. डी. पी. रस्ता | D71: 0 | E71: 0
C72: हडपसर स. नं. ८७, ८९, ९२, ९३, १०६, ३१२, ३१४, ३१ पैकी डी. पी. रस्त्यासाठी | D72: 0 | E72: 0
C73: हडपसर स.नं. २५ ईडब्ल्यूएस पैकी जागा संपादन करणेबाबत | D73: 0 | E73: 0
C74: घोरपडी गाव अनंत टॉकीज ते श्रीवस्ती नगर १२ मी डी.पी. रस्ता | D74: 0 | E74: 0
C75: कोंढवा खु.॥ स.नं. ५अ, ५ ब हायस्कूलसाठी संपादन | D75: 0 | E75: 0
C76: कोंढवा खु.॥ स.नं. १७ पै. मुलांचे खेळाचे मैदानासाठी | D76: 0 | E76: 0
C77: पुणे, पेठ पाषाण स.नं. ११० (पै.) पार्क (उान) साठी संपादन | D77: 0 | E77: 0
C78: हडपसर स.नं. ८४ पैकी प्ले ग्राऊंड साठी संपादन | D78: 0 | E78: 0
C79: वानवडी स.नं. ४९, ५८, ५९ | D79: 0 | E79: 0
C80: नाना पेठ, सि.सं. नं. ४०५ पै. उानासाठी आरक्षित जागा संपादन करणे | D80: 0 | E80: 0
... C95: हिंगणे / कर्वेनगर स.नं. ४० हायस्कूलसाठी | D95: 0 | E95: 0
D96: 0 | E96: 0
D97: 0 | E97: 0
C98: जाहीर झालेल्या निवाड्यापोटी भरण्याची रक्कम | D98: 0 | E98: 0
A99: 1 | C99: कर्वे रस्तारूंद जाहीर झालेल्या निवाड्यापोटी राहीलेली भरावयाची रक्कम | D99: 0 | E99: 0
A100: 2 | C100: सदाशिव पेठ घरांक ४६८ पार्किंगसाठी संपादन करणे | D100: 0 | E100: 0
D101: 0 | E101: 0
D102: 0 | E102: 0
C103: भूमिप्रापण खाते :- | D103: 0 | E103: 0
A104: 1 | C104: केळकर रस्ता (मंदार लॉज ते नारायण पेठ पोलीस चौकी) | D104: 0 | E104: 0
A105: 2 | C105: म्हात्रे पूल ते छत्रपती राजाराम पूल दरम्यानच्या नदीकाठचा १००'' डी.पी. रस्ता | D105: 0 | E105: 0
A106: 3 | C106: सातारा रस्ता | D106: 0 | E106: 0
A107: 4 | C107: सिंहगड रस्ता | D107: 0 | E107: 0
A108: 5 | C108: जंगली महाराज रस्ता | D108: 0 | E108: 0
A109: 6 | C109: पवित्र मंगल कार्यालया, पर्वती (सातारा रस्ता) | D109: 0 | E109: 0
A110: 7 | C110: नेहरू रस्ता, रास्ता पेठ पॉवर हाऊस ते लक्ष्मी रस्ता | D110: 0 | E110: 0
A111: 8 | C111: कर्वे रस्ता (खंडूजीबाबा चौक ते एस.एन.डी.टी.) | D111: 0 | E111: 0
A112: 9 | C112: शंकरशेठ रस्ता | D112: 0 | E112: 0
A113: 10 | C113: सेनापती बापट रस्ता | D113: 0 | E113: 0
A114: 11 | C114: उंबर्‍या गणपती चौक ते खुन्या मुरलीधर रस्ता | D114: 0 | E114: 0
A115: 12 | C115: भाऊ महाराज बोळ | D115: 0 | E115: 0
... A121: 18 | C121: रामवाडी जकातनाका ते लोहगाव विमानतळ | D121: 0 | E121: 0
D122: 0 | E122: 0
C123: जकात नाका :- | D123: 0 | E123: 0
A124: 1 | C124: शिंदेवाडी, स.नं. १०० ते १०६ (पैकी) | D124: 0 | E124: 0
A125: 2 | C125: फुरसुंगी, स.नं. १७५ पैकी | D125: 0 | E125: 0
A126: 3 | C126: वाघोली, गट नं. २३७८, २३७९ | D126: 0 | E126: 0
A127: 4 | C127: बावधन खुर्द, स.नं. ६४ | D127: 0 | E127: 0
A128: 5 | C128: हडपसर, स.नं. ६३ पैकी | D128: 0 | E128: 0
A129: 6 | C129: उंड्री, स.नं. ५४ पैकी | D129: 0 | E129: 0
...

Sheet A_Special_Fund
A1: सन 2018-19 चे उपनगरे विकास निधीचे | I1: योजनांतर्गत खर्चाबाबतचे अंदाजपत्रक
A2: अनुक्रमांक | B2: मान्यतेचा ठराव क्र. दिनांक (कोड) | C2: प्रभाग क्रमांक | D2: BPL | E2: कामाचे नाव अगर वर्णन | F2: दि. 31 मार्च 2018 अखेरपर्यंत केलेली तरतूद | I2: दि. 31 मार्च 2016 पर्यंतचा खर्चाचा नक्‍की आकडा | J2: 2016-17 मधील खर्चाचा नक्‍की आकडा | K2: 2017-18 मधील खर्चाची अंदाजी रक्‍कम | L2: 2018-19 साठी अधिक तरतूद | N2: 2018-19 साठी एकूण तरतूद | O2: शेरा
F3: कर्जातून | G3: महसूल निधीतून | H3: एकूण | L3: कर्जातून | M3: महसूल निधी व इतर निधी
E8: ४. झोपडपट्टी निर्मूलन व पुनर्वसन निधीतून करावयाची कामे | F8: 0 | G8: 0 | H8: 0 | I8: 0 | J8: 0 | K8: 0 | M8: 0 | N8: 0
A9: 1 | B9: FE14A101# | C9: _ | D9: _ | E9: निरनिराळ्या झोपडपट्टींमध्ये विविध विकासाची कामे करणे | F9: 33377000 | G9: 1530296070 | H9: 1563673070 | I9: 1186303250 | J9: 251305849 | K9: 126063971 | M9: 0 | N9: 0
A10: 2 | B10: FE14A104 | D10: B | E10: झो.नि.पु. अंतर्गत करावयाची कामे | F10: 0 | G10: 217214647 | H10: 217214647 | I10: 194201996 | J10: 2087651 | K10: 20925000 | M10: 1200000 | N10: 1200000
A11: 3 | B11: FE14A105# | C11: _ | D11: _ | E11: सुलभ पद्धतीची शौच्छालये बांधणे | F11: 0 | G11: 1371944850 | H11: 1371944850 | I11: 959891297 | J11: 61343612 | K11: 350709941 | M11: 0 | N11: 0
A12: 4 | B12: FE14A107 | D12: B | E12: दलित वस्ती सुधारणा अंतर्गत कामे करणे | F12: 0 | G12: 257194516 | H12: 257194516 | I12: 143291516 | J12: 21525306 | K12: 92377694 | M12: 50000000 | N12: 50000000
A13: 5 | B13: FE14A129 | D13: PL | E13: सार्वजनिक ठिकाणी शौचालय बांधणे | F13: 0 | G13: 49398926 | H13: 49398926 | I13: 28473926 | J13: 5535285 | K13: 15389715 | M13: 12000000 | N13: 12000000
A14: 6 | B14: FE14A130 | D14: PL | E14: सार्वजनिक ठिकाणी मुतार्‍या बांधणे | F14: 0 | G14: 42622473 | H14: 42622473 | I14: 17350588 | J14: 4346885 | K14: 20925000 | M14: 1200000 | N14: 1200000
A15: 7 | B15: FE14A131 | C15: 71 | E15: प्रभाग क्र. ७१ गंगाधाम चौक, नविन डी.पी. रस्ता सुलभ स्वच्छतागृह बांधणे | F15: 0 | G15: 1900000 | H15: 1900000 | I15: 1702765 | J15: 197235 | K15: 0 | M15: 0 | N15: 0
A16: 8 | B16: FE14A132 | C16: 18 | E16: प्रभाग क्र. १८ व वडगाव शेरी परिसरामध्ये विविध ठिकाणी स्वच्छतागृह बांधणे | F16: 0 | G16: 814635 | H16: 814635 | I16: 339297 | J16: 475338 | K16: 0 | M16: 0 | N16: 0
A17: 10 | B17: FE14A134 | E17: सन २०१४-१५ या आर्थिक वर्षातील अपूर्ण कामाच्या बिलासाठी सन १५-१६ च्या अंदाजपत्रकीय तरतुदीमधून ५% वजावट करून प्राप्त झालेली रक्कम | F17: 0 | G17: 2567092 | H17: 2567092 | I17: 2567092 | J17: 0 | K17: 0 | M17: 0 | N17: 0
F18: 0 | G18: 0 | H18: 0 | I18: 0 | J18: 0 | K18: 0 | M18: 0 | N18: 0
E19: ४. झोपडपट्टी निर्मूलन व पुनर्वसन निधीतून करावयाची कामे बेरीज | F19: 33377000 | G19: 3475146259 | H19: 3508523259 | I19: 2535314777 | J19: 346817161 | K19: 626391321 | M19: 64400000 | N19: 64400000
F20: 0 | G20: 0 | H20: 0 | I20: 0 | J20: 0 | K20: 0 | M20: 0 | N20: 0
E21: क्षेत्रिय कार्यालयाने करावयाची कामे :- | F21: 0 | G21: 0 | H21: 0 | I21: 0 | J21: 0 | K21: 0 | M21: 0 | N21: 0
F22: 0 | G22: 0 | H22: 0 | I22: 0 | J22: 0 | K22: 0 | M22: 0 | N22: 0
A23: • | B23: FE14A118# | C23: W5 | D23: B | E23: क्षेत्रिय कार्यालय : झो.नि.पु. विभागाने करावयाची कामे | F23: 0 | G23: 240351629 | H23: 240351629 | I23: 230908835 | J23: 3141990 | K23: 6300804 | M23: 6200000 | N23: 6200000
A24: • | B24: FE14A121# | C24: C5 | D24: B | E24: क्षेत्रिय कार्यालय : नागरिकांच्या सहभाग योजनेतून झो.नि.पु. विभागाने करावयाची कामे | F24: 0 | G24: 136079154 | H24: 136079154 | I24: 132596154 | J24: 3107582 | K24: 375418 | M24: 1700000 | N24: 1700000
F25: 0 | G25: 0 | H25: 0 | I25: 0 | J25: 0 | K25: 0 | M25: 0 | N25: 0
E26: क्षेत्रिय कार्यालयाने करावयाची कामे एकूण बेरीज | F26: 0 | G26: 376430783 | H26: 376430783 | I26: 363504989 | J26: 6249572 | K26: 6676222 | M26: 7900000 | N26: 7900000
F27: 0 | G27: 0 | H27: 0 | I27: 0 | J27: 0 | K27: 0 | M27: 0 | N27: 0
E28: ४. झोपडपट्टी निर्मूलन व पुनर्वसन निधीतून करावयाची कामे + क्षेत्रिय कार्यालयाने करावयाची कामे एकूण बेरीज | F28: 33377000 | G28: 3851577042 | H28: 3884954042 | I28: 2898819766 | J28: 353066733 | K28: 633067543 | M28: 72300000 | N28: 72300000
F29: 0 | G29: 0 | H29: 0 | I29: 0 | J29: 0 | K29: 0 | M29: 0 | N29: 0
E30: ४अ. मागासवर्गीय कल्याणकारी योजना निधी | F30: 0 | G30: 0 | H30: 0 | I30: 0 | J30: 0 | K30: 0 | M30: 0 | N30: 0
A31: 1 | B31: FE14B101 | D31: B-FA | E31: समाज विकास विभाग अंतर्गत मागासवर्गीय योजना | F31: 0 | G31: 434454191 | H31: 434454191 | I31: 364454191 | J31: 31975263 | K31: 38024737 | M31: 37500000 | N31: 37500000
A32: 2 | B32: FE14B112 | D32: B-FA | E32: लोकशाहीर अण्णाभाऊ साठे शैक्षणिक मदत योजना | F32: 0 | G32: 159992082 | H32: 159992082 | I32: 101992082 | J32: 0 | K32: 58000000 | M32: 31000000 | N32: 31000000
A33: 3 | B33: FE14B113 | D33: B-FA | E33: मौ. अबुल कलाम आझाद शैक्षणिक मदत योजना | F33: 0 | G33: 318978546 | H33: 318978546 | I33: 214978546 | J33: 43880000 | K33: 60120000 | M33: 51000000 | N33: 51000000
A34: 6 | B34: FE14B121 | D34: B-T | E34: मागासवर्गीय विद्यार्थ्यांना स्पर्धा परिक्षा मार्गदर्शन केंद्र चालविणे | F34: 0 | G34: 8806896 | H34: 8806896 | I34: 4806896 | J34: 595000 | K34: 3405000 | M34: 2000000 | N34: 2000000
A35: 7 | B35: FE14B122 | D35: B-T | E35: बालविकास केंद्र व वस्ती रिसोर्स सेंटर सुरू करणे | F35: 0 | G35: 11286196 | H35: 11286196 | I35: 5986196 | J35: 1418717 | K35: 3881283 | M35: 2500000 | N35: 2500000
A36: 8 | B36: FE14B123 | D36: B | E36: मागासवर्गीय कल्याणकारी योजनेअंतर्गत विविध योजना राबविणेसाठी मानधन तत्वावरील सेवकांचा मानधन खर्च | F36: 0 | G36: 23029628 | H36: 23029628 | I36: 16029628 | J36: 3487933 | K36: 3512067 | M36: 8500000 | N36: 8500000
A37: 9 | B37: FE14B126 | D37: B | E37: बार्टीचे ४ केंद्र सुरू करणे (कोथरूड, सहकारनगर, शिवाजीनगर, भवानीपेठ) | F37: 0 | G37: 3000000 | H37: 3000000 | I37: 0 | J37: 0 | K37: 3000000 | M37: 0 | N37: 0
A38: 10 | B38: FE14B127 | D38: B | E38: डॉ.बाबासाहेब आंबेडकर यांच्या 125 व्या जयंती निमित्त माता रमार्इ भिमराव आंबेडकर योजनेअंतर्गत गवनि घोषीत व शहरी गरीब योजनेतील पात्र ठरणाऱ्या विधवा, निराधार महिलांसाठी दरमहा रू.1000/- अर्थसहाय्य करणे (मागासवर्गीय कल्याणकारी योजना) | F38: 0 | G38: 50878788 | H38: 50878788 | I38: 878788 | J38: 124000 | K38: 49876000 | M38: 0 | N38: 0
A39: 11 | B39: FE14B128 | D39: B-FA | E39: डॉ. बाबासाहेब आंबेडकर विद्यार्थी वसतिगृह, घोले रोड येथील खाणावळीचा खर्च | F39: 0 | G39: 10000000 | H39: 10000000 | I39: 0 | J39: 0 | K39: 10000000 | M39: 4000000 | N39: 4000000
A40: 12 | B40: FE14B129 | D40: B-I | E40: शहरात आदिवासी विद्यार्थ्यांसाठी वसतिगृहे उभारणे | F40: 0 | G40: 10000000 | H40: 10000000 | I40: 0 | J40: 0 | K40: 10000000 | M40: 10000000 | N40: 10000000
A41: 13 | B41: FE14B130 | E41: बार्टी संस्थेच्या मदतीने विविध व्यावसायिक प्रशिक्षण देणे | F41: 0 | G41: 0 | H41: 0 | I41: 0 | J41: 0 | K41: 0 | M41: 5000000 | N41: 5000000
A42: 14 | B42: FE14B131 | D42: B-T | E42: विविध व्यावसायिक प्रशिक्षण देणे | F42: 0 | G42: 0 | H42: 0 | I42: 0 | J42: 0 | K42: 0 | M42: 5000000 | N42: 5000000
A43: 15 | B43: FE14B132 | D43: B-S | E43: मागासवर्गीय कल्याणकारी योजनेचा अभ्यास, ऑडिट व सर्वेक्षण करणे | F43: 0 | G43: 0 | H43: 0 | I43: 0 | J43: 0 | K43: 0 | M43: 1000000 | N43: 1000000
F44: 0 | G44: 0 | H44: 0 | I44: 0 | J44: 0 | K44: 0 | M44: 0 | N44: 0
E45: ४अ. मागासवर्गीय कल्याणकारी योजना निधी बेरीज | F45: 0 | G45: 1030426327 | H45: 1030426327 | I45: 709126327 | J45: 81480913 | K45: 239819087 | M45: 157500000 | N45: 157500000
F46: 0 | G46: 0 | H46: 0 | I46: 0 | J46: 0 | K46: 0 | M46: 0 | N46: 0
E47: ४ब. महिलाबालकल्याण योजना निधी | F47: 0 | G47: 0 | H47: 0 | I47: 0 | J47: 0 | K47: 0 | M47: 0 | N47: 0
A48: 1 | B48: FE14C101 | D48: PL-FA | E48: महिलाबालकल्याण योजना | F48: 0 | G48: 383238654 | H48: 383238654 | I48: 314238654 | J48: 15985554 | K48: 53014446 | M48: 38000000 | N48: 38000000
A49: 2 | B49: FE14C108 | D49: PL-FA | E49: महिला सक्षमिकरणासाठी अनुदानाची योजना | F49: 0 | G49: 165662778 | H49: 165662778 | I49: 134662778 | J49: 9949150 | K49: 21050850 | M49: 17000000 | N49: 17000000
A50: 3 | B50: FE14C116 | D50: PL | E50: बचत गटाच्या शिखर संस्थेचा व्यवस्थापन खर्च | F50: 0 | G50: 14652681 | H50: 14652681 | I50: 12652681 | J50: 0 | K50: 2000000 | M50: 0 | N50: 0
A51: 4 | B51: FE14C117 | D51: PL | E51: बचत गटातील महिलांना कुटुंबनियोजनासाठी प्रोत्साहन | F51: 0 | G51: 4226160 | H51: 4226160 | I51: 2976160 | J51: 70000 | K51: 1180000 | M51: 0 | N51: 0
A52: 5 | B52: FE14C118 | D52: PL | E52: नागरवस्तीच्या वापरातील समाजमंदिरे / इतर वास्तूंच्या विद्युत बिलांसाठी | F52: 0 | G52: 6015230 | H52: 6015230 | I52: 3564440 | J52: 250790 | K52: 2200000 | M52: 1500000 | N52: 1500000
A53: 14 | B53: FE14C125# | C53: M1- | D53: _ | E53: महिलाबाल कल्याण योजना अंतर्गत करावयाची कामे | F53: 0 | G53: 363787800 | H53: 363787800 | I53: 0 | J53: 46327153 | K53: 317460647 | M53: 35000000 | N53: 35000000
A54: 6 | B54: FE14C134 | D54: PL-FA | E54: रस्त्यांवरील मुलांसाठी घरटे प्रकल्प | F54: 0 | G54: 66493122 | H54: 66493122 | I54: 43993122 | J54: 8336824 | K54: 14163176 | M54: 20000000 | N54: 20000000
A55: 7 | B55: FE14C135 | D55: PL-FA | E55: कन्यारत्न योजना | F55: 0 | G55: 1350000 | H55: 1350000 | I55: 750000 | J55: 0 | K55: 600000 | M55: 300000 | N55: 300000
A56: 8 | B56: FE14C136 | D56: PL | E56: कागदी पिशव्या तयार करणार्‍या बचत गटांना अनुदान | F56: 0 | G56: 1706610 | H56: 1706610 | I56: 1506610 | J56: 0 | K56: 200000 | M56: 0 | N56: 0
A57: 9 | B57: FE14C138 | D57: PL | E57: राणी लक्ष्मीबाई महिला औोगिक प्रशिक्षण संस्था पुणे मनपा संयुक्त प्रकल्पा अंतर्गत मुलभूत सुविधा करणे | F57: 0 | G57: 7801055 | H57: 7801055 | I57: 7801055 | J57: 0 | K57: 0 | M57: 0 | N57: 0
A58: 10 | B58: FE14C139 | D58: PL-T | E58: UCD मार्फत राबविल्या जाणार्‍या निरनिराळया उपक्रमासाठी लागणारा खर्च स्वयंरोजगार, प्रशिक्षण, साहित्य खरेदी इ. | F58: 0 | G58: 11078934 | H58: 11078934 | I58: 5078934 | J58: 1090522 | K58: 4909478 | M58: 4000000 | N58: 4000000
A59: 11 | B59: FE14C140 | D59: PL-I | E59: समाज विकास केंद्रात Day-Care Centre सुरू करणे | F59: 0 | G59: 3515543 | H59: 3515543 | I59: 673866 | J59: 141677 | K59: 2700000 | M59: 2000000 | N59: 2000000
A60: 12 | B60: FE14C142 | D60: PL-T | E60: शेजार समुहगट व इतर महिलांसाठी विविध कल्याणकारी योजना, बाल विकास केंद्र, स्वच्छ झोपडपट्टी स्पर्धा, आरोग्य विषयक शिबीरे, झोपडपट्टीत उत्कृष्ट काम करणार्‍या व्यक्ती व संस्था याना पारितोषिक देणे महिला व बालके यांचेसाठी स्पर्धा घेणे इ. | F60: 0 | G60: 4887015 | H60: 4887015 | I60: 2387015 | J60: 376413 | K60: 2123587 | M60: 1500000 | N60: 1500000
A61: 13 | B61: FE14C143 | D61: PL | E61: महिला व बाल कल्याण योजनेअंतर्गत विविध योजना राबविणेसाठी मानधन तत्वावरील सेवकांचा मानधन खर्च | F61: 0 | G61: 10938493 | H61: 10938493 | I61: 7138493 | J61: 1793149 | K61: 2006851 | M61: 4000000 | N61: 4000000
A62: 14 | B62: FE14C146 | D62: PL | E62: बालवाडी पोषण आहार | F62: 0 | G62: 117249556 | H62: 117249556 | I62: 63249556 | J62: 10250154 | K62: 43749846 | M62: 0 | N62: 0
A63: 15 | B63: FE14C147 | D63: PL | E63: अनैतिक व्यवसायात गुंतलेल्या महिलांसाठी व्यावसायिक प्रशिक्षण व स्वयंरोजगारासाठी अनुदान खर्च | F63: 0 | G63: 3831273 | H63: 3831273 | I63: 2371273 | J63: 0 | K63: 1460000 | M63: 0 | N63: 0
A64: 16 | B64: FE14C155 | D64: PL | E64: आधार केंद्र प्रशासकीय खर्च | F64: 0 | G64: 4566042 | H64: 4566042 | I64: 66042 | J64: 0 | K64: 4500000 | M64: 0 | N64: 0
A65: 17 | B65: FE14C156 | D65: PL | E65: युवतींसाठी १५ केंद्रांवर स्वसंरक्षणाचे प्रशिक्षण देणे | F65: 0 | G65: 3862910 | H65: 3862910 | I65: 1111110 | J65: 151800 | K65: 2600000 | M65: 0 | N65: 0
... A78: 1 | B78: FE14C211 | D78: L-I | E78: १५ क्षेत्रिय कार्यालय येथे हिरकणी कक्ष सुरू करणे | F78: 0 | G78: 0 | H78: 0 | I78: 0 | J78: 0 | K78: 0 | M78: 3000000 | N78: 3000000
A79: 1 | B79: FE14C212 | E79: महिला बचत गटांना रोजगार निर्मितीसाठी ई-मार्केटिंग साठी संकेतस्थळ सुरू करणे. | F79: 0 | G79: 0 | H79: 0 | I79: 0 | J79: 0 | K79: 0 | M79: 2000000 | N79: 2000000
A80: 1 | B80: FE14C213 | D80: PL-FA | E80: महिला मालमत्ता धारकांना सर्वसाधारण करामध्ये प्रोत्साहन म्हणून र.रू. ५००/- पर्यंत सुट देणे तसेच स्व कमाईतून उभारलेली मालमत्तेचा महिलेच्या अथवा मुलांच्या नावे समान हिस्सा दिल्यास १% अथवा जास्तीत जास्त ५०००/- पर्यंत मालमत्ता करामध्ये सवलत देणे | F80: 0 | G80: 0 | H80: 0 | I80: 0 | J80: 0 | K80: 0 | M80: 9000000 | N80: 9000000
A81: 1 | B81: FE14C214 | D81: PL-FA | E81: ज्या कंपनीमध्ये संचालक मंडळासह सर्व कर्मचारी १००% महिला असल्यास कंपनीच्या मालमत्ता करामध्ये १% जास्तीत जास्त अथवा रक्कम रू. १००००/- पर्यंत सवलत देणे | F81: 0 | G81: 0 | H81: 0 | I81: 0 | J81: 0 | K81: 0 | M81: 1000000 | N81: 1000000
A82: 1 | B82: FE14C215 | D82: PL-FA | E82: PMPML मार्फत चालविल्या जाणार्‍या महिलांसाठीच्या बसचा प्रवास महिन्यातून एकदा मोफत उपलब्ध करून देणे | F82: 0 | G82: 0 | H82: 0 | I82: 0 | J82: 0 | K82: 0 | M82: 10000000 | N82: 10000000
A83: 1 | B83: FE14C216 | D83: PL-S | E83: महिला बालकल्याण योजनेचा अभ्यास ऑडिट आणि सर्वेक्षण करणे | F83: 0 | G83: 0 | H83: 0 | I83: 0 | J83: 0 | K83: 0 | M83: 1000000 | N83: 1000000
F84: 0 | G84: 0 | H84: 0 | I84: 0 | J84: 0 | K84: 0 | M84: 0 | N84: 0
E85: ४ब. महिलाबालकल्याण योजना निधी बेरीज | F85: 0 | G85: 1355691052 | H85: 1355691052 | I85: 624405485 | J85: 97566686 | K85: 633718881 | M85: 281300000 | N85: 281300000
F86: 0 | G86: 0 | H86: 0 | I86: 0 | J86: 0 | K86: 0 | M86: 0 | N86: 0
E87: ४क. युवक कल्याणकारी योजना निधी (नागरवस्ती विकास योजना) | F87: 0 | G87: 0 | H87: 0 | I87: 0 | J87: 0 | K87: 0 | M87: 0 | N87: 0
A88: 1 | B88: FE14D101 | D88: P-FA | E88: शहरातील तरुणांसाठी स्वयंरोजगार व प्रशिक्षणासाठी अनुदान देणे | F88: 0 | G88: 108082854 | H88: 108082854 | I88: 85382854 | J88: 10716238 | K88: 11983762 | M88: 12500000 | N88: 12500000
A89: 2 | B89: FE14D118 | D89: P-FA | E89: लोकशाहीर अण्णाभाऊ साठे शैक्षणिक मदत योजना व मौ. अब्दुल कलाम आझाद शैक्षणिक मदत योजना | F89: 0 | G89: 820885588 | H89: 820885588 | I89: 633385588 | J89: 136650000 | K89: 50850000 | M89: 130000000 | N89: 130000000
A90: 3 | B90: FE14D121 | E90: ज्येष्ठ नागरिकांसाठी विरंगुळा केंद्र सुरू करणे | F90: 0 | G90: 3600000 | H90: 3600000 | I90: 0 | J90: 14250 | K90: 3585750 | M90: 0 | N90: 0
A91: 4 | B91: FE14D122 | D91: P-I | E91: शहरात विविध ठिकाणी नाईट शेल्टर योजना राबविणे | F91: 0 | G91: 19973652 | H91: 19973652 | I91: 4197936 | J91: 2175716 | K91: 13600000 | M91: 10000000 | N91: 10000000
A92: 5 | B92: FE14D123 | D92: P | E92: प्रशिक्षण संस्थांतील शिक्षक व इतर कर्मचार्‍यांचे मानधन देणे | F92: 0 | G92: 7541333 | H92: 7541333 | I92: 2591333 | J92: 2412509 | K92: 2537491 | M92: 7000000 | N92: 7000000
A93: 6 | B93: FE14D124 | D93: P | E93: युवक / युवतींसाठी ग्रंथालय सुरू करणे (सावित्रीबाई फुले ग्रंथालय) | F93: 0 | G93: 1700000 | H93: 1700000 | I93: 0 | J93: 0 | K93: 1700000 | M93: 0 | N93: 0
A94: 7 | B94: FE14D125 | D94: P-I | E94: हॅलो माय फ्रेड योजना राबविणे,युवकांसाठी कॉल सेंटर सुरू करणे (मानसिक आरोग्य) | F94: 0 | G94: 1569807 | H94: 1569807 | I94: 289510 | J94: 120297 | K94: 1160000 | M94: 2000000 | N94: 2000000
A95: 8 | B95: FE14D126 | D95: P-I | E95: नागरवस्ती विकास योजना विभागाच्या ताब्यात असणार्‍या जागेपोटी PMPML प्रशासनास भाडे देणे | F95: 0 | G95: 1500000 | H95: 1500000 | I95: 0 | J95: 0 | K95: 1500000 | M95: 1500000 | N95: 1500000
A96: 9 | B96: FE14D128 | E96: स्थानिक तसेच परराज्यातील व इतर देशातील आलेल्या विार्थ्याचे सांस्कृतिक कार्यक्रम आयोजित करणे. (सांस्कृतिक देवाणघेवाण करणे व सद्‌भावना निर्माण करणे) | F96: 0 | G96: 1407275 | H96: 1407275 | I96: 1407275 | J96: 0 | K96: 0 | M96: 0 | N96: 0
A97: 10 | B97: FE14D129 | D97: P-T | E97: स्पर्धा परिक्षा मार्गदर्शन केंद्र चालविणे | F97: 0 | G97: 1700000 | H97: 1700000 | I97: 0 | J97: 0 | K97: 1700000 | M97: 3000000 | N97: 3000000
A98: 12 | B98: FE14D130 | E98: केंद्र व राज्य शासन यांनी विशेष प्राविण्य (राष्ट्रपती पदक, शौर्य पदक), स्वातंत्र सैनिक बस पासेस पोटी रक्‍कम पी.एम.पी. एम.एल.प्रशासनास अदा करणे | F98: 0 | G98: 718200 | H98: 718200 | I98: 0 | J98: 0 | K98: 718200 | M98: 0 | N98: 0
A99: 13 | B99: FE14D131 | E99: लाव्हलीहुड अॅण्ड सिटीझन व्हॉलेंटरिंग सेंटर | F99: 0 | G99: 3500000 | H99: 3500000 | I99: 0 | J99: 2484215 | K99: 1015785 | M99: 0 | N99: 0
A100: 14 | B100: FE14D132 | E100: मुले व तरुणांमध्ये विज्ञानाचा उलगडा होण्यासाठी कार्यक्रम राबविणे | F100: 0 | G100: 1000000 | H100: 1000000 | I100: 0 | J100: 0 | K100: 1000000 | M100: 0 | N100: 0
A101: 11 | B101: FE14D133 | E101: शरद स्वावलंबी जीवन योजनेअंतर्गत गवनि घोषित व शहरी गरीब योजनेअंतर्गत ज्येष्ठ नागरिकांना (पुरुष) दरमहा र.रु. 1,000 अर्थसहाय्‌य देणे | F101: 0 | G101: 60000000 | H101: 60000000 | I101: 0 | J101: 0 | K101: 60000000 | M101: 0 | N101: 0
A102: 12 | B102: FE14D134 | E102: स.नं. ६९ हडपसर येथे युथ गाईडन्स सेंटर उभारणे | F102: 0 | G102: 7125000 | H102: 7125000 | I102: 0 | J102: 0 | K102: 7125000 | M102: 0 | N102: 0
A103: 13 | B103: FE14D135 | E103: म. फुले संग्रहालय घोले रोड, शिवाजीनगर येथील एमपीएसी / युपीएसी विद्यार्थ्यांसाठी स्पर्धा परिक्षा मार्गदर्शन केंद्र सुरू करणे | F103: 0 | G103: 3000000 | H103: 3000000 | I103: 0 | J103: 0 | K103: 3000000 | M103: 0 | N103: 0
A104: 14 | B104: FE14D136 | D104: P-I | E104: पुणे शहरात Light House प्रकल्प सुरू करणे | F104: 0 | G104: 50000000 | H104: 50000000 | I104: 0 | J104: 0 | K104: 50000000 | M104: 50000000 | N104: 50000000
A105: 1 | B105: FE14D137 | D105: P-I | E105: समाज विकास केंद्रात अभ्यासिका सुरू करणे. | F105: 0 | G105: 0 | H105: 0 | I105: 0 | J105: 0 | K105: 0 | M105: 3000000 | N105: 3000000
A106: 2 | B106: FE14D138 | E106: Digital Locker सुविधा उपलब्ध करणे | F106: 0 | G106: 0 | H106: 0 | I106: 0 | J106: 0 | K106: 0 | M106: 1000000 | N106: 1000000
A107: 3 | B107: FE14D139 | D107: P | E107: रोजगार निर्मितीसाठी पोर्टल सुरू करणे. | F107: 0 | G107: 0 | H107: 0 | I107: 0 | J107: 0 | K107: 0 | M107: 5000000 | N107: 5000000
A108: 4 | B108: FE14D140 | D108: PL-FA | E108: अभियांत्रिकी शिक्षणानंतर पुढील गुणवत्ता वाढीसाठी Certified Course घेणार्‍या विद्यार्थ्यांना र.रू २५,००० पर्यंत फी साठी आर्थिक सहाय्य करणे | F108: 0 | G108: 0 | H108: 0 | I108: 0 | J108: 0 | K108: 0 | M108: 20000000 | N108: 20000000
A109: 5 | B109: FE14D141 | E109: डॉ. बाबासाहेब आंबेडकर विद्यार्थी वसतीगृह, घोले रोड येथील विद्यार्थ्यांचा खानावळीचा खर्च देणे | F109: 0 | G109: 0 | H109: 0 | I109: 0 | J109: 0 | K109: 0 | M109: 5000000 | N109: 5000000
A110: 6 | B110: FE14D142 | D110: P-S | E110: युवक कल्याणकारी योजनेचे अभ्यास ऑडिट आणि सर्वेक्षण करणे | F110: 0 | G110: 0 | H110: 0 | I110: 0 | J110: 0 | K110: 0 | M110: 1000000 | N110: 1000000
A111: 6 | B111: FE14D143 | E111: Startup प्रोत्साहन करणेसाठी विशेष योजना राबविणे | F111: 0 | G111: 0 | H111: 0 | I111: 0 | J111: 0 | K111: 0 | M111: 50000000 | N111: 50000000
F112: 0 | G112: 0 | H112: 0 | I112: 0 | J112: 0 | K112: 0 | M112: 0 | N112: 0
E113: ४क. युवक कल्याणकारी योजना निधी बेरीज | F113: 0 | G113: 1093303709 | H113: 1093303709 | I113: 727254496 | J113: 154573225 | K113: 211475988 | M113: 301000000 | N113: 301000000
F114: 0 | G114: 0 | H114: 0 | I114: 0 | J114: 0 | K114: 0 | M114: 0 | N114: 0
E115: ४ड. दिव्यांग कल्याणकारी योजना निधी | F115: 0 | G115: 0 | H115: 0 | I115: 0 | J115: 0 | K115: 0 | M115: 0 | N115: 0
A116: 1 | B116: FE14E101 | E116: दिव्यांग कल्याणकारी योजना | F116: 0 | G116: 355309730 | H116: 355309730 | I116: 165309730 | J116: 89998245 | K116: 100001755 | M116: 0 | N116: 0
...

Sheet A_DPDC_Machinery_Tree
A1: सन 2018-19 चे अंदाजपत्रक – खास निधीतून करावयाची योजनांतर्गत कामे
A2: अनुक्रमांक | B2: विवरण | D2: नक्की आकडा | G2: मान्य अंदाज 2017-18 | H2: नवीन अंदाज 2018-19
D3: 2014-15 | E3: 2015-16 | F3: 2016-17
C7: ५. पुणे जिल्हा नियोजन व विकास मंडळ निधीतून करावयाची कामे
C8: ५अ. मा. आमदारांनी सुचविल्याप्रमाणे करावयाची विकासाची कामे
A9: 1 | B9: FE15A101 | C9: बोपोडी मतदार संघ क्र. २४६ | D9: 0 | E9: 0 | F9: 0 | G9: 5000000 | H9: 5000000
A10: 2 | B10: FE15A102 | C10: शिवाजीनगर मतदार संघ क्र. २४७ | D10: 13029718 | E10: 10537543 | F10: 6974020 | G10: 5000000 | H10: 5000000
A11: 3 | B11: FE15A103 | C11: पर्वती मतदार संघ क्र. २४८ | D11: 2017582 | E11: 3329762 | F11: 6077423 | G11: 5000000 | H11: 5000000
A12: 4 | B12: FE15A104 | C12: कसबा पेठ मतदार संघ क्र. २४९ | D12: 12514432 | E12: 16963092 | F12: 9342997 | G12: 5000000 | H12: 5000000
A13: 5 | B13: FE15A105 | C13: भवानी पेठ मतदार संघ क्र. २५० | D13: 0 | E13: 0 | F13: 0 | G13: 5000000 | H13: 5000000
A14: 6 | B14: FE15A106 | C14: पुणे (कॅन्टोन्मेंट) मतदार संघ क्र. २५१ | D14: 8828578 | E14: 2055269 | F14: 3669469 | G14: 5000000 | H14: 5000000
A15: 7 | B15: FE15A107 | C15: विधान परिषद सदस्य | D15: 669792 | E15: 4063280 | F15: 3175750 | G15: 2500000 | H15: 2500000
D16: 0 | E16: 0 | F16: 0 | G16: 0 | H16: 0
A17: 8 | B17: FE15A108 | C17: ५ब. मा. खासदारांनी सुचविल्याप्रमाणे करावयाची विकासाची कामे | D17: 3109500 | E17: 1785256 | F17: 3969772 | G17: 20000000 | H17: 20000000
D18: 0 | E18: 0 | F18: 0 | G18: 0 | H18: 0
A19: 9 | B19: FE15A110 | C19: महानगरपालिका क्षेत्रात मुलभूत सोईसुविधांसाठी विशेष अनुदान | D19: 21871594 | E19: 56938302 | F19: 37747679 | G19: 0 | H19: 0
A20: 10 | B20: FE15A111 | C20: मुळशी मतदार संघ | D20: 0 | E20: 0 | F20: 0 | G20: 2500000 | H20: 2500000
A21: 11 | B21: FE15A112 | C21: कोथरूड विधानसभा मतदार संघ | D21: 4018776 | E21: 1965863 | F21: 4981436 | G21: 5000000 | H21: 5000000
A22: 12 | B22: FE15A113 | C22: हडपसर विधानसभा मतदार संघ | D22: 2705850 | E22: 231750 | F22: 1365800 | G22: 5000000 | H22: 5000000
A23: 13 | B23: FE15A114 | C23: वडगांवशेरी विधानसभा मतदार संघ | D23: 249992 | E23: 1258089 | F23: 429548 | G23: 5000000 | H23: 5000000
A24: 14 | B24: FE15A115 | C24: खडकवासला विधानसभा मतदार संघ | D24: 254896 | E24: 698976 | F24: 0 | G24: 5000000 | H24: 5000000
A25: 15 | B25: FE15A117 | C25: सर्वसाधारण जिल्हा वार्षिक योजना अंतर्गत नाविन्यपूर्ण योजनांचा निधी | D25: 0 | E25: 0 | F25: 4417087 | G25: 0 | H25: 0
A26: RE53A101 | C26: ५. पुणे जिल्हा नियोजन व विकास मंडळ निधीतून करावयाची कामे बेरीज | D26: 69270710 | E26: 99827182 | F26: 82150981 | G26: 75000000 | H26: 75000000
D27: 0 | E27: 0 | F27: 0 | G27: 0 | H27: 0
D28: 0 | E28: 0 | F28: 0 | G28: 0 | H28: 0
C29: ७. यंत्रसामुग्री घसारा निधीतून विकत घ्याववयाची नवीन सामुग्री | D29: 0 | E29: 0 | F29: 0 | G29: 0 | H29: 0
C30: अग्निशामक दलासाठी यंत्रसामुग्री :- | D30: 0 | E30: 0 | F30: 0 | G30: 0 | H30: 0
B31: FE17A103-1 | C31: वॉटर टँकर पंपासह (2 नग) | D31: 0 | E31: 3921953 | F31: 5629684 | G31: 10000000 | H31: 16000000
B32: FE17A103-2 | C32: फायर इंजिन गाडी (7 नग) | D32: 24000000 | E32: 20520000 | F32: 17850000 | G32: 10000000 | H32: 40000000
B33: FE17A103-4 | C33: हायड्रोलिक प्लॅटफॉर्म | D33: 0 | E33: 0 | F33: 0 | G33: 15000000 | H33: 0
B34: FE17A103-12 | C34: रेस्क्यू इक्वीपमेंट व लाईट मास्ट | D34: 11319330 | E34: 0 | F34: 0 | G34: 10000000 | H34: 0
B35: FE17A103-30 | C35: अल्ट्रा हायप्रेशर पिआर्सी मशीन | D35: 5991000 | E35: 0 | F35: 0 | G35: 0 | H35: 0
B36: FE17A103-31 | C36: मुख्य अग्निशमन अधिकारी यांचे कार्यालय वापरासाठी महेंद्र कंपनीचे स्कॉर्पीओ जीप खरेदी | D36: 0 | E36: 0 | F36: 595000 | G36: 0 | H36: 0
B37: FE17A103-32 | C37: अत्याधुनिक बिनतारी संदेशवहन यंत्रणा उभारणे | D37: 0 | E37: 0 | F37: 0 | G37: 10000000 | H37: 0
B38: FE17A107-23 | C38: आरोग्य विभागाकडील सरासरी आयुर्मान संपलेल्या आर्टीक्युलेटेड क्रेन निरस्त करून नवीन वाहने खरेदी करणे | D38: 0 | E38: 2054871 | F38: 0 | G38: 0 | H38: 0
B39: FE17A113-6 | C39: विद्युत विभाग :- हायड्रॉलिक प्लॅटफॉर्म (2 नग) | D39: 0 | E39: 0 | F39: 0 | G39: 0 | H39: 5000000
B40: FE17A114-6 | C40: बॅकहो लोडर खरेदी करणे | D40: 0 | E40: 0 | F40: 0 | G40: 6000000 | H40: 6000000
B41: FE17A114-9 | C41: पथ विभागासाठी ५ टिपर खरेदी करणे | D41: 0 | E41: 0 | F41: 0 | G41: 51000000 | H41: 20000000
B42: FE17A114-10 | C42: पथ विभागाकडील कोठ्यांसाठी रोलर्स, मिक्‍सर्स, पेव्हर अन्य यंत्रसामुग्री खरेदी करणे | D42: 0 | E42: 0 | F42: 0 | G42: 25000000 | H42: 0
... B102: FE17A298 | C102: प्र.क.५० ब मध्ये घनकचरा व्यवस्थापनासाठी छोटे वाहन खरेदी करणे. | D102: 0 | E102: 466088 | F102: 0 | G102: 0 | H102: 0
D103: 0 | E103: 0 | F103: 0 | G103: 0 | H103: 0
A104: RE51A101 | C104: ७. यंत्रसामुग्री घसारा निधी बेरीज | D104: 76946295 | E104: 124947035 | F104: 146333075 | G104: 322240000 | H104: 382500000
D105: 0 | E105: 0 | F105: 0 | G105: 0 | H105: 0
C106: १०. वृक्ष संरक्षण व संवर्धन प्राधिकारी निधीतून (अ‍ॅथॉरिटी फंडातून) करावयाचा खर्च | D106: 0 | E106: 0 | F106: 0 | G106: 0 | H106: 0
C107: १०क. वृक्ष संवर्धन व संरक्षण कार्यालयाकडील खर्च :- | D107: 0 | E107: 0 | F107: 0 | G107: 0 | H107: 0
B108: FE20A101A | C108: १. कायम सेवकवर्ग वेतन | D108: 27176981 | E108: 19762428 | F108: 29803186 | G108: 55000000 | H108: 55000000
B109: FE20A102A | C109: २. हंगामी सेवकवर्ग | D109: 1252190 | E109: 1377902 | F109: 0 | G109: 1000000 | H109: 1000000
D110: 0 | E110: 0 | F110: 0 | G110: 0 | H110: 0
C111: १०क. बेरीज | D111: 28429171 | E111: 21140330 | F111: 29803186 | G111: 56000000 | H111: 56000000
D112: 0 | E112: 0 | F112: 0 | G112: 0 | H112: 0
C113: १०ग. संकीर्ण :- | D113: 0 | E113: 0 | F113: 0 | G113: 0 | H113: 0
B114: FE20C101 | C114: १. मुद्रण | D114: 106875 | E114: 270588 | F114: 374590 | G114: 380000 | H114: 418000
B115: FE20C102 | C115: २. लेखन व साहित्य | D115: 301362 | E115: 322845 | F115: 499927 | G115: 500000 | H115: 1500000
B116: FE20C103 | C116: ३. प्रकटन खर्च | D116: 626432 | E116: 795948 | F116: 345240 | G116: 1000000 | H116: 1100000
B117: FE20C104 | C117: ४. टपालखर्च व पावती तिकिटे | D117: 58901 | E117: 54421 | F117: 55664 | G117: 100000 | H117: 110000
B118: FE20C105 | C118: ५. गणवेष | D118: 28837 | E118: 27116 | F118: 104468 | G118: 200000 | H118: 220000
B119: FE20C106 | C119: ६. पुस्तके व शिलकी साहित्य | D119: 0 | E119: 0 | F119: 0 | G119: 10000 | H119: 100000
B120: FE20C107 | C120: ७. मुलांसाठी मनोरंजन व इतर खर्च | D120: 225722 | E120: 232227 | F120: 263614 | G120: 550000 | H120: 605000
B121: FE20C108 | C121: ८. ट्री अ‍ॅथॉरिटी सभा चहापान खर्च (न.स.) | D121: 70758 | E121: 29825 | F121: 19500 | G121: 100000 | H121: 110000
D122: 0 | E122: 0 | F122: 0 | G122: 0 | H122: 0
C123: १०ग. बेरीज | D123: 1418887 | E123: 1732970 | F123: 1663003 | G123: 2840000 | H123: 4163000
D124: 0 | E124: 0 | F124: 0 | G124: 0 | H124: 0
B125: FE20D101 | C125: नर्सरीच्या वाढीसाठी रोपे, उपकरणे, खते, साहित्य खरेदी व दुरुस्ती देखभाल | D125: 0 | E125: 0 | F125: 884329 | G125: 1200000 | H125: 2000000
B126: FE20Q101 | C126: पुणे शहरात शालेय विार्थ्यांसाठी पर्यावरणावर आधारित विविध उपक्रम राबविणे | D126: 119976 | E126: 0 | F126: 29378 | G126: 300000 | H126: 345000
B127: FE20E101 | C127: ड. मनपातर्फे फळाफुलांचे प्रदर्शन | D127: 1039550 | E127: 547797 | F127: 810942 | G127: 1500000 | H127: 1725000
B128: FE20G101 | C128: छ. वृक्ष लागवडीसाठी ३ ते ४ वर्षे वयाची व १० ते १५ फूट उंचीची रोपे, झाडांचे संरक्षणासाठी ट्री गार्ड खरेदी व जुने ट्री गार्ड दुरुस्ती | D128: 1083452 | E128: 181496 | F128: 1692680 | G128: 3000000 | H128: 3450000
B129: FE20H101 | C129: ज. झाडांची हालवाहलव | D129: 0 | E129: 0 | F129: 1057886 | G129: 1000000 | H129: 1150000
B130: FE20I101 | C130: ञ. मनपा सार्वजनिक जागेवरील वृक्षारोपण, संरक्षण देखभाल व तद्‌नुषंगिक खर्च | D130: 5307179 | E130: 4446832 | F130: 6589012 | G130: 12000000 | H130: 15000000
B131: FE20K101 | C131: फ. ट्री अ‍ॅथॉरिटीस निरनिराळ्या ठिकाणी भेट देण्यासाठी खर्च | D131: 0 | E131: 0 | F131: 0 | G131: 1200000 | H131: 1380000
B132: FE20L101 | C132: १०ब. वृक्षारोपण उत्तेजनार्थ बक्षिसे | D132: 159650 | E132: 0 | F132: 0 | G132: 1000000 | H132: 1150000
B133: FE20M101 | C133: १०भ. कामगार नुकसान भरपाई कायाखाली नुकसानभरपाई | D133: 0 | E133: 0 | F133: 0 | G133: 150000 | H133: 172500
B134: FE20N101 | C134: १०क्ष. वृक्षगणना व अनुषंगिक कामे | D134: 218567 | E134: 0 | F134: 14418019 | G134: 50000000 | H134: 50000000
B135: FE20P101 | C135: झाडांना पाणी घालण्यासाठी टँकर खरेदी करणे | D135: 1446001 | E135: 1996371 | F135: 668250 | G135: 5000000 | H135: 7500000
B136: FE20P103 | C136: टायर्स सुटे भाग व देखभाल | D136: 4799997 | E136: 4799935 | F136: 6188802 | G136: 8000000 | H136: 9200000
... B147: FE20P117 | C147: पुणे मनपा उद्यानांच्या अंतर्गत असणारे जलाशयातील जैवविविधता वृध्दिंगत करणे, परिसंस्थेचे संवर्धन करणे यासाठी उपाययोजना करणे | D147: 0 | E147: 0 | F147: 2308045 | G147: 0 | H147: 0
D148: 0 | E148: 0 | F148: 0 | G148: 0 | H148: 0
C149: १०. वृक्ष संरक्षण व संवर्धन प्राधिकारी निधीतून (अ‍ॅथॉरिटी फंडातून) करावयाचा खर्च एकूण बेरीज | D149: 48696450 | E149: 66949572 | F149: 93185628 | G149: 184490000 | H149: 202180500
D150: 0 | E150: 0 | F150: 0 | G150: 0 | H150: 0
B151: FE31A101 | C151: १९. संकल्प निधी | D151: 6161486 | E151: 6721230 | F151: 10615950 | G151: 0 | H151: 0
D152: 0 | E152: 0 | F152: 0 | G152: 0 | H152: 0
A153: • | C153: १९. संकल्प निधी बेरीज | D153: 6161486 | E153: 6721230 | F153: 10615950 | G153: 0 | H153: 0

Sheet A_Capital_List
F1: प्रकल्पीय रक्कम | G1: 1819 आयुक्त | H1: H
A3: पथ विभागाकडील कामाच्या याद्या
A6: यादी क्र. A2
A7: शहरातील रस्ते डांबरीकरणाने विकसित करणे
A8: CE20A102/A2-
A10: क्र. | B10: code | C10: ward | E10: कामाचे नाव | F10: प्रकल्पीय रक्कम | G10: तरतूद
A12: 1 | B12: CE20A102/A2-101 | E12: शिवणे खराडी नदीकाठचा रस्ता विकसित करणेसाठी भूसंपादनासाठी | G12: 20000000
A13: 2 | B13: CE20A102/A2-102 | E13: बावधन स.क्र.24, 49,58 पी.व्ही.आय.पी.आय.टी.येथील 24/18/12 मी. रस्त्याचे विकसन करणे, भूसंपादनासाठी | G13: 10000000
A14: 3 | B14: CE20A102/A2-103 | E14: खडकवासला विधानसभा मतदारसंघ अंतर्गत नवले पुल ते सिंहगड 12 मी डी पी रस्ता दोन्ही बाजुचा सर्व्हिस रस्ता व लगतचे रस्ते करणे, भूसंपादनासाठी | G14: 5000000
A15: 4 | B15: CE20A102/A2-104 | E15: सुस ते पाषाण यांना जोडणार्‍या स.न.१३४ ,१३५,१३६,१३७,१३८ व १४० पाषाण या मिळकतीमधून जाणार्‍या ३६ मी. डी.पी.रस्त्याचे डांबरीकरण / काँक्रिटीकरण करणे, भूसंपादनासाठी | G15: 10000000
A16: 5 | B16: CE20A102/A2-105 | E16: सॅलिसबरी पार्क येथील गिडणी पार्क परिसरामध्ये विविध ठिकाणी मिलींग करुन डांबरीकरण करणे | G16: 10000000
A17: 6 | B17: CE20A102/A2-106 | E17: हडपसर औदयोगिक वसाहतीमधील टाटा हनीवेल कंपनी जवळीलहडपसर औद्योगिक वसाहत ते मगरपट्टच्या मागील 24.00 मी. एच.सी.एम.टी.आर. रस्ता जोडणारया डी.पी. रस्तच्या दोनही कॅनॉलवरील पुल बांधणे. | F17: 50000000 | G17: 20000000
E19: सन 2017-18 मधील अपूर्ण कामांसाठी सन 2018-19 मध्ये उपलब्ध केलेली तरतूद
A20: 7 | B20: CE20A102/A2-1109+ | E20: सन 2016 - 2017 मधील कामे पुर्ण करणेसाठी व जुने देयकासाठी (पेडींग बिलासाठी) | F20: 0 | G20: 200000000
A21: 8 | B21: CE20A102/A2-1427+ | C21: 30.,34 | E21: सिंहगड रस्ता वडगाव बु. स.न. ३० पासून पु.ल. देशपांडे उदयान पर्यंत ७.५ मी. रुंदीचा रस्ता कॅनालच्या कडेने विकसित करणे | F21: 160000000 | G21: 20000000
A22: 9 | B22: CE20A102/A2-1539+ | C22: 41 | E22: हडपसर औोध्योगीक वसाहत येथे कॅनालवर पुल बांधणे. | F22: 60000000 | G22: 15000000
A23: 10 | B23: CE20A102/A2-1546+ | C23: 4 | E23: खराडी येथील ब्लु बेरी व डेक्‍कन गोल्ड येथील अर्धवट असलेला १२मी. डी.पी.रस्ता ६०मी.डी रस्त्यला जोडणे. | F23: 10000000 | G23: 5000000
A24: 11 | B24: CE20A102/A2-1590+ | C24: G | E24: शिवणे खराडी नदीकाठचा रस्ता विकसित करणे (डीफर्ड पेमेंट पदधतीने) | F24: 3650000000 | G24: 300000000
A25: 12 | B25: CE20A102/SA2-296+ | E25: सुस ते पाषाण यांना जोडणार्‍या स.न.१३४ ,१३५,१३६,१३७,१३८ व १४० पाषाण या मिळकतीमधून जाणार्‍या ३६ मी. डी.पी.रस्त्याचे डांबरीकरण / काँक्रिटीकरण करणे. | F25: 100000000 | G25: 10000000
A26: 13 | B26: CE20A102/SA2-524 | E26: बालेवाडी मुख्य रस्त्याची उर्वरित विकास कामे करणे | F26: 10000000 | G26: 10000000
A27: 14 | B27: CE20A102/SA2-724 | C27: 26 | E27: महमंद वाडी प्र.क्र. 26 न्याती क्‍लब समोरील टी रस्ते स.नं. 40, 42 येथील डी.पी. रस्ते तयार करणे. | F27: 28000000 | G27: 10000000
A28: 15 | B28: CE20A102/SA2-772 | C28: 30 | E28: आशा हॉटेल ते म्हसोबा चौक पर्यंतचा 12 मी डी पी रस्ता विकसित करणे | F28: 5000000 | G28: 5000000
A29: 16 | B29: CE20A102/SA2-784 | C29: 31 | E29: तिरुपतीनगर रस्ता विकसित करणे. | F29: 5000000 | G29: 5000000
A30: 17 | B30: CE20A102/SA2-829 | C30: 33 | E30: बावधन खु. फॉर्च्युना बिल्डिंग ते स.नं. १५१ , 24 मी डी.पी. रोड तयार करणे | F30: 30000000 | G30: 5000000
A31: 18 | B31: CE20A102/SA2-911 | C31: 36 | E31: प्रभाग क्र.३६ मधील बिबवेवाडी मुख्य रस्ता विकसित करणे | F31: 286500000 | G31: 110000000
A32: 19 | B32: CE20A102/SA2-914 | C32: 10 | E32: बावधन स.क्र.24, 49,58 पी.व्ही.आय.पी.आय.टी.येथील 24/18/12 मी. रस्त्याचे विकसन करणे. | F32: 40000000 | G32: 5000000
A33: 20 | B33: CE20A102/SA2-920 | C33: 33 | E33: खडकवासला विधानसभा मतदारसंघ अंतर्गत नवले पुल ते सिंहगड 12 मी डी पी रस्ता दोन्ही बाजुचा सर्व्हिस रस्ता व लगतचे रस्ते करणे (डांबरीकरण करणे) | F33: 250000000 | G33: 5000000
E35: यादी क्र. A2 एकूण | F35: 4684500000 | G35: 780000000
A38: यादी क्र. A6
A39: शहरामधील रस्ते विकसित करणे
A40: CE20A1249/A6-
A42: क्र. | B42: code | C42: ward | E42: कामाचे नाव | F42: प्रकल्पीय रक्कम | G42: तरतूद
A44: 1 | B44: CE20A1249/A6-101 | C44: 38 | E44: धनकवडी स. नं. 30,31,32 कात्रज 12 डी. पी. रस्ता विकसीत करणे. | F44: 14000000 | G44: 3000000
A45: 2 | B45: CE20A1249/A6-102 | C45: 38 | E45: धनकवडी स. नं. २३ कात्रज 12 डी. पी. रस्ता विकसीत करणे. | F45: 8000000 | G45: 3000000
A46: 3 | B46: CE20A1249/A6-103 | C46: 39 | E46: धनकवडी मधील आंबेगाव पठार फॉरेस्ट कडेला 18 मी. डी. पी.रस्ता विकसीत करणे. | F46: 15000000 | G46: 3000000
A47: 4 | B47: CE20A1249/A6-104 | C47: 35 | E47: पदमावती सोसायटी ते तीन हत्ती चौकापर्यंतचा कलम २०५ रस्ता विकसीत करणे. | F47: 9000000 | G47: 3000000
A48: 5 | B48: CE20A1249/A6-105 | C48: 35 | E48: धनकवडी मानवेंद्र सोसायटी ते स. नं. 5,6,10 मधुन जाणारा 12 मी. डी. पी. विकसीत करणे. | F48: 10000000 | G48: 3000000
A49: 6 | B49: CE20A1249/A6-106 | C49: 40 | E49: मैत्री चौकालत कात्रज डेअरी उत्तेरेकडील स. नं. १३३ मधुन जाणारा 24 मी. डी. पी. रस्ता विकसीत करणे. | F49: 12000000 | G49: 3000000
A50: 7 | B50: CE20A1249/A6-107 | C50: 40 | E50: कात्रज बायपास रस्ता ते आंबेगाव बु स. नं. २८ कडे जाणारा १८ मी. रूंदीचा रस्ता व सर्व्हिस रस्ता विकसीत करणे. | F50: 15000000 | G50: 5500000
A51: 8 | B51: CE20A1249/A6-108 | C51: 40 | E51: आंबेगाव बु. स. नं.36 व 39 मधील 12 मी. डी. पी. रस्त्यावरील नाल्यावर कर्ल्व्हट करणे व रस्ता करणे. | F51: 15000000 | G51: 3000000
A52: 9 | B52: CE20A1249/A6-109 | C52: 40 | E52: दत्तनगर चौक ते न-हे दरम्यान विंडसर कौटी येथील वळण काढुन रस्ता सरळ करणे. | F52: 12500000 | G52: 3000000
A53: 10 | B53: CE20A1249/A6-110 | C53: 35 | E53: पदमावती येथील गाडगीळ उदयाना जवळील नल्यावरील कल्वर्ट मजबुती करण करणे. | F53: 5000000 | G53: 3000000
A54: 11 | B54: CE20A1249/A6-111 | C54: 36 | E54: बिबवेवाडी सर्व्हे नं 572,573,575,577,578,579 मधुन जाणारा 24 मी. डी.पी. रस्ता विकसीत करणे. | F54: 20000000 | G54: 3000000
A55: 12 | B55: CE20A1249/A6-112 | C55: 13 | E55: राहुलनगर प्रितमनगर 18 मी डी पी रस्ता विकसित करणे. | F55: 10000000 | G55: 3000000
... A70: 27 | B70: CE20A1249/A6-127 | C70: 33 | E70: वडगाव खुर्द मधुकोष सोसा. लगतचा १८ मी. डी.पी.रस्ता विकसित करणे | F70: 15000000 | G70: 3000000
A71: 28 | B71: CE20A1249/A6-128 | C71: 12,14 | E71: बालभारती चौक ते पौड फाटा रस्ता विकसीत करणे. सल्लागार | F71: 300000000 | G71: 3000000
A72: 29 | B72: CE20A1249/A6-129 | C72: 9 | E72: लक्ष्मी माता मंदीर ते दसरा चौक हायवे पर्यंत रस्ता विकसीत करणे | F72: 20000000 | G72: 5500000
A73: 30 | B73: CE20A1249/A6-130 | C73: 7 | E73: संगमवाडी गावठाण येथील रस्ते विकसित करणे व पावसाळी लाईन टाकणे | F73: 5000000 | G73: 3000000
A74: 31 | B74: CE20A1249/A6-131 | C74: 7 | E74: सुस रस्ता विकसीत करणे | F74: 10000000 | G74: 3000000
A75: 32 | B75: CE20A1249/A6-132 | C75: 9 | E75: बाणेर स.न. १०१, १०३,१०४ मधील पुणे मनपा हद्‌दीपर्यंतचा डी.पी. रस्ता मर्सिडीज बेज शोरुम लगतचा रस्ता विकसित करणे | F75: 35000000 | G75: 8000000
A76: 33 | B76: CE20A1249/A6-133 | C76: 9 | E76: झुंज बंगला ते सोमेश्वर मंदीर १५ मी. रस्त्याचे उर्वरित काम करणे | F76: 5000000 | G76: 3000000
A77: 34 | B77: CE20A1249/A6-134 | C77: 9 | E77: औंध बालेवाडी रस्त्यामधील पिंपळे निलख चौकाजवळील स.न. १५२ येथील उर्वरित बॉक्स कल्व्हर्ट बांधणे | F77: 10000000 | G77: 3000000
A78: 35 | B78: CE20A1249/A6-135 | C78: 9 | E78: बालेवाडी स.न. 10-16 मधील रस्ता विकसित करणे | F78: 30000000 | G78: 8000000
A79: 36 | B79: CE20A1249/A6-136 | C79: 9 | E79: बालेववाडी स.न. ३२, ३४ वाटिका सोसा.समोरील १८ मी. रस्ता विकसित करणे | F79: 35000000 | G79: 3000000
A80: 37 | B80: CE20A1249/A6-137 | C80: 9 | E80: सुस बाणेर हद्‌दीवरील १८ मी. रस्ता विकसित करणे | F80: 10000000 | G80: 3000000
A81: 38 | B81: CE20A1249/A6-138 | C81: 9 | E81: बाणेर स न 66, 68 बालेवाडी स नं 23 व इतर मधील ताब्यात आलेल्या जागेत कनेक्टीव्हीटी जोडण्यासाठी रस्ता विकसीत करणे. | F81: 10000000 | G81: 3000000
A82: 39 | B82: CE20A1249/A6-139 | C82: 14 | E82: र्फग्युसन कॉलेज रस्त्यावरील गरवारे चौक ते ॲग्रीक्लचर कॉलेज चौक फुटपाथ विकसन व सुशोभीकरण करणे. | F82: 180000000 | G82: 3000000
A83: 40 | B83: CE20A1249/A6-140 | E83: बालेवाडी बाणेर रोड नजीक रामनदीकिनारी रस्त्याचे कडेला रिटेनींग वॉल बांधाणे. | F83: 15000000 | G83: 3000000
A84: 41 | B84: CE20A1249/A6-141 | C84: 5 | E84: वडगाव शेरी बिशप स्कुल ते पेपल सेमिनरी 18 मी . डी. पी. रस्ता विकसीत करणे. | F84: 0 | G84: 5000000
A85: 42 | B85: CE20A1249/A6-142 | C85: 26 | E85: महंमदवाडी स.नं. 17-18 मधून जाणारा 18 मी. डी.पी. रस्ता विकसीत करणे. | F85: 50000000 | G85: 3000000
A86: 43 | B86: CE20A1249/A6-143 | C86: 26 | E86: महंमदवाडी स.नं. 47 ते 70 पालखी रस्ता 18 मी. डी.पी. विकसीत करणे | F86: 150000000 | G86: 3000000
A87: 44 | B87: CE20A1249/A6-144 | C87: 26 | E87: हडपसर स.नं. 67-55-52 मधून हांडेवाडी सातव चौक ते डेरे कंपनी उर्वरीत 18 मी. डी.पी. रस्ता विकसीत करणे. | F87: 30000000 | G87: 3000000
A88: 45 | B88: CE20A1249/A6-145 | C88: 26 | E88: महमदवाडी स.नं. 96 ते 4 व 6 मधून देसार्इ हॉस्पीटल ते दिल्ली पब्लिक स्कूल बाह्यवळण 24 मी. डी.पी. रस्ता विकसीत करणे. | F88: 70000000 | G88: 3000000
A89: 46 | B89: CE20A1249/A6-146 | C89: 26 | E89: महंमदवाडी स.नं. 12-13 ते स.नं. 57,58 मधील 18 मी. डी.पी. रस्ता विकसीत करणे. | F89: 50000000 | G89: 3000000
A90: 47 | B90: CE20A1249/A6-147 | C90: 23 | E90: हडपसर स.नं. 24,25 ते ग्लार्इडींग सेंटरच्या बाजूने 20 मी. डी.पी.रस्ता विकसीत करणे. | F90: 70000000 | G90: 3000000
A91: 48 | B91: CE20A1249/A6-148 | C91: 23 | E91: हडपसर स.नं. 77 लगत धवल विंड स्केप समोरील 12 मी. डी.पी. रस्ता विकसीत करणे. | F91: 10000000 | G91: 3000000
A92: 49 | B92: CE20A1249/A6-149 | C92: 23 | E92: हडपसर स.नं. 80 मधील 12 मी. डी.पी. रस्ता विकसीत करणे. | F92: 10000000 | G92: 3000000
A93: 50 | B93: CE20A1249/A6-150 | C93: 22 | E93: मगरपट्टा 30 मी. डी.पी. रस्ता विकसीत करणे. | F93: 50000000 | G93: 50000000
A94: 51 | B94: CE20A1249/A6-151 | C94: 22 | E94: हडपसर माळवाडी संजीवनी हॉस्पीटल ते पी एम पी एल डेपो 18 मी.डि.पी. रस्ता विकसीत करणे. | F94: 20000000 | G94: 3000000
A95: 52 | B95: CE20A1249/A6-152 | C95: 22 | E95: मगरपटट्टा कुमार पॅरेडार्इज झेड प्लस चौक ( मगरपटटा रस्ता ) 18 मी. डी.पी. रस्ता रुंदीकरण करून विकसीत करणे. | F95: 50000000 | G95: 3000000
... A115: 72 | B115: CE20A1249/A6-172 | C115: 25 | E115: साळुंके विहार रस्ता रुंदीकरण व विकसीत करणे. | F115: 30000000 | G115: 3000000
A116: 73 | B116: CE20A1249/A6-173 | C116: G | E116: कोढंवा येथील व्ही आय टी व्होस्टेल समोरील स नं 2,3,4 मधील 30 मी. डी.पी. रस्ता विकसीत करणे. | F116: 50000000 | G116: 5500000
A117: 74 | B117: CE20A1249/A6-174 | C117: 14 | E117: गरवारे पुल ते अॅग्रीक्‍लचर कॉलेज चौक एफ सी रोड विकसीत करणे. | F117: 10000000 | G117: 80000000
A118: 75 | B118: CE20A1249/A6-175 | C118: G | E118: पौड फाटा उड्डाण पुल ते वारजे जकात नाका म.कर्वे रस्ता विकसीत करणे. | G118: 100000000
A119: 76 | B119: CE20A1249/A6-176 | C119: 40 | E119: आंबेगाव हद्दीवरील वडगांव ते कात्रज चौका पर्यंत रस्ते विकसीत करणे. | F119: 25000000 | G119: 10000000
A120: 77 | B120: CE20A1249/A6-177 | C120: 40 | E120: दत्तनगर ते आंबेगाव बु कडे जाणारा रस्ता रिलीकॉन सोसायटी जवळील रस्ता सरळ करणे. | G120: 10000000
A121: 78 | B121: CE20A1249/A6-178 | E121: वारजे येथील १२ मीटर हायवेलगतच्या डिपी रस्त्यांचे उर्वरीत कामे करणे | G121: 20000000
A122: 79 | B122: CE20A1249/A6-179 | E122: जुन्या हददीतील लोहगाव नगर रोडला जोडणारा सध्या अंशतः विकसीत १०० फुटी डिपी रस्ता ताब्यात घेवून विकसीत करणे | G122: 30000000
A123: 80 | B123: CE20A1249/A6-180 | E123: वडगावशेरी चंदननगर पाण्याची टाकी ते जुना मुंढवा येथील रस्ता विकसित करणे | G123: 8000000
E125: सन 2017-18 मधील अपूर्ण कामांसाठी सन 2018-19 मध्ये उपलब्ध केलेली तरतूद
A126: 81 | B126: CE20A1249/A6-1 | C126: 15 | E126: लक्ष्मी रस्ता, कुमठेकर रस्ता, टिळक रस्ता स्वारगेट चौक ते अलका थीएटर, बाजीराव रस्ता मित्रमंडळ चौक ते शनिवारवाडा येथे फुटपाथ विषयक विविध विकासाची कामे करणे. | F126: 35000000 | G126: 20000000
A127: 82 | B127: CE20A1249/A6-2 | C127: 38 | E127: कात्रज - सातारा रोड गुजरवाडी फाटा ते स.नं.45 कात्रज हद्दीपर्यंतचा 18 मीटर डी.पी.रस्ता विकसीत करणे. | F127: 57500000 | G127: 7500000
A128: 83 | B128: CE20A1249/A6-3 | C128: 34 | E128: हिंगणे वडगाव व विश्रांतीनगर ते तुकाईनगर २४ मी.डी.पी. रस्ता कॅनॉल व विकसित करणे (कॅनॉलवरील पुल विकसित करणे) | F128: 15000000 | G128: 7500000
A129: 84 | B129: CE20A1249/A6-4 | C129: 34 | E129: वडगांव बु।। स.नं. १७,१८ ते स.न. ३२ इंडियन हयुम पाईप पर्यंतचा 3० मी. डी.पी. रस्ता विकसित करणे (डांबरीकरण करणे) | F129: 25000000 | G129: 10000000
A130: 85 | B130: CE20A1249/A6-14 | C130: 1 | E130: येरवडा सर्व्हे ऑफ इंडिया ते कॉमर झोन ते जेल वसाहतीमधून एअरपोर्टकडे जाणारा 20 मीटर डी.पी. रस्ता विकसित करणे | F130: 20000000 | G130: 10000000
A131: 86 | B131: CE20A1249/SA6-175+ | E131: ५०९ चौक ते लोहगांव 30 मी.डी.पी.रस्ता विकसीत करणे. (धानोरी जकात नाका) | F131: 190000000 | G131: 16000000
A132: 87 | B132: CE20A1252+ | E132: पुणे शहरातील HCMTR रस्ते विकसीत करणे. ( सल्लागार फी ) | G132: 20000000
E134: यादी क्र. A6 एकूण | F134: 3013000000 | G134: 643000000
A136: यादी क्र. A9
A137: शहरातील रस्ते पुनर्डांबरीकरण करणे
A138: CE20A1259/A9-
A140: क्र. | B140: code | C140: ward | E140: कामाचे नाव | F140: प्रकल्पीय रक्कम | G140: तरतूद
A142: 1 | B142: CE20A1259/A9-1 | E142: आंबेगाव बु. ते वडगाव सिंहगड कॉलेजकडे जाणारा रस्ता डांबरीकरण करणे. | F142: 8000000 | G142: 3000000
A143: 2 | B143: CE20A1259/A9-2 | C143: 40 | E143: वडगांव बु. नवले पुल ते कात्रज चौक व कात्रज चौक ते कात्रज घाट दरम्यान महापालिका मार्गाचे मजबुती करण व पुर्णडांबरीकरण करणे. | F143: 60000000 | G143: 7000000
A144: 3 | B144: CE20A1259/A9-3 | C144: 37 | E144: काकडे वस्ती ते आई माता मंदीर दरम्यान रस्त्याचे रूंदीकरण करून रस्ता डांबरीकरण करणे. | F144: 15000000 | G144: 3000000
A145: 4 | B145: CE20A1259/A9-4 | C145: 16 | E145: कमला नेहरू हॉस्पिटल ते ठाकरे चौक (बाबुराव सणस कन्या शाळा) ते नरपथ गिरी चौक रस्ता करणे. | F145: 5000000 | G145: 3000000
A146: 5 | B146: CE20A1259/A9-5 | C146: 15 | E146: कुमठेकर रोड रामेश्वर चौक ते शनिपार ते खालकर तालीम मिलिंग करुन पुनःडांबरीकरण करणे. | F146: 5000000 | G146: 3000000
A147: 6 | B147: CE20A1259/A9-6 | C147: 29 | E147: पेशवे पथ मिलिंग करुन पुनःडांबरीकरण करणे. | F147: 5000000 | G147: 3000000
A148: 7 | B148: CE20A1259/A9-7 | C148: 19 | E148: नेहरू रस्ता रामोशी गेट ते संत कबीर चौक डांबरीकरण करणे. | F148: 5000000 | G148: 3000000
A149: 8 | B149: CE20A1259/A9-8 | C149: 19 | E149: नेहरू रस्ता ते ज्योतिबा फुले स्मारक रस्ता डांबरीकरण करणे. | F149: 5000000 | G149: 3000000
...

Sheet C_Revenue_Income
A1: पाणीपुरवठा व जलोत्सारण प्रकल्पांतर्गत | G1: खास निधी 'क' चा जमेचा गोषवारा व तपशील
A2: विवरण | C2: नक्की आकडा | H2: 2017-18 वर्षाचा अंदाज | J2: 2018-19 वर्षाचा अंदाज | M2: 2017-18 वर्षाच्या मान्य अंदाजाशी तुलना केलेला 2018-19 वर्षाचा मा. महा. आयुक्त यांनी सुचविलेला अंदाज
C3: 2014-15 | D3: 2015-16 | E3: 2016-17 | F3: 2016-17 शेवटची सहामाही | G3: 2017-18 पहिली सहामाही | H3: मान्य अंदाज | I3: दुरूस्त अंदाज | J3: मा. महापालिका आयुक्त यांनी सुचविलेला | K3: मा. स्थायी समितीने मान्यता दिलेला | L3: मा. महानगर- पालिकेने संमत केलेला
M5: अधिक | N5: कमी
A7: अधिनियमाप्रमाणे कमीत कमी रोख शिल्लक ठेवण्याची रक्कम जमेस धरून वर्षारंभीची शिल्लक | C7: 100000 | D7: 100000 | E7: 100000 | F7: 100000 | G7: 0 | H7: 100000 | I7: 100000 | J7: 100000 | K7: 0 | L7: 0 | M7: 0 | N7: 0
C8: 0 | D8: 0 | E8: 0 | F8: 0 | G8: 0 | H8: 0 | I8: 0 | J8: 0 | K8: 0 | L8: 0 | M8: 0 | N8: 0
A9: १. पाणीपुरवठा (अति. न.अ.) | C9: 0 | D9: 0 | E9: 0 | F9: 0 | G9: 0 | H9: 0 | I9: 0 | J9: 0 | K9: 0 | L9: 0 | M9: 0 | N9: 0
A10: क. पाणीपट्टी साधारण पाणीपट्टी (कआकसंप्र) | B10: XI12A101 | C10: 1341089335 | D10: 1852452983 | E10: 1114584244 | F10: 316808513 | G10: 932668414 | H10: 2290000000 | I10: 2290000000 | J10: 1800000000 | K10: 0 | L10: 0 | M10: 0 | N10: 490000000
A11: ख. शासनाकडून (कआकसंप्र) | B11: XI12B101 | C11: 0 | D11: 0 | E11: 0 | F11: 0 | G11: 0 | H11: 100000 | I11: 100000 | J11: 100000 | K11: 0 | L11: 0 | M11: 0 | N11: 0
A12: च. PMPML कडील मिळकतीवरील पाणीपट्टी (कआकसंप्र) | B12: XI12F101 | C12: 0 | D12: 0 | E12: 0 | F12: 0 | G12: 0 | H12: 100000 | I12: 100000 | J12: 100000 | K12: 0 | L12: 0 | M12: 0 | N12: 0
A13: छ. जललाभ कर (Water Benefit Tax) (कआकसंप्र) | B13: XI12G101 | C13: 302692528 | D13: 418910163 | E13: 543166436 | F13: 210147743 | G13: 375121840 | H13: 800000000 | I13: 800000000 | J13: 920000000 | K13: 0 | L13: 0 | M13: 120000000 | N13: 0
A14: ग. पाणीपट्टी पाणीमापकानुसार (अति.न.अ.) | B14: XI12C101 | C14: 359356133 | D14: 388645935 | E14: 401229463 | F14: 187649622 | G14: 241451816 | H14: 1161700000 | I14: 1161700000 | J14: 1164000000 | K14: 0 | L14: 0 | M14: 2300000 | N14: 0
A15: ग१. मीटर पाणीपट्टी थकबाकीपोटी जमा | B15: XI12C101A | C15: 0 | D15: 0 | E15: 0 | F15: 0 | G15: 0 | H15: 140000000 | I15: 140000000 | J15: 140000000 | K15: 0 | L15: 0 | M15: 0 | N15: 0
A16: ग२. गवनि खात्याअंतर्गत होणारी पाणीपट्टी जमा | B16: XI12C101B | C16: 41474022 | D16: 33175546 | E16: 10942484 | F16: 4397287 | G16: 5287392 | H16: 25000000 | I16: 25000000 | J16: 25000000 | K16: 0 | L16: 0 | M16: 0 | N16: 0
A17: अनधिकृत कनेक्शन नियमित करण्यापोटी जमा | B17: XI12S101 | C17: 74895 | D17: 30515 | E17: 739 | F17: 739 | G17: 0 | H17: 180000000 | I17: 180000000 | J17: 40500000 | K17: 0 | L17: 0 | M17: 0 | N17: 139500000
A18: घ. पाणीमापक भाडे | B18: XI12D101 | C18: 1972 | D18: 5797 | E18: 5473 | F18: 5473 | G18: 3074 | H18: 75000000 | I18: 75000000 | J18: 75000000 | K18: 0 | L18: 0 | M18: 0 | N18: 0
A19: ड. नवीन नळ आकार नळदुरुस्ती व साफसफी (परतजमा) | B19: XI12E101 | C19: 6509624 | D19: 8676617 | E19: 7255295 | F19: 1871539 | G19: 14329307 | H19: 500000 | I19: 500000 | J19: 15000000 | K19: 0 | L19: 0 | M19: 14500000 | N19: 0
A20: ऊर्जा बचत कक्षामार्फत पाणीपुरवठा योजनेसंदर्भात ऊर्जा संवर्धन पथदर्शी प्रकल्पासाठी मेढाकडून अनुदान | B20: XI12E102 | C20: 0 | D20: 500000 | E20: 0 | F20: 0 | G20: 0 | H20: 0 | I20: 0 | J20: 0 | K20: 0 | L20: 0 | M20: 0 | N20: 0
A21: ठ. कॉलनी रस्त्यावर पाईप टाकणे कामापोटी सुपरव्हिजन स्क्रुटीनी फी व अन्य जमा होणार | B21: XI12K101 | C21: 1180267 | D21: 1352460 | E21: 12393427 | F21: 7225349 | G21: 5125128 | H21: 8000000 | I21: 8000000 | J21: 20000000 | K21: 0 | L21: 0 | M21: 12000000 | N21: 0
... A29: ण. अंदाजपत्रक 'अ' कडून वर्ग | B29: XI12M101 | C29: 3087694698 | D29: 400282726 | E29: 2363450642 | F29: 2363450642 | G29: 0 | H29: -253367047 | I29: -253367047 | J29: 685744409 | K29: 0 | L29: 0 | M29: 939111456 | N29: 0
C30: 0 | D30: 0 | E30: 0 | F30: 0 | G30: 0 | H30: 0 | I30: 0 | J30: 0 | K30: 0 | L30: 0 | M30: 0 | N30: 0
A31: १. बेरीज | C31: 5165719080 | D31: 3145131258 | E31: 4517524035 | F31: 3129490693 | G31: 1599094226 | H31: 4486832953 | I31: 4486832953 | J31: 4999700000 | K31: 0 | L31: 0 | M31: 1142911456 | N31: 630044409
C32: 0 | D32: 0 | E32: 0 | F32: 0 | G32: 0 | H32: 0 | I32: 0 | J32: 0 | K32: 0 | L32: 0 | M32: 0 | N32: 0
A33: १अ. पुणे कॅन्टोन्मेंट पाणीपुरवठा जमा (अति.न.अ.) | C33: 0 | D33: 0 | E33: 0 | F33: 0 | G33: 0 | H33: 0 | I33: 0 | J33: 0 | K33: 0 | L33: 0 | M33: 0 | N33: 0
A34: (१) पाणीमापकानुसार पाणीपट्टी | B34: XI12Q101 | C34: 181297563 | D34: 237495666 | E34: 172872513 | F34: 66129497 | G34: 1370736 | H34: 130000000 | I34: 130000000 | J34: 200000000 | K34: 0 | L34: 0 | M34: 70000000 | N34: 0
A35: (२) H.E. Factory कडून येणारी जमा | B35: XI12Q102 | C35: 20768047 | D35: 12409034 | E35: 131099065 | F35: 99855514 | G35: 120948445 | H35: 50000000 | I35: 50000000 | J35: 70000000 | K35: 0 | L35: 0 | M35: 20000000 | N35: 0
C36: 0 | D36: 0 | E36: 0 | F36: 0 | G36: 0 | H36: 0 | I36: 0 | J36: 0 | K36: 0 | L36: 0 | M36: 0 | N36: 0
A37: १अ. बेरीज | C37: 202065610 | D37: 249904700 | E37: 303971578 | F37: 165985011 | G37: 122319181 | H37: 180000000 | I37: 180000000 | J37: 270000000 | K37: 0 | L37: 0 | M37: 90000000 | N37: 0
C38: 0 | D38: 0 | E38: 0 | F38: 0 | G38: 0 | H38: 0 | I38: 0 | J38: 0 | K38: 0 | L38: 0 | M38: 0 | N38: 0
A39: पुणे शहरात तंत्रशुध्द पध्दतीने पाणीपुरवठा करण्याची योजना (24x7) अनुदान (AMRUT) | B39: ZI12A111 | C39: 0 | D39: 0 | E39: 0 | F39: 0 | G39: 0 | H39: 350000000 | I39: 350000000 | J39: 750000000 | K39: 0 | L39: 0 | M39: 400000000 | N39: 0
A40: पुणे शहरात तंत्रशुध्द पध्दतीने पाणीपुरवठा करण्याची योजना (24x7) कर्जरोखे विक्री | B40: ZI12A112 | C40: 0 | D40: 0 | E40: 0 | F40: 0 | G40: 0 | H40: 2000000000 | I40: 2000000000 | J40: 0 | K40: 0 | L40: 0 | M40: 0 | N40: 2000000000
C41: 0 | D41: 0 | E41: 0 | F41: 0 | G41: 0 | H41: 0 | I41: 0 | J41: 0 | K41: 0 | L41: 0 | M41: 0 | N41: 0
A42: राष्ट्रीय नदीसुधारणा प्रकल्पातंर्गत (JICA) केंद्र सरकारकडून अनुदान | B42: ZI12A102 | C42: 0 | D42: 0 | E42: 259899999 | F42: 259899999 | G42: 0 | H42: 1275000000 | I42: 1275000000 | J42: 0 | K42: 0 | L42: 0 | M42: 0 | N42: 1275000000
C43: 0 | D43: 0 | E43: 0 | F43: 0 | G43: 0 | H43: 0 | I43: 0 | J43: 0 | K43: 0 | L43: 0 | M43: 0 | N43: 0
A44: १. एकूण बेरीज | C44: 5367784690 | D44: 3395035958 | E44: 5081395612 | F44: 3555375703 | G44: 1721413407 | H44: 8291832953 | I44: 8291832953 | J44: 6019700000 | K44: 0 | L44: 0 | M44: 1632911456 | N44: 3905044409
C45: 0 | D45: 0 | E45: 0 | F45: 0 | G45: 0 | H45: 0 | I45: 0 | J45: 0 | K45: 0 | L45: 0 | M45: 0 | N45: 0
A46: २. गटारे व नाले सुधारणा (अति.न.अ.) | C46: 0 | D46: 0 | E46: 0 | F46: 0 | G46: 0 | H46: 0 | I46: 0 | J46: 0 | K46: 0 | L46: 0 | M46: 0 | N46: 0
A47: क. सफाईपट्टी (कआकसंप्र) | B47: XI23A101 | C47: 1496037193 | D47: 2066573109 | E47: 2148672982 | F47: 859816399 | G47: 1393154490 | H47: 2750000000 | I47: 2750000000 | J47: 3096000000 | K47: 0 | L47: 0 | M47: 346000000 | N47: 0
A48: घ. सुअरेज बेनिफीट टॅक्स (कआकसंप्र) | B48: XI23D101 | C48: 619016536 | D48: 883719673 | E48: 967066203 | F48: 383016898 | G48: 645474320 | H48: 1600000000 | I48: 1600000000 | J48: 1680000000 | K48: 0 | L48: 0 | M48: 80000000 | N48: 0
A49: ग. ड्रेनेज / सलेज कनेक्शन व सेवावाढ आकार नियोजित बांधकाम क्षेत्रफळावर रु. ११ चौ. मि. | B49: XI23C101 | C49: 7333434 | D49: 8579633 | E49: 9116859 | F49: 4345583 | G49: 3652209 | H49: 10000000 | I49: 10000000 | J49: 10000000 | K49: 0 | L49: 0 | M49: 0 | N49: 0
C50: 0 | D50: 0 | E50: 0 | F50: 0 | G50: 0 | H50: 0 | I50: 0 | J50: 0 | K50: 0 | L50: 0 | M50: 0 | N50: 0
A51: २. बेरीज | C51: 2122387163 | D51: 2958872415 | E51: 3124856044 | F51: 1247178880 | G51: 2042281019 | H51: 4360000000 | I51: 4360000000 | J51: 4786000000 | K51: 0 | L51: 0 | M51: 426000000 | N51: 0
C52: 0 | D52: 0 | E52: 0 | F52: 0 | G52: 0 | H52: 0 | I52: 0 | J52: 0 | K52: 0 | L52: 0 | M52: 0 | N52: 0
A53: ३. डेव्हलपमेंट निधीकडून जमा (बांधकाम नियोजन) | B53: XI23F101 | C53: 450385939 | D53: 632249002 | E53: 681398032 | F53: 681398032 | G53: 0 | H53: 900000000 | I53: 900000000 | J53: 562500000 | K53: 0 | L53: 0 | M53: 0 | N53: 337500000
C54: 0 | D54: 0 | E54: 0 | F54: 0 | G54: 0 | H54: 0 | I54: 0 | J54: 0 | K54: 0 | L54: 0 | M54: 0 | N54: 0
A55: १. + २. + ३. एकूण बेरीज | C55: 7940557792 | D55: 6986157375 | E55: 8887649688 | F55: 5483952615 | G55: 3763694426 | H55: 13551832953 | I55: 13551832953 | J55: 11368200000 | K55: 0 | L55: 0 | M55: 2058911456 | N55: 4242544409
C56: 0 | D56: 0 | E56: 0 | F56: 0 | G56: 0 | H56: 0 | I56: 0 | J56: 0 | K56: 0 | L56: 0 | M56: 0 | N56: 0
A57: वर्षारंभीच्या शिलकेसह एकूण जमा | C57: 7940657792 | D57: 6986257375 | E57: 8887749688 | F57: 5484052615 | G57: 3763694426 | H57: 13551932953 | I57: 13551932953 | J57: 11368300000 | K57: 0 | L57: 0 | M57: 2058911456 | N57: 4242544409
C58: 0 | D58: 0 | E58: 0 | F58: 0 | G58: 0 | H58: 0 | I58: 0 | J58: 0 | K58: 0 | L58: 0 | M58: 0 | N58: 0
A59: अंदाजपत्रक 'क' एकूण जमा | C59: 7940657792 | D59: 6986257375 | E59: 8887749688 | F59: 5484052615 | G59: 3763694426 | H59: 13551932953 | I59: 13551932953 | J59: 11368300000 | K59: 0 | L59: 0 | M59: 2058911456 | N59: 4242544409

Sheet C_Revenue_Expenditure
A1: योजनेतर खर्च तपशील
A2: विवरण | D2: नक्‍की आकडा | G2: मान्य अंदाज 2017-18 | H2: नवीन अंदाज 2018-19
D3: 2014-15 | E3: 2015-16 | F3: 2016-17
A5: १. पाणीपुरवठा | D5: 0 | E5: 0 | F5: 0 | G5: 0 | H5: 0
A6: क. पाणीपुरवठा | D6: 0 | E6: 0 | F6: 0 | G6: 0 | H6: 0
A7: १. मध्यवर्ती कार्यालय, कायम सेवकवर्ग वेतन | B7: XE12A101A | D7: 17277661 | E7: 20163697 | F7: 24270905 | G7: 28000000 | H7: 30000000
A8: २अ. कायम सेवकवर्ग वेतन | B8: XE12A101B | D8: 94860971 | E8: 112681352 | F8: 129159922 | G8: 145000000 | H8: 143000000
A9: २ब. कायम सेवकवर्ग वेतन (वि.का.) | B9: XE12A###A | D9: 9542874 | E9: 10813818 | F9: 10793008 | G9: 15000000 | H9: 15000000
A10: ३. संकीर्ण | B10: XE12A103 | D10: 785104 | E10: 799999 | F10: 496203 | G10: 1080000 | H10: 1200000
A11: ४. पाण्याची किंमत (पर्वती पंपिंग स्टेशन) | B11: XE12A104 | D11: 161500000 | E11: 149074723 | F11: 130832460 | G11: 145000000 | H11: 160000000
A12: ५. पाणी शुद्ध करणे व तद्‌नुषंगिक कामे करणे | B12: XE12A105 | D12: 52999452 | E12: 54099331 | F12: 68067821 | G12: 58880000 | H12: 60000000
A13: ६. प्रयोगशाळा देखभाल खर्च | B13: XE12A106 | D13: 1193434 | E13: 1131134 | F13: 956631 | G13: 1080000 | H13: 1200000
A14: ७-अ. पंपिंग वीज खर्च | B14: XE12A107 | D14: 494546000 | E14: 493452559 | F14: 479999999 | G14: 570000000 | H14: 667000000
A15: ९. कोठी इतर साहित्य खर्च | B15: XE12A109 | D15: 3239120 | E15: 1275116 | F15: 2975682 | G15: 2520000 | H15: 2800000
A16: १२. पर्वती जलकेंद्रातील यंत्रसामुग्रीवरील घसारा (मु.ले.) | B16: XE12A112 | D16: 163912 | E16: 163906 | F16: 164000 | G16: 190000 | H16: 215000
A17: १४. जलप्रदूषण प्रतिबंधक खर्च | B17: XE12A115 | D17: 8850000 | E17: 3224833 | F17: 4823834 | G17: 4320000 | H17: 4700000
A18: १८. जलकेंद्र पाण्याच्या टाक्या येथे प्रकाश व्यवस्था व दूरध्वनी व्यवस्था | B18: XE12A120 | D18: 0 | E18: 0 | F18: 0 | G18: 360000 | H18: 800000
... A37: पर्वती जलकेंद्र प्रयोगशाळा येथे पाणी तपासणीसाठी लागणारी विविध उपकरणे व तद्‌नुषंगिक साहित्य खरेदी करणे | B37: XE12A146 | D37: 0 | E37: 0 | F37: 0 | G37: 360000 | H37: 500000
A38: क. बेरीज | D38: 908151990 | E38: 903255059 | F38: 957068541 | G38: 1080510000 | H38: 1221070000
D39: 0 | E39: 0 | F39: 0 | G39: 0 | H39: 0
A40: ख१. नळ खाते (स्वारगेट विभाग) | D40: 0 | E40: 0 | F40: 0 | G40: 0 | H40: 0
A41: १. कायम सेवक वर्ग वेतन | B41: XE12B101A | D41: 166857797 | E41: 180097170 | F41: 198416480 | G41: 215000000 | H41: 233500000
A42: २. संकीर्ण | B42: XE12B102 | D42: 344423 | E42: 665438 | F42: 799999 | G42: 900000 | H42: 1000000
A43: ४. शहरांतील / नव्याने समाविष्ट गावांतील सर्व व्हॉल्व्हज्‌ चालू व बंद करणे | B43: XE12B107 | D43: 26432807 | E43: 41880675 | F43: 31092583 | G43: 39600000 | H43: 39600000
A44: ८. टँकरने पाणीपुरवठा करणे | B44: XE12B111 | D44: 10314298 | E44: 12384914 | F44: 16107816 | G44: 7200000 | H44: 14000000
A45: ९. कोठी व इतर साहित्य खरेदी | B45: XE12B112 | D45: 15266437 | E45: 11946296 | F45: 23841464 | G45: 21600000 | H45: 40000000
A46: १०. देखभाल दुरुस्ती : नळदुरुस्ती व स्वच्छता तातडीच्या दुरुस्त्या चेंबर करणे, आर.सी.सी, कव्हर बसविणे व तदनुषंगिक कामे करणे | B46: XE12B113 | D46: 27459984 | E46: 27690999 | F46: 44788541 | G46: 43200000 | H46: 54000000
A47: ११. टाक्‍यांची दुरुस्ती | B47: XE12B114 | D47: 99862 | E47: 0 | F47: 0 | G47: 720000 | H47: 800000
A48: पाणीपुरवठा विभागाकडील देखभाल दुरूस्तीची कामे | B48: XE12B115# | D48: 0 | E48: 0 | F48: 20005303 | G48: 16650000 | H48: 0
D49: 0 | E49: 0 | F49: 0 | G49: 0 | H49: 0
A50: ख१. बेरीज | D50: 246775608 | E50: 274665492 | F50: 335052186 | G50: 344870000 | H50: 382900000
D51: 0 | E51: 0 | F51: 0 | G51: 0 | H51: 0
A52: ख२. नळ खाते (विभागीय कार्यालय) | D52: 0 | E52: 0 | F52: 0 | G52: 0 | H52: 0
A53: १. कायम सेवकवर्ग वेतन | B53: XE12B###A | D53: 35079153 | E53: 38369636 | F53: 36831303 | G53: 55000000 | H53: 50000000
A54: क्षेत्रीय कार्यालयाने करावयाची योजनेतर कामे | B54: XE12B301/W6-# | D54: 0 | E54: 0 | F54: 1380528 | G54: 0 | H54: 1300000
A55: क्षेत्रीय कार्यालयाने नागरिकांच्या सहभागातून करावयाची योजनेतर कामे | B55: XE12B302/C6-# | D55: 5632324 | E55: 4386080 | F55: 8138352 | G55: 10200000 | H55: 10200000
D56: 0 | E56: 0 | F56: 0 | G56: 0 | H56: 0
A57: ख२. बेरीज | D57: 40711477 | E57: 42755716 | F57: 46350183 | G57: 65200000 | H57: 61500000
D58: 0 | E58: 0 | F58: 0 | G58: 0 | H58: 0
A59: ख. एकूण बेरीज | D59: 287487085 | E59: 317421208 | F59: 381402369 | G59: 410070000 | H59: 444400000
D60: 0 | E60: 0 | F60: 0 | G60: 0 | H60: 0
A61: ग. पाणीमापके | D61: 0 | E61: 0 | F61: 0 | G61: 0 | H61: 0
A62: १. पाणीमापके दुरुस्ती | B62: XE12C101 | D62: 0 | E62: 148032 | F62: 0 | G62: 216000 | H62: 250000
A63: ३. संगणक यंत्रासाठी तयार करावयाच्या फॉर्मचा मुशाहिरा | B63: XE12C103 | D63: 0 | E63: 363600 | F63: 180000 | G63: 432000 | H63: 450000
A64: ४. मीटर बीले वाटप करणे | B64: XE12C104 | D64: 0 | E64: 0 | F64: 0 | G64: 360000 | H64: 400000
D65: 0 | E65: 0 | F65: 0 | G65: 0 | H65: 0
A66: ग. बेरीज | D66: 0 | E66: 511632 | F66: 180000 | G66: 1008000 | H66: 1100000
D67: 0 | E67: 0 | F67: 0 | G67: 0 | H67: 0
A68: च. मनपा सेवकांना द्यावयाचा महागाईभत्ता | B68: XE12F101 | D68: 7328815 | E68: 3861139 | F68: 2917610 | G68: 20000000 | H68: 20000000
A69: छ. नवीन वेतनश्रेणीनुसार द्यावयाच्या वेतनापोटी हप्ता | B69: XE12G101 | D69: 21175165 | E69: 17071529 | F69: 0 | G69: 0 | H69: 0
A70: ज. सानुग्रह अनुदान | B70: XE12H101 | D70: 24105719 | E70: 28248873 | F70: 1497925 | G70: 50000000 | H70: 60000000
A71: झ. मनपा सेवकांना प्रवासभत्ता सवलतीसाठी द्यावयाची रक्कम | B71: XE12I101 | D71: 749000 | E71: 588000 | F71: 170500 | G71: 10000000 | H71: 20000000
A72: थ. सेवानिवृत्ती वेतन व तोषदान | B72: XE12K101 | D72: 110000000 | E72: 150000000 | F72: 170000000 | G72: 200000000 | H72: 200000000
A73: प. पेट्रोल, डिझेल, टायर्स, सुटे भाग, देखभाल, दुरुस्ती | B73: XE12M101 | D73: 8496859 | E73: 7862004 | F73: 6787777 | G73: 7000000 | H73: 5000000
A74: ज्ञ१. कर्ज उभारण्याचा खर्च, कर्जाचे हप्ते व व्याज (मु.ले.) | B74: XE12Z101 | D74: 70458965 | E74: 60324000 | F74: 280324000 | G74: 195260536 | H74: 351800000
D75: 0 | E75: 0 | F75: 0 | G75: 0 | H75: 0
A76: १. पाणीपुरवठा एकूण बेरीज | D76: 1437953598 | E76: 1489143444 | F76: 1800348722 | G76: 1973848536 | H76: 2323370000
D77: 0 | E77: 0 | F77: 0 | G77: 0 | H77: 0
A78: १अ. पुणे लष्कर व खडकी पाणीपुरवठा | D78: 0 | E78: 0 | F78: 0 | G78: 0 | H78: 0
A79: क१. लष्कर पाणीपुरवठा | D79: 0 | E79: 0 | F79: 0 | G79: 0 | H79: 0
A80: १. कायम सेवकवर्ग वेतन | B80: XE12N101A | D80: 125571755 | E80: 141758453 | F80: 154711302 | G80: 165000000 | H80: 183600000
A81: २. संकीर्ण | B81: XE12N102 | D81: 591350 | E81: 791489 | F81: 661556 | G81: 1080000 | H81: 1200000
A82: ३. पाण्याची किंमत | B82: XE12N103 | D82: 55250000 | E82: 44200000 | F82: 47149281 | G82: 47200000 | H82: 50000000
A83: ४. पाणी शुद्ध करणे, तद्‌नुषंगिक कामे करणे | B83: XE12N104 | D83: 5237396 | E83: 9805000 | F83: 7072354 | G83: 6120000 | H83: 10000000
A84: ५. प्रयोगशाळा सँपल टेस्टींगसाठी होणारा खर्च | B84: XE12N105 | D84: 333940 | E84: 621063 | F84: 401450 | G84: 720000 | H84: 900000
A85: ६. पंपिंग वीज खर्च | B85: XE12N106 | D85: 205299773 | E85: 125601032 | F85: 158844185 | G85: 180000000 | H85: 198500000
A86: ८. कोठी व इतर साहित्य खर्च | B86: XE12N108 | D86: 392453 | E86: 0 | F86: 0 | G86: 360000 | H86: 800000
A87: ९. पंपाचे डिझेल इंजिनसाठी व इतर इंजिनसाठी लागणारे तेल | B87: XE12N109 | D87: 401925 | E87: 0 | F87: 0 | G87: 360000 | H87: 500000
A88: १३. पाणीपुरवठा केंद्र भवनाची देखभाल व दुरुस्ती | B88: XE12N117 | D88: 0 | E88: 0 | F88: 0 | G88: 500000 | H88: 500000
A89: १४. पाणीपुरवठा केंद्राच्या भवनातील दिवाबत्ती (वि.अ.) | B89: XE12N118 | D89: 247504 | E89: 0 | F89: 0 | G89: 0 | H89: 0
A90: १६. पुणे लष्कर पाणीपुरवठा हद्दीतील व्हॉल्व्ह चालू करणे व बंद करणे | B90: XE12N120 | D90: 10664463 | E90: 11465014 | F90: 21309129 | G90: 21600000 | H90: 29500000
A91: १७. टँकरने पाणीपुरवठा करणे | B91: XE12N121 | D91: 9933536 | E91: 15046296 | F91: 23417337 | G91: 14400000 | H91: 19500000
... A96: लष्कर व बंडगार्डन पाणीपुरवठा वितरण विभाग देखभाल दुरूस्ती | B96: XE12N127 | D96: 0 | E96: 0 | F96: 0 | G96: 0 | H96: 19500000
D97: 0 | E97: 0 | F97: 0 | G97: 0 | H97: 0
A98: क१. लष्कर पाणीपुरवठा बेरीज | D98: 429562407 | E98: 373977799 | F98: 463805433 | G98: 465096000 | H98: 585300000
D99: 0 | E99: 0 | F99: 0 | G99: 0 | H99: 0
A100: क२. लष्कर पाणीपुरवठा (विभागीय कार्यालय) | D100: 0 | E100: 0 | F100: 0 | G100: 0 | H100: 0
A101: १. कायम सेवक वर्ग वेतन | B101: XE12N###A | D101: 5515675 | E101: 4824374 | F101: 4378290 | G101: 10000000 | H101: 5600000
D102: 0 | E102: 0 | F102: 0 | G102: 0 | H102: 0
A103: क२. बेरीज | D103: 5515675 | E103: 4824374 | F103: 4378290 | G103: 10000000 | H103: 5600000
D104: 0 | E104: 0 | F104: 0 | G104: 0 | H104: 0
A105: क. एकूण बेरीज | D105: 435078082 | E105: 378802173 | F105: 468183723 | G105: 475096000 | H105: 590900000
D106: 0 | E106: 0 | F106: 0 | G106: 0 | H106: 0
A107: ख१. खडकी व SNDT चतुःश्रृंगी पाणीपुरवठा | D107: 0 | E107: 0 | F107: 0 | G107: 0 | H107: 0
A108: १. कायम सेवकवर्ग वेतन | B108: XE12P101A | D108: 15931207 | E108: 15370386 | F108: 16549329 | G108: 30000000 | H108: 18700000
A109: २. संकीर्ण | B109: XE12P102 | D109: 192046 | E109: 201181 | F109: 299534 | G109: 270000 | H109: 300000
A110: ३. पाण्याची किंमत | B110: XE12P103 | D110: 25500000 | E110: 18780489 | F110: 23791985 | G110: 25000000 | H110: 28000000
A111: ४. पाणी शुद्ध करणे व तद्‌नुषंगिक कामे करणे | B111: XE12P104 | D111: 200894 | E111: 946730 | F111: 0 | G111: 1080000 | H111: 2500000
A112: ६. पंपिंग वीज खर्च | B112: XE12P106 | D112: 6372930 | E112: 31870 | F112: 5999980 | G112: 12500000 | H112: 15000000
A113: १०. कोठी व इतर साहित्य खर्च | B113: XE12P110 | D113: 109176 | E113: 30264 | F113: 242220 | G113: 252000 | H113: 2500000
A114: १७. टाक्‍यांची दुरुस्ती | B114: XE12P119 | D114: 496377 | E114: 879137 | F114: 1003984 | G114: 810000 | H114: 1000000
A115: १८. देखभाल दुरुस्त्या : नळदुरुस्ती व तातडीच्या दुरुस्त्या इत्यादी | B115: XE12P120 | D115: 16862280 | E115: 26192028 | F115: 37704778 | G115: 32300000 | H115: 41500000
A116: १९. व्हॉल्व्ह सोड बंद करणे | B116: XE12P121 | D116: 7312657 | E116: 7047999 | F116: 12690315 | G116: 9000000 | H116: 14500000
A117: २०. टँकरने पाणीपुरवठा करणे | B117: XE12P122 | D117: 3803772 | E117: 11344047 | F117: 24553555 | G117: 16200000 | H117: 22000000
D118: 0 | E118: 0 | F118: 0 | G118: 0 | H118: 0
A119: ख१. बेरीज | D119: 76781339 | E119: 80824131 | F119: 122835680 | G119: 127412000 | H119: 146000000
D120: 0 | E120: 0 | F120: 0 | G120: 0 | H120: 0
A121: ख२. खडकी व SNDT चतुःश्रृंगी पाणीपुरवठा (विभा. कार्या.) | D121: 0 | E121: 0 | F121: 0 | G121: 0 | H121: 0
A122: १. कायम सेवकवर्ग वेतन | B122: XE12P###A | D122: 308548 | E122: 338046 | F122: 0 | G122: 2000000 | H122: 0
D123: 0 | E123: 0 | F123: 0 | G123: 0 | H123: 0
...

Sheet C_Revenue_List
F1: प्रकल्पीय रक्कम | G1: 1819 आयुक्त
A3: पाणीपुरवठा विभागाकडील कामाच्या याद्या
A6: यादी क्र. X2
A7: मलनिःस्सारण विभागाकडील देखभाल दुरूस्तीची कामे
A8: XE23A117/X2-
A10: क्र. | B10: code | C10: ward | E10: कामाचे नाव | F10: प्रकल्पीय रक्कम | G10: तरतूद
A12: 1 | B12: XE23A117/X2-101 | E12: धनकवडी सहकारनगर क्षेत्रिय कार्यालयाच्या अंतर्गत येणा-या ६०० मि. मी. व त्यापुढील व्यासाच्या नाल्यातील व मुख्य रस्त्यावरील मलवाहिन्यांची देखभाल व दुरुस्तीची कामे करणे. | G12: 4500000
A13: 2 | B13: XE23A117/X2-102 | E13: धनकवडी सहकारनगर क्षेत्रिय कार्यालया लगत नव्याने समाविष्ठ ग्रामपंचायत काळातील गावांमधील अस्तित्वातील मैलापाणी वहन व्यवस्था सुधारणे कामी अत्यावश्यक देखभाल व दुरुस्ती तसेच तद्‌नुषंगिक कामे करणे. (आंबेगाव खुर्द / आंबेगाव बु।।.) | G13: 10000000
A14: 3 | B14: XE23A117/X2-103 | E14: वारजे कर्वेनगर क्षेत्रिय कार्यालया लगत नव्याने समाविष्ठ ग्रामपंचायत काळातील गावांमधील अस्तित्वातील मैलापाणी वहन व्यवस्था सुधारणे कामी अत्यावश्यक देखभाल व दुरुस्ती तसेच तद्‌नुषंगिक कामे करणे. (शिवणे / उत्तमनगर) | G14: 5000000
A15: 4 | B15: XE23A117/X2-104 | E15: प्रभाग क्र. ३९ मध्ये धनकवडी गावठाण मधील ग्रामपंचायत काळातील जुन्या व जीर्ण झालेल्या मलवाहिन्या काढून मोठ्या व्यासाच्या मलवाहिन्या विकसीत करणे व देखभाल व दुरुस्तीची कामे करणे व तद्‌नुषंगिक कामे करणे. | G15: 8000000
A16: 5 | B16: XE23A117/X2-105 | E16: प्रभाग क्र. ३८ मध्ये के. के. मार्केट ते लेकटाऊन दरम्यान मुख्य मलवाहिनी टाकणे व दुरुस्ती करणे. | G16: 7000000
A17: 6 | B17: XE23A117/X2-106 | E17: प्रभाग क्र. ४१ मधील भैरोबा नाल्यामधील मुख्य ड्रेनेज लाईन व चेंबर दुरुस्ती विषयक कामे करणे. | G17: 4000000
A18: 7 | B18: XE23A117/X2-107 | E18: कोंढवा येवलेवाडी क्षेत्रिय कार्यालयाच्या अखत्यारीत येणाऱ्या परिसरामधील अस्तित्वातील मलवाहिन्यांची दैनदिन देखभाल दुरुस्ती करणे. | G18: 4000000
A19: 8 | B19: XE23A117/X2-108 | E19: नव्याने मनपा हद्दीमध्ये समाविष्ट झालेल्या कोंढवा येवलेवाडी क्षेत्रिय कार्यालयाच्या अखत्यारीतील ग्रामपंचायत काळामधील अस्तित्वातील मैलापाणी वहन व्यवस्था अबाधित राहणेकरीता मलवाहिन्यांची दैनदिन देखभाल दुरुस्ती करणे. | G19: 6000000
A20: 9 | B20: XE23A117/X2-109 | E20: हडपसर क्षेत्रिय कार्यालयाअंतर्गत येणाऱ्या मुख्य रस्त्यावरील व नाल्यातील ६०० मि. मी. व्यासाच्या मलवाहिन्यांची देखभाल दुरुस्ती करणे. | G20: 5000000
A21: 10 | B21: XE23A117/X2-110 | E21: हडपसर क्षेत्रिय कार्यालयाअंतर्गत येणाऱ्या पुणे मनपाचे हद्दीमध्ये नव्याने समाविष्ट झालेल्या गावांच्या परिसरात अस्तित्वातील मुख्य मलवाहिन्यांची देखभाल दुरुस्ती करणे. | G21: 5000000
A22: 11 | B22: XE23A117/X2-111 | E22: बिबवेवाडी क्षेत्रिय कार्यालयाअंतर्गत येणाऱ्या ६०० मि. मी. व त्यापुढील व्यासाच्या मुख्य रस्त्यावरील व नाल्यातील मुख्य मलवाहिन्यांची देखभाल दुरुस्ती करणे. | G22: 4500000
A23: 12 | B23: XE23A117/X2-112 | E23: कसबा - विश्रामवाडा क्षेत्रिय कार्यालय अंतर्गत येणारे ६०० मि. मी. व त्यापुढील व्यासाच्या मुख्य मलवाहिन्यांची देखभाल व दुरुस्ती करणे. | G23: 4500000
... A48: 37 | B48: XE23A117/X2-137 | E48: मलनि:सारण विभागाकडील प्रशासकीय कार्यालयाकरीता झेरॉक्स मशिन आणि प्रिंटर्सचे ड्रम, टोनर पुरविणे तसेच वार्षिक देखभाल दुरुस्ती व तद्‌नुषंगिक कामे करणे. | G48: 500000
E50: यादी क्र. X2 एकूण | F50: 0 | G50: 168000000

Sheet C_Capital_Expenditure
A1: सन 2018-19 चे योजनांतर्गत | I1: खर्चाबाबतचे अंदाजपत्रक
A2: अनुक्रमांक | B2: मान्यतेचा ठराव क्र. दिनांक (कोड) | C2: प्रभाग क्रमांक | D2: BPL | E2: कामाचे नाव अगर वर्णन | F2: दि. 31 मार्च 2018 अखेरपर्यंत केलेली तरतूद | I2: दि. 31 मार्च 2017 पर्यंतचा खर्चाचा नक्‍की आकडा | J2: 2017-18 मधील खर्चाची अंदाजी रक्कम | L2: 2018-19 साठी अधिक तरतूद | N2: 2018-19 साठी एकूण तरतूद | O2: प्रकल्पीय रक्कम
F3: कर्जातून | G3: महसूल निधीतून | H3: एकूण | J3: प्रत्यक्ष उपलब्ध तरतूद | K3: कर्जातून तरतूद | L3: कर्जातून | M3: महसूल निधी व इतर निधी
E8: 1. पाणीपुरवठा | F8: 0 | G8: 0 | H8: 0 | I8: 0 | J8: 0 | M8: 0 | N8: 0
F9: 0 | G9: 0 | H9: 0 | I9: 0 | J9: 0 | M9: 0 | N9: 0
A10: 2 | B10: ZE16A103# | C10: P1- | D10: _ | E10: शहरामध्ये जलशुध्दीकरण केंद्रे बांधणे | F10: 0 | G10: 0 | H10: 0 | I10: 0 | J10: 0 | M10: 32500000 | N10: 32500000
A11: 1 | B11: ZE16A104# | C11: P2- | D11: _ | E11: शहरामध्ये पाण्याच्या नवीन लाईन विकसित करणे | F11: 0 | G11: 6484371460 | H11: 6484371460 | I11: 5119012214 | J11: 1365359246 | M11: 211000000 | N11: 211000000
A12: 2 | B12: ZE16A106# | C12: P3- | D12: _ | E12: शहरामध्ये पाण्याच्या टाक्या बांधणे / बोअरवेल घेणे | F12: 0 | G12: 578881020 | H12: 578881020 | I12: 204561005 | J12: 374320015 | M12: 84200000 | N12: 84200000
A13: 3 | B13: ZE16A107# | C13: P8- | D13: _ | E13: शहरामधील विविध जलशुध्दीकरण केंद्रामध्ये विद्युत / यांत्रिकीविषयक कामे करणे | F13: 0 | G13: 523169558 | H13: 523169558 | I13: 365174123 | J13: 157995435 | M13: 445400000 | N13: 445400000
A14: 5 | B14: #+ | E14: सन २०१४-१५ मधील अपूर्ण कामांसाठी सन २०१५-१६ मध्ये उपलब्ध केलेली तरतूद | F14: 0 | G14: 1365768924 | H14: 1365768924 | I14: 1365768924 | J14: 0 | M14: 0 | N14: 0
F15: 0 | G15: 0 | H15: 0 | I15: 0 | J15: 0 | M15: 0 | N15: 0
E16: पाणीपुरवठा एकूण | F16: 0 | G16: 8952190962 | H16: 8952190962 | I16: 7054516266 | J16: 1897674696 | M16: 773100000 | N16: 773100000
F17: 0 | G17: 0 | H17: 0 | I17: 0 | J17: 0 | M17: 0 | N17: 0
F18: 0 | G18: 0 | H18: 0 | I18: 0 | J18: 0 | M18: 0 | N18: 0
E19: 2. मलनिःसारण | F19: 0 | G19: 0 | H19: 0 | I19: 0 | J19: 0 | M19: 0 | N19: 0
F20: 0 | G20: 0 | H20: 0 | I20: 0 | J20: 0 | M20: 0 | N20: 0
A21: 1 | B21: ZE16B102# | C21: D2- | D21: _ | E21: शहरामध्ये मलवाहिन्या विकसित करणे | F21: 0 | G21: 5229133792 | H21: 5229133792 | I21: 3894301064 | J21: 1334832728 | M21: 173000000 | N21: 173000000
A22: 2 | B22: ZE16B103# | C22: D3- | D22: _ | E22: शहरामध्ये नाला चॅनलायझेशन करणे / नाल्याला सिमाभिंत बांधणे व तद्नुषंगिक कामे करणे | F22: 0 | G22: 262385423 | H22: 262385423 | I22: 48694838 | J22: 213690585 | M22: 65200000 | N22: 65200000
A23: 3 | B23: ZE16B104# | E23: शहरामध्ये मैलापाणी शुध्दीकरण केंद्रामध्ये स्थापत्यविषयक कामे करणे | F23: 0 | G23: 41102691 | H23: 41102691 | I23: 38592666 | J23: 2510025 | M23: 0 | N23: 0
A24: 4 | B24: ZE16B105# | C24: D5- | D24: _ | E24: शहरामध्ये मैलापाणी शुध्दीकरण केंद्रामध्ये विद्युत / यांत्रिकीविषयक कामे करणे | F24: 0 | G24: 78080800 | H24: 78080800 | I24: 31415131 | J24: 46665669 | M24: 25000000 | N24: 25000000
A25: 6 | B25: #+ | E25: सन २०१४-१५ मधील अपूर्ण कामांसाठी सन २०१५-१६ मध्ये उपलब्ध केलेली तरतूद | F25: 0 | G25: 12417042 | H25: 12417042 | I25: 12417042 | J25: 0 | M25: 0 | N25: 0
F26: 0 | G26: 0 | H26: 0 | I26: 0 | J26: 0 | M26: 0 | N26: 0
E27: मलनिःसारण एकूण | F27: 0 | G27: 5623119748 | H27: 5623119748 | I27: 4025420741 | J27: 1597699007 | M27: 263200000 | N27: 263200000
F28: 0 | G28: 0 | H28: 0 | I28: 0 | J28: 0 | M28: 0 | N28: 0
E29: 3. पाणीपुरवठा प्रकल्प | F29: 0 | G29: 0 | H29: 0 | I29: 0 | J29: 0 | M29: 0 | N29: 0
F30: 0 | G30: 0 | H30: 0 | I30: 0 | J30: 0 | M30: 0 | N30: 0
A31: 1 | B31: ZE16C101# | C31: PR1- | E31: शहरामध्ये पाणीपुरवठा प्रकल्प अंतर्गत कामे करणे | F31: 0 | G31: 5742363009 | H31: 5742363009 | I31: 4467048116 | J31: 1275314893 | M31: 51500000 | N31: 51500000
A32: 2 | B32: ZE16C102# | C32: PR2- | E32: राष्ट्रीय नदी सुधारणा योजना (जायका) | F32: 0 | G32: 2173500000 | H32: 2173500000 | I32: 50762847 | J32: 2122737153 | M32: 750000000 | N32: 750000000
A33: 3 | B33: ZE16C103# | C33: PR3- | E33: पुणे शहरात तंत्रशुध्द पध्दतीने पाणीपुरवठा करण्याची योजना (24x7) | F33: 0 | G33: 5403653500 | H33: 5403653500 | I33: 233040090 | J33: 5170613410 | M33: 3350000000 | N33: 3350000000
B34: #+ | E34: सन २०१४-१५ मधील अपूर्ण कामांसाठी सन २०१५-१६ मध्ये उपलब्ध केलेली तरतूद | F34: 0 | G34: 184537846 | H34: 184537846 | I34: 184537846 | J34: 0 | M34: 0 | N34: 0
F35: 0 | G35: 0 | H35: 0 | I35: 0 | J35: 0 | M35: 0 | N35: 0
E36: पाणीपुरवठा प्रकल्प एकूण | F36: 0 | G36: 13504054355 | H36: 13504054355 | I36: 4935388899 | J36: 8568665456 | M36: 4151500000 | N36: 4151500000
F37: 0 | G37: 0 | H37: 0 | I37: 0 | J37: 0 | M37: 0 | N37: 0
E38: 4. मलनिःसारण प्रकल्प | F38: 0 | G38: 0 | H38: 0 | I38: 0 | J38: 0 | M38: 0 | N38: 0
F39: 0 | G39: 0 | H39: 0 | I39: 0 | J39: 0 | M39: 0 | N39: 0
A40: 1 | B40: ZE16D101# | E40: मलनिःसारण प्रकल्प टप्पा क्र. १ | F40: 0 | G40: 3312765570 | H40: 3312765570 | I40: 3312765570 | J40: 0 | M40: 0 | N40: 0
A41: 2 | B41: ZE16D102# | C41: MP2- | E41: शहरामध्ये मोठ्या व्यासाच्या मलवाहिन्या विकसित करणे | F41: 0 | G41: 678797496 | H41: 678797496 | I41: 168975023 | J41: 509822473 | M41: 473400000 | N41: 473400000
A42: 1 | B42: ZE16D103# | C42: MP3- | E42: शहरामध्ये मैलापाणी शुध्दीकरण केंद्र उभारणे / पंपिंग स्टेशन उभारणे | F42: 0 | G42: 0 | H42: 0 | I42: 0 | J42: 0 | M42: 45000000 | N42: 45000000
A43: 4 | B43: #+ | E43: सन २०१४-१५ मधील अपूर्ण कामांसाठी सन २०१५-१६ मध्ये उपलब्ध केलेली तरतूद | F43: 0 | G43: 199400443 | H43: 199400443 | I43: 199400443 | J43: 0 | M43: 0 | N43: 0
F44: 0 | G44: 0 | H44: 0 | I44: 0 | J44: 0 | M44: 0 | N44: 0
E45: मलनिःसारण प्रकल्प एकूण | F45: 0 | G45: 4190963509 | H45: 4190963509 | I45: 3681141036 | J45: 509822473 | M45: 518400000 | N45: 518400000
F46: 0 | G46: 0 | H46: 0 | I46: 0 | J46: 0 | M46: 0 | N46: 0
E47: क्षेत्रिय कार्यालयाने करावयाची कामे :- | F47: 0 | G47: 0 | H47: 0 | I47: 0 | J47: 0 | M47: 0 | N47: 0
F48: 0 | G48: 0 | H48: 0 | I48: 0 | J48: 0 | M48: 0 | N48: 0
A49: • | B49: ZE16A115# | C49: W6 | E49: क्षेत्रिय कार्यालय : पाणीपुरवठा विभागाने करावयाची कामे | F49: 0 | G49: 111521801 | H49: 111521801 | I49: 111492587 | J49: 29214 | M49: 0 | N49: 0
A50: • | B50: ZE16A117# | C50: C6 | E50: क्षेत्रिय कार्यालय : नागरिकांच्या सहभाग योजनेतून पाणीपुरवठा विभागाने करावयाची कामे | F50: 0 | G50: 56909307 | H50: 56909307 | I50: 53875469 | J50: 3033838 | M50: 3000000 | N50: 3000000
F51: 0 | G51: 0 | H51: 0 | I51: 0 | J51: 0 | M51: 0 | N51: 0
A52: • | B52: ZE16B113# | C52: W7 | E52: क्षेत्रिय कार्यालय : मलनिःसारण विभागाने करावयाची कामे | F52: 0 | G52: 405876369 | H52: 405876369 | I52: 395592881 | J52: 10283488 | M52: 18500000 | N52: 18500000
A53: • | B53: ZE16B130# | C53: C7 | E53: क्षेत्रिय कार्यालय : नागरिकांच्या सहभाग योजनेतून मलनिःसारण विभागाने करावयाची कामे | F53: 0 | G53: 150974128 | H53: 150974128 | I53: 142201225 | J53: 8772903 | M53: 13500000 | N53: 13500000
F54: 0 | G54: 0 | H54: 0 | I54: 0 | J54: 0 | M54: 0 | N54: 0
E55: क्षेत्रिय कार्यालयाने करावयाची कामे एकूण बेरीज | F55: 0 | G55: 725281605 | H55: 725281605 | I55: 703162162 | J55: 22119443 | M55: 35000000 | N55: 35000000
A57: • | B57: • | C57: • | D57: • | E57: 1. पाणीपुरवठा | F57: 0 | G57: 8952190962 | H57: 8952190962 | I57: 7054516266 | J57: 1897674696 | K57: 0 | L57: 0 | M57: 773100000 | N57: 773100000 | O57: 0
A58: • | B58: • | C58: • | D58: • | E58: क्षेत्रिय कार्यालय : पाणीपुरवठा विभागाने करावयाची कामे | F58: 0 | G58: 168431108 | H58: 168431108 | I58: 165368056 | J58: 3063052 | K58: 0 | L58: 0 | M58: 3000000 | N58: 3000000 | O58: 0
A59: • | B59: ZE16A | C59: XE12X101 | E59: पाणीपुरवठा एकूण | F59: 0 | G59: 9120622070 | H59: 9120622070 | I59: 7219884322 | J59: 1900737748 | K59: 0 | L59: 0 | M59: 776100000 | N59: 776100000 | O59: 0
A60: • | B60: • | C60: • | D60: •
A61: • | B61: • | C61: • | D61: • | E61: 2. मलनिःसारण | F61: 0 | G61: 5623119748 | H61: 5623119748 | I61: 4025420741 | J61: 1597699007 | K61: 0 | L61: 0 | M61: 263200000 | N61: 263200000 | O61: 0
A62: • | B62: • | C62: • | D62: • | E62: क्षेत्रिय कार्यालय : मलनिःसारण विभागाने करावयाची कामे | F62: 0 | G62: 556850497 | H62: 556850497 | I62: 537794106 | J62: 19056391 | K62: 0 | L62: 0 | M62: 32000000 | N62: 32000000 | O62: 0
A63: • | B63: ZE16B | C63: XE23X101 | E63: मलनिःसारण एकूण | F63: 0 | G63: 6179970245 | H63: 6179970245 | I63: 4563214847 | J63: 1616755398 | K63: 0 | L63: 0 | M63: 295200000 | N63: 295200000 | O63: 0
A64: • | B64: • | C64: • | D64: •
A65: • | B65: ZE16C | C65: XE41X101 | E65: पाणीपुरवठा प्रकल्प एकूण | F65: 0 | G65: 13504054355 | H65: 13504054355 | I65: 4935388899 | J65: 8568665456 | K65: 0 | L65: 0 | M65: 4151500000 | N65: 4151500000 | O65: 0
A66: • | B66: ZE16D | C66: XE41X102 | E66: मलनिःसारण प्रकल्प एकूण | F66: 0 | G66: 4190963509 | H66: 4190963509 | I66: 3681141036 | J66: 509822473 | K66: 0 | L66: 0 | M66: 518400000 | N66: 518400000 | O66: 0
A67: • | B67: • | C67: • | D67: •
A68: • | B68: ZE Total | C68: • | D68: • | E68: पाणीपुरवठा + मलनिःसारण + पाणीपुरवठा प्रकल्प + मलनिःसारण प्रकल्प : एकूण बेरीज | F68: 0 | G68: 32995610179 | H68: 32995610179 | I68: 20399629104 | J68: 12595981075 | K68: 0 | L68: 0 | M68: 5741200000 | N68: 5741200000 | O68: 0

Sheet C_Capital_List
F1: प्रकल्पीय रक्कम | G1: 1819 आयुक्त
A2: पाणीपुरवठा विभागाकडील कामाच्या याद्या
A5: यादी क्र. P1
A6: शहरामध्ये जलशुध्दीकरण केंद्रे बांधणे
A7: ZE16A103/P1-
A9: क्र. | B9: code | C9: ward | E9: कामाचे नाव | F9: प्रकल्पीय रक्कम | G9: तरतूद
A11: 1 | B11: ZE16A103/P1-11 | E11: शिवणे व उत्तमनगर पाणीपुरवठ्यासाठी वाढीव 5 एम.एल.डी.जलशुद्धीकरण केंद्र बांधणे व नलिका टाकणे | F11: 0 | G11: 15000000
A12: 2 | B12: ZE16A103/P1-12 | E12: एम.जे.पी.कडून कोंढवे धावडे येथिल जलशुद्धीकरण प्रकल्प ताब्यात घेणे | G12: 17500000
E14: यादी क्र. P1 एकूण | F14: 0 | G14: 32500000
A16: यादी क्र. P2
A17: शहरामध्ये पाण्याच्या नवीन लाईन विकसित करणे
A18: ZE16A104/P2-
A20: क्र. | B20: code | C20: ward | E20: कामाचे नाव | F20: प्रकल्पीय रक्कम | G20: तरतूद
A22: 1 | B22: ZE16A104/P2-51 | E22: ग्रामपंचायत आंबेगाव बुद्रुक कमान ते मारुती मंदिर, मेन चौक १२" पाण्याची लाईन टाकणे | G22: 2500000
A23: 2 | B23: ZE16A104/P2-52 | E23: अभिनव कॉलेज ते श्रीराम निवास ८" व ६" पाण्याची लाईन टाकणे | G23: 2000000
A24: 3 | B24: ZE16A104/P2-53 | E24: NH 4 सर्व्हिस रोड ते आंबेगाव बुद्रुक पाण्याची टाकी १२" पाण्याची लाईन टाकणे | G24: 1000000
A25: 4 | B25: ZE16A104/P2-54 | E25: शिलाई वर्ल्ड शॉप ते गणपत सदन १२" पाण्याची लाईन टाकणे | G25: 2000000
A26: 5 | B26: ZE16A104/P2-55 | E26: गणपत सदन ते जिल्हा परिषद शाळा १२" पाण्याची लाईन टाकणे | G26: 1000000
A27: 6 | B27: ZE16A104/P2-56 | E27: राम मंदिर ते शिव गोरक्ष दर्शन १२" पाण्याची लाईन टाकणे | G27: 2000000
A28: 7 | B28: ZE16A104/P2-57 | E28: शिव गोरक्ष दर्शन ते गणराज हाईट्स ८" व ६" पाण्याची लाईन टाकणे | G28: 1000000
A29: 8 | B29: ZE16A104/P2-58 | E29: शिव गोरक्ष दर्शन ते मारुती ८" पाण्याची लाईन टाकणे | G29: 1000000
A30: 9 | B30: ZE16A104/P2-59 | E30: मारुती मंदिर ते गायमुख ८" पाण्याची लाईन टाकणे | G30: 2000000
A31: 10 | B31: ZE16A104/P2-60 | E31: श्रीराम नागरी ते हिल व्ह्यू ६" व ४" पाण्याची लाईन टाकणे | G31: 1500000
A32: 11 | B32: ZE16A104/P2-61 | E32: भारतनगर , दत्तनगर, गुजरवाडी रोड अंतर्गत गल्ल्यांमध्ये पाण्याची लार्इन टाकणे. | G32: 2000000
A33: 12 | B33: ZE16A104/P2-62 | E33: व्ही. आय. टी. चौक ते राजीव गांधीनगर 12 इंची व्यासाची जलवाहिनी मुख्य रस्त्याने विकसित करणे. | G33: 2000000
... A48: 27 | B48: ZE16A104/P2-77 | E48: स्वारगेट वरुन येणारी २७इंची मोठया व्यासाची लाईन क्‍वार्टरगेट चौकापर्यंत टाकणे | G48: 5000000
E50: सन 2017-18 मधील अपूर्ण कामांसाठी सन 2018-19 मध्ये उपलब्ध केलेली तरतूद
A51: 28 | B51: ZE16A104/P2-2 | E51: एस.एन.डी.टी. एच.एल.आर. ते चतुःश्रृंगी टाकी दरम्यान एम.एस. नलिका टाकणे या कामातील उर्वरित कामे करणे | F51: 46100000 | G51: 10000000
A52: 29 | B52: ZE16A104/P2-3 | E52: प्रसार भारती ते चैतन्य हेल्थ क्लबपर्यंत ८००मि.मी.पोलादी जलवाहिनी टाकणे | F52: 10000000 | G52: 3000000
A53: 30 | B53: ZE16A104/SP2-21 | E53: प्र.क्र.९ अ मध्ये भारतीय अनुसंधान केंद्र कृषी विभाग ते लक्ष्मण पार्क पर्यंत पाणी लाईन टाकणे. | F53: 10000000 | G53: 3000000
A54: 31 | B54: ZE16A104/SP2-325 | E54: प्रभाग क्र. ७३ अ मध्ये अहिल्यादेवी चौक ते खुशबू हॉटेल जलवाहिनी टाकणे | F54: 7000000 | G54: 1000000
A55: 32 | B55: ZE16A104A/P2-1355+ | E55: चतुःश्रृंगी पाणी पुरवठा विभागाअंतर्गतची मागील बिले अदा करणे (कॉमन) | F55: 5000000 | G55: 8000000
A56: 33 | B56: ZE16A104A/P2-312+ | E56: लष्कर जलकेद्र वितरण व्यवस्थे मागिल बिले देण्यासाठी आवश्यक तरतुद | F56: 10000000 | G56: 5000000
A57: 34 | B57: ZE16A104A/P2-648+ | E57: बालेवाडी गांवठाण येथे संपवेल बांधणे. | F57: 7200000 | G57: 3500000
A58: 35 | B58: ZE16A104A/P2-742+ | E58: एलएलआर टाकी ते निलायम चित्रपटगृह दरम्यान १२०० मि.मी. व्यासाची एम.एस. लाईन टाकणे व फलो मीटर बसविणे, एलएलआर टाकीच्या कार्यकक्षेत फलो मीटर व कंट्रोल व्हॉल्व्ह बसविणे | G58: 5000000
A59: 36 | B59: ZE16A104A/S5-1175+ | E59: प्र.क्र.९ मधील नवीन विकसित भागात ४ इंची, ६ इंची, ८ इंची जलवाहिनी टाकणे. | F59: 40000000 | G59: 2000000
A60: 37 | B60: ZE16A104A/S5-35+ | E60: प्र.क्र.९ मध्ये पाषाणकर गॅरेज खिंड ते जकात नाका बालेवाडी मुख्य जलवाहिनी टाकणे. | F60: 10000000 | G60: 5000000
A61: 38 | B61: ZE16C101/PR1-539+ | E61: वडगाव स.नं. ४५ इन्स्टिटयुट इ.एस.आर.पासुन वडगाव झोनकरीता वितरण व्यवस्था करणे. | F61: 7000000 | G61: 5000000
A62: 39 | B62: ZE16C101/PR1-623+ | E62: बाणेर बालेवाडी भागातील जलवितरण व्यवस्था तयार करणे. | F62: 44000000 | G62: 3000000
A63: 40 | B63: ZE16C101/PR1-624+ | E63: सुस व बाणेर टाकीपासून जलवितरण व्यवस्था तयार करणे. | F63: 51700000 | G63: 3000000
A64: 41 | B64: ZE16C101/PR1-625+ | E64: एस.एन.डी.टी. एच.एल.आर. ते चतुःश्रृंगी टाकी दरम्यान एम.एस. नलिका टाकणे | G64: 5000000
A65: 42 | B65: ZE16C101/PR1-756+ | E65: एस.एन.डी.टी. कॉलेज त रेक्सॉन कंपनी दरम्यानची १२०० मि.मी.व्यासाची जुनी प्रिस्ट्रेडलाईन बदलून नविन एम.एस.लाईन टाकणे | F65: 20000000 | G65: 8000000
A66: 43 | B66: ZE16A104/P2-111+ | E66: स्वारगेट पाणीपुरवठा विभागा अंतर्गतची मागील बिले अदा करणे (कॉमन) | G66: 5000000
A67: 44 | B67: ZE16A104/SP2-632 | E67: प्रभाग क्र.7 ड मध्ये विविध ठिकाणी पाण्याची लाईन टाकणे | G67: 1000000
A68: 45 | B68: ZE16A104/SP2-641 | E68: प्रभाग क्र.8 ब औंध येथील संघवी नगर येथे 8 इंची पाण्याची लाईन टाकणे | G68: 500000
A69: 46 | B69: ZE16A104/SP2-642 | E69: प्रभाग क्र.8 ब औंध येथील सर्जा हॉटेल ते परिहार चौक 6 इंची पाण्याची लाईन टाकणे | G69: 500000
A70: 47 | B70: ZE16A104/SP2-656 | E70: प्रभाग क्र.9 अ मध्ये पाणीपुरवठा विषयक कामे करणे | G70: 500000
A71: 48 | B71: ZE16A104/SP2-660 | E71: प्रभाग क्र.9 ब नवीन बाणेर पाषाण लिंक रोड 120 फुटी कुमार शांतीनिकेतन परिसरात नवीन मोठी पाण्याची पाईपलाईन टाकणे | G71: 4000000
A72: 49 | B72: ZE16A104/SP2-661 | E72: प्रभाग क्र.9 ब बाणेर पाषाण लिंक रोड 120 फुटी कुमार शांतीनिकेतन परिसरात नवीन मोठी पाण्याची पाईपलाईन टाकणे. | G72: 500000
A73: 50 | B73: ZE16A104/SP2-662 | E73: प्रभाग क्र.9 क बालेवाडी शिवनेरी पार्क येथे 12 इंची,6 इंची डी आय पाईप लाईन टाकणे | G73: 500000
A74: 51 | B74: ZE16A104/SP2-664 | E74: प्रभाग क्र.9 क बाणेर गावठाण परिसरात पाण्याची लाईन टाकणे | G74: 500000
A75: 52 | B75: ZE16A104/SP2-665 | E75: प्रभाग क्र.9 क बालेवाडी गावठाण परिसरात पाण्याची लाईन टाकणे | G75: 500000
A76: 53 | B76: ZE16A104/SP2-666 | E76: प्रभाग क्र.9 क बाणेर स.नं.32,33 येथे जलवाहिनी विकसित करणे | G76: 500000
A77: 54 | B77: ZE16A104/SP2-670 | E77: प्रभाग क्र.9 क बालेवाडी फाटा ते लक्ष्मीमाता मंदिरापर्यत मुख्य जलवाहिनी विकसित करणे | G77: 3000000
... A118: 95 | B118: ZE16A104/SP2-1131 | E118: प्रभाग क्र. 40ड, अंजलीनगर परिसरात जय मल्हार मंदिर परिसरात पाण्याची लाईन टाकणे | G118: 500000
E120: यादी क्र. P2 एकूण | F120: 268000000 | G120: 211000000
A123: यादी क्र. P3
A124: शहरामध्ये पाण्याच्या टाक्या बांधणे / बोअरवेल घेणे
A125: ZE16A106/P3-
A127: क्र. | B127: code | C127: ward | E127: कामाचे नाव | F127: प्रकल्पीय रक्कम | G127: तरतूद
A129: 1 | B129: ZE16A106/P3-2 | E129: भामा आसखेड प्रकल्प अंतर्गत कुरूळी ग्रामपंचायत येथे आर.सी.सी पाण्याची टाकी बांधणे तसेच मौजे वाकी तर्फे वाडा येथे काँक्रिटी रस्ता करणे , सौर दिप बसविणे व विविध विकास कामे करणे | F129: 28000000 | G129: 3200000
E131: सन 2017-18 मधील अपूर्ण कामांसाठी सन 2018-19 मध्ये उपलब्ध केलेली तरतूद
A132: 2 | B132: ZE16A104A/P2-1227+ | E132: प्रभाग क्र. ६३ शिवनेरीनगर येथे टाकी बांधणे व तद्‌नुषिगक कामे करणे | F132: 20000000 | G132: 8000000
A133: 3 | B133: ZE16A104A/P2-1243+ | E133: प्र.क्र.४५ हडपसर स.नं.५३/९+९ब+१० सलेन पार्क येथे २५००लाख लि.क्षमतेची टाकी बांधणे | F133: 55000000 | G133: 8000000
A134: 4 | B134: ZE16A104A/P2-142+ | E134: चतुःश्रृंगी टाकी येथे नविन टाकी बांधणे | F134: 80000000 | G134: 8000000
A135: 5 | B135: ZE16A104A/P2-339+ | E135: प्र.क्र.४मध्ये म्हाडा हौसींग बोर्ड येथील स.नं.१९१अ येरवडा, संपवेल शेजारील मोकळया जागेत पाण्याची टाकी बांधणे | F135: 60000000 | G135: 8000000
A136: 6 | B136: ZE16A104A/P2-632+ | E136: रामटेकडी येथे ६० लक्ष लिटर्स क्षमतेची पाणी साठवण टाकी बांधणे. | F136: 50000000 | G136: 8000000
A137: 7 | B137: ZE16A104A/S5-1638+ | E137: प्र.क्र. ११ ब मॅफको पाण्याची टाकी दुरुस्ती करणे | F137: 56000000 | G137: 7000000
A138: 8 | B138: ZE16A104A/S5-1640+ | E138: प्रभाग क्र. ११ ब आशानगर येथे पाण्याची टाकी बांधणे. | F138: 44100000 | G138: 17000000
A139: 9 | B139: ZE16C101/PR1-758+ | E139: पाषाण जलकेंद्र येथे पाण्याची टाकी बांधणे | F139: 50000000 | G139: 17000000
E141: यादी क्र. P3 एकूण | F141: 673400000 | G141: 84200000
A144: यादी क्र. P8
A145: शहरामधील विविध जलशुध्दीकरण केंद्रामध्ये विद्युत / यांत्रिकीविषयक कामे करणे
A146: ZE16A107/P8-
A148: क्र. | B148: code | C148: ward | E148: कामाचे नाव | F148: प्रकल्पीय रक्कम | G148: तरतूद
A150: 1 | B150: ZE16A107/P8-101 | E150: लष्कर जलकेंद्र अंतर्गत नव्याने समाविष्ठ झालेली मुंढवा (उर्वरीत केशवनगर), हडपसर (संपुर्ण साडेसतरा नळी), उंड्री, लोहगाव पंपींग यंत्रणेची देखभाल दुरूस्ती करणे. | G150: 4000000
A151: 2 | B151: ZE16A107/P8-102 | E151: फुरसुंगी उपसागृहोकरीता फ्लोमीटर पुरविणे व बसविणे. | G151: 4000000
A152: 3 | B152: ZE16A107/P8-103 | E152: इंदिरानगर पंपिंग स्टेशन येथे सॉफ्ट स्टार्टर पुरविणे, बसविणे व विदयुत विषयक कामे करणे. | G152: 1000000
A153: 4 | B153: ZE16A107/P8-104 | E153: पद्‌मावती पंपिंग स्टेशन येथे पंपासाठी आवश्यक स्पेअर्स पुरविणे, बसविणे व तद्‌नुषंगिक कामे करणे. | G153: 1500000
A154: 5 | B154: ZE16A107/P8-105 | E154: पद्‌मावती पंपिंग स्टेशन व इंदिरानगर पंपिंग स्टेशन येथे सी.सी.टि.व्ही. यंत्रणा पुरविणे, बसविणे व चालू करुन देणे . | G154: 1000000
A155: 6 | B155: ZE16A107/P8-106 | E155: पर्वती रॉ वॉटर पंपिंग स्टेशन येथे सी.सी.टि.व्ही. यंत्रणा पुरविणे, बसविणे व चालू करुन देणे | G155: 1000000
A156: 7 | B156: ZE16A107/P8-107 | E156: इंदिरानगर पंपिंग स्टेशन येथील खराब झालेल्या पंपाच्या सक्शन/डिलीव्हरी एम.एस. लाईनस्‌ बदलणे, स्थापत्य विषयक व तदनुषंगिक दुरुस्ती कामे करणे. | G156: 1000000
A157: 8 | B157: ZE16A107/P8-108 | E157: पर्वती जलकेंद्र येथील केमिकल हाऊससाठी निर्गमनासाठी स्वतंत्र जिना (FRP मटेरियलमध्ये) पुरविणे व बसविणे. | G157: 1000000
A158: 9 | B158: ZE16A107/P8-109 | E158: पर्वती जलकेंद्र येथील स्टिलिंग चेंबर, क्लेरिफायर व इतर आवश्यक ठिकाणी लोखंडी रेलिंग पुरविणे व बसविणे. | G158: 1000000
A159: 10 | B159: ZE16A107/P8-110 | E159: पर्वती जलकेंद्र येथील स्टिलिंग चेंबरवरील प्लॅटफॉर्म व क्लेरिफायरच्या प्लेटस्‌ ऋठझ मटेरियलमध्ये पुरविणे व बसविणे व तदनुषंगिक कामे करणे. | G159: 1000000
A160: 11 | B160: ZE16A107/P8-111 | E160: पर्वती जलकेंद्र येथील केमिकल टाक्यांसाठी ऋठझ जिने व प्लॅट फॉर्म पुरविणे व बसविणे. | G160: 1000000
A161: 12 | B161: ZE16A107/P8-112 | E161: पर्वती जलकेंद्र येथे क्लोरीन गॅस लीक डिटेक्टर व ब्रिदींग अपरेटस पुरविणे व बसविणे. | G161: 1000000
... A271: 122 | B271: ZE16A107/P8-222 | E271: लष्कर पाणीपुरवठा विभागाच्या अखत्यारीत असणाऱ्या पाण्याच्या टाकीकरीता लेव्हल इंडीक्टेर/ ट्रान्समीटर बसविणे | G271: 1000000
E273: सन 2017-18 मधील अपूर्ण कामांसाठी सन 2018-19 मध्ये उपलब्ध केलेली तरतूद
E274: फिल्टर व केमिकल टाकया येथील विविध कामे करणे
A275: 123 | B275: ZE16A107/P8-34 | E275: इ) पर्वती जलकेंद्र येथील स्टेज १ व स्टेज २ येथील इनटेक गेट पुरविणे, बदलणे व तद्‌नुषंगिक मेकॅनिकल व सिव्हील विषयक कामे करणे. | G275: 2500000
A276: 124 | B276: ZE16A107/P8-37 | E276: ऐ) पर्वती जलकेंद्र येथील फिल्टर बेडमधील वाळू बदलणे, व्ही.वायर पध्दतीने अंडर ड्रेन सिस्टीम बसविणे वतद्‌नुषंगिक कामे करणे. | G276: 1000000
E278: यादी क्र. P8 एकूण | F278: 0 | G278: 445400000
A281: पाणीपुरवठा प्रकल्प टप्पा क्र. १ - प्रकल्पांतर्गत कामे
A284: यादी क्र. PR1
A285: शहरामध्ये पाणीपुरवठा प्रकल्प अंतर्गत कामे करणे
A286: ZE16C101/PR1-
A288: क्र. | B288: code | C288: ward | E288: कामाचे नाव | F288: प्रकल्पीय रक्कम | G288: तरतूद
E290: सन 2017-18 मधील अपूर्ण कामांसाठी सन 2018-19 मध्ये उपलब्ध केलेली तरतूद
A291: 1 | B291: ZE16A103/P1-125+ | E291: पर्वती जलकेद्र येथे नवीन ५०० एमएल डी क्षमतेचे जलशुध्दी करण केंद्र बांधणे. | F291: 20000000 | G291: 20000000
...

Sheet WO_Work18
A1: उप आयुक्त विभाग क्र. : | B1: 1 | C1: 1 | D1: 1 | E1: 2 | F1: 2 | G1: 2 | H1: 3 | I1: 3 | J1: 3 | K1: 4 | L1: 4 | M1: 4 | N1: 5 | O1: 5 | P1: 5
A2: विवरण | B2: नगररोड - वडगावशेरी | C2: येरवडा - कळस - धानोरी | D2: ढोलेपाटील | E2: औंध - बाणेर | F2: शिवाजीनगर - घोले रोड | G2: कोथरूड - बावधन | H2: धनकवडी - सहकारनगर | I2: सिंहगड रोड | J2: वारजे - कर्वेनगर | K2: हडपसर - मुंढवा | L2: वानवडी - रामटेकडी | M2: कोंढवा - येवलेवाडी | N2: कसबा - विश्रामबागवाडा | O2: भवानी पेठ | P2: बिबवेवाडी | Q2: एकूण
A4: अंदाजपत्रकातील तरतुदींचा विभागवार वाटप तक्ता - अंदाजपत्रक 'अ'
A6: १. मुख्य देखरेख वसुली
A7: र. विभागीय कार्यालये | B7: RE11W111A | C7: RE11W114A | D7: RE11W110A | E7: RE11W112A | F7: RE11W103A | G7: RE11W104A | H7: RE11W115A | I7: RE11W105A | J7: RE11W113A | K7: RE11W109A | L7: RE11W116A | M7: RE11W106A | N7: RE11W102A | O7: RE11W108A | P7: RE11W107A
A8: ३. क्षेत्रीय कार्यालये कायम सेवकवर्ग वेतन | B8: 42500000 | C8: 14800000 | D8: 20400000 | E8: 27500000 | F8: 15000000 | G8: 15500000 | H8: 23000000 | I8: 31000000 | J8: 29000000 | K8: 22000000 | L8: 23500000 | M8: 23000000 | N8: 25000000 | O8: 28000000 | P8: 14800000 | Q8: 355000000
B9: RE11W111B | C9: RE11W114B | D9: RE11W110B | E9: RE11W112B | F9: RE11W103B | G9: RE11W104B | H9: RE11W115B | I9: RE11W105B | J9: RE11W113B | K9: RE11W109B | L9: RE11W116B | M9: RE11W106B | N9: RE11W102B | O9: RE11W108B | P9: RE11W107B
A10: ४. क्षेत्रीय कार्यालये संकीर्ण | B10: 490000 | C10: 420000 | D10: 420000 | E10: 1008000 | F10: 700000 | G10: 454000 | H10: 560000 | I10: 420000 | J10: 602000 | K10: 700000 | L10: 435000 | M10: 700000 | N10: 490000 | O10: 700000 | P10: 438000 | Q10: 8537000
B11: RE11W111E | C11: RE11W114E | D11: RE11W110E | E11: RE11W112E | F11: RE11W103E | G11: RE11W104E | H11: RE11W115E | I11: RE11W105E | J11: RE11W113E | K11: RE11W109E | L11: RE11W116E | M11: RE11W106E | N11: RE11W102E | O11: RE11W108E | P11: RE11W107E
A12: ५. प्रभाग समिती चहापान खर्च | B12: 28000 | C12: 25000 | D12: 35000 | E12: 50000 | F12: 35000 | G12: 30000 | H12: 42000 | I12: 53000 | J12: 35000 | K12: 35000 | L12: 29000 | M12: 35000 | N12: 350000 | O12: 42000 | P12: 35000 | Q12: 859000
B13: RE11W111G | C13: RE11W114G | D13: RE11W110G | E13: RE11W112G | F13: RE11W103G | G13: RE11W104G | H13: RE11W115G | I13: RE11W105G | J13: RE11W113G | K13: RE11W109G | L13: RE11W116G | M13: RE11W106G | N13: RE11W102G | O13: RE11W108G | P13: RE11W107G
A14: समाविष्ट गावांमध्ये देखभाल दुरूस्तीची कामे करणे (पथ, विद्युत, भवन, पाणीपुरवठा, मलनिःसारण इ.) | B14: 5000000 | H14: 10000000 | I14: 5000000 | J14: 10000000 | K14: 20000000 | M14: 5000000 | Q14: 55000000
A16: ४. झोपडपट्टी निर्मूलन व पुनर्वसन
A17: ख२. सबइंजिनियर (हेल्थ) (वि.का.) | B17: RE14B211A | C17: RE14B214A | D17: RE14B210A | E17: RE14B212A | F17: RE14B203A | G17: RE14B204A | H17: RE14B215A | I17: RE14B205A | J17: RE14B213A | K17: RE14B209A | L17: RE14B216A | M17: RE14B206A | N17: RE14B202A | O17: RE14B208A | P17: RE14B207A
A18: सार्वजनिक/सुलभ शौचालय दुरूस्ती, मुतार्‍या दुरूस्ती कामे करणे | B18: 1470000 | C18: 2100000 | D18: 2100000 | E18: 3220000 | F18: 1750000 | G18: 770000 | H18: 1400000 | I18: 1400000 | J18: 1050000 | K18: 2100000 | L18: 2100000 | M18: 1400000 | N18: 3150000 | O18: 1610000 | P18: 770000 | Q18: 26390000
B19: RE14B211B | C19: RE14B214B | D19: RE14B210B | E19: RE14B212B | F19: RE14B203B | G19: RE14B204B | H19: RE14B215B | I19: RE14B205B | J19: RE14B213B | K19: RE14B209B | L19: RE14B216B | M19: RE14B206B | N19: RE14B202B | O19: RE14B208B | P19: RE14B207B
A20: काँक्रीटीकरणाची व फरशीची कामे / पेव्हींगची कामे व देखभाल दुरूस्ती करणे | B20: 840000 | C20: 700000 | D20: 1400000 | E20: 980000 | F20: 700000 | G20: 630000 | H20: 700000 | I20: 1050000 | J20: 1050000 | K20: 1400000 | L20: 1050000 | M20: 1400000 | N20: 2450000 | O20: 700000 | P20: 560000 | Q20: 15610000
B21: RE14B211C | C21: RE14B214C | D21: RE14B210C | E21: RE14B212C | F21: RE14B203C | G21: RE14B204C | H21: RE14B215C | I21: RE14B205C | J21: RE14B213C | K21: RE14B209C | L21: RE14B216C | M21: RE14B206C | N21: RE14B202C | O21: RE14B208C | P21: RE14B207C
A22: जुन्या ड्रेनेज लाईन बदलणे व दुरूस्ती करणे | B22: 2100000 | C22: 1400000 | D22: 1400000 | E22: 2240000 | F22: 700000 | G22: 630000 | H22: 700000 | I22: 700000 | J22: 1050000 | K22: 2100000 | L22: 1050000 | M22: 1400000 | N22: 2450000 | O22: 700000 | P22: 840000 | Q22: 19460000
B23: RE14B211D | C23: RE14B214D | D23: RE14B210D | E23: RE14B212D | F23: RE14B203D | G23: RE14B204D | H23: RE14B215D | I23: RE14B205D | J23: RE14B213D | K23: RE14B209D | L23: RE14B216D | M23: RE14B206D | N23: RE14B202D | O23: RE14B208D | P23: RE14B207D
A24: ड्रेनेज लाईन व चेंबर साफसफाई करणे | B24: 2100000 | C24: 1750000 | D24: 1400000 | E24: 2030000 | F24: 700000 | G24: 630000 | H24: 700000 | I24: 700000 | J24: 840000 | K24: 2100000 | L24: 1260000 | M24: 2100000 | N24: 3150000 | O24: 1400000 | P24: 1050000 | Q24: 21910000
B25: RE14B211E | C25: RE14B214E | D25: RE14B210E | E25: RE14B212E | F25: RE14B203E | G25: RE14B204E | H25: RE14B215E | I25: RE14B205E | J25: RE14B213E | K25: RE14B209E | L25: RE14B216E | M25: RE14B206E | N25: RE14B202E | O25: RE14B208E | P25: RE14B207E
A26: देखभाल दुरुस्तीसाठी साहित्य खरेदी - पुरविणे व बसविणे | B26: 210000 | C26: 280000 | D26: 350000 | E26: 700000 | F26: 350000 | G26: 280000 | H26: 280000 | I26: 280000 | J26: 140000 | K26: 1050000 | L26: 280000 | M26: 350000 | N26: 630000 | O26: 350000 | P26: 700000 | Q26: 6230000
A27: ग२. नागरवस्ती विकास योजना (वि.कार्या.) | B27: RE14C211A | C27: RE14C214A | D27: RE14C210A | E27: RE14C212A | F27: RE14C203A | G27: RE14C204A | H27: RE14C215A | I27: RE14C205A | J27: RE14C213A | K27: RE14C209A | L27: RE14C216A | M27: RE14C206A | N27: RE14C202A | O27: RE14C208A | P27: RE14C207A
A28: १. कायम सेवकवर्ग वेतन | F28: 3000000 | Q28: 3000000
A30: ७. आरोग्य
A31: लोकारोग्य (विभागीय कार्यालय) | B31: RE17F211A | C31: RE17F214A | D31: RE17F210A | E31: RE17F212A | F31: RE17F203A | G31: RE17F204A | H31: RE17F215A | I31: RE17F205A | J31: RE17F213A | K31: RE17F209A | L31: RE17F216A | M31: RE17F206A | N31: RE17F202A | O31: RE17F208A | P31: RE17F207A
A32: १. कायम सेवकवर्ग वेतन | B32: 8000000 | C32: 4200000 | D32: 6000000 | E32: 2700000 | F32: 5100000 | G32: 1700000 | H32: 3000000 | I32: 5700000 | J32: 1700000 | K32: 4700000 | L32: 6500000 | M32: 4000000 | N32: 10000000 | O32: 3200000 | P32: 3500000 | Q32: 70000000
A34: ९. पथांची झाडलोट, कचरावाहतूक इ.
A35: क२. पथांची झाडलोट (विभा. कार्या.) | B35: RE19A211A | C35: RE19A214A | D35: RE19A210A | E35: RE19A212A | F35: RE19A203A | G35: RE19A204A | H35: RE19A215A | I35: RE19A205A | J35: RE19A213A | K35: RE19A209A | L35: RE19A216A | M35: RE19A206A | N35: RE19A202A | O35: RE19A208A | P35: RE19A207A
A36: १. कायम सेवकवर्ग वेतन | B36: 77400000 | C36: 76400000 | D36: 76400000 | E36: 77400000 | F36: 76400000 | G36: 76400000 | H36: 77400000 | I36: 76400000 | J36: 76400000 | K36: 77400000 | L36: 76400000 | M36: 76400000 | N36: 76400000 | O36: 76400000 | P36: 76400000 | Q36: 1150000000
B37: RE19A211C | C37: RE19A214C | D37: RE19A210C | E37: RE19A212C | F37: RE19A203C | G37: RE19A204C | H37: RE19A215C | I37: RE19A205C | J37: RE19A213C | K37: RE19A209C | L37: RE19A216C | M37: RE19A206C | N37: RE19A202C | O37: RE19A208C | P37: RE19A207C
A38: घंटागाड्या,सायकल रिक्षा पुरविणे व दुरूस्ती,बकेट खरेदी करणे, आरोग्यकोठ्या दुरूस्त करणे | B38: 700000 | C38: 280000 | D38: 280000 | E38: 910000 | F38: 350000 | G38: 315000 | H38: 280000 | I38: 350000 | J38: 420000 | K38: 1750000 | L38: 700000 | M38: 350000 | N38: 1750000 | O38: 350000 | P38: 315000 | Q38: 9100000
B39: RE19A211D | C39: RE19A214D | D39: RE19A210D | E39: RE19A212D | F39: RE19A203D | G39: RE19A204D | H39: RE19A215D | I39: RE19A205D | J39: RE19A213D | K39: RE19A209D | L39: RE19A216D | M39: RE19A206D | N39: RE19A202D | O39: RE19A208D | P39: RE19A207D
A40: आऊटसोर्सिंगने कचरा संदर्भात कामे करून घेणे | B40: 56000000 | C40: 35000000 | D40: 29820000 | E40: 50400000 | F40: 16800000 | G40: 38500000 | H40: 35000000 | I40: 25200000 | J40: 28000000 | K40: 35000000 | L40: 51520000 | M40: 280000 | N40: 9450000 | O40: 3500000 | P40: 24500000 | Q40: 438970000
B41: RE19A211E | C41: RE19A214E | D41: RE19A210E | E41: RE19A212E | F41: RE19A203E | G41: RE19A204E | H41: RE19A215E | I41: RE19A205E | J41: RE19A213E | K41: RE19A209E | L41: RE19A216E | M41: RE19A206E | N41: RE19A202E | O41: RE19A208E | P41: RE19A207E
A42: बायोगॅस, गांडुळखत प्रकल्प संबंधी आवश्यक ती कामे करणे | B42: 420000 | C42: 280000 | D42: 350000 | E42: 420000 | F42: 2030000 | G42: 210000 | H42: 1260000 | I42: 0 | J42: 280000 | K42: 280000 | L42: 0 | M42: 140000 | N42: 350000 | O42: 350000 | P42: 630000 | Q42: 7000000
A44: ख२. कचरा वाहतूक (विभा. कार्या.) | B44: RE19B211A | C44: RE19B214A | D44: RE19B210A | E44: RE19B212A | F44: RE19B203A | G44: RE19B204A | H44: RE19B215A | I44: RE19B205A | J44: RE19B213A | K44: RE19B209A | L44: RE19B216A | M44: RE19B206A | N44: RE19B202A | O44: RE19B208A | P44: RE19B207A
A45: १. कायम सेवकवर्ग वेतन | B45: 49300000 | C45: 49300000 | D45: 49400000 | E45: 49300000 | F45: 49300000 | G45: 49400000 | H45: 49300000 | I45: 49300000 | J45: 49400000 | K45: 49300000 | L45: 49300000 | M45: 49400000 | N45: 49300000 | O45: 49300000 | P45: 49400000 | Q45: 740000000
A46: ग२. मैला व मैलापाणी वाहतूक (आ.प्र.) | B46: RE19C211A | C46: RE19C214A | D46: RE19C210A | E46: RE19C212A | F46: RE19C203A | G46: RE19C204A | H46: RE19C215A | I46: RE19C205A | J46: RE19C213A | K46: RE19C209A | L46: RE19C216A | M46: RE19C206A | N46: RE19C202A | O46: RE19C208A | P46: RE19C207A
A47: १. कायम सेवकवर्ग वेतन | B47: 28300000 | C47: 28300000 | D47: 28400000 | E47: 28300000 | F47: 28300000 | G47: 28400000 | H47: 28300000 | I47: 28300000 | J47: 28400000 | K47: 28300000 | L47: 28300000 | M47: 28400000 | N47: 28300000 | O47: 28300000 | P47: 28400000 | Q47: 425000000
A49: घ२. भुयारी गटारे, कुंड्या व चेंबर्स स्वच्छता | B49: RE19D211A | C49: RE19D214A | D49: RE19D210A | E49: RE19D212A | F49: RE19D203A | G49: RE19D204A | H49: RE19D215A | I49: RE19D205A | J49: RE19D213A | K49: RE19D209A | L49: RE19D216A | M49: RE19D206A | N49: RE19D202A | O49: RE19D208A | P49: RE19D207A
A50: १. कायम सेवकवर्ग वेतन | B50: 7120000 | C50: 7120000 | D50: 7120000 | E50: 7120000 | F50: 7120000 | G50: 7120000 | H50: 7120000 | I50: 7120000 | J50: 7120000 | K50: 7120000 | L50: 7120000 | M50: 7120000 | N50: 7120000 | O50: 7120000 | P50: 7120000 | Q50: 106800000
A52: च२. झोपडपट्टी वस्त्यांची स्वच्छता व साफसफाईची कामे (विभा.कार्या.)
B53: RE19E211A | C53: RE19E214A | D53: RE19E210A | E53: RE19E212A | F53: RE19E203A | G53: RE19E204A | H53: RE19E215A | I53: RE19E205A | J53: RE19E213A | K53: RE19E209A | L53: RE19E216A | M53: RE19E206A | N53: RE19E202A | O53: RE19E208A | P53: RE19E207A
A54: १. कायम सेवकवर्ग वेतन | B54: 15400000 | C54: 15300000 | D54: 15300000 | E54: 15400000 | F54: 15400000 | G54: 15300000 | H54: 15400000 | I54: 15300000 | J54: 15300000 | K54: 15300000 | L54: 15400000 | M54: 15300000 | N54: 15300000 | O54: 15300000 | P54: 15300000 | Q54: 230000000
A56: १०. पथ सुधारणा (विशेष कार्याधिकारी)
A57: क२. पथ सुधारणा (विशेष कार्याधिकारी) | B57: RE20A211A | C57: RE20A214A | D57: RE20A210A | E57: RE20A212A | F57: RE20A203A | G57: RE20A204A | H57: RE20A215A | I57: RE20A205A | J57: RE20A213A | K57: RE20A209A | L57: RE20A216A | M57: RE20A206A | N57: RE20A202A | O57: RE20A208A | P57: RE20A207A
A58: १. कायम सेवकवर्ग वेतन | B58: 10000000 | C58: 10000000 | D58: 10000000 | E58: 10000000 | F58: 10000000 | G58: 10000000 | H58: 10000000 | I58: 10000000 | J58: 10000000 | K58: 10000000 | L58: 10000000 | M58: 10000000 | N58: 10000000 | O58: 10000000 | P58: 10000000 | Q58: 150000000
A59: ख२. पथ दुरुस्ती (विभागीय कार्यालय) | B59: RE20B211A | C59: RE20B214A | D59: RE20B210A | E59: RE20B212A | F59: RE20B203A | G59: RE20B204A | H59: RE20B215A | I59: RE20B205A | J59: RE20B213A | K59: RE20B209A | L59: RE20B216A | M59: RE20B206A | N59: RE20B202A | O59: RE20B208A | P59: RE20B207A
A60: पथांवरील राडारोडा उचलणे | B60: 2100000 | C60: 1050000 | D60: 1400000 | E60: 1330000 | F60: 980000 | G60: 840000 | H60: 1050000 | I60: 1050000 | J60: 1400000 | K60: 1750000 | L60: 770000 | M60: 1050000 | N60: 1890000 | O60: 2100000 | P60: 1120000 | Q60: 19880000
B61: RE20B211B | C61: RE20B214B | D61: RE20B210B | E61: RE20B212B | F61: RE20B203B | G61: RE20B204B | H61: RE20B215B | I61: RE20B205B | J61: RE20B213B | K61: RE20B209B | L61: RE20B216B | M61: RE20B206B | N61: RE20B202B | O61: RE20B208B | P61: RE20B207B
A62: निरनिराळ्या पथावरील खड्‌डे दुरुस्ती करणे | B62: 4200000 | C62: 840000 | D62: 1750000 | E62: 1470000 | F62: 1050000 | G62: 840000 | H62: 1050000 | I62: 1050000 | J62: 700000 | K62: 1750000 | L62: 1050000 | M62: 1400000 | N62: 2100000 | O62: 2100000 | P62: 700000 | Q62: 22050000
B63: RE20B211C | C63: RE20B214C | D63: RE20B210C | E63: RE20B212C | F63: RE20B203C | G63: RE20B204C | H63: RE20B215C | I63: RE20B205C | J63: RE20B213C | K63: RE20B209C | L63: RE20B216C | M63: RE20B206C | N63: RE20B202C | O63: RE20B208C | P63: RE20B207C
A64: रियन्सटेंटमेंटची कामे करणे. | B64: 4200000 | C64: 1750000 | D64: 2800000 | E64: 3220000 | F64: 2100000 | G64: 1890000 | H64: 2100000 | I64: 1050000 | J64: 1750000 | K64: 1750000 | L64: 1750000 | M64: 1750000 | N64: 3150000 | O64: 2100000 | P64: 1400000 | Q64: 32760000
B65: RE20B211D | C65: RE20B214D | D65: RE20B210D | E65: RE20B212D | F65: RE20B203D | G65: RE20B204D | H65: RE20B215D | I65: RE20B205D | J65: RE20B213D | K65: RE20B209D | L65: RE20B216D | M65: RE20B206D | N65: RE20B202D | O65: RE20B208D | P65: RE20B207D
A66: पथावरील पुतळ्यांची स्वच्छता व दुरूस्ती करणे | B66: 140000 | C66: 280000 | D66: 210000 | E66: 280000 | F66: 350000 | G66: 210000 | H66: 210000 | I66: 210000 | J66: 35000 | K66: 210000 | L66: 70000 | M66: 140000 | N66: 1050000 | O66: 350000 | P66: 245000 | Q66: 3990000
B67: RE20B211E | C67: RE20B214E | D67: RE20B210E | E67: RE20B212E | F67: RE20B203E | G67: RE20B204E | H67: RE20B215E | I67: RE20B205E | J67: RE20B213E | K67: RE20B209E | L67: RE20B216E | M67: RE20B206E | N67: RE20B202E | O67: RE20B208E | P67: RE20B207E
A68: साईन बोर्डस्‌ रंगविणे, रंगरंगोटी, रेलींगची कामे व डिव्हायडरची कामे करणे | B68: 3500000 | C68: 1400000 | D68: 3500000 | E68: 2800000 | F68: 1400000 | G68: 1960000 | H68: 1400000 | I68: 1400000 | J68: 4200000 | K68: 2450000 | L68: 1449000 | M68: 1400000 | N68: 2800000 | O68: 1750000 | P68: 1400000 | Q68: 32809000
B69: RE20B211F | C69: RE20B214F | D69: RE20B210F | E69: RE20B212F | F69: RE20B203F | G69: RE20B204F | H69: RE20B215F | I69: RE20B205F | J69: RE20B213F | K69: RE20B209F | L69: RE20B216F | M69: RE20B206F | N69: RE20B202F | O69: RE20B208F | P69: RE20B207F
A70: फूटपाथ दुरूस्ती करणे | B70: 2100000 | C70: 1050000 | D70: 2800000 | E70: 1820000 | F70: 1050000 | G70: 840000 | H70: 840000 | I70: 1400000 | J70: 1400000 | K70: 1750000 | L70: 700000 | M70: 1050000 | N70: 2800000 | O70: 1750000 | P70: 560000 | Q70: 21910000
B71: RE20B211G | C71: RE20B214G | D71: RE20B210G | E71: RE20B212G | F71: RE20B203G | G71: RE20B204G | H71: RE20B215G | I71: RE20B205G | J71: RE20B213G | K71: RE20B209G | L71: RE20B216G | M71: RE20B206G | N71: RE20B202G | O71: RE20B208G | P71: RE20B207G
A72: पेव्हींग ब्लॉकची दुरूस्ती / कामे करणे | B72: 2100000 | C72: 350000 | D72: 1400000 | E72: 770000 | F72: 490000 | G72: 315000 | H72: 700000 | I72: 700000 | J72: 700000 | K72: 1750000 | L72: 280000 | M72: 1050000 | N72: 2100000 | O72: 350000 | P72: 385000 | Q72: 13440000
B73: RE20B211H | C73: RE20B214H | D73: RE20B210H | E73: RE20B212H | F73: RE20B203H | G73: RE20B204H | H73: RE20B215H | I73: RE20B205H | J73: RE20B213H | K73: RE20B209H | L73: RE20B216H | M73: RE20B206H | N73: RE20B202H | O73: RE20B208H | P73: RE20B207H
A74: मोबाईल पार्टी व रिक्युपमेंटची बिले देणे | B74: 6300000 | C74: 1400000 | D74: 4200000 | E74: 2590000 | F74: 1750000 | G74: 1960000 | H74: 1400000 | I74: 1400000 | J74: 1400000 | K74: 1750000 | L74: 1400000 | M74: 1400000 | N74: 3150000 | O74: 1750000 | P74: 1400000 | Q74: 33250000
B75: RE20B211J | C75: RE20B214J | D75: RE20B210J | E75: RE20B212J | F75: RE20B203J | G75: RE20B204J | H75: RE20B215J | I75: RE20B205J | J75: RE20B213J | K75: RE20B209J | L75: RE20B216J | M75: RE20B206J | N75: RE20B202J | O75: RE20B208J | P75: RE20B207J
A76: कोठीसाठी आवश्यक साहित्य पुरविणे व खरेदी करणे | B76: 210000 | C76: 210000 | D76: 700000 | E76: 280000 | F76: 350000 | G76: 210000 | H76: 350000 | I76: 280000 | J76: 350000 | K76: 1750000 | L76: 175000 | M76: 140000 | N76: 210000 | O76: 350000 | P76: 175000 | Q76: 5740000
B77: RE20B211K | C77: RE20B214K | D77: RE20B210K | E77: RE20B212K | F77: RE20B203K | G77: RE20B204K | H77: RE20B215K | I77: RE20B205K | J77: RE20B213K | K77: RE20B209K | L77: RE20B216K | M77: RE20B206K | N77: RE20B202K | O77: RE20B208K | P77: RE20B207K
A78: किरकोळ दुरुस्तीची कामे मजुरांमार्फत करून घेणे | B78: 2100000 | C78: 700000 | D78: 700000 | E78: 560000 | F78: 700000 | G78: 630000 | H78: 700000 | I78: 700000 | J78: 700000 | K78: 1750000 | L78: 560000 | M78: 1050000 | N78: 490000 | O78: 1750000 | P78: 1050000 | Q78: 14140000
B79: RE20B211L | C79: RE20B214L | D79: RE20B210L | E79: RE20B212L | F79: RE20B203L | G79: RE20B204L | H79: RE20B215L | I79: RE20B205L | J79: RE20B213L | K79: RE20B209L | L79: RE20B216L | M79: RE20B206L | N79: RE20B202L | O79: RE20B208L | P79: RE20B207L
A80: पावसाळी लाईन ६०० मि.मि.पर्यंत पाईप टाकणे/दुरूस्ती करणे व इतर अनुषंगिक कामे करणे | B80: 2100000 | C80: 490000 | D80: 420000 | E80: 840000 | F80: 700000 | G80: 560000 | H80: 840000 | I80: 700000 | J80: 1400000 | K80: 1750000 | L80: 1050000 | M80: 1400000 | N80: 2800000 | O80: 1050000 | P80: 350000 | Q80: 16450000
B81: RE20B211M | C81: RE20B214M | D81: RE20B210M | E81: RE20B212M | F81: RE20B203M | G81: RE20B204M | H81: RE20B215M | I81: RE20B205M | J81: RE20B213M | K81: RE20B209M | L81: RE20B216M | M81: RE20B206M | N81: RE20B202M | O81: RE20B208M | P81: RE20B207M
A82: पावसाळी जाळ्या पुरविणे, बसविणे व दुरूस्ती करणे | B82: 2100000 | C82: 350000 | D82: 350000 | E82: 630000 | F82: 350000 | G82: 420000 | H82: 560000 | I82: 1050000 | J82: 1400000 | K82: 1750000 | L82: 420000 | M82: 700000 | N82: 2450000 | O82: 700000 | P82: 350000 | Q82: 13580000
B83: RE20B211N | C83: RE20B214N | D83: RE20B210N | E83: RE20B212N | F83: RE20B203N | G83: RE20B204N | H83: RE20B215N | I83: RE20B205N | J83: RE20B213N | K83: RE20B209N | L83: RE20B216N | M83: RE20B206N | N83: RE20B202N | O83: RE20B208N | P83: RE20B207N
A84: काँक्रीटीकरण करणे / फरशी बसविणे व दुरूस्ती करणे | B84: 2100000 | C84: 350000 | D84: 350000 | E84: 560000 | F84: 350000 | G84: 350000 | H84: 560000 | I84: 700000 | J84: 700000 | K84: 1750000 | L84: 280000 | M84: 1050000 | N84: 1400000 | O84: 700000 | P84: 280000 | Q84: 11480000
B85: RE20B211P | C85: RE20B214P | D85: RE20B210P | E85: RE20B212P | F85: RE20B203P | G85: RE20B204P | H85: RE20B215P | I85: RE20B205P | J85: RE20B213P | K85: RE20B209P | L85: RE20B216P | M85: RE20B206P | N85: RE20B202P | O85: RE20B208P | P85: RE20B207P
A86: मुरूम पुरविणे व रस्ता दुरूस्त करणे | B86: 2100000 | C86: 210000 | D86: 350000 | E86: 280000 | F86: 350000 | G86: 210000 | H86: 420000 | I86: 700000 | J86: 700000 | K86: 1750000 | L86: 210000 | M86: 350000 | N86: 210000 | O86: 350000 | P86: 210000 | Q86: 8400000
A88: ग२. पथांवरील दिवाबत्ती (वि.कार्या.) | B88: RE20C211A | C88: RE20C214A | D88: RE20C210A | E88: RE20C212A | F88: RE20C203A | G88: RE20C204A | H88: RE20C215A | I88: RE20C205A | J88: RE20C213A | K88: RE20C209A | L88: RE20C216A | M88: RE20C206A | N88: RE20C202A | O88: RE20C208A | P88: RE20C207A
A89: कायम सेवकवर्ग वेतन | B89: 8700000 | C89: 8700000 | D89: 8600000 | E89: 8700000 | F89: 8700000 | G89: 8600000 | H89: 8700000 | I89: 8700000 | J89: 8600000 | K89: 8700000 | L89: 8700000 | M89: 8600000 | N89: 8700000 | O89: 8700000 | P89: 8600000 | Q89: 130000000
B90: RE20C211C | C90: RE20C214C | D90: RE20C210C | E90: RE20C212C | F90: RE20C203C | G90: RE20C204C | H90: RE20C215C | I90: RE20C205C | J90: RE20C213C | K90: RE20C209C | L90: RE20C216C | M90: RE20C206C | N90: RE20C202C | O90: RE20C208C | P90: RE20C207C
A91: रस्त्यावरील दिवे, देखभाल दुरूस्ती तसेच विुत विषयक आवश्यक कामे करणे | B91: 2800000 | C91: 2800000 | D91: 24500000 | E91: 3500000 | F91: 4200000 | G91: 3150000 | H91: 3500000 | I91: 2800000 | J91: 2800000 | K91: 2100000 | L91: 2100000 | M91: 3150000 | N91: 3150000 | O91: 3500000 | P91: 1680000 | Q91: 65730000
B92: RE20C211D | C92: RE20C214D | D92: RE20C210D | E92: RE20C212D | F92: RE20C203D | G92: RE20C204D | H92: RE20C215D | I92: RE20C205D | J92: RE20C213D | K92: RE20C209D | L92: RE20C216D | M92: RE20C206D | N92: RE20C202D | O92: RE20C208D | P92: RE20C207D
A93: किरकोळ दुरुस्तीची कामे मजुरांमार्फत करून घेणे | B93: 700000 | C93: 840000 | D93: 4200000 | E93: 980000 | F93: 490000 | G93: 1050000 | H93: 2100000 | I93: 1750000 | J93: 1050000 | K93: 1750000 | L93: 385000 | M93: 700000 | N93: 630000 | O93: 560000 | P93: 385000 | Q93: 17570000
A96: १२. भवने, भूमी व मनपा वसाहती यांची व्यवस्था
B97: RE22C211B | C97: RE22C214B | D97: RE22C210B | E97: RE22C212B | F97: RE22C203B | G97: RE22C204B | H97: RE22C215B | I97: RE22C205B | J97: RE22C213B | K97: RE22C209B | L97: RE22C216B | M97: RE22C206B | N97: RE22C202B | O97: RE22C208B | P97: RE22C207B
A98: भवन दुरुस्ती (शाळा, दवाखाने, मार्केट, क्षेत्रिय कार्यालय, मनपा वसाहती इ.) | B98: 2100000 | C98: 1400000 | D98: 2100000 | E98: 1820000 | F98: 1400000 | G98: 2450000 | H98: 1400000 | I98: 1540000 | J98: 1050000 | K98: 1750000 | L98: 1750000 | M98: 1750000 | N98: 4550000 | O98: 2100000 | P98: 1050000 | Q98: 28210000
B99: RE22C211C | C99: RE22C214C | D99: RE22C210C | E99: RE22C212C | F99: RE22C203C | G99: RE22C204C | H99: RE22C215C | I99: RE22C205C | J99: RE22C213C | K99: RE22C209C | L99: RE22C216C | M99: RE22C206C | N99: RE22C202C | O99: RE22C208C | P99: RE22C207C
A100: इतर भवन दुरुस्ती (घाट, स्मशानभूमी, विसर्जन हौद इ.) | B100: 2100000 | C100: 1050000 | D100: 2100000 | E100: 770000 | F100: 1050000 | G100: 1960000 | H100: 1400000 | I100: 1400000 | J100: 700000 | K100: 1750000 | L100: 1750000 | M100: 1400000 | N100: 3150000 | O100: 1050000 | P100: 1050000 | Q100: 22680000
B101: RE22C211D | C101: RE22C214D | D101: RE22C210D | E101: RE22C212D | F101: RE22C203D | G101: RE22C204D | H101: RE22C215D | I101: RE22C205D | J101: RE22C213D | K101: RE22C209D | L101: RE22C216D | M101: RE22C206D | N101: RE22C202D | O101: RE22C208D | P101: RE22C207D
A102: उत्सवानिमित्त (पालखी, जयंती, गणेशोत्सव इ.) मांडव उभारणे व तदनुषंगिक कामे करणे | B102: 1050000 | C102: 1400000 | D102: 1750000 | E102: 1190000 | F102: 1400000 | G102: 1050000 | H102: 1400000 | I102: 840000 | J102: 1050000 | K102: 1750000 | L102: 840000 | M102: 700000 | N102: 4200000 | O102: 10500000 | P102: 700000 | Q102: 29820000
B103: RE22C211E | C103: RE22C214E | D103: RE22C210E | E103: RE22C212E | F103: RE22C203E | G103: RE22C204E | H103: RE22C215E | I103: RE22C205E | J103: RE22C213E | K103: RE22C209E | L103: RE22C216E | M103: RE22C206E | N103: RE22C202E | O103: RE22C208E | P103: RE22C207E
A104: किरकोळ दुरुस्तीसाठी कोठीस साहित्य पुरविणे | B104: 420000 | C104: 280000 | D104: 350000 | E104: 350000 | F104: 350000 | G104: 1050000 | H104: 350000 | I104: 560000 | J104: 210000 | K104: 2100000 | L104: 280000 | M104: 350000 | N104: 420000 | O104: 700000 | P104: 210000 | Q104: 7980000
A106: १३. बांधकाम नियोजन, नगर रचना इ.
A107: छ२. भवन विभाग (विभागीय कार्या.)
B108: RE23G211A | C108: RE23G214A | D108: RE23G210A | E108: RE23G212A | F108: RE23G203A | G108: RE23G204A | H108: RE23G215A | I108: RE23G205A | J108: RE23G213A | K108: RE23G209A | L108: RE23G216A | M108: RE23G206A | N108: RE23G202A | O108: RE23G208A | P108: RE23G207A
A109: १. कायम सेवकवर्ग वेतन | B109: 3000000 | C109: 7000000 | D109: 4000000 | E109: 2000000 | F109: 3000000 | G109: 6000000 | H109: 4000000 | I109: 4000000 | J109: 0 | K109: 6000000 | L109: 4000000 | M109: 2000000 | N109: 2000000 | O109: 3000000 | P109: 800000 | Q109: 50800000
A111: १५. अनुज्ञापत्र व आकाशचिन्हे, पथांवरील अतिक्रमणे काढणे इत्यादी -
B112: RE25B211B | C112: RE25B214B | D112: RE25B210B | E112: RE25B212B | F112: RE25B203B | G112: RE25B204B | H112: RE25B215B | I112: RE25B205B | J112: RE25B213B | K112: RE25B209B | L112: RE25B216B | M112: RE25B206B | N112: RE25B202B | O112: RE25B208B | P112: RE25B207B
A113: किरकोळ दुरुस्तीची कामे मजुरांमार्फत करून घेणे | B113: 3500000 | C113: 840000 | D113: 14000000 | E113: 1540000 | F113: 1400000 | G113: 994000 | H113: 1050000 | I113: 1050000 | J113: 1050000 | K113: 1750000 | L113: 3276000 | M113: 700000 | N113: 840000 | O113: 1750000 | P113: 1400000 | Q113: 35140000
B114: RE25B211C | C114: RE25B214C | D114: RE25B210C | E114: RE25B212C | F114: RE25B203C | G114: RE25B204C | H114: RE25B215C | I114: RE25B205C | J114: RE25B213C | K114: RE25B209C | L114: RE25B216C | M114: RE25B206C | N114: RE25B202C | O114: RE25B208C | P114: RE25B207C
...

Sheet JNNURM
A1: • | B1: • | C1: • | D1: • | E1: code | F1: AMRUT, JNNURM (वाढीव कालावधी) व Smart City आभियान | G1: सुधारित मंजूर तरतूद | H1: सन 2018-19 साठी आवश्यक तरतूद (आ)
H2: 0
H3: 0
A4: 6 | F4: शहरी गरिबांसाठी मुलभूत सुविधा (BSUP) : | H4: 0
B5: 1 | D5: P | E5: FE38A101 | F5: शहरी गरिब व आर्थिक मागासांसाठी एकात्मिक पुनर्वसन योजना तयार करून हडपसर येथे ६००० घरे बांधून करणे | G5: 1092520000 | H5: 70000000
B6: 3 | D6: P | E6: FE38A103 | F6: शहरी गरीब व आर्थिक मागासांसाठी एकात्मिक पुनर्वसन योजना तयार करून वारजे येथे २५७६ घरे बांधून करणे. | G6: 630876000 | H6: 10000000
B7: 8 | E7: FE38A108 | F7: इनसिटू रिहॅबिलीटेशन | G7: 1404200000 | H7: 50000000
H8: 0
F9: शहरी गरिबांसाठी मुलभूत सुविधा (BSUP) : एकूण | H9: 130000000
H10: 0
H11: 0
A12: 14 | E12: FE48A101 | F12: केंद्र शासन पुरस्कृत विविध योजनांसाठी (JNNURM, AMRUT व Smart City आभियान इत्यादी) प्रकल्पासंबधित केंद्रशासन व राज्यशासनाशी समन्वय साधणेसाठी व अन्य विशेष इतर कामांसाठी PIU Cell | G12: 5400000 | H12: 20000000
H13: 0
E14: FE49A104 | F14: JUUNRM वाढीव कालावधी मध्ये मंजूर झालेले तसेच AMRUT अभियानामध्ये समावेश झालेल्या भामा आसखेड पाणी पुरवठा प्रकल्पासाठी तरतूद | H14: 1120000000
E15: FE49A105 | F15: JNNURM वाढीव कालावधी मध्ये मंजूर झालेले तसेच AMRUT अभियानामध्ये समावेश झालेल्या वडगाव बुद्रुक प्रकल्पासाठी तरतूद | H15: 50000000
H16: 0
E17: FE50A103A | F17: अमृत अभियानांतर्गत पुणे हरित क्षेत्र विकास प्रकल्प २०१५-१६ | H17: 5000000
E18: FE50A103B | F18: अमृत अभियानांतर्गत पुणे हरित क्षेत्र विकास प्रकल्प २०१६-१७ | H18: 10000000
E19: FE50A103D | F19: अमृत अभियानांतर्गत पुणे हरित क्षेत्र विकास प्रकल्प २०१७-१८ | H19: 20000000
E20: FE50A105 | F20: Smart City अभियान अंतर्गत तज्ञ सालागारांची फी अदा करणेबाबत | H20: 10000000
H21: 0
A22: • | B22: • | C22: • | D22: • | E22: • | F22: AMRUT, JNNURM (वाढीव कालावधी) व Smart City आभियान एकूण | H22: 1365000000
H23: 0
F24: ( टीप 1 :- जवाहरलाल नेहरू नागरी पुनर्निर्माण योजना निधीतून काम पूर्ण होण्यासाठी आवश्यक असलेल्या रकमेपर्यंत खर्च करण्यात येईल.) | H24: 0
F25: ( टीप 2 :- केंद्र शासनाकडून प्रकल्प मान्य होऊन पहिला हप्ता प्राप्त झाल्यानंतरच खर्च करण्यात येईल.) | H25: 0

Sheet SPV
E1: सार्वजनिक वाहतूक सुधारणा व विशेष प्रकल्प विभागामार्फत करावयाची कामे : | F1: àH$ënr` aŠH$_ | G1: 1819 आयुक्‍त
G2: 0
G3: 0
A4: 13 | C4: FE61A118# | E4: सार्वजनिक वाहतूक सुधारणा कामे :- (Comprehensive Mobility Plan) | G4: 0
C5: FE61A118/A-135 | D5: 35 | E5: विविध प्रकारच्या प्रकल्पांच्या अभ्यासासाठी तरतूद (feasibility report, techno-economical report, environmental report & other reports) | F5: 20000000 | G5: 10000000
C6: FE61A118/A-136 | D6: 36 | E6: स्वारगेट चौकात उड्डाणपूल बांधणे | F6: 1600000000 | G6: 20000000
C7: FE61A118/A-142 | D7: 42 | E7: बालेवाडी स.नं. ४२ ते ४७ ते वाकड रस्ता येथे मुळा नदीवर पुल बांधणे | F7: 280000000 | G7: 30000000
C8: FE61A118/A-144 | D8: 44 | E8: बंडगार्डन येथे बंधार्‍यासाठी लोखंडी गेट बसविणेकरिता सिव्हील व विुत विषयक कामे करणे | F8: 15000000 | G8: 3000000
C9: FE61A118/A-145 | D9: 45 | E9: मुंबई-पुणे महामार्गावर सुतारवाडी येथे ३० मीटर रुंद अंडरपास करणे (नॅशनल हायवे अ‍ॅथॉरिटीज अंडरपास वाढीव रुंदीकरण कामासाठी निधी उपलब्ध करणे) | F9: 43000000 | G9: 14000000
G10: 0
A11: 14 | E11: पुणे शहरात आवश्यक तेथे भुयारी मार्ग / उड्डाणपूल रेल्वे बांधकाम करणे :- (Non Comprehensive Mobility Plan) | G11: 0
C12: FE61A118/B-101 | D12: 1 | E12: लूल्ला नगर, कोंढवा रोड चौकात उड्डाणपूल बांधणे. | F12: 150000000 | G12: 120000000
C13: FE61A118/B-110 | E13: घोरपडी पुणे येथे पुणे सोलापूर व पुणे -मिरज रेल्वे लाईनवर उड्‌डाणपूल बांधणे. | F13: 450000000 | G13: 10000000
C14: FE61A118/B-112 | E14: बोपोडी चौक मुंबई - पुणे रस्ता येथे वाहन भूयारी व पादचारी मार्ग करणे. | F14: 100000000 | G14: 50000000
C15: FE61A118/B-113 | E15: भूसंपादन, संरक्षण खाते / अन्य खात्यांच्या परवानग्या अथवा अन्य स्वरुपाच्या तांत्रिक अडचणी / प्रश्न मार्गी लागल्यानंतर बंद असलेले / रखडलेले प्रकल्प सुरु करणेसाठी करावयाची तरतूद, उदा. हांडेवाडी ससाणेनगर अंडरपास, अलंकार टॉकीज रेल्वे ओव्हरब्रीज, अभियांत्रिकी महाविद्यालय उड्‌डाणपूल, बालेवाडी पूल, मुंढवा पूल इ. | G15: 250000000
C16: FE61A118/B-114 | E16: सेव्हन लव्हज चौक ते वखार महामंडळ चौक उड्‌डाणपूल बांधणे | G16: 150000000
G17: 0
G18: 0
A19: 15 | E19: Signal Free Roads | G19: 0
C20: FE61A118/C-105 | D20: 5 | E20: अभियांत्रिकी महाविालय चौक ते पाटील इस्टेट दरम्यान उड्डाणपूल बांधणे | F20: 800000000 | G20: 50000000
C21: FE61A118/C-112 | D21: 12 | E21: कमिन्स कॉलेज जंक्शन, वारजे रोड येथे उड्डाणपूल बांधणे | F21: 450000000 | G21: 25000000
C22: FE61A118/C-115 | D22: 15 | E22: रामवाडी भूयारी मार्गाचे उर्वरीत काम पूर्ण करणे | F22: 40000000 | G22: 15000000
C23: FE61A118/C-116 | D23: 16 | E23: हॅरिस पूलालगत नवीन पूल बांधणे | F23: 10000000 | G23: 50000000
G24: 0
A25: 16 | C25: FE61A119 | E25: पुणे मेट्रो रेल्वे प्रकल्प | F25: 73000000000 | G25: 120000000
A26: 25 | C26: FE61A127 | E26: खराडी गावठाणापासून मुंढवा येथे मुळामुठा नदीवर पूल बांधणे व येरवडा येथील जुन्या पुलाची देखभाल दुरूस्ती कामे करणे व नवीन पूल बांधणे | F26: 250000000 | G26: 80000000
A27: 26 | C27: FE61A128 | E27: हडपसर मध्ये काळेपडळ व रामटेकडी येथील गेट क्र.६ व ७ तसेच गेट क्र. ७ व ८ या दरम्यान हलक्‍या वाहनांकरिता भुयारी मार्ग बांधणे. | G27: 80000000
A28: 27 | C28: FE61A129 | E28: औंध-सांगवी जोडणा-या मुळा नदीवर पुल बांधणे | G28: 80000000
A29: 28 | C29: FE61A130 | E29: शिवाजीनगर म्हसोबा गेट समोरील पुला खाली म्युरल करणे | G29: 8000000
G30: 0
E31: एकूण बेरीज | G31: 1165000000
E33: ( टीप :- आर्थिक वर्षात सार्वजनिक वाहतूक सुधारणा व विशेष प्रकल्पासाठी अतिरिक्त निधीची गरज भासल्यास जागतिक बँक, जपान बँक व वित्त संस्थांकडून कर्ज घेऊन तरतूद उपलब्ध करता येईल. )

Sheet PMAY
E1: प्रधानमंत्री आवास योजना | F1: àH$ënr` aŠH$_ | G1: 1819 आयुक्‍त
G3: 0
A4: 1 | C4: FE62A101 | E4: प्रधानमंत्री आवास योजनेअंतर्गत विविध योजना राबविणे | G4: 400000000
G5: 0
E6: एकूण बेरीज | G6: 400000000

Sheet SMRY-1819
A1: * | B1: ward | C1: * | D1: क्षेत्रीय कार्यालयाने करावयाची कामे : सन 2018-19 | E1: पथ | F1: विद्युत | G1: भवन | H1: गवनि | I1: पाणीपुरवठा | J1: मलनिःसारण | K1: एकूण | L1: 0
D4: (आकडे लाखात) | E4: 2 | F4: 1 | G4: 4 | H4: 5 | I4: 6 | J4: 7 | K4: Total
A6: Ward Nos. | B6: Sr. | C6: Wards | D6: =D1 -> क्षेत्रीय कार्यालयाने करावयाची कामे : सन 2018-19 | E6: 2 | F6: 1 | G6: 4 | H6: 5 | I6: 6 | J6: 7 | K6: Total
A8: =WardOfficeNonPlan1819!A8 -> 3, 4, 5 | B8: =WardOfficeNonPlan1819!B8 -> 1 | C8: =WardOfficeNonPlan1819!C8 -> 3 | D8: =WardOfficeNonPlan1819!D8 -> नगररोड - वडगावशेरी क्षेत्रीय कार्यालय एकूण बेरीज | E8: =WardOfficeNonPlan1819!E8+WardOfficePlan1819!E8+CitizensNonPlan1819!E8+CitizensPlan1819!E8 -> 297 | F8: =WardOfficeNonPlan1819!F8+WardOfficePlan1819!F8+CitizensNonPlan1819!F8+CitizensPlan1819!F8 -> 78 | G8: =WardOfficeNonPlan1819!G8+WardOfficePlan1819!G8+CitizensNonPlan1819!G8+CitizensPlan1819!G8 -> 62.5 | H8: =WardOfficeNonPlan1819!H8+WardOfficePlan1819!H8+CitizensNonPlan1819!H8+CitizensPlan1819!H8 -> 37.5 | I8: =WardOfficeNonPlan1819!I8+WardOfficePlan1819!I8+CitizensNonPlan1819!I8+CitizensPlan1819!I8 -> 22 | J8: =WardOfficeNonPlan1819!J8+WardOfficePlan1819!J8+CitizensNonPlan1819!J8+CitizensPlan1819!J8 -> 253 | K8: =SUM(E8:J8) -> 750
A9: =WardOfficeNonPlan1819!A9 -> 1, 2, 6 | B9: =WardOfficeNonPlan1819!B9 -> 2 | C9: =WardOfficeNonPlan1819!C9 -> 3 | D9: =WardOfficeNonPlan1819!D9 -> येरवडा - कळस - धानोरी क्षेत्रीय कार्यालय एकूण बेरीज | E9: =WardOfficeNonPlan1819!E9+WardOfficePlan1819!E9+CitizensNonPlan1819!E9+CitizensPlan1819!E9 -> 211.5 | F9: =WardOfficeNonPlan1819!F9+WardOfficePlan1819!F9+CitizensNonPlan1819!F9+CitizensPlan1819!F9 -> 135.5 | G9: =WardOfficeNonPlan1819!G9+WardOfficePlan1819!G9+CitizensNonPlan1819!G9+CitizensPlan1819!G9 -> 213 | H9: =WardOfficeNonPlan1819!H9+WardOfficePlan1819!H9+CitizensNonPlan1819!H9+CitizensPlan1819!H9 -> 40 | I9: =WardOfficeNonPlan1819!I9+WardOfficePlan1819!I9+CitizensNonPlan1819!I9+CitizensPlan1819!I9 -> 10 | J9: =WardOfficeNonPlan1819!J9+WardOfficePlan1819!J9+CitizensNonPlan1819!J9+CitizensPlan1819!J9 -> 135 | K9: =SUM(E9:J9) -> 745
A10: =WardOfficeNonPlan1819!A10 -> 20, 21 | B10: =WardOfficeNonPlan1819!B10 -> 3 | C10: =WardOfficeNonPlan1819!C10 -> 2 | D10: =WardOfficeNonPlan1819!D10 -> ढोलेपाटील क्षेत्रीय कार्यालय एकूण बेरीज | E10: =WardOfficeNonPlan1819!E10+WardOfficePlan1819!E10+CitizensNonPlan1819!E10+CitizensPlan1819!E10 -> 119.5 | F10: =WardOfficeNonPlan1819!F10+WardOfficePlan1819!F10+CitizensNonPlan1819!F10+CitizensPlan1819!F10 -> 74.5 | G10: =WardOfficeNonPlan1819!G10+WardOfficePlan1819!G10+CitizensNonPlan1819!G10+CitizensPlan1819!G10 -> 135.5 | H10: =WardOfficeNonPlan1819!H10+WardOfficePlan1819!H10+CitizensNonPlan1819!H10+CitizensPlan1819!H10 -> 105.5 | I10: =WardOfficeNonPlan1819!I10+WardOfficePlan1819!I10+CitizensNonPlan1819!I10+CitizensPlan1819!I10 -> 20 | J10: =WardOfficeNonPlan1819!J10+WardOfficePlan1819!J10+CitizensNonPlan1819!J10+CitizensPlan1819!J10 -> 45.5 | K10: =SUM(E10:J10) -> 500.5
A11: =WardOfficeNonPlan1819!A11 -> 8, 9 | B11: =WardOfficeNonPlan1819!B11 -> 4 | C11: =WardOfficeNonPlan1819!C11 -> 2 | D11: =WardOfficeNonPlan1819!D11 -> औंध - बाणेर क्षेत्रीय कार्यालय एकूण बेरीज | E11: =WardOfficeNonPlan1819!E11+WardOfficePlan1819!E11+CitizensNonPlan1819!E11+CitizensPlan1819!E11 -> 197.5 | F11: =WardOfficeNonPlan1819!F11+WardOfficePlan1819!F11+CitizensNonPlan1819!F11+CitizensPlan1819!F11 -> 31.5 | G11: =WardOfficeNonPlan1819!G11+WardOfficePlan1819!G11+CitizensNonPlan1819!G11+CitizensPlan1819!G11 -> 96 | H11: =WardOfficeNonPlan1819!H11+WardOfficePlan1819!H11+CitizensNonPlan1819!H11+CitizensPlan1819!H11 -> 85 | I11: =WardOfficeNonPlan1819!I11+WardOfficePlan1819!I11+CitizensNonPlan1819!I11+CitizensPlan1819!I11 -> 5 | J11: =WardOfficeNonPlan1819!J11+WardOfficePlan1819!J11+CitizensNonPlan1819!J11+CitizensPlan1819!J11 -> 85 | K11: =SUM(E11:J11) -> 500
A12: =WardOfficeNonPlan1819!A12 -> 7, 14 | B12: =WardOfficeNonPlan1819!B12 -> 5 | C12: =WardOfficeNonPlan1819!C12 -> 2 | D12: =WardOfficeNonPlan1819!D12 -> शिवाजीनगर - घोले रोड क्षेत्रीय कार्यालय एकूण बेरीज | E12: =WardOfficeNonPlan1819!E12+WardOfficePlan1819!E12+CitizensNonPlan1819!E12+CitizensPlan1819!E12 -> 72 | F12: =WardOfficeNonPlan1819!F12+WardOfficePlan1819!F12+CitizensNonPlan1819!F12+CitizensPlan1819!F12 -> 175 | G12: =WardOfficeNonPlan1819!G12+WardOfficePlan1819!G12+CitizensNonPlan1819!G12+CitizensPlan1819!G12 -> 39 | H12: =WardOfficeNonPlan1819!H12+WardOfficePlan1819!H12+CitizensNonPlan1819!H12+CitizensPlan1819!H12 -> 81 | I12: =WardOfficeNonPlan1819!I12+WardOfficePlan1819!I12+CitizensNonPlan1819!I12+CitizensPlan1819!I12 -> 5 | J12: =WardOfficeNonPlan1819!J12+WardOfficePlan1819!J12+CitizensNonPlan1819!J12+CitizensPlan1819!J12 -> 78 | K12: =SUM(E12:J12) -> 450
A13: =WardOfficeNonPlan1819!A13 -> 10, 11, 12 | B13: =WardOfficeNonPlan1819!B13 -> 6 | C13: =WardOfficeNonPlan1819!C13 -> 3 | D13: =WardOfficeNonPlan1819!D13 -> कोथरूड - बावधन क्षेत्रीय कार्यालय एकूण बेरीज | E13: =WardOfficeNonPlan1819!E13+WardOfficePlan1819!E13+CitizensNonPlan1819!E13+CitizensPlan1819!E13 -> 321.25 | F13: =WardOfficeNonPlan1819!F13+WardOfficePlan1819!F13+CitizensNonPlan1819!F13+CitizensPlan1819!F13 -> 85 | G13: =WardOfficeNonPlan1819!G13+WardOfficePlan1819!G13+CitizensNonPlan1819!G13+CitizensPlan1819!G13 -> 71.5 | H13: =WardOfficeNonPlan1819!H13+WardOfficePlan1819!H13+CitizensNonPlan1819!H13+CitizensPlan1819!H13 -> 82.5 | I13: =WardOfficeNonPlan1819!I13+WardOfficePlan1819!I13+CitizensNonPlan1819!I13+CitizensPlan1819!I13 -> 0 | J13: =WardOfficeNonPlan1819!J13+WardOfficePlan1819!J13+CitizensNonPlan1819!J13+CitizensPlan1819!J13 -> 189 | K13: =SUM(E13:J13) -> 749.25
A14: =WardOfficeNonPlan1819!A14 -> 35, 39, 40 | B14: =WardOfficeNonPlan1819!B14 -> 7 | C14: =WardOfficeNonPlan1819!C14 -> 3 | D14: =WardOfficeNonPlan1819!D14 -> धनकवडी - सहकारनगर क्षेत्रीय कार्यालय एकूण बेरीज | E14: =WardOfficeNonPlan1819!E14+WardOfficePlan1819!E14+CitizensNonPlan1819!E14+CitizensPlan1819!E14 -> 325 | F14: =WardOfficeNonPlan1819!F14+WardOfficePlan1819!F14+CitizensNonPlan1819!F14+CitizensPlan1819!F14 -> 71.5 | G14: =WardOfficeNonPlan1819!G14+WardOfficePlan1819!G14+CitizensNonPlan1819!G14+CitizensPlan1819!G14 -> 111 | H14: =WardOfficeNonPlan1819!H14+WardOfficePlan1819!H14+CitizensNonPlan1819!H14+CitizensPlan1819!H14 -> 64 | I14: =WardOfficeNonPlan1819!I14+WardOfficePlan1819!I14+CitizensNonPlan1819!I14+CitizensPlan1819!I14 -> 3 | J14: =WardOfficeNonPlan1819!J14+WardOfficePlan1819!J14+CitizensNonPlan1819!J14+CitizensPlan1819!J14 -> 175 | K14: =SUM(E14:J14) -> 749.5
A15: =WardOfficeNonPlan1819!A15 -> 30, 33, 34 | B15: =WardOfficeNonPlan1819!B15 -> 8 | C15: =WardOfficeNonPlan1819!C15 -> 3 | D15: =WardOfficeNonPlan1819!D15 -> सिंहगड रोड क्षेत्रीय कार्यालय एकूण बेरीज | E15: =WardOfficeNonPlan1819!E15+WardOfficePlan1819!E15+CitizensNonPlan1819!E15+CitizensPlan1819!E15 -> 301.5 | F15: =WardOfficeNonPlan1819!F15+WardOfficePlan1819!F15+CitizensNonPlan1819!F15+CitizensPlan1819!F15 -> 78.5 | G15: =WardOfficeNonPlan1819!G15+WardOfficePlan1819!G15+CitizensNonPlan1819!G15+CitizensPlan1819!G15 -> 22.5 | H15: =WardOfficeNonPlan1819!H15+WardOfficePlan1819!H15+CitizensNonPlan1819!H15+CitizensPlan1819!H15 -> 137 | I15: =WardOfficeNonPlan1819!I15+WardOfficePlan1819!I15+CitizensNonPlan1819!I15+CitizensPlan1819!I15 -> 5 | J15: =WardOfficeNonPlan1819!J15+WardOfficePlan1819!J15+CitizensNonPlan1819!J15+CitizensPlan1819!J15 -> 206 | K15: =SUM(E15:J15) -> 750.5
A16: =WardOfficeNonPlan1819!A16 -> 13, 31, 32 | B16: =WardOfficeNonPlan1819!B16 -> 9 | C16: =WardOfficeNonPlan1819!C16 -> 3 | D16: =WardOfficeNonPlan1819!D16 -> वारजे - कर्वेनगर क्षेत्रीय कार्यालय एकूण बेरीज | E16: =WardOfficeNonPlan1819!E16+WardOfficePlan1819!E16+CitizensNonPlan1819!E16+CitizensPlan1819!E16 -> 254.5 | F16: =WardOfficeNonPlan1819!F16+WardOfficePlan1819!F16+CitizensNonPlan1819!F16+CitizensPlan1819!F16 -> 129.5 | G16: =WardOfficeNonPlan1819!G16+WardOfficePlan1819!G16+CitizensNonPlan1819!G16+CitizensPlan1819!G16 -> 74.5 | H16: =WardOfficeNonPlan1819!H16+WardOfficePlan1819!H16+CitizensNonPlan1819!H16+CitizensPlan1819!H16 -> 84 | I16: =WardOfficeNonPlan1819!I16+WardOfficePlan1819!I16+CitizensNonPlan1819!I16+CitizensPlan1819!I16 -> 5 | J16: =WardOfficeNonPlan1819!J16+WardOfficePlan1819!J16+CitizensNonPlan1819!J16+CitizensPlan1819!J16 -> 202.5 | K16: =SUM(E16:J16) -> 750
A17: =WardOfficeNonPlan1819!A17 -> 22, 23, 26 | B17: =WardOfficeNonPlan1819!B17 -> 10 | C17: =WardOfficeNonPlan1819!C17 -> 3 | D17: =WardOfficeNonPlan1819!D17 -> हडपसर - मुंढवा क्षेत्रीय कार्यालय एकूण बेरीज | E17: =WardOfficeNonPlan1819!E17+WardOfficePlan1819!E17+CitizensNonPlan1819!E17+CitizensPlan1819!E17 -> 316 | F17: =WardOfficeNonPlan1819!F17+WardOfficePlan1819!F17+CitizensNonPlan1819!F17+CitizensPlan1819!F17 -> 108 | G17: =WardOfficeNonPlan1819!G17+WardOfficePlan1819!G17+CitizensNonPlan1819!G17+CitizensPlan1819!G17 -> 108 | H17: =WardOfficeNonPlan1819!H17+WardOfficePlan1819!H17+CitizensNonPlan1819!H17+CitizensPlan1819!H17 -> 35 | I17: =WardOfficeNonPlan1819!I17+WardOfficePlan1819!I17+CitizensNonPlan1819!I17+CitizensPlan1819!I17 -> 20 | J17: =WardOfficeNonPlan1819!J17+WardOfficePlan1819!J17+CitizensNonPlan1819!J17+CitizensPlan1819!J17 -> 163 | K17: =SUM(E17:J17) -> 750
A18: =WardOfficeNonPlan1819!A18 -> 24, 25, 27 | B18: =WardOfficeNonPlan1819!B18 -> 11 | C18: =WardOfficeNonPlan1819!C18 -> 3 | D18: =WardOfficeNonPlan1819!D18 -> वानवडी - रामटेकडी क्षेत्रीय कार्यालय एकूण बेरीज | E18: =WardOfficeNonPlan1819!E18+WardOfficePlan1819!E18+CitizensNonPlan1819!E18+CitizensPlan1819!E18 -> 324.75 | F18: =WardOfficeNonPlan1819!F18+WardOfficePlan1819!F18+CitizensNonPlan1819!F18+CitizensPlan1819!F18 -> 92 | G18: =WardOfficeNonPlan1819!G18+WardOfficePlan1819!G18+CitizensNonPlan1819!G18+CitizensPlan1819!G18 -> 55 | H18: =WardOfficeNonPlan1819!H18+WardOfficePlan1819!H18+CitizensNonPlan1819!H18+CitizensPlan1819!H18 -> 31.5 | I18: =WardOfficeNonPlan1819!I18+WardOfficePlan1819!I18+CitizensNonPlan1819!I18+CitizensPlan1819!I18 -> 18 | J18: =WardOfficeNonPlan1819!J18+WardOfficePlan1819!J18+CitizensNonPlan1819!J18+CitizensPlan1819!J18 -> 166 | K18: =SUM(E18:J18) -> 687.25
A19: =WardOfficeNonPlan1819!A19 -> 38, 41 | B19: =WardOfficeNonPlan1819!B19 -> 12 | C19: =WardOfficeNonPlan1819!C19 -> 2 | D19: =WardOfficeNonPlan1819!D19 -> कोंढवा - येवलेवाडी क्षेत्रीय कार्यालय एकूण बेरीज | E19: =WardOfficeNonPlan1819!E19+WardOfficePlan1819!E19+CitizensNonPlan1819!E19+CitizensPlan1819!E19 -> 186.5 | F19: =WardOfficeNonPlan1819!F19+WardOfficePlan1819!F19+CitizensNonPlan1819!F19+CitizensPlan1819!F19 -> 57.5 | G19: =WardOfficeNonPlan1819!G19+WardOfficePlan1819!G19+CitizensNonPlan1819!G19+CitizensPlan1819!G19 -> 22.5 | H19: =WardOfficeNonPlan1819!H19+WardOfficePlan1819!H19+CitizensNonPlan1819!H19+CitizensPlan1819!H19 -> 25 | I19: =WardOfficeNonPlan1819!I19+WardOfficePlan1819!I19+CitizensNonPlan1819!I19+CitizensPlan1819!I19 -> 0 | J19: =WardOfficeNonPlan1819!J19+WardOfficePlan1819!J19+CitizensNonPlan1819!J19+CitizensPlan1819!J19 -> 208.5 | K19: =SUM(E19:J19) -> 500
... A22: =WardOfficeNonPlan1819!A22 -> 28, 36, 37 | B22: =WardOfficeNonPlan1819!B22 -> 15 | C22: =WardOfficeNonPlan1819!C22 -> 3 | D22: =WardOfficeNonPlan1819!D22 -> बिबवेवाडी क्षेत्रीय कार्यालय एकूण बेरीज | E22: =WardOfficeNonPlan1819!E22+WardOfficePlan1819!E22+CitizensNonPlan1819!E22+CitizensPlan1819!E22 -> 299.5 | F22: =WardOfficeNonPlan1819!F22+WardOfficePlan1819!F22+CitizensNonPlan1819!F22+CitizensPlan1819!F22 -> 93 | G22: =WardOfficeNonPlan1819!G22+WardOfficePlan1819!G22+CitizensNonPlan1819!G22+CitizensPlan1819!G22 -> 61 | H22: =WardOfficeNonPlan1819!H22+WardOfficePlan1819!H22+CitizensNonPlan1819!H22+CitizensPlan1819!H22 -> 71 | I22: =WardOfficeNonPlan1819!I22+WardOfficePlan1819!I22+CitizensNonPlan1819!I22+CitizensPlan1819!I22 -> 5 | J22: =WardOfficeNonPlan1819!J22+WardOfficePlan1819!J22+CitizensNonPlan1819!J22+CitizensPlan1819!J22 -> 138 | K22: =SUM(E22:J22) -> 667.5
C24: =SUM(C8:C23) -> 41 | D24: =""&TEXT(D6,"0")&" एकूण बेरीज" -> क्षेत्रीय कार्यालयाने करावयाची कामे : सन 2018-19 एकूण बेरीज | E24: =SUM(E8:E23) -> 3614 | F24: =SUM(F8:F23) -> 1329.5 | G24: =SUM(G8:G23) -> 1444 | H24: =SUM(H8:H23) -> 1180 | I24: =SUM(I8:I23) -> 145 | J24: =SUM(J8:J23) -> 2337 | K24: =SUM(K8:K23) -> 10049.5

Sheet WardOfficeNonPlan1819
A1: code | B1: ward | C1: * | D1: क्षेत्रीय कार्यालयाने करावयाची योजनेतर कामे : सन 2018-19 | E1: पथ | F1: विद्युत | G1: भवन | H1: गवनि | I1: पाणीपुरवठा | J1: मलनिःसारण | K1: एकूण | L1: 0
D4: (आकडे लाखात) | E4: W2 | F4: W1 | G4: W4 | H4: W5 | I4: W6 | J4: W7
A6: Ward Nos. | B6: Sr. | C6: Wards | D6: =D1 -> क्षेत्रीय कार्यालयाने करावयाची योजनेतर कामे : सन 2018-19 | E6: RE20A301/W2- | F6: RE20C301/W1- | G6: RE22C301/W4- | H6: RE14B301/W5- | I6: XE12B301/W6- | J6: XE23A301/W7- | K6: Total
A8: 3, 4, 5 | B8: 1 | C8: 3 | D8: =D286 -> नगररोड - वडगावशेरी क्षेत्रीय कार्यालय एकूण बेरीज | E8: =E286 -> 190 | F8: =F286 -> 40 | G8: =G286 -> 37.5 | H8: =H286 -> 22.5 | I8: =I286 -> 0 | J8: =J286 -> 160 | K8: =SUM(E8:J8) -> 450
A9: 1, 2, 6 | B9: 2 | C9: 3 | D9: =D541 -> येरवडा - कळस - धानोरी क्षेत्रीय कार्यालय एकूण बेरीज | E9: =E541 -> 112 | F9: =F541 -> 85 | G9: =G541 -> 123 | H9: =H541 -> 30 | I9: =I541 -> 10 | J9: =J541 -> 90 | K9: =SUM(E9:J9) -> 450
A10: 20, 21 | B10: 3 | C10: 2 | D10: =D713 -> ढोलेपाटील क्षेत्रीय कार्यालय एकूण बेरीज | E10: =E713 -> 85 | F10: =F713 -> 52.5 | G10: =G713 -> 102.5 | H10: =H713 -> 37.5 | I10: =I713 -> 3 | J10: =J713 -> 20 | K10: =SUM(E10:J10) -> 300.5
A11: 8, 9 | B11: 4 | C11: 2 | D11: =D885 -> औंध - बाणेर क्षेत्रीय कार्यालय एकूण बेरीज | E11: =E885 -> 102.5 | F11: =F885 -> 26.5 | G11: =G885 -> 51 | H11: =H885 -> 60 | I11: =I885 -> 0 | J11: =J885 -> 60 | K11: =SUM(E11:J11) -> 300
A12: 7, 14 | B12: 5 | C12: 2 | D12: =D1057 -> शिवाजीनगर - घोले रोड क्षेत्रीय कार्यालय एकूण बेरीज | E12: =E1057 -> 30 | F12: =F1057 -> 150 | G12: =G1057 -> 20 | H12: =H1057 -> 15 | I12: =I1057 -> 0 | J12: =J1057 -> 35 | K12: =SUM(E12:J12) -> 250
A13: 10, 11, 12 | B13: 6 | C13: 3 | D13: =D1312 -> कोथरूड - बावधन क्षेत्रीय कार्यालय एकूण बेरीज | E13: =E1312 -> 35 | F13: =F1312 -> 25 | G13: =G1312 -> 32.5 | H13: =H1312 -> 37.5 | I13: =I1312 -> 0 | J13: =J1312 -> 70 | K13: =SUM(E13:J13) -> 200
A14: 35, 39, 40 | B14: 7 | C14: 3 | D14: =D1567 -> धनकवडी - सहकारनगर क्षेत्रीय कार्यालय एकूण बेरीज | E14: =E1567 -> 175 | F14: =F1567 -> 2.5 | G14: =G1567 -> 37.5 | H14: =H1567 -> 50 | I14: =I1567 -> 0 | J14: =J1567 -> 87.5 | K14: =SUM(E14:J14) -> 352.5
A15: 30, 33, 34 | B15: 8 | C15: 3 | D15: =D1822 -> सिंहगड रोड क्षेत्रीय कार्यालय एकूण बेरीज | E15: =E1822 -> 236.5 | F15: =F1822 -> 33.5 | G15: =G1822 -> 22.5 | H15: =H1822 -> 58 | I15: =I1822 -> 0 | J15: =J1822 -> 100 | K15: =SUM(E15:J15) -> 450.5
A16: 13, 31, 32 | B16: 9 | C16: 3 | D16: =D2077 -> वारजे - कर्वेनगर क्षेत्रीय कार्यालय एकूण बेरीज | E16: =E2077 -> 80.5 | F16: =F2077 -> 54.5 | G16: =G2077 -> 18.5 | H16: =H2077 -> 29 | I16: =I2077 -> 0 | J16: =J2077 -> 97.5 | K16: =SUM(E16:J16) -> 280
A17: 22, 23, 26 | B17: 10 | C17: 3 | D17: =D2332 -> हडपसर - मुंढवा क्षेत्रीय कार्यालय एकूण बेरीज | E17: =E2332 -> 145 | F17: =F2332 -> 57.5 | G17: =G2332 -> 80 | H17: =H2332 -> 25 | I17: =I2332 -> 0 | J17: =J2332 -> 75 | K17: =SUM(E17:J17) -> 382.5
A18: 24, 25, 27 | B18: 11 | C18: 3 | D18: =D2587 -> वानवडी - रामटेकडी क्षेत्रीय कार्यालय एकूण बेरीज | E18: =E2587 -> 178.5 | F18: =F2587 -> 60 | G18: =G2587 -> 35 | H18: =H2587 -> 12.5 | I18: =I2587 -> 0 | J18: =J2587 -> 82 | K18: =SUM(E18:J18) -> 368
A19: 38, 41 | B19: 12 | C19: 2 | D19: =D2759 -> कोंढवा - येवलेवाडी क्षेत्रीय कार्यालय एकूण बेरीज | E19: =E2759 -> 100.5 | F19: =F2759 -> 22.5 | G19: =G2759 -> 22.5 | H19: =H2759 -> 25 | I19: =I2759 -> 0 | J19: =J2759 -> 129.5 | K19: =SUM(E19:J19) -> 300
A20: 15, 16, 29 | B20: 13 | C20: 3 | D20: =D3014 -> कसबा - विश्रामबागवाडा क्षेत्रीय कार्यालय एकूण बेरीज | E20: =E3014 -> 122.5 | F20: =F3014 -> 10 | G20: =G3014 -> 142.5 | H20: =H3014 -> 80 | I20: =I3014 -> 0 | J20: =J3014 -> 95 | K20: =SUM(E20:J20) -> 450
A21: 17, 18, 19 | B21: 14 | C21: 3 | D21: =D3269 -> भवानी पेठ क्षेत्रीय कार्यालय एकूण बेरीज | E21: =E3269 -> 80 | F21: =F3269 -> 60 | G21: =G3269 -> 127.5 | H21: =H3269 -> 80 | I21: =I3269 -> 0 | J21: =J3269 -> 102.5 | K21: =SUM(E21:J21) -> 450
A22: 28, 36, 37 | B22: 15 | C22: 3 | D22: =D3524 -> बिबवेवाडी क्षेत्रीय कार्यालय एकूण बेरीज | E22: =E3524 -> 71 | F22: =F3524 -> 40.5 | G22: =G3524 -> 7.5 | H22: =H3524 -> 21 | I22: =I3524 -> 0 | J22: =J3524 -> 40 | K22: =SUM(E22:J22) -> 180
C24: =SUM(C8:C23) -> 41 | D24: =""&TEXT(D6,"0")&" एकूण बेरीज" -> क्षेत्रीय कार्यालयाने करावयाची योजनेतर कामे : सन 2018-19 एकूण बेरीज | E24: =SUM(E8:E23) -> 1744 | F24: =SUM(F8:F23) -> 720 | G24: =SUM(G8:G23) -> 860 | H24: =SUM(H8:H23) -> 583 | I24: =SUM(I8:I23) -> 13 | J24: =SUM(J8:J23) -> 1244 | K24: =SUM(K8:K23) -> 5164
L26: 0
L33: 0
D34: नगररोड - वडगावशेरी क्षेत्रीय कार्यालय | K34: =SUM(E34:J34) -> 0
K35: =SUM(E35:J35) -> 0
A36: XE23A301/W7-301 | B36: 3 | D36: प्रभाग क्र.3 ओव्हाळ वस्ती परिसरात ड्रेनेज लाईन बदलणे | E36: 0 | F36: 0 | G36: 0 | H36: 0 | I36: 0 | J36: 7.5 | K36: =SUM(E36:J36) -> 7.5
A37: RE20A301/W2-402 | B37: 3 | D37: प्रभाग क्र.3 ओव्हाळ वस्ती परिसरातील रस्ते विकसित करणे. | E37: 7.5 | F37: 0 | G37: 0 | H37: 0 | I37: 0 | J37: 0 | K37: =SUM(E37:J37) -> 7.5
A38: XE23A301/W7-302 | B38: 3 | D38: प्रभाग क्र.3 वैष्णवी शाळा येथील परिसरात ड्रेनेज लाईन बदलणे. | E38: 0 | F38: 0 | G38: 0 | H38: 0 | I38: 0 | J38: 7.5 | K38: =SUM(E38:J38) -> 7.5
A39: RE20C301/W1-301 | B39: 3 | D39: प्रभाग क्र.3 गुरुद्वारा लोहगाव परिसरात विद्युत विषयक कामे करणे. | E39: 0 | F39: 5 | G39: 0 | H39: 0 | I39: 0 | J39: 0 | K39: =SUM(E39:J39) -> 5
A40: RE20C301/W1-302 | B40: 3 | D40: प्रभाग क्र.3 विमाननगर परिसरात विद्युत विषयक कामे करणे. | E40: 0 | F40: 5 | G40: 0 | H40: 0 | I40: 0 | J40: 0 | K40: =SUM(E40:J40) -> 5
A41: RE20A301/W2-403 | B41: 3 | D41: प्रभाग क्र.3 गुरुद्वारा येथे पदपथ विकसित करणे. | E41: 7.5 | F41: 0 | G41: 0 | H41: 0 | I41: 0 | J41: 0 | K41: =SUM(E41:J41) -> 7.5
A42: XE23A301/W7-303 | B42: 3 | D42: प्रभाग क्र.3 नाले साफसफाई व ड्रेनेज लाईन साफसफाई करणे. | E42: 0 | F42: 0 | G42: 0 | H42: 0 | I42: 0 | J42: 5 | K42: =SUM(E42:J42) -> 5
A43: RE14B301/W5-201 | B43: 3 | D43: प्रभाग क्र.3 रामवाडी वैकफिल्ड झोपडपटटी मध्ये चेंबर दुरुस्ती व ड्रेनेज लाईन दुरुस्ती करणे. | E43: 0 | F43: 0 | G43: 0 | H43: 2.5 | I43: 0 | J43: 0 | K43: =SUM(E43:J43) -> 2.5
A44: RE14B301/W5-202 | B44: 3 | D44: प्रभाग क्र.3 यमुनानगर मध्ये चेंबर दुरुस्ती व ड्रेनेज लाईन दुरुस्ती करणे. | E44: 0 | F44: 0 | G44: 0 | H44: 2.5 | I44: 0 | J44: 0 | K44: =SUM(E44:J44) -> 2.5
A45: RE14B301/W5-203 | B45: 3 | D45: प्रभाग क्र.3 सिध्दार्थनगर मध्ये चेंबर दुरुस्ती व ड्रेनेज लाईन दुरुस्ती करणे. | E45: 0 | F45: 0 | G45: 0 | H45: 2.5 | I45: 0 | J45: 0 | K45: =SUM(E45:J45) -> 2.5
A46: RE20A301/W2-404 | B46: 3 | D46: प्रभाग क्र.3 राजीव गांधी शाळा,कलवड परिसरातील रस्ते विकसित करणे. | E46: 5 | F46: 0 | G46: 0 | H46: 0 | I46: 0 | J46: 0 | K46: =SUM(E46:J46) -> 5
A47: XE23A301/W7-304 | B47: 3 | D47: प्रभाग क्र.3 खेसेपार्क परिसरातील ड्रेनेज लाईन व चेंबर दुरुस्तीची कामे करणे. | E47: 0 | F47: 0 | G47: 0 | H47: 0 | I47: 0 | J47: 5 | K47: =SUM(E47:J47) -> 5
... A63: RE20A301/W2-412 | B63: 3 | D63: प्रभाग क्र.3 मध्ये कलवड वस्ती, खेसेपार्क व दादाची पडळ परिसरात रेस्ते विषयक कामे करणे. | E63: 5 | F63: 0 | G63: 0 | H63: 0 | I63: 0 | J63: 0 | K63: =SUM(E63:J63) -> 5
B64: 3 | D64: 0 | E64: 0 | F64: 0 | G64: 0 | H64: 0 | I64: 0 | J64: 0 | K64: =SUM(E64:J64) -> 0 | L64: 0
B65: 3 | D65: 0 | E65: 0 | F65: 0 | G65: 0 | H65: 0 | I65: 0 | J65: 0 | K65: =SUM(E65:J65) -> 0 | L65: 0
B66: 3 | D66: 0 | E66: 0 | F66: 0 | G66: 0 | H66: 0 | I66: 0 | J66: 0 | K66: =SUM(E66:J66) -> 0 | L66: 0
B67: 3 | D67: 0 | E67: 0 | F67: 0 | G67: 0 | H67: 0 | I67: 0 | J67: 0 | K67: =SUM(E67:J67) -> 0 | L67: 0
B68: 3 | D68: 0 | E68: 0 | F68: 0 | G68: 0 | H68: 0 | I68: 0 | J68: 0 | K68: =SUM(E68:J68) -> 0 | L68: 0
B69: 3 | D69: 0 | E69: 0 | F69: 0 | G69: 0 | H69: 0 | I69: 0 | J69: 0 | K69: =SUM(E69:J69) -> 0 | L69: 0
B70: 3 | D70: 0 | E70: 0 | F70: 0 | G70: 0 | H70: 0 | I70: 0 | J70: 0 | K70: =SUM(E70:J70) -> 0 | L70: 0
B71: 3 | D71: 0 | E71: 0 | F71: 0 | G71: 0 | H71: 0 | I71: 0 | J71: 0 | K71: =SUM(E71:J71) -> 0 | L71: 0
B72: 3 | D72: 0 | E72: 0 | F72: 0 | G72: 0 | H72: 0 | I72: 0 | J72: 0 | K72: =SUM(E72:J72) -> 0 | L72: 0
B73: 3 | D73: 0 | E73: 0 | F73: 0 | G73: 0 | H73: 0 | I73: 0 | J73: 0 | K73: =SUM(E73:J73) -> 0 | L73: 0
B74: 3 | D74: 0 | E74: 0 | F74: 0 | G74: 0 | H74: 0 | I74: 0 | J74: 0 | K74: =SUM(E74:J74) -> 0 | L74: 0
B75: 3 | D75: 0 | E75: 0 | F75: 0 | G75: 0 | H75: 0 | I75: 0 | J75: 0 | K75: =SUM(E75:J75) -> 0 | L75: 0
... B115: 3 | D115: 0 | E115: 0 | F115: 0 | G115: 0 | H115: 0 | I115: 0 | J115: 0 | K115: =SUM(E115:J115) -> 0 | L115: 0
B116: 3 | K116: =SUM(E116:J116) -> 0
B117: 3 | D117: एकूण बेरीज | E117: =SUM(E36:E116) -> 67.5 | F117: =SUM(F36:F116) -> 20 | G117: =SUM(G36:G116) -> 0 | H117: =SUM(H36:H116) -> 12.5 | I117: =SUM(I36:I116) -> 0 | J117: =SUM(J36:J116) -> 50 | K117: =SUM(K36:K116) -> 150
K118: =SUM(E118:J118) -> 0
A119: RE20A301/W2-413 | B119: 4 | D119: प्रभाग क्र.4 विविध ठिकाणी डांबरीकरण करणे | E119: 7.5 | F119: 0 | G119: 0 | H119: 0 | I119: 0 | J119: 0 | K119: =SUM(E119:J119) -> 7.5
A120: XE23A301/W7-310 | B120: 4 | D120: प्रभाग क्र.4 गणेशनगर परिसरात ड्रेनेज लाईन व चेंबर साफसफाई करणे. | E120: 0 | F120: 0 | G120: 0 | H120: 0 | I120: 0 | J120: 7.5 | K120: =SUM(E120:J120) -> 7.5
