Workbook
Name BdgtNo: #REF!
Name BdgtYear: #REF!
Name BdgtYrFrom: #REF!
Name BdgtYrTo: #REF!
Name Description: "P_A_C_Ex"
Name FinYrFrom: #REF!
Name FinYrTo: #REF!
Name Head: #REF!
Name Last2Yr: #REF!
Name Last3Yr: #REF!
Name Last4Yr: #REF!
Name Last5Yr: #REF!
Name List_Smry_0: A_Capital_List!#REF!
Name List_Smry_0: A_Revenue_List!#REF!
Name List_Smry_0: C_Capital_List!$A$1784:$G$1786
Name List_Smry_0: C_Revenue_List!#REF!
Name List_Smry_1: A_Capital_List!#REF!
Name List_Smry_1: A_Revenue_List!#REF!
Name List_Smry_1: C_Capital_List!#REF!
Name List_Smry_1: C_Revenue_List!#REF!
Name List_Smry_2: A_Capital_List!#REF!
Name List_Smry_2: A_Revenue_List!#REF!
Name List_Smry_2: C_Capital_List!$A$1784:$G$1785
Name List_Smry_2: C_Revenue_List!#REF!
Name P_A_A_Ex: #REF!
Name P_A_A01: #REF!
Name P_A_A02: #REF!
Name P_A_A03: A_Revenue_Income!$A$7:$N$490
Name P_A_A04: #REF!
Name P_A_A05: A_Revenue_Expenditure!$A$4:$H$1628
Name P_A_A08: #REF!
Name P_A_A09: #REF!
Name P_A_A10: #REF!,#REF!
Name P_A_A11: #REF!
Name P_A_A12: A_Capital_Expenditure!$A$7:$O$220
Name P_A_A13: #REF!
Name P_A_A14: A_Land_Acquisition!$A$5:$E$387
Name P_A_A15: A_Fund_Expenditure!$A$6:$O$159
Name P_A_A16: A_DPDC_Machinery_Tree!$A$7:$G$121
Name P_A_AC_In1: #REF!
Name P_A_APP: #REF!
Name P_A_Bdgt: A_DPDC_Machinery_Tree!$A$7:$G$121
Name P_A_Bdgt: A_Fund_Expenditure!$A$6:$O$159
Name P_A_Bdgt: A_Land_Acquisition!$A$5:$E$387
Name P_A_Bdgt: A_Revenue_Income!$A$7:$N$490
Name P_A_Bdgt: C_Capital_Expenditure!$A$6:$O$63
Name P_A_Bdgt: C_Revenue_Expenditure!$A$4:$H$359
Name P_A_Bdgt: WO_Work20_SC!$A$3:$Q$144
Name P_A_C_Ex: #REF!
Name P_A_C01: #REF!
Name P_A_C02: C_Revenue_Income!$A$7:$N$62
Name P_A_C02A: #REF!
Name P_A_C03: C_Revenue_Expenditure!$A$4:$H$359
Name P_A_C05: #REF!
Name P_A_C07: C_Capital_Expenditure!$A$6:$O$63
Name P_A_Doller_MC: #REF!,#REF!,#REF!
Name P_A_Doller_SC: #REF!,#REF!,#REF!
Name P_A_dvdr: #REF!
Name P_A_Fnl_Rec: #REF!
Name P_A_Info: #REF!

Sheet A_Revenue_Income
A1: जमेचा | G1: तपशील
A2: विवरण | C2: नक्की आकडा | H2: 2019-20 वर्षाचा अंदाज | J2: 2020-21 वर्षाचा अंदाज | M2: 2019-20 वर्षाच्या मान्य अंदाजाशी तुलना केलेला 2020-21 वर्षाचा मा. स्थायी समितीने मान्यता दिलेला अंदाज
C3: 2016-17 | D3: 2017-18 | E3: 2018-19 | F3: 2018-19 शेवटची सहामाही | G3: 2019-20 पहिली सहामाही | H3: मान्य अंदाज | I3: दुरूस्त अंदाज | J3: मा. महापालिका आयुक्त यांनी सुचविलेला | K3: मा. स्थायी समितीने मान्यता दिलेला | L3: मा. महानगर- पालिकेने संमत केलेला
M5: अधिक | N5: कमी
A7: अधिनियमाप्रमाणे कमीत कमी रोख शिल्लक ठेवण्याची रक्कम जमेस धरून वर्षारंभीची शिल्लक | C7: 100000 | D7: 100000 | E7: 100000 | F7: 100000 | G7: 0 | H7: 100000 | I7: 100000 | J7: 100000 | K7: 100000 | L7: 0 | M7: 0 | N7: 0
C8: 0 | D8: 0 | E8: 0 | F8: 0 | G8: 0 | H8: 0 | I8: 0 | J8: 0 | K8: 0 | L8: 0 | M8: 0 | N8: 0
A9: १. सर्वसाधारण कर, अप्रत्यक्ष कर व इतर जमा | C9: 0 | D9: 0 | E9: 0 | F9: 0 | G9: 0 | H9: 0 | I9: 0 | J9: 0 | K9: 0 | L9: 0 | M9: 0 | N9: 0
A10: क. सर्वसाधारण पट्टी | C10: 0 | D10: 0 | E10: 0 | F10: 0 | G10: 0 | H10: 0 | I10: 0 | J10: 0 | K10: 0 | L10: 0 | M10: 0 | N10: 0
A11: १. नागरिकांकडून (कआकसंप्र) | B11: RI11A101 | C11: 3579419675 | D11: 3311564173 | E11: 3361147014 | F11: 942374982 | G11: 2536000928 | H11: 5790000000 | I11: 5790000000 | J11: 8050000000 | K11: 8050000000 | L11: 0 | M11: 2260000000 | N11: 0
A12: लोहगाव (उर्वरित) | B12: RI11AA101 | C12: 0 | D12: 6685 | E12: 37675 | F12: 11400 | G12: 214260 | H12: 80000000 | I12: 80000000 | J12: 0 | K12: 0 | L12: 0 | M12: 0 | N12: 80000000
A13: मुंढवा (उर्वरित केशवनगर) | B13: RI11AB101 | C13: 0 | D13: 2930 | E13: 8185 | F13: 1450 | G13: 389885 | H13: 40000000 | I13: 40000000 | J13: 0 | K13: 0 | L13: 0 | M13: 0 | N13: 40000000
A14: हडपसर (संपूर्ण साडेसतरानळी) | B14: RI11AC101 | C14: 0 | D14: 865 | E14: 3735 | F14: 1250 | G14: 150 | H14: 150000000 | I14: 150000000 | J14: 0 | K14: 0 | L14: 0 | M14: 0 | N14: 150000000
A15: शिवणे (संपूर्ण उत्तमनगर) | B15: RI11AD101 | C15: 0 | D15: 295 | E15: 13465 | F15: 2765 | G15: 141865 | H15: 10000000 | I15: 10000000 | J15: 0 | K15: 0 | L15: 0 | M15: 0 | N15: 10000000
A16: शिवणे | B16: RI11AE101 | C16: 0 | D16: 0 | E16: 9565 | F16: 4425 | G16: 1127870 | H16: 50000000 | I16: 50000000 | J16: 0 | K16: 0 | L16: 0 | M16: 0 | N16: 50000000
A17: आंबेगाव खुर्द | B17: RI11AF101 | C17: 0 | D17: 4070 | E17: 6810 | F17: 1890 | G17: 872045 | H17: 40000000 | I17: 40000000 | J17: 0 | K17: 0 | L17: 0 | M17: 0 | N17: 40000000
A18: उंड्री | B18: RI11AG101 | C18: 0 | D18: 3145 | E18: 3755 | F18: 2370 | G18: 220900 | H18: 40000000 | I18: 40000000 | J18: 0 | K18: 0 | L18: 0 | M18: 0 | N18: 40000000
A19: धायरी | B19: RI11AH101 | C19: 0 | D19: 1460 | E19: 32565 | F19: 4570 | G19: 21470 | H19: 60000000 | I19: 60000000 | J19: 0 | K19: 0 | L19: 0 | M19: 0 | N19: 60000000
A20: आंबेगाव बुद्रुक | B20: RI11AJ101 | C20: 0 | D20: 19000 | E20: 19645 | F20: 5320 | G20: 1014975 | H20: 80000000 | I20: 80000000 | J20: 0 | K20: 0 | L20: 0 | M20: 0 | N20: 80000000
A21: फुरसुंगी | B21: RI11AK101 | C21: 0 | D21: 31460 | E21: 110450 | F21: 32485 | G21: 512980 | H21: 100000000 | I21: 100000000 | J21: 0 | K21: 0 | L21: 0 | M21: 0 | N21: 100000000
A22: उरुळी देवाची | B22: RI11AL101 | C22: 0 | D22: 15030 | E22: 33235 | F22: 14385 | G22: 38190 | H22: 40000000 | I22: 40000000 | J22: 0 | K22: 0 | L22: 0 | M22: 0 | N22: 40000000
... A26: ५. मिळकतकर थकबाकी वसुली (कआकसंप्र) | B26: RI11A106 | C26: 0 | D26: 0 | E26: 0 | F26: 0 | G26: 0 | H26: 2000000000 | I26: 2000000000 | J26: 0 | K26: 3500000000 | L26: 0 | M26: 1500000000 | N26: 0
C27: 0 | D27: 0 | E27: 0 | F27: 0 | G27: 0 | H27: 0 | I27: 0 | J27: 0 | K27: 0 | L27: 0 | M27: 0 | N27: 0
A28: क. सर्वसाधारण कर बेरीज | C28: 3814921689 | D28: 3431242459 | E28: 3525303066 | F28: 994425018 | G28: 2681682415 | H28: 8630000000 | I28: 8630000000 | J28: 8207800000 | K28: 11707800000 | L28: 0 | M28: 3077800000 | N28: 0
C29: 0 | D29: 0 | E29: 0 | F29: 0 | G29: 0 | H29: 0 | I29: 0 | J29: 0 | K29: 0 | L29: 0 | M29: 0 | N29: 0
A30: ख. आयातकर | C30: 0 | D30: 0 | E30: 0 | F30: 0 | G30: 0 | H30: 0 | I30: 0 | J30: 0 | K30: 0 | L30: 0 | M30: 0 | N30: 0
A31: १. पक्की जमा (आ.क.प्र.) | B31: RI11B101 | C31: -10809081 | D31: 0 | E31: -5618500 | F31: 0 | G31: 0 | H31: 0 | I31: 0 | J31: 0 | K31: 0 | L31: 0 | M31: 0 | N31: 0
C32: 0 | D32: 0 | E32: 0 | F32: 0 | G32: 0 | H32: 0 | I32: 0 | J32: 0 | K32: 0 | L32: 0 | M32: 0 | N32: 0
A33: ख. निव्वळ आयातकर एकूण बेरीज | C33: -10809081 | D33: 0 | E33: -5618500 | F33: 0 | G33: 0 | H33: 0 | I33: 0 | J33: 0 | K33: 0 | L33: 0 | M33: 0 | N33: 0
C34: 0 | D34: 0 | E34: 0 | F34: 0 | G34: 0 | H34: 0 | I34: 0 | J34: 0 | K34: 0 | L34: 0 | M34: 0 | N34: 0
A35: ख-१. स्थानिक संस्था कर | C35: 0 | D35: 0 | E35: 0 | F35: 0 | G35: 0 | H35: 0 | I35: 0 | J35: 0 | K35: 0 | L35: 0 | M35: 0 | N35: 0
A36: स्थानिक संस्था कर नोंदणी शुल्क | B36: RI11B201 | C36: -3033323 | D36: 489206 | E36: 300 | F36: 0 | G36: 0 | H36: 0 | I36: 0 | J36: 0 | K36: 0 | L36: 0 | M36: 0 | N36: 0
A37: स्थानिक संस्था कर | B37: RI11B202 | C37: 3919870123 | D37: 1514559653 | E37: 14074585 | F37: 3253814 | G37: 659630 | H37: 10000000 | I37: 10000000 | J37: 10000000 | K37: 10000000 | L37: 0 | M37: 0 | N37: 0
A38: चौरस मीटर बांधकामाप्रमाणे भरावयाची ठोक रक्कम | B38: RI11B202B | C38: 152493815 | D38: 87144478 | E38: 3832035 | F38: 2115948 | G38: 3179873 | H38: 1000000 | I38: 1000000 | J38: 100000 | K38: 100000 | L38: 0 | M38: 0 | N38: 900000
A39: निर्गत मालापोटी १० % हिस्सा | B39: RI11B202D | C39: 6045544 | D39: 1498056 | E39: 0 | F39: 0 | G39: 0 | H39: 0 | I39: 0 | J39: 0 | K39: 0 | L39: 0 | M39: 0 | N39: 0
A40: इतर जमा - स्थानिक संस्था कर | B40: RI11B202E | C40: 76000 | D40: 0 | E40: 25232 | F40: 0 | G40: 0 | H40: 1000 | I40: 1000 | J40: 0 | K40: 0 | L40: 0 | M40: 0 | N40: 1000
A41: स्थानिक संस्था करापोटी व्याज | B41: RI11B203 | C41: 17179218 | D41: 24745902 | E41: 6911393 | F41: -216938 | G41: 452870 | H41: 500000 | I41: 500000 | J41: 1400000 | K41: 1400000 | L41: 0 | M41: 900000 | N41: 0
A42: स्थानिक संस्था कर शास्ती (दंड) | B42: RI11B204 | C42: 2020670 | D42: 295000 | E42: 80000 | F42: 40000 | G42: 0 | H42: 0 | I42: 0 | J42: 0 | K42: 0 | L42: 0 | M42: 0 | N42: 0
A43: राज्य शासनाकडून मुद्रांक शुल्क अधिभारापोटी मिळालेली रक्कम (१%) | B43: RI11B206 | C43: 2194142347 | D43: 1769515876 | E43: 2758200420 | F43: 2051760336 | G43: 512940084 | H43: 2000000000 | I43: 2000000000 | J43: 2500000000 | K43: 2500000000 | L43: 0 | M43: 500000000 | N43: 0
A44: मनपा ठेकेदारांच्या बिलांमधून एल.बी.टी. वसुली | B44: RI11B207 | C44: 11186427 | D44: 3161206 | E44: 92301 | F44: 51487 | G44: 87 | H44: 0 | I44: 0 | J44: 0 | K44: 0 | L44: 0 | M44: 0 | N44: 0
A45: राज्यशासनाकडून एल.बी.टी.साठी सहाय्यक अनुदान | B45: RI11B208 | C45: 7646900000 | D45: 4285500000 | E45: 0 | F45: 0 | G45: 0 | H45: 0 | I45: 0 | J45: 0 | K45: 0 | L45: 0 | M45: 0 | N45: 0
C46: 0 | D46: 0 | E46: 0 | F46: 0 | G46: 0 | H46: 0 | I46: 0 | J46: 0 | K46: 0 | L46: 0 | M46: 0 | N46: 0
A47: ख-१. स्थानिक संस्था कर बेरीज | C47: 13946880821 | D47: 7686909377 | E47: 2783216266 | F47: 2057004647 | G47: 517232544 | H47: 2011501000 | I47: 2011501000 | J47: 2511500000 | K47: 2511500000 | L47: 0 | M47: 499999000 | N47: 0
C48: 0 | D48: 0 | E48: 0 | F48: 0 | G48: 0 | H48: 0 | I48: 0 | J48: 0 | K48: 0 | L48: 0 | M48: 0 | N48: 0
A49: वजा :- स्थानिक संस्था कर रिफंड | B49: RI11B251 | C49: 0 | D49: 0 | E49: 24998 | F49: 49996 | G49: -17276886 | H49: 20000000 | I49: 20000000 | J49: 120000000 | K49: 120000000 | L49: 0 | M49: 100000000 | N49: 0
C50: 0 | D50: 0 | E50: 0 | F50: 0 | G50: 0 | H50: 0 | I50: 0 | J50: 0 | K50: 0 | L50: 0 | M50: 0 | N50: 0
A51: ख-१. स्थानिक संस्था कर एकूण बेरीज | C51: 13946880821 | D51: 7686909377 | E51: 2783191268 | F51: 2056954651 | G51: 534509430 | H51: 1991501000 | I51: 1991501000 | J51: 2391500000 | K51: 2391500000 | L51: 0 | M51: 399999000 | N51: 0
C52: 0 | D52: 0 | E52: 0 | F52: 0 | G52: 0 | H52: 0 | I52: 0 | J52: 0 | K52: 0 | L52: 0 | M52: 0 | N52: 0
A53: राज्यशासनाकडून महाराष्ट्र वस्तू व सेवा कर अंतर्गत अनुदान (GST) | B53: RI11B209 | C53: 0 | D53: 10984000000 | E53: 15728200000 | F53: 7864600000 | G53: 8512800000 | H53: 18010000000 | I53: 18010000000 | J53: 18387600000 | K53: 18387600000 | L53: 0 | M53: 377600000 | N53: 0
A54: ग. इतर कर | C54: 0 | D54: 0 | E54: 0 | F54: 0 | G54: 0 | H54: 0 | I54: 0 | J54: 0 | K54: 0 | L54: 0 | M54: 0 | N54: 0
A55: १. करमणूककर (कआकसंप्र) | B55: RI11C101 | C55: 14975320 | D55: 16637835 | E55: 18144020 | F55: 10959890 | G55: 7874450 | H55: 22500000 | I55: 22500000 | J55: 22500000 | K55: 22500000 | L55: 0 | M55: 0 | N55: 0
A56: २. व्यवसायकर (कआकसंप्र) शासनाकडून व्यवसाय करापोटी मिळणारी नुकसान भरपाई | B56: RI11C102 | C56: 0 | D56: 0 | E56: 0 | F56: 0 | G56: 0 | H56: 2300000 | I56: 2300000 | J56: 3500000 | K56: 3500000 | L56: 0 | M56: 1200000 | N56: 0
A57: ३. राज्य शासनाने बसविलेल्या करमणूककरापोटी मिळणारा हिस्सा (शासनाकडून) (कआकसंप्र) | B57: RI11C103 | C57: 0 | D57: 0 | E57: 0 | F57: 0 | G57: 0 | H57: 20000000 | I57: 20000000 | J57: 20000000 | K57: 20000000 | L57: 0 | M57: 0 | N57: 0
C58: 0 | D58: 0 | E58: 0 | F58: 0 | G58: 0 | H58: 0 | I58: 0 | J58: 0 | K58: 0 | L58: 0 | M58: 0 | N58: 0
A59: ग. बेरीज | C59: 14975320 | D59: 16637835 | E59: 18144020 | F59: 10959890 | G59: 7874450 | H59: 44800000 | I59: 44800000 | J59: 46000000 | K59: 46000000 | L59: 0 | M59: 1200000 | N59: 0
C60: 0 | D60: 0 | E60: 0 | F60: 0 | G60: 0 | H60: 0 | I60: 0 | J60: 0 | K60: 0 | L60: 0 | M60: 0 | N60: 0
A61: घ. महानगरपालिका अधिनियमाखाली दंडाबाबत शासकीय सहाय्य (वि. सल्लागार) | B61: RI11D101 | C61: 1398273 | D61: 1321170 | E61: 733050 | F61: 733050 | G61: 0 | H61: 0 | I61: 0 | J61: 0 | K61: 0 | L61: 0 | M61: 0 | N61: 0
C62: 0 | D62: 0 | E62: 0 | F62: 0 | G62: 0 | H62: 0 | I62: 0 | J62: 0 | K62: 0 | L62: 0 | M62: 0 | N62: 0
A63: ड-१ गुंतविलेल्या रकमांवरील व्याज (मु.ले.) | B63: RI11E101 | C63: 1136681699 | D63: 1089426825 | E63: 1622335365 | F63: 1396765594 | G63: 304699392 | H63: 1000000000 | I63: 1000000000 | J63: 911000000 | K63: 921100000 | L63: 0 | M63: 0 | N63: 78900000
A64: ड-३ विविध खात्यांच्या ऑडिट अहवालातून वसुली | B64: RI11E107 | C64: 769540 | D64: 1913151 | E64: 710465 | F64: 423184 | G64: 248769 | H64: 2000000 | I64: 2000000 | J64: 2000000 | K64: 2000000 | L64: 0 | M64: 0 | N64: 0
A65: पुणे महानगरपालिकेस बक्षिसापोटी मिळालेल्या रकमा | B65: RI11E122 | C65: 0 | D65: 0 | E65: 0 | F65: 0 | G65: 0 | H65: 500000 | I65: 500000 | J65: 500000 | K65: 500000 | L65: 0 | M65: 0 | N65: 0
A66: सेवकांसाठी सेवापुस्तक शुल्क | B66: RI11E123 | C66: 1860 | D66: 8095 | E66: 8405 | F66: 8285 | G66: 2160 | H66: 0 | I66: 0 | J66: 0 | K66: 0 | L66: 0 | M66: 0 | N66: 0
A67: पुणे मनपाच्या हद्दीत नव्याने समाविष्ट झालेल्या 11 गावातील इतर जमा (मु.ले.) | B67: RI11E124 | C67: 0 | D67: 54205641 | E67: 99689170 | F67: 99689170 | G67: 2078 | H67: 0 | I67: 0 | J67: 0 | K67: 0 | L67: 0 | M67: 0 | N67: 0
C68: 0 | D68: 0 | E68: 0 | F68: 0 | G68: 0 | H68: 0 | I68: 0 | J68: 0 | K68: 0 | L68: 0 | M68: 0 | N68: 0
A69: ज. इतर जमा | C69: 0 | D69: 0 | E69: 0 | F69: 0 | G69: 0 | H69: 0 | I69: 0 | J69: 0 | K69: 0 | L69: 0 | M69: 0 | N69: 0
A70: ज१. जुनी रद्दी विक्री (मसआ.जिंघ.) | B70: RI11H101 | C70: 336827 | D70: 0 | E70: 191635 | F70: 191075 | G70: 21135 | H70: 500000 | I70: 500000 | J70: 500000 | K70: 500000 | L70: 0 | M70: 0 | N70: 0
C71: 0 | D71: 0 | E71: 0 | F71: 0 | G71: 0 | H71: 0 | I71: 0 | J71: 0 | K71: 0 | L71: 0 | M71: 0 | N71: 0
A72: ज२. शुल्काचे उत्पन्न | C72: 0 | D72: 0 | E72: 0 | F72: 0 | G72: 0 | H72: 0 | I72: 0 | J72: 0 | K72: 0 | L72: 0 | M72: 0 | N72: 0
A73: अ. मसुदा शुल्क (वि. सल्लागार) | B73: RI11H102A | C73: 4911565 | D73: 4450136 | E73: 5721837 | F73: 4353754 | G73: 1959511 | H73: 10000000 | I73: 10000000 | J73: 10000000 | K73: 10000000 | L73: 0 | M73: 0 | N73: 0
A74: ब. दाव्याचा खर्च व प्रोसेस शुल्क (वि. सल्लागार) | B74: RI11H102B | C74: 0 | D74: 350 | E74: 7750 | F74: 6700 | G74: 0 | H74: 200000 | I74: 200000 | J74: 200000 | K74: 200000 | L74: 0 | M74: 0 | N74: 0
A75: क. नक्कल शुल्क (झोनिपु) | B75: RI11H102C | C75: 176631 | D75: 141998 | E75: 103721 | F75: 53864 | G75: 38570 | H75: 300000 | I75: 300000 | J75: 300000 | K75: 300000 | L75: 0 | M75: 0 | N75: 0
A76: ड. अधिपत्र (Warrant) शुल्क (कआकसंप्र) | B76: RI11H102D | C76: 14083529 | D76: 10440743 | E76: 11012968 | F76: 7872811 | G76: 2816785 | H76: 20000000 | I76: 20000000 | J76: 20000000 | K76: 20000000 | L76: 0 | M76: 0 | N76: 0
A77: ई. सूचनापत्र (Notice) शुल्क (कआकसंप्र) | B77: RI11H102E | C77: 4355036 | D77: 989585 | E77: 995201 | F77: 678281 | G77: 252526 | H77: 0 | I77: 0 | J77: 500000 | K77: 500000 | L77: 0 | M77: 500000 | N77: 0
A78: फ. मिळकतीच्या मालकी हक्काबद्दल शुल्क (कआकसंप्र) | B78: RI11H102F | C78: 69135530 | D78: 77588900 | E78: 129719220 | F78: 56592195 | G78: 40969645 | H78: 80000000 | I78: 80000000 | J78: 85000000 | K78: 85000000 | L78: 0 | M78: 5000000 | N78: 0
A79: ग. मिळकतकर थकबाकी शास्ती (२%) (कआकसंप्र) | B79: RI11H102G | C79: 712193608 | D79: 556106175 | E79: 772687238 | F79: 533877605 | G79: 254032139 | H79: 1300000000 | I79: 1300000000 | J79: 1530000000 | K79: 1530000000 | L79: 0 | M79: 230000000 | N79: 0
C80: 0 | D80: 0 | E80: 0 | F80: 0 | G80: 0 | H80: 0 | I80: 0 | J80: 0 | K80: 0 | L80: 0 | M80: 0 | N80: 0
A81: ज२. बेरीज | C81: 804855899 | D81: 649717887 | E81: 920247935 | F81: 603435210 | G81: 300069176 | H81: 1410500000 | I81: 1410500000 | J81: 1646000000 | K81: 1646000000 | L81: 0 | M81: 235500000 | N81: 0
C82: 0 | D82: 0 | E82: 0 | F82: 0 | G82: 0 | H82: 0 | I82: 0 | J82: 0 | K82: 0 | L82: 0 | M82: 0 | N82: 0
A83: ज३. किरकोळ जमा | C83: 0 | D83: 0 | E83: 0 | F83: 0 | G83: 0 | H83: 0 | I83: 0 | J83: 0 | K83: 0 | L83: 0 | M83: 0 | N83: 0
A84: अ. न नेलेली व जप्त केलेली अनामत पक्की जमा (मु.ले.) | B84: RI11H103A | C84: 554926 | D84: 15736 | E84: 36948 | F84: 36948 | G84: 411521 | H84: 0 | I84: 0 | J84: 0 | K84: 0 | L84: 0 | M84: 0 | N84: 0
A85: क.१ मतदार याद्या विक्री (म.स.आ.) | B85: RI11H103C | C85: 1458419 | D85: 20547 | E85: 0 | F85: 0 | G85: 0 | H85: 15000 | I85: 15000 | J85: 15000 | K85: 15000 | L85: 0 | M85: 0 | N85: 0
A86: क.२ इतर किरकोळ जमा | B86: RI11H103D | C86: 45344 | D86: 5662 | E86: 6175 | F86: 500 | G86: 8436 | H86: 5000 | I86: 5000 | J86: 5000 | K86: 5000 | L86: 0 | M86: 0 | N86: 0
A87: ड. इतर खात्यांकडील पुस्तके, मॅन्युअल्स्‌, नकाशे इ. (मसआ.जिंघ.) | B87: RI11H103E | C87: 29362 | D87: 3434 | E87: 9497 | F87: 6907 | G87: 3495 | H87: 0 | I87: 0 | J87: 0 | K87: 0 | L87: 0 | M87: 0 | N87: 0
A88: ई. भांडार खात्याकडील जुने साहित्य विक्री (म.स.आ.) | B88: RI11H103F | C88: 11910838 | D88: 28131029 | E88: 1442300 | F88: 0 | G88: 1102256 | H88: 34000000 | I88: 34000000 | J88: 40000000 | K88: 40000000 | L88: 0 | M88: 6000000 | N88: 0
A89: छ. घरबांधणी कर्ज फॉर्म विक्री (मसआ.जिंघ.) | B89: RI11H103K | C89: 1500 | D89: 2925 | E89: 3100 | F89: 3100 | G89: 700 | H89: 0 | I89: 0 | J89: 0 | K89: 0 | L89: 0 | M89: 0 | N89: 0
A90: सेवकवर्ग विभाग इतर जमा | B90: RI11H103N | C90: 2486592 | D90: 1756 | E90: 40640 | F90: 1990 | G90: 7400 | H90: 2500000 | I90: 2500000 | J90: 2000000 | K90: 2000000 | L90: 0 | M90: 0 | N90: 500000
A91: सुरक्षा विभाग इतर जमा | B91: RI11H103P | C91: 30869 | D91: 12456 | E91: 117856 | F91: 94918 | G91: 0 | H91: 0 | I91: 0 | J91: 0 | K91: 0 | L91: 0 | M91: 0 | N91: 0
A92: महाराष्ट्र माहितीचा अधिकार अधिनियम | B92: RI11H103R | C92: 662909 | D92: 508187 | E92: 761562 | F92: 564205 | G92: 260083 | H92: 500000 | I92: 500000 | J92: 2000 | K92: 2000 | L92: 0 | M92: 0 | N92: 498000
A93: CFC अंतर्गत जमा होणारी रक्कम | B93: RI11H103S | C93: 1103375 | D93: 934036 | E93: 1515652 | F93: 611352 | G93: 483690 | H93: 0 | I93: 0 | J93: 0 | K93: 0 | L93: 0 | M93: 0 | N93: 0
C94: 0 | D94: 0 | E94: 0 | F94: 0 | G94: 0 | H94: 0 | I94: 0 | J94: 0 | K94: 0 | L94: 0 | M94: 0 | N94: 0
A95: ज३. बेरीज | C95: 18284134 | D95: 29635768 | E95: 3933730 | F95: 1319920 | G95: 2277581 | H95: 37020000 | I95: 37020000 | J95: 42022000 | K95: 42022000 | L95: 0 | M95: 5002000 | N95: 0
C96: 0 | D96: 0 | E96: 0 | F96: 0 | G96: 0 | H96: 0 | I96: 0 | J96: 0 | K96: 0 | L96: 0 | M96: 0 | N96: 0
A97: ज. इतर जमा एकूण बेरीज | C97: 823476860 | D97: 679353655 | E97: 924373300 | F97: 604946205 | G97: 302367892 | H97: 1448020000 | I97: 1448020000 | J97: 1688522000 | K97: 1688522000 | L97: 0 | M97: 240502000 | N97: 0
C98: 0 | D98: 0 | E98: 0 | F98: 0 | G98: 0 | H98: 0 | I98: 0 | J98: 0 | K98: 0 | L98: 0 | M98: 0 | N98: 0
A99: १. सर्वसाधारणकर, अप्रत्यक्षकर व इतर जमा एकूण बेरीज | C99: 19728296981 | D99: 23945018208 | E99: 24697069609 | F99: 13029505047 | G99: 12344186586 | H99: 31126821000 | I99: 31126821000 | J99: 31634922000 | K99: 35145022000 | L99: 0 | M99: 4018201000 | N99: 0
A100: २. प्राथमिक शिक्षण | C100: 0 | D100: 0 | E100: 0 | F100: 0 | G100: 0 | H100: 0 | I100: 0 | J100: 0 | K100: 0 | L100: 0 | M100: 0 | N100: 0
A101: शासकीय अनुदान - प्राथमिक शिक्षण | B101: RI12A101 | C101: 720924317 | D101: 815116563 | E101: 830367728 | F101: 396511805 | G101: 477114000 | H101: 850000000 | I101: 850000000 | J101: 1100000000 | K101: 1100000000 | L101: 0 | M101: 250000000 | N101: 0
A102: प्राथमिक शिक्षण विभाग – शाळा भाडे | B102: RI12A103 | C102: 92664 | D102: 925702 | E102: 4574741 | F102: 3742932 | G102: 1006430 | H102: 750000 | I102: 750000 | J102: 800000 | K102: 800000 | L102: 0 | M102: 50000 | N102: 0
A103: दंड, साक्षी, भत्ता इत्यादी | B103: RI12A104 | C103: 0 | D103: 0 | E103: 0 | F103: 0 | G103: 0 | H103: 0 | I103: 0 | J103: 10000 | K103: 10000 | L103: 0 | M103: 10000 | N103: 0
A104: बालवाडी शुल्क | B104: RI12A105 | C104: 0 | D104: 0 | E104: 0 | F104: 0 | G104: 0 | H104: 5000 | I104: 5000 | J104: 5000 | K104: 5000 | L104: 0 | M104: 0 | N104: 0
A105: इंग्रजी माध्यम फी | B105: RI12A107 | C105: 0 | D105: 0 | E105: 0 | F105: 0 | G105: 0 | H105: 200000 | I105: 200000 | J105: 150000 | K105: 150000 | L105: 0 | M105: 0 | N105: 50000
...

Sheet A_Revenue_Expenditure
A1: योजनेतर खर्च तपशील
A2: विवरण | D2: नक्‍की आकडा | G2: मान्य अंदाज 2019-20 | H2: नवीन अंदाज 2020-21
D3: 2016-17 | E3: 2017-18 | F3: 2018-19
A5: १. मुख्य देखरेख, वसुली वगैरे | D5: 0 | E5: 0 | F5: 0 | G5: 0 | H5: 0
A6: क. महानगरपालिका व स्थायी समिती | D6: 0 | E6: 0 | F6: 0 | G6: 0 | H6: 0
A7: १ नगरसचिव यांचे कार्यालय | D7: 0 | E7: 0 | F7: 0 | G7: 0 | H7: 0
A8: १. नगरसचिव (म्युनिसिपल सेक्रेटरी) (मुं.प्रां. मनपा अधिनियम, कलम४५(३) प्रमाणे) वेतन | B8: RE11A101A | D8: 1345488 | E8: 1142457 | F8: 1357957 | G8: 1500000 | H8: 1600000
A9: २. कायम सेवकवर्ग वेतन | B9: RE11A102A | D9: 38012640 | E9: 39568566 | F9: 38537287 | G9: 40000000 | H9: 42500000
A10: ३. संकीर्ण (न.स.) | B10: RE11A103 | D10: 5914622 | E10: 4393519 | F10: 4967904 | G10: 8000000 | H10: 7200000
A11: ३अ. मागील बिले देण्यासाठी (न.स.) | B11: RE11A103A | D11: 2128349 | E11: 3965718 | F11: 2886671 | G11: 3200000 | H11: 3600000
A12: ४. प्रवास खर्च (न.स.) | B12: RE11A104 | D12: 12586 | E12: 22316 | F12: 35207 | G12: 1600000 | H12: 1800000
A13: ५. ग्रंथालय व वाचनालय | B13: RE11A105 | D13: 179955 | E13: 196204 | F13: 172716 | G13: 200000 | H13: 225000
A14: ६. समारंभ खर्च (न.स. व वि.अ.) | B14: RE11A106 | D14: 0 | E14: 45760 | F14: 68200 | G14: 400000 | H14: 450000
A15: १०. अखिल भारतीय/महाराष्ट्र महापौर परिषद व अखिल भारतीय स्थानिक स्वराज्य संस्था प्रतिनिधी अधिवेशन | B15: RE11A110 | D15: 0 | E15: 0 | F15: 0 | G15: 160000 | H15: 270000
A16: ११. मनपा व शासकीय निवृत्त सेवकांना द्यावयाचा चहापान खर्च | B16: RE11A111 | D16: 780 | E16: 114450 | F16: 3000 | G16: 240000 | H16: 270000
A17: १३. महाराष्ट्र राज्य महानगरपालिका स्थायी समिती अध्यक्ष परिषद वर्गणी व तद्‌नुषंगिक खर्च | B17: RE11A113 | D17: 0 | E17: 0 | F17: 0 | G17: 800 | H17: 900
A18: १४. मा. महापौर यांचा व्ययनियमन (सम्प्च्युअरी) भत्ता | B18: RE11A114 | D18: 0 | E18: 0 | F18: 0 | G18: 4000 | H18: 4500
A19: १५. मा. महापौर यांचा ऐच्छिक खर्च | B19: RE11A115 | D19: 159775 | E19: 199238 | F19: 95427 | G19: 160000 | H19: 180000
... A50: नगरसचिव विभागामार्फत आवश्यक सेवक भरती करणे (कंत्राटी) | B50: RE11A280 | D50: 0 | E50: 0 | F50: 0 | G50: 0 | H50: 10000000
D51: 0 | E51: 0 | F51: 0 | G51: 0 | H51: 0
A52: क. मनपा व स्थायी समिती बेरीज | D52: 111232206 | E52: 109200819 | F52: 87211238 | G52: 143029200 | H52: 172230100
D53: 0 | E53: 0 | F53: 0 | G53: 0 | H53: 0
A54: ख. मुख्य लेखापरिक्षक यांचे कार्यालय | D54: 0 | E54: 0 | F54: 0 | G54: 0 | H54: 0
A55: १. मुख्य लेखापरिक्षक (म्युनिसिपल चीफ ऑडिटर) (मु.प्रां. मनपा अधिनियम, कलम ४५ (३) प्रमाणे) यांचे वेतन | B55: RE11B101A | D55: 1610523 | E55: 4018155 | F55: 2623589 | G55: 2500000 | H55: 2700000
A56: २. कायम सेवकवर्ग वेतन | B56: RE11B102A | D56: 27837708 | E56: 23877085 | F56: 29232284 | G56: 30000000 | H56: 30000000
A57: ३. संकीर्ण | B57: RE11B103 | D57: 53529 | E57: 109686 | F57: 115189 | G57: 240000 | H57: 225000
D58: 0 | E58: 0 | F58: 0 | G58: 0 | H58: 0
A59: ख. मुख्यलेखापरिक्षक यांचे कार्या. बेरीज | D59: 29501760 | E59: 28004926 | F59: 31971062 | G59: 32740000 | H59: 32925000
D60: 0 | E60: 0 | F60: 0 | G60: 0 | H60: 0
A61: ग१. महापालिका आयुक्त यांचे कार्यालय | D61: 0 | E61: 0 | F61: 0 | G61: 0 | H61: 0
A62: १. महापालिका आयुक्त (म्युनिसिपल कमिशनर) (मु. प्रां. मनपा अधिनियम, कलम ३७ (१) प्रमाणे) यांचे वेतन | B62: RE11C101A | D62: 2174568 | E62: 2633227 | F62: 2531394 | G62: 3000000 | H62: 3200000
A63: २. उपआयुक्त (जनरल) (मुं. प्रां. मनपा अधिनियम, कलम ४५(३) प्रमाणे) यांचे वेतन | B63: RE11C102A | D63: 558905 | E63: 610426 | F63: 1175614 | G63: 2200000 | H63: 2500000
A64: ३. कायम सेवकवर्ग वेतन | B64: RE11C103A | D64: 25487531 | E64: 28024193 | F64: 29549463 | G64: 30000000 | H64: 31000000
A65: ४. संकीर्ण | B65: RE11C104 | D65: 1172964 | E65: 1342954 | F65: 1356556 | G65: 1600000 | H65: 1800000
A66: ६. मा. महापालिका आयुक्त यांचा ऐच्छिक खर्च (म.स.आ.) | B66: RE11C106 | D66: 0 | E66: 14147 | F66: 50003 | G66: 800000 | H66: 720000
D67: 0 | E67: 0 | F67: 0 | G67: 0 | H67: 0
A68: ग१. महापालिका आयुक्त कार्यालय बेरीज | D68: 29393968 | E68: 32624947 | F68: 34663030 | G68: 37600000 | H68: 39220000
A69: ग२. अतिरिक्त महापालिका आयुक्त (विशेष) यांचे कार्यालय | D69: 0 | E69: 0 | F69: 0 | G69: 0 | H69: 0
A70: १. अतिरिक्त महापालिका आयुक्त (विशेष) यांचे वेतन | B70: RE11C126A | D70: 1172527 | E70: 1012344 | F70: 2041368 | G70: 3000000 | H70: 3200000
A71: २. कायम सेवकवर्ग वेतन | B71: RE11C127A | D71: 12260312 | E71: 12079222 | F71: 13598908 | G71: 15000000 | H71: 15000000
A72: ३. संकीर्ण | B72: RE11C128 | D72: 187547 | E72: 101682 | F72: 295033 | G72: 600000 | H72: 720000
A73: ४. मनपा सेवकांस विविध सेमिनर, कॉन्फरन्स, प्रशिक्षण इ. साठी हजर राहण्यासाठी खर्च | B73: RE11C129 | D73: 17191 | E73: 21737 | F73: 33097 | G73: 340000 | H73: 270000
A74: 5. अतिरिक्त महापालिका आयुक्त (विशेष) यांचेकडे येणार्‍या पाहुण्यांचा आतिथ्याकरिता होणारा खर्च | B74: RE11C129C | D74: 14310 | E74: 12368 | F74: 9570 | G74: 240000 | H74: 270000
A75: ग२. अतिरिक्त महापालिका आयुक्त (विशेष) यांचे कार्यालय बेरीज | D75: 13651887 | E75: 13227353 | F75: 15977976 | G75: 19180000 | H75: 19460000
D76: 0 | E76: 0 | F76: 0 | G76: 0 | H76: 0
A77: ग३. अतिरिक्त महापालिका आयुक्त (जनरल) यांचे कार्यालय | D77: 0 | E77: 0 | F77: 0 | G77: 0 | H77: 0
A78: १. मा. अतिरिक्त महापालिका आयुक्त (जनरल) यांचे वेतन | B78: RE11C131A | D78: 1017661 | E78: 722990 | F78: 570358 | G78: 3000000 | H78: 3200000
A79: २. कायम सेवकवर्ग वेतन | B79: RE11C132A | D79: 9750326 | E79: 12644018 | F79: 11585239 | G79: 15000000 | H79: 15000000
A80: ३. संकीर्ण | B80: RE11C133 | D80: 109248 | E80: 194999 | F80: 169434 | G80: 640000 | H80: 720000
A81: ४.अतिरिक्त महापालिका आयुक्त (जनरल) यांचेकडे येणार्‍या पाहुण्यांचा आतिथ्याकरिता होणारा खर्च | B81: RE11C134 | D81: 14516 | E81: 7999 | F81: 4633 | G81: 160000 | H81: 270000
A82: ५. अधिकारी / सेवक प्रशिक्षण वर्ग / कार्यशाळेस उपस्थित राहण्याचा प्रवासखर्च, कार्यशाळा शुल्क, प्रशिक्षण शुल्क वगैरे | B82: RE11C135 | D82: 0 | E82: 0 | F82: 66363 | G82: 240000 | H82: 270000
D83: 0 | E83: 0 | F83: 0 | G83: 0 | H83: 0
A84: ग३. अतिरिक्त महापालिका आयुक्त (जनरल) यांचे कार्यालय बेरीज | D84: 10891751 | E84: 13570006 | F84: 12396027 | G84: 19040000 | H84: 19460000
D85: 0 | E85: 0 | F85: 0 | G85: 0 | H85: 0
A86: ग४. अतिरिक्त महापालिका आयुक्त (इस्टेट) यांचे कार्यालय | D86: 0 | E86: 0 | F86: 0 | G86: 0 | H86: 0
A87: १. मा. अतिरिक्त महापालिका आयुक्त (इस्टेट) यांचे वेतन | B87: RE11C141 | D87: 1303409 | E87: 295904 | F87: 881779 | G87: 3000000 | H87: 3200000
A88: २. कायम सेवकवर्ग वेतन | B88: RE11C142 | D88: 11057473 | E88: 9284889 | F88: 7129521 | G88: 12500000 | H88: 8000000
A89: ३. संकीर्ण | B89: RE11C143 | D89: 194543 | E89: 90845 | F89: 418716 | G89: 600000 | H89: 720000
A90: ४.अतिरिक्त महापालिका आयुक्त (इस्टेट) यांचेकडे येणार्‍या पाहुण्यांचा आतिथ्याकरिता होणारा खर्च | B90: RE11C144 | D90: 4300 | E90: 0 | F90: 0 | G90: 152000 | H90: 270000
A91: 6. प्रशिक्षण वर्ग / कार्यशाळेस उपस्थित राहण्याचा प्रवासखर्च | B91: RE11C146 | D91: 0 | E91: 0 | F91: 167071 | G91: 224000 | H91: 270000
A92: ग४. अतिरिक्त महापालिका आयुक्त (इस्टेट) यांचे कार्यालय बेरीज | D92: 12559725 | E92: 9671638 | F92: 8597087 | G92: 16476000 | H92: 12460000
A93: ग५. दक्षता विभाग | D93: 0 | E93: 0 | F93: 0 | G93: 0 | H93: 0
A94: १. कायम सेवकवर्ग वेतन | B94: RE11C151 | D94: 9876040 | E94: 10884531 | F94: 9473049 | G94: 12500000 | H94: 12500000
A95: २. संकीर्ण | B95: RE11C152 | D95: 69450 | E95: 0 | F95: 79462 | G95: 200000 | H95: 180000
A96: ग५. दक्षता विभाग बेरीज | D96: 9945490 | E96: 10884531 | F96: 9552511 | G96: 12700000 | H96: 12680000
D97: 0 | E97: 0 | F97: 0 | G97: 0 | H97: 0
A98: ग१+ग२+ग३+ग४+ग५ एकूण बेरीज | D98: 76442821 | E98: 79978475 | F98: 81186631 | G98: 104996000 | H98: 103280000
D99: 0 | E99: 0 | F99: 0 | G99: 0 | H99: 0
A100: घ१. उपआयुक्त (विशेष) यांचे कार्यालय | D100: 0 | E100: 0 | F100: 0 | G100: 0 | H100: 0
A101: १. उपआयुक्त (विशेष) (मुं. प्रां. मनपा अधिनियम, कलम ४५(३) प्रमाणे) यांचे वेतन | B101: RE11D101A | D101: 487765 | E101: 0 | F101: 0 | G101: 2200000 | H101: 2500000
A102: २. कायम सेवकवर्ग वेतन | B102: RE11D102A | D102: 6473172 | E102: 7388195 | F102: 8214909 | G102: 7500000 | H102: 8500000
A103: ३. संकीर्ण | B103: RE11D103 | D103: 99567 | E103: 37222 | F103: 31644 | G103: 120000 | H103: 135000
D104: 0 | E104: 0 | F104: 0 | G104: 0 | H104: 0
A105: घ१. उपआयुक्त (विशेष) कार्यालय बेरीज | D105: 7060504 | E105: 7425417 | F105: 8246553 | G105: 9820000 | H105: 11135000
A106: मुख्य समन्वयक कार्यालय (Smart City व AMRUT योजना) | D106: 0 | E106: 0 | F106: 0 | G106: 0 | H106: 0
A107: 1. संकीर्ण | B107: RE11D111 | D107: 1332134 | E107: 0 | F107: 0 | G107: 1200000 | H107: 0
D108: 0 | E108: 0 | F108: 0 | G108: 0 | H108: 0
A109: मुख्य समन्वयक कार्यालय (Smart City व AMRUT योजना) कार्यालय बेरीज | D109: 1332134 | E109: 0 | F109: 0 | G109: 1200000 | H109: 0
D110: 0 | E110: 0 | F110: 0 | G110: 0 | H110: 0
A111: घ२. सेवकवर्ग विभाग | D111: 0 | E111: 0 | F111: 0 | G111: 0 | H111: 0
A112: १. कायम सेवकवर्ग वेतन | B112: RE11D126A | D112: 24996357 | E112: 28475728 | F112: 30921722 | G112: 30000000 | H112: 34500000
A113: २. संकीर्ण | B113: RE11D127 | D113: 352110 | E113: 281198 | F113: 214222 | G113: 560000 | H113: 540000
A114: ४. विविध रिक्त पदे भरण्यासाठी आयोजित करण्यात येणार्‍या परीक्षांसाठी खर्च | B114: RE11D127B | D114: 0 | E114: 841876 | F114: 0 | G114: 0 | H114: 0
A115: ५. प्रशिक्षण प्रबोधिनीसाठी फर्निचर व तद्‌नुषंगिक कामे करणे व साहित्य घेणे | B115: RE11D127C | D115: 0 | E115: 0 | F115: 55555 | G115: 800000 | H115: 792000
A116: ६. अधिकारी / कर्मचार्‍यांसाठी प्रशिक्षण आयोजन करणेसाठी खर्च | B116: RE11D127D | D116: 762802 | E116: 81944 | F116: 138226 | G116: 2400000 | H116: 2376000
A117: ७. पुणे मनपामध्ये बायोमॅट्रिक अटेंडन्स प्रणाली कार्यान्वीत करणे | B117: RE11D127E | D117: 0 | E117: 456000 | F117: 0 | G117: 4000000 | H117: 3600000
A118: ८. सेवकवर्ग विभागासाठी फर्निचर करणे | B118: RE11D127F | D118: 0 | E118: 8024 | F118: 0 | G118: 800000 | H118: 720000
A119: नगरसेवकांसाठी नागरिक समस्या सोडविण्यासाठी प्रशिक्षण वर्ग | B119: RE11D127G | D119: 0 | E119: 0 | F119: 0 | G119: 800000 | H119: 0
A120: समाविष्ट गावांतील सेवकांच्या वेतनासाठी | B120: RE11D127H | D120: 0 | E120: 0 | F120: 66257402 | G120: 180000000 | H120: 16600000
A121: शताब्दी वर्षानिमित्त श्री शिवाजी मराठा सोसायटी, पुणे यांना देणगी (देणगी विभाग) | B121: RE11D127J | D121: 0 | E121: 0 | F121: 0 | G121: 0 | H121: 5000000
A122: मनपा पदाधिकारी, अधिकारी, नगरसेवक, कर्मचारी यांना प्रशिक्षणासाठी वसंतराव भागवत प्रबोधिनी स्थापन करणे. | B122: RE11D127K | D122: 0 | E122: 0 | F122: 299000 | G122: 4000000 | H122: 4000000
D123: 0 | E123: 0 | F123: 0 | G123: 0 | H123: 0
A124: घ२. सेवकवर्ग विभाग बेरीज | D124: 26111269 | E124: 30144770 | F124: 97886127 | G124: 223360000 | H124: 68128000
D125: 0 | E125: 0 | F125: 0 | G125: 0 | H125: 0
A126: घ२अ. सेवाभरती व परीक्षा नियंत्रण विभाग | D126: 0 | E126: 0 | F126: 0 | G126: 0 | H126: 0
A127: १. कायम सेवकवर्ग वेतन | B127: RE11D151 | D127: 0 | E127: 0 | F127: 0 | G127: 7000000 | H127: 2500000
A128: 3. विविध रिक्त पदे भरण्यासाठी आयोजित करण्यात येणार्‍या परीक्षांसाठी खर्च | B128: RE11D153 | D128: 160799 | E128: 0 | F128: 0 | G128: 2400000 | H128: 2376000
D129: 0 | E129: 0 | F129: 0 | G129: 0 | H129: 0
A130: घ२अ. सेवाभरती व परीक्षा नियंत्रण विभाग बेरीज | D130: 160799 | E130: 0 | F130: 0 | G130: 9400000 | H130: 4876000
D131: 0 | E131: 0 | F131: 0 | G131: 0 | H131: 0
...

Sheet A_Revenue_List
A2: यादी क्र. R1
A3: थोर व्यक्तींच्या जयंती / पुण्यतिथी साजरी करणे (यादी R1)
A4: RE11A274/R1-
A6: क्र. | B6: code | C6: ward | D6: कामाचे नाव | E6: प्रकल्पीय रक्कम | F6: तरतूद
A8: 1 | B8: RE11A274/R1-1 | D8: महात्मा फुले जयंती | F8: 100000
A9: 2 | B9: RE11A274/R1-2 | D9: डॉ. बाबासाहेब आंबेडकर जयंती | F9: 150000
A10: 3 | B10: RE11A274/R1-3 | D10: लोकशाहीर अण्णाभाऊ साठे जयंती | F10: 200000
A11: 4 | B11: RE11A274/R1-4 | D11: ईद-ए-मिलाद (पैगंबर जयंती) | F11: 150000
A12: 5 | B12: RE11A274/R1-5 | D12: शहरातील शिवजयंती साजरी करणे, रोषणाई करणे | F12: 200000
A13: 6 | B13: RE11A274/R1-6 | D13: महात्मा फुले यांची पुण्यतिथी साजरी करणे (दि. 28 नोव्हेंबर) | F13: 500000
A14: 7 | B14: RE11A274/R1-7 | D14: मौलाना अब्दुल कलाम आझाद जयंती व पुण्यतिथी साजरी करणे | F14: 600000
A15: 8 | B15: RE11A274/R1-8 | D15: लहुजी वस्ताद साळवे जयंती महोत्सव गंज पेठ व संगमवाडी येथे साजरा करणे | F15: 500000
A16: 9 | B16: RE11A274/R1-9 | D16: नेताजी सुभाषचंद्र बोस यांची जयंती साजरी करणे | F16: 10000
A17: 10 | B17: RE11A274/R1-10 | D17: येरवडा येथे लोकशाहिर अण्णाभाऊ साठे जयंती महोत्सव साजरा करणे | F17: 100000
A18: 11 | B18: RE11A274/R1-11 | D18: श्री संत रोहिदास महाराज जयंती, पुण्यतिथी साजरी करणे | F18: 50000
A19: 12 | B19: RE11A274/R1-13 | D19: मौलाना अबुल कलाम आझाद जयंती महोत्सव | F19: 500000
A20: 13 | B20: RE11A274/R1-14 | D20: महावीर जयंती | F20: 100000
D22: यादी क्र. R1 एकूण | E22: 0 | F22: 3160000
A24: यादी क्र. R2
A25: शहरामध्ये विविध कार्यक्रम, उत्सव, महोत्सव, संमेलन/ सहप्रायोजक तत्वावर कार्यक्रम साजरे करणे (यादी R2)
A26: RE11A275/R2-
A28: क्र. | B28: code | C28: ward | D28: कामाचे नाव | E28: प्रकल्पीय रक्कम | F28: तरतूद
A30: 1 | B30: RE11A275/R2-1 | D30: महानगरपालिका वर्धापन दिन / सुवर्ण महोत्सव साजरा करणे | F30: 700000
A31: 2 | B31: RE11A275/R2-2 | D31: वर्षातील महत्त्वपूर्ण दिन | F31: 600000
A32: 3 | B32: RE11A275/R2-3 | D32: शिवाजीमहाराज आग्र्‍याहून सुटून परत आले तो स्मृती दिन साजरा करणे | F32: 515000
A33: 4 | B33: RE11A275/R2-4 | D33: शनिवारवाडा सांस्कृतिक महोत्सव | F33: 2000000
A34: 5 | B34: RE11A275/R2-5 | D34: भारतरत्न डॉ. बाबासाहेब आंबेडकर सांस्कृतिक महोत्सव साजरा करणे/ भिम फेस्टिवल (शनिवारवाडा पटांगण) / फुले आंबेडकर फेस्टिवल (समताभूमी) | F34: 2000000
A35: 6 | B35: RE11A275/R2-6 | D35: शिवमहोत्सव साजरा करणे (१४ ते २० फेब्रुवारी) | F35: 2000000
A36: 7 | B36: RE11A275/R2-7 | D36: अण्णाभाऊ साठे महोत्सव | F36: 2000000
A37: 8 | B37: RE11A275/R2-8 | D37: जागतिक आदिवासी दिन | F37: 500000
A38: 9 | B38: RE11A275/R2-9 | D38: पत्रकार डी.आर.कुलकर्णी गृहनिर्माण संस्था व्यासपीठ, जनजागृती व प्रशिक्षण कार्यक्रमांचे आयोजन करणे. | F38: 5000000
D40: यादी क्र. R2 एकूण | E40: 0 | F40: 15315000
A42: यादी क्र. R3
A43: सत्कार, अभिनंदन, पुरस्कार, बक्षिसे यासारखे कार्यक्रम साजरे करणे (यादी R3)
A44: RE11A276/R3-
A46: क्र. | B46: code | C46: ward | D46: कामाचे नाव | E46: प्रकल्पीय रक्कम | F46: तरतूद
A48: 1 | B48: RE11A276/R3-1 | D48: गणेशोत्सव प्रशस्तिपत्रके वितरण | F48: 1000000
A49: 2 | B49: RE11A276/R3-2 | D49: श्री. संत ज्ञानेश्वर व तुकाराम महाराज पालखी स्वागत व दिंडी प्रमुखांचा स्मृतीचिन्ह देऊन सत्कार | F49: 1000000
A50: 3 | B50: RE11A276/R3-3 | D50: प्रतिवर्षी पुणे शहरातील इयत्ता १० वी, १२ वी परिक्षेत गुणवत्ता यादीत येणार्‍या विद्यार्थ्यांचे अभिनंदन | F50: 60000
A51: 4 | B51: RE11A276/R3-4 | D51: बालगंधर्व पुरस्कार प्रदानकरिता | F51: 500000
A52: 5 | B52: RE11A276/R3-5 | D52: पठ्ठे बापूराव पुरस्कारकरिता | F52: 500000
A53: 6 | B53: RE11A276/R3-6 | D53: आचार्य अत्रे पुरस्कारकरिता | F53: 300000
A54: 8 | B54: RE11A276/R3-8 | D54: महर्षि वाल्मिकी पुरस्कार | F54: 500000
A55: 9 | B55: RE11A276/R3-9 | D55: सावित्रीबाई फुले पुरस्कार | F55: 500000
A56: 10 | B56: RE11A276/R3-10 | D56: मौलाना अब्दुल कलाम आझाद पुरस्कार | F56: 500000
A57: 11 | B57: RE11A276/R3-11 | D57: जयंतराव टिळक पुरस्कार | F57: 500000
A58: 12 | B58: RE11A276/R3-12 | D58: १ ऑक्टोंबर - जागतिक ज्येष्ठ नागरिक दिनाच्या मेळाव्याकरता आच्छादित मंडप टाकणे व स्मृतिचिन्हे देणे | F58: 100000
A59: 13 | B59: RE11A276/R3-13 | D59: कै.यशवंतराव चव्हाण यांचे स्मरणार्थ कोथरुड पुणे येथे कै. यशवंतराव चव्हाण पुरस्कार देणे | F59: 175000
... A73: 27 | B73: RE11A276/R3-30 | D73: लोकमान्य टिळक शैक्षणिक गुणवत्ता पुरस्कार | F73: 5000000
D75: यादी क्र. R3 एकूण | E75: 0 | F75: 16435000
A78: यादी क्र. SR9
A79: संगणक व संगणक तंत्रज्ञान याकरिता विविध कामे करणे (यादी SR9)
A80: RE11N122/SR9-
A82: क्र. | B82: code | C82: ward | D82: कामाचे नाव | E82: प्रकल्पीय रक्कम | F82: तरतूद
A84: 1 | B84: RE11N122/SR9-51 | C84: 1D | D84: प्रभाग क्र.1ड, (कळस –धानोरी) मध्ये पुणे मनपाच्या विविध शाळेमधील विदयार्थ्यांकरिता Tab (CTS Software सह) पुरविणे | F84: 1000000
A85: 2 | B85: RE11N122/SR9-52 | C85: 1D | D85: प्रभाग क्र.1ड, (कळस –धानोरी) मध्ये पुणे मनपाच्या प्राथमिक शाळेमधील विदयार्थ्यांकरिता Tab (CTS Software सह) पुरविणे | F85: 1000000
A86: 3 | B86: RE11N122/SR9-53 | C86: 2B | D86: प्रभाग क्र.2ब, मधील मनपा शाळेमध्ये संगणक पुरविणे | F86: 1000000
A87: 4 | B87: RE11N122/SR9-54 | C87: 3B | D87: प्रभाग क्र.3ब,मधील पुणे मनपाच्या प्राथमिक शाळेमधील विदयार्थ्यांकरिता Tab (CTS Software सह) पुरविणे | F87: 1000000
A88: 5 | B88: RE11N122/SR9-55 | C88: 5B | D88: प्रभाग क्र.5ब, मध्ये पुणे मनपाच्या शाळेमध्ये विदयार्थ्यांकरिता टॅब पुरविणे | F88: 1000000
A89: 6 | B89: RE11N122/SR9-56 | C89: 7A | D89: प्रभाग क्र.7अ, मध्ये शाळेतील विदयार्थ्यांसाठी Tab (CTS Software सह) पुरविणे | F89: 1000000
A90: 7 | B90: RE11N122/SR9-57 | C90: 7B | D90: प्रभाग क्र.7ब,मध्ये पुणे मनपाच्या प्राथमिक शाळेमधील विद्यार्थ्यांकरिता Tab (CTS Software सह) पुरविणे | F90: 1000000
A91: 8 | B91: RE11N122/SR9-58 | C91: 10C | D91: प्रभाग क्र.10क, मधील पुणे मनपाच्या शाळेमधील विदयार्थ्याकरिता टॅब पुरविणे | F91: 1000000
A92: 9 | B92: RE11N122/SR9-59 | C92: 13C | D92: प्रभाग क्र. 13 क, मध्ये पुणे महानगरपालिकेच्या प्राथमिक शाळेमधील विद्यार्थ्याकरिता Tab (CTS Software सह) पुरविणे | F92: 1000000
A93: 10 | B93: RE11N122/SR9-60 | C93: 18B | D93: प्रभाग क्र.18ब,मधील पुणे महानगरपालिकेच्या प्राथमिक शाळेत विदयार्थ्यांकरिता Tab (CTS Software सह) पुरविणे | F93: 1000000
A94: 11 | B94: RE11N122/SR9-61 | C94: 18C | D94: प्रभाग क्र. 18 क, मध्ये म.न.पा. शाळांमध्ये व पोलीस चौक्या, वाचनालये यांना संगणक पुरविणे. | F94: 500000
A95: 12 | B95: RE11N122/SR9-62 | C95: 19A | D95: प्रभाग क्र. 19 अ, प्रभागातील सर्व मनपा शाळेतील आधुनिक संगणकाला माध्यमातून शैक्षणिक उपक्रम राबविणे. | F95: 1000000
... A103: 20 | B103: RE11N122/SR9-70 | C103: 29D | D103: प्रभाग क्र. 29 ड – मनपा शाळांमध्ये संगणक पुरवणे. | F103: 1000000
A104: 21 | B104: RE11N122/SR9-71 | D104: औषध वितरण व्यवस्थेत सुसुत्रता आणण्यासाठी सॉफ्टवेअर विकसित करणे | F104: 2500000
A105: 22 | B105: RE11N122/SR9-72 | D105: महिला व ज्येष्ठ नागरीकांना संगणकाचे प्राथमिक शिक्षण घेण्यासाठी प्रशिक्षण | F105: 2500000
A106: 23 | B106: RE11N122/SR9-73 | D106: केंद्र व राज्य व पुणे मनपाच्या विविध योजनांचा प्रचार व प्रसिध्दी करण्यासाठी संकेतस्थळ तयार करणे व पुस्तिका तयार करणे. | F106: 7500000
D108: यादी क्र. SR9 एकूण | E108: 0 | F108: 35500000
A111: यादी क्र. SR10
A112: सार्वजनिक स्वच्छतागृहात संडास, बाथरूम, ओपन गटारे साहित्य व दुरुस्त्या करणे (यादी R10)
A113: RE14B103/SR10-
A115: क्र. | B115: code | C115: ward | D115: कामाचे नाव | E115: प्रकल्पीय रक्कम | F115: तरतूद
A117: 1 | B117: RE14B103/SR10-1 | C117: 1A | D117: प्रभाग क्र.1अ मध्ये विविध ठिकाणी शौचालय दुरूस्तीची कामे करणे | F117: 1000000
A118: 2 | B118: RE14B103/SR10-2 | C118: 1A | D118: प्रभाग क्र.1अ मध्ये विश्रांतवाडी मध्ये विविध ठिकाणी शौचालय दुरूस्तीची कामे करणे | F118: 500000
A119: 3 | B119: RE14B103/SR10-3 | C119: 1A | D119: प्रभाग क्र.1अ मध्ये कळस विश्रांतवाडी धानोरी येथे विविध ठिकाणी शौचालय दुरूस्तीची कामे करणे | F119: 500000
A120: 4 | B120: RE14B103/SR10-4 | C120: 1B | D120: प्रभाग क्र.1ब, मधील धानोरी कळस येथील शौचालय दुरूस्ती करणे | F120: 1000000
A121: 5 | B121: RE14B103/SR10-5 | C121: 2A | D121: प्रभाग क्र.2अ,मध्ये नागपूर चाळ येथील सार्वजनिक शौचालय दुरूस्ती करणे | F121: 1000000
A122: 6 | B122: RE14B103/SR10-6 | C122: 2B | D122: प्रभाग क्र.2ब, मधील जाधव नगर, इंदिरानगर येथील शौचालयांची दुरूस्ती करणे | F122: 500000
A123: 7 | B123: RE14B103/SR10-7 | C123: 2B | D123: प्रभाग क्र.2ब, मधील पंचशीलनगर,कामगारनगर,एकतानगर येथील शौचालयांची दुरूस्ती करणे | F123: 500000
A124: 8 | B124: RE14B103/SR10-8 | C124: 2B | D124: प्रभाग क्र.2ब, मधील विविध ठिकाणच्या शौचालयांची दुरूस्ती व रंगरंगोटी करणे | F124: 500000
A125: 9 | B125: RE14B103/SR10-9 | C125: 2B | D125: प्रभाग क्र.2ब, मधील मनपाच्या विविध शाळांमध्ये शौचालयांची दुरूस्ती करणे | F125: 500000
A126: 10 | B126: RE14B103/SR10-10 | C126: 3A | D126: प्रभाग क्र.3अ,मध्ये विविध ठिकाणी शौचालय दुरूस्ती विषयक कामे करणे | F126: 1000000
A127: 11 | B127: RE14B103/SR10-11 | C127: 3A | D127: प्रभाग क्र.3अ, मध्ये वैकफिल्ड,गांधीनगर,सिध्दार्थनगर येथील शौचालय दुरूस्ती करणे | F127: 1000000
A128: 12 | B128: RE14B103/SR10-12 | C128: 3C | D128: प्रभाग क्र.3क, मधील विविध ठिकाणी शौचालय दुरूस्ती करणे | F128: 1000000
... A299: 183 | B299: RE14B103/SR10-183 | C299: 36B | D299: प्रभाग क्र. 36 ब मध्ये शौचालय दुरुस्ती करणे. | F299: 1000000
A300: 184 | B300: RE14B103/SR10-184 | D300: तळजाई झोपडपट्टी मधील सार्वजनिक शौचालय दुरूस्त करणे | F300: 2500000
D302: यादी क्र. SR10 एकूण | E302: 0 | F302: 184400000
A305: यादी क्र. R4
A306: शहरातील विविध स्मशानभूमी, दफनभूमीमध्ये देखभालदुरूस्तीची कामे करणे (यादी R4)
A307: RE17F169/R4-
A309: क्र. | B309: code | C309: ward | D309: कामाचे नाव | E309: प्रकल्पीय रक्कम | F309: तरतूद
A311: 1 | B311: RE17F169/R4-1 | D311: वैकुंठ स्मशानभूमी येथे सुधारणा कामे करणे | F311: 5400000
A312: 2 | B312: RE17F169/R4-2 | D312: शहरातील हिंदू स्मशानभूमी येथे सुधारणा कामे करणे | F312: 10800000
A313: 3 | B313: RE17F169/R4-3 | D313: शहरातील मुस्लिम कब्रस्तान येथे सुधारणा कामे करणे | F313: 5400000
A314: 4 | B314: RE17F169/R4-4 | D314: शहरातील ख्रिश्चन दफनभूमी येथे सुधारणा कामे करणे | F314: 3600000
A315: 5 | B315: RE17F169/R4-5 | D315: लिंगायत स्मशानभूमी येथे विविध सुधारणा कामे करणे | F315: 5400000
A316: 6 | B316: RE17F169/R4-6 | D316: लिंगायत ख्रिश्चन मुस्लिम स्मशानभूमीमध्ये माती टाकणे | F316: 3600000
...

Sheet A_Capital_Expenditure
A1: सन 2020-21 चे योजनांतर्गत | I1: खर्चाबाबतचे अंदाजपत्रक
A2: अनुक्रमांक | B2: मान्यतेचा ठराव क्र. दिनांक (कोड) | C2: प्रभाग क्रमांक | D2: BPL | E2: कामाचे नाव अगर वर्णन | F2: दि. 31 मार्च 2020 अखेरपर्यंत केलेली तरतूद | I2: दि. 31 मार्च 2019 पर्यंतचा खर्चाचा नक्‍की आकडा | J2: 2019-20 मधील खर्चाची अंदाजी रक्कम | L2: 2020-21 साठी अधिक तरतूद | N2: 2020-21 साठी एकूण तरतूद | O2: प्रकल्पीय रक्कम
F3: कर्जातून | G3: महसूल निधीतून | H3: एकूण | J3: प्रत्यक्ष उपलब्ध तरतूद | K3: कर्जातून तरतूद | L3: कर्जातून | M3: महसूल निधी व इतर निधी
E7: १. मनपा भवन व मनपा इमारती | F7: 0 | G7: 0 | H7: 0 | I7: 0 | J7: 0 | M7: 0 | N7: 0
A8: 1 | B8: CE11A129# | C8: J1- | D8: SJ1- | E8: शहरात विविध ठिकाणी मनपासाठी इमारती बांधणे व विकास कामे करणे | F8: 0 | G8: 662260838 | H8: 662260838 | I8: 603672243 | J8: 58588595 | M8: 167300000 | N8: 167300000
F9: 0 | G9: 0 | H9: 0 | I9: 0 | J9: 0 | M9: 0 | N9: 0
E10: १. मनपा भवन व मनपा इमारती एकूण बेरीज | F10: 0 | G10: 662260838 | H10: 662260838 | I10: 603672243 | J10: 58588595 | M10: 167300000 | N10: 167300000
F11: 0 | G11: 0 | H11: 0 | I11: 0 | J11: 0 | M11: 0 | N11: 0
E12: २. प्राथमिक शिक्षण | F12: 0 | G12: 0 | H12: 0 | I12: 0 | J12: 0 | M12: 0 | N12: 0
A13: 1 | B13: CE12A381# | C13: _ | D13: _ | E13: प्राथमिक शाळेमध्ये मुलभूत सोयी सुविधांसाठी विविध विकासकामे करणे | F13: 0 | G13: 1413642992 | H13: 1413642992 | I13: 1216649043 | J13: 196993949 | M13: 0 | N13: 0
A14: 2 | B14: CE12A422# | C14: J2- | D14: SJ2- | E14: प्राथमिक शाळेसाठी नवीन इमारत बांधणे / वर्गखोल्या बांधणे / मैदाने विकसित करणे व मुलभूत सोयी सुविधांसाठी विविध विकासकामे करणे | F14: 0 | G14: 1090664562 | H14: 1090664562 | I14: 480383579 | J14: 610280983 | M14: 493800000 | N14: 493800000
A15: 3 | B15: CE12A423# | C15: _ | D15: _ | E15: प्राथमिक शाळेसाठी वर्गखोल्या बांधणे | F15: 0 | G15: 48906901 | H15: 48906901 | I15: 48906901 | J15: 0 | M15: 0 | N15: 0
A16: 4 | B16: CE12A424# | C16: _ | D16: _ | E16: प्राथमिक शाळांची मैदाने विकसित करणे | F16: 0 | G16: 10533916 | H16: 10533916 | I16: 10533916 | J16: 0 | M16: 0 | N16: 0
F17: 0 | G17: 0 | H17: 0 | I17: 0 | J17: 0 | M17: 0 | N17: 0
E18: २. प्राथमिक शिक्षण एकूण बेरीज | F18: 0 | G18: 2563748371 | H18: 2563748371 | I18: 1756473439 | J18: 807274932 | M18: 493800000 | N18: 493800000
F19: 0 | G19: 0 | H19: 0 | I19: 0 | J19: 0 | M19: 0 | N19: 0
E20: ३. दुय्यम शिक्षण | F20: 0 | G20: 0 | H20: 0 | I20: 0 | J20: 0 | M20: 0 | N20: 0
A21: 1 | B21: CE13A128# | C21: J5- | E21: माध्यमिक शाळांमध्ये मुलभूत सोयी सुविधांसाठी विविध विकासकामे करणे | F21: 0 | G21: 59867417 | H21: 59867417 | I21: 52485069 | J21: 7382348 | M21: 16800000 | N21: 16800000
F22: 0 | G22: 0 | H22: 0 | I22: 0 | J22: 0 | M22: 0 | N22: 0
E23: ३. दुय्यम शिक्षण एकूण बेरीज | F23: 0 | G23: 59867417 | H23: 59867417 | I23: 52485069 | J23: 7382348 | M23: 16800000 | N23: 16800000
F24: 0 | G24: 0 | H24: 0 | I24: 0 | J24: 0 | M24: 0 | N24: 0
E25: ७. आरोग्य विभाग | F25: 0 | G25: 0 | H25: 0 | I25: 0 | J25: 0 | M25: 0 | N25: 0
A26: 1 | B26: CE17A192# | C26: _ | D26: _ | E26: दवाखान्यातील मुलभूत सोयी सुविधांसाठी विविध विकासकामे करणे | F26: 0 | G26: 610691818 | H26: 610691818 | I26: 570366405 | J26: 40325413 | M26: 0 | N26: 0
A27: 2 | B27: CE17A227# | C27: J12- | D27: SJ12 | E27: शहरामध्ये विविध ठिकाणी स्मशानभूमी / दफनभूमी विकसित करणे / दशक्रीया विधीसाठी घाट बांधणे व विविध विकासकामे करणे | F27: 0 | G27: 686631360 | H27: 686631360 | I27: 465820672 | J27: 220810688 | M27: 209600000 | N27: 209600000
A28: 3 | B28: CE17A242# | C28: J6- | D28: SJ6- | E28: शहरामध्ये दवाखाने / प्रसुतिगृह बांधणे / दवाखान्यांसाठी विविध उपकरणे खरेदी करणे / दवाखान्यातील मुलभूत सोयी सुविधांसाठी विविध विकासकामे करणे | F28: 0 | G28: 840987568 | H28: 840987568 | I28: 264252728 | J28: 576734840 | M28: 828200000 | N28: 828200000
A29: 4 | B29: CE17A243# | C29: _ | D29: _ | E29: प्राथमिक आरोग्य केंद्र उभारणे | F29: 0 | G29: 21662492 | H29: 21662492 | I29: 21662492 | J29: 0 | M29: 0 | N29: 0
A30: 5 | B30: CE17A244# | C30: _ | D30: _ | E30: शहरातील दवाखान्यांसाठी विविध उपकरणे खरेदी करणे | F30: 0 | G30: 163080010 | H30: 163080010 | I30: 153267558 | J30: 9812452 | M30: 0 | N30: 0
A31: 6 | B31: CE17A246# | C31: _ | D31: _ | E31: शहरातील दशक्रीया विधीसाठी घाट बांधणे, विविध विकास कामे करणे | F31: 0 | G31: 6384646 | H31: 6384646 | I31: 6384646 | J31: 0 | M31: 0 | N31: 0
F32: 0 | G32: 0 | H32: 0 | I32: 0 | J32: 0 | M32: 0 | N32: 0
E33: ७. आरोग्य विभाग एकूण बेरीज | F33: 0 | G33: 2329437894 | H33: 2329437894 | I33: 1481754501 | J33: 847683393 | M33: 1037800000 | N33: 1037800000
F34: 0 | G34: 0 | H34: 0 | I34: 0 | J34: 0 | M34: 0 | N34: 0
E35: ९. पथांची झाडलोट / घनकचरा व्यवस्थापन विभाग | F35: 0 | G35: 0 | H35: 0 | I35: 0 | J35: 0 | M35: 0 | N35: 0
A36: 1 | B36: CE19A116 | E36: उरूळी देवाची/फुरसंगी डेपो परिसर कचरा डेपोवरील उर्वरित कचर्‍याचे नॉर्म्सप्रमाणे कॅपिंग करणे व तद्‌नुषंगिक कामे करणे | F36: 0 | G36: 813320173 | H36: 813320173 | I36: 790856400 | J36: 22463773 | M36: 16000000 | N36: 16000000
A37: 2 | B37: CE19A117 | E37: उरुळी देवाची/फुरसुंगी येथील कचरा डेपोच्या भोवती सिमाभिंत बांधणे. | F37: 0 | G37: 51114640 | H37: 51114640 | I37: 43929374 | J37: 7185266 | M37: 5600000 | N37: 5600000
A38: 3 | B38: CE19A120 | E38: व्हर्मीकंपोस्ट पध्दतीचे प्रक्रिया प्रकल्प उभारणे. | F38: 0 | G38: 158603349 | H38: 158603349 | I38: 153449062 | J38: 5154287 | M38: 0 | N38: 0
A39: 4 | B39: CE19A122 | E39: कचरा प्रक्रिया प्रकल्पासाठी जागा ताब्यात घेणे, कंपाउंड करणे, रस्ते करणे व तदनुषंगिक कामे करणे. | F39: 0 | G39: 70227366 | H39: 70227366 | I39: 61347347 | J39: 8880019 | M39: 8000000 | N39: 8000000
A40: 5 | B40: CE19A123 | E40: ताब्यात येणार्‍या जागांवर प्रक्रिया प्रकल्प उभारणे, प्रकल्पांसाठी आवश्यक सुविधा विषयक कामे करणे इत्यादी. | F40: 0 | G40: 201235156 | H40: 201235156 | I40: 170507493 | J40: 30727663 | M40: 64000000 | N40: 64000000
A41: 6 | B41: CE19A139 | E41: उरुळी देवाची/फुरसंगी येथील गावांमध्ये विविध विकास कामे करणे | F41: 0 | G41: 522978961 | H41: 522978961 | I41: 503977745 | J41: 19001216 | M41: 4000000 | N41: 4000000
A42: 7 | B42: CE19A141 | E42: घनकचरा व्यवस्थापनकडील कचरागाडया, बंदिस्त करणे विविध रॅम्प बंदिस्त करणे व कॉक्रीट करणे. | F42: 0 | G42: 121265592 | H42: 121265592 | I42: 111136555 | J42: 10129037 | M42: 8000000 | N42: 8000000
A43: 8 | B43: CE19A143 | E43: गार्डन वेस्टसाठी विविध ठिकाणी पुणे मनपा हद्दीत श्रेडर मशिन बसविणे | F43: 0 | G43: 7120378 | H43: 7120378 | I43: 4692213 | J43: 2428165 | M43: 1600000 | N43: 1600000
A44: 9 | B44: CE19A152A | E44: कचरा गोळा करण्यासाठी घंटागाडया खरेदी करणे (3मे.टन किंवा त्यापेक्षा जास्त) | F44: 0 | G44: 31689015 | H44: 31689015 | I44: 31689015 | J44: 0 | M44: 0 | N44: 0
A45: 10 | B45: CE19A152B | E45: उरुळी देवाची साठी आग विझविण्यासाठी फायर इंजिन आणि वॉटर ब्राउझर | F45: 0 | G45: 14472816 | H45: 14472816 | I45: 14472816 | J45: 0 | M45: 0 | N45: 0
A46: 11 | B46: CE19A153 | E46: प्लास्टिक व इलेक्ट्रॉनिक वस्तू विभाजीत करणेकरीता शेड बांधणे | F46: 0 | G46: 21676121 | H46: 21676121 | I46: 16028393 | J46: 5647728 | M46: 4000000 | N46: 4000000
A47: 12 | B47: CE19A154# | D47: SH1- | E47: शहरात घनकचरा संदर्भात विविध विकास कामे करणे | F47: 0 | G47: 386667527 | H47: 386667527 | I47: 225676807 | J47: 160990720 | M47: 42000000 | N47: 42000000
A48: 13 | B48: CE19A155 | E48: e-waste जमा करणे व प्रक्रिया करणे | F48: 0 | G48: 3800000 | H48: 3800000 | I48: 850000 | J48: 2950000 | M48: 4000000 | N48: 4000000
A49: 14 | B49: CE19A156 | E49: कचरा वाहतुकीसाठी नव्याने उपनगरांमध्ये रॅम्पचे आधुनिकीकरण, विकासकामे करणे, यंत्रसामग्री | F49: 0 | G49: 57897720 | H49: 57897720 | I49: 16692150 | J49: 41205570 | M49: 32000000 | N49: 32000000
A50: 15 | B50: CE19A157 | E50: उरळी देवाची / फुरसुंगी येथे इनर्ट / रिजेक्ट मटेरीयलसाठी नव्याने शास्त्रोक्त लॅण्डफील विकसीत करणे व त्याची देखभाल दुरुस्ती करणे | F50: 0 | G50: 235367790 | H50: 235367790 | I50: 99323460 | J50: 136044330 | M50: 72000000 | N50: 72000000
A51: 16 | B51: CE19A158 | E51: पुणे महानगरपालिकाच्या नव्याने समाविष्ट होणाऱ्या गावामध्ये घनकचरा व्यवस्थापनाशी संबधीत कामे करणे | F51: 0 | G51: 74128767 | H51: 74128767 | I51: 12283063 | J51: 61845704 | M51: 0 | N51: 0
A52: 17 | B52: CE19A162 | E52: पुणे शहराच्या घनकचर्‍यासाठी ताब्यात येणार्‍या जागांवर नव्याने शास्त्रीय पध्दतीने भूभराव विकसित करणे व त्याची देखभाल दुरूस्ती करणे | F52: 0 | G52: 2108051 | H52: 2108051 | I52: 2108051 | J52: 0 | M52: 0 | N52: 0
A53: 18 | B53: CE19A163 | E53: घनकचरा व्यवस्थापनाअंतर्गत विकेंद्रीत पध्दतीने प्रभाग व वॉर्डनिहाय कचरा प्रकिया केंद्र उभारणे व तद्‌नुषंगिक कामे करणे | F53: 0 | G53: 326188998 | H53: 326188998 | I53: 277884540 | J53: 48304458 | M53: 80000000 | N53: 80000000
A54: 19 | B54: CE19A168 | E54: पुणे मनपाच्या अस्तित्वातील कचरा हस्तांतर केंद्र व हजेरीकोठ्‌या व विविध प्रकल्प याठिकाणी सेवकांसाठी सुविधा पुरविणे व बांधकामासाठी देखभाल दुरूस्ती करणे | F54: 0 | G54: 17325786 | H54: 17325786 | I54: 6796246 | J54: 10529540 | M54: 8000000 | N54: 8000000
A55: 20 | B55: CE19A169 | E55: स्वच्छ भारत अभियान अंतर्गत मनपाचा हिस्सा | F55: 0 | G55: 210191994 | H55: 210191994 | I55: 201723994 | J55: 8468000 | M55: 4000000 | N55: 4000000
A56: 21 | B56: CE19A171 | E56: समग्रसाठी मनपाचा हिस्सा | F56: 0 | G56: 55793528 | H56: 55793528 | I56: 16177027 | J56: 39616501 | M56: 0 | N56: 0
A57: 22 | B57: CE19A172 | E57: शहरातील विविध कचरा प्रकल्पावरून देवाची उरुळी येथे कचरा / रिजेक्ट वाहतूक करणे व शास्त्रोक्त पद्धतीने विल्हेवाट लावण्यासाठी मशिनरी पुरवणे व तदनुषंगिक कामे करणे | F57: 0 | G57: 12429373 | H57: 12429373 | I57: 12429373 | J57: 0 | M57: 0 | N57: 0
A58: 23 | B58: CE19A173 | E58: सार्वजनीक स्वच्छतागृह बांधणे | F58: 0 | G58: 94184641 | H58: 94184641 | I58: 28816137 | J58: 65368504 | M58: 4000000 | N58: 4000000
A59: 24 | B59: CE19A174 | E59: e-toilet करणे, जुन्या बसचे स्वच्छतागृहामध्ये रूपांतर करणे | F59: 0 | G59: 11812243 | H59: 11812243 | I59: 4000851 | J59: 7811392 | M59: 0 | N59: 0
... A75: 40 | B75: CE19A190 | E75: हडपसर रामटेकडी येथील 750 मेट्रीकटन क्षमतेच्या वेस्ट वे एनर्जी कचरा प्रकल्प येथे विविध विकास कामे करणे. | F75: 0 | G75: 0 | H75: 0 | I75: 0 | J75: 0 | M75: 400000000 | N75: 400000000
F76: 0 | G76: 0 | H76: 0 | I76: 0 | J76: 0 | M76: 0 | N76: 0
E77: ९. पथांची झाडलोट / घनकचरा व्यवस्थापन विभाग एकूण बेरीज | F77: 0 | G77: 3868342962 | H77: 3868342962 | I77: 2878817357 | J77: 989525605 | M77: 1164000000 | N77: 1164000000
F78: 0 | G78: 0 | H78: 0 | I78: 0 | J78: 0 | M78: 0 | N78: 0
E79: १०क. पथ सुधारणा विभाग | F79: 0 | G79: 0 | H79: 0 | I79: 0 | J79: 0 | M79: 0 | N79: 0
A80: 1 | B80: CE20A102# | C80: A2- | D80: SA2- | E80: शहरामधील रस्ते विकसित करणे आणि डांबरीकरण करणे | F80: 11538000 | G80: 8688103444 | H80: 8699641444 | I80: 7136426072 | J80: 1563215372 | M80: 2994200000 | N80: 2994200000
A81: 2 | B81: CE20A103# | C81: A13- | D81: SA13 | E81: Pedestrian Policy नुसार शहरातील फूटपाथ विकसित करणे | F81: 0 | G81: 3081429053 | H81: 3081429053 | I81: 2497734409 | J81: 583694644 | M81: 630100000 | N81: 630100000
A82: 3 | B82: CE20A104# | C82: _ | D82: _ | E82: शहरात पेव्हिंग ब्लॉक, इंटरलॉकिंग ब्लॉक बसविणे | F82: 0 | G82: 313790000 | H82: 313790000 | I82: 126414135 | J82: 187375865 | M82: 0 | N82: 0
A83: 4 | B83: CE20A884# | C83: A10- | D83: SA10 | E83: शहरात विविध विकासाची कामे करणे | F83: 0 | G83: 2018789970 | H83: 2018789970 | I83: 1297705618 | J83: 721084352 | M83: 455680000 | N83: 455680000
A84: 5 | B84: CE20A1249# | C84: A6- | D84: _ | E84: शहरामधील रस्ते विकसित करणे | F84: 0 | G84: 5533992070 | H84: 5533992070 | I84: 1366818885 | J84: 4167173185 | M84: 2484160000 | N84: 2484160000
A85: 6 | B85: CE20A1250# | C85: _ | D85: _ | E85: पुणे शहरात CMP आराखड्यानुसार (PPP / Development TDR / Deffered payment / Premium charges) अन्वये प्रशासकीय मुल्यमापनानुसार प्रत्यक्ष अंमलबजावणी करून कामे करणे | F85: 0 | G85: 310594176 | H85: 310594176 | I85: 310594176 | J85: 0 | M85: 0 | N85: 0
A86: 7 | B86: CE20A1259# | C86: A9- | E86: शहरातील रस्ते पुनर्डांबरीकरण करणे | F86: 0 | G86: 1155766848 | H86: 1155766848 | I86: 573462228 | J86: 582304620 | M86: 284800000 | N86: 284800000
A87: 8 | B87: CE20A1262# | C87: A15- | D87: SA15 | E87: शहरातील रस्ते काँक्रीटने विकसित करणे | F87: 0 | G87: 4499459455 | H87: 4499459455 | I87: 3150064484 | J87: 1349394971 | M87: 1202000000 | N87: 1202000000
A88: 9 | B88: CE20A1263# | C88: A16- | D88: _ | E88: शहरामध्ये BRT मार्ग विकसित करणे | F88: 0 | G88: 2227679121 | H88: 2227679121 | I88: 1812587133 | J88: 415091988 | M88: 96000000 | N88: 96000000
A89: 10 | B89: CE20A1264# | C89: A17- | E89: शहरामध्ये सायकल ट्रॅक विकसित करणे | F89: 0 | G89: 236895593 | H89: 236895593 | I89: 68895593 | J89: 168000000 | M89: 101600000 | N89: 101600000
A90: 11 | B90: CE20A1266# | C90: A18- | E90: नविन समाविष्ट गावांमध्ये रस्ते विकसित करणे | F90: 0 | G90: 518740000 | H90: 518740000 | I90: 154166049 | J90: 364573951 | M90: 20400000 | N90: 20400000
F91: 0 | G91: 0 | H91: 0 | I91: 0 | J91: 0 | M91: 0 | N91: 0
E92: १०क. पथ सुधारणा विभाग एकूण बेरीज | F92: 11538000 | G92: 28585239730 | H92: 28596777730 | I92: 18494868782 | J92: 10101908948 | M92: 8268940000 | N92: 8268940000
F93: 0 | G93: 0 | H93: 0 | I93: 0 | J93: 0 | M93: 0 | N93: 0
E94: १०ख. वाहतूक नियंत्रण विभाग | F94: 0 | G94: 0 | H94: 0 | I94: 0 | J94: 0 | M94: 0 | N94: 0
A95: 1 | B95: CE20B101# | C95: T1- | D95: _ | E95: शहरामधील चौकांची सुधारणा / विकासकामे करणे | F95: 0 | G95: 620530783 | H95: 620530783 | I95: 218958501 | J95: 401572282 | M95: 224000000 | N95: 224000000
A96: 2 | B96: CE20B102# | C96: T2- | D96: ST2- | E96: शहरामधील चौकांची सुधारणा / विकासकामे करणे, वाहतूक सुधारण्यासाठी विविध विकास कामे करणे | F96: 0 | G96: 4468770639 | H96: 4468770639 | I96: 1826744984 | J96: 2642025655 | M96: 1827100000 | N96: 1827100000
A97: 3 | B97: CE20B104# | C97: _ | D97: _ | E97: नवीन सिग्न्ल बसविणे व जुने सिग्न्ल दुरुस्त करणे | F97: 0 | G97: 815141 | H97: 815141 | I97: 815141 | J97: 0 | M97: 0 | N97: 0
A98: 4 | B98: CE20B107# | C98: _ | E98: रस्त्यांवरील टी जंक्शनचा विकास व सुधारणा व वाहनतळ निर्माण करणे | F98: 0 | G98: 66954542 | H98: 66954542 | I98: 46384542 | J98: 20570000 | M98: 0 | N98: 0
A99: 5 | B99: CE20B108# | C99: T7- | D99: ST7- | E99: शहरातील वाहनतळांचा जागा विकसित करणे / वाहनतळ निर्माण करणे | F99: 0 | G99: 394663867 | H99: 394663867 | I99: 36499575 | J99: 358164292 | M99: 679000000 | N99: 679000000
A100: 6 | B100: CE20B251 | C100: G | D100: P | E100: पुणे शहरातील रिक्षांना CNG Kit बसविणेसाठी अनुदान देणे | F100: 0 | G100: 104600941 | H100: 104600941 | I100: 92136941 | J100: 12464000 | M100: 10000000 | N100: 10000000
F101: 0 | G101: 0 | H101: 0 | I101: 0 | J101: 0 | M101: 0 | N101: 0
E102: १०ख. वाहतूक नियंत्रण विभाग एकूण बेरीज | F102: 0 | G102: 5656335913 | H102: 5656335913 | I102: 2221539684 | J102: 3434796229 | M102: 2740100000 | N102: 2740100000
F103: 0 | G103: 0 | H103: 0 | I103: 0 | J103: 0 | M103: 0 | N103: 0
E104: १०ग. विद्युत विभाग | F104: 0 | G104: 0 | H104: 0 | I104: 0 | J104: 0 | M104: 0 | N104: 0
A105: 1 | B105: CE20C352# | C105: B5- | D105: SB5- | E105: शहरातील विविध ठिकाणी प्रकाश व्यवस्था करणे | F105: 0 | G105: 5780801655 | H105: 5780801655 | I105: 4755746164 | J105: 1025055491 | M105: 847760000 | N105: 847760000
A106: 2 | B106: CE20C550# | C106: _ | D106: SB7- | E106: शहरामध्ये भूमिगत केबल टाकणे | F106: 0 | G106: 731493752 | H106: 731493752 | I106: 487663224 | J106: 243830528 | M106: 238000000 | N106: 238000000
A107: 3 | B107: CE20C551# | C107: B8- | D107: _ | E107: शहरामधील विविध भवनांमध्ये विद्युतविषयक कामे करणे | F107: 0 | G107: 176193112 | H107: 176193112 | I107: 165158621 | J107: 11034491 | M107: 48720000 | N107: 48720000
F108: 0 | G108: 0 | H108: 0 | I108: 0 | J108: 0 | M108: 0 | N108: 0
E109: १०ग. विद्युत विभाग एकूण बेरीज | F109: 0 | G109: 6688488519 | H109: 6688488519 | I109: 5408568009 | J109: 1279920510 | M109: 1134480000 | N109: 1134480000
F110: 0 | G110: 0 | H110: 0 | I110: 0 | J110: 0 | M110: 0 | N110: 0
E111: १०घ. पूल व नदी सुधारणा (विकास योजना) | F111: 0 | G111: 0 | H111: 0 | I111: 0 | J111: 0 | M111: 0 | N111: 0
A112: 1 | B112: CE20D170# | C112: L1- | D112: SL1- | E112: शहरात विविध ठिकाणी पूल बांधणे / उड्डाणपूल बांधणे / भुयारी मार्ग करणे | F112: 0 | G112: 2787369250 | H112: 2787369250 | I112: 708189989 | J112: 2079179261 | M112: 1939900000 | N112: 1939900000
A113: 2 | B113: CE20D219# | C113: L2- | D113: SL2- | E113: शहरातील नदी सुधारणा कामे करणे व तद्‌नुषंगिक कामे करणे | F113: 0 | G113: 155501793 | H113: 155501793 | I113: 59119568 | J113: 96382225 | M113: 90000000 | N113: 90000000
F114: 0 | G114: 0 | H114: 0 | I114: 0 | J114: 0 | M114: 0 | N114: 0
E115: १०घ. पूल व नदी सुधारणा (विकास योजना) एकूण बेरीज | F115: 0 | G115: 2942871043 | H115: 2942871043 | I115: 767309557 | J115: 2175561486 | M115: 2029900000 | N115: 2029900000
F116: 0 | G116: 0 | H116: 0 | I116: 0 | J116: 0 | M116: 0 | N116: 0
E117: १०च. स्ट्रॉम वॉटर ड्रेन प्रकल्प | F117: 0 | G117: 0 | H117: 0 | I117: 0 | J117: 0 | M117: 0 | N117: 0
A118: 1 | B118: CE20E101# | C118: F1- | D118: SF1- | E118: पुणे शहरातील पावसाळी पाण्याच्या व्यवस्थापनासाठी नाला सुधारणा कामे, कल्व्हर्टस व पावसाळी लाईन टाकणे | F118: 0 | G118: 4478142098 | H118: 4478142098 | I118: 3988702848 | J118: 489439250 | M118: 481500000 | N118: 481500000 | O118: 20000000000
...

Sheet A_Land_Acquisition
A1: सन 2020-21 चे अंदाजपत्रक - खास निधीतून करावयाची योजनांतर्गत कामे
A2: अनुक्रमांक | C2: कामाचे नाव | D2: मान्य अंदाज 2019-20 | E2: नवीन अंदाज 2020-21
A6: s
A7: (अ) | C7: भूमी संपादन निधीतून करावयाचा खर्च | D7: 0 | E7: 0
D8: 0 | E8: 0
A9: 1 | B9: FE11A101 | C9: भूमी संपादन विशेष अधिकारी यांचा कार्यालयीन खर्च - | D9: 14000000 | E9: 16000000
A10: 2 | C10: कोर्टाच्या निकालानुसार वाढीव नुकसानभरपाई कोर्ट खर्च, वकील फी, जॉइन्ट जज्ज यांचा खर्च वगैरे | D10: 0 | E10: 0
A11: 3 | C11: भूमी संपादन अधिनियमात नव्याने केलेल्या दुरुस्तीमुळे यापूर्वी जाहीर झालेल्या योजनापोटी ावयाच्या वाढीव रकमेचा खर्च | D11: 0 | E11: 0
A12: 4 | C12: परचेस नोटीसांमुळे (नवीन) पाठवावयाच्या भूमी संपादन योजनांसाठी तरतूद | D12: 0 | E12: 0
A13: 5 | C13: ताब्यात घेतलेल्या मिळकती पाडणे, ड्रेनेज, वॉटर, इलेक्ट्रीक टेलिफोन वगैरे कनेक्शन्स हलविणे, जोडणे व इतर तद्‌नुषंगिक कामे करणे. | D13: 0 | E13: 0
A14: 6 | C14: कार्यालयीन कामासाठी साधने, डेडस्टॉक वस्तू खरेदी करणे, हत्यारे खरेदी करणे, कार्यालय व कोठीची दुरुस्ती करणे, आवश्यक सुधारणा करणे, प्रकटन खर्च, प्रवास खर्च वगैर | D14: 0 | E14: 0
A15: 7 | C15: मुंबई प्रांतिक मनपा अधिनियम १९४९ च्या कलम २१३ अन्वये रस्तारूंदीसाठी ताब्यात घेतलेल्या मोकळ्या जागा व त्याप्रित्यर्थ ावयाची नुकसानभरपाईची रक्कम | D15: 0 | E15: 0
A16: 8 | C16: इतर योजनांमधील मोजणी फी व इतर तद्‌नुषंगिक रक्कम | D16: 0 | E16: 0
A17: 9 | C17: भूमी संपादन अधिकारी ह्यांचेकडील खालील नमूद केलेल्या ज्या जागांचे निवाडे जाहीर करतील त्यासाठी रक्कम | D17: 0 | E17: 0
A18: 10 | C18: संगणक दुरूस्ती व आवश्यक साहित्य | D18: 0 | E18: 0
D19: 0 | E19: 0
C20: (अ) बेरीज | D20: 14000000 | E20: 16000000
D21: 0 | E21: 0
D22: 0 | E22: 0
B23: FE11A102 | C23: भूसंपादनासाठी आवश्यक जागांची यादी :- | D23: 196000000 | E23: 224000000
D24: 0 | E24: 0
C25: सी.वाय.जी अंतर्गत रस्ते : | D25: 0 | E25: 0
C26: बाणेर मुख्य रस्ता २६१ ते १०५ | D26: 0 | E26: 0
C27: बाणेर स.क्र. १३३ ते बालेवाडी स.क्र. १० बालेवाडीकडे जाणारा रस्ता मुख्य रस्ता (बालेवाडी) | D27: 0 | E27: 0
C28: बालेवाडी स.क्र. ३४, ३५ जी१ गार्डनचे आरक्षण | D28: 0 | E28: 0
C29: बाणेर स.क्र. २८, २९० जी२ गार्डनचे आरक्षण व बाणेर स.क्र. ३५ जी३ गार्डनचे आरक्षण | D29: 0 | E29: 0
C30: कल्याणीनगर जंक्शन ते आळंदी रोड | D30: 0 | E30: 0
C31: बाणेर स.क्र. १०५, १०६, ११०, १११ पीएमटी१ | D31: 0 | E31: 0
C32: बाणेर स.क्र. ३३ पी.३ | D32: 0 | E32: 0
C33: बाणेर स.क्र. १०० पी.४ | D33: 0 | E33: 0
C34: बाणेर स.क्र. १७४ पी.४ | D34: 0 | E34: 0
C35: बाणेर स.क्र. ७९ पी.६ | D35: 0 | E35: 0
C36: बाणेर स.क्र. १०५, १०६ पी.७ पार्किंगचे आरक्षण | D36: 0 | E36: 0
... C42: एअरपोर्ट रोड ते डेक्कन कॉलेज व्हाया हॉटमिक्स प्लँट | D42: 0 | E42: 0
D43: 0 | E43: 0
C44: जेएनएनयुआरएम / बीआरटी अंतर्गत रस्ते : | D44: 0 | E44: 0
C45: बाणेर स.क्र. १०७, १०८ व ११० मधून जाणारा १८ मी. रस्ता. | D45: 0 | E45: 0
C46: मौजे खराडी ता. हवेली, संगमवाडी ते खराडी २४ मी. नदीकाठचा डी.पी. रस्ता | D46: 0 | E46: 0
C47: मौजे वडगांव शेरी ता. हवेली, संगमवाडी ते खराडी २४ मी. नदीकाठचा डी.पी. रस्ता | D47: 0 | E47: 0
C48: सिंहगड रस्ता महानगरपालिका हद्द दरम्यान नियोजनाते विकसीत करणे (वडगांव बुद्रुक) | D48: 0 | E48: 0
C49: सिंहगड रस्ता महानगरपालिका हद्द दरम्यान नियोजनाते विकसीत करणे (वडगांव खुर्द) | D49: 0 | E49: 0
C50: विश्रांतवाडी ते धानोरी | D50: 0 | E50: 0
C51: संचेती हॉस्पिटल ते गव्हर्नमेंट पोल्ट्री फार्म | D51: 0 | E51: 0
C52: पुणे स्टेशन ते मनपा रोड (कॅनॉट रोड) | D52: 0 | E52: 0
D53: 0 | E53: 0
C54: आरआरडीपी अंतर्गत रस्ते : | D54: 0 | E54: 0
C55: मुळा नदिवरील पिंपळे निलेख यांना जोडणारा पुल रस्त्याचे भुसंपाद (बाणेर) | D55: 0 | E55: 0
C56: सुतारवाडी रस्ता २४ मी. (जुना) | D56: 0 | E56: 0
C57: कोथरूड एकलव्य कॉलेज ते हायवेपर्यंत मुख्य रस्ता (१५ मी. नवीन) | D57: 0 | E57: 0
C58: कोथरूड महात्मा सोसायटी एकलव्य कॉलेज ते हायवे परिसरातील डी.पी. रस्ते (१५ मी.) व ( १८ मी.) | D58: 0 | E58: 0
C59: बालभारती ते पौड फाटा रस्ता | D59: 0 | E59: 0
C60: वारजे जकातनाका ते नवीन अहिरे हद्द एन.डी.ए. रोड जुना जकातनाका ते हायवे व वारजे माळवाडी टेकडीपर्यंत | D60: 0 | E60: 0
C61: जे.पी. नाईक इन्स्टिटयुट ते गणंजय सोसायटी | D61: 0 | E61: 0
C62: अलंकार पोलीस चौकी गिरीजा शंकर सोसायटी पश्चिमानगरी ते नाईक पूल डी.पी. रस्ता | D62: 0 | E62: 0
C63: चांदणी चौक ते सुस चौक | D63: 0 | E63: 0
C64: सिंहगड रोड दोन्ही कॅनॉलवरील प्रस्तावित पुलासह (वडगांव बुद्रुक) | D64: 0 | E64: 0
C65: सुस रस्ता ते बाणेर रस्ता रामनदी कडेचा रस्ता (बाणेर) | D65: 0 | E65: 0
... C67: सुस रस्ता ते बाणेर रस्ता रामनदी कडेचा रस्ता या रस्त्याचे भूसंपादन करणेबाबत (पाषाण) | D67: 0 | E67: 0
D68: 0 | E68: 0
C69: भूसंपादनाची इतर प्रकरणे : | D69: 0 | E69: 0
C70: पुणेमुंबई रस्ता हॅरीस ब्रिज ते खडकी कॅन्टोन्मेंट | D70: 0 | E70: 0
C71: हडपसर स.नं. २२६, २२४, २६६, २११, २१०, २०९, २०८, २०७ पोस्ट ऑफीस बाजूने जाणारा १८ मी. डी. पी. रस्ता | D71: 0 | E71: 0
C72: हडपसर स. नं. ८७, ८९, ९२, ९३, १०६, ३१२, ३१४, ३१ पैकी डी. पी. रस्त्यासाठी | D72: 0 | E72: 0
C73: हडपसर स.नं. २५ ईडब्ल्यूएस पैकी जागा संपादन करणेबाबत | D73: 0 | E73: 0
C74: घोरपडी गाव अनंत टॉकीज ते श्रीवस्ती नगर १२ मी डी.पी. रस्ता | D74: 0 | E74: 0
C75: कोंढवा खु.॥ स.नं. ५अ, ५ ब हायस्कूलसाठी संपादन | D75: 0 | E75: 0
C76: कोंढवा खु.॥ स.नं. १७ पै. मुलांचे खेळाचे मैदानासाठी | D76: 0 | E76: 0
C77: पुणे, पेठ पाषाण स.नं. ११० (पै.) पार्क (उान) साठी संपादन | D77: 0 | E77: 0
C78: हडपसर स.नं. ८४ पैकी प्ले ग्राऊंड साठी संपादन | D78: 0 | E78: 0
C79: वानवडी स.नं. ४९, ५८, ५९ | D79: 0 | E79: 0
C80: नाना पेठ, सि.सं. नं. ४०५ पै. उानासाठी आरक्षित जागा संपादन करणे | D80: 0 | E80: 0
... C95: हिंगणे / कर्वेनगर स.नं. ४० हायस्कूलसाठी | D95: 0 | E95: 0
D96: 0 | E96: 0
D97: 0 | E97: 0
C98: जाहीर झालेल्या निवाड्यापोटी भरण्याची रक्कम | D98: 0 | E98: 0
A99: 1 | C99: कर्वे रस्तारूंद जाहीर झालेल्या निवाड्यापोटी राहीलेली भरावयाची रक्कम | D99: 0 | E99: 0
A100: 2 | C100: सदाशिव पेठ घरांक ४६८ पार्किंगसाठी संपादन करणे | D100: 0 | E100: 0
D101: 0 | E101: 0
D102: 0 | E102: 0
C103: भूमिप्रापण खाते :- | D103: 0 | E103: 0
A104: 1 | C104: केळकर रस्ता (मंदार लॉज ते नारायण पेठ पोलीस चौकी) | D104: 0 | E104: 0
A105: 2 | C105: म्हात्रे पूल ते छत्रपती राजाराम पूल दरम्यानच्या नदीकाठचा १००'' डी.पी. रस्ता | D105: 0 | E105: 0
A106: 3 | C106: सातारा रस्ता | D106: 0 | E106: 0
A107: 4 | C107: सिंहगड रस्ता | D107: 0 | E107: 0
A108: 5 | C108: जंगली महाराज रस्ता | D108: 0 | E108: 0
A109: 6 | C109: पवित्र मंगल कार्यालया, पर्वती (सातारा रस्ता) | D109: 0 | E109: 0
A110: 7 | C110: नेहरू रस्ता, रास्ता पेठ पॉवर हाऊस ते लक्ष्मी रस्ता | D110: 0 | E110: 0
A111: 8 | C111: कर्वे रस्ता (खंडूजीबाबा चौक ते एस.एन.डी.टी.) | D111: 0 | E111: 0
A112: 9 | C112: शंकरशेठ रस्ता | D112: 0 | E112: 0
A113: 10 | C113: सेनापती बापट रस्ता | D113: 0 | E113: 0
A114: 11 | C114: उंबर्‍या गणपती चौक ते खुन्या मुरलीधर रस्ता | D114: 0 | E114: 0
A115: 12 | C115: भाऊ महाराज बोळ | D115: 0 | E115: 0
... A121: 18 | C121: रामवाडी जकातनाका ते लोहगाव विमानतळ | D121: 0 | E121: 0
D122: 0 | E122: 0
C123: जकात नाका :- | D123: 0 | E123: 0
A124: 1 | C124: शिंदेवाडी, स.नं. १०० ते १०६ (पैकी) | D124: 0 | E124: 0
A125: 2 | C125: फुरसुंगी, स.नं. १७५ पैकी | D125: 0 | E125: 0
A126: 3 | C126: वाघोली, गट नं. २३७८, २३७९ | D126: 0 | E126: 0
A127: 4 | C127: बावधन खुर्द, स.नं. ६४ | D127: 0 | E127: 0
A128: 5 | C128: हडपसर, स.नं. ६३ पैकी | D128: 0 | E128: 0
...

Sheet A_Fund_Expenditure
A1: सन 2020-21 चे उपनगरे विकास निधीचे | I1: योजनांतर्गत खर्चाबाबतचे अंदाजपत्रक
A2: अनुक्रमांक | B2: मान्यतेचा ठराव क्र. दिनांक (कोड) | C2: प्रभाग क्रमांक | D2: BPL | E2: कामाचे नाव अगर वर्णन | F2: दि. 31 मार्च 2020 अखेरपर्यंत केलेली तरतूद | I2: दि. 31 मार्च 2018 पर्यंतचा खर्चाचा नक्‍की आकडा | J2: 2018-19 मधील खर्चाचा नक्‍की आकडा | K2: 2019-20 मधील खर्चाची अंदाजी रक्‍कम | L2: 2020-21 साठी अधिक तरतूद | N2: 2020-21 साठी एकूण तरतूद | O2: शेरा
F3: कर्जातून | G3: महसूल निधीतून | H3: एकूण | L3: कर्जातून | M3: महसूल निधी व इतर निधी
E7: ४. झोपडपट्टी निर्मूलन व पुनर्वसन निधी | F7: 0 | G7: 0 | H7: 0 | I7: 0 | J7: 0 | K7: 0 | M7: 0 | N7: 0
A8: 1 | B8: FE14A101# | C8: _ | D8: SG1- | E8: निरनिराळ्या झोपडपट्टींमध्ये विविध विकासाची कामे करणे | F8: 33377000 | G8: 1481216179 | H8: 1514593179 | I8: 1451524833 | J8: 22589988 | K8: 40478358 | M8: 48000000 | N8: 48000000
A9: 2 | B9: FE14A104 | D9: B | E9: झो.नि.पु. अंतर्गत करावयाची कामे | F9: 0 | G9: 218678409 | H9: 218678409 | I9: 200515533 | J9: 2344077 | K9: 15818799 | M9: 15750000 | N9: 15750000
A10: 3 | B10: FE14A105# | C10: _ | D10: SG2- | E10: शहरामध्ये शौच्छालये / मुताऱ्या बांधणे | F10: 0 | G10: 1592998612 | H10: 1592998612 | I10: 1110668506 | J10: 197318651 | K10: 285011455 | M10: 83500000 | N10: 83500000
A11: 4 | B11: FE14A107 | D11: B | E11: दलित वस्ती सुधारणा अंतर्गत कामे करणे | F11: 0 | G11: 217095507 | H11: 217095507 | I11: 180595507 | J11: 20909876 | K11: 15590124 | M11: 0 | N11: 0
A12: 5 | B12: FE14A129 | D12: PL | E12: सार्वजनिक ठिकाणी शौचालय बांधणे | F12: 0 | G12: 61972215 | H12: 61972215 | I12: 36833637 | J12: 8957746 | K12: 16180832 | M12: 15750000 | N12: 15750000
A13: 6 | B13: FE14A130 | D13: PL | E13: सार्वजनिक ठिकाणी मुतार्‍या बांधणे | F13: 0 | G13: 40276532 | H13: 40276532 | I13: 23650532 | J13: 875626 | K13: 15750374 | M13: 15750000 | N13: 15750000
A14: 7 | B14: FE14A135 | E14: प्रभाग क्र.14ब, मधील बाबासाहेब आंबेडकर हॉस्टेल विकसित करणेकरिता अहवाल तयार करणे | F14: 0 | G14: 2000000 | H14: 2000000 | I14: 0 | J14: 0 | K14: 2000000 | M14: 0 | N14: 0
F15: 0 | G15: 0 | H15: 0 | I15: 0 | J15: 0 | K15: 0 | M15: 0 | N15: 0
E16: ४. झोपडपट्टी निर्मूलन व पुनर्वसन निधी एकूण बेरीज | F16: 33377000 | G16: 3614237454 | H16: 3647614454 | I16: 3003788548 | J16: 252995964 | K16: 390829942 | M16: 178750000 | N16: 178750000
F17: 0 | G17: 0 | H17: 0 | I17: 0 | J17: 0 | K17: 0 | M17: 0 | N17: 0
E18: क्षेत्रिय कार्यालयाने करावयाची कामे | F18: 0 | G18: 0 | H18: 0 | I18: 0 | J18: 0 | K18: 0 | M18: 0 | N18: 0
F19: 0 | G19: 0 | H19: 0 | I19: 0 | J19: 0 | K19: 0 | M19: 0 | N19: 0
A20: • | B20: FE14A118# | C20: W5 | D20: B | E20: क्षेत्रिय कार्यालय : झो.नि.पु. विभागाने करावयाची कामे | F20: 0 | G20: 250536825 | H20: 250536825 | I20: 234050825 | J20: 4402967 | K20: 12083033 | M20: 7950000 | N20: 7950000
A21: • | B21: FE14A121# | C21: C5 | D21: B | E21: क्षेत्रिय कार्यालय : नागरिकांच्या सहभाग योजनेतून झो.नि.पु. विभागाने करावयाची कामे | F21: 0 | G21: 136782423 | H21: 136782423 | I21: 136868423 | J21: 1265713 | K21: -1351713 | M21: 5950000 | N21: 5950000
F22: 0 | G22: 0 | H22: 0 | I22: 0 | J22: 0 | K22: 0 | M22: 0 | N22: 0
E23: क्षेत्रिय कार्यालयाने करावयाची कामे एकूण बेरीज | F23: 0 | G23: 387319248 | H23: 387319248 | I23: 370919248 | J23: 5668680 | K23: 10731320 | M23: 13900000 | N23: 13900000
F24: 0 | G24: 0 | H24: 0 | I24: 0 | J24: 0 | K24: 0 | M24: 0 | N24: 0
E25: ४. झोपडपट्टी निर्मूलन व पुनर्वसन निधीतून करावयाची कामे + क्षेत्रिय कार्यालयाने करावयाची कामे एकूण बेरीज | F25: 33377000 | G25: 4001556702 | H25: 4034933702 | I25: 3374707796 | J25: 258664644 | K25: 401561262 | M25: 192650000 | N25: 192650000
F26: 0 | G26: 0 | H26: 0 | I26: 0 | J26: 0 | K26: 0 | M26: 0 | N26: 0
E27: ४अ. मागासवर्गीय कल्याणकारी योजना निधी | F27: 0 | G27: 0 | H27: 0 | I27: 0 | J27: 0 | K27: 0 | M27: 0 | N27: 0
A28: 1 | B28: FE14B101 | D28: B-FA | E28: समाज विकास विभाग अंतर्गत मागासवर्गीय योजना | F28: 0 | G28: 496023151 | H28: 496023151 | I28: 418523151 | J28: 27131465 | K28: 50368535 | M28: 35000000 | N28: 35000000
A29: 2 | B29: FE14B112 | D29: B-FA | E29: लोकशाहीर अण्णाभाऊ साठे शैक्षणिक मदत योजना | F29: 0 | G29: 185242082 | H29: 185242082 | I29: 123242082 | J29: 24625000 | K29: 37375000 | M29: 41000000 | N29: 41000000
A30: 3 | B30: FE14B113 | D30: B-FA | E30: मौ. अबुल कलाम आझाद शैक्षणिक मदत योजना | F30: 0 | G30: 393988546 | H30: 393988546 | I30: 291988546 | J30: 40770000 | K30: 61230000 | M30: 71000000 | N30: 71000000
A31: 4 | B31: FE14B121 | D31: B-T | E31: मागासवर्गीय विद्यार्थ्यांना स्पर्धा परिक्षा मार्गदर्शन केंद्र चालविणे | F31: 0 | G31: 10401896 | H31: 10401896 | I31: 5401896 | J31: 442000 | K31: 4558000 | M31: 3000000 | N31: 3000000
A32: 5 | B32: FE14B122 | D32: B-T | E32: बालविकास केंद्र व वस्ती रिसोर्स सेंटर सुरू करणे | F32: 0 | G32: 13983487 | H32: 13983487 | I32: 9483487 | J32: 1446452 | K32: 3053548 | M32: 2000000 | N32: 2000000
A33: 6 | B33: FE14B123 | D33: B | E33: मागासवर्गीय कल्याणकारी योजनेअंतर्गत विविध योजना राबविणेसाठी मानधन तत्वावरील सेवकांचा मानधन खर्च | F33: 0 | G33: 31457860 | H33: 31457860 | I33: 22957860 | J33: 8044799 | K33: 455201 | M33: 5000000 | N33: 5000000
A34: 7 | B34: FE14B126 | D34: B | E34: बार्टीचे ४ केंद्र सुरू करणे (कोथरूड, सहकारनगर, शिवाजीनगर, भवानीपेठ) | F34: 0 | G34: 0 | H34: 0 | I34: 0 | J34: 0 | K34: 0 | M34: 0 | N34: 0
A35: 8 | B35: FE14B127 | D35: B | E35: माता रमार्इ भिमराव आंबेडकर योजनेअंतर्गत गवनि घोषीत व शहरी गरीब योजनेतील पात्र ठरणाऱ्या विधवा, निराधार महिलांसाठी दरमहा रू.1,000/- अर्थसहाय्य करणे (मागासवर्गीय कल्याणकारी योजना) | F35: 0 | G35: 16002788 | H35: 16002788 | I35: 1002788 | J35: 0 | K35: 15000000 | M35: 17000000 | N35: 17000000
A36: 9 | B36: FE14B128 | D36: B-FA | E36: डॉ. बाबासाहेब आंबेडकर विद्यार्थी वसतिगृह, घोले रोड येथील खाणावळीचा खर्च | F36: 0 | G36: 13920540 | H36: 13920540 | I36: 4920540 | J36: 2215717 | K36: 6784283 | M36: 5000000 | N36: 5000000
A37: 10 | B37: FE14B129 | D37: B-I | E37: शहरात आदिवासी विद्यार्थ्यांसाठी वसतिगृहे उभारणे | F37: 0 | G37: 40000000 | H37: 40000000 | I37: 0 | J37: 3885336 | K37: 36114664 | M37: 30000000 | N37: 30000000
A38: 11 | B38: FE14B130 | E38: बार्टी संस्थेच्या मदतीने विविध व्यावसायिक प्रशिक्षण देणे | F38: 0 | G38: 5000000 | H38: 5000000 | I38: 0 | J38: 0 | K38: 5000000 | M38: 0 | N38: 0
A39: 12 | B39: FE14B131 | D39: B-T | E39: विविध व्यावसायिक प्रशिक्षण देणे | F39: 0 | G39: 7000000 | H39: 7000000 | I39: 0 | J39: 795454 | K39: 6204546 | M39: 0 | N39: 0
A40: 13 | B40: FE14B132 | D40: B-S | E40: मागासवर्गीय कल्याणकारी योजनेचा अभ्यास, ऑडिट व सर्वेक्षण करणे | F40: 0 | G40: 1000000 | H40: 1000000 | I40: 0 | J40: 0 | K40: 1000000 | M40: 0 | N40: 0
A41: 14 | B41: FE14B133 | D41: B | E41: लोकशाहिर अण्णा भाऊ साठे यांच्या जन्मशताब्दी वर्षानिमित्त विविध कार्यक्रमाचे आयोजन करणे | F41: 0 | G41: 0 | H41: 0 | I41: 0 | J41: 0 | K41: 0 | M41: 10000000 | N41: 10000000
F42: 0 | G42: 0 | H42: 0 | I42: 0 | J42: 0 | K42: 0 | M42: 0 | N42: 0
E43: ४अ. मागासवर्गीय कल्याणकारी योजना निधी एकूण बेरीज | F43: 0 | G43: 1214020350 | H43: 1214020350 | I43: 877520350 | J43: 109356223 | K43: 227143777 | M43: 219000000 | N43: 219000000
F44: 0 | G44: 0 | H44: 0 | I44: 0 | J44: 0 | K44: 0 | M44: 0 | N44: 0
E45: ४ब. महिलाबालकल्याण योजना निधी | F45: 0 | G45: 0 | H45: 0 | I45: 0 | J45: 0 | K45: 0 | M45: 0 | N45: 0
A46: 1 | B46: FE14C101 | D46: PL-FA | E46: महिलाबालकल्याण योजना | F46: 0 | G46: 432408734 | H46: 432408734 | I46: 354408734 | J46: 30529057 | K46: 47470943 | M46: 35000000 | N46: 35000000
A47: 2 | B47: FE14C108 | D47: PL-FA | E47: महिला सक्षमिकरणासाठी अनुदानाची योजना | F47: 0 | G47: 203676928 | H47: 203676928 | I47: 159176928 | J47: 12726500 | K47: 31773500 | M47: 27500000 | N47: 27500000
A48: 3 | B48: FE14C116 | D48: PL | E48: बचत गटाच्या शिखर संस्थेचा व्यवस्थापन खर्च | F48: 0 | G48: 13352681 | H48: 13352681 | I48: 13352681 | J48: 0 | K48: 0 | M48: 0 | N48: 0
A49: 4 | B49: FE14C117 | D49: PL | E49: बचत गटातील महिलांना कुटुंबनियोजनासाठी प्रोत्साहन | F49: 0 | G49: 3356160 | H49: 3356160 | I49: 3356160 | J49: 0 | K49: 0 | M49: 0 | N49: 0
A50: 5 | B50: FE14C118 | D50: PL | E50: नागरवस्तीच्या वापरातील समाजमंदिरे / इतर वास्तूंच्या विद्युत बिलांसाठी | F50: 0 | G50: 7388740 | H50: 7388740 | I50: 4388740 | J50: 1500000 | K50: 1500000 | M50: 1650000 | N50: 1650000
A51: 6 | B51: FE14C125# | C51: M1- | D51: SM1- | E51: महिलाबाल कल्याण योजना अंतर्गत करावयाची कामे | F51: 0 | G51: 253899930 | H51: 253899930 | I51: 70679930 | J51: 15876182 | K51: 167343818 | M51: 101000000 | N51: 101000000
A52: 7 | B52: FE14C134 | D52: PL-FA | E52: रस्त्यांवरील मुलांसाठी घरटे प्रकल्प | F52: 0 | G52: 101049174 | H52: 101049174 | I52: 61049174 | J52: 9899086 | K52: 30100914 | M52: 20000000 | N52: 20000000
A53: 8 | B53: FE14C135 | D53: PL-FA | E53: कन्यारत्न योजना | F53: 0 | G53: 1050000 | H53: 1050000 | I53: 750000 | J53: 0 | K53: 300000 | M53: 0 | N53: 0
A54: 9 | B54: FE14C136 | D54: PL | E54: कागदी पिशव्या तयार करणार्‍या बचत गटांना अनुदान | F54: 0 | G54: 1506610 | H54: 1506610 | I54: 1506610 | J54: 0 | K54: 0 | M54: 0 | N54: 0
A55: 10 | B55: FE14C139 | D55: PL-T | E55: UCD मार्फत राबविल्या जाणार्‍या निरनिराळया उपक्रमासाठी लागणारा खर्च स्वयंरोजगार, प्रशिक्षण, साहित्य खरेदी इ. | F55: 0 | G55: 16784856 | H55: 16784856 | I55: 8784856 | J55: 3720044 | K55: 4279956 | M55: 4000000 | N55: 4000000
A56: 11 | B56: FE14C140 | D56: PL-I | E56: पाळणाघर | F56: 0 | G56: 4977931 | H56: 4977931 | I56: 977931 | J56: 142839 | K56: 3857161 | M56: 10000000 | N56: 10000000
A57: 12 | B57: FE14C140A | E57: असंघटित / संघटीत क्षेत्रात काम करणाऱ्या स्त्रियांच्या सोयीसाठी पाळणाघर सुरू करणे | F57: 0 | G57: 20000000 | H57: 20000000 | I57: 0 | J57: 0 | K57: 20000000 | M57: 0 | N57: 0
A58: 13 | B58: FE14C142 | D58: PL-T | E58: शेजार समुहगट व इतर महिलांसाठी विविध स्पर्धा, उपक्रम घेणे | F58: 0 | G58: 7177474 | H58: 7177474 | I58: 3677474 | J58: 272310 | K58: 3227690 | M58: 0 | N58: 0
A59: 14 | B59: FE14C143 | D59: PL | E59: महिला व बाल कल्याण योजनेअंतर्गत विविध योजना राबविणेसाठी मानधन तत्वावरील सेवकांचा मानधन खर्च | F59: 0 | G59: 19684381 | H59: 19684381 | I59: 10684381 | J59: 2123424 | K59: 6876576 | M59: 5000000 | N59: 5000000
A60: 15 | B60: FE14C146 | D60: PL | E60: बालवाडी पोषण आहार | F60: 0 | G60: 90826738 | H60: 90826738 | I60: 90826738 | J60: 0 | K60: 0 | M60: 0 | N60: 0
A61: 16 | B61: FE14C147 | D61: PL | E61: अनैतिक व्यवसायात गुंतलेल्या महिलांसाठी व्यावसायिक प्रशिक्षण व स्वयंरोजगारासाठी अनुदान खर्च | F61: 0 | G61: 2371273 | H61: 2371273 | I61: 2371273 | J61: 0 | K61: 0 | M61: 0 | N61: 0
A62: 17 | B62: FE14C155 | D62: PL | E62: आधार केंद्र प्रशासकीय खर्च | F62: 0 | G62: 66042 | H62: 66042 | I62: 66042 | J62: 0 | K62: 0 | M62: 0 | N62: 0
A63: 18 | B63: FE14C156 | D63: PL | E63: युवतींसाठी विविध ठिकाणी स्वसंरक्षणाचे प्रशिक्षण देणे | F63: 0 | G63: 6262910 | H63: 6262910 | I63: 1262910 | J63: 588889 | K63: 4411111 | M63: 2500000 | N63: 2500000
A64: 19 | B64: FE14C160 | D64: PL-FA | E64: मुलगी दत्तक योजना | F64: 0 | G64: 33827000 | H64: 33827000 | I64: 13827000 | J64: 1440000 | K64: 18560000 | M64: 20000000 | N64: 20000000
A65: 20 | B65: FE14C191 | D65: PL-I | E65: बचत गटातील उत्पादित केलेल्या मालाचे प्रदर्शन आयोजित करणे | F65: 0 | G65: 26295784 | H65: 26295784 | I65: 6295784 | J65: 8767056 | K65: 11232944 | M65: 10000000 | N65: 10000000
A66: 21 | B66: FE14C192 | D66: PL | E66: मराठा चेंबर्स ऑफ कॉमर्स यांच्या संयुक्त विमाने इन्क्युबेशन सेंटर सुरू करणे | F66: 0 | G66: 0 | H66: 0 | I66: 0 | J66: 0 | K66: 0 | M66: 0 | N66: 0
A67: 22 | B67: FE14C193 | D67: PL | E67: अनैतिक व्यवसायात गुंतलेल्या महिलांच्या मुलांसाठी शैक्षणिक अर्थसहाय्य व समुपदेशक केंद्र खर्च | F67: 0 | G67: 0 | H67: 0 | I67: 0 | J67: 0 | K67: 0 | M67: 0 | N67: 0
A68: 23 | B68: FE14C208 | D68: PL-I | E68: पुणे शहरातील रस्त्यांवरील मुलांकरिता विविध उपक्रम राबविणे | F68: 0 | G68: 64750000 | H68: 64750000 | I68: 0 | J68: 0 | K68: 64750000 | M68: 50000000 | N68: 50000000
A69: 24 | B69: FE14C209 | D69: PL-T | E69: राणी लक्ष्मीबाई महिला सक्षमीकरण योजना | F69: 0 | G69: 55000000 | H69: 55000000 | I69: 0 | J69: 0 | K69: 55000000 | M69: 30000000 | N69: 30000000
... A71: 26 | B71: FE14C211 | D71: L-I | E71: १५ क्षेत्रिय कार्यालय येथे हिरकणी कक्ष सुरू करणे | F71: 0 | G71: 6000000 | H71: 6000000 | I71: 0 | J71: 328922 | K71: 5671078 | M71: 3000000 | N71: 3000000
A72: 27 | B72: FE14C212 | E72: महिला बचत गटांना रोजगार निर्मितीसाठी e-marketing साठी संकेतस्थळ सुरू करणे. | F72: 0 | G72: 7000000 | H72: 7000000 | I72: 0 | J72: 0 | K72: 7000000 | M72: 2500000 | N72: 2500000
A73: 28 | B73: FE14C213 | D73: PL-FA | E73: महिला मालमत्ता धारकांना सर्वसाधारण करामध्ये प्रोत्साहन म्हणून र.रू. ५००/- पर्यंत सुट देणे तसेच स्व कमाईतून उभारलेली मालमत्तेचा महिलेच्या अथवा मुलांच्या नावे समान हिस्सा दिल्यास १% अथवा जास्तीत जास्त ५०००/- पर्यंत मालमत्ता करामध्ये सवलत देणे | F73: 0 | G73: 9000000 | H73: 9000000 | I73: 0 | J73: 0 | K73: 9000000 | M73: 0 | N73: 0
A74: 29 | B74: FE14C214 | D74: PL-FA | E74: ज्या कंपनीमध्ये संचालक मंडळासह सर्व कर्मचारी १००% महिला असल्यास कंपनीच्या मालमत्ता करामध्ये १% जास्तीत जास्त अथवा रक्कम रू. १००००/- पर्यंत सवलत देणे | F74: 0 | G74: 1000000 | H74: 1000000 | I74: 0 | J74: 0 | K74: 1000000 | M74: 0 | N74: 0
A75: 30 | B75: FE14C215 | D75: PL-FA | E75: PMPML मार्फत चालविल्या जाणार्‍या महिलांसाठीच्या बसचा प्रवास महिन्यातून एकदा मोफत उपलब्ध करून देणे | F75: 0 | G75: 10000000 | H75: 10000000 | I75: 0 | J75: 0 | K75: 10000000 | M75: 0 | N75: 0
A76: 31 | B76: FE14C216 | D76: PL-S | E76: महिला बालकल्याण योजनेचा अभ्यास ऑडिट आणि सर्वेक्षण करणे | F76: 0 | G76: 1000000 | H76: 1000000 | I76: 0 | J76: 0 | K76: 1000000 | M76: 0 | N76: 0
A77: 32 | B77: FE14C217 | D77: L | E77: राणी लक्ष्मीबाई दत्तक योजना | F77: 0 | G77: 15000000 | H77: 15000000 | I77: 0 | J77: 0 | K77: 15000000 | M77: 15000000 | N77: 15000000
A78: 33 | B78: FE14C218 | D78: L | E78: अनाथ मुलांना शैक्षणिक सुविधा पुरविणे | F78: 0 | G78: 21000000 | H78: 21000000 | I78: 0 | J78: 0 | K78: 21000000 | M78: 21000000 | N78: 21000000
A79: 34 | B79: FE14C219 | D79: L | E79: स्वच्छ झोपडपट्टी स्पर्धा, झोपडीत घनकचरा व्यवस्थापनाचे उत्कृष्ट काम करणाऱ्या व्यक्तीं व संस्था यांना परितोषिक देणे | F79: 0 | G79: 2000000 | H79: 2000000 | I79: 0 | J79: 0 | K79: 2000000 | M79: 5000000 | N79: 5000000
A80: 35 | B80: FE14C220 | D80: L | E80: महिला व बालके यांचेसाठी स्पर्धा घेणे | F80: 0 | G80: 2000000 | H80: 2000000 | I80: 0 | J80: 0 | K80: 2000000 | M80: 0 | N80: 0
A81: 36 | B81: FE14C221 | D81: L | E81: स्त्री संसाधन केंद्र (सक्षमा कक्ष) चालविणे | F81: 0 | G81: 10000000 | H81: 10000000 | I81: 0 | J81: 0 | K81: 10000000 | M81: 10000000 | N81: 10000000
A82: 37 | B82: FE14C222 | D82: L | E82: Gender Responsibility अभ्यासगट तयार करणे व शहर पातळीवर महिलांच्या सुरक्षिततेसाठी उपाययोजना करणे | F82: 0 | G82: 5000000 | H82: 5000000 | I82: 0 | J82: 0 | K82: 5000000 | M82: 5000000 | N82: 5000000
A83: 38 | B83: FE14C223 | D83: L | E83: सार्वजनिक ठिकाणी महिलांच्या सुरक्षिततेसाठी safety mapping व safety audit करणे | F83: 0 | G83: 5000000 | H83: 5000000 | I83: 0 | J83: 0 | K83: 5000000 | M83: 5000000 | N83: 5000000
F84: 0 | G84: 0 | H84: 0 | I84: 0 | J84: 0 | K84: 0 | M84: 0 | N84: 0
E85: ४ब. महिलाबालकल्याण योजना निधी एकूण बेरीज | F85: 0 | G85: 1466713346 | H85: 1466713346 | I85: 807443346 | J85: 87914309 | K85: 571355691 | M85: 391150000 | N85: 391150000
F86: 0 | G86: 0 | H86: 0 | I86: 0 | J86: 0 | K86: 0 | M86: 0 | N86: 0
E87: ४क. युवक कल्याणकारी योजना निधी (नागरवस्ती विकास योजना) | F87: 0 | G87: 0 | H87: 0 | I87: 0 | J87: 0 | K87: 0 | M87: 0 | N87: 0
A88: 1 | B88: FE14D101 | D88: P-FA | E88: शहरातील तरुणांसाठी स्वयंरोजगार व प्रशिक्षणासाठी अनुदान देणे | F88: 0 | G88: 132647026 | H88: 132647026 | I88: 111397026 | J88: 12014431 | K88: 9235569 | M88: 10000000 | N88: 10000000
A89: 2 | B89: FE14D118 | D89: P-FA | E89: लोकशाहीर अण्णाभाऊ साठे शैक्षणिक मदत योजना व मौ. अब्दुल कलाम आझाद शैक्षणिक मदत योजना | F89: 0 | G89: 1115295588 | H89: 1115295588 | I89: 890795588 | J89: 111750000 | K89: 112750000 | M89: 120000000 | N89: 120000000
A90: 3 | B90: FE14D121 | E90: ज्येष्ठ नागरिकांसाठी विरंगुळा केंद्र सुरू करणे | F90: 0 | G90: 14250 | H90: 14250 | I90: 14250 | J90: 0 | K90: 0 | M90: 0 | N90: 0
A91: 4 | B91: FE14D122 | D91: P-I | E91: शहरात विविध ठिकाणी नाईट शेल्टर योजना राबविणे | F91: 0 | G91: 25103214 | H91: 25103214 | I91: 8103214 | J91: 2364944 | K91: 14635056 | M91: 20000000 | N91: 20000000
A92: 5 | B92: FE14D123 | D92: P | E92: प्रशिक्षण संस्थांतील शिक्षक व इतर कर्मचार्‍यांचे मानधन देणे | F92: 0 | G92: 21040594 | H92: 21040594 | I92: 7040594 | J92: 1917553 | K92: 12082447 | M92: 10000000 | N92: 10000000
A93: 6 | B93: FE14D124 | D93: P | E93: युवक / युवतींसाठी ग्रंथालय सुरू करणे (सावित्रीबाई फुले ग्रंथालय) | F93: 0 | G93: 0 | H93: 0 | I93: 0 | J93: 0 | K93: 0 | M93: 0 | N93: 0
A94: 7 | B94: FE14D125 | D94: P-I | E94: हॅलो माय फ्रेड योजना राबविणे,युवकांसाठी कॉल सेंटर सुरू करणे (मानसिक आरोग्य) | F94: 0 | G94: 3809807 | H94: 3809807 | I94: 409807 | J94: 0 | K94: 3400000 | M94: 1500000 | N94: 1500000
A95: 8 | B95: FE14D126 | D95: P-I | E95: नागरवस्ती विकास योजना विभागाच्या ताब्यात असणार्‍या जागेपोटी PMPML प्रशासनास भाडे देणे | F95: 0 | G95: 2550000 | H95: 2550000 | I95: 0 | J95: 0 | K95: 2550000 | M95: 5000000 | N95: 5000000
A96: 9 | B96: FE14D129 | D96: P-T | E96: स्पर्धा परिक्षा मार्गदर्शन केंद्र चालविणे | F96: 0 | G96: 5440000 | H96: 5440000 | I96: 340000 | J96: 544000 | K96: 4556000 | M96: 1000000 | N96: 1000000
A97: 10 | B97: FE14D131 | E97: लाव्हलीहुड अॅण्ड सिटीझन व्हॉलेंटरिंग सेंटर | F97: 0 | G97: 2484215 | H97: 2484215 | I97: 2484215 | J97: 0 | K97: 0 | M97: 0 | N97: 0
A98: 11 | B98: FE14D133 | E98: शरद स्वावलंबी जीवन योजनेअंतर्गत गवनि घोषित व शहरी गरीब योजनेअंतर्गत ज्येष्ठ नागरिकांना (पुरुष) दरमहा र.रु. 1,000 अर्थसहाय्‌य देणे | F98: 0 | G98: 0 | H98: 0 | I98: 0 | J98: 0 | K98: 0 | M98: 0 | N98: 0
A99: 12 | B99: FE14D134 | E99: स.नं. ६९ हडपसर येथे युथ गाईडन्स सेंटर उभारणे | F99: 0 | G99: 0 | H99: 0 | I99: 0 | J99: 0 | K99: 0 | M99: 0 | N99: 0
A100: 13 | B100: FE14D135 | E100: म. फुले संग्रहालय घोले रोड, शिवाजीनगर येथील एमपीएसी / युपीएसी विद्यार्थ्यांसाठी स्पर्धा परिक्षा मार्गदर्शन केंद्र सुरू करणे | F100: 0 | G100: 0 | H100: 0 | I100: 0 | J100: 0 | K100: 0 | M100: 0 | N100: 0
A101: 14 | B101: FE14D136 | D101: P-I | E101: पुणे शहरात Light House प्रकल्प सुरू करणे | F101: 0 | G101: 50000000 | H101: 50000000 | I101: 0 | J101: 0 | K101: 50000000 | M101: 35000000 | N101: 35000000
A102: 15 | B102: FE14D137 | D102: P-I | E102: समाज विकास केंद्रात अभ्यासिका सुरू करणे. | F102: 0 | G102: 3000000 | H102: 3000000 | I102: 0 | J102: 987000 | K102: 2013000 | M102: 0 | N102: 0
A103: 16 | B103: FE14D138 | E103: Digital Locker सुविधा उपलब्ध करणे | F103: 0 | G103: 1000000 | H103: 1000000 | I103: 0 | J103: 0 | K103: 1000000 | M103: 0 | N103: 0
A104: 17 | B104: FE14D139 | D104: P | E104: रोजगार निर्मितीसाठी पोर्टल सुरू करणे. | F104: 0 | G104: 0 | H104: 0 | I104: 0 | J104: 0 | K104: 0 | M104: 0 | N104: 0
...

Sheet A_DPDC_Machinery_Tree
A1: सन 2020-21 चे अंदाजपत्रक – खास निधीतून करावयाची योजनांतर्गत कामे
A2: अनुक्रमांक | B2: विवरण | F2: मान्य अंदाज 2019-20 | G2: नवीन अंदाज 2020-21
D3: 2017-18 | E3: 2018-19
C7: ५. पुणे जिल्हा नियोजन व विकास मंडळ निधीतून करावयाची कामे
C8: ५अ. मा. आमदारांनी सुचविल्याप्रमाणे करावयाची विकासाची कामे
A9: 1 | B9: FE15A101 | C9: बोपोडी मतदार संघ क्र. २४६ | D9: 0 | E9: 0 | F9: 5000000 | G9: 5000000
A10: 2 | B10: FE15A102 | C10: शिवाजीनगर मतदार संघ क्र. २४७ | D10: 8245720 | E10: 7569383 | F10: 5000000 | G10: 5000000
A11: 3 | B11: FE15A103 | C11: पर्वती मतदार संघ क्र. २४८ | D11: 7741474 | E11: 4049517 | F11: 5000000 | G11: 5000000
A12: 4 | B12: FE15A104 | C12: कसबा पेठ मतदार संघ क्र. २४९ | D12: 19590563 | E12: 17250785 | F12: 5000000 | G12: 5000000
A13: 5 | B13: FE15A105 | C13: भवानी पेठ मतदार संघ क्र. २५० | D13: 2233120 | E13: 0 | F13: 5000000 | G13: 5000000
A14: 6 | B14: FE15A106 | C14: पुणे (कॅन्टोन्मेंट) मतदार संघ क्र. २५१ | D14: 6010802 | E14: 6022891 | F14: 5000000 | G14: 5000000
A15: 7 | B15: FE15A107 | C15: विधान परिषद सदस्य | D15: 2598815 | E15: 1627378 | F15: 2500000 | G15: 2500000
D16: 0 | E16: 0 | F16: 0 | G16: 0
A17: 8 | B17: FE15A108 | C17: ५ब. मा. खासदारांनी सुचविल्याप्रमाणे करावयाची विकासाची कामे | D17: 12299310 | E17: 48067028 | F17: 20000000 | G17: 20000000
D18: 0 | E18: 0 | F18: 0 | G18: 0
A19: 9 | B19: FE15A110 | C19: महानगरपालिका क्षेत्रात मुलभूत सोईसुविधांसाठी विशेष अनुदान | D19: 43052096 | E19: 8971934 | F19: 0 | G19: 0
A20: 10 | B20: FE15A111 | C20: मुळशी मतदार संघ | D20: 0 | E20: 0 | F20: 2500000 | G20: 2500000
A21: 11 | B21: FE15A112 | C21: कोथरूड विधानसभा मतदार संघ | D21: 4660732 | E21: 2487968 | F21: 5000000 | G21: 5000000
A22: 12 | B22: FE15A113 | C22: हडपसर विधानसभा मतदार संघ | D22: 950400 | E22: 1486525 | F22: 5000000 | G22: 5000000
A23: 13 | B23: FE15A114 | C23: वडगांवशेरी विधानसभा मतदार संघ | D23: 0 | E23: 0 | F23: 5000000 | G23: 5000000
A24: 14 | B24: FE15A115 | C24: खडकवासला विधानसभा मतदार संघ | D24: 2531383 | E24: 0 | F24: 5000000 | G24: 5000000
A25: 15 | B25: FE15A117 | C25: सर्वसाधारण जिल्हा वार्षिक योजना अंतर्गत नाविन्यपूर्ण योजनांचा निधी | D25: 2499811 | E25: 0 | F25: 0 | G25: 0
A26: RE53A101 | C26: ५. पुणे जिल्हा नियोजन व विकास मंडळ निधीतून करावयाची कामे बेरीज | D26: 112414226 | E26: 97533409 | F26: 75000000 | G26: 75000000
D27: 0 | E27: 0 | F27: 0 | G27: 0
D28: 0 | E28: 0 | F28: 0 | G28: 0
C29: ७. यंत्रसामुग्री घसारा निधीतून विकत घ्याववयाची नवीन सामुग्री | D29: 0 | E29: 0 | F29: 0 | G29: 0
C30: अग्निशामक दलासाठी यंत्रसामुग्री :- | D30: 0 | E30: 0 | F30: 0 | G30: 0
B31: FE17A103-1 | C31: वॉटर टँकर पंपासह (2 नग) | D31: 9299998 | E31: 11680000 | F31: 39480000 | G31: 0
B32: FE17A103-2 | C32: फायर इंजिन गाडी (7 नग) | D32: 9300000 | E32: 29199998 | F32: 55440000 | G32: 56000000
B33: FE17A103-4 | C33: हायड्रोलिक प्लॅटफॉर्म | D33: 12798069 | E33: 0 | F33: 0 | G33: 0
B34: FE17A103-12 | C34: रेस्क्यू इक्वीपमेंट व लाईट मास्ट | D34: 7388960 | E34: 0 | F34: 28000000 | G34: 44000000
B35: FE17A103-31 | C35: मुख्य अग्निशमन अधिकारी यांचे कार्यालय वापरासाठी महेंद्र कंपनीचे स्कॉर्पीओ जीप खरेदी | D35: 0 | E35: 0 | F35: 0 | G35: 0
B36: FE17A107-23 | C36: आरोग्य विभागाकडील सरासरी आयुर्मान संपलेल्या आर्टीक्युलेटेड क्रेन निरस्त करून नवीन वाहने खरेदी करणे | D36: 0 | E36: 0 | F36: 0 | G36: 5600000
B37: FE17A114-6 | C37: बॅकहो लोडर खरेदी करणे | D37: 0 | E37: 4000200 | F37: 10500000 | G37: 0
B38: FE17A114-9 | C38: पथ विभागासाठी टिपर खरेदी करणे | D38: 0 | E38: 13749120 | F38: 10500000 | G38: 8000000
B39: FE17A114-10 | C39: पथ विभागाकडील कोठ्यांसाठी रोलर्स, मिक्‍सर्स, पेव्हर अन्य यंत्रसामुग्री खरेदी करणे | D39: 18701411 | E39: 0 | F39: 0 | G39: 0
B40: FE17A124 | C40: मोटार वाहन विभाग मशिनरी | D40: 124045 | E40: 81895 | F40: 1050000 | G40: 1600000
B41: FE17A146 | C41: मनपा पदाधिकारी व अधिकार्‍यांसाठी मोटारकार खरेदी करणे | D41: 9660473 | E41: 3145700 | F41: 7000000 | G41: 8000000
B42: FE17A149-3 | C42: कंटेनर दुरुस्ती व रंगवणे | D42: 1844372 | E42: 1973896 | F42: 1750000 | G42: 2000000
... B55: FE17A277# | C55: यंत्रसामुग्री घसारा निधीतून विकत घ्याववयाची सामुग्री (यादी Y1) | D55: 40925716 | E55: 40881598 | F55: 209200000 | G55: 106000000
D56: 0 | E56: 0 | F56: 0 | G56: 0
A57: RE51A101 | C57: ७. यंत्रसामुग्री घसारा निधी बेरीज | D57: 211333544 | E57: 244736988 | F57: 590000000 | G57: 384320000
D58: 0 | E58: 0 | F58: 0 | G58: 0
C59: १०. वृक्ष संरक्षण व संवर्धन प्राधिकारी निधीतून (अ‍ॅथॉरिटी फंडातून) करावयाचा खर्च | D59: 0 | E59: 0 | F59: 0 | G59: 0
C60: १०क. वृक्ष संवर्धन व संरक्षण कार्यालयाकडील खर्च :- | D60: 0 | E60: 0 | F60: 0 | G60: 0
B61: FE20A101A | C61: १. कायम सेवकवर्ग वेतन | D61: 32171322 | E61: 31913916 | F61: 55000000 | G61: 57750000
B62: FE20A102A | C62: २. हंगामी सेवकवर्ग | D62: 0 | E62: 0 | F62: 1000000 | G62: 1050000
D63: 0 | E63: 0 | F63: 0 | G63: 0
C64: १०क. बेरीज | D64: 32171322 | E64: 31913916 | F64: 56000000 | G64: 58800000
D65: 0 | E65: 0 | F65: 0 | G65: 0
C66: १०ग. संकीर्ण :- | D66: 0 | E66: 0 | F66: 0 | G66: 0
B67: FE20C101 | C67: १. मुद्रण | D67: 245100 | E67: 416140 | F67: 418000 | G67: 438900
B68: FE20C102 | C68: २. लेखन व साहित्य | D68: 10242 | E68: 264514 | F68: 550000 | G68: 577500
B69: FE20C103 | C69: ३. प्रकटन खर्च | D69: 0 | E69: 0 | F69: 1100000 | G69: 1155000
B70: FE20C104 | C70: ४. टपालखर्च व पावती तिकिटे | D70: 9960 | E70: 0 | F70: 110000 | G70: 115500
B71: FE20C105 | C71: ५. गणवेष | D71: 0 | E71: 0 | F71: 220000 | G71: 231000
B72: FE20C106 | C72: ६. पुस्तके व शिलकी साहित्य | D72: 0 | E72: 0 | F72: 110000 | G72: 115500
B73: FE20C107 | C73: ७. मुलांसाठी मनोरंजन व इतर खर्च | D73: 252267 | E73: 216769 | F73: 605000 | G73: 635250
B74: FE20C108 | C74: ८. ट्री अ‍ॅथॉरिटी सभा चहापान खर्च (न.स.) | D74: 12188 | E74: 0 | F74: 110000 | G74: 121000
D75: 0 | E75: 0 | F75: 0 | G75: 0
C76: १०ग. बेरीज | D76: 529757 | E76: 897423 | F76: 3223000 | G76: 3389650
D77: 0 | E77: 0 | F77: 0 | G77: 0
B78: FE20D101 | C78: नर्सरीच्या वाढीसाठी रोपे, उपकरणे, खते, साहित्य खरेदी व दुरुस्ती देखभाल | D78: 1136351 | E78: 1544104 | F78: 2200000 | G78: 2200000
B79: FE20Q101 | C79: पुणे शहरात शालेय विार्थ्यांसाठी पर्यावरणावर आधारित विविध उपक्रम राबविणे | D79: 0 | E79: 0 | F79: 379500 | G79: 200000
B80: FE20E101 | C80: ड. मनपातर्फे फळाफुलांचे प्रदर्शन | D80: 1212805 | E80: 1725000 | F80: 1897500 | G80: 1970000
B81: FE20G101 | C81: छ. वृक्ष लागवडीसाठी ३ ते ४ वर्षे वयाची व १० ते १५ फूट उंचीची रोपे, झाडांचे संरक्षणासाठी ट्री गार्ड खरेदी व जुने ट्री गार्ड दुरुस्ती | D81: 2527071 | E81: 2653704 | F81: 3795000 | G81: 4000000
B82: FE20H101 | C82: ज. झाडांची हालवाहलव | D82: 0 | E82: 931460 | F82: 1265000 | G82: 1300000
B83: FE20I101 | C83: ञ. मनपा सार्वजनिक जागेवरील वृक्षारोपण, संरक्षण देखभाल व तद्‌नुषंगिक खर्च | D83: 8203519 | E83: 4573903 | F83: 16500000 | G83: 20000000
B84: FE20K101 | C84: फ. ट्री अ‍ॅथॉरिटीस निरनिराळ्या ठिकाणी भेट देण्यासाठी खर्च | D84: 0 | E84: 0 | F84: 1518000 | G84: 1518000
B85: FE20L101 | C85: १०ब. वृक्षारोपण उत्तेजनार्थ बक्षिसे | D85: 332750 | E85: 0 | F85: 1265000 | G85: 1265000
B86: FE20M101 | C86: १०भ. कामगार नुकसान भरपाई कायाखाली नुकसानभरपाई | D86: 0 | E86: 0 | F86: 189750 | G86: 189750
B87: FE20N101 | C87: १०क्ष. वृक्षगणना व अनुषंगिक कामे | D87: 38817000 | E87: 28484982 | F87: 55000000 | G87: 30000000
B88: FE20P101 | C88: झाडांना पाणी घालण्यासाठी टँकर खरेदी करणे | D88: 0 | E88: 0 | F88: 8250000 | G88: 1200000
B89: FE20P103 | C89: टायर्स सुटे भाग व देखभाल | D89: 7989237 | E89: 7556692 | F89: 10120000 | G89: 12500000
... B114: FE20P132 | C114: प्र. क्र. 25 ब मधील वनविभागाच्या सर्व जागेवर वृक्ष लागवड करणे | D114: 0 | E114: 0 | F114: 0 | G114: 500000
D115: 0 | E115: 0 | F115: 0 | G115: 0
C116: १०. वृक्ष संरक्षण व संवर्धन प्राधिकारी निधीतून (अ‍ॅथॉरिटी फंडातून) करावयाचा खर्च एकूण बेरीज | D116: 103597963 | E116: 95235512 | F116: 213042250 | G116: 197238900
D117: 0 | E117: 0 | F117: 0 | G117: 0
B118: FE31A101 | C118: १९. संकल्प निधी | D118: 12952518 | E118: 8912638 | F118: 0 | G118: 0
D119: 0 | E119: 0 | F119: 0 | G119: 0
A120: • | C120: १९. संकल्प निधी बेरीज | D120: 12952518 | E120: 8912638 | F120: 0 | G120: 0

Sheet A_Capital_List
A1: पथ विभागाकडील कामाच्या याद्या
A3: यादी क्र. A2
A4: शहरामधील रस्ते विकसित करणे आणि डांबरीकरण करणे
A5: CE20A102/A2-
A7: क्र. | B7: code | C7: ward | D7: कामाचे नाव | E7: प्रकल्पीय रक्कम | F7: तरतूद
A9: 1 | B9: CE20A102/A2-202 | C9: 8 | D9: पुणे पेठ औंध, स.नं. 126 / 2 क, सि.स.नं. 1185 येथील रस्ता विकसनसाठी भूसंपादन करणे. | F9: 4000000
A10: 2 | B10: CE20A102/A2-203 | C10: 9 | D10: स.नं. 116, 118 व स.नं. 113 मधून जाणारा 24 मी.डी.पी. रस्त्याचे भूसंपादन करणे. | F10: 4000000
A11: 3 | B11: CE20A102/A2-204 | C11: 9 | D11: शिवशक्ती चौक पाषाण स.नं. 112 व 123 मधून जाणारा 24 मी. डी.पी. रस्त्याचे भूसंपादन करणे. | F11: 4000000
A12: 4 | B12: CE20A102/A2-205 | C12: 9 | D12: सुस ते पाषाण यांना जोडणारा स.नं. 134, 135, 136, 137, 138 व 140 मधून जाणारा 36 मी.डी.पी. रस्त्याचे भूसंपादन करणे. | F12: 6000000
A13: 5 | B13: CE20A102/A2-206 | C13: 9 | D13: बाणेर स.नं. 102 व 103 मधून जाणा-या 36 मी.डी.पी. रस्त्याचे भूसंपादन करणे. | F13: 6000000
A14: 6 | B14: CE20A102/A2-207 | C14: 9 | D14: पाषाण स.नं. 1, 2, 3, 4, 5, 6, 7, 10, 11, 12 व 13 मधून जाणा-या 30 मी. रस्त्याचे भूसंपादन करणे. | F14: 4000000
A15: 7 | B15: CE20A102/A2-208 | C15: 27 | D15: प्रभाग क्रमांक 27 मधील शिवनेरीनगर येथील 18 मी. डी.पी. रस्ता कुमार पृथ्वी पर्यंत भूसंपादन करणे. | F15: 8000000
A16: 8 | B16: CE20A102/A2-209 | C16: 40 | D16: प्रभाग क्रमांक 40, दत्तनगर चौक ते लेक विस्टा, जांभूळवाडी रस्ता रुंदीकरणासह विकसित करणे व भूसंपादन करणे. | F16: 4000000
A17: 9 | B17: CE20A102/A2-210 | C17: 3 | D17: विमाननगर येथील साकोरेनगर ते निको गार्डन रस्ता डांबरीकरण करणे. | F17: 3200000
A18: 10 | B18: CE20A102/A2-211 | C18: 3 | D18: प्रभाग क्रमांक 3 मधील हर्मेस ड्रोम सोसायटी ते गणपती चौक रस्ता डांबरीकरण करणे. | F18: 3200000
A19: 11 | B19: CE20A102/A2-212 | C19: 4 | D19: खराडी श्री.छत्रपती शिवाजी महाराज पुतळा ते यशवंतनगर रस्ता डांबरीकरण करणे. | F19: 3200000
A20: 12 | B20: CE20A102/A2-213 | C20: 9 | D20: पाषाण स.नं. 137 व 138 मधून जाणा-या 12 मी.डी.पी.रस्त्याचे डांबरीकरण करणे व पदपथ करणे. | F20: 3200000
... A56: 48 | B56: CE20A102/A2-249 | C56: 40 | D56: प्रभाग क्रमांक 40, मैत्री चौक ते वंडरसिटी पर्यंतचा रस्ता भूसंपादन करून डांबरीकरण करणे. | F56: 3200000
A57: 49 | B57: CE20A102/A2-250 | C57: G | D57: पुणे नगर सर्व्हिस रस्ता डांबरीकरण करणे व तद्नुषंगिक कामे करणे. | F57: 3200000
A58: 50 | B58: CE20A102/A2-251 | C58: 11 | D58: प्रभाग क्रमांक 11, शिवराय शाळा समोरील 24 मी.डी. रस्ता पुर्न:डांबरीकरण करणे. | F58: 2000000
A59: 51 | B59: CE20A102/A2-252 | C59: 20 | D59: पॉवर हाऊस चौक ते ए.डी.कॅम्प रस्ता पुर्न:डांबरीकरण करणे. | F59: 2400000
A60: 52 | B60: CE20A102/A2-253 | C60: 24 | D60: हेलन केलर रस्ता पुर्न:डांबरीकरण करणे. | F60: 3200000
A61: 53 | B61: CE20A102/A2-254 | C61: 24 | D61: प्रभाग क्रमांक 24 मध्ये सय्यद नगर रस्ता पुर्न:डांबरीकरण करणे. | F61: 4000000
A62: 54 | B62: CE20A102/A2-255 | C62: 27 | D62: प्रभाग क्रमांक 27 मधील युनिटी पार्क रस्ता पुर्न:डांबरीकरण करणे. | F62: 6400000
A63: 55 | B63: CE20A102/A2-256 | C63: 40 | D63: प्रभाग क्रमांक 40, कात्रज चौक ते मांगडेवाडी पर्यंतचा रस्ता पुर्न:डांबरीकरण करणे. | F63: 3200000
A64: 56 | B64: CE20A102/A2-257 | C64: 41 | D64: प्रभाग क्रमांक 41, कोंढवा बुद्रुक खडी मशीन चौक ते येवलेवाडी रस्ता पुर्न:डांबरीकरण करणे. | F64: 4800000
A65: 57 | B65: CE20A102/A2-258 | C65: 41 | D65: प्रभाग क्रमांक 41, येवलेवाडी कमान ते मनपा शाळेपर्यंत रस्ता पुर्न:डांबरीकरण करणे. | F65: 3200000
A66: 58 | B66: CE20A102/A2-259 | C66: 41 | D66: प्रभाग क्रमांक 41, कोंढवा बुद्रुक अग्नीशमन केंद्र ते मनपा व्हेईकल पार्कींगपर्यंत 18मी. डी.पी. रस्ता पुर्न:डांबरीकरण करणे. | F66: 3200000
F67: 0
D68: सन 2019-20 मधील अपूर्ण कामांसाठी सन 2020-21 मध्ये उपलब्ध केलेली तरतूद | F68: 0
A69: 59 | B69: CE20A102/SA2-1725 | D69: तळजाई ते सिंहगड रस्ता नव्याने रस्ता करणेसाठी बोगदा तयार करणेसाठी सल्लागार नेमणे व डी.पी.आर.करणे. | F69: 10400000
A70: 60 | B70: CE20A102/A2-106 | D70: हडपसर औदयोगिक वसाहतीमधील टाटा हनीवेल कंपनी जवळील हडपसर औद्योगिक वसाहत ते मगरपट्टच्या मागील 24.00 मी. HCMTR रस्ता जोडणारया डी.पी. रस्तच्या दोनही कॅनॉलवरील पुल बांधणे | F70: 20000000
A71: 61 | B71: CE20A102/A2-1109+ | D71: सन 2019-20 मधील कामे पुर्ण करणेसाठी व जुने देयकासाठी (पेडींग बिलासाठी) | F71: 112000000
A72: 62 | B72: CE20A102/A2-1590+ | D72: शिवणे खराडी नदीकाठचा रस्ता विकसित करणे डीर्फड | E72: 3180000000 | F72: 280000000
A73: 63 | B73: CE20A102/A2-1619 | C73: 35D | D73: प्र. क्र. ३५ ड मधील मौलाना आझाद रस्ता विकसित करणे. | E73: 12900000 | F73: 1600000
A74: 64 | B74: CE20A102/A2-911 | C74: 36 | D74: बिबवेवाडी मुख्य रस्ता विकसित करणे | E74: 192600000 | F74: 40000000
A75: 65 | B75: CE20A102/SA2-1681 | C75: 23D | D75: प.क्र.23 ड हडपसर गाव ससाणेनगर रोडवरील छोटा कॅनॉलवरील पुल बांधुन रस्त्याची रूंदी वाढवुन रस्ता विकसित करणे | F75: 2400000
A76: 66 | B76: CE20A102/SA2-1715 | C76: 32 | D76: वारजे येथील कॅनॉल रोड ते मुठानदी पात्रापर्यंत हायवेलगत 12 मीटर सर्व्हिंस रस्ता डांबरीकरण करणे, आर.सी.सी.कल्व्हर्ट बांधणे,आर.सी.सी. रिटेनिंग वॉल करणे. | F76: 4000000
A77: 67 | B77: CE20A102/SA2-914 | D77: औंध, जंगली महाराज रोड च्या धर्तीवर USDG प्रमाणे बावधन परिसर विकसित करणे | F77: 13200000
A78: 68 | B78: CE20A884/SA10-309 | C78: 35D | D78: प्र. क्र. ३५ ड मधील शिवदर्शन येथे विविध विकास कामे करणे. | F78: 1600000
A79: 69 | B79: CE20A102/SA2-2153 | C79: 19C | D79: प्रभाग क्र १९ क मधील विविध ठिकाणचे रस्ते डांबरीकरण करणे | F79: 2400000
D81: यादी क्र. A2 एकूण | E81: 3385500000 | F81: 691200000
A84: यादी क्र. SA2
A85: शहरामधील रस्ते विकसित करणे आणि डांबरीकरण करणे
A86: CE20A102/SA2-
A88: क्र. | B88: code | C88: ward | D88: कामाचे नाव | E88: प्रकल्पीय रक्कम | F88: तरतूद
A90: 1 | B90: CE20A102/SA2-1 | C90: 1A | D90: प्रभाग क्र.1अ मध्ये विविध ठिकाणी रस्ते डांबरीकरण करणे | F90: 2500000
A91: 2 | B91: CE20A102/SA2-2 | C91: 1B | D91: प्रभाग क्र.1ब, मध्ये विविध ठिकाणी रस्ते विकसित करणे | F91: 1000000
A92: 3 | B92: CE20A102/SA2-3 | C92: 1B | D92: प्रभाग क्र.1ब,कळस धानोरी येथे रस्ते विकसित करणे | F92: 1000000
A93: 4 | B93: CE20A102/SA2-4 | C93: 1B | D93: प्रभाग क्र.1ब, धानोरी कळस येथे रस्ते विकसित करणे | F93: 1000000
A94: 5 | B94: CE20A102/SA2-5 | C94: 1B | D94: प्रभाग क्र.1ब,गणेशनगर, विश्रांतवाडी, भैरवनगर, चौधरीनगर, धानोरी, मुंजाबावस्ती, कलवड येथे विविध ठिकाणी रस्ते विकसित करणे | F94: 1000000
A95: 6 | B95: CE20A102/SA2-6 | C95: 1B | D95: प्रभाग क्र.1ब,गणेश नगर,विश्रांतवाडी,भैरवनगर,चौधरीनगर येथे विविध ठिकाणी रस्ते विकसित करणे | F95: 1000000
A96: 7 | B96: CE20A102/SA2-7 | C96: 1B | D96: प्रभाग क्र.1ब,चौधरीनगर,धानोरी, मुंजाबावस्ती,कलवड येथे विविध ठिकाणी रस्ते विकसित करणे | F96: 1000000
A97: 8 | B97: CE20A102/SA2-8 | C97: 1B | D97: प्रभाग क्र.1ब, विश्रांतवाडी,भैरवनगर,कलवड येथे विविध ठिकाणी रस्ते विकसित करणे | F97: 1000000
A98: 9 | B98: CE20A102/SA2-9 | C98: 1B | D98: प्रभाग क्र.1ब, भैरवनगर,चौधरीनगर,धानोरी,मुंजाबावस्ती कलवड येथे विविध ठिकाणी रस्ते विकसित करणे | F98: 1000000
A99: 10 | B99: CE20A102/SA2-10 | C99: 1B | D99: प्रभाग क्र.1ब, धानोरी, मुंजाबावस्ती येथे विविध ठिकाणी रस्ते विकसित करणे | F99: 1000000
A100: 11 | B100: CE20A102/SA2-11 | C100: 1C | D100: प्रभाग क्र.1क, मध्ये विविध ठिकाणी रस्ते डांबरीकरण करणे,साईडपट्ट्या मारणे | F100: 2000000
A101: 12 | B101: CE20A102/SA2-12 | C101: 1C | D101: प्रभाग क्र.1क, लोहगाव परिसरात रस्ते विकसित करणे | F101: 2000000
... A824: 735 | B824: CE20A102/SA2-735 | C824: 41D | D824: प्र.क्र. 41 ड, कोंढवा बु. सुखसागरनगर, गोकुळनगर विविध ठिकाणी रस्ते विकसित करणे. | F824: 2500000
A825: 736 | B825: CE20A102/SA2-736 | C825: 16 | D825: प्रभाग क्र. 16, मध्ये विविध ठिकाणी रस्ते करणे. | F825: 1000000
A826: 737 | B826: CE20A102/SA2-737 | D826: शिवरामदादा तालीम ते गोविंद हलवाई चौक रस्ता करणे. | F826: 1000000
A827: 738 | B827: CE20A102/SA2-738 | D827: 126 गणेश पेठ भाजी आळी येथे रस्ता करणे. | F827: 1000000
A828: 739 | B828: CE20A102/SA2-739 | D828: कोथरूड मतदार संघात विविध ठिकाणी रस्ते करणे. | F828: 1000000
A829: 740 | B829: CE20A102/SA2-740 | D829: पर्वती मतदार संघात विविध ठिकाणी रस्ते कारणे. | F829: 1000000
A830: 741 | B830: CE20A102/SA2-741 | D830: कसबा मतदार संघात विविध ठिकाणी रस्ते करणे. | F830: 1000000
A831: 742 | B831: CE20A102/SA2-742 | D831: शिवाजीनगर मतदार संघात विविध ठिकाणी रस्ते करणे. | F831: 1000000
A832: 743 | B832: CE20A102/SA2-743 | D832: पुणे कॅन्टोन्मेट मतदार संघात विविध ठिकाणी रस्ते करणे. | F832: 1000000
A833: 744 | B833: CE20A102/SA2-744 | D833: वडगावशेरी मतदार संघात विविध ठिकाणी रस्ते करणे. | F833: 1000000
A834: 745 | B834: CE20A102/SA2-745 | D834: लोहगाव येथे विविध ठिकाणी गल्ली बोळात रस्ते करणे. | F834: 2000000
A835: 746 | B835: CE20A102/SA2-746 | C835: 15A | D835: प्रभाग क्र.15 अ, मध्ये शिवाजी रस्ता (राष्ट्रभूषण ते स्वारगेट) विकसित करणे. | F835: 5000000
A836: 747 | B836: CE20A102/SA2-747 | C836: 15A | D836: प्रभाग क्र.15 अ, मध्ये टिळक रस्ता डांबरीकरण करणे. | F836: 4000000
A837: 748 | B837: CE20A102/SA2-748 | C837: 15A | D837: प्रभाग क्र.15 अ, मध्ये केळकर रस्ता डांबरीकरण करणे. | F837: 4000000
A838: 749 | B838: CE20A102/SA2-749 | C838: 15A | D838: प्रभाग क्र.15 अ, मध्ये महात्मा फुले मंडई ते शनिपार रस्ता डांबरीकरण करणे. | F838: 4000000
A839: 750 | B839: CE20A102/SA2-750 | C839: 15A | D839: प्रभाग क्र.15 अ, मध्ये बाजीराव रस्ता डांबरीकरण करणे. | F839: 5000000
A840: 751 | B840: CE20A102/SA2-751 | C840: 15A | D840: प्रभाग क्र.15 अ, मध्ये बाजीराव रस्ता ते मामलेदार कचेरी रस्ता करणे. | F840: 2000000
A841: 752 | B841: CE20A102/SA2-752 | C841: 15A | D841: प्रभाग क्र.15 अ, मध्ये खजिना विहीर चौक परिसरातील रस्ते डांबरीकरण करणे. | F841: 1000000
A842: 753 | B842: CE20A102/SA2-753 | C842: 15A | D842: प्रभाग क्र.15 अ, मध्ये शुक्रवार पेठ साठे कॉलनी परिसरातील रस्ता करणे. | F842: 2000000
A843: 754 | B843: CE20A102/SA2-754 | C843: 15A | D843: प्रभाग क्र.15 अ, मध्ये सदाशिव पेठ रेणुका प्रशाला परिसरातील रस्ते करणे. | F843: 2000000
A844: 755 | B844: CE20A102/SA2-755 | C844: 15A | D844: प्रभाग क्र.15 अ, मध्ये सदाशिव पेठ पंताचा गोठ परिसरामध्ये रस्ते करणे. | F844: 1000000
A845: 756 | B845: CE20A102/SA2-756 | C845: 15A | D845: प्रभाग क्र.15 अ, मध्ये सदाशिव पेठ लज्जत हॉटेल परिसरामध्ये व प्रभागात रस्ता करणे. | F845: 2000000
A846: 757 | B846: CE20A102/SA2-757 | C846: 15A | D846: प्रभाग क्र.15 अ, मध्ये शुक्रवार पेठ चिंचेची तालीम परिसरामध्ये व प्रभागात रस्ता करणे. | F846: 2000000
... A849: 760 | B849: CE20A102/SA2-760 | C849: 8C | D849: प्रभाग क्र. 8 क मधील परिसरात विविध ठिकाणी डांबरीकरण करणे. | F849: 1000000
A850: 761 | B850: CE20A102/SA2-761 | D850: ऑचीड पॅलेस ते कड रस्ता विकसित करणे. | F850: 10000000
A851: 762 | B851: CE20A102/SA2-762 | D851: मोहम्मदवाडी स.नं. 20/26 मधील डीपी रस्ता विकसित करणे. | F851: 10000000
A852: 763 | B852: CE20A102/SA2-763 | D852: स.नं. 2 ते देसाई हॉस्पिटल मुख्य रस्ता विकसित करणे. | F852: 10000000
A853: 764 | B853: CE20A102/SA2-764 | C853: 30 | D853: प्रभाग क्र. 30 मध्ये जनता वसाहत मुख्य रस्ता विकसित करणे. | F853: 10000000
A854: 765 | B854: CE20A102/SA2-765 | C854: 30 | D854: प्रभाग क्र. 30 मध्ये नवश्या मारुती परिसरात रस्ता करणे. | F854: 10000000
A855: 766 | B855: CE20A102/SA2-766 | C855: 30 | D855: प्रभाग क्र. 30 मध्ये सरितानगर फेज 1, 2 मधील रस्ते करणे. | F855: 10000000
A856: 767 | B856: CE20A102/SA2-767 | C856: 30 | D856: प्रभाग क्र. 30 आशा हॉटेल ते दत्तवाडी चौक रस्ता करणे. | F856: 5000000
A857: 768 | B857: CE20A102/SA2-768 | D857: उंड्री स.नं. 16 / 1ब / 2 / 3 मधील रस्ते विकसित करणे व संरक्षक भिंत बांधणे. | F857: 10000000
A858: 769 | B858: CE20A102/SA2-769 | C858: 30 | D858: प्रभाग क्र. 30 मध्ये कॅनॉल लगतचा रस्ता विकसित करणे. | F858: 10000000
A859: 770 | B859: CE20A102/SA2-770 | C859: 38 | D859: प्रभाग क्र. 38 मध्ये गुजरवाडीकडे जाणा-या मुख्य 18 मीटर डीपी रस्त्याचे उर्वरित काम पूर्ण करणे व वरखडे नगर येथील 12 मीटर डीपी रस्ता विकसित करणे. | F859: 10000000
A860: 771 | B860: CE20A102/SA2-771 | D860: वडगाव बुद्रुक स.नं. 41 ते 42 जाधवनगर, सिंहगड कॉलेज येथील विकास आराखड्यातील रस्ता करणे. | F860: 15000000
A861: 772 | B861: CE20A102/SA2-772 | D861: वडगाव बुद्रुक स.नं. 54 ते 55 हायवे, शेळकेनगर, सन ओरोसीन सोसायटी येथील विकास आराखड्यातील रस्ता करणे. | F861: 15000000
A862: 773 | B862: CE20A102/SA2-773 | D862: वडगाव बुद्रुक येथील विकास आराखड्यातील पाउंजाई मंदिर ते अमरज्योत चौक रस्ता करणे. | F862: 10000000
A863: 774 | B863: CE20A102/SA2-774 | D863: पुणे कॅन्टोन्मेंट मतदार संघामध्ये विविध ठिकाणी रस्ते विकसित करणे व अनुषंगाने कामे करणे. | F863: 10000000
A864: 775 | B864: CE20A102/SA2-775 | C864: 36D | D864: प्रभाग क्र. 36 ड, मध्ये महावीर जवळ रस्ता करणे. | F864: 1000000
A865: 776 | B865: CE20A102/SA2-776 | C865: 36D | D865: प्रभाग क्र. 36 ड, मध्ये यश लॉन्सकडे जाणारा रस्ता करणे. | F865: 1000000
A866: 777 | B866: CE20A102/SA2-777 | C866: 36D | D866: प्रभाग क्र. 36 ड, मध्ये गणेश स्वीट ते पापळ वस्ती रस्ता करणे. | F866: 1000000
A867: 778 | B867: CE20A102/SA2-778 | C867: 36D | D867: प्रभाग क्र. 36 ड, मध्ये इंदिरानगर मुख्य रस्ता करणे. | F867: 7500000
...

Sheet C_Revenue_Income
A1: पाणीपुरवठा व जलोत्सारण प्रकल्पांतर्गत | G1: खास निधी 'क' चा जमेचा गोषवारा व तपशील
A2: विवरण | C2: नक्की आकडा | H2: 2019-20 वर्षाचा अंदाज | J2: 2020-21 वर्षाचा अंदाज | M2: 2019-20 वर्षाच्या मान्य अंदाजाशी तुलना केलेला 2020-21 वर्षाचा मा. स्थायी समितीने मान्यता दिलेला अंदाज
C3: 2016-17 | D3: 2017-18 | E3: 2018-19 | F3: 2018-19 शेवटची सहामाही | G3: 2019-20 पहिली सहामाही | H3: मान्य अंदाज | I3: दुरूस्त अंदाज | J3: मा. महापालिका आयुक्त यांनी सुचविलेला | K3: मा. स्थायी समितीने मान्यता दिलेला | L3: मा. महानगर- पालिकेने संमत केलेला
M5: अधिक | N5: कमी
A7: अधिनियमाप्रमाणे कमीत कमी रोख शिल्लक ठेवण्याची रक्कम जमेस धरून वर्षारंभीची शिल्लक | C7: 100000 | D7: 100000 | E7: 100000 | F7: 100000 | G7: 0 | H7: 100000 | I7: 100000 | J7: 100000 | K7: 100000 | L7: 0 | M7: 0 | N7: 0
C8: 0 | D8: 0 | E8: 0 | F8: 0 | G8: 0 | H8: 0 | I8: 0 | J8: 0 | K8: 0 | L8: 0 | M8: 0 | N8: 0
A9: १. पाणीपुरवठा (अति. न.अ.) | C9: 0 | D9: 0 | E9: 0 | F9: 0 | G9: 0 | H9: 0 | I9: 0 | J9: 0 | K9: 0 | L9: 0 | M9: 0 | N9: 0
A10: क. पाणीपट्टी साधारण पाणीपट्टी (कआकसंप्र) | B10: XI12A101 | C10: 1114584244 | D10: 1147803539 | E10: 1337732647 | F10: 225587270 | G10: 1325821932 | H10: 1773500000 | I10: 1773500000 | J10: 2610000000 | K10: 2610000000 | L10: 0 | M10: 836500000 | N10: 0
A11: ख. शासनाकडून (कआकसंप्र) | B11: XI12B101 | C11: 0 | D11: 0 | E11: 0 | F11: 0 | G11: 0 | H11: 100000 | I11: 100000 | J11: 100000 | K11: 100000 | L11: 0 | M11: 0 | N11: 0
A12: च. PMPML कडील मिळकतीवरील पाणीपट्टी (कआकसंप्र) | B12: XI12F101 | C12: 0 | D12: 0 | E12: 0 | F12: 0 | G12: 0 | H12: 100000 | I12: 100000 | J12: 100000 | K12: 100000 | L12: 0 | M12: 0 | N12: 0
A13: छ. जललाभ कर (Water Benefit Tax) (कआकसंप्र) | B13: XI12G101 | C13: 543166436 | D13: 519828924 | E13: 558386876 | F13: 148046386 | G13: 433807213 | H13: 928600000 | I13: 928600000 | J13: 1180000000 | K13: 1180000000 | L13: 0 | M13: 251400000 | N13: 0
A14: ग. पाणीपट्टी पाणीमापकानुसार (अति.न.अ.) | B14: XI12C101 | C14: 401229463 | D14: 545850894 | E14: 884181735 | F14: 287116123 | G14: 240063023 | H14: 2350000000 | I14: 2350000000 | J14: 1650000000 | K14: 1650000000 | L14: 0 | M14: 0 | N14: 700000000
A15: ग१. मीटर पाणीपट्टी थकबाकीपोटी जमा | B15: XI12C101A | C15: 0 | D15: 0 | E15: 0 | F15: 0 | G15: 0 | H15: 550000000 | I15: 550000000 | J15: 50000000 | K15: 50000000 | L15: 0 | M15: 0 | N15: 500000000
A16: ग२. गवनि खात्याअंतर्गत होणारी पाणीपट्टी जमा | B16: XI12C101B | C16: 10942484 | D16: 8191908 | E16: 14631177 | F16: 4633185 | G16: 8615370 | H16: 25000000 | I16: 25000000 | J16: 25000000 | K16: 25000000 | L16: 0 | M16: 0 | N16: 0
A17: अनधिकृत कनेक्शन नियमित करण्यापोटी जमा | B17: XI12S101 | C17: 739 | D17: 3067 | E17: 0 | F17: 0 | G17: 3070 | H17: 40000000 | I17: 40000000 | J17: 5000000 | K17: 5000000 | L17: 0 | M17: 0 | N17: 35000000
A18: घ. पाणीमापक भाडे | B18: XI12D101 | C18: 5473 | D18: 13202 | E18: 2741759 | F18: 2741759 | G18: 17 | H18: 75000000 | I18: 75000000 | J18: 2500000 | K18: 2500000 | L18: 0 | M18: 0 | N18: 72500000
A19: ड. नवीन नळ आकार नळदुरुस्ती व साफसफी (परतजमा) | B19: XI12E101 | C19: 7255295 | D19: 15447884 | E19: 6506111 | F19: 1853833 | G19: 3018500 | H19: 15000000 | I19: 15000000 | J19: 2500000 | K19: 2500000 | L19: 0 | M19: 0 | N19: 12500000
A20: ठ. कॉलनी रस्त्यावर पाईप टाकणे कामापोटी सुपरव्हिजन स्क्रुटीनी फी व अन्य जमा होणार | B20: XI12K101 | C20: 12393427 | D20: 10956334 | E20: 17461303 | F20: 5209272 | G20: 350817 | H20: 22500000 | I20: 22500000 | J20: 32500000 | K20: 32500000 | L20: 0 | M20: 10000000 | N20: 0
A21: ढ. जलकेंद्राच्या आवारांतील निवास स्थानापोटी जमा होणारे भाडे | B21: XI12L101 | C21: 1089901 | D21: 1412457 | E21: 0 | F21: 0 | G21: 0 | H21: 2000000 | I21: 2000000 | J21: 2000000 | K21: 2000000 | L21: 0 | M21: 0 | N21: 0
... A28: ण. अंदाजपत्रक 'अ' कडून वर्ग | B28: XI12M101 | C28: 2363450642 | D28: -696342303 | E28: 1955095785 | F28: 1955095785 | G28: 0 | H28: -820000000 | I28: -820000000 | J28: 831267000 | K28: 1243100000 | L28: 0 | M28: 2063100000 | N28: 0
C29: 0 | D29: 0 | E29: 0 | F29: 0 | G29: 0 | H29: 0 | I29: 0 | J29: 0 | K29: 0 | L29: 0 | M29: 0 | N29: 0
A30: १. बेरीज | C30: 4517524035 | D30: 1619170660 | E30: 4860707869 | F30: 2677408797 | G30: 2042767757 | H30: 5084100000 | I30: 5084100000 | J30: 6563267000 | K30: 6975000000 | L30: 0 | M30: 1890900000 | N30: 0
C31: 0 | D31: 0 | E31: 0 | F31: 0 | G31: 0 | H31: 0 | I31: 0 | J31: 0 | K31: 0 | L31: 0 | M31: 0 | N31: 0
A32: १अ. पुणे कॅन्टोन्मेंट पाणीपुरवठा जमा (अति.न.अ.) | C32: 0 | D32: 0 | E32: 0 | F32: 0 | G32: 0 | H32: 0 | I32: 0 | J32: 0 | K32: 0 | L32: 0 | M32: 0 | N32: 0
A33: (१) पाणीमापकानुसार पाणीपट्टी | B33: XI12Q101 | C33: 172872513 | D33: 74930244 | E33: 164167267 | F33: -35832733 | G33: 113521737 | H33: 200000000 | I33: 200000000 | J33: 210000000 | K33: 210000000 | L33: 0 | M33: 10000000 | N33: 0
A34: (२) H.E. Factory कडून येणारी जमा | B34: XI12Q102 | C34: 131099065 | D34: 156399237 | E34: 50889083 | F34: -19110917 | G34: 15765267 | H34: 75000000 | I34: 75000000 | J34: 85000000 | K34: 85000000 | L34: 0 | M34: 10000000 | N34: 0
C35: 0 | D35: 0 | E35: 0 | F35: 0 | G35: 0 | H35: 0 | I35: 0 | J35: 0 | K35: 0 | L35: 0 | M35: 0 | N35: 0
A36: १अ. बेरीज | C36: 303971578 | D36: 231329481 | E36: 215056350 | F36: -54943650 | G36: 129287004 | H36: 275000000 | I36: 275000000 | J36: 295000000 | K36: 295000000 | L36: 0 | M36: 20000000 | N36: 0
C37: 0 | D37: 0 | E37: 0 | F37: 0 | G37: 0 | H37: 0 | I37: 0 | J37: 0 | K37: 0 | L37: 0 | M37: 0 | N37: 0
A38: पुणे शहरात तंत्रशुध्द पध्दतीने पाणीपुरवठा करण्याची योजना (24x7) अनुदान (AMRUT) | B38: ZI12A111 | C38: 0 | D38: 0 | E38: 0 | F38: -750000000 | G38: 0 | H38: 0 | I38: 0 | J38: 0 | K38: 0 | L38: 0 | M38: 0 | N38: 0
A39: पुणे शहरात तंत्रशुध्द पध्दतीने पाणीपुरवठा (24x7) योजनेंतर्गत टाक्या बांधणेसाठी अनुदान (AMRUT) | B39: ZI12A111A | C39: 0 | D39: 399000000 | E39: 308700000 | F39: 308700000 | G39: 0 | H39: 500000000 | I39: 500000000 | J39: 310000000 | K39: 310000000 | L39: 0 | M39: 0 | N39: 190000000
A40: पुणे शहरात तंत्रशुध्द पध्दतीने पाणीपुरवठा करण्याची योजना (24x7) कर्जरोखे विक्री | B40: ZI12A112 | C40: 0 | D40: 2000000000 | E40: 0 | F40: 0 | G40: 0 | H40: 2000000000 | I40: 2000000000 | J40: 2000000000 | K40: 2000000000 | L40: 0 | M40: 0 | N40: 0
C41: 0 | D41: 0 | E41: 0 | F41: 0 | G41: 0 | H41: 0 | I41: 0 | J41: 0 | K41: 0 | L41: 0 | M41: 0 | N41: 0
A42: राष्ट्रीय नदीसुधारणा प्रकल्पातंर्गत (JICA) केंद्र सरकारकडून अनुदान | B42: ZI12A102 | C42: 259899999 | D42: 0 | E42: 317500000 | F42: 317500000 | G42: 0 | H42: 680000000 | I42: 680000000 | J42: 250000000 | K42: 250000000 | L42: 0 | M42: 0 | N42: 430000000
C43: 0 | D43: 0 | E43: 0 | F43: 0 | G43: 0 | H43: 0 | I43: 0 | J43: 0 | K43: 0 | L43: 0 | M43: 0 | N43: 0
A44: १. एकूण बेरीज | C44: 5081395612 | D44: 4249500141 | E44: 5701964219 | F44: 2498665147 | G44: 2172054761 | H44: 8539100000 | I44: 8539100000 | J44: 9418267000 | K44: 9830000000 | L44: 0 | M44: 1290900000 | N44: 0
C45: 0 | D45: 0 | E45: 0 | F45: 0 | G45: 0 | H45: 0 | I45: 0 | J45: 0 | K45: 0 | L45: 0 | M45: 0 | N45: 0
A46: २. गटारे व नाले सुधारणा (अति.न.अ.) | C46: 0 | D46: 0 | E46: 0 | F46: 0 | G46: 0 | H46: 0 | I46: 0 | J46: 0 | K46: 0 | L46: 0 | M46: 0 | N46: 0
A47: क. सफाईपट्टी (कआकसंप्र) | B47: XI23A101 | C47: 2148672982 | D47: 1941205852 | E47: 2085529792 | F47: -1010470208 | G47: 1598114042 | H47: 3961000000 | I47: 3961000000 | J47: 3400000000 | K47: 3400000000 | L47: 0 | M47: 0 | N47: 561000000
A48: घ. सुअरेज बेनिफीट टॅक्स (कआकसंप्र) | B48: XI23D101 | C48: 967066203 | D48: 896401311 | E48: 961744905 | F48: -718255095 | G48: 745079105 | H48: 1820000000 | I48: 1820000000 | J48: 2280000000 | K48: 2280000000 | L48: 0 | M48: 460000000 | N48: 0
A49: ग. ड्रेनेज / सलेज कनेक्शन व सेवावाढ आकार नियोजित बांधकाम क्षेत्रफळावर रु. ११ चौ. मि. | B49: XI23C101 | C49: 9116859 | D49: 7945543 | E49: 9453661 | F49: -546339 | G49: 3740029 | H49: 0 | I49: 0 | J49: 0 | K49: 0 | L49: 0 | M49: 0 | N49: 0
C50: 0 | D50: 0 | E50: 0 | F50: 0 | G50: 0 | H50: 0 | I50: 0 | J50: 0 | K50: 0 | L50: 0 | M50: 0 | N50: 0
A51: २. बेरीज | C51: 3124856044 | D51: 2845552706 | E51: 3056728358 | F51: -1729271642 | G51: 2346933176 | H51: 5781000000 | I51: 5781000000 | J51: 5680000000 | K51: 5680000000 | L51: 0 | M51: 0 | N51: 101000000
C52: 0 | D52: 0 | E52: 0 | F52: 0 | G52: 0 | H52: 0 | I52: 0 | J52: 0 | K52: 0 | L52: 0 | M52: 0 | N52: 0
A53: ३. डेव्हलपमेंट निधीकडून जमा Development Charges (बांधकाम नियोजन) | B53: XI23F101 | C53: 681398032 | D53: 1155272716 | E53: 1022164378 | F53: 1022164378 | G53: 0 | H53: 690000000 | I53: 690000000 | J53: 540000000 | K53: 540000000 | L53: 0 | M53: 0 | N53: 150000000
C54: 0 | D54: 0 | E54: 0 | F54: 0 | G54: 0 | H54: 0 | I54: 0 | J54: 0 | K54: 0 | L54: 0 | M54: 0 | N54: 0
A55: १. + २. + ३. एकूण बेरीज | C55: 8887649688 | D55: 8250325563 | E55: 9780856955 | F55: 1791557883 | G55: 4518987937 | H55: 15010100000 | I55: 15010100000 | J55: 15638267000 | K55: 16050000000 | L55: 0 | M55: 1039900000 | N55: 0
C56: 0 | D56: 0 | E56: 0 | F56: 0 | G56: 0 | H56: 0 | I56: 0 | J56: 0 | K56: 0 | L56: 0 | M56: 0 | N56: 0
A57: वर्षारंभीच्या शिलकेसह एकूण जमा | C57: 8887749688 | D57: 8250425563 | E57: 9780956955 | F57: 1791657883 | G57: 4518987937 | H57: 15010200000 | I57: 15010200000 | J57: 15638367000 | K57: 16050100000 | L57: 0 | M57: 1039900000 | N57: 0
C58: 0 | D58: 0 | E58: 0 | F58: 0 | G58: 0 | H58: 0 | I58: 0 | J58: 0 | K58: 0 | L58: 0 | M58: 0 | N58: 0
C59: 0 | D59: 0 | E59: 0 | F59: 0 | G59: 0 | H59: 0 | I59: 0 | J59: 0 | K59: 0 | L59: 0 | M59: 0 | N59: 0
A60: वजा : अंदाजपत्रक 'अ' कडून वर्ग | C60: 2363450642 | D60: -696342303 | E60: 1955095785 | F60: 1955095785 | G60: 0 | H60: -820000000 | I60: -820000000 | J60: 831267000 | K60: 1243100000 | L60: 0 | M60: 2063100000 | N60: 0
C61: 0 | D61: 0 | E61: 0 | F61: 0 | G61: 0 | H61: 0 | I61: 0 | J61: 0 | K61: 0 | L61: 0 | M61: 0 | N61: 0
A62: अंदाजपत्रक 'क' एकूण जमा | C62: 6524299046 | D62: 8946767866 | E62: 7825861170 | F62: -163437902 | G62: 4518987937 | H62: 15830200000 | I62: 15830200000 | J62: 14807100000 | K62: 14807000000 | L62: 0 | M62: 0 | N62: 1023200000

Sheet C_Revenue_Expenditure
A1: योजनेतर खर्च तपशील
A2: विवरण | D2: नक्‍की आकडा | G2: मान्य अंदाज 2019-20 | H2: नवीन अंदाज 2020-21
D3: 2016-17 | E3: 2017-18 | F3: 2018-19
A5: १. पाणीपुरवठा | D5: 0 | E5: 0 | F5: 0 | G5: 0 | H5: 0
A6: क. पाणीपुरवठा | D6: 0 | E6: 0 | F6: 0 | G6: 0 | H6: 0
A7: १. मध्यवर्ती कार्यालय, कायम सेवकवर्ग वेतन | B7: XE12A101A | D7: 24270905 | E7: 23580337 | F7: 21639240 | G7: 30000000 | H7: 23300000
A8: २अ. कायम सेवकवर्ग वेतन | B8: XE12A101B | D8: 129159922 | E8: 144923511 | F8: 133028605 | G8: 150000000 | H8: 140000000
A9: २ब. कायम सेवकवर्ग वेतन (वि.का.) | B9: XE12A###A | D9: 10793008 | E9: 9860217 | F9: 8092170 | G9: 15000000 | H9: 15000000
A10: ३. संकीर्ण | B10: XE12A103 | D10: 496203 | E10: 650931 | F10: 446243 | G10: 880000 | H10: 900000
A11: ४. पाण्याची किंमत (पर्वती पंपिंग स्टेशन) | B11: XE12A104 | D11: 130832460 | E11: 319936464 | F11: 793046040 | G11: 1360000000 | H11: 729000000
A12: ५. पाणी शुद्ध करणे व तद्‌नुषंगिक कामे करणे | B12: XE12A105 | D12: 68067821 | E12: 58867962 | F12: 50205650 | G12: 48000000 | H12: 64800000
A13: ६. प्रयोगशाळा देखभाल खर्च | B13: XE12A106 | D13: 956631 | E13: 227793 | F13: 0 | G13: 985000 | H13: 1080000
A14: ७-अ. पंपिंग वीज खर्च | B14: XE12A107 | D14: 479999999 | E14: 601043722 | F14: 693640000 | G14: 763800000 | H14: 792000000
A15: ९. कोठी इतर साहित्य खर्च | B15: XE12A109 | D15: 2975682 | E15: 1189931 | F15: 340813 | G15: 2080000 | H15: 2250000
A16: १२. पर्वती जलकेंद्रातील यंत्रसामुग्रीवरील घसारा (मु.ले.) | B16: XE12A112 | D16: 164000 | E16: 190000 | F16: 215000 | G16: 0 | H16: 0
A17: १४. जलप्रदूषण प्रतिबंधक खर्च | B17: XE12A115 | D17: 4823834 | E17: 2007642 | F17: 0 | G17: 3360000 | H17: 2700000
A18: १८. जलकेंद्र पाण्याच्या टाक्या येथे प्रकाश व्यवस्था व दूरध्वनी व्यवस्था | B18: XE12A120 | D18: 0 | E18: 0 | F18: 0 | G18: 640000 | H18: 900000
... A38: पर्वती जलकेंद्र प्रयोगशाळा येथे पाणी तपासणीसाठी लागणारी विविध उपकरणे व तद्‌नुषंगिक साहित्य खरेदी करणे | B38: XE12A146 | D38: 0 | E38: 359999 | F38: 0 | G38: 400000 | H38: 0
A39: क. बेरीज | D39: 957068541 | E39: 1278265818 | F39: 1799104371 | G39: 2477705000 | H39: 1981945000
D40: 0 | E40: 0 | F40: 0 | G40: 0 | H40: 0
A41: ख१. नळ खाते (स्वारगेट विभाग) | D41: 0 | E41: 0 | F41: 0 | G41: 0 | H41: 0
A42: १. कायम सेवक वर्ग वेतन | B42: XE12B101A | D42: 198416480 | E42: 215760319 | F42: 221769160 | G42: 220000000 | H42: 244000000
A43: २. संकीर्ण | B43: XE12B102 | D43: 799999 | E43: 652480 | F43: 463550 | G43: 720000 | H43: 648000
A44: ४. शहरांतील / नव्याने समाविष्ट गावांतील सर्व व्हॉल्व्हज्‌ चालू व बंद करणे | B44: XE12B107 | D44: 31092583 | E44: 36455792 | F44: 39585979 | G44: 30800000 | H44: 47250000
A45: ८. टँकरने पाणीपुरवठा करणे | B45: XE12B111 | D45: 16107816 | E45: 9305117 | F45: 14825987 | G45: 12000000 | H45: 19800000
A46: ९. कोठी व इतर साहित्य खरेदी | B46: XE12B112 | D46: 23841464 | E46: 20282433 | F46: 17886533 | G46: 25200000 | H46: 27000000
A47: १०. देखभाल दुरुस्ती : नळदुरुस्ती व स्वच्छता तातडीच्या दुरुस्त्या चेंबर करणे, आर.सी.सी, कव्हर बसविणे व तदनुषंगिक कामे करणे | B47: XE12B113 | D47: 44788541 | E47: 45376228 | F47: 47904841 | G47: 35200000 | H47: 50400000
A48: ११. टाक्‍यांची दुरुस्ती | B48: XE12B114 | D48: 0 | E48: 719282 | F48: 0 | G48: 640000 | H48: 926100
A49: पाणीपुरवठा विभागाकडील देखभाल दुरूस्तीची कामे (यादी X1) | B49: XE12B115# | D49: 20005303 | E49: 9880350 | F49: 2634964 | G49: 0 | H49: 30700000
D50: 0 | E50: 0 | F50: 0 | G50: 0 | H50: 0
A51: ख१. बेरीज | D51: 335052186 | E51: 338432001 | F51: 345071014 | G51: 324560000 | H51: 420724100
D52: 0 | E52: 0 | F52: 0 | G52: 0 | H52: 0
A53: ख२. नळ खाते (विभागीय कार्यालय) | D53: 0 | E53: 0 | F53: 0 | G53: 0 | H53: 0
A54: १. कायम सेवकवर्ग वेतन | B54: XE12B###A | D54: 36831303 | E54: 31495599 | F54: 23964490 | G54: 50000000 | H54: 40000000
A55: क्षेत्रीय कार्यालयाने करावयाची योजनेतर कामे | B55: XE12B301/W6-# | D55: 1380528 | E55: 0 | F55: 943661 | G55: 5450000 | H55: 0
A56: क्षेत्रीय कार्यालयाने नागरिकांच्या सहभागातून करावयाची योजनेतर कामे | B56: XE12B302/C6-# | D56: 8138352 | E56: 2161144 | F56: 2817441 | G56: 6800000 | H56: 10300000
D57: 0 | E57: 0 | F57: 0 | G57: 0 | H57: 0
A58: ख२. बेरीज | D58: 46350183 | E58: 33656743 | F58: 27725592 | G58: 62250000 | H58: 50300000
D59: 0 | E59: 0 | F59: 0 | G59: 0 | H59: 0
A60: ख. एकूण बेरीज | D60: 381402369 | E60: 372088744 | F60: 372796606 | G60: 386810000 | H60: 471024100
D61: 0 | E61: 0 | F61: 0 | G61: 0 | H61: 0
A62: ग. पाणीमापके | D62: 0 | E62: 0 | F62: 0 | G62: 0 | H62: 0
A63: १. पाणीमापके दुरुस्ती | B63: XE12C101 | D63: 0 | E63: 0 | F63: 0 | G63: 240000 | H63: 216000
A64: ३. संगणक यंत्रासाठी तयार करावयाच्या फॉर्मचा मुशाहिरा | B64: XE12C103 | D64: 180000 | E64: 151380 | F64: 0 | G64: 400000 | H64: 360000
A65: ४. मीटर बीले वाटप करणे | B65: XE12C104 | D65: 0 | E65: 0 | F65: 0 | G65: 320000 | H65: 288000
D66: 0 | E66: 0 | F66: 0 | G66: 0 | H66: 0
A67: ग. बेरीज | D67: 180000 | E67: 151380 | F67: 0 | G67: 960000 | H67: 864000
D68: 0 | E68: 0 | F68: 0 | G68: 0 | H68: 0
A69: च. मनपा सेवकांना द्यावयाचा महागाईभत्ता | B69: XE12F101 | D69: 2917610 | E69: 2318349 | F69: 1822664 | G69: 20000000 | H69: 20000000
A70: 7व्या वेतनआयोगापोटी द्यावयाच्या फरकाची रक्कम | B70: XE12G101 | D70: 0 | E70: 0 | F70: 0 | G70: 0 | H70: 50000000
A71: ज. सानुग्रह अनुदान | B71: XE12H101 | D71: 1497925 | E71: 38967247 | F71: 39452188 | G71: 60000000 | H71: 60000000
A72: झ. मनपा सेवकांना प्रवासभत्ता सवलतीसाठी द्यावयाची रक्कम | B72: XE12I101 | D72: 170500 | E72: 86000 | F72: 317000 | G72: 20000000 | H72: 20000000
A73: थ. सेवानिवृत्ती वेतन व तोषदान | B73: XE12K101 | D73: 170000000 | E73: 200000000 | F73: 184000000 | G73: 200000000 | H73: 300000000
A74: प. पेट्रोल, डिझेल, टायर्स, सुटे भाग, देखभाल, दुरुस्ती | B74: XE12M101 | D74: 6787777 | E74: 4987489 | F74: 4593077 | G74: 10000000 | H74: 9000000
A75: ज्ञ१. कर्ज उभारण्याचा खर्च, कर्जाचे हप्ते व व्याज (मु.ले.) | B75: XE12Z101 | D75: 280324000 | E75: 100656190 | F75: 152047800 | G75: 771800000 | H75: 751800000
D76: 0 | E76: 0 | F76: 0 | G76: 0 | H76: 0
A77: १. पाणीपुरवठा एकूण बेरीज | D77: 1800348722 | E77: 1997521217 | F77: 2554133706 | G77: 3947275000 | H77: 3664633100
D78: 0 | E78: 0 | F78: 0 | G78: 0 | H78: 0
A79: १अ. पुणे लष्कर व खडकी पाणीपुरवठा | D79: 0 | E79: 0 | F79: 0 | G79: 0 | H79: 0
A80: क१. लष्कर पाणीपुरवठा | D80: 0 | E80: 0 | F80: 0 | G80: 0 | H80: 0
A81: १. कायम सेवकवर्ग वेतन | B81: XE12N101A | D81: 154711302 | E81: 171815479 | F81: 164571931 | G81: 180000000 | H81: 184100000
A82: २. संकीर्ण | B82: XE12N102 | D82: 661556 | E82: 570212 | F82: 339066 | G82: 880000 | H82: 900000
A83: ३. पाण्याची किंमत | B83: XE12N103 | D83: 47149281 | E83: 47175046 | F83: 500000000 | G83: 100000000 | H83: 58500000
A84: ४. पाणी शुद्ध करणे, तद्‌नुषंगिक कामे करणे | B84: XE12N104 | D84: 7072354 | E84: 6120000 | F84: 9199955 | G84: 8480000 | H84: 10800000
A85: ५. प्रयोगशाळा सँपल टेस्टींगसाठी होणारा खर्च | B85: XE12N105 | D85: 401450 | E85: 720000 | F85: 0 | G85: 720000 | H85: 620000
A86: ६. पंपिंग वीज खर्च | B86: XE12N106 | D86: 158844185 | E86: 179699445 | F86: 250891228 | G86: 200000000 | H86: 220500000
A87: ८. कोठी व इतर साहित्य खर्च | B87: XE12N108 | D87: 0 | E87: 422 | F87: 452573 | G87: 640000 | H87: 900000
A88: ९. पंपाचे डिझेल इंजिनसाठी व इतर इंजिनसाठी लागणारे तेल | B88: XE12N109 | D88: 0 | E88: 330100 | F88: 0 | G88: 400000 | H88: 360000
A89: १३. पाणीपुरवठा केंद्र भवनाची देखभाल व दुरुस्ती | B89: XE12N117 | D89: 0 | E89: 0 | F89: 0 | G89: 400000 | H89: 1800000
A90: १६. पुणे लष्कर पाणीपुरवठा हद्दीतील व्हॉल्व्ह चालू करणे व बंद करणे | B90: XE12N120 | D90: 21309129 | E90: 21234286 | F90: 27371424 | G90: 22000000 | H90: 36000000
A91: १७. टँकरने पाणीपुरवठा करणे | B91: XE12N121 | D91: 23417337 | E91: 13382460 | F91: 23044690 | G91: 16000000 | H91: 26100000
A92: १९. देखभाल दुरुस्ती (यंत्रसामुग्री सुटे भाग, ट्रान्सफॉर्मर ऑईल, सर्किट ब्रेकर्स, विुत उपकरणांची देखभाल दुरूस्ती, बागकाम, भवनांची देखभाल दुरूस्ती, दिवाबत्ती, नळदुरूस्त्या व इतर दुरूस्त्या) | B92: XE12N123 | D92: 43913857 | E92: 35381571 | F92: 21084056 | G92: 23760000 | H92: 27000000
... A96: लष्कर व बंडगार्डन पाणीपुरवठा वितरण विभाग देखभाल दुरूस्ती | B96: XE12N127 | D96: 0 | E96: 0 | F96: 9927837 | G96: 8400000 | H96: 9000000
D97: 0 | E97: 0 | F97: 0 | G97: 0 | H97: 0
A98: क१. लष्कर पाणीपुरवठा बेरीज | D98: 463805433 | E98: 485206153 | F98: 1015240125 | G98: 573440000 | H98: 589180000
D99: 0 | E99: 0 | F99: 0 | G99: 0 | H99: 0
A100: क२. लष्कर पाणीपुरवठा (विभागीय कार्यालय) | D100: 0 | E100: 0 | F100: 0 | G100: 0 | H100: 0
A101: १. कायम सेवक वर्ग वेतन | B101: XE12N###A | D101: 4378290 | E101: 5087378 | F101: 5709141 | G101: 7500000 | H101: 10000000
D102: 0 | E102: 0 | F102: 0 | G102: 0 | H102: 0
A103: क२. बेरीज | D103: 4378290 | E103: 5087378 | F103: 5709141 | G103: 7500000 | H103: 10000000
D104: 0 | E104: 0 | F104: 0 | G104: 0 | H104: 0
A105: क. एकूण बेरीज | D105: 468183723 | E105: 490293531 | F105: 1020949266 | G105: 580940000 | H105: 599180000
D106: 0 | E106: 0 | F106: 0 | G106: 0 | H106: 0
A107: ख१. खडकी व SNDT चतुःश्रृंगी पाणीपुरवठा | D107: 0 | E107: 0 | F107: 0 | G107: 0 | H107: 0
A108: १. कायम सेवकवर्ग वेतन | B108: XE12P101A | D108: 16549329 | E108: 18694524 | F108: 16102534 | G108: 20000000 | H108: 19000000
A109: २. संकीर्ण | B109: XE12P102 | D109: 299534 | E109: 96474 | F109: 25737 | G109: 240000 | H109: 216000
A110: ३. पाण्याची किंमत | B110: XE12P103 | D110: 23791985 | E110: 24942539 | F110: 18145010 | G110: 70000000 | H110: 31500000
A111: ४. पाणी शुद्ध करणे व तद्‌नुषंगिक कामे करणे | B111: XE12P104 | D111: 0 | E111: 239250 | F111: 588800 | G111: 2080000 | H111: 2700000
A112: ६. पंपिंग वीज खर्च | B112: XE12P106 | D112: 5999980 | E112: 12275180 | F112: 13798530 | G112: 17000000 | H112: 17550000
A113: १०. कोठी व इतर साहित्य खर्च | B113: XE12P110 | D113: 242220 | E113: 7562 | F113: 1523759 | G113: 1920000 | H113: 2700000
A114: १७. टाक्‍यांची दुरुस्ती | B114: XE12P119 | D114: 1003984 | E114: 674254 | F114: 897502 | G114: 800000 | H114: 900000
A115: १८. देखभाल दुरुस्त्या : नळदुरुस्ती व तातडीच्या दुरुस्त्या इत्यादी | B115: XE12P120 | D115: 37704778 | E115: 28996371 | F115: 38291485 | G115: 33440000 | H115: 48600000
A116: १९. व्हॉल्व्ह सोड बंद करणे | B116: XE12P121 | D116: 12690315 | E116: 11458654 | F116: 15013778 | G116: 11760000 | H116: 18000000
A117: २०. टँकरने पाणीपुरवठा करणे | B117: XE12P122 | D117: 24553555 | E117: 21662258 | F117: 20543132 | G117: 17600000 | H117: 21600000
D118: 0 | E118: 0 | F118: 0 | G118: 0 | H118: 0
A119: ख. एकूण बेरीज | D119: 122835680 | E119: 119047066 | F119: 124930267 | G119: 174840000 | H119: 162766000
D120: 0 | E120: 0 | F120: 0 | G120: 0 | H120: 0
A121: 7व्या वेतनआयोगापोटी द्यावयाच्या फरकाची रक्कम | B121: XE12P118C | D121: 0 | E121: 0 | F121: 0 | G121: 0 | H121: 50000000
A122: ज सानुग्रह अनुदान | B122: XE12P118D | D122: 11527610 | E122: 11817540 | F122: 12052729 | G122: 60000000 | H122: 70000000
A123: च मनपा सेवकांना द्यावयाचा महागाई भत्ता | B123: XE12P118E | D123: 2302354 | E123: 2071765 | F123: 1146221 | G123: 20000000 | H123: 10000000
...

Sheet C_Revenue_List
A1: पाणीपुरवठा विभागाकडील कामाच्या याद्या
A3: यादी क्र. SX1
A4: पाणीपुरवठा विभागाकडील देखभाल दुरूस्तीची कामे
A5: XE12B115/SX1-
A7: क्र. | B7: code | C7: ward | D7: कामाचे नाव | E7: प्रकल्पीय रक्कम | F7: तरतूद
A9: 1 | B9: XE12B115/SX1-1 | C9: 2C | D9: प्रभाग क्र.2क,विविध ठिकाणी पाण्याची लाईन दुरूस्त करणे | F9: 1000000
A10: 2 | B10: XE12B115/SX1-2 | C10: 3A | D10: प्रभाग क्र.3अ,मध्ये पाणीपुरवठा विषयक दुरूस्ती कामे करणे | F10: 1000000
A11: 3 | B11: XE12B115/SX1-3 | C11: 3C | D11: प्रभाग क्र.3क, परिसरात पाणीपुरवठा व्हॉल्व्ह दुरूस्ती विषयक कामे करणे | F11: 1000000
A12: 4 | B12: XE12B115/SX1-4 | C12: 5D | D12: प्रभाग क्र.5ड मध्ये पाणीपुरवठा विषयक मेंटन्स विषयक कामे करणे | F12: 1000000
A13: 5 | B13: XE12B115/SX1-5 | C13: 6B | D13: प्रभाग क्र.6ब, मध्ये विविध ठिकाणी पिण्याच्या पाण्याच्या लाईनचे दुरूस्ती विषयक कामे करणे | F13: 500000
A14: 6 | B14: XE12B115/SX1-6 | C14: 9B | D14: प्रभाग क्र.9ब, मध्ये विविध ठिकाणी बोरवेल घेणे व बोरवेल दुरूस्ती विषयक कामे करणे | F14: 1000000
A15: 7 | B15: XE12B115/SX1-7 | C15: 14A | D15: प्रभाग क्र. 14 अ, मध्ये विविध ठिकाणी नळ कोंडाळे दुरुस्ती करणे. | F15: 500000
A16: 8 | B16: XE12B115/SX1-8 | C16: 17B | D16: प्रभाग क्र. 17 ब, मध्ये विविध नळ कोंडाळे दुरुस्ती करणे. | F16: 1000000
A17: 9 | B17: XE12B115/SX1-9 | C17: 17D | D17: प्रभाग क्र. 17 ड, मध्ये नळकोंडाळे दुरुस्ती विषयक कामे करणे. | F17: 1000000
A18: 10 | B18: XE12B115/SX1-10 | C18: 18A | D18: प्रभाग क्र.18 अ,मध्ये विविध नळकोंडाळे दुरूस्ती करणे | F18: 1000000
A19: 11 | B19: XE12B115/SX1-11 | C19: 18A | D19: प्रभाग क्र.18 अ, मध्ये पी.एम.सी.कॉलनी क्र.8 व 9 येथे पाण्याची टाकी दुरूस्त करणे | F19: 1000000
A20: 12 | B20: XE12B115/SX1-12 | C20: 18D | D20: प्रभाग क्र. 18 ड, मध्ये पुणे मनपा विविध ठिकाणी पिण्याच्या पाण्याच्या टाक्या साफसफाई करणे. | F20: 300000
... A24: 16 | B24: XE12B115/SX1-16 | C24: 36B | D24: प्रभाग क्र. 36 ब मध्ये पाणीपुरवठा देखभाल व दुरुस्तीविषयक कामे करणे. | F24: 1000000
A25: 17 | B25: XE12B115/SX1-17 | D25: लष्कर पाणीपुरवठयासाठी DPR तयार करणे | F25: 5000000
A26: 18 | B26: XE12B115/SX1-18 | D26: पुणे शहर व लगतच्या टेकडयांवर शहरी जलयुक्त शिवार योजना राबविणे | F26: 1000000
A27: 19 | B27: XE12B115/SX1-19 | D27: पुणे महानगरपालिका हद्दीमध्ये जलयुक्त शहर अभियान व जलशक्ती अभियान राबविणे | F27: 10000000
D29: यादी क्र. SX1 एकूण | E29: 0 | F29: 30700000
A32: यादी क्र. X2
A33: मलनिःस्सारण विभागाकडील देखभाल दुरूस्तीची कामे
A34: XE23A117/X2-
A36: क्र. | B36: code | C36: ward | D36: कामाचे नाव | E36: प्रकल्पीय रक्कम | F36: तरतूद
A38: 1 | B38: XE23A117/X2-190 | D38: निरी अगर अन्य शासकीय संस्था यांचेकडून पुणे महानगरपालिकेच्या विविध मैलापाणी शुध्दीकरण केंद्राची वार्षिक तपासणी तसेच मान्यताप्राप्त प्रयोगशाळेमधून पाण्याची तपासणी करुन घेणे. | F38: 1800000
A39: 2 | B39: XE23A117/X2-191 | D39: विठ्ठलवाडी मैलापाणी शुध्दीकरण केंद्र / उपसा केंद्र येथे सेकंडरी झोनमधील सेटलींक टँकमधील चॅनलमध्ये फरशी बसविणे आवारातील रस्ते डांबरीकरण करणे व तद्‌नुषंगिक दुरुस्ती कामे करणे. | F39: 1800000
A40: 3 | B40: XE23A117/X2-192 | D40: बहिरोबा मैलापाणी शुध्दीकरण केंद्र येथे डायजेस्टर / थिकनर विषयक दुरुस्ती कामे करणे व खराब झालेल्या लाईन्स बदलणे व तद्‌नुषंगिक कामे करणे. | F40: 1800000
A41: 4 | B41: XE23A117/X2-193 | D41: कोथरुड बावधन क्षेत्रिय कार्यालयाच्या अंतर्गत येणाऱ्या मुख्य मलवाहिन्यांची देखभाल व दुरुस्ती करणे तसेच तद्‌नुषंगिक कामे करणे. | F41: 3150000
A42: 5 | B42: XE23A117/X2-194 | D42: औध बाणेर क्षेत्रिय कार्यालयाच्या प्रभाग क्र. ८ अंतर्गत येणाऱ्या मुख्य मलवाहिन्यांची देखभाल व दुरुस्ती करणे तसेच तद्‌नुषंगिक कामे करणे. | F42: 2700000
A43: 6 | B43: XE23A117/X2-195 | D43: औध बाणेर क्षेत्रिय कार्यालयाच्या प्रभाग क्र. ९ अंतर्गत येणाऱ्या मुख्य मलवाहिन्यांची देखभाल व दुरुस्ती करणे तसेच तद्‌नुषंगिक कामे करणे. | F43: 2700000
A44: 7 | B44: XE23A117/X2-196 | D44: भैरवी नाल्यातील जागोजागी खचलेली मुख्य मलवाहिनी बदलणे तसेच देखभाल व दुरुस्ती करणे. | F44: 2700000
A45: 8 | B45: XE23A117/X2-197 | D45: बावधन परिसरातील नाल्यामधील मुख्य मलवाहिन्यांची देखभाल, दुरुस्ती तसेच तद्‌नुषंगिक कामे करणे. | F45: 2700000
A46: 9 | B46: XE23A117/X2-198 | D46: वारजे क्षेत्रिय कार्यालयाअंतर्गत येणाऱ्या मुख्य मलवाहिन्यांची देखभाल व दुरुस्ती करणे. | F46: 1800000
A47: 10 | B47: XE23A117/X2-199 | D47: शिवणे उत्तमनगर येथील अस्तित्वात असलेल्या जुन्या व जीर्ण झालेल्या मलवाहिन्यांची देखभाल व दुरुस्ती करणे. | F47: 2250000
A48: 11 | B48: XE23A117/X2-200 | D48: आंबेगाव खुर्द आणि आंबेगाव बुद्रुक येथील अस्तित्वात असलेल्या जुन्या व जीर्ण झालेल्या मलवाहिन्यांची देखभाल व दुरुस्ती करणे. | F48: 2250000
A49: 12 | B49: XE23A117/X2-201 | D49: पुणे मनपा हद्दीमध्ये नव्याने समाविष्ठ झालेल्या गावांमधील अस्तित्वातील मलवाहिन्यांची देखभाल, दुरुस्ती व तद्‌नुषंगिक तसेच इत्यादी कामे करणे. | F49: 2250000
... A93: 57 | B93: XE23A117/X2-247 | D93: हडपसर क्षेत्रिय कार्यालयाच्या परिसरातील भैरोबा नाला व त्याचे उपनाल्यात अतिवृष्टीमुळे नादुरुस्त झालेल्या मुख्य मलवाहिन्या व चेंबर्स दुरुस्ती करणे. | F93: 2700000
D95: यादी क्र. X2 एकूण | E95: 0 | F95: 131400000
A98: यादी क्र. SX2
A99: मलनिःस्सारण विभागाकडील देखभाल दुरूस्तीची कामे
A100: XE23A117/SX2-
A102: क्र. | B102: code | C102: ward | D102: कामाचे नाव | E102: प्रकल्पीय रक्कम | F102: तरतूद
A104: 1 | B104: XE23A117/SX2-1 | C104: 1A | D104: प्रभाग क्र.1अ मध्ये विविध ठिकाणी नालासफाई करणे | F104: 1000000
A105: 2 | B105: XE23A117/SX2-2 | C105: 1A | D105: प्रभाग क्र.1अ मध्ये ड्रेनेज लाईन साफसफाई करणे व चेंबर दुरूस्ती करणे | F105: 500000
A106: 3 | B106: XE23A117/SX2-3 | C106: 2A | D106: प्रभाग क्र.2,मध्ये शांतीनगर येथील शौचालय दुरूस्ती करणे आणि ड्रेनेज व चेंबर दुरूस्ती करणे | F106: 1000000
A107: 4 | B107: XE23A117/SX2-4 | C107: 2C | D107: प्रभाग क्र.2क, विविध ठिकाणी ड्रेनेज लाईन देखभाल दुरूस्ती विषयक कामे करणे | F107: 1000000
A108: 5 | B108: XE23A117/SX2-5 | C108: 2C | D108: प्रभाग क्र.2क,विविध ठिकाणी नादुरूस्त झालेले चेंबर व ड्रेनेज लाईन दुरूस्त करणे | F108: 1000000
A109: 6 | B109: XE23A117/SX2-6 | C109: 2D | D109: प्रभाग क्र.2ड,मधील विविध ठिकाणी खचलेले चेंबर दुरूस्ती व नविन लाईन टाकणे | F109: 1500000
A110: 7 | B110: XE23A117/SX2-7 | C110: 3B | D110: प्रभाग क्र.3ब,ड्रेनेज लाईनचे चेंबर कव्हर बदलणे व प्लास्टर करणे | F110: 1000000
A111: 8 | B111: XE23A117/SX2-8 | C111: 3D | D111: प्रभाग क्र.3ड, मधील इंदिरानगर येथे ड्रेनेज व चेंबर दुरूस्तीची कामे करणे | F111: 1000000
A112: 9 | B112: XE23A117/SX2-9 | C112: 3D | D112: प्रभाग क्र.3ड, मधील महात्मा गांधीनगर मध्ये चेंबर दुरूस्तीची कामे करणे | F112: 1000000
A113: 10 | B113: XE23A117/SX2-10 | C113: 3D | D113: प्रभाग क्र.3ड, मधील शांतीरक्षक, त्रिदलनगर व एच टाईप मध्ये चेंबर दुरूस्तीची कामे करणे | F113: 1000000
A114: 11 | B114: XE23A117/SX2-11 | C114: 3D | D114: प्रभाग क्र.3ड, मधील पानसरे वस्ती ते राजीव गांधी शाळेपर्यंतच्या भागात ड्रेनेज लाईनची दुरूस्ती करणे | F114: 1000000
A115: 12 | B115: XE23A117/SX2-12 | C115: 3D | D115: प्रभाग क्र.3ड, मधील मुख्य रस्त्याच्या पूर्व भागातील सर्व चेंबर दुरूस्त करणे | F115: 1000000
... A176: 73 | B176: XE23A117/SX2-73 | C176: 14B | D176: प्रभाग क्र.14 ब, मध्ये विविध ठिकाणी चेंबर दुरुस्ती विषयक कामे करणे. | F176: 1000000
A177: 74 | B177: XE23A117/SX2-74 | D177: ड्रेनेज लाईनमधील गाळ काढण्यासाठी प्रभागनिहाय छोटे जेटिंग मशीन, वाहन घेऊन कर्मचारी नियुक्ती करणे | F177: 10000000
D179: यादी क्र. SX2 एकूण | E179: 0 | F179: 87000000

Sheet C_Capital_Expenditure
A1: सन 2020-21 चे योजनांतर्गत | I1: खर्चाबाबतचे अंदाजपत्रक
A2: अनुक्रमांक | B2: मान्यतेचा ठराव क्र. दिनांक (कोड) | C2: प्रभाग क्रमांक | D2: BPL | E2: कामाचे नाव अगर वर्णन | F2: दि. 31 मार्च 2020 अखेरपर्यंत केलेली तरतूद | I2: दि. 31 मार्च 2019 पर्यंतचा खर्चाचा नक्‍की आकडा | J2: 2019-20 मधील खर्चाची अंदाजी रक्कम | L2: 2020-21 साठी अधिक तरतूद | N2: 2020-21 साठी एकूण तरतूद | O2: प्रकल्पीय रक्कम
F3: कर्जातून | G3: महसूल निधीतून | H3: एकूण | J3: प्रत्यक्ष उपलब्ध तरतूद | K3: कर्जातून तरतूद | L3: कर्जातून | M3: महसूल निधी व इतर निधी
E7: 1. पाणीपुरवठा विभाग | G7: 0 | H7: 0 | I7: 0 | J7: 0 | M7: 0 | N7: 0
G8: 0 | H8: 0 | I8: 0 | J8: 0 | M8: 0 | N8: 0
A9: 1 | B9: ZE16A103# | C9: P1- | D9: SP1- | E9: शहरामध्ये पाण्याच्या टाक्या बांधणे / बोअरवेल घेणे / जलशुध्दीकरण केंद्रे बांधणे आणि विद्युत / स्थापत्य / यांत्रिकीविषयक कामे करणे | G9: 71225000 | H9: 71225000 | I9: 48702034 | J9: 22522966 | M9: 241900000 | N9: 241900000
A10: 2 | B10: ZE16A104# | C10: P2- | D10: SP2- | E10: शहरामध्ये पाण्याच्या लाईन टाकणे | G10: 6803069983 | H10: 6803069983 | I10: 5961612743 | J10: 841457240 | M10: 626650000 | N10: 626650000
A11: 3 | B11: ZE16A106# | C11: _ | D11: _ | E11: शहरामध्ये पाण्याच्या टाक्या बांधणे / बोअरवेल घेणे | G11: 365293698 | H11: 365293698 | I11: 337366334 | J11: 27927364 | M11: 0 | N11: 0
A12: 4 | B12: ZE16A107# | C12: _ | D12: _ | E12: शहरामध्ये जलशुध्दीकरण केंद्रे बांधणे आणि विद्युत विषयक, स्थापत्य विषयक, यांत्रिकीविषयक कामे करणे | G12: 753060436 | H12: 753060436 | I12: 546607775 | J12: 206452661 | M12: 0 | N12: 0
G13: 0 | H13: 0 | I13: 0 | J13: 0 | M13: 0 | N13: 0
E14: 1. पाणीपुरवठा विभाग एकूण बेरीज | G14: 7992649117 | H14: 7992649117 | I14: 6894288886 | J14: 1098360231 | M14: 868550000 | N14: 868550000
G15: 0 | H15: 0 | I15: 0 | J15: 0 | M15: 0 | N15: 0
G16: 0 | H16: 0 | I16: 0 | J16: 0 | M16: 0 | N16: 0
E17: 2. मलनिःसारण विभाग | G17: 0 | H17: 0 | I17: 0 | J17: 0 | M17: 0 | N17: 0
G18: 0 | H18: 0 | I18: 0 | J18: 0 | M18: 0 | N18: 0
A19: 1 | B19: ZE16B102# | C19: D2- | D19: SD2- | E19: शहरामध्ये मलवाहिन्या विकसित करणे | G19: 7596517334 | H19: 7596517334 | I19: 6034421183 | J19: 1562096151 | M19: 1769900000 | N19: 1769900000
A20: 2 | B20: ZE16B103# | C20: D3- | D20: SD3- | E20: शहरामध्ये नाला चॅनलायझेशन करणे / नाल्याला सिमाभिंत बांधणे व तदनुषंगिक कामे करणे | G20: 543050037 | H20: 543050037 | I20: 178774824 | J20: 364275213 | M20: 431100000 | N20: 431100000
A21: 4 | B21: ZE16B105# | C21: D5- | D21: _ | E21: शहरामध्ये मैलापाणी शुध्दीकरण केंद्रे बांधणे आणि विद्युत / स्थापत्य / यांत्रिकीविषयक कामे करणे | G21: 232931117 | H21: 232931117 | I21: 65625133 | J21: 167305984 | M21: 50000000 | N21: 50000000
G22: 0 | H22: 0 | I22: 0 | J22: 0 | M22: 0 | N22: 0
E23: 2. मलनिःसारण विभाग एकूण बेरीज | G23: 8372498488 | H23: 8372498488 | I23: 6278821140 | J23: 2093677348 | M23: 2251000000 | N23: 2251000000
G24: 0 | H24: 0 | I24: 0 | J24: 0 | M24: 0 | N24: 0
E25: 3. पाणीपुरवठा प्रकल्प | G25: 0 | H25: 0 | I25: 0 | J25: 0 | M25: 0 | N25: 0
G26: 0 | H26: 0 | I26: 0 | J26: 0 | M26: 0 | N26: 0
A27: 1 | B27: ZE16C101# | C27: PR1- | E27: शहरामध्ये पाणीपुरवठा प्रकल्प अंतर्गत कामे करणे | G27: 6864809703 | H27: 6864809703 | I27: 5632912540 | J27: 1231897163 | M27: 618000000 | N27: 618000000
A28: 2 | B28: ZE16C102# | C28: PR2- | E28: राष्ट्रीय नदी सुधारणा योजना (JICA) | G28: 1133842394 | H28: 1133842394 | I28: 333778590 | J28: 800063804 | M28: 850000000 | N28: 850000000
A29: 3 | B29: ZE16C103# | C29: PR3- | E29: पुणे शहरात तंत्रशुध्द पध्दतीने पाणीपुरवठा करण्याची योजना (24x7) | G29: 6474351411 | H29: 6474351411 | I29: 1906921348 | J29: 4567430063 | M29: 3616000000 | N29: 3616000000
G30: 0 | H30: 0 | I30: 0 | J30: 0 | M30: 0 | N30: 0
E31: 3. पाणीपुरवठा प्रकल्प एकूण बेरीज | G31: 14473003508 | H31: 14473003508 | I31: 7873612478 | J31: 6599391030 | M31: 5084000000 | N31: 5084000000
G32: 0 | H32: 0 | I32: 0 | J32: 0 | M32: 0 | N32: 0
E33: 4. मलनिःसारण प्रकल्प | G33: 0 | H33: 0 | I33: 0 | J33: 0 | M33: 0 | N33: 0
G34: 0 | H34: 0 | I34: 0 | J34: 0 | M34: 0 | N34: 0
A35: 1 | B35: ZE16D101# | E35: मलनिःसारण प्रकल्प टप्पा क्र. १ | G35: 3312765570 | H35: 3312765570 | I35: 3312765570 | J35: 0 | M35: 0 | N35: 0
A36: 2 | B36: ZE16D102# | C36: MP2- | D36: MP2- | E36: शहरामध्ये मोठ्या व्यासाच्या मलवाहिन्या विकसित करणे | G36: 847802423 | H36: 847802423 | I36: 806001895 | J36: 41800528 | M36: 285100000 | N36: 285100000
A37: 3 | B37: ZE16D103# | C37: _ | D37: _ | E37: शहरामध्ये मैलापाणी शुध्दीकरण केंद्र उभारणे / पंपिंग स्टेशन उभारणे | G37: 138850000 | H37: 138850000 | I37: 6106864 | J37: 132743136 | M37: 0 | N37: 0
G38: 0 | H38: 0 | I38: 0 | J38: 0 | M38: 0 | N38: 0
E39: 4. मलनिःसारण प्रकल्प एकूण बेरीज | G39: 4299417993 | H39: 4299417993 | I39: 4124874329 | J39: 174543664 | M39: 285100000 | N39: 285100000
G40: 0 | H40: 0 | I40: 0 | J40: 0 | M40: 0 | N40: 0
E41: क्षेत्रिय कार्यालयाने करावयाची कामे | G41: 0 | H41: 0 | I41: 0 | J41: 0 | M41: 0 | N41: 0
G42: 0 | H42: 0 | I42: 0 | J42: 0 | M42: 0 | N42: 0
A43: • | B43: ZE16A115# | C43: W6 | E43: क्षेत्रिय कार्यालय : पाणीपुरवठा विभागाने करावयाची कामे | G43: 112242587 | H43: 112242587 | I43: 111492587 | J43: 750000 | M43: 0 | N43: 0
A44: • | B44: ZE16A117# | C44: C6 | E44: क्षेत्रिय कार्यालय : नागरिकांच्या सहभाग योजनेतून पाणीपुरवठा विभागाने करावयाची कामे | G44: 60775469 | H44: 60775469 | I44: 54109040 | J44: 6666429 | M44: 4500000 | N44: 4500000
G45: 0 | H45: 0 | I45: 0 | J45: 0 | M45: 0 | N45: 0
A46: • | B46: ZE16B113# | C46: W7 | E46: क्षेत्रिय कार्यालय : मलनिःसारण विभागाने करावयाची कामे | G46: 461048881 | H46: 461048881 | I46: 410980533 | J46: 50068348 | M46: 30150000 | N46: 30150000
A47: • | B47: ZE16B130# | C47: C7 | E47: क्षेत्रिय कार्यालय : नागरिकांच्या सहभाग योजनेतून मलनिःसारण विभागाने करावयाची कामे | G47: 169972367 | H47: 169972367 | I47: 162265398 | J47: 7706969 | M47: 16100000 | N47: 16100000
G48: 0 | H48: 0 | I48: 0 | J48: 0 | M48: 0 | N48: 0
E49: क्षेत्रिय कार्यालयाने करावयाची कामे एकूण बेरीज | G49: 804039304 | H49: 804039304 | I49: 738847558 | J49: 65191746 | M49: 50750000 | N49: 50750000
A51: • | B51: • | C51: • | D51: • | E51: 1. पाणीपुरवठा विभाग | F51: 0 | G51: 7992649117 | H51: 7992649117 | I51: 6894288886 | J51: 1098360231 | K51: 0 | L51: 0 | M51: 868550000 | N51: 868550000 | O51: 0
A52: • | B52: • | C52: • | D52: • | E52: क्षेत्रिय कार्यालय : पाणीपुरवठा विभागाने करावयाची कामे | F52: 0 | G52: 173018056 | H52: 173018056 | I52: 165601627 | J52: 7416429 | K52: 0 | L52: 0 | M52: 4500000 | N52: 4500000 | O52: 0
A53: • | B53: ZE16A | C53: XE12X101 | E53: 1. पाणीपुरवठा विभाग एकूण बेरीज | F53: 0 | G53: 8165667173 | H53: 8165667173 | I53: 7059890513 | J53: 1105776660 | K53: 0 | L53: 0 | M53: 873050000 | N53: 873050000 | O53: 0
A54: • | B54: • | C54: • | D54: •
A55: • | B55: • | C55: • | D55: • | E55: 2. मलनिःसारण विभाग | F55: 0 | G55: 8372498488 | H55: 8372498488 | I55: 6278821140 | J55: 2093677348 | K55: 0 | L55: 0 | M55: 2251000000 | N55: 2251000000 | O55: 0
A56: • | B56: • | C56: • | D56: • | E56: क्षेत्रिय कार्यालय : मलनिःसारण विभागाने करावयाची कामे | F56: 0 | G56: 631021248 | H56: 631021248 | I56: 573245931 | J56: 57775317 | K56: 0 | L56: 0 | M56: 46250000 | N56: 46250000 | O56: 0
A57: • | B57: ZE16B | C57: XE23X101 | E57: 2. मलनिःसारण विभाग एकूण बेरीज | F57: 0 | G57: 9003519736 | H57: 9003519736 | I57: 6852067071 | J57: 2151452665 | K57: 0 | L57: 0 | M57: 2297250000 | N57: 2297250000 | O57: 0
A58: • | B58: • | C58: • | D58: •
A59: • | B59: ZE16C | C59: XE41X101 | E59: 3. पाणीपुरवठा प्रकल्प एकूण बेरीज | F59: 0 | G59: 14473003508 | H59: 14473003508 | I59: 7873612478 | J59: 6599391030 | K59: 0 | L59: 0 | M59: 5084000000 | N59: 5084000000 | O59: 0
A60: • | B60: ZE16D | C60: XE41X102 | E60: 4. मलनिःसारण प्रकल्प एकूण बेरीज | F60: 0 | G60: 4299417993 | H60: 4299417993 | I60: 4124874329 | J60: 174543664 | K60: 0 | L60: 0 | M60: 285100000 | N60: 285100000 | O60: 0
A61: • | B61: • | C61: • | D61: •
A62: • | B62: ZE Total | C62: • | D62: • | E62: पाणीपुरवठा + मलनिःसारण + पाणीपुरवठा प्रकल्प + मलनिःसारण प्रकल्प : एकूण बेरीज | F62: 0 | G62: 35941608410 | H62: 35941608410 | I62: 25910444391 | J62: 10031164019 | K62: 0 | L62: 0 | M62: 8539400000 | N62: 8539400000 | O62: 0

Sheet C_Capital_List
A1: यादी क्र. P1
A2: शहरामध्ये पाण्याच्या टाक्या बांधणे / बोअरवेल घेणे / जलशुध्दीकरण केंद्रे बांधणे आणि विद्युत / स्थापत्य / यांत्रिकीविषयक कामे करणे
A3: ZE16A103/P1-
A5: क्र. | B5: code | C5: ward | D5: कामाचे नाव | E5: प्रकल्पीय रक्कम | F5: तरतूद
A7: 1 | B7: ZE16A103/P1-1 | D7: घोलेरोड क्षेत्रिय कार्यालया अंतर्गत बोअरवेल दुरुस्ती करणे | F7: 800000
A8: 2 | B8: ZE16A103/P1-2 | D8: औंध क्षेत्रिय कार्यालया अंतर्गत बोअरवेल दुरुस्ती करणे | F8: 800000
A9: 3 | B9: ZE16A103/P1-3 | C9: 7 | D9: प्रभाग क्र. 7 मध्ये विविध ठिकाणी बोअरवेल बसविणे | F9: 800000
A10: 4 | B10: ZE16A103/P1-4 | C10: 8 | D10: प्रभाग क्र. 8 मध्ये विविध ठिकाणी बोअरवेल बसविणे | F10: 800000
A11: 5 | B11: ZE16A103/P1-5 | C11: 9 | D11: प्रभाग क्र.9 मध्ये विविध ठिकाणी बोअरवेल बसविणे | F11: 800000
A12: 6 | B12: ZE16A103/P1-6 | C12: 14 | D12: प्रभाग क्र.14 मध्ये विविध ठिकाणी बोअरवेल बसविणे | F12: 800000
A13: 7 | B13: ZE16A103/P1-7 | D13: पर्वती जलकेंद्र येथील रॉ वॉटर पंपिंग स्टेशन देखभाल दुरूस्ती विषयक कामे करणे. | F13: 8000000
A14: 8 | B14: ZE16A103/P1-8 | D14: पर्वती जलकेंद्रातील बेड वॉशिंगचे पाणी अत्याधूनिक यंत्राद्‌वारे रिसायलिंग करणे | F14: 4000000
A15: 9 | B15: ZE16A103/P1-9 | D15: पर्वती जलकेंद्र येथे पंप हाऊस क्र.१,२ व ३ साठी ए.पी.एफ.सी. युनिट पुरविणे व बसविणे. | F15: 4000000
A16: 10 | B16: ZE16A103/P1-10 | D16: पर्वती जलकेंद्रातील पंप हाऊस क्र.२ मधील एस.एन.डी.टी. झोनसाठीच्या पंपाच्या डिलेव्हरी साईडचे व्हॉल्व्ह बदलणे. | F16: 2400000
A17: 11 | B17: ZE16A103/P1-11 | D17: पर्वती जलकेंद्रातील पंप हाऊस क्र.१ व संपवेल जवळील नाला चॅनेलायझिंग करणे. | F17: 4000000
A18: 12 | B18: ZE16A103/P1-12 | D18: पर्वती जलकेंद्र येथील सेकंड स्टेजकडील बेड वॉशिंगकरीता ७.५ एच.पी. क्षमतेचा कॉम्प्रेसर पुरविणे व बसविणे | F18: 1200000
A19: 13 | B19: ZE16A103/P1-13 | D19: पर्वती जलकेंद्र येथील सेंकंड स्टेजकडील क्लॅरिफायर क्र.३ चे क्लॅरिफॉक्युलेटर, गिअर असेंब्ली पुरविणे व बसविणे | F19: 2000000
A20: 14 | B20: ZE16A103/P1-14 | D20: पर्वती जलकेंद्राकडील सेकंड स्टेजकडील फिल्टर बेडच्या व्हॉल्व्हसाठी इलेक्ट्रीकल अ‍ॅक्च्युएटर बसवून, सेमि ऑटोमेशन करणे. | F20: 2800000
A21: 15 | B21: ZE16A103/P1-15 | D21: पर्वती जलकेंद्रातील फिल्टर विभागातील बेड वॉशिंगसाठी सबमर्सिबल पंपसेट पुरविणे व बसविणे. | F21: 2000000
A22: 16 | B22: ZE16A103/P1-16 | D22: पर्वती जलकेंद्र २ रा टप्पा फिल्टर बेडची वाळू बदलणे व रिगे्रडेशन करणे. | F22: 4000000
A23: 17 | B23: ZE16A103/P1-17 | D23: रॉ वॉटर पंपिंग स्टेशन येथे पंप बसविणे व तद्‌नुषंगिक कामे करणे. | F23: 1200000
A24: 18 | B24: ZE16A103/P1-18 | D24: पुणे महानगरपालिका हद्दीत नव्याने समाविष्ट गावांतील विविध ठिकाणचे पंपसेट बदलणे. | F24: 2000000
... A82: 76 | B82: ZE16A103/P1-76 | D82: वारजे व खडकवासला येथे पंप पुरविणे व बसविणे | F82: 8000000
F83: 0
D84: सन 2019-20 मधील अपूर्ण कामांसाठी सन 2020-21 मध्ये उपलब्ध केलेली तरतूद | F84: 0
A85: 77 | B85: ZE16A107/P8-251 | D85: पुणे शहरामधील विविध जलशुध्दीकरण केंद्रामध्ये विद्युत / यांत्रिकीविषयक कामे करणे | F85: 6000000
A86: 78 | B86: ZE16A107/P8-178 | D86: रावेत जलउपसाकेंद्र येथे 335 एच.पी. क्षमतेचा पंप मोटरसेट पुरविणे व बसविणे. | E86: 1750000 | F86: 1400000
A87: 79 | B87: ZE16A107/P8-179 | D87: चिखली जलशुध्दीकरण केंद्र येथे 225 एच.पी. क्षमतेचा पंप मोटरसेट पुरविणे व बसविणे. | E87: 1750000 | F87: 1400000
A88: 80 | B88: ZE16A107/SP8-1 | D88: लष्कर जलशुध्दीकरण केंद्राची नव्याने उभारणे करणे | E88: 1750000000 | F88: 2000000
D90: यादी क्र. P1 एकूण | E90: 1753500000 | F90: 219600000
A93: यादी क्र. SP1
A94: शहरामध्ये पाण्याच्या टाक्या बांधणे / बोअरवेल घेणे / जलशुध्दीकरण केंद्रे बांधणे आणि विद्युत / स्थापत्य / यांत्रिकीविषयक कामे करणे
A95: ZE16A103/SP1-
A97: क्र. | B97: code | C97: ward | D97: कामाचे नाव | E97: प्रकल्पीय रक्कम | F97: तरतूद
A99: 1 | B99: ZE16A103/SP1-201 | C99: 4D | D99: प्रभाग क्र 4ड विविध ठिकाणी गार्डन प्लेग्राऊंड बोर घेणे | F99: 1000000
A100: 2 | B100: ZE16A103/SP1-202 | C100: 5A | D100: प्रभाग क्र.5अ मध्ये विविध ठिकाणी बोरवेल रिपेरिंग करणे व तद्‌नंषिक कामे करणे. | F100: 1000000
A101: 3 | B101: ZE16A103/SP1-203 | C101: 5B | D101: प्रभाग क्र.5ब,मध्ये विविध ठिकाणी बोरवेल रिपेरिंग करणे | F101: 500000
A102: 4 | B102: ZE16A103/SP1-204 | C102: 5D | D102: प्रभाग क्र.5ड मध्ये विविध ठिकाणी बोरवेल रिपेरिंग करणे | F102: 1000000
A103: 5 | B103: ZE16A103/SP1-205 | C103: 7A | D103: प्रभाग क्र.7अ, मध्ये विविध ठिकाणी बोअरवेल दुरूस्ती करणे व नवीन बोअरवेल बांधणे | F103: 1000000
A104: 6 | B104: ZE16A103/SP1-206 | C104: 11A | D104: प्रभाग क्र.11 अ, मध्ये किष्किंधानगर या भागात 3 लाख लिटर क्षमता असलेली पिण्याच्या पाण्याची टाकी बांधणे. | F104: 2000000
A105: 7 | B105: ZE16A103/SP1-207 | C105: 12B | D105: प्रभाग क्र. 12 ब, मध्ये विविध मनपा इमारतींसाठी रीडो टेक्नॉलॉजी आधारित अत्याधुनिक जलशुद्धीकरण यंत्रणा पुरविणे व बसविणे. | F105: 1000000
A106: 8 | B106: ZE16A103/SP1-208 | C106: 18D | D106: प्रभाग क्र. 18 ड, मध्ये विविध ठिकाणी नवीन नळ कोंडाळे बांधणे. | F106: 300000
A107: 9 | B107: ZE16A103/SP1-209 | C107: 20A | D107: प्रभाग क्र.20अ, मध्ये ताडीवाला रोड परिसरामध्ये विविध ठिकाणी बोरवेल दुरूस्ती विषयक कामे करणे | F107: 500000
A108: 10 | B108: ZE16A103/SP1-210 | C108: 21D | D108: प्रभाग क्र. 21 ड, मध्ये प्रभागामध्ये विविध ठिकाणी बोरिंग बनविणे. | F108: 1000000
A109: 11 | B109: ZE16A103/SP1-211 | C109: 29A | D109: प्रभाग क्र. 29 अ मध्ये उदयानात संपवेल बांधून टँकर पॉईंट चालू करणे | F109: 2000000
A110: 12 | B110: ZE16A103/SP1-212 | C110: 29C | D110: प्रभाग क्र.29क येथे विविध ठिकाणी वॉटर फिल्टर व वॉटर कुलर पुरविणे | F110: 1000000
... A114: 16 | B114: ZE16A103/SP1-216 | C114: 14B | D114: प्रभाग क्र.14 ब, मध्ये विविध ठिकाणी बोर मारणे. | F114: 1000000
A115: 17 | B115: ZE16A103/SP1-217 | D115: आदर्श पाणी पुरवठा योजनेचे प्रमुख घटक असणा-या शहरातील पिण्याच्या पाण्याच्या हौदांचे पुनर्जीवन करणे. (उदा.बदामी हौद, पुष्करणी हौद) | F115: 5000000
A116: 18 | B116: ZE16A103/SP1-218 | C116: 8A | D116: प्रभाग क्र. 8 अ मध्ये विविध ठिकाणी बोअरवेल कामे करणे. | F116: 1000000
D118: यादी क्र. SP1 एकूण | E118: 0 | F118: 22300000
A121: यादी क्र. P2
A122: शहरामध्ये पाण्याच्या लाईन टाकणे
A123: ZE16A104/P2-
A125: क्र. | B125: code | C125: ward | D125: कामाचे नाव | E125: प्रकल्पीय रक्कम | F125: तरतूद
A127: 1 | B127: ZE16A104/P2-201 | C127: 42 | D127: नव्याने समाविष्ठ 11 गावांमध्ये पाणीपुरवठा विषयक व इतर विकास कामे करणे | F127: 96000000
A128: 2 | B128: ZE16A104/P2-202 | C128: 28 | D128: प्रभाग क्र.२८ मध्ये नव्याने जलवाहिनी विकसित करणे व इतर कामे करणे | F128: 1600000
A129: 3 | B129: ZE16A104/P2-203 | C129: 30 | D129: प्रभाग क्र.३० मध्ये नव्याने जलवाहिनी विकसित करणे व इतर कामे करणे | F129: 2800000
A130: 4 | B130: ZE16A104/P2-204 | C130: 33 | D130: प्रभाग क्र. 33 मध्ये नव्याने जलवाहिनी विकसित करणे व इतर कामे करणे | F130: 3600000
A131: 5 | B131: ZE16A104/P2-205 | C131: 34 | D131: प्रभाग क्र. 34 विविध ठिकाणी पाण्याची लार्इन टाकणे व इतर कामे करणे . | F131: 2400000
A132: 6 | B132: ZE16A104/P2-206 | C132: 35 | D132: प्रभाग क्र. 3५ विविध ठिकाणी पाण्याची लार्इन टाकणे व इतर कामे करणे . | F132: 4000000
A133: 7 | B133: ZE16A104/P2-207 | C133: 36 | D133: प्रभाग क्र. 3६ विविध ठिकाणी पाण्याची लार्इन टाकणे व इतर कामे करणे . | F133: 1200000
A134: 8 | B134: ZE16A104/P2-208 | C134: 36 | D134: प्रभाग क्र. 36 मध्ये टाकीची देखभाल दुरुस्ती विषयक कामे करणे. | F134: 1600000
A135: 9 | B135: ZE16A104/P2-209 | C135: 37 | D135: प्रभाग क्र. 3७ मध्ये विविध ठिकाणी पाण्याची लार्इन टाकणे व इतर कामे करणे . | F135: 1200000
A136: 10 | B136: ZE16A104/P2-210 | C136: 38 | D136: प्रभाग क्र. 3८ मध्ये नव्याने जलवाहिनी विकसित करणे व इतर कामे करणे | F136: 2400000
A137: 11 | B137: ZE16A104/P2-211 | C137: 39 | D137: प्रभाग क्र. 39 मध्ये नव्याने जलवाहिनी विकसित करणे व इतर कामे करणे | F137: 2800000
A138: 12 | B138: ZE16A104/P2-212 | C138: 40 | D138: प्रभाग क्र. ४० मध्ये विविध ठिकाणी पाण्याची लार्इन टाकणे व इतर कामे करणे . | F138: 6400000
A139: 13 | B139: ZE16A104/P2-213 | C139: 41 | D139: प्रभाग क्र. 41 मध्ये विविध ठिकाणी पाण्याची लार्इन टाकणे व इतर कामे करणे . | F139: 4000000
A140: 14 | B140: ZE16A104/P2-214 | D140: कात्रज येथील महादेव मंदिराच्या टाकीचे पाईप लाईनचे कामे करणे | F140: 6400000
A141: 15 | B141: ZE16A104/P2-215 | D141: लष्कर जलकेंद्र वितरण व्यवस्थेसाठी युटीलिटी व्हॅन खरेदी करणे. | F141: 4000000
A142: 16 | B142: ZE16A104/P2-216 | D142: नवीन लष्कर जल केंद्र आवारातील सर्च टॉवर शिफ्ट करणे. | F142: 1200000
A143: 17 | B143: ZE16A104/P2-217 | D143: लष्कर जलकेंद्रामधील मनपा वसाहत मध्ये विविध कामे करणे. | F143: 1600000
A144: 18 | B144: ZE16A104/P2-218 | D144: नवीन व जुने लष्कर जलकेंद्र कार्यालय मधील स्थापत्य विषयक विविध कामे व ड्रेनेज विषयक कामे करणे. | F144: 800000
A145: 19 | B145: ZE16A104/P2-219 | D145: नवीन लष्कर जलकेंद्राच्या क्लेरीफाय्रचे स्थापत्य विषयक कामे करणे. | F145: 1200000
A146: 20 | B146: ZE16A104/P2-220 | D146: नवीन लष्कर जलकेंद्रांतर्गत रस्ते विकसित करणे. | F146: 1200000
A147: 21 | B147: ZE16A104/P2-221 | D147: नवीन लष्कर जल केंद्राच्या फिल्टर हाउस मधील जड साहित्य ने-आण करण्यासाठी प्रवेशद्वार करणे. | F147: 400000
A148: 22 | B148: ZE16A104/P2-222 | C148: 27 | D148: प्र.क्र.२७ मध्ये विविध ठिकाणी पाण्याची लार्इन टाकणे व इतर कामे करणे . | F148: 1200000
A149: 23 | B149: ZE16A104/P2-223 | D149: रामटेकडी रेल्वे गेट ते हवेली हॉटेल काळेपडळ (ससाणेनगर रोड मार्गे) येथे १४'' एम एस लाईन व १०'' एम एस लाईन टाकणे. | F149: 24000000
A150: 24 | B150: ZE16A104/P2-224 | C150: 23 | D150: प्र.क्र.२३ मध्ये विविध ठिकाणी पाण्याची लार्इन टाकणे व इतर कामे करणे . | F150: 2400000
A151: 25 | B151: ZE16A104/P2-225 | C151: 26 | D151: प्र.क्र.२६मध्ये नव्याने जलवाहिनी विकसित करणे व इतर कामे करणे | F151: 3200000
A152: 26 | B152: ZE16A104/P2-226 | D152: फुरसुंगी गावठाण येथे विविध जी.आय वितरण नलिका विकसित करणे. | F152: 1600000
A153: 27 | B153: ZE16A104/P2-227 | D153: फुरसुंगी भेकराई नगर, गंगानगर येथे विविध जी.आय वितरण नलिका विकसित करणे. | F153: 1600000
A154: 28 | B154: ZE16A104/P2-228 | D154: उरुळी देवाची येथे विविध जी.आय वितरण नलिका विकसित करणे. | F154: 1600000
A155: 29 | B155: ZE16A104/P2-229 | D155: फुरसुंगी पावरहाउस येथे डी.आय.जलवाहिनी विकसित करणे. | F155: 1200000
A156: 30 | B156: ZE16A104/P2-230 | C156: 21 | D156: प्र.क्र.२१ मध्ये नव्याने जलवाहिनी विकसित करणे व इतर कामे करणे | F156: 4000000
A157: 31 | B157: ZE16A104/P2-231 | C157: 42 | D157: प्र.क्र.४२ मध्ये नव्याने जलवाहिनी विकसित करणे व इतर कामे करणे | F157: 6400000
A158: 32 | B158: ZE16A104/P2-232 | C158: 24 | D158: प्र.क्र.२४ मध्ये विविध ठिकाणी पाण्याची लार्इन टाकणे व इतर कामे करणे . | F158: 4000000
A159: 33 | B159: ZE16A104/P2-233 | D159: लष्कर जलकेंद्र ते बकरी हिल टाकी पर्यंत १००० मीमी व्यासाची नवीन (रायझिंग मेन)जलनलिका टाकणे. | E159: 80000000 | F159: 16000000
A160: 34 | B160: ZE16A104/P2-234 | D160: लष्कर जलकेंद्र गेट पासून मम्मादेवी चौक,बिशप चर्च दरम्यान ४०० मिमी व्यासाची एम.एस.लाईन टाकणे. | F160: 4800000
A161: 35 | B161: ZE16A104/P2-235 | D161: हायसर्व्हिस टाकीचे अवारात पेव्हिंग ब्लॉक बसविणे व इतर कामे करणे. | F161: 800000
A162: 36 | B162: ZE16A104/P2-236 | D162: हायसर्व्हिस टाकी मधील साचलेला गाळ काढणे तसेच बाजूच्या दगडी भिंती मधील गळती कमी करण्यासाठी आतील बाजूने वॉटरप्रूफिंग प्लास्टर करणे. | F162: 800000
A163: 37 | B163: ZE16A104/P2-237 | D163: वानवडी प्र.क्र.२५ मध्ये एस.आर.पी.एफ.ग्रुप १ व २ चे मधील हद्दीपासून ते एस.आर.पी.एफ. गेट क्र.१ पर्यंत ५०० मिमी व्यासाची जुनी पी.एस.सी.जलनलिका बदलून नव्याने ५०० मिमी व्यासाची एम.एस.जलनलिका टाकणे. | F163: 6000000
A164: 38 | B164: ZE16A104/P2-238 | D164: वानवडी बकरी हिल टाकी अवारात पेव्हिंग ब्लॉक बसविणे. | F164: 800000
A165: 39 | B165: ZE16A104/P2-239 | C165: 25 | D165: प्र.क्र.२५ लुल्लानगर चौक ते वानवडी बाजार पोलिस चौकी पर्यंत ५०० मिमी व्यासाची नवीन एम.एस.जलनलिका टाकणे. | F165: 6000000
A166: 40 | B166: ZE16A104/P2-240 | D166: बकरी हिल ते लुल्लानगर चौक पर्यंत ६०० मिमी एम.एस.लाईन टाकणे.(चालू कामाचे बिल देणेसाठी) | F166: 3200000
A167: 41 | B167: ZE16A104/P2-241 | C167: 22 | D167: प्र.क्र २२ मध्ये नव्याने जलवाहिनी विकसित करणे व इतर कामे करणे | F167: 3200000
A168: 42 | B168: ZE16A104/P2-242 | D168: बकरी हिल झोन २ पासून शिवरकर रोड इनामदार हॉस्पिटल पर्यंत (विशाल मेगा मार्ट)६०० मिमी व्यासाची एम.एस.नलिका विकसित करणे. | F168: 3200000
A169: 43 | B169: ZE16A104/P2-243 | C169: 2 | D169: प्रभाग क्र २, ठाकरसी टाकी ते विश्रांतवाडी एक्स्प्रेस लाईनवर वॉल्व्ह बसविणे तदनुषंगिक कामे करणे. | F169: 1200000
A170: 44 | B170: ZE16A104/P2-244 | D170: येरवडा, विश्रांतवाडी, टिंगरेनगर, होसिग बोर्ड , अंतर्गत येणाऱ्या पंपिंग स्टेशन तसेच पाण्याच्या टाकी करिता स्थापत्य विषयक कामे करणे. | F170: 1200000
A171: 45 | B171: ZE16A104/P2-245 | C171: 6 | D171: प्रभाग क्र ६, मध्ये परिसरात पाण्याच्या लाईन टाकणे. | F171: 2800000
A172: 46 | B172: ZE16A104/P2-246 | D172: MLR टाकी सुरक्षिततेच्या दृष्टीने सिमाभिंत बांधणे | F172: 1600000
...

Sheet SMRY-2021
A1: code | B1: ward | C1: * | D1: क्षेत्रीय कार्यालयाने करावयाची कामे : सन 2020-21 | E1: पथ | F1: विद्युत | G1: भवन | H1: झोनिपु | I1: पाणीपुरवठा | J1: मलनिःसारण | K1: एकूण
D4: (आकडे लाखात) | E4: 2 | F4: 1 | G4: 4 | H4: 5 | I4: 6 | J4: 7 | K4: Total
A6: code | B6: Sr. | C6: Wards | D6: क्षेत्रीय कार्यालयाने करावयाची कामे : सन 2020-21 | E6: 2 | F6: 1 | G6: 4 | H6: 5 | I6: 6 | J6: 7 | K6: Total
B8: =WardOfficeNonPlan2021!B8 -> 1 | C8: =WardOfficeNonPlan2021!C8 -> 3, 4, 5 | D8: =WardOfficeNonPlan2021!D8 -> नगररोड - वडगावशेरी क्षेत्रीय कार्यालय एकूण बेरीज | E8: =WardOfficeNonPlan2021!E8+WardOfficePlan2021!E8+CitizensNonPlan2021!E8+CitizensPlan2021!E8 -> 249.88 | F8: =WardOfficeNonPlan2021!F8+WardOfficePlan2021!F8+CitizensNonPlan2021!F8+CitizensPlan2021!F8 -> 106.88 | G8: =WardOfficeNonPlan2021!G8+WardOfficePlan2021!G8+CitizensNonPlan2021!G8+CitizensPlan2021!G8 -> 105.88 | H8: =WardOfficeNonPlan2021!H8+WardOfficePlan2021!H8+CitizensNonPlan2021!H8+CitizensPlan2021!H8 -> 50 | I8: =WardOfficeNonPlan2021!I8+WardOfficePlan2021!I8+CitizensNonPlan2021!I8+CitizensPlan2021!I8 -> 10 | J8: =WardOfficeNonPlan2021!J8+WardOfficePlan2021!J8+CitizensNonPlan2021!J8+CitizensPlan2021!J8 -> 217.38 | K8: =SUM(E8:J8) -> 740.02
B9: =WardOfficeNonPlan2021!B9 -> 2 | C9: =WardOfficeNonPlan2021!C9 -> 1, 2, 6 | D9: =WardOfficeNonPlan2021!D9 -> येरवडा - कळस - धानोरी क्षेत्रीय कार्यालय एकूण बेरीज | E9: =WardOfficeNonPlan2021!E9+WardOfficePlan2021!E9+CitizensNonPlan2021!E9+CitizensPlan2021!E9 -> 201 | F9: =WardOfficeNonPlan2021!F9+WardOfficePlan2021!F9+CitizensNonPlan2021!F9+CitizensPlan2021!F9 -> 85.5 | G9: =WardOfficeNonPlan2021!G9+WardOfficePlan2021!G9+CitizensNonPlan2021!G9+CitizensPlan2021!G9 -> 146.5 | H9: =WardOfficeNonPlan2021!H9+WardOfficePlan2021!H9+CitizensNonPlan2021!H9+CitizensPlan2021!H9 -> 97.5 | I9: =WardOfficeNonPlan2021!I9+WardOfficePlan2021!I9+CitizensNonPlan2021!I9+CitizensPlan2021!I9 -> 0 | J9: =WardOfficeNonPlan2021!J9+WardOfficePlan2021!J9+CitizensNonPlan2021!J9+CitizensPlan2021!J9 -> 219.5 | K9: =SUM(E9:J9) -> 750
B10: =WardOfficeNonPlan2021!B10 -> 3 | C10: =WardOfficeNonPlan2021!C10 -> 5, 20, 21 | D10: =WardOfficeNonPlan2021!D10 -> ढोलेपाटील क्षेत्रीय कार्यालय एकूण बेरीज | E10: =WardOfficeNonPlan2021!E10+WardOfficePlan2021!E10+CitizensNonPlan2021!E10+CitizensPlan2021!E10 -> 130 | F10: =WardOfficeNonPlan2021!F10+WardOfficePlan2021!F10+CitizensNonPlan2021!F10+CitizensPlan2021!F10 -> 45 | G10: =WardOfficeNonPlan2021!G10+WardOfficePlan2021!G10+CitizensNonPlan2021!G10+CitizensPlan2021!G10 -> 107.5 | H10: =WardOfficeNonPlan2021!H10+WardOfficePlan2021!H10+CitizensNonPlan2021!H10+CitizensPlan2021!H10 -> 147.5 | I10: =WardOfficeNonPlan2021!I10+WardOfficePlan2021!I10+CitizensNonPlan2021!I10+CitizensPlan2021!I10 -> 10 | J10: =WardOfficeNonPlan2021!J10+WardOfficePlan2021!J10+CitizensNonPlan2021!J10+CitizensPlan2021!J10 -> 60 | K10: =SUM(E10:J10) -> 500
B11: =WardOfficeNonPlan2021!B11 -> 4 | C11: =WardOfficeNonPlan2021!C11 -> 8, 9 | D11: =WardOfficeNonPlan2021!D11 -> औंध - बाणेर क्षेत्रीय कार्यालय एकूण बेरीज | E11: =WardOfficeNonPlan2021!E11+WardOfficePlan2021!E11+CitizensNonPlan2021!E11+CitizensPlan2021!E11 -> 141.5 | F11: =WardOfficeNonPlan2021!F11+WardOfficePlan2021!F11+CitizensNonPlan2021!F11+CitizensPlan2021!F11 -> 74 | G11: =WardOfficeNonPlan2021!G11+WardOfficePlan2021!G11+CitizensNonPlan2021!G11+CitizensPlan2021!G11 -> 116.5 | H11: =WardOfficeNonPlan2021!H11+WardOfficePlan2021!H11+CitizensNonPlan2021!H11+CitizensPlan2021!H11 -> 76 | I11: =WardOfficeNonPlan2021!I11+WardOfficePlan2021!I11+CitizensNonPlan2021!I11+CitizensPlan2021!I11 -> 0 | J11: =WardOfficeNonPlan2021!J11+WardOfficePlan2021!J11+CitizensNonPlan2021!J11+CitizensPlan2021!J11 -> 92 | K11: =SUM(E11:J11) -> 500
B12: =WardOfficeNonPlan2021!B12 -> 5 | C12: =WardOfficeNonPlan2021!C12 -> 7, 14 | D12: =WardOfficeNonPlan2021!D12 -> शिवाजीनगर - घोले रोड क्षेत्रीय कार्यालय एकूण बेरीज | E12: =WardOfficeNonPlan2021!E12+WardOfficePlan2021!E12+CitizensNonPlan2021!E12+CitizensPlan2021!E12 -> 93 | F12: =WardOfficeNonPlan2021!F12+WardOfficePlan2021!F12+CitizensNonPlan2021!F12+CitizensPlan2021!F12 -> 89 | G12: =WardOfficeNonPlan2021!G12+WardOfficePlan2021!G12+CitizensNonPlan2021!G12+CitizensPlan2021!G12 -> 25 | H12: =WardOfficeNonPlan2021!H12+WardOfficePlan2021!H12+CitizensNonPlan2021!H12+CitizensPlan2021!H12 -> 127.5 | I12: =WardOfficeNonPlan2021!I12+WardOfficePlan2021!I12+CitizensNonPlan2021!I12+CitizensPlan2021!I12 -> 19 | J12: =WardOfficeNonPlan2021!J12+WardOfficePlan2021!J12+CitizensNonPlan2021!J12+CitizensPlan2021!J12 -> 146.5 | K12: =SUM(E12:J12) -> 500
B13: =WardOfficeNonPlan2021!B13 -> 6 | C13: =WardOfficeNonPlan2021!C13 -> 10, 11, 12 | D13: =WardOfficeNonPlan2021!D13 -> कोथरूड - बावधन क्षेत्रीय कार्यालय एकूण बेरीज | E13: =WardOfficeNonPlan2021!E13+WardOfficePlan2021!E13+CitizensNonPlan2021!E13+CitizensPlan2021!E13 -> 260.5 | F13: =WardOfficeNonPlan2021!F13+WardOfficePlan2021!F13+CitizensNonPlan2021!F13+CitizensPlan2021!F13 -> 43.5 | G13: =WardOfficeNonPlan2021!G13+WardOfficePlan2021!G13+CitizensNonPlan2021!G13+CitizensPlan2021!G13 -> 122 | H13: =WardOfficeNonPlan2021!H13+WardOfficePlan2021!H13+CitizensNonPlan2021!H13+CitizensPlan2021!H13 -> 136.5 | I13: =WardOfficeNonPlan2021!I13+WardOfficePlan2021!I13+CitizensNonPlan2021!I13+CitizensPlan2021!I13 -> 30 | J13: =WardOfficeNonPlan2021!J13+WardOfficePlan2021!J13+CitizensNonPlan2021!J13+CitizensPlan2021!J13 -> 157.5 | K13: =SUM(E13:J13) -> 750
B14: =WardOfficeNonPlan2021!B14 -> 7 | C14: =WardOfficeNonPlan2021!C14 -> 35, 39, 40 | D14: =WardOfficeNonPlan2021!D14 -> धनकवडी - सहकारनगर क्षेत्रीय कार्यालय एकूण बेरीज | E14: =WardOfficeNonPlan2021!E14+WardOfficePlan2021!E14+CitizensNonPlan2021!E14+CitizensPlan2021!E14 -> 270 | F14: =WardOfficeNonPlan2021!F14+WardOfficePlan2021!F14+CitizensNonPlan2021!F14+CitizensPlan2021!F14 -> 93 | G14: =WardOfficeNonPlan2021!G14+WardOfficePlan2021!G14+CitizensNonPlan2021!G14+CitizensPlan2021!G14 -> 102 | H14: =WardOfficeNonPlan2021!H14+WardOfficePlan2021!H14+CitizensNonPlan2021!H14+CitizensPlan2021!H14 -> 66 | I14: =WardOfficeNonPlan2021!I14+WardOfficePlan2021!I14+CitizensNonPlan2021!I14+CitizensPlan2021!I14 -> 0 | J14: =WardOfficeNonPlan2021!J14+WardOfficePlan2021!J14+CitizensNonPlan2021!J14+CitizensPlan2021!J14 -> 219 | K14: =SUM(E14:J14) -> 750
B15: =WardOfficeNonPlan2021!B15 -> 8 | C15: =WardOfficeNonPlan2021!C15 -> 30, 33, 34 | D15: =WardOfficeNonPlan2021!D15 -> सिंहगड रोड क्षेत्रीय कार्यालय एकूण बेरीज | E15: =WardOfficeNonPlan2021!E15+WardOfficePlan2021!E15+CitizensNonPlan2021!E15+CitizensPlan2021!E15 -> 301 | F15: =WardOfficeNonPlan2021!F15+WardOfficePlan2021!F15+CitizensNonPlan2021!F15+CitizensPlan2021!F15 -> 100 | G15: =WardOfficeNonPlan2021!G15+WardOfficePlan2021!G15+CitizensNonPlan2021!G15+CitizensPlan2021!G15 -> 59 | H15: =WardOfficeNonPlan2021!H15+WardOfficePlan2021!H15+CitizensNonPlan2021!H15+CitizensPlan2021!H15 -> 45 | I15: =WardOfficeNonPlan2021!I15+WardOfficePlan2021!I15+CitizensNonPlan2021!I15+CitizensPlan2021!I15 -> 10 | J15: =WardOfficeNonPlan2021!J15+WardOfficePlan2021!J15+CitizensNonPlan2021!J15+CitizensPlan2021!J15 -> 235 | K15: =SUM(E15:J15) -> 750
B16: =WardOfficeNonPlan2021!B16 -> 9 | C16: =WardOfficeNonPlan2021!C16 -> 13, 31, 32 | D16: =WardOfficeNonPlan2021!D16 -> वारजे - कर्वेनगर क्षेत्रीय कार्यालय एकूण बेरीज | E16: =WardOfficeNonPlan2021!E16+WardOfficePlan2021!E16+CitizensNonPlan2021!E16+CitizensPlan2021!E16 -> 239 | F16: =WardOfficeNonPlan2021!F16+WardOfficePlan2021!F16+CitizensNonPlan2021!F16+CitizensPlan2021!F16 -> 156 | G16: =WardOfficeNonPlan2021!G16+WardOfficePlan2021!G16+CitizensNonPlan2021!G16+CitizensPlan2021!G16 -> 96 | H16: =WardOfficeNonPlan2021!H16+WardOfficePlan2021!H16+CitizensNonPlan2021!H16+CitizensPlan2021!H16 -> 105 | I16: =WardOfficeNonPlan2021!I16+WardOfficePlan2021!I16+CitizensNonPlan2021!I16+CitizensPlan2021!I16 -> 0 | J16: =WardOfficeNonPlan2021!J16+WardOfficePlan2021!J16+CitizensNonPlan2021!J16+CitizensPlan2021!J16 -> 154 | K16: =SUM(E16:J16) -> 750
B17: =WardOfficeNonPlan2021!B17 -> 10 | C17: =WardOfficeNonPlan2021!C17 -> 22, 23, 26 | D17: =WardOfficeNonPlan2021!D17 -> हडपसर - मुंढवा क्षेत्रीय कार्यालय एकूण बेरीज | E17: =WardOfficeNonPlan2021!E17+WardOfficePlan2021!E17+CitizensNonPlan2021!E17+CitizensPlan2021!E17 -> 310 | F17: =WardOfficeNonPlan2021!F17+WardOfficePlan2021!F17+CitizensNonPlan2021!F17+CitizensPlan2021!F17 -> 45 | G17: =WardOfficeNonPlan2021!G17+WardOfficePlan2021!G17+CitizensNonPlan2021!G17+CitizensPlan2021!G17 -> 95 | H17: =WardOfficeNonPlan2021!H17+WardOfficePlan2021!H17+CitizensNonPlan2021!H17+CitizensPlan2021!H17 -> 35 | I17: =WardOfficeNonPlan2021!I17+WardOfficePlan2021!I17+CitizensNonPlan2021!I17+CitizensPlan2021!I17 -> 10 | J17: =WardOfficeNonPlan2021!J17+WardOfficePlan2021!J17+CitizensNonPlan2021!J17+CitizensPlan2021!J17 -> 255 | K17: =SUM(E17:J17) -> 750
B18: =WardOfficeNonPlan2021!B18 -> 11 | C18: =WardOfficeNonPlan2021!C18 -> 24, 25, 27 | D18: =WardOfficeNonPlan2021!D18 -> वानवडी - रामटेकडी क्षेत्रीय कार्यालय एकूण बेरीज | E18: =WardOfficeNonPlan2021!E18+WardOfficePlan2021!E18+CitizensNonPlan2021!E18+CitizensPlan2021!E18 -> 240 | F18: =WardOfficeNonPlan2021!F18+WardOfficePlan2021!F18+CitizensNonPlan2021!F18+CitizensPlan2021!F18 -> 34.5 | G18: =WardOfficeNonPlan2021!G18+WardOfficePlan2021!G18+CitizensNonPlan2021!G18+CitizensPlan2021!G18 -> 144.5 | H18: =WardOfficeNonPlan2021!H18+WardOfficePlan2021!H18+CitizensNonPlan2021!H18+CitizensPlan2021!H18 -> 0 | I18: =WardOfficeNonPlan2021!I18+WardOfficePlan2021!I18+CitizensNonPlan2021!I18+CitizensPlan2021!I18 -> 27 | J18: =WardOfficeNonPlan2021!J18+WardOfficePlan2021!J18+CitizensNonPlan2021!J18+CitizensPlan2021!J18 -> 236.5 | K18: =SUM(E18:J18) -> 682.5
B19: =WardOfficeNonPlan2021!B19 -> 12 | C19: =WardOfficeNonPlan2021!C19 -> 38, 41 | D19: =WardOfficeNonPlan2021!D19 -> कोंढवा - येवलेवाडी क्षेत्रीय कार्यालय एकूण बेरीज | E19: =WardOfficeNonPlan2021!E19+WardOfficePlan2021!E19+CitizensNonPlan2021!E19+CitizensPlan2021!E19 -> 183.5 | F19: =WardOfficeNonPlan2021!F19+WardOfficePlan2021!F19+CitizensNonPlan2021!F19+CitizensPlan2021!F19 -> 80 | G19: =WardOfficeNonPlan2021!G19+WardOfficePlan2021!G19+CitizensNonPlan2021!G19+CitizensPlan2021!G19 -> 51.5 | H19: =WardOfficeNonPlan2021!H19+WardOfficePlan2021!H19+CitizensNonPlan2021!H19+CitizensPlan2021!H19 -> 15 | I19: =WardOfficeNonPlan2021!I19+WardOfficePlan2021!I19+CitizensNonPlan2021!I19+CitizensPlan2021!I19 -> 0 | J19: =WardOfficeNonPlan2021!J19+WardOfficePlan2021!J19+CitizensNonPlan2021!J19+CitizensPlan2021!J19 -> 170 | K19: =SUM(E19:J19) -> 500
... B23: =WardOfficeNonPlan2021!B23 -> 16 | C23: =WardOfficeNonPlan2021!C23 -> 42 | D23: =WardOfficeNonPlan2021!D23 -> नव्याने समाविष्ट झालेली गावे एकूण बेरीज | E23: =WardOfficeNonPlan2021!E23+WardOfficePlan2021!E23+CitizensNonPlan2021!E23+CitizensPlan2021!E23 -> 18.5 | F23: =WardOfficeNonPlan2021!F23+WardOfficePlan2021!F23+CitizensNonPlan2021!F23+CitizensPlan2021!F23 -> 8.5 | G23: =WardOfficeNonPlan2021!G23+WardOfficePlan2021!G23+CitizensNonPlan2021!G23+CitizensPlan2021!G23 -> 22.5 | H23: =WardOfficeNonPlan2021!H23+WardOfficePlan2021!H23+CitizensNonPlan2021!H23+CitizensPlan2021!H23 -> 0 | I23: =WardOfficeNonPlan2021!I23+WardOfficePlan2021!I23+CitizensNonPlan2021!I23+CitizensPlan2021!I23 -> 0 | J23: =WardOfficeNonPlan2021!J23+WardOfficePlan2021!J23+CitizensNonPlan2021!J23+CitizensPlan2021!J23 -> 60.5 | K23: =SUM(E23:J23) -> 110
C25: =SUM(C8:C24) -> 42 | D25: =""&TEXT(D6,"0")&" एकूण बेरीज" -> क्षेत्रीय कार्यालयाने करावयाची कामे : सन 2020-21 एकूण बेरीज | E25: =SUM(E8:E24) -> 3183.88 | F25: =SUM(F8:F24) -> 1178.88 | G25: =SUM(G8:G24) -> 1592.88 | H25: =SUM(H8:H24) -> 1301.5 | I25: =SUM(I8:I24) -> 148 | J25: =SUM(J8:J24) -> 2814.88 | K25: =SUM(K8:K24) -> 10220.02

Sheet WardOfficeNonPlan2021
A1: code | B1: ward | C1: * | D1: क्षेत्रीय कार्यालयाने करावयाची योजनेतर कामे : सन 2020-21 | E1: पथ | F1: विद्युत | G1: भवन | H1: झोनिपु | I1: पाणीपुरवठा | J1: मलनिःसारण | K1: एकूण | L1: 0
D4: (आकडे लाखात) | E4: W2 | F4: W1 | G4: W4 | H4: W5 | I4: W6 | J4: W7
A6: code | B6: Sr. | C6: Wards | D6: क्षेत्रीय कार्यालयाने करावयाची योजनेतर कामे : सन 2020-21 | E6: RE20A301/W2- | F6: RE20C301/W1- | G6: RE22C301/W4- | H6: RE14B301/W5- | I6: XE12B301/W6- | J6: XE23A301/W7- | K6: Total
B8: 1 | C8: 3, 4, 5 | D8: नगररोड - वडगावशेरी क्षेत्रीय कार्यालय एकूण बेरीज | E8: 24.38 | F8: 5.88 | G8: 39.38 | H8: 37.5 | I8: 0 | J8: 42.88 | K8: 150.02
B9: 2 | C9: 1, 2, 6 | D9: येरवडा - कळस - धानोरी क्षेत्रीय कार्यालय एकूण बेरीज | E9: 111 | F9: 45.5 | G9: 91.5 | H9: 57.5 | I9: 0 | J9: 144.5 | K9: 450
B10: 3 | C10: 5, 20, 21 | D10: ढोलेपाटील क्षेत्रीय कार्यालय एकूण बेरीज | E10: 77.5 | F10: 27.5 | G10: 67.5 | H10: 97.5 | I10: 0 | J10: 30 | K10: 300
B11: 4 | C11: 8, 9 | D11: औंध - बाणेर क्षेत्रीय कार्यालय एकूण बेरीज | E11: 73.5 | F11: 50 | G11: 64.5 | H11: 52 | I11: 0 | J11: 60 | K11: 300
B12: 5 | C12: 7, 14 | D12: शिवाजीनगर - घोले रोड क्षेत्रीय कार्यालय एकूण बेरीज | E12: 70 | F12: 40 | G12: 20 | H12: 67.5 | I12: 0 | J12: 102.5 | K12: 300
B13: 6 | C13: 10, 11, 12 | D13: कोथरूड - बावधन क्षेत्रीय कार्यालय एकूण बेरीज | E13: 112.5 | F13: 32.5 | G13: 60 | H13: 93.5 | I13: 0 | J13: 82.5 | K13: 381
B14: 7 | C14: 35, 39, 40 | D14: धनकवडी - सहकारनगर क्षेत्रीय कार्यालय एकूण बेरीज | E14: 93 | F14: 41.5 | G14: 40.5 | H14: 21.5 | I14: 0 | J14: 88 | K14: 284.5
B15: 8 | C15: 30, 33, 34 | D15: सिंहगड रोड क्षेत्रीय कार्यालय एकूण बेरीज | E15: 131 | F15: 60 | G15: 44 | H15: 35 | I15: 0 | J15: 180 | K15: 450
B16: 9 | C16: 13, 31, 32 | D16: वारजे - कर्वेनगर क्षेत्रीय कार्यालय एकूण बेरीज | E16: 111.5 | F16: 78.5 | G16: 20 | H16: 35 | I16: 0 | J16: 83.5 | K16: 328.5
B17: 10 | C17: 22, 23, 26 | D17: हडपसर - मुंढवा क्षेत्रीय कार्यालय एकूण बेरीज | E17: 197.5 | F17: 15 | G17: 35 | H17: 25 | I17: 0 | J17: 135 | K17: 407.5
B18: 11 | C18: 24, 25, 27 | D18: वानवडी - रामटेकडी क्षेत्रीय कार्यालय एकूण बेरीज | E18: 70 | F18: 0 | G18: 57.5 | H18: 0 | I18: 0 | J18: 92.5 | K18: 220
B19: 12 | C19: 38, 41 | D19: कोंढवा - येवलेवाडी क्षेत्रीय कार्यालय एकूण बेरीज | E19: 97.5 | F19: 40 | G19: 42.5 | H19: 10 | I19: 0 | J19: 110 | K19: 300
... B22: 15 | C22: 28, 36, 37 | D22: बिबवेवाडी क्षेत्रीय कार्यालय एकूण बेरीज | E22: 75 | F22: 40 | G22: 20 | H22: 37.5 | I22: 0 | J22: 72.5 | K22: 245
B23: 16 | C23: 42 | D23: नव्याने समाविष्ट झालेली गावे एकूण बेरीज | E23: 13.5 | F23: 2 | G23: 14.5 | H23: 0 | I23: 0 | J23: 45 | K23: 75
C25: 42 | D25: #REF! | E25: 1465.38 | F25: 553.38 | G25: 826.88 | H25: 739.5 | I25: 0 | J25: 1506.38 | K25: 5091.52
D35: नगररोड - वडगावशेरी क्षेत्रीय कार्यालय | K35: 0
K36: 0
A37: RE20A301/W2-501 | B37: 3 | D37: प्रभाग क्र. 3 अ विविध ठिकाणी राडारोडा उचलणे | E37: 2.5 | F37: 0 | G37: 0 | H37: 0 | I37: 0 | J37: 0 | K37: 2.5
A38: XE23A301/W7-401 | B38: 3 | D38: प्रभाग क्र. 3 अ विविध ठिकाणी ड्रेनेज लाईन , पावसाळी लाईन साफसफाई करणे | E38: 0 | F38: 0 | G38: 0 | H38: 0 | I38: 0 | J38: 2.5 | K38: 2.5
A39: RE22C301/W4-401 | B39: 3 | D39: प्रभाग क्र. 3 अ विविध ठिकाणी समाज मंदीरे दुरूस्ती विषयक कामे करणे | E39: 0 | F39: 0 | G39: 2.5 | H39: 0 | I39: 0 | J39: 0 | K39: 2.5
A40: RE14B301/W5-301 | B40: 3 | D40: प्रभाग क्र.3 अ मधील विविध ठिकाणचे शौचालय दुरूस्ती व स्वच्छ सर्वेक्षण अंतर्गत सार्वजनिक भिंतीचे रंगरंगोटी विषयक कामे करणे | E40: 0 | F40: 0 | G40: 0 | H40: 5 | I40: 0 | J40: 0 | K40: 5
A41: RE20A301/W2-502 | B41: 3 | D41: प्रभाग क्र. 3 ब मधील विविध ठिकाणी राडारोडा उचलणे | E41: 5 | F41: 0 | G41: 0 | H41: 0 | I41: 0 | J41: 0 | K41: 5
A42: XE23A301/W7-402 | B42: 3 | D42: प्रभाग क्र. 3 ब सोपाननगर, सोमनाथनगर येथील पावसाळी लाइन व नाला साफसफाई करणे | E42: 0 | F42: 0 | G42: 0 | H42: 0 | I42: 0 | J42: 5 | K42: 5
A43: RE20A301/W2-503 | B43: 3 | D43: प्रभाग क्र. 3 ब मध्ये लाकडी आभासाचे बेंच बसविणे व दुरूस्ती करणे | E43: 2.5 | F43: 0 | G43: 0 | H43: 0 | I43: 0 | J43: 0 | K43: 2.5
A44: RE14B301/W5-302 | B44: 3 | D44: प्रभाग क्र. 3 क मधील शौचालय दुरूस्ती करणे | E44: 0 | F44: 0 | G44: 0 | H44: 5 | I44: 0 | J44: 0 | K44: 5
A45: RE22C301/W4-402 | B45: 3 | D45: प्रभाग क्र. 3 क मध्ये रंगरंगोटी कामे करणे | E45: 0 | F45: 0 | G45: 5 | H45: 0 | I45: 0 | J45: 0 | K45: 5
A46: XE23A301/W7-403 | B46: 3 | D46: प्रभाग क्र. 3 क मध्ये ड्रेनेज लाइन साफसफाई कामे करणे | E46: 0 | F46: 0 | G46: 0 | H46: 0 | I46: 0 | J46: 2.5 | K46: 2.5
A47: RE14B301/W5-303 | B47: 3 | D47: प्रभाग क्र. 3 ड महात्मा गांधी नगर व जयप्रकाश नगर मधील शौचालाची दुरूस्ती करणे | E47: 0 | F47: 0 | G47: 0 | H47: 5 | I47: 0 | J47: 0 | K47: 5
A48: RE14B301/W5-304 | B48: 3 | D48: प्रभाग क्र. 3 ड इंदिरानगर बर्माशेल झोपडपट्‌टीतील शौचालय दुरूस्ती करणे | E48: 0 | F48: 0 | G48: 0 | H48: 5 | I48: 0 | J48: 0 | K48: 5
A49: RE22C301/W4-403 | B49: 3 | D49: प्रभाग क्र.3 ड विजय टिंगरे गार्डन् परिसरात विविध विकास कामे करणे | E49: 0 | F49: 0 | G49: 2.5 | H49: 0 | I49: 0 | J49: 0 | K49: 2.5
B50: 3 | K50: 0
B51: 3 | D51: एकूण बेरीज | E51: 10 | F51: 0 | G51: 10 | H51: 20 | I51: 0 | J51: 10 | K51: 50
K52: 0
A53: RE14B301/W5-305 | B53: 4 | D53: प्रभाग क्र. 4 अ मध्ये आंबेडकर वसाहत शौचालय दुरूस्ती करणे | E53: 0 | F53: 0 | G53: 0 | H53: 2.5 | I53: 0 | J53: 0 | K53: 2.5
A54: XE23A301/W7-404 | B54: 4 | D54: प्रभाग क्र. 4 अ मधील बोराटे वस्ती, बिडी कामगार, गणेश नगर येथे ड्रेनेज विषयक कामे करणे | E54: 0 | F54: 0 | G54: 0 | H54: 0 | I54: 0 | J54: 2.5 | K54: 2.5
A55: RE20A301/W2-504 | B55: 4 | D55: प्रभाग क्र.4 अ मधील विविध ठिकाणी डांबरीकरण करणे | E55: 2.5 | F55: 0 | G55: 0 | H55: 0 | I55: 0 | J55: 0 | K55: 2.5
A56: RE20C301/W1-301 | B56: 4 | D56: प्रभाग क्र. 4 अ मध्ये विविध ठिकाणी विद्‌युत विषयक कामे करणे | E56: 0 | F56: 1 | G56: 0 | H56: 0 | I56: 0 | J56: 0 | K56: 1
A57: RE22C301/W4-404 | B57: 4 | D57: प्रभाग क्र. 4 अ मध्ये विविध ठिकाणी भित्तीचित्रे रंगरंगोटी कामे करणे | E57: 0 | F57: 0 | G57: 1.5 | H57: 0 | I57: 0 | J57: 0 | K57: 1.5
A58: RE14B301/W5-306 | B58: 4 | D58: प्रभाग क्र. 4 अ मध्ये विविध ठिकाणी शौचालय दुरूस्ती कामे करणे | E58: 0 | F58: 0 | G58: 0 | H58: 2.5 | I58: 0 | J58: 0 | K58: 2.5
A59: RE22C301/W4-405 | B59: 4 | D59: प्रभाग क्र.4 ब मधील सार्वजनिक स्वच्छता गृहाची विविध सुधारणा कामे करणे व स्वच्छ सर्वेक्षण अंतर्गत भिंती रंगविणे | E59: 0 | F59: 0 | G59: 5 | H59: 0 | I59: 0 | J59: 0 | K59: 5
A60: XE23A301/W7-405 | B60: 4 | D60: प्रभाग क्र. 4 ब विविध ठिकाणचे ड्रेनेज विषयक कामे करणे | E60: 0 | F60: 0 | G60: 0 | H60: 0 | I60: 0 | J60: 2.38 | K60: 2.38
A61: RE22C301/W4-406 | B61: 4 | D61: प्रभाग क्र. 4 ब मधील मनपा शाळांची विविध सुधारणा कामे करणे | E61: 0 | F61: 0 | G61: 1.88 | H61: 0 | I61: 0 | J61: 0 | K61: 1.88
A62: RE20A301/W2-505 | B62: 4 | D62: प्रभाग क्र. 4 ब विविध ठिकाणी डांबरीकरण करणे | E62: 1.88 | F62: 0 | G62: 0 | H62: 0 | I62: 0 | J62: 0 | K62: 1.88
A63: RE20C301/W1-302 | B63: 4 | D63: प्रभाग क्र. 4 ब मधील विद्‌युत विषयक कामे करणे | E63: 0 | F63: 1.38 | G63: 0 | H63: 0 | I63: 0 | J63: 0 | K63: 1.38
A64: RE22C301/W4-407 | B64: 4 | D64: प्रभाग क्र. 4 क मधील शौचालयाची दुरूस्ती कामे करणे | E64: 0 | F64: 0 | G64: 5 | H64: 0 | I64: 0 | J64: 0 | K64: 5
... A74: RE20A301/W2-506 | B74: 4 | D74: प्रभाग क्र. 4 ड मध्ये विविध ठिकाणी काँक्रिट करणे | E74: 2.5 | F74: 0 | G74: 0 | H74: 0 | I74: 0 | J74: 0 | K74: 2.5
B75: 4 | K75: 0
B76: 4 | D76: एकूण बेरीज | E76: 6.88 | F76: 5.88 | G76: 19.38 | H76: 5 | I76: 0 | J76: 12.88 | K76: 50.02
K77: 0
A78: RE14B301/W5-307 | B78: 5 | D78: प्रभाग क्र. 5 अ मध्ये शौचालय देखभाल व दुरूस्ती करणे | E78: 0 | F78: 0 | G78: 0 | H78: 5 | I78: 0 | J78: 0 | K78: 5
A79: XE23A301/W7-410 | B79: 5 | D79: प्रभाग क्र. 5 अ मध्ये ड्रेनेज लाइन साफसफाई व दुरूस्ती कामे करणे | E79: 0 | F79: 0 | G79: 0 | H79: 0 | I79: 0 | J79: 5 | K79: 5
A80: RE20A301/W2-507 | B80: 5 | D80: प्रभाग क्र. 5 अ मध्ये भिंती रंगविणे व सुशोभिकरण करणे | E80: 2.5 | F80: 0 | G80: 0 | H80: 0 | I80: 0 | J80: 0 | K80: 2.5
A81: RE14B301/W5-308 | B81: 5 | D81: प्रभाग क्र. 5 ब मध्ये सार्वजनिक शौचालय दुरूस्ती व देखभाल करणे | E81: 0 | F81: 0 | G81: 0 | H81: 5 | I81: 0 | J81: 0 | K81: 5
A82: XE23A301/W7-411 | B82: 5 | D82: प्रभाग क्र. 5 ब मध्ये विविध ठिकाणी ड्रेनेज साफसफाई व दुरूस्तीविषयक कामे करणे | E82: 0 | F82: 0 | G82: 0 | H82: 0 | I82: 0 | J82: 5 | K82: 5
A83: RE22C301/W4-411 | B83: 5 | D83: प्रभाग क्र. 5 ब मध्ये स्वच्छताविषयक व सुशोभिकरण करणेकामी रंगरंगोटी करणे | E83: 0 | F83: 0 | G83: 2.5 | H83: 0 | I83: 0 | J83: 0 | K83: 2.5
A84: RE14B301/W5-309 | B84: 5 | D84: प्रभाग क्र. 5 क मध्ये शौचालय देखभाल व दुरूस्ती कामे करणे | E84: 0 | F84: 0 | G84: 0 | H84: 2.5 | I84: 0 | J84: 0 | K84: 2.5
A85: RE20A301/W2-508 | B85: 5 | D85: प्रभाग् क्र. 5 क मध्ये भिंती रंगविणे व सुशोभिकरण करणे | E85: 2.5 | F85: 0 | G85: 0 | H85: 0 | I85: 0 | J85: 0 | K85: 2.5
A86: RE20A301/W2-509 | B86: 5 | D86: प्रभाग क्र. 5 क मध्ये राडारोडा उचलणे | E86: 2.5 | F86: 0 | G86: 0 | H86: 0 | I86: 0 | J86: 0 | K86: 2.5
A87: XE23A301/W7-412 | B87: 5 | D87: प्रभाग क्र. 5 क मध्ये ड्रेनेज लाइन साफसफाई, नाला साफसफाई व दुरूस्ती विषयक कामे करणे | E87: 0 | F87: 0 | G87: 0 | H87: 0 | I87: 0 | J87: 5 | K87: 5
A88: XE23A301/W7-413 | B88: 5 | D88: प्रभाग क्र. 5 ड मध्ये विविध ठिकाणी ड्रेनेज विषयक दुरूस्ती कामे करणे | E88: 0 | F88: 0 | G88: 0 | H88: 0 | I88: 0 | J88: 5 | K88: 5
A89: RE22C301/W4-412 | B89: 5 | D89: प्रभाग क्र. 5 ड मध्ये मनपा शाळेतील शौचालय दुरूस्ती विषयक कामे करणे | E89: 0 | F89: 0 | G89: 5 | H89: 0 | I89: 0 | J89: 0 | K89: 5
A90: RE22C301/W4-413 | B90: 5 | D90: प्रभाग क्र. 5 ड मध्ये विविध ठिकाणचे स्वच्छतेविषयक व सुशोभिकरणाची रंगरंगोटी करणे | E90: 0 | F90: 0 | G90: 2.5 | H90: 0 | I90: 0 | J90: 0 | K90: 2.5
B91: 5 | K91: 0
B92: 5 | D92: एकूण बेरीज | E92: 7.5 | F92: 0 | G92: 10 | H92: 12.5 | I92: 0 | J92: 20 | K92: 50
K93: 0
K94: 0
B95: 0 | D95: नगररोड - वडगावशेरी क्षेत्रीय कार्यालय एकूण बेरीज | E95: 24.38 | F95: 5.88 | G95: 39.38 | H95: 37.5 | I95: 0 | J95: 42.88 | K95: 150.02
K96: 0
K97: 0
D98: येरवडा - कळस - धानोरी क्षेत्रीय कार्यालय | K98: 0
K99: 0
A100: RE20A301/W2-510 | B100: 1 | D100: प्रभाग क्र. 1 अ मधील कळस विश्रांतवाडी परिसरात डांबरीकरण करणे | E100: 5 | F100: 0 | G100: 0 | H100: 0 | I100: 0 | J100: 0 | K100: 5
A101: XE23A301/W7-414 | B101: 1 | D101: प्रभाग क्र. 1 अ कळस विश्रांतवाडी परिसरात ४५० मिमी व्यासा पर्यंतची ड्रेनेज लाईन दुरूस्ती करणे व साफसफाई करणे. | E101: 0 | F101: 0 | G101: 0 | H101: 0 | I101: 0 | J101: 5 | K101: 5
A102: XE23A301/W7-415 | B102: 1 | D102: प्रभाग क्र. 1 अ कळस विश्रांतवाडी माळवाडी भिमनगर कलवड धानोरी परिसरात ३०० मीमी व्यासा पुढील जेटिंग मशिन तसेच चॅपियन मशिन ने ड्रेनेज लाईन साफसफाई करणे. तसेच देखभाल दुरूस्ती करणे. | E102: 0 | F102: 0 | G102: 0 | H102: 0 | I102: 0 | J102: 5 | K102: 5
A103: XE23A301/W7-416 | B103: 1 | D103: प्रभाग क्र. 1 अ धानोरी जकात नाका येथे नाला सफाई करणे. | E103: 0 | F103: 0 | G103: 0 | H103: 0 | I103: 0 | J103: 5 | K103: 5
A104: RE22C301/W4-414 | B104: 1 | D104: प्रभाग क्र. 1 अ कळस विश्रांतवाडी परिसरात मनपा शाळा , दवाखाने, स्मशानभुमी दुरूस्ती विषयक कामे करणे. | E104: 0 | F104: 0 | G104: 2.5 | H104: 0 | I104: 0 | J104: 0 | K104: 2.5
A105: RE14B301/W5-310 | B105: 1 | D105: प्रभाग क्र. 1 अ कळस विश्रांतवाडी गणेशनगर परिसरात शौचालय दुरूस्ती करणे. | E105: 0 | F105: 0 | G105: 0 | H105: 5 | I105: 0 | J105: 0 | K105: 5
A106: RE20A301/W2-511 | B106: 1 | D106: प्रभाग क्र. 1 अ कळस धानोरी विश्रांतवाडी परिसरात राडारोडा उचलणे. | E106: 2.5 | F106: 0 | G106: 0 | H106: 0 | I106: 0 | J106: 0 | K106: 2.5
A107: RE20A301/W2-512 | B107: 1 | D107: प्रभाग क्र. 1 अ गणेशनगर, कळस, माळवाडी, भिमनगर, कलवड, धानोरी परिसरात काँक्रीटीकरण करणे व पथ विषयक कामे करणे. | E107: 5 | F107: 0 | G107: 0 | H107: 0 | I107: 0 | J107: 0 | K107: 5
A108: RE20C301/W1-305 | B108: 1 | D108: प्रभाग क्र.१ मधील विविध सार्वजनिक शौचालया मध्ये विदयुत विषयक कामे करणे. | E108: 0 | F108: 2.5 | G108: 0 | H108: 0 | I108: 0 | J108: 0 | K108: 2.5
A109: RE20A301/W2-513 | B109: 1 | D109: प्रभाग क्र. 1 ब मध्ये राडारोडा उचलणे | E109: 2.5 | F109: 0 | G109: 0 | H109: 0 | I109: 0 | J109: 0 | K109: 2.5
A110: XE23A301/W7-417 | B110: 1 | D110: प्रभाग क्र. 1 ब धानोरी परिसरातील नालेसाफसफार्इ करणे | E110: 0 | F110: 0 | G110: 0 | H110: 0 | I110: 0 | J110: 2.5 | K110: 2.5
A111: XE23A301/W7-418 | B111: 1 | D111: प्रभाग क्र. 1 ब कळस विश्रांतवाडी परिसरातील नाले साफसफार्इ करणे | E111: 0 | F111: 0 | G111: 0 | H111: 0 | I111: 0 | J111: 2.5 | K111: 2.5
... A137: RE20C301/W1-308 | B137: 1 | D137: प्रभाग क्र. १ ड मध्ये विदयुत विषयक कामे करणे. | E137: 0 | F137: 5 | G137: 0 | H137: 0 | I137: 0 | J137: 0 | K137: 5
B138: 1 | K138: 0
B139: 1 | D139: एकूण बेरीज | E139: 47.5 | F139: 15 | G139: 17.5 | H139: 15 | I139: 0 | J139: 55 | K139: 150
K140: 0
A141: XE23A301/W7-427 | B141: 2 | D141: प्रभाग क्र. २ अ मध्ये नागपुरचाळ येथील ड्रेनेज लाईन टाकणे, चेंबर साफसफाई करणे . | E141: 0 | F141: 0 | G141: 0 | H141: 0 | I141: 0 | J141: 4 | K141: 4
A142: XE23A301/W7-428 | B142: 2 | D142: प्रभाग क्र. २ अ मध्ये म. हौसिंग बोर्ड येथील ड्रेनेज लाईन टाकणे काँक्रीटीकरण करणे. | E142: 0 | F142: 0 | G142: 0 | H142: 0 | I142: 0 | J142: 3 | K142: 3
A143: XE23A301/W7-429 | B143: 2 | D143: प्रभाग क्र. २ अ मधील बैटीचाळ येथील काँक्रीटीकरण करणे व चेंबर साफसफाई करणे. | E143: 0 | F143: 0 | G143: 0 | H143: 0 | I143: 0 | J143: 2.5 | K143: 2.5
A144: XE23A301/W7-430 | B144: 2 | D144: प्रभाग क्र. २ अ मधील टिंगरेनगर येथील ड्रेनेज लाईन करणे, चेंबर साफसफाई करणे, पावसाळी लाईन व नाला सफाई करणे. | E144: 0 | F144: 0 | G144: 0 | H144: 0 | I144: 0 | J144: 5 | K144: 5
A145: RE20A301/W2-522 | B145: 2 | D145: प्रभाग क्र. २ अ मध्ये रस्ते डांबरीकरण करणे. | E145: 5 | F145: 0 | G145: 0 | H145: 0 | I145: 0 | J145: 0 | K145: 5
A146: RE14B301/W5-314 | B146: 2 | D146: प्रभाग क्र. २ अ मध्ये नागपुरचाळ येथील विविध शौचालय दुरूस्ती करणे | E146: 0 | F146: 0 | G146: 0 | H146: 5 | I146: 0 | J146: 0 | K146: 5
A147: RE22C301/W4-419 | B147: 2 | D147: प्रभाग क्र. २ अ मध्ये मनपा शाळांमध्ये विविध विकासकामे करणे | E147: 0 | F147: 0 | G147: 2.5 | H147: 0 | I147: 0 | J147: 0 | K147: 2.5
A148: RE22C301/W4-420 | B148: 2 | D148: प्रभाग क्र. २ अ मधील समाजमंदिरांची दुरूस्ती व उर्वरित कामे करणे | E148: 0 | F148: 0 | G148: 2.5 | H148: 0 | I148: 0 | J148: 0 | K148: 2.5
A149: RE20A301/W2-523 | B149: 2 | D149: प्रभाग क्र. २ अ मधील टिंगरेनगर येथील रस्ते डांबरीकरण करणे | E149: 4 | F149: 0 | G149: 0 | H149: 0 | I149: 0 | J149: 0 | K149: 4
A150: RE20A301/W2-524 | B150: 2 | D150: प्रभाग क्र. २ अ मध्ये विविध ठिकाणी राडारोडा उचलणे | E150: 2.5 | F150: 0 | G150: 0 | H150: 0 | I150: 0 | J150: 0 | K150: 2.5
...

Sheet WardOfficePlan2021
A1: code | B1: ward | C1: * | D1: क्षेत्रीय कार्यालयाने करावयाची योजनांतर्गत कामे : सन 2020-21 | E1: पथ | F1: विद्युत | G1: भवन | H1: झोनिपु | I1: पाणीपुरवठा | J1: मलनिःसारण | K1: एकूण | L1: 0
D4: (आकडे लाखात) | E4: W2 | F4: W1 | G4: W4 | H4: W5 | I4: W6 | J4: W7
A6: code | B6: Sr. | C6: Wards | D6: क्षेत्रीय कार्यालयाने करावयाची योजनांतर्गत कामे : सन 2020-21 | E6: CE20A176/W2- | F6: CE20C118/W1- | G6: CE22A114/W4- | H6: FE14A118/W5- | I6: ZE16A115/W6- | J6: ZE16B113/W7- | K6: Total
B8: 1 | C8: 3, 4, 5 | D8: नगररोड - वडगावशेरी क्षेत्रीय कार्यालय एकूण बेरीज | E8: 116.5 | F8: 26 | G8: 27.5 | H8: 7.5 | I8: 0 | J8: 122.5 | K8: 300
B9: 2 | C9: 1, 2, 6 | D9: येरवडा - कळस - धानोरी क्षेत्रीय कार्यालय एकूण बेरीज | E9: 0 | F9: 0 | G9: 0 | H9: 0 | I9: 0 | J9: 0 | K9: 0
B10: 3 | C10: 5, 20, 21 | D10: ढोलेपाटील क्षेत्रीय कार्यालय एकूण बेरीज | E10: 0 | F10: 0 | G10: 0 | H10: 0 | I10: 0 | J10: 0 | K10: 0
B11: 4 | C11: 8, 9 | D11: औंध - बाणेर क्षेत्रीय कार्यालय एकूण बेरीज | E11: 0 | F11: 0 | G11: 0 | H11: 0 | I11: 0 | J11: 0 | K11: 0
B12: 5 | C12: 7, 14 | D12: शिवाजीनगर - घोले रोड क्षेत्रीय कार्यालय एकूण बेरीज | E12: 0 | F12: 0 | G12: 0 | H12: 0 | I12: 0 | J12: 0 | K12: 0
B13: 6 | C13: 10, 11, 12 | D13: कोथरूड - बावधन क्षेत्रीय कार्यालय एकूण बेरीज | E13: 24.5 | F13: 0 | G13: 33.5 | H13: 11 | I13: 0 | J13: 0 | K13: 69
B14: 7 | C14: 35, 39, 40 | D14: धनकवडी - सहकारनगर क्षेत्रीय कार्यालय एकूण बेरीज | E14: 77 | F14: 23.5 | G14: 26.5 | H14: 18.5 | I14: 0 | J14: 20 | K14: 165.5
B15: 8 | C15: 30, 33, 34 | D15: सिंहगड रोड क्षेत्रीय कार्यालय एकूण बेरीज | E15: 0 | F15: 0 | G15: 0 | H15: 0 | I15: 0 | J15: 0 | K15: 0
B16: 9 | C16: 13, 31, 32 | D16: वारजे - कर्वेनगर क्षेत्रीय कार्यालय एकूण बेरीज | E16: 42 | F16: 22.5 | G16: 27 | H16: 12.5 | I16: 0 | J16: 17.5 | K16: 121.5
B17: 10 | C17: 22, 23, 26 | D17: हडपसर - मुंढवा क्षेत्रीय कार्यालय एकूण बेरीज | E17: 12.5 | F17: 0 | G17: 10 | H17: 5 | I17: 0 | J17: 15 | K17: 42.5
B18: 11 | C18: 24, 25, 27 | D18: वानवडी - रामटेकडी क्षेत्रीय कार्यालय एकूण बेरीज | E18: 65 | F18: 27.5 | G18: 35 | H18: 0 | I18: 0 | J18: 65 | K18: 192.5
B19: 12 | C19: 38, 41 | D19: कोंढवा - येवलेवाडी क्षेत्रीय कार्यालय एकूण बेरीज | E19: 0 | F19: 0 | G19: 0 | H19: 0 | I19: 0 | J19: 0 | K19: 0
... B22: 15 | C22: 28, 36, 37 | D22: बिबवेवाडी क्षेत्रीय कार्यालय एकूण बेरीज | E22: 27.5 | F22: 45 | G22: 10 | H22: 25 | I22: 0 | J22: 60 | K22: 167.5
B23: 16 | C23: 42 | D23: नव्याने समाविष्ट झालेली गावे एकूण बेरीज | E23: 5 | F23: 2.5 | G23: 0 | H23: 0 | I23: 0 | J23: 1.5 | K23: 9
C25: 42 | D25: #REF! | E25: 370 | F25: 147 | G25: 169.5 | H25: 79.5 | I25: 0 | J25: 301.5 | K25: 1067.5
D35: नगररोड - वडगावशेरी क्षेत्रीय कार्यालय | K35: 0
K36: 0
A37: FE14A118/W5-201 | B37: 3 | D37: प्रभाग क्र. 3 अ यमुनानगर येथील अस्तित्वातील शौचालयांचे स्वच्छ सर्वेक्षण अंतर्गत नुतणीकरण करणे | E37: 0 | F37: 0 | G37: 0 | H37: 7.5 | I37: 0 | J37: 0 | K37: 7.5
A38: CE20A176/W2-301 | B38: 3 | D38: प्रभाग क्र. 3 अ विमाननगर परिसरात फुटपाथ विषयक कामे करणे | E38: 10 | F38: 0 | G38: 0 | H38: 0 | I38: 0 | J38: 0 | K38: 10
A39: CE20C118/W1-201 | B39: 3 | D39: प्रभाग क्र. 3 अ मध्ये विविध ठिकाणी विद्‌युत विषयक कामे करणे | E39: 0 | F39: 7.5 | G39: 0 | H39: 0 | I39: 0 | J39: 0 | K39: 7.5
A40: CE20A176/W2-302 | B40: 3 | D40: प्रभाग क्र. 3 ब मध्ये विविध ठिकाणी फुटपाथ करणे | E40: 6.5 | F40: 0 | G40: 0 | H40: 0 | I40: 0 | J40: 0 | K40: 6.5
A41: CE22A114/W4-201 | B41: 3 | D41: प्रभाग क्र. 3 ब मध्ये विविध ठिकाणी पाणपोई व वाचनालय करणे | E41: 0 | F41: 0 | G41: 6.5 | H41: 0 | I41: 0 | J41: 0 | K41: 6.5
A42: CE22A114/W4-202 | B42: 3 | D42: प्रभाग क्र. 3 ब मध्ये विविध ठिकाणी स्वच्छ सर्वेक्षण अंतर्गत रंगरंगोटी करणे | E42: 0 | F42: 0 | G42: 6 | H42: 0 | I42: 0 | J42: 0 | K42: 6
A43: ZE16B113/W7-301 | B43: 3 | D43: प्रभाग क्र. 3 ब मध्ये ड्रेनेज विषयक कामे करणे | E43: 0 | F43: 0 | G43: 0 | H43: 0 | I43: 0 | J43: 6 | K43: 6
A44: CE20A176/W2-303 | B44: 3 | D44: प्रभाग क्र. 3 क मधील कलवड व संतनगर भागातील रस्ते विकसित करणे | E44: 10 | F44: 0 | G44: 0 | H44: 0 | I44: 0 | J44: 0 | K44: 10
A45: CE20A176/W2-304 | B45: 3 | D45: प्रभाग क्र. 3 क विमाननगर येथे फुटपाथ विकसित करणे | E45: 7.5 | F45: 0 | G45: 0 | H45: 0 | I45: 0 | J45: 0 | K45: 7.5
A46: ZE16B113/W7-302 | B46: 3 | D46: प्रभाग क्र. 3 क मध्ये विविध ठिकाणी ड्रेनेज विषयक कामे करणे | E46: 0 | F46: 0 | G46: 0 | H46: 0 | I46: 0 | J46: 7.5 | K46: 7.5
A47: CE20A176/W2-305 | B47: 3 | D47: प्रभाग क्र. 3 ड मध्ये विविध ठिकाणी फुटपाथ करणे | E47: 10 | F47: 0 | G47: 0 | H47: 0 | I47: 0 | J47: 0 | K47: 10
A48: ZE16B113/W7-303 | B48: 3 | D48: प्रभाग क्र. 3 ड गांधीनगर, जयप्रकाश नगर, बर्माशेल, इंदिरानगर परिसरातील जुन्या ड्रेनेज लाइन काढून नवीन ड्रेनेज लाइन टाकणे | E48: 0 | F48: 0 | G48: 0 | H48: 0 | I48: 0 | J48: 7.5 | K48: 7.5
A49: CE20A176/W2-306 | B49: 3 | D49: प्रभाग क्र. 3 ड विविध ठिकाणी रस्ते डांबरीकरण करणे | E49: 7.5 | F49: 0 | G49: 0 | H49: 0 | I49: 0 | J49: 0 | K49: 7.5
B50: 3 | K50: 0
B51: 3 | D51: एकूण बेरीज | E51: 51.5 | F51: 7.5 | G51: 12.5 | H51: 7.5 | I51: 0 | J51: 21 | K51: 100
K52: 0
A53: ZE16B113/W7-304 | B53: 4 | D53: प्रभाग क्र. 4 अ मध्ये आंबेडकर वसाहत येथे ड्रेनेज लाइन दुरूस्ती टाकणे | E53: 0 | F53: 0 | G53: 0 | H53: 0 | I53: 0 | J53: 6.25 | K53: 6.25
A54: ZE16B113/W7-305 | B54: 4 | D54: प्रभाग क्र. 4 अ मध्ये बिडी कामगार वसाहत येथे ड्रेनेज लाइन टाकणे | E54: 0 | F54: 0 | G54: 0 | H54: 0 | I54: 0 | J54: 6.25 | K54: 6.25
A55: ZE16B113/W7-306 | B55: 4 | D55: प्रभाग क्र.4 अ मध्ये ड्रेनेज विषयक कामे करणे | E55: 0 | F55: 0 | G55: 0 | H55: 0 | I55: 0 | J55: 6.25 | K55: 6.25
A56: ZE16B113/W7-307 | B56: 4 | D56: प्रभाग क्र. 4 अ मध्ये ड्रेनेज लाइन टाकणे | E56: 0 | F56: 0 | G56: 0 | H56: 0 | I56: 0 | J56: 6.25 | K56: 6.25
A57: CE20A176/W2-307 | B57: 4 | D57: प्रभाग क्र. 4 ब विविध ठिकाणी डांबरीकरण करणे | E57: 6.5 | F57: 0 | G57: 0 | H57: 0 | I57: 0 | J57: 0 | K57: 6.5
A58: ZE16B113/W7-308 | B58: 4 | D58: प्रभाग क्र. 4 ब विविध ठिकाणी ड्रेनेज विषयक कामे करणे | E58: 0 | F58: 0 | G58: 0 | H58: 0 | I58: 0 | J58: 6.25 | K58: 6.25
A59: CE20A176/W2-308 | B59: 4 | D59: प्रभाग क्र. 4 ब विविध ठिकाणी रस्ते कॉंक्रिटीकरण करणे | E59: 6.5 | F59: 0 | G59: 0 | H59: 0 | I59: 0 | J59: 0 | K59: 6.5
A60: ZE16B113/W7-309 | B60: 4 | D60: प्रभाग क्र. 4 ब विविध ठिकाणी ड्रेनेज लाइन टाकणे | E60: 0 | F60: 0 | G60: 0 | H60: 0 | I60: 0 | J60: 6 | K60: 6
A61: CE20C118/W1-202 | B61: 4 | D61: प्रभाग क्र. 4 मध्ये खराडी परिसरात विद्‌युत विषयक कामे करणे | E61: 0 | F61: 6.25 | G61: 0 | H61: 0 | I61: 0 | J61: 0 | K61: 6.25
A62: ZE16B113/W7-310 | B62: 4 | D62: प्रभाग क्र. 4 क खराडी भागात ड्रेनेज लाइन टाकणे | E62: 0 | F62: 0 | G62: 0 | H62: 0 | I62: 0 | J62: 6.25 | K62: 6.25
A63: ZE16B113/W7-311 | B63: 4 | D63: प्रभाग क्र. 4 क थिटे वस्ती येथे ड्रेनेज लाइन टाकणे | E63: 0 | F63: 0 | G63: 0 | H63: 0 | I63: 0 | J63: 6.25 | K63: 6.25
A64: ZE16B113/W7-312 | B64: 4 | D64: प्रभाग क्र. 4 क चंदननगर येथे ड्रेनेज लाइन टाकणे | E64: 0 | F64: 0 | G64: 0 | H64: 0 | I64: 0 | J64: 6.25 | K64: 6.25
... A68: ZE16B113/W7-314 | B68: 4 | D68: प्रभाग क्र. 4 ड मध्ये विविध ठिकाणी ड्रेनेज लाइन टाकणे | E68: 0 | F68: 0 | G68: 0 | H68: 0 | I68: 0 | J68: 6.25 | K68: 6.25
B69: 4 | K69: 0
B70: 4 | D70: एकूण बेरीज | E70: 19 | F70: 12.5 | G70: 0 | H70: 0 | I70: 0 | J70: 68.5 | K70: 100
K71: 0
A72: CE20A176/W2-310 | B72: 5 | D72: प्रभाग क्र. 5 अ मध्ये वडगांवशेरी, साईनाथनगर रस्ते विकसित करणे | E72: 9.5 | F72: 0 | G72: 0 | H72: 0 | I72: 0 | J72: 0 | K72: 9.5
A73: ZE16B113/W7-315 | B73: 5 | D73: प्रभाग क्र. 5 अ मध्ये वडगांवशेरी परिसरात ड्रेनेज लाइन टाकणे | E73: 0 | F73: 0 | G73: 0 | H73: 0 | I73: 0 | J73: 9.5 | K73: 9.5
A74: CE20C118/W1-204 | B74: 5 | D74: प्रभाग क्र. 5 अ मध्ये वडगांवशेरीमध्ये विद्‌युत विषयक कामे करणे | E74: 0 | F74: 6 | G74: 0 | H74: 0 | I74: 0 | J74: 0 | K74: 6
A75: CE20A176/W2-311 | B75: 5 | D75: प्रभाग क्र. 5 ब मध्ये कल्याणीनगर परिसरात विविध ठिकाणी डांबरीकरण करणे | E75: 7.5 | F75: 0 | G75: 0 | H75: 0 | I75: 0 | J75: 0 | K75: 7.5
A76: CE22A114/W4-203 | B76: 5 | D76: प्रभाग क्र. 5 ब मध्ये मनपा शाळांमध्ये विविध सुधारणा कामे करणे | E76: 0 | F76: 0 | G76: 7.5 | H76: 0 | I76: 0 | J76: 0 | K76: 7.5
A77: ZE16B113/W7-316 | B77: 5 | D77: प्रभाग क्र. 5 ब मध्ये विविध ठिकाणचे ड्रेनेज दुरूस्तीविषयक कामे करणे | E77: 0 | F77: 0 | G77: 0 | H77: 0 | I77: 0 | J77: 10 | K77: 10
A78: ZE16B113/W7-317 | B78: 5 | D78: प्रभाग क्र. 5 क वडगांवशेरी परिसरात ड्रेनेज लाइन टाकणे | E78: 0 | F78: 0 | G78: 0 | H78: 0 | I78: 0 | J78: 6 | K78: 6
A79: CE20A176/W2-312 | B79: 5 | D79: प्रभाग क्र. 5 क मध्ये कल्याणीनगर परिसरात फुटपाथ करणे | E79: 6 | F79: 0 | G79: 0 | H79: 0 | I79: 0 | J79: 0 | K79: 6
A80: CE20A176/W2-313 | B80: 5 | D80: प्रभाग क्र. 5 क मध्ये विविध सुधारणा कामे करणे | E80: 6.5 | F80: 0 | G80: 0 | H80: 0 | I80: 0 | J80: 0 | K80: 6.5
A81: CE20A176/W2-314 | B81: 5 | D81: प्रभाग क्र. 5 क मध्ये वडगांवशेरी परिसरात रस्ते विकसित करणे | E81: 6.5 | F81: 0 | G81: 0 | H81: 0 | I81: 0 | J81: 0 | K81: 6.5
A82: CE20A176/W2-315 | B82: 5 | D82: प्रभाग क्र. 5 ड मध्ये विविध ठिकाणचे डांबरीकरण करणे | E82: 10 | F82: 0 | G82: 0 | H82: 0 | I82: 0 | J82: 0 | K82: 10
A83: CE22A114/W4-204 | B83: 5 | D83: प्रभाग क्र. 5 ड मध्ये साइनाथनगर भाजी मंडईचे विविध सुधारणा विषयक कामे करणे | E83: 0 | F83: 0 | G83: 7.5 | H83: 0 | I83: 0 | J83: 0 | K83: 7.5
A84: ZE16B113/W7-318 | B84: 5 | D84: प्रभाग क्र. 5 ड मध्ये विविध ठिकाणचे ड्रेनेज विषयक कामे करणे | E84: 0 | F84: 0 | G84: 0 | H84: 0 | I84: 0 | J84: 7.5 | K84: 7.5
B85: 5 | K85: 0
B86: 5 | D86: एकूण बेरीज | E86: 46 | F86: 6 | G86: 15 | H86: 0 | I86: 0 | J86: 33 | K86: 100
K87: 0
K88: 0
B89: 0 | D89: नगररोड - वडगावशेरी क्षेत्रीय कार्यालय एकूण बेरीज | E89: 116.5 | F89: 26 | G89: 27.5 | H89: 7.5 | I89: 0 | J89: 122.5 | K89: 300
K90: 0
D91: कोथरूड - बावधन क्षेत्रीय कार्यालय | K91: 0
K92: 0
A93: CE22A114/W4-205 | B93: 10 | D93: प्रभाग क्र.१० प्रभागात स्वच्छ अभियांनातर्गक भिंती रंगविणे | E93: 0 | F93: 0 | G93: 2.5 | H93: 0 | I93: 0 | J93: 0 | K93: 2.5
A94: CE20A176/W2-316 | B94: 10 | D94: प्रभाग क्र.१० प्रभागात रस्ते डांबरीकरण करणे. | E94: 2 | F94: 0 | G94: 0 | H94: 0 | I94: 0 | J94: 0 | K94: 2
A95: CE22A114/W4-206 | B95: 10 | D95: प्रभाग क्र.१० मनपा इमारतीची रंगरंगोटी व इतर कामे करणे. | E95: 0 | F95: 0 | G95: 2.5 | H95: 0 | I95: 0 | J95: 0 | K95: 2.5
A96: CE22A114/W4-207 | B96: 10 | D96: प्रभाग क्र.१० शास्त्रीनगर स्मशानभुमी स्थापत्य विषयक कामे करणे. | E96: 0 | F96: 0 | G96: 2 | H96: 0 | I96: 0 | J96: 0 | K96: 2
A97: CE20A176/W2-317 | B97: 10 | D97: प्रभाग क्र.१० डावी उजवी भुसारी डांबरीकरण करणे. | E97: 2.5 | F97: 0 | G97: 0 | H97: 0 | I97: 0 | J97: 0 | K97: 2.5
A98: CE20A176/W2-318 | B98: 10 | D98: प्रभाग क्र.१० बावधन परिसरात डांबरीकरण करणे. | E98: 2.5 | F98: 0 | G98: 0 | H98: 0 | I98: 0 | J98: 0 | K98: 2.5
A99: CE20A176/W2-319 | B99: 10 | D99: प्रभाग क्र.१० उजवी व डावी भुसारी व इतर ठिकाणी डांबरीकरण करणे. | E99: 2.5 | F99: 0 | G99: 0 | H99: 0 | I99: 0 | J99: 0 | K99: 2.5
A100: CE20A176/W2-320 | B100: 10 | D100: प्रभाग क्र.१० बावधन मध्ये फुटपाथ तयार करणे. | E100: 2.5 | F100: 0 | G100: 0 | H100: 0 | I100: 0 | J100: 0 | K100: 2.5
A101: CE22A114/W4-208 | B101: 10 | D101: प्रभाग क्र.१० बावधन स्मशानभुमी मध्ये विविध विकास कामे करणे | E101: 0 | F101: 0 | G101: 2.5 | H101: 0 | I101: 0 | J101: 0 | K101: 2.5
A102: CE20A176/W2-321 | B102: 10 | D102: प्रभाग क्र.१० प्रभागात फुटपाथ विषयक कामे करणे. | E102: 2.5 | F102: 0 | G102: 0 | H102: 0 | I102: 0 | J102: 0 | K102: 2.5
A103: CE20A176/W2-322 | B103: 10 | D103: प्रभाग क्र.१० बावधन विविध विकास ठिकाण फुटपाथ करणे. | E103: 2.5 | F103: 0 | G103: 0 | H103: 0 | I103: 0 | J103: 0 | K103: 2.5
A104: FE14A118/W5-202 | B104: 10 | D104: प्रभाग क्र.१० शास्त्रीनगर स्मशानभूमी येथील नाल्याच्या कडेने चेनलींक फेन्सींग करणे. | E104: 0 | F104: 0 | G104: 0 | H104: 2.5 | I104: 0 | J104: 0 | K104: 2.5
... A111: FE14A118/W5-206 | B111: 10 | D111: प्रभाग क्र.१० महाडकर सोसायटी येथील नाल्याची साफसफाई व चेनलींक फेन्सींगचे काम करणे. | E111: 0 | F111: 0 | G111: 0 | H111: 2 | I111: 0 | J111: 0 | K111: 2
B112: 10 | K112: 0
B113: 10 | D113: एकूण बेरीज | E113: 17 | F113: 0 | G113: 16 | H113: 11 | I113: 0 | J113: 0 | K113: 44
K114: 0
A115: CE22A114/W4-212 | B115: 11 | D115: प्रभाग क्र.११ मध्ये गणपती विसर्जन हौदाची व्यवस्था करणे (भाग -१) | E115: 0 | F115: 0 | G115: 2.5 | H115: 0 | I115: 0 | J115: 0 | K115: 2.5
A116: CE20A176/W2-323 | B116: 11 | D116: प्रभाग क्र.११ मध्ये विविध ठिकाणी दिशादर्शक फलक बसविणे. | E116: 2.5 | F116: 0 | G116: 0 | H116: 0 | I116: 0 | J116: 0 | K116: 2.5
A117: CE22A114/W4-213 | B117: 11 | D117: प्रभाग क्र.११ मध्ये गणपती विसर्जन हौदाची व्यवस्था करणे (भाग -२) | E117: 0 | F117: 0 | G117: 2.5 | H117: 0 | I117: 0 | J117: 0 | K117: 2.5
A118: CE20A176/W2-324 | B118: 11 | D118: प्रभाग क्र.११ मध्ये विविध ठिकाणी दिशादर्शक फलक व थर्माप्लास्टिक पेंट करणे. | E118: 2.5 | F118: 0 | G118: 0 | H118: 0 | I118: 0 | J118: 0 | K118: 2.5
A119: CE22A114/W4-214 | B119: 11 | D119: प्र.क्र.११ मध्ये स्वच्छ भारत अभियांना अंतर्गत रामबाग कॉलनी, पौड रस्ता परिसरात भिंती रंगविणे. | E119: 0 | F119: 0 | G119: 2.5 | H119: 0 | I119: 0 | J119: 0 | K119: 2.5
A120: CE22A114/W4-215 | B120: 11 | D120: केळेवाडी, जयभवानीनगर, हनुमाननगर व विविध ठिकाणी भिंती रंगविणे. | E120: 0 | F120: 0 | G120: 2.5 | H120: 0 | I120: 0 | J120: 0 | K120: 2.5
B121: 11 | K121: 0
B122: 11 | D122: एकूण बेरीज | E122: 5 | F122: 0 | G122: 10 | H122: 0 | I122: 0 | J122: 0 | K122: 15
K123: 0
A124: CE20A176/W2-325 | B124: 12 | D124: प्रभाग क्र.१२ मधध्ये विविध ठिकाणी वाहतुक नामदर्शक दिशादर्शक फलक लावणे व पत्रे मारणे. | E124: 2.5 | F124: 0 | G124: 0 | H124: 0 | I124: 0 | J124: 0 | K124: 2.5
A125: CE22A114/W4-216 | B125: 12 | D125: प्रभाग क्र.१२ मध्ये डहाणूकर कॉलनी परिसरात गणपती विसर्जनाची व्यवस्था करणे. | E125: 0 | F125: 0 | G125: 2.5 | H125: 0 | I125: 0 | J125: 0 | K125: 2.5
...

Sheet CitizensNonPlan2021
A1: code | B1: ward | C1: * | D1: क्षेत्रीय कार्यालयाने नागरिकांच्या सहभागातून करावयाची योजनेतर कामे : सन 2020-21 | E1: पथ | F1: विद्युत | G1: भवन | H1: झोनिपु | I1: पाणीपुरवठा | J1: मलनिःसारण | K1: एकूण | L1: 0
D4: (आकडे लाखात) | E4: C2 | F4: C1 | G4: C4 | H4: C5 | I4: C6 | J4: C7
A6: code | B6: Sr. | C6: Wards | D6: क्षेत्रीय कार्यालयाने नागरिकांच्या सहभागातून करावयाची योजनेतर कामे : सन 2020-21 | E6: RE20A302/C2- | F6: RE20C302/C1- | G6: RE22C302/C4- | H6: RE14B302/C5- | I6: XE12B302/C6- | J6: XE23A302/C7- | K6: Total
B8: 1 | C8: 3, 4, 5 | D8: नगररोड - वडगावशेरी क्षेत्रीय कार्यालय एकूण बेरीज | E8: 109 | F8: 75 | G8: 39 | H8: 5 | I8: 10 | J8: 52 | K8: 290
B9: 2 | C9: 1, 2, 6 | D9: येरवडा - कळस - धानोरी क्षेत्रीय कार्यालय एकूण बेरीज | E9: 90 | F9: 40 | G9: 55 | H9: 40 | I9: 0 | J9: 75 | K9: 300
B10: 3 | C10: 5, 20, 21 | D10: ढोलेपाटील क्षेत्रीय कार्यालय एकूण बेरीज | E10: 52.5 | F10: 17.5 | G10: 40 | H10: 50 | I10: 10 | J10: 30 | K10: 200
B11: 4 | C11: 8, 9 | D11: औंध - बाणेर क्षेत्रीय कार्यालय एकूण बेरीज | E11: 68 | F11: 24 | G11: 52 | H11: 24 | I11: 0 | J11: 32 | K11: 200
B12: 5 | C12: 7, 14 | D12: शिवाजीनगर - घोले रोड क्षेत्रीय कार्यालय एकूण बेरीज | E12: 23 | F12: 49 | G12: 5 | H12: 60 | I12: 19 | J12: 44 | K12: 200
B13: 6 | C13: 10, 11, 12 | D13: कोथरूड - बावधन क्षेत्रीय कार्यालय एकूण बेरीज | E13: 92.5 | F13: 1 | G13: 25.5 | H13: 29 | I13: 15 | J13: 75 | K13: 238
B14: 7 | C14: 35, 39, 40 | D14: धनकवडी - सहकारनगर क्षेत्रीय कार्यालय एकूण बेरीज | E14: 53 | F14: 3 | G14: 25 | H14: 22 | I14: 0 | J14: 97 | K14: 200
B15: 8 | C15: 30, 33, 34 | D15: सिंहगड रोड क्षेत्रीय कार्यालय एकूण बेरीज | E15: 170 | F15: 40 | G15: 15 | H15: 10 | I15: 10 | J15: 55 | K15: 300
B16: 9 | C16: 13, 31, 32 | D16: वारजे - कर्वेनगर क्षेत्रीय कार्यालय एकूण बेरीज | E16: 43 | F16: 40 | G16: 9 | H16: 10 | I16: 0 | J16: 29 | K16: 131
B17: 10 | C17: 22, 23, 26 | D17: हडपसर - मुंढवा क्षेत्रीय कार्यालय एकूण बेरीज | E17: 95 | F17: 25 | G17: 50 | H17: 5 | I17: 10 | J17: 90 | K17: 275
B18: 11 | C18: 24, 25, 27 | D18: वानवडी - रामटेकडी क्षेत्रीय कार्यालय एकूण बेरीज | E18: 33 | F18: 5 | G18: 14 | H18: 0 | I18: 7 | J18: 51 | K18: 110
B19: 12 | C19: 38, 41 | D19: कोंढवा - येवलेवाडी क्षेत्रीय कार्यालय एकूण बेरीज | E19: 51 | F19: 15 | G19: 4 | H19: 0 | I19: 0 | J19: 30 | K19: 100
... B22: 15 | C22: 28, 36, 37 | D22: बिबवेवाडी क्षेत्रीय कार्यालय एकूण बेरीज | E22: 10 | F22: 0 | G22: 30 | H22: 30 | I22: 0 | J22: 35 | K22: 105
B23: 16 | C23: 42 | D23: नव्याने समाविष्ट झालेली गावे एकूण बेरीज | E23: 0 | F23: 4 | G23: 8 | H23: 0 | I23: 0 | J23: 14 | K23: 26
C25: 42 | D25: #REF! | E25: 1056 | F25: 386.5 | G25: 460.5 | H25: 423 | I25: 103 | J25: 846 | K25: 3275
D35: नगररोड - वडगावशेरी क्षेत्रीय कार्यालय | K35: 0
K36: 0
A37: RE14B302/C5-501 | B37: 3 | D37: प्रभाग क्र.३ मधील सिद्धार्थनगर मधील शौचालय दुरुस्ती करणे | H37: 5 | K37: 5
A38: RE20C302/C1-501 | B38: 3 | D38: प्रभाग क्र.३ संजय पार्क परिसरातील विद्युत तारा भूमिगत करणे | F38: 5 | K38: 5
A39: RE20A302/C2-401 | B39: 3 | D39: प्रभाग क्र.३ संजय पार्क वसाहत येथील अंतर्गत गल्ली कॉक्रीटीकरन करणे | E39: 5 | K39: 5
A40: RE20C302/C1-502 | B40: 3 | D40: प्रभाग क्र.३ संजय पार्क विमान दर्शन हौ.सोसा.लेन.नं.४ येथील विद्युत वाहिनी भूमिगत करणे | F40: 5 | K40: 5
A41: XE12B302/C6-301 | B41: 3 | D41: प्रभाग क्र.३ विविध ठिकाणी पाण्याची ६ इंची लाईन टाकणे | I41: 5 | K41: 5
A42: RE20A302/C2-402 | B42: 3 | D42: प्रभाग क्र.३ इनॉरबिट शेजारील गार्डन मध्ये विविध दुरुस्ती विषयक कामे करणे | E42: 5 | K42: 5
A43: RE20A302/C2-403 | B43: 3 | D43: प्रभाग क्र.३ विविध ठिकाणी (सोमनाथनगर) खोलेले ब्लॉक दुरुस्ती करणे | E43: 5 | K43: 5
A44: XE23A302/C7-901 | B44: 3 | D44: प्रभाग क्र.३ मध्ये ड्रेनेज विषयक दुरुस्ती कामे करणे | J44: 5 | K44: 5
A45: RE20A302/C2-404 | B45: 3 | D45: प्रभाग क्र.३ विमाननगर भागात फुटपाथ दुरुस्ती करणे | E45: 5 | K45: 5
A46: RE20A302/C2-405 | B46: 3 | D46: प्रभाग क्र.३ विमाननगर भागात अंतर्गत फुटपाथ दुरुस्तीची कामे करणे | E46: 5 | K46: 5
A47: RE20C302/C1-503 | B47: 3 | D47: प्रभाग क्र.३ स.नं.२४१-४२ इंदिरानगर मध्ये लाईटचे ५ पोल बसविणे (पथ,दिवे),१० दिवे डब्बल ब्राकेट एकूण ५ गल्ल्यात प्रत्येकी ५ पोल बसविणे | F47: 5 | K47: 5
A48: XE12B302/C6-302 | B48: 3 | D48: प्रभाग क्र.३ स.नं.१०३ जय प्रकाश नगर येथे पाण्याच्या लाईन टाकून कॉक्रीटी करणे | I48: 5 | K48: 5
A49: RE20A302/C2-406 | B49: 3 | D49: प्रभाग क्र.३ महात्मा गांधीनगर मधील खराब रस्ते खोदून कॉक्रीटी करणे | E49: 5 | K49: 5
A50: XE23A302/C7-902 | B50: 3 | D50: प्रभाग क्र.३ स.नं.२४२ वाल्मिकी गल्ली इंदिरानगर येथे ड्रेनेज लाईन टाकणे व कॉक्रीट करणे | J50: 5 | K50: 5
A51: RE20A302/C2-407 | B51: 3 | D51: प्रभाग क्र.३ सोमनाथ नगर गार्डनच्या बाजूचा रस्ता खराब झालेला आहे, घुशीमुळे पूर्ण टाईल्स खराब झालेले आहेत दुरुस्ती करावे | E51: 5 | K51: 5
A52: RE20C302/C1-504 | B52: 3 | D52: प्रभाग क्र.३ २० वर्षापूर्वीचे लाईटचे खांब बदलून द्यावेत | F52: 5 | K52: 5
A53: XE23A302/C7-903 | B53: 3 | D53: प्रभाग क्र.३ गणपती चौक-नगररोड पर्यत ड्रेनेज लाईन बसले गेलेने पुनः नवीन लाईन टाकून चेंबर बांधणे | J53: 5 | K53: 5
A54: RE20A302/C2-408 | B54: 3 | D54: प्रभाग क्र.३ बेकर कंपनी ते डब्लूयु एन सी कॉर्नर पर्यंत गीगास्पेस जवळचा फुटपाथ दुरुस्त करावा | E54: 5 | K54: 5
B55: 3 | K55: 0
B56: 3 | D56: एकूण बेरीज | E56: 40 | F56: 20 | G56: 0 | H56: 5 | I56: 10 | J56: 15 | K56: 90
K57: 0
A58: RE20A302/C2-409 | B58: 4 | D58: प्रभाग क्र. ४ शंकरनगर येथील तोंडारकर सर (गल्ली क्र.७ ) यांचे घराजवळ रस्ते कॉक्रीटी करणे | E58: 5 | K58: 5
A59: RE20C302/C1-505 | B59: 4 | D59: प्रभाग क्र. ४ आंबेडकर वसाहत येथे प्रकाश व्यवस्था करणे | F59: 5 | K59: 5
A60: RE20C302/C1-506 | B60: 4 | D60: प्रभाग क्र. ४ तुळजाभवानी नगर अहिल्याबाई होळकर बचत गट हॉल ते ढोले पाटील वसाहती पर्यंत प्रकाश व्यवस्था करणे | F60: 5 | K60: 5
A61: RE20C302/C1-507 | B61: 4 | D61: प्रभाग क्र. ४ गंगा कोन्स्टेला ते पाण्याची टाकी पर्यंत प्रकाश व्यवस्था करणे | F61: 5 | K61: 5
A62: RE20C302/C1-508 | B62: 4 | D62: प्रभाग क्र. ४ शंकर नगर येथील श्रीराम सोसायटी स.नं.३८/२ सचिन क्षीरसागर घराजवळ विद्युत वाहिन्या भूमिगत करणे | F62: 5 | K62: 5
A63: RE20C302/C1-509 | B63: 4 | D63: प्रभाग क्र. ४ खराडी बिडी कामगार वसाहत परिसरात पथदिवे / प्रकाश व्यवस्था करणे | F63: 5 | K63: 5
A64: RE20C302/C1-510 | B64: 4 | D64: प्रभाग क्र. ४ खुळेवाडी येथे पथ दिवे बसविणे | F64: 5 | K64: 5
A65: RE20A302/C2-410 | B65: 4 | D65: प्रभाग क्र. ४ खराडी गाव येथील मुकुंद चव्हाण यांचे घरापासून सयाजी गायकवाड यांचे घरापर्यंत रस्ता कॉक्रीट करणे | E65: 5 | K65: 5
A66: XE23A302/C7-904 | B66: 4 | D66: प्रभाग क्र. ४ गणेश नगर लेन नं.१२ स.नं. ४८/४ ड्रेनेज लाईन टाकणे | J66: 5 | K66: 5
A67: XE23A302/C7-905 | B67: 4 | D67: प्रभाग क्र. ४ गणेश नगर लेन नं.०९ स.नं. ४८/४ ड्रेनेज लाईन टाकणे | J67: 5 | K67: 5
A68: RE20A302/C2-411 | B68: 4 | D68: प्रभाग क्र. ४ बिडी कामगार उत्तर बाजूस वसाहतीमध्ये गल्ली बोळ कॉक्रीट करणे | E68: 5 | K68: 5
A69: XE23A302/C7-906 | B69: 4 | D69: प्रभाग क्र. ४ बिडी कामगार येथील मलनिस्सारण वाहिनीचे देखभाल व दुरुस्ती करणे | J69: 5 | K69: 5
A70: RE20A302/C2-412 | B70: 4 | D70: प्रभाग क्र. ४ खुळेवाडी येथे गल्ली बोळात कॉक्रीटकरण करणे | E70: 5 | K70: 5
A71: RE20C302/C1-511 | B71: 4 | D71: प्रभाग क्र. ४ राजाराम पाटील नगर स.नं.६३ येथे पथदिवे बसविणे | F71: 5 | K71: 5
A72: RE20A302/C2-413 | B72: 4 | D72: प्रभाग क्र. ४ खराडी चावडी ते विद्युत दाहिनी पर्यंत रस्ता कॉक्रीट करणे | E72: 5 | K72: 5
A73: RE20A302/C2-414 | B73: 4 | D73: प्रभाग क्र. ४ दक्षिण बाजूच्या वसाहतीमध्ये बिडी कामगार येथे गल्ली बोळ कॉक्रीट करणे | E73: 5 | K73: 5
A74: XE23A302/C7-907 | B74: 4 | D74: खराडकर पार्क येथील नरवडे घरापासून कोद्रे यांचे घरापर्यंत ड्रेनेज लाईन टाकणे | J74: 5 | K74: 5
A75: RE20A302/C2-415 | B75: 4 | D75: प्रभाग क्र. ४ एकनाथ पठारे वस्ती येथे रस्ते कॉक्रीटकरण करणे | E75: 5 | K75: 5
A76: RE20A302/C2-416 | B76: 4 | D76: प्रभाग क्र. ४ शंकर नगर येथील श्रीराम सोसायटी स.नं.३८/४ गल्ली नं.८ येथे मोरे यांचे घराजवळ कॉक्रीट करणे | E76: 5 | K76: 5
A77: RE20C302/C1-512 | B77: 4 | D77: प्रभाग क्र. ४ इ ऑन चौक ते फोरेस्ट कौंटी पर्यंतच्या रस्त्यावर प्रकाश व्यवस्था करणे | F77: 5 | K77: 5
B78: 4 | K78: 0
B79: 4 | D79: एकूण बेरीज | E79: 40 | F79: 40 | G79: 0 | H79: 0 | I79: 0 | J79: 20 | K79: 100
K80: 0
A81: XE23A302/C7-908 | B81: 5 | D81: प्रभाग क्र.५ मध्ये विविध ठिकाणी ड्रेनेज लाईन दुरुस्त करणे व साफ करणे | J81: 5 | K81: 5
A82: RE20A302/C2-417 | B82: 5 | D82: प्रभाग क्र.५ मध्ये गल्लीबोळ व विविध ठिकाणी कॉक्रीट करणे | E82: 5 | K82: 5
A83: RE20A302/C2-418 | B83: 5 | D83: प्रभाग क्र.५ मधील विविध ठिकाणी राडारोडा उचलणे | E83: 5 | K83: 5
