Workbook
Name BdgtNo: [1]index!$L$9
Name BdgtYear: [1]index!$L$8
Name BdgtYrFrom: [1]index!$L$15
Name BdgtYrTo: [1]index!$L$16
Name Description: "P_A_C_Ex"
Name FinYrFrom: [1]index!$L$13
Name FinYrTo: [1]index!$L$14
Name Head: '[1]a|ex|smry'!$B$1:$AE$1
Name Last2Yr: [1]index!$L$7
Name Last3Yr: [1]index!$L$6
Name Last4thYear: [1]index!$L$12
Name Last4Yr: [1]index!$L$5
Name Last5thYear: [1]index!$L$11
Name Last5Yr: [1]index!$L$4
Name List_Smry_0: list21!#REF!
Name List_Smry_1: list21!#REF!
Name List_Smry_2: list21!#REF!
Name P_A_A03: A_Revenue_Income!$A$7:$N$503
Name P_A_A05: A_Revenue_Expenditure!$A$4:$H$1654
Name P_A_A10: [1]A10!$A$2:$P$38,[1]A10!$I$45:$P$75
Name P_A_A12: A_Capital_Expenditure!$A$7:$N$212
Name P_A_A14: A_Land_Acquisition!$A$5:$E$387
Name P_A_A15: A_Fund_Expenditure!$A$7:$N$148
Name P_A_A16: A_DPDC_Machinery_Tree!$A$6:$G$118
Name P_A_Bdgt: A_DPDC_Machinery_Tree!$A$6:$G$118
Name P_A_Bdgt: A_Fund_Expenditure!$A$7:$N$148
Name P_A_Bdgt: A_Land_Acquisition!$A$5:$E$387
Name P_A_Bdgt: A_Revenue_Income!$A$7:$N$503
Name P_A_Bdgt: C_Revenue_Expenditure!$A$4:$H$368
Name P_A_Bdgt: WO_Work21_MC!$A$4:$Q$145
Name P_A_C02: C_Revenue_Income!$A$7:$N$61
Name P_A_C03: C_Revenue_Expenditure!$A$4:$H$368
Name P_A_Doller_MC: [1]dollar!$B$12:$AK$62,[1]dollar!$AM$76:$BH$134,[1]dollar!$BS$176:$BX$231
Name P_A_Doller_SC: [1]dollar!$B$12:$AK$62,[1]dollar!$AM$76:$BH$134,[1]dollar!$BY$176:$CD$231
Name P_A_jnnurm: JNNURM!$A$1:$H$27
Name P_A_ListA: list21!$A$2:$E$7216
Name P_A_ListC: list21!$A$7219:$E$9324
Name P_A_Smry: A_Fund_Expenditure!$A$139:$N$148
Name P_A_SPV: PMAY!$A$1:$G$7
Name P_A_SPV: SPV!$A$1:$G$25
Name P_A_W_RE: WO_Work21_MC!$A$4:$Q$162
Name Print_Area_Bdgt: [1]A10!$A$2:$P$38,[1]A10!$I$45:$P$75
Name txt_cd_1: A_DPDC_Machinery_Tree!$E:$E
Name Yantra_Series: A_DPDC_Machinery_Tree!#REF!

Sheet A_Revenue_Income
A1: जमेचा | G1: तपशील
A2: विवरण | C2: नक्की आकडा | H2: 2020-21 वर्षाचा अंदाज | J2: 2021-22 वर्षाचा अंदाज | M2: 2020-21 वर्षाच्या मान्य अंदाजाशी तुलना केलेला 2021-22 वर्षाचा मा. स्थायी समितीने मान्यता दिलेला अंदाज
C3: 2017-18 | D3: 2018-19 | E3: 2019-20 | F3: 2019-20 शेवटची सहामाही | G3: 2020-21 पहिली सहामाही | H3: मान्य अंदाज | I3: दुरूस्त अंदाज | J3: मा. महापालिका आयुक्त यांनी सुचविलेला | K3: मा. स्थायी समितीने मान्यता दिलेला | L3: मा. महानगर- पालिकेने संमत केलेला
M5: अधिक | N5: कमी
A7: अधिनियमाप्रमाणे कमीत कमी रोख शिल्लक ठेवण्याची रक्कम जमेस धरून वर्षारंभीची शिल्लक | B7: 0 | C7: 100000 | D7: 100000 | E7: 100000 | F7: 100000 | G7: 0 | H7: 100000 | I7: 100000 | J7: 100000 | K7: 100000 | L7: 0 | M7: 0 | N7: 0
C8: 0 | D8: 0 | E8: 0 | F8: 0 | G8: 0 | H8: 0 | I8: 0 | J8: 0 | K8: 0 | L8: 0 | M8: 0 | N8: 0
A9: १. सर्वसाधारण कर, अप्रत्यक्ष कर व इतर जमा | C9: 0 | D9: 0 | E9: 0 | F9: 0 | G9: 0 | H9: 0 | I9: 0 | J9: 0 | K9: 0 | L9: 0 | M9: 0 | N9: 0
A10: क. सर्वसाधारण पट्टी | C10: 0 | D10: 0 | E10: 0 | F10: 0 | G10: 0 | H10: 0 | I10: 0 | J10: 0 | K10: 0 | L10: 0 | M10: 0 | N10: 0
A11: १. नागरिकांकडून (कआकसंप्र) | B11: RI11A101 | C11: 3311564173 | D11: 3361147014 | E11: 3613696720 | F11: 1077695792 | G11: 2531474118 | H11: 8050000000 | I11: 8050000000 | J11: 9050000000 | K11: 11050000000 | L11: 0 | M11: 3000000000 | N11: 0
A12: लोहगाव (उर्वरित) | B12: RI11AA101 | C12: 6685 | D12: 37675 | E12: 646073 | F12: 431813 | G12: 191050 | H12: 0 | I12: 0 | J12: 0 | K12: 0 | L12: 0 | M12: 0 | N12: 0
A13: मुंढवा (उर्वरित केशवनगर) | B13: RI11AB101 | C13: 2930 | D13: 8185 | E13: 1067975 | F13: 678090 | G13: 70995 | H13: 0 | I13: 0 | J13: 0 | K13: 0 | L13: 0 | M13: 0 | N13: 0
A14: हडपसर (संपूर्ण साडेसतरानळी) | B14: RI11AC101 | C14: 865 | D14: 3735 | E14: 85825 | F14: 85675 | G14: 8800 | H14: 0 | I14: 0 | J14: 0 | K14: 0 | L14: 0 | M14: 0 | N14: 0
A15: शिवणे (संपूर्ण उत्तमनगर) | B15: RI11AD101 | C15: 295 | D15: 13465 | E15: 387130 | F15: 245265 | G15: 85205 | H15: 0 | I15: 0 | J15: 0 | K15: 0 | L15: 0 | M15: 0 | N15: 0
A16: शिवणे | B16: RI11AE101 | C16: 0 | D16: 9565 | E16: 2103535 | F16: 975665 | G16: 138550 | H16: 0 | I16: 0 | J16: 0 | K16: 0 | L16: 0 | M16: 0 | N16: 0
A17: आंबेगाव खुर्द | B17: RI11AF101 | C17: 4070 | D17: 6810 | E17: 1974340 | F17: 1102295 | G17: 86270 | H17: 0 | I17: 0 | J17: 0 | K17: 0 | L17: 0 | M17: 0 | N17: 0
A18: उंड्री | B18: RI11AG101 | C18: 3145 | D18: 3755 | E18: 1132345 | F18: 911445 | G18: 826845 | H18: 0 | I18: 0 | J18: 0 | K18: 0 | L18: 0 | M18: 0 | N18: 0
A19: धायरी | B19: RI11AH101 | C19: 1460 | D19: 32565 | E19: 24150 | F19: 2680 | G19: 124535 | H19: 0 | I19: 0 | J19: 0 | K19: 0 | L19: 0 | M19: 0 | N19: 0
A20: आंबेगाव बुद्रुक | B20: RI11AJ101 | C20: 19000 | D20: 19645 | E20: 2560515 | F20: 1545540 | G20: 215745 | H20: 0 | I20: 0 | J20: 0 | K20: 0 | L20: 0 | M20: 0 | N20: 0
A21: फुरसुंगी | B21: RI11AK101 | C21: 31460 | D21: 110450 | E21: 2070710 | F21: 1557730 | G21: 293510 | H21: 0 | I21: 0 | J21: 0 | K21: 0 | L21: 0 | M21: 0 | N21: 0
A22: उरुळी देवाची | B22: RI11AL101 | C22: 15030 | D22: 33235 | E22: 101150 | F22: 62960 | G22: 40770 | H22: 0 | I22: 0 | J22: 0 | K22: 0 | L22: 0 | M22: 0 | N22: 0
... A27: पुणे मनपा हद्दीमध्ये नव्याने समाविष्ट होणारी 23 गावे (कआकसंप्र) | B27: RI11A107 | C27: 0 | D27: 0 | E27: 0 | F27: 0 | G27: 0 | H27: 0 | I27: 0 | J27: 1300000000 | K27: 2300000000 | L27: 0 | M27: 2300000000 | N27: 0
C28: 0 | D28: 0 | E28: 0 | F28: 0 | G28: 0 | H28: 0 | I28: 0 | J28: 0 | K28: 0 | L28: 0 | M28: 0 | N28: 0
A29: क. सर्वसाधारण कर बेरीज | C29: 3431242459 | D29: 3525303066 | E29: 3803991790 | F29: 1122309375 | G29: 2596010987 | H29: 11707800000 | I29: 11707800000 | J29: 10516500000 | K29: 13516500000 | L29: 0 | M29: 1808700000 | N29: 0
C30: 0 | D30: 0 | E30: 0 | F30: 0 | G30: 0 | H30: 0 | I30: 0 | J30: 0 | K30: 0 | L30: 0 | M30: 0 | N30: 0
A31: ख. आयातकर | C31: 0 | D31: 0 | E31: 0 | F31: 0 | G31: 0 | H31: 0 | I31: 0 | J31: 0 | K31: 0 | L31: 0 | M31: 0 | N31: 0
A32: १. पक्की जमा (आ.क.प्र.) | B32: RI11B101 | C32: 0 | D32: -5618500 | E32: -4881548 | F32: -4881548 | G32: 0 | H32: 0 | I32: 0 | J32: 0 | K32: 0 | L32: 0 | M32: 0 | N32: 0
C33: 0 | D33: 0 | E33: 0 | F33: 0 | G33: 0 | H33: 0 | I33: 0 | J33: 0 | K33: 0 | L33: 0 | M33: 0 | N33: 0
A34: ख. निव्वळ आयातकर एकूण बेरीज | C34: 0 | D34: -5618500 | E34: -4881548 | F34: -4881548 | G34: 0 | H34: 0 | I34: 0 | J34: 0 | K34: 0 | L34: 0 | M34: 0 | N34: 0
C35: 0 | D35: 0 | E35: 0 | F35: 0 | G35: 0 | H35: 0 | I35: 0 | J35: 0 | K35: 0 | L35: 0 | M35: 0 | N35: 0
A36: ख-१. स्थानिक संस्था कर | C36: 0 | D36: 0 | E36: 0 | F36: 0 | G36: 0 | H36: 0 | I36: 0 | J36: 0 | K36: 0 | L36: 0 | M36: 0 | N36: 0
A37: स्थानिक संस्था कर नोंदणी शुल्क | B37: RI11B201 | C37: 489206 | D37: 300 | E37: 0 | F37: 0 | G37: 0 | H37: 0 | I37: 0 | J37: 0 | K37: 0 | L37: 0 | M37: 0 | N37: 0
A38: स्थानिक संस्था कर | B38: RI11B202 | C38: 1514559653 | D38: 14074585 | E38: 1120093 | F38: 460463 | G38: 0 | H38: 10000000 | I38: 10000000 | J38: 5000000 | K38: 5000000 | L38: 0 | M38: 0 | N38: 5000000
A39: चौरस मीटर बांधकामाप्रमाणे भरावयाची ठोक रक्कम | B39: RI11B202B | C39: 87144478 | D39: 3832035 | E39: 5510120 | F39: 2330247 | G39: 0 | H39: 100000 | I39: 100000 | J39: 200000 | K39: 200000 | L39: 0 | M39: 100000 | N39: 0
A40: निर्गत मालापोटी १० % हिस्सा | B40: RI11B202D | C40: 1498056 | D40: 0 | E40: 0 | F40: 0 | G40: 0 | H40: 0 | I40: 0 | J40: 0 | K40: 0 | L40: 0 | M40: 0 | N40: 0
A41: इतर जमा - स्थानिक संस्था कर | B41: RI11B202E | C41: 0 | D41: 25232 | E41: 1780 | F41: 1780 | G41: 0 | H41: 0 | I41: 0 | J41: 0 | K41: 0 | L41: 0 | M41: 0 | N41: 0
A42: स्थानिक संस्था करापोटी व्याज | B42: RI11B203 | C42: 24745902 | D42: 6911393 | E42: 821243 | F42: 368373 | G42: 0 | H42: 1400000 | I42: 1400000 | J42: 500000 | K42: 500000 | L42: 0 | M42: 0 | N42: 900000
A43: स्थानिक संस्था कर शास्ती (दंड) | B43: RI11B204 | C43: 295000 | D43: 80000 | E43: 25000 | F43: 25000 | G43: 5000 | H43: 0 | I43: 0 | J43: 0 | K43: 0 | L43: 0 | M43: 0 | N43: 0
A44: राज्य शासनाकडून मुद्रांक शुल्क अधिभारापोटी मिळालेली रक्कम (१%) | B44: RI11B206 | C44: 1769515876 | D44: 2758200420 | E44: 1749317051 | F44: 1236376967 | G44: 247275393 | H44: 2500000000 | I44: 2500000000 | J44: 1700000000 | K44: 1700000000 | L44: 0 | M44: 0 | N44: 800000000
A45: मनपा ठेकेदारांच्या बिलांमधून LBT वसुली | B45: RI11B207 | C45: 3161206 | D45: 92301 | E45: 889 | F45: 802 | G45: 6082 | H45: 0 | I45: 0 | J45: 0 | K45: 0 | L45: 0 | M45: 0 | N45: 0
A46: राज्यशासनाकडून LBT साठी सहाय्यक अनुदान | B46: RI11B208 | C46: 4285500000 | D46: 0 | E46: 0 | F46: 0 | G46: 0 | H46: 0 | I46: 0 | J46: 0 | K46: 0 | L46: 0 | M46: 0 | N46: 0
C47: 0 | D47: 0 | E47: 0 | F47: 0 | G47: 0 | H47: 0 | I47: 0 | J47: 0 | K47: 0 | L47: 0 | M47: 0 | N47: 0
A48: ख-१. स्थानिक संस्था कर बेरीज | C48: 7686909377 | D48: 2783216266 | E48: 1756796176 | F48: 1239563632 | G48: 247286475 | H48: 2511500000 | I48: 2511500000 | J48: 1705700000 | K48: 1705700000 | L48: 0 | M48: 0 | N48: 805800000
C49: 0 | D49: 0 | E49: 0 | F49: 0 | G49: 0 | H49: 0 | I49: 0 | J49: 0 | K49: 0 | L49: 0 | M49: 0 | N49: 0
A50: वजा :- स्थानिक संस्था कर रिफंड | B50: RI11B251 | C50: 0 | D50: 24998 | E50: 17276886 | F50: 0 | G50: 0 | H50: 120000000 | I50: 120000000 | J50: 0 | K50: 0 | L50: 0 | M50: 0 | N50: 120000000
C51: 0 | D51: 0 | E51: 0 | F51: 0 | G51: 0 | H51: 0 | I51: 0 | J51: 0 | K51: 0 | L51: 0 | M51: 0 | N51: 0
A52: ख-१. स्थानिक संस्था कर एकूण बेरीज | C52: 7686909377 | D52: 2783191268 | E52: 1739519290 | F52: 1239563632 | G52: 247286475 | H52: 2391500000 | I52: 2391500000 | J52: 1705700000 | K52: 1705700000 | L52: 0 | M52: 0 | N52: 685800000
C53: 0 | D53: 0 | E53: 0 | F53: 0 | G53: 0 | H53: 0 | I53: 0 | J53: 0 | K53: 0 | L53: 0 | M53: 0 | N53: 0
A54: राज्यशासनाकडून महाराष्ट्र वस्तू व सेवा कर अंतर्गत अनुदान (GST) | B54: RI11B209 | C54: 10984000000 | D54: 15728200000 | E54: 17025600000 | F54: 8512800000 | G54: 9193800000 | H54: 18387600000 | I54: 18387600000 | J54: 19858800000 | K54: 19858800000 | L54: 0 | M54: 1471200000 | N54: 0
A55: ग. इतर कर | C55: 0 | D55: 0 | E55: 0 | F55: 0 | G55: 0 | H55: 0 | I55: 0 | J55: 0 | K55: 0 | L55: 0 | M55: 0 | N55: 0
A56: १. करमणूककर (कआकसंप्र) | B56: RI11C101 | C56: 16637835 | D56: 18144020 | E56: 17587320 | F56: 9712870 | G56: 1562130 | H56: 22500000 | I56: 22500000 | J56: 22500000 | K56: 22500000 | L56: 0 | M56: 0 | N56: 0
A57: २. व्यवसायकर (कआकसंप्र) शासनाकडून व्यवसाय करापोटी मिळणारी नुकसान भरपाई | B57: RI11C102 | C57: 0 | D57: 0 | E57: 0 | F57: 0 | G57: 0 | H57: 3500000 | I57: 3500000 | J57: 3500000 | K57: 3500000 | L57: 0 | M57: 0 | N57: 0
A58: ३. राज्य शासनाने बसविलेल्या करमणूककरापोटी मिळणारा हिस्सा (शासनाकडून) (कआकसंप्र) | B58: RI11C103 | C58: 0 | D58: 0 | E58: 0 | F58: 0 | G58: 0 | H58: 20000000 | I58: 20000000 | J58: 0 | K58: 0 | L58: 0 | M58: 0 | N58: 20000000
C59: 0 | D59: 0 | E59: 0 | F59: 0 | G59: 0 | H59: 0 | I59: 0 | J59: 0 | K59: 0 | L59: 0 | M59: 0 | N59: 0
A60: ग. बेरीज | C60: 16637835 | D60: 18144020 | E60: 17587320 | F60: 9712870 | G60: 1562130 | H60: 46000000 | I60: 46000000 | J60: 26000000 | K60: 26000000 | L60: 0 | M60: 0 | N60: 20000000
C61: 0 | D61: 0 | E61: 0 | F61: 0 | G61: 0 | H61: 0 | I61: 0 | J61: 0 | K61: 0 | L61: 0 | M61: 0 | N61: 0
A62: घ. महानगरपालिका अधिनियमाखाली दंडाबाबत शासकीय सहाय्य (वि. सल्लागार) | B62: RI11D101 | C62: 1321170 | D62: 733050 | E62: 1316400 | F62: 1316400 | G62: 0 | H62: 0 | I62: 0 | J62: 0 | K62: 0 | L62: 0 | M62: 0 | N62: 0
C63: 0 | D63: 0 | E63: 0 | F63: 0 | G63: 0 | H63: 0 | I63: 0 | J63: 0 | K63: 0 | L63: 0 | M63: 0 | N63: 0
A64: ड-१ गुंतविलेल्या रकमांवरील व्याज (मु.ले.) | B64: RI11E101 | C64: 1089426825 | D64: 1622335365 | E64: 1603520711 | F64: 1298821319 | G64: 325255021 | H64: 921100000 | I64: 921100000 | J64: 470000000 | K64: 470000000 | L64: 0 | M64: 0 | N64: 451100000
A65: ड-३ विविध खात्यांच्या ऑडिट अहवालातून वसुली | B65: RI11E107 | C65: 1913151 | D65: 710465 | E65: 333042 | F65: 84273 | G65: 5611 | H65: 2000000 | I65: 2000000 | J65: 0 | K65: 0 | L65: 0 | M65: 0 | N65: 2000000
A66: ज्यादा आकार वसुली (मु.ले.) | B66: RI11E109 | C66: 0 | D66: 0 | E66: 2434560 | F66: 2434560 | G66: 686301 | H66: 0 | I66: 0 | J66: 0 | K66: 0 | L66: 0 | M66: 0 | N66: 0
A67: पुणे महानगरपालिकेस बक्षिसापोटी मिळालेल्या रकमा | B67: RI11E122 | C67: 0 | D67: 0 | E67: 0 | F67: 0 | G67: 0 | H67: 500000 | I67: 500000 | J67: 0 | K67: 0 | L67: 0 | M67: 0 | N67: 500000
A68: सेवकांसाठी सेवापुस्तक शुल्क | B68: RI11E123 | C68: 8095 | D68: 8405 | E68: 4440 | F68: 2280 | G68: 0 | H68: 0 | I68: 0 | J68: 0 | K68: 0 | L68: 0 | M68: 0 | N68: 0
A69: पुणे मनपाच्या हद्दीत नव्याने समाविष्ट झालेल्या 11 गावातील इतर जमा (मु.ले.) | B69: RI11E124 | C69: 54205641 | D69: 99689170 | E69: 9061000 | F69: 9058922 | G69: 0 | H69: 0 | I69: 0 | J69: 0 | K69: 0 | L69: 0 | M69: 0 | N69: 0
C70: 0 | D70: 0 | E70: 0 | F70: 0 | G70: 0 | H70: 0 | I70: 0 | J70: 0 | K70: 0 | L70: 0 | M70: 0 | N70: 0
A71: ज. इतर जमा | C71: 0 | D71: 0 | E71: 0 | F71: 0 | G71: 0 | H71: 0 | I71: 0 | J71: 0 | K71: 0 | L71: 0 | M71: 0 | N71: 0
A72: ज१. जुनी रद्दी विक्री (मसआ.जिंघ.) | B72: RI11H101 | C72: 0 | D72: 191635 | E72: 72394 | F72: 51259 | G72: 35383 | H72: 500000 | I72: 500000 | J72: 0 | K72: 0 | L72: 0 | M72: 0 | N72: 500000
C73: 0 | D73: 0 | E73: 0 | F73: 0 | G73: 0 | H73: 0 | I73: 0 | J73: 0 | K73: 0 | L73: 0 | M73: 0 | N73: 0
A74: ज२. शुल्काचे उत्पन्न | C74: 0 | D74: 0 | E74: 0 | F74: 0 | G74: 0 | H74: 0 | I74: 0 | J74: 0 | K74: 0 | L74: 0 | M74: 0 | N74: 0
A75: अ. मसुदा शुल्क (वि. सल्लागार) | B75: RI11H102A | C75: 4450136 | D75: 5721837 | E75: 5185432 | F75: 3225921 | G75: 751348 | H75: 10000000 | I75: 10000000 | J75: 5000000 | K75: 5000000 | L75: 0 | M75: 0 | N75: 5000000
A76: ब. दाव्याचा खर्च व प्रोसेस शुल्क (वि. सल्लागार) | B76: RI11H102B | C76: 350 | D76: 7750 | E76: 0 | F76: 0 | G76: 0 | H76: 200000 | I76: 200000 | J76: 0 | K76: 0 | L76: 0 | M76: 0 | N76: 200000
A77: क. नक्कल शुल्क (झोनिपु) | B77: RI11H102C | C77: 141998 | D77: 103721 | E77: 115549 | F77: 76979 | G77: 14192 | H77: 300000 | I77: 300000 | J77: 300000 | K77: 300000 | L77: 0 | M77: 0 | N77: 0
A78: ड. अधिपत्र (Warrant) शुल्क (कआकसंप्र) | B78: RI11H102D | C78: 10440743 | D78: 11012968 | E78: 8291369 | F78: 5474584 | G78: 2226610 | H78: 20000000 | I78: 20000000 | J78: 20000000 | K78: 20000000 | L78: 0 | M78: 0 | N78: 0
A79: ई. सूचनापत्र (Notice) शुल्क (कआकसंप्र) | B79: RI11H102E | C79: 989585 | D79: 995201 | E79: 707417 | F79: 454891 | G79: 73833 | H79: 500000 | I79: 500000 | J79: 500000 | K79: 500000 | L79: 0 | M79: 0 | N79: 0
A80: फ. मिळकतीच्या मालकी हक्काबद्दल शुल्क (कआकसंप्र) | B80: RI11H102F | C80: 77588900 | D80: 129719220 | E80: 90083435 | F80: 49113790 | G80: 12071970 | H80: 85000000 | I80: 85000000 | J80: 90000000 | K80: 90000000 | L80: 0 | M80: 5000000 | N80: 0
A81: ग. मिळकतकर थकबाकी शास्ती (२%) (कआकसंप्र) | B81: RI11H102G | C81: 556106175 | D81: 772687238 | E81: 694859495 | F81: 440827356 | G81: 159785182 | H81: 1530000000 | I81: 1530000000 | J81: 1750000000 | K81: 1750000000 | L81: 0 | M81: 220000000 | N81: 0
C82: 0 | D82: 0 | E82: 0 | F82: 0 | G82: 0 | H82: 0 | I82: 0 | J82: 0 | K82: 0 | L82: 0 | M82: 0 | N82: 0
A83: ज२. बेरीज | C83: 649717887 | D83: 920247935 | E83: 799242697 | F83: 499173521 | G83: 174923135 | H83: 1646000000 | I83: 1646000000 | J83: 1865800000 | K83: 1865800000 | L83: 0 | M83: 219800000 | N83: 0
C84: 0 | D84: 0 | E84: 0 | F84: 0 | G84: 0 | H84: 0 | I84: 0 | J84: 0 | K84: 0 | L84: 0 | M84: 0 | N84: 0
A85: ज३. किरकोळ जमा | C85: 0 | D85: 0 | E85: 0 | F85: 0 | G85: 0 | H85: 0 | I85: 0 | J85: 0 | K85: 0 | L85: 0 | M85: 0 | N85: 0
A86: अ. न नेलेली व जप्त केलेली अनामत पक्की जमा (मु.ले.) | B86: RI11H103A | C86: 15736 | D86: 36948 | E86: 433965 | F86: 22444 | G86: 0 | H86: 0 | I86: 0 | J86: 0 | K86: 0 | L86: 0 | M86: 0 | N86: 0
A87: क.१ मतदार याद्या विक्री (म.स.आ.) | B87: RI11H103C | C87: 20547 | D87: 0 | E87: 0 | F87: 0 | G87: 0 | H87: 15000 | I87: 15000 | J87: 17125000 | K87: 17125000 | L87: 0 | M87: 17110000 | N87: 0
A88: क.२ इतर किरकोळ जमा | B88: RI11H103D | C88: 5662 | D88: 6175 | E88: 8972 | F88: 536 | G88: 0 | H88: 5000 | I88: 5000 | J88: 10000 | K88: 10000 | L88: 0 | M88: 5000 | N88: 0
A89: ड. इतर खात्यांकडील पुस्तके, मॅन्युअल्स्‌, नकाशे इ. (मसआ.जिंघ.) | B89: RI11H103E | C89: 3434 | D89: 9497 | E89: 13582 | F89: 10087 | G89: 1340 | H89: 0 | I89: 0 | J89: 0 | K89: 0 | L89: 0 | M89: 0 | N89: 0
A90: ई. भांडार खात्याकडील जुने साहित्य विक्री (म.स.आ.) | B90: RI11H103F | C90: 28131029 | D90: 1442300 | E90: 1933256 | F90: 831000 | G90: 426000 | H90: 40000000 | I90: 40000000 | J90: 40000000 | K90: 40000000 | L90: 0 | M90: 0 | N90: 0
A91: छ. घरबांधणी कर्ज फॉर्म विक्री (मसआ.जिंघ.) | B91: RI11H103K | C91: 2925 | D91: 3100 | E91: 1700 | F91: 1000 | G91: 0 | H91: 0 | I91: 0 | J91: 0 | K91: 0 | L91: 0 | M91: 0 | N91: 0
A92: सेवकवर्ग विभाग इतर जमा | B92: RI11H103N | C92: 1756 | D92: 40640 | E92: 7400 | F92: 0 | G92: 6200 | H92: 2000000 | I92: 2000000 | J92: 0 | K92: 0 | L92: 0 | M92: 0 | N92: 2000000
A93: सुरक्षा विभाग इतर जमा | B93: RI11H103P | C93: 12456 | D93: 117856 | E93: 1350 | F93: 1350 | G93: 0 | H93: 0 | I93: 0 | J93: 0 | K93: 0 | L93: 0 | M93: 0 | N93: 0
A94: महाराष्ट्र माहितीचा अधिकार अधिनियम | B94: RI11H103R | C94: 508187 | D94: 761562 | E94: 425054 | F94: 164971 | G94: 47334 | H94: 2000 | I94: 2000 | J94: 3000 | K94: 3000 | L94: 0 | M94: 1000 | N94: 0
A95: CFC अंतर्गत जमा होणारी रक्कम | B95: RI11H103S | C95: 934036 | D95: 1515652 | E95: 998055 | F95: 514365 | G95: 119370 | H95: 0 | I95: 0 | J95: 0 | K95: 0 | L95: 0 | M95: 0 | N95: 0
C96: 0 | D96: 0 | E96: 0 | F96: 0 | G96: 0 | H96: 0 | I96: 0 | J96: 0 | K96: 0 | L96: 0 | M96: 0 | N96: 0
A97: ज३. बेरीज | C97: 29635768 | D97: 3933730 | E97: 3823334 | F97: 1545753 | G97: 600244 | H97: 42022000 | I97: 42022000 | J97: 57138000 | K97: 57138000 | L97: 0 | M97: 15116000 | N97: 0
C98: 0 | D98: 0 | E98: 0 | F98: 0 | G98: 0 | H98: 0 | I98: 0 | J98: 0 | K98: 0 | L98: 0 | M98: 0 | N98: 0
A99: ज. इतर जमा एकूण बेरीज | C99: 679353655 | D99: 924373300 | E99: 803138425 | F99: 500770533 | G99: 175558762 | H99: 1688522000 | I99: 1688522000 | J99: 1922938000 | K99: 1922938000 | L99: 0 | M99: 234416000 | N99: 0
C100: 0 | D100: 0 | E100: 0 | F100: 0 | G100: 0 | H100: 0 | I100: 0 | J100: 0 | K100: 0 | L100: 0 | M100: 0 | N100: 0
A101: १. सर्वसाधारणकर, अप्रत्यक्षकर व इतर जमा एकूण बेरीज | C101: 23945018208 | D101: 24697069609 | E101: 25001625430 | F101: 12691992616 | G101: 12540165287 | H101: 35145022000 | I101: 35145022000 | J101: 34499938000 | K101: 37499938000 | L101: 0 | M101: 2354916000 | N101: 0
A102: २. प्राथमिक शिक्षण | C102: 0 | D102: 0 | E102: 0 | F102: 0 | G102: 0 | H102: 0 | I102: 0 | J102: 0 | K102: 0 | L102: 0 | M102: 0 | N102: 0
A103: शासकीय अनुदान - प्राथमिक शिक्षण | B103: RI12A101 | C103: 815116563 | D103: 830367728 | E103: 883423008 | F103: 406309008 | G103: 407445000 | H103: 1100000000 | I103: 1100000000 | J103: 1210000000 | K103: 1210000000 | L103: 0 | M103: 110000000 | N103: 0
A104: प्राथमिक शिक्षण विभाग – शाळा भाडे | B104: RI12A103 | C104: 925702 | D104: 4574741 | E104: 896883 | F104: -109547 | G104: 157179 | H104: 800000 | I104: 800000 | J104: 900000 | K104: 900000 | L104: 0 | M104: 100000 | N104: 0
A105: दंड, साक्षी, भत्ता इत्यादी | B105: RI12A104 | C105: 0 | D105: 0 | E105: 0 | F105: 0 | G105: 0 | H105: 10000 | I105: 10000 | J105: 10000 | K105: 10000 | L105: 0 | M105: 0 | N105: 0
A106: बालवाडी शुल्क | B106: RI12A105 | C106: 0 | D106: 0 | E106: 0 | F106: 0 | G106: 0 | H106: 5000 | I106: 5000 | J106: 5000 | K106: 5000 | L106: 0 | M106: 0 | N106: 0
...

Sheet A_Revenue_Expenditure
A1: योजनेतर खर्च तपशील
A2: विवरण | D2: नक्‍की आकडा | G2: मान्य अंदाज 2020-21 | H2: नवीन अंदाज
D3: 2017-18 | E3: 2018-19 | F3: 2019-20 | H3: 2021-22
A5: १. मुख्य देखरेख, वसुली वगैरे | D5: 0 | E5: 0 | F5: 0 | G5: 0 | H5: 0
A6: क. महानगरपालिका व स्थायी समिती | D6: 0 | E6: 0 | F6: 0 | G6: 0 | H6: 0
A7: १ नगरसचिव यांचे कार्यालय | D7: 0 | E7: 0 | F7: 0 | G7: 0 | H7: 0
A8: १. नगरसचिव (म्युनिसिपल सेक्रेटरी) (मुं.प्रां. मनपा अधिनियम, कलम४५(३) प्रमाणे) वेतन | B8: RE11A101A | D8: 1142457 | E8: 1357957 | F8: 1343918 | G8: 1600000 | H8: 1500000
A9: २. कायम सेवकवर्ग वेतन | B9: RE11A102A | D9: 39568566 | E9: 38537287 | F9: 37739899 | G9: 42500000 | H9: 45000000
A10: ३. संकीर्ण (न.स.) | B10: RE11A103 | D10: 4393519 | E10: 4967904 | F10: 727424 | G10: 7200000 | H10: 10000000
A11: ३अ. मागील बिले देण्यासाठी (न.स.) | B11: RE11A103A | D11: 3965718 | E11: 2886671 | F11: 1251212 | G11: 3600000 | H11: 4000000
A12: ४. प्रवास खर्च (न.स.) | B12: RE11A104 | D12: 22316 | E12: 35207 | F12: 133002 | G12: 1800000 | H12: 2000000
A13: ५. ग्रंथालय व वाचनालय | B13: RE11A105 | D13: 196204 | E13: 172716 | F13: 189625 | G13: 225000 | H13: 250000
A14: ६. समारंभ खर्च (न.स. व वि.अ.) | B14: RE11A106 | D14: 45760 | E14: 68200 | F14: 0 | G14: 450000 | H14: 500000
A15: १०. अखिल भारतीय/महाराष्ट्र महापौर परिषद व अखिल भारतीय स्थानिक स्वराज्य संस्था प्रतिनिधी अधिवेशन | B15: RE11A110 | D15: 0 | E15: 0 | F15: 0 | G15: 270000 | H15: 300000
A16: ११. मनपा व शासकीय निवृत्त सेवकांना द्यावयाचा चहापान खर्च | B16: RE11A111 | D16: 114450 | E16: 3000 | F16: 0 | G16: 270000 | H16: 300000
A17: १३. महाराष्ट्र राज्य महानगरपालिका स्थायी समिती अध्यक्ष परिषद वर्गणी व तद्‌नुषंगिक खर्च | B17: RE11A113 | D17: 0 | E17: 0 | F17: 0 | G17: 900 | H17: 1000
A18: १४. मा. महापौर यांचा व्ययनियमन (सम्प्च्युअरी) भत्ता | B18: RE11A114 | D18: 0 | E18: 0 | F18: 0 | G18: 4500 | H18: 5000
A19: १५. मा. महापौर यांचा ऐच्छिक खर्च | B19: RE11A115 | D19: 199238 | E19: 95427 | F19: 57402 | G19: 180000 | H19: 200000
... A53: नगरसचिव विभागामार्फत आवश्यक सेवक भरती करणे (कंत्राटी) | B53: RE11A280 | D53: 0 | E53: 0 | F53: 0 | G53: 10000000 | H53: 10000000
D54: 0 | E54: 0 | F54: 0 | G54: 0 | H54: 0
A55: क. मनपा व स्थायी समिती बेरीज | D55: 109200819 | E55: 87211238 | F55: 94077423 | G55: 172230100 | H55: 173656000
D56: 0 | E56: 0 | F56: 0 | G56: 0 | H56: 0
A57: ख. मुख्य लेखापरिक्षक यांचे कार्यालय | D57: 0 | E57: 0 | F57: 0 | G57: 0 | H57: 0
A58: १. मुख्य लेखापरिक्षक (म्युनिसिपल चीफ ऑडिटर) (मु.प्रां. मनपा अधिनियम, कलम ४५ (३) प्रमाणे) यांचे वेतन | B58: RE11B101A | D58: 4018155 | E58: 2623589 | F58: 2390291 | G58: 2700000 | H58: 2500000
A59: २. कायम सेवकवर्ग वेतन | B59: RE11B102A | D59: 23877085 | E59: 29232284 | F59: 26552946 | G59: 30000000 | H59: 29000000
A60: ३. संकीर्ण | B60: RE11B103 | D60: 109686 | E60: 115189 | F60: 66256 | G60: 225000 | H60: 225000
D61: 0 | E61: 0 | F61: 0 | G61: 0 | H61: 0
A62: ख. मुख्यलेखापरिक्षक यांचे कार्या. बेरीज | D62: 28004926 | E62: 31971062 | F62: 29009493 | G62: 32925000 | H62: 31725000
D63: 0 | E63: 0 | F63: 0 | G63: 0 | H63: 0
A64: ग१. महापालिका आयुक्त यांचे कार्यालय | D64: 0 | E64: 0 | F64: 0 | G64: 0 | H64: 0
A65: १. महापालिका आयुक्त (म्युनिसिपल कमिशनर) (मु. प्रां. मनपा अधिनियम, कलम ३७ (१) प्रमाणे) यांचे वेतन | B65: RE11C101A | D65: 2633227 | E65: 2531394 | F65: 2816569 | G65: 3200000 | H65: 3000000
A66: २. उपआयुक्त (जनरल) (मुं. प्रां. मनपा अधिनियम, कलम ४५(३) प्रमाणे) यांचे वेतन | B66: RE11C102A | D66: 610426 | E66: 1175614 | F66: 1635153 | G66: 2500000 | H66: 2500000
A67: ३. कायम सेवकवर्ग वेतन | B67: RE11C103A | D67: 28024193 | E67: 29549463 | F67: 28289154 | G67: 31000000 | H67: 29500000
A68: ४. संकीर्ण | B68: RE11C104 | D68: 1342954 | E68: 1356556 | F68: 1450875 | G68: 1800000 | H68: 2000000
A69: ६. मा. महापालिका आयुक्त यांचा ऐच्छिक खर्च (म.स.आ.) | B69: RE11C106 | D69: 14147 | E69: 50003 | F69: 139240 | G69: 720000 | H69: 850000
D70: 0 | E70: 0 | F70: 0 | G70: 0 | H70: 0
A71: ग१. महापालिका आयुक्त कार्यालय बेरीज | D71: 32624947 | E71: 34663030 | F71: 34330991 | G71: 39220000 | H71: 37850000
D72: 0 | E72: 0 | F72: 0 | G72: 0 | H72: 0
A73: ग२. अतिरिक्त महापालिका आयुक्त (विशेष) यांचे कार्यालय | D73: 0 | E73: 0 | F73: 0 | G73: 0 | H73: 0
A74: १. अतिरिक्त महापालिका आयुक्त (विशेष) यांचे वेतन | B74: RE11C126A | D74: 1012344 | E74: 2041368 | F74: 1390901 | G74: 3200000 | H74: 3000000
A75: २. कायम सेवकवर्ग वेतन | B75: RE11C127A | D75: 12079222 | E75: 13598908 | F75: 14067805 | G75: 15000000 | H75: 15000000
A76: ३. संकीर्ण | B76: RE11C128 | D76: 101682 | E76: 295033 | F76: 145323 | G76: 720000 | H76: 800000
A77: ४. मनपा सेवकांस विविध सेमिनर, कॉन्फरन्स, प्रशिक्षण इ. साठी हजर राहण्यासाठी खर्च | B77: RE11C129 | D77: 21737 | E77: 33097 | F77: 48945 | G77: 270000 | H77: 300000
A78: 5. अतिरिक्त महापालिका आयुक्त (विशेष) यांचेकडे येणार्‍या पाहुण्यांचा आतिथ्याकरिता होणारा खर्च | B78: RE11C129C | D78: 12368 | E78: 9570 | F78: 0 | G78: 270000 | H78: 300000
A79: ग२. अतिरिक्त महापालिका आयुक्त (विशेष) यांचे कार्यालय बेरीज | D79: 13227353 | E79: 15977976 | F79: 15652974 | G79: 19460000 | H79: 19400000
D80: 0 | E80: 0 | F80: 0 | G80: 0 | H80: 0
A81: ग३. अतिरिक्त महापालिका आयुक्त (जनरल) यांचे कार्यालय | D81: 0 | E81: 0 | F81: 0 | G81: 0 | H81: 0
A82: १. मा. अतिरिक्त महापालिका आयुक्त (जनरल) यांचे वेतन | B82: RE11C131A | D82: 722990 | E82: 570358 | F82: 1508356 | G82: 3200000 | H82: 3000000
A83: २. कायम सेवकवर्ग वेतन | B83: RE11C132A | D83: 12644018 | E83: 11585239 | F83: 10819677 | G83: 15000000 | H83: 13500000
A84: ३. संकीर्ण | B84: RE11C133 | D84: 194999 | E84: 169434 | F84: 102866 | G84: 720000 | H84: 800000
A85: ४.अतिरिक्त महापालिका आयुक्त (जनरल) यांचेकडे येणार्‍या पाहुण्यांचा आतिथ्याकरिता होणारा खर्च | B85: RE11C134 | D85: 7999 | E85: 4633 | F85: 15818 | G85: 270000 | H85: 300000
A86: ५. अधिकारी / सेवक प्रशिक्षण वर्ग / कार्यशाळेस उपस्थित राहण्याचा प्रवासखर्च, कार्यशाळा शुल्क, प्रशिक्षण शुल्क वगैरे | B86: RE11C135 | D86: 0 | E86: 66363 | F86: 79157 | G86: 270000 | H86: 200000
D87: 0 | E87: 0 | F87: 0 | G87: 0 | H87: 0
A88: ग३. अतिरिक्त महापालिका आयुक्त (जनरल) यांचे कार्यालय बेरीज | D88: 13570006 | E88: 12396027 | F88: 12525874 | G88: 19460000 | H88: 17800000
D89: 0 | E89: 0 | F89: 0 | G89: 0 | H89: 0
A90: ग४. अतिरिक्त महापालिका आयुक्त (इस्टेट) यांचे कार्यालय | D90: 0 | E90: 0 | F90: 0 | G90: 0 | H90: 0
A91: १. मा. अतिरिक्त महापालिका आयुक्त (इस्टेट) यांचे वेतन | B91: RE11C141 | D91: 295904 | E91: 881779 | F91: 2297535 | G91: 3200000 | H91: 3000000
A92: २. कायम सेवकवर्ग वेतन | B92: RE11C142 | D92: 9284889 | E92: 7129521 | F92: 8690113 | G92: 8000000 | H92: 10000000
A93: ३. संकीर्ण | B93: RE11C143 | D93: 90845 | E93: 418716 | F93: 139447 | G93: 720000 | H93: 800000
A94: ४.अतिरिक्त महापालिका आयुक्त (इस्टेट) यांचेकडे येणार्‍या पाहुण्यांचा आतिथ्याकरिता होणारा खर्च | B94: RE11C144 | D94: 0 | E94: 0 | F94: 6374 | G94: 270000 | H94: 300000
A95: 6. प्रशिक्षण वर्ग / कार्यशाळेस उपस्थित राहण्याचा प्रवासखर्च | B95: RE11C146 | D95: 0 | E95: 167071 | F95: 217849 | G95: 270000 | H95: 300000
A96: ग४. अतिरिक्त महापालिका आयुक्त (इस्टेट) यांचे कार्यालय बेरीज | D96: 9671638 | E96: 8597087 | F96: 11351318 | G96: 12460000 | H96: 14400000
A97: ग५. दक्षता विभाग | D97: 0 | E97: 0 | F97: 0 | G97: 0 | H97: 0
A98: १. कायम सेवकवर्ग वेतन | B98: RE11C151 | D98: 10884531 | E98: 9473049 | F98: 9733412 | G98: 12500000 | H98: 12000000
A99: २. संकीर्ण | B99: RE11C152 | D99: 0 | E99: 79462 | F99: 49286 | G99: 180000 | H99: 200000
A100: ग५. दक्षता विभाग बेरीज | D100: 10884531 | E100: 9552511 | F100: 9782698 | G100: 12680000 | H100: 12200000
D101: 0 | E101: 0 | F101: 0 | G101: 0 | H101: 0
A102: ग१+ग२+ग३+ग४+ग५ एकूण बेरीज | D102: 79978475 | E102: 81186631 | F102: 83643855 | G102: 103280000 | H102: 101650000
D103: 0 | E103: 0 | F103: 0 | G103: 0 | H103: 0
A104: घ१. उपआयुक्त (विशेष) यांचे कार्यालय | D104: 0 | E104: 0 | F104: 0 | G104: 0 | H104: 0
A105: १. उपआयुक्त (विशेष) (मुं. प्रां. मनपा अधिनियम, कलम ४५(३) प्रमाणे) यांचे वेतन | B105: RE11D101A | D105: 0 | E105: 0 | F105: 1171262 | G105: 2500000 | H105: 2300000
A106: २. कायम सेवकवर्ग वेतन | B106: RE11D102A | D106: 7388195 | E106: 8214909 | F106: 7634116 | G106: 8500000 | H106: 9500000
A107: ३. संकीर्ण | B107: RE11D103 | D107: 37222 | E107: 31644 | F107: 38712 | G107: 135000 | H107: 100000
D108: 0 | E108: 0 | F108: 0 | G108: 0 | H108: 0
A109: घ१. उपआयुक्त (विशेष) कार्यालय बेरीज | D109: 7425417 | E109: 8246553 | F109: 8844090 | G109: 11135000 | H109: 11900000
A110: घ२. सेवकवर्ग विभाग | D110: 0 | E110: 0 | F110: 0 | G110: 0 | H110: 0
A111: १. कायम सेवकवर्ग वेतन | B111: RE11D126A | D111: 28475728 | E111: 30921722 | F111: 32741529 | G111: 34500000 | H111: 36000000
A112: २. संकीर्ण | B112: RE11D127 | D112: 281198 | E112: 214222 | F112: 82917 | G112: 540000 | H112: 400000
A113: ४. विविध रिक्त पदे भरण्यासाठी आयोजित करण्यात येणार्‍या परीक्षांसाठी खर्च | B113: RE11D127B- | D113: 841876 | E113: 0 | F113: 0 | G113: 0 | H113: 0
A114: ५. प्रशिक्षण प्रबोधिनीसाठी फर्निचर व तद्‌नुषंगिक कामे करणे व साहित्य घेणे | B114: RE11D127C | D114: 0 | E114: 55555 | F114: 0 | G114: 792000 | H114: 500000
A115: ६. अधिकारी / कर्मचार्‍यांसाठी प्रशिक्षण आयोजन करणेसाठी खर्च | B115: RE11D127D | D115: 81944 | E115: 138226 | F115: 31555 | G115: 2376000 | H115: 1500000
A116: ७. पुणे मनपामध्ये बायोमॅट्रिक अटेंडन्स प्रणाली कार्यान्वीत करणे | B116: RE11D127E | D116: 456000 | E116: 0 | F116: 0 | G116: 3600000 | H116: 500000
A117: ८. सेवकवर्ग विभागासाठी फर्निचर करणे | B117: RE11D127F | D117: 8024 | E117: 0 | F117: 0 | G117: 720000 | H117: 500000
A118: समाविष्ट गावांतील सेवकांच्या वेतनासाठी | B118: RE11D127H | D118: 0 | E118: 66257402 | F118: 106962499 | G118: 16600000 | H118: 0
A119: शताब्दी वर्षानिमित्त श्री शिवाजी मराठा सोसायटी, पुणे यांना देणगी (देणगी विभाग) | B119: RE11D127J | D119: 0 | E119: 0 | F119: 0 | G119: 5000000 | H119: 0
A120: मनपा पदाधिकारी, अधिकारी, नगरसेवक, कर्मचारी यांना प्रशिक्षणासाठी वसंतराव भागवत प्रबोधिनी स्थापन करणे. | B120: RE11D127K | D120: 0 | E120: 299000 | F120: 0 | G120: 4000000 | H120: 0
A121: पत्रकार डी.आर.कुलकर्णी गृहनिर्माण संस्था प्रशिक्षण | B121: RE11D127L | D121: 0 | E121: 0 | F121: 0 | G121: 0 | H121: 10000000
D122: 0 | E122: 0 | F122: 0 | G122: 0 | H122: 0
A123: घ२. सेवकवर्ग विभाग बेरीज | D123: 30144770 | E123: 97886127 | F123: 139818500 | G123: 68128000 | H123: 49400000
D124: 0 | E124: 0 | F124: 0 | G124: 0 | H124: 0
A125: घ२अ. सेवाभरती व परीक्षा नियंत्रण विभाग | D125: 0 | E125: 0 | F125: 0 | G125: 0 | H125: 0
A126: १. कायम सेवकवर्ग वेतन | B126: RE11D151 | D126: 0 | E126: 0 | F126: 0 | G126: 2500000 | H126: 0
A127: 3. विविध रिक्त पदे भरण्यासाठी आयोजित करण्यात येणार्‍या परीक्षांसाठी खर्च | B127: RE11D153 | D127: 0 | E127: 0 | F127: 0 | G127: 2376000 | H127: 2000000
D128: 0 | E128: 0 | F128: 0 | G128: 0 | H128: 0
A129: घ२अ. सेवाभरती व परीक्षा नियंत्रण विभाग बेरीज | D129: 0 | E129: 0 | F129: 0 | G129: 4876000 | H129: 2000000
D130: 0 | E130: 0 | F130: 0 | G130: 0 | H130: 0
A131: घ२ब. मागासवर्ग विभाग | D131: 0 | E131: 0 | F131: 0 | G131: 0 | H131: 0
A132: १. कायम सेवकवर्ग वेतन | B132: RE11D161 | D132: 0 | E132: 0 | F132: 220446 | G132: 500000 | H132: 500000
D133: 0 | E133: 0 | F133: 0 | G133: 0 | H133: 0
A134: घ२ब. मागासवर्ग विभाग बेरीज | D134: 0 | E134: 0 | F134: 220446 | G134: 500000 | H134: 500000
...

Sheet A_Capital_Expenditure
H1: खर्चाबाबतचे अंदाजपत्रक
A2: मान्यतेचा ठराव क्र. दिनांक (Code) | B2: प्रभाग क्रमांक | C2: BPL | D2: कामाचे नाव अगर वर्णन | E2: दि. 31 मार्च 2021 अखेरपर्यंत केलेली तरतूद | H2: दि. 31 मार्च 2020 पर्यंतचा खर्चाचा नक्‍की आकडा | I2: 2020-21 मधील खर्चाची अंदाजी रक्कम | K2: 2021-22 साठी अधिक तरतूद | M2: 2021-22 साठी एकूण तरतूद | N2: प्रकल्पीय रक्कम
E3: कर्जातून | F3: महसूल निधीतून | G3: एकूण | I3: प्रत्यक्ष उपलब्ध तरतूद | J3: कर्जातून तरतूद | K3: कर्जातून | L3: महसूल निधी व इतर निधी
D8: १. मनपा भवन व मनपा इमारती | E8: 0 | F8: 0 | G8: 0 | H8: 0 | I8: 0 | L8: 0 | M8: 0
A9: CE11A129# | B9: J1- | C9: SJ1- | D9: शहरात विविध ठिकाणी मनपासाठी इमारती बांधणे व विकास कामे करणे | E9: 0 | F9: 823472243 | G9: 823472243 | H9: 631004899 | I9: 192467344 | L9: 198670000 | M9: 198670000
E10: 0 | F10: 0 | G10: 0 | H10: 0 | I10: 0 | L10: 0 | M10: 0
D11: १. मनपा भवन व मनपा इमारती एकूण बेरीज | E11: 0 | F11: 823472243 | G11: 823472243 | H11: 631004899 | I11: 192467344 | L11: 198670000 | M11: 198670000
E12: 0 | F12: 0 | G12: 0 | H12: 0 | I12: 0 | L12: 0 | M12: 0
D13: २. प्राथमिक शिक्षण | E13: 0 | F13: 0 | G13: 0 | H13: 0 | I13: 0 | L13: 0 | M13: 0
A14: CE12A381# | B14: _ | C14: _ | D14: प्राथमिक शाळेमध्ये मुलभूत सोयी सुविधांसाठी विविध विकासकामे करणे | E14: 0 | F14: 1370733043 | G14: 1370733043 | H14: 1301502862 | I14: 69230181 | L14: 0 | M14: 0
A15: CE12A422# | B15: J2- | C15: SJ2- | D15: प्राथमिक शाळेसाठी नवीन इमारत बांधणे / वर्गखोल्या बांधणे / मैदाने विकसित करणे व मुलभूत सोयी सुविधांसाठी विविध विकासकामे करणे | E15: 0 | F15: 1522133579 | G15: 1522133579 | H15: 749217804 | I15: 772915775 | L15: 237150000 | M15: 237150000
E16: 0 | F16: 0 | G16: 0 | H16: 0 | I16: 0 | L16: 0 | M16: 0
C17: B | D17: २. प्राथमिक शिक्षण एकूण बेरीज | E17: 0 | F17: 2952307439 | G17: 2952307439 | H17: 2110161483 | I17: 842145956 | L17: 237150000 | M17: 237150000
E18: 0 | F18: 0 | G18: 0 | H18: 0 | I18: 0 | L18: 0 | M18: 0
D19: ३. दुय्यम शिक्षण | E19: 0 | F19: 0 | G19: 0 | H19: 0 | I19: 0 | L19: 0 | M19: 0
A20: CE13A128# | B20: J5- | D20: माध्यमिक शाळांमध्ये मुलभूत सोयी सुविधांसाठी विविध विकासकामे करणे | E20: 0 | F20: 72785069 | G20: 72785069 | H20: 52979572 | I20: 19805497 | L20: 235600000 | M20: 235600000
E21: 0 | F21: 0 | G21: 0 | H21: 0 | I21: 0 | L21: 0 | M21: 0
C22: B | D22: ३. दुय्यम शिक्षण एकूण बेरीज | E22: 0 | F22: 72785069 | G22: 72785069 | H22: 52979572 | I22: 19805497 | L22: 235600000 | M22: 235600000
E23: 0 | F23: 0 | G23: 0 | H23: 0 | I23: 0 | L23: 0 | M23: 0
D24: ७. आरोग्य विभाग | E24: 0 | F24: 0 | G24: 0 | H24: 0 | I24: 0 | L24: 0 | M24: 0
A25: CE17A192# | B25: _ | C25: _ | D25: दवाखान्यातील मुलभूत सोयी सुविधांसाठी विविध विकासकामे करणे | E25: 0 | F25: 601866405 | G25: 601866405 | H25: 583746804 | I25: 18119601 | L25: 0 | M25: 0
A26: CE17A227# | B26: J12- | C26: SJ12 | D26: शहरामध्ये विविध ठिकाणी स्मशानभूमी / दफनभूमी विकसित करणे / दशक्रीया विधीसाठी घाट बांधणे व विविध विकासकामे करणे | E26: 0 | F26: 856012672 | G26: 856012672 | H26: 554940123 | I26: 301072549 | L26: 211850000 | M26: 211850000
A27: CE17A242# | B27: J6- | C27: SJ6- | D27: शहरामध्ये दवाखाने / प्रसुतिगृह बांधणे / दवाखान्यांसाठी विविध उपकरणे खरेदी करणे / दवाखान्यातील मुलभूत सोयी सुविधांसाठी विविध विकासकामे करणे | E27: 0 | F27: 1498602728 | G27: 1498602728 | H27: 392314381 | I27: 1106288347 | L27: 2195800000 | M27: 2195800000
A28: CE17A244# | B28: _ | C28: _ | D28: शहरातील दवाखान्यांसाठी विविध उपकरणे खरेदी करणे | E28: 0 | F28: 153267558 | G28: 153267558 | H28: 153267558 | I28: 0 | L28: 0 | M28: 0
E29: 0 | F29: 0 | G29: 0 | H29: 0 | I29: 0 | L29: 0 | M29: 0
C30: B | D30: ७. आरोग्य विभाग एकूण बेरीज | E30: 0 | F30: 3137796501 | G30: 3137796501 | H30: 1712316004 | I30: 1425480497 | L30: 2407650000 | M30: 2407650000
E31: 0 | F31: 0 | G31: 0 | H31: 0 | I31: 0 | L31: 0 | M31: 0
D32: ९. पथांची झाडलोट / घनकचरा व्यवस्थापन विभाग | E32: 0 | F32: 0 | G32: 0 | H32: 0 | I32: 0 | L32: 0 | M32: 0
A33: CE19A116 | D33: उरूळी देवाची/फुरसंगी डेपो परिसर कचरा डेपोवरील उर्वरित कचर्‍याचे नॉर्म्सप्रमाणे कॅपिंग करणे व तद्‌नुषंगिक कामे करणे | E33: 0 | F33: 824356400 | G33: 824356400 | H33: 805338528 | I33: 19017872 | L33: 14000000 | M33: 14000000
A34: CE19A117 | D34: उरुळी देवाची/फुरसुंगी येथील कचरा डेपोच्या भोवती सिमाभिंत बांधणे. | E34: 0 | F34: 55129374 | G34: 55129374 | H34: 48089046 | I34: 7040328 | L34: 4900000 | M34: 4900000
A35: CE19A120 | D35: व्हर्मीकंपोस्ट पध्दतीचे प्रक्रिया प्रकल्प उभारणे. | E35: 0 | F35: 153449062 | G35: 153449062 | H35: 153449062 | I35: 0 | L35: 0 | M35: 0
A36: CE19A122 | D36: कचरा प्रक्रिया प्रकल्पासाठी जागा ताब्यात घेणे, कंपाउंड करणे, रस्ते करणे व तदनुषंगिक कामे करणे. | E36: 0 | F36: 74597347 | G36: 74597347 | H36: 61347347 | I36: 13250000 | L36: 7000000 | M36: 7000000
A37: CE19A123 | D37: ताब्यात येणार्‍या जागांवर प्रक्रिया प्रकल्प उभारणे, प्रकल्पांसाठी आवश्यक सुविधा विषयक कामे करणे इत्यादी. | E37: 0 | F37: 255507493 | G37: 255507493 | H37: 187680442 | I37: 67827051 | L37: 70000000 | M37: 70000000
A38: CE19A139 | D38: उरुळी देवाची/फुरसंगी येथील गावांमध्ये विविध विकास कामे करणे | E38: 0 | F38: 518477745 | G38: 518477745 | H38: 505228418 | I38: 13249327 | L38: 7000000 | M38: 7000000
A39: CE19A141 | D39: घनकचरा व्यवस्थापनकडील कचरागाडया, बंदिस्त करणे विविध रॅम्प बंदिस्त करणे व कॉक्रीट करणे. | E39: 0 | F39: 126136555 | G39: 126136555 | H39: 115427594 | I39: 10708961 | L39: 7000000 | M39: 7000000
A40: CE19A143 | D40: गार्डन वेस्टसाठी विविध ठिकाणी पुणे मनपा हद्दीत श्रेडर मशिन बसविणे | E40: 0 | F40: 7622213 | G40: 7622213 | H40: 4943903 | I40: 2678310 | L40: 1050000 | M40: 1050000
A41: CE19A153 | D41: प्लास्टिक व इलेक्ट्रॉनिक वस्तू विभाजीत करणेकरीता शेड बांधणे | E41: 0 | F41: 20028393 | G41: 20028393 | H41: 16028393 | I41: 4000000 | L41: 3500000 | M41: 3500000
A42: CE19A154# | C42: SH1- | D42: शहरात घनकचरा संदर्भात विविध विकास कामे करणे | E42: 0 | F42: 331176807 | G42: 331176807 | H42: 250178553 | I42: 80998254 | L42: 359000000 | M42: 359000000
A43: CE19A155 | D43: e-waste जमा करणे व प्रक्रिया करणे | E43: 0 | F43: 4850000 | G43: 4850000 | H43: 850000 | I43: 4000000 | L43: 3500000 | M43: 3500000
A44: CE19A156 | D44: कचरा वाहतुकीसाठी नव्याने उपनगरांमध्ये रॅम्पचे आधुनिकीकरण, विकासकामे करणे, यंत्रसामग्री | E44: 0 | F44: 87192150 | G44: 87192150 | H44: 52004216 | I44: 35187934 | L44: 28000000 | M44: 28000000
A45: CE19A157 | D45: उरळी देवाची / फुरसुंगी येथे इनर्ट / रिजेक्ट मटेरीयलसाठी नव्याने शास्त्रोक्त लॅण्डफील विकसीत करणे व त्याची देखभाल दुरुस्ती करणे | E45: 0 | F45: 255323460 | G45: 255323460 | H45: 183323460 | I45: 72000000 | L45: 77000000 | M45: 77000000
A46: CE19A158 | D46: पुणे महानगरपालिकाच्या नव्याने समाविष्ट होणाऱ्या गावामध्ये घनकचरा व्यवस्थापनाशी संबधीत कामे करणे | E46: 0 | F46: 38558063 | G46: 38558063 | H46: 15305818 | I46: 23252245 | L46: 14000000 | M46: 14000000
A47: CE19A163 | D47: घनकचरा व्यवस्थापनाअंतर्गत विकेंद्रीत पध्दतीने प्रभाग व वॉर्डनिहाय कचरा प्रकिया केंद्र उभारणे व तद्‌नुषंगिक कामे करणे | E47: 0 | F47: 419884540 | G47: 419884540 | H47: 332026101 | I47: 87858439 | L47: 105000000 | M47: 105000000
A48: CE19A168 | D48: पुणे मनपाच्या अस्तित्वातील कचरा हस्तांतर केंद्र व हजेरीकोठ्‌या व विविध प्रकल्प याठिकाणी सेवकांसाठी सुविधा पुरविणे व बांधकामासाठी देखभाल दुरूस्ती करणे | E48: 0 | F48: 25296246 | G48: 25296246 | H48: 9568891 | I48: 15727355 | L48: 7000000 | M48: 7000000
A49: CE19A169 | D49: स्वच्छ भारत अभियान अंतर्गत मनपाचा हिस्सा | E49: 0 | F49: 210833994 | G49: 210833994 | H49: 206833993 | I49: 4000001 | L49: 700000 | M49: 700000
A50: CE19A171 | D50: समग्रसाठी मनपाचा हिस्सा | E50: 0 | F50: 16177027 | G50: 16177027 | H50: 16177027 | I50: 0 | L50: 0 | M50: 0
A51: CE19A173 | D51: सार्वजनीक स्वच्छतागृह बांधणे | E51: 0 | F51: 50316137 | G51: 50316137 | H51: 36890495 | I51: 13425642 | L51: 7000000 | M51: 7000000
A52: CE19A174 | D52: e-toilet करणे, जुन्या बसचे स्वच्छतागृहामध्ये रूपांतर करणे | E52: 0 | F52: 4000851 | G52: 4000851 | H52: 4000851 | I52: 0 | L52: 0 | M52: 0
A53: CE19A178 | D53: उरूळी देवाची/फुरसंगी डेपो येथील साठलेल्या कचऱ्यावर बायोमायनिंग प्रक्रिया करणे | E53: 0 | F53: 222600605 | G53: 222600605 | H53: 118564507 | I53: 104036098 | L53: 164500000 | M53: 164500000
A54: CE19A179 | D54: उरूळी देवाची/फुरसंगी डेपो येथील साठलेल्या कचऱ्यावर बायोमायनिंग प्रक्रिया करण्यासाठीच्या ठिकाणी रस्ता करणे, R.O. Plant बसविणे | E54: 0 | F54: 50479313 | G54: 50479313 | H54: 29754250 | I54: 20725063 | L54: 22400000 | M54: 22400000
... A65: CE19A191 | D65: Pune Cantonment Board येथे दैनंदिन 100 मे. टन कचऱ्यावर प्रक्रिया करणेसाठी प्रकल्प क्षमता वाढ, SLF व आधुनिकीकरण असा संयुक्त प्रकल्प | E65: 0 | F65: 0 | G65: 0 | H65: 0 | I65: 0 | L65: 70000000 | M65: 70000000
E66: 0 | F66: 0 | G66: 0 | H66: 0 | I66: 0 | L66: 0 | M66: 0
D67: ९. पथांची झाडलोट / घनकचरा व्यवस्थापन विभाग एकूण बेरीज | E67: 0 | F67: 4584632357 | G67: 4584632357 | H67: 3259378442 | I67: 1325253915 | L67: 1380650000 | M67: 1380650000
E68: 0 | F68: 0 | G68: 0 | H68: 0 | I68: 0 | L68: 0 | M68: 0
D69: १०क. पथ सुधारणा विभाग | E69: 0 | F69: 0 | G69: 0 | H69: 0 | I69: 0 | L69: 0 | M69: 0
A70: CE20A102# | B70: A2- | C70: SA2- | D70: शहरामधील रस्ते विकसित करणे आणि डांबरीकरण करणे | E70: 11538000 | F70: 11338645116 | G70: 11350183116 | H70: 7853839714 | I70: 3496343402 | L70: 5211950000 | M70: 5211950000
A71: CE20A103# | B71: A13- | C71: SA13 | D71: Pedestrian Policy नुसार शहरातील फूटपाथ विकसित करणे | E71: 0 | F71: 3559721409 | G71: 3559721409 | H71: 2776354995 | I71: 783366414 | L71: 653273000 | M71: 653273000
A72: CE20A104# | B72: _ | C72: _ | D72: शहरात पेव्हिंग ब्लॉक, इंटरलॉकिंग ब्लॉक बसविणे | E72: 0 | F72: 286422135 | G72: 286422135 | H72: 226512603 | I72: 59909532 | L72: 0 | M72: 0
A73: CE20A884# | B73: A10- | C73: SA10 | D73: शहरात विविध विकासाची कामे करणे | E73: 0 | F73: 2298703118 | G73: 2298703118 | H73: 1489770240 | I73: 808932878 | L73: 217430000 | M73: 217430000
A74: CE20A1248# | B74: A5- | D74: शहरातील प्रमुख डी.पी. रस्त्यांचे भूसंपादन करणे | E74: 0 | F74: 0 | G74: 0 | H74: 0 | I74: 0 | L74: 175000000 | M74: 175000000
A75: CE20A1249# | B75: A6- | C75: _ | D75: शहरामधील रस्ते विकसित करणे | E75: 0 | F75: 7948830451 | G75: 7948830451 | H75: 2185604505 | I75: 5763225946 | L75: 1222921000 | M75: 1222921000
A76: CE20A1250# | B76: _ | C76: _ | D76: पुणे शहरात CMP आराखड्यानुसार (PPP / Development TDR / Deffered payment / Premium charges) अन्वये प्रशासकीय मुल्यमापनानुसार प्रत्यक्ष अंमलबजावणी करून कामे करणे | E76: 0 | F76: 310594176 | G76: 310594176 | H76: 310594176 | I76: 0 | L76: 0 | M76: 0
A77: CE20A1259# | B77: A9- | D77: शहरातील रस्ते पुनर्डांबरीकरण करणे | E77: 0 | F77: 1405832228 | G77: 1405832228 | H77: 805228150 | I77: 600604078 | L77: 672126000 | M77: 672126000
A78: CE20A1262# | B78: A15- | C78: SA15 | D78: शहरातील रस्ते काँक्रीटने विकसित करणे | E78: 0 | F78: 5385287330 | G78: 5385287330 | H78: 3796718452 | I78: 1588568878 | L78: 936120000 | M78: 936120000
A79: CE20A1263# | B79: A16- | C79: _ | D79: शहरामध्ये BRT मार्ग विकसित करणे | E79: 0 | F79: 2302487133 | G79: 2302487133 | H79: 2110407726 | I79: 192079407 | L79: 42000000 | M79: 42000000
A80: CE20A1264# | B80: A17- | D80: शहरामध्ये सायकल ट्रॅक विकसित करणे | E80: 0 | F80: 238495593 | G80: 238495593 | H80: 126914065 | I80: 111581528 | L80: 57000000 | M80: 57000000
A81: CE20A1266# | B81: A18- | D81: नविन समाविष्ट गावांमध्ये रस्ते विकसित करणे | E81: 0 | F81: 490506049 | G81: 490506049 | H81: 231770360 | I81: 258735689 | L81: 53200000 | M81: 53200000
E82: 0 | F82: 0 | G82: 0 | H82: 0 | I82: 0 | L82: 0 | M82: 0
D83: १०क. पथ सुधारणा विभाग एकूण बेरीज | E83: 11538000 | F83: 35565524738 | G83: 35577062738 | H83: 21913714986 | I83: 13663347752 | L83: 9241020000 | M83: 9241020000
E84: 0 | F84: 0 | G84: 0 | H84: 0 | I84: 0 | L84: 0 | M84: 0
E85: 0 | F85: 0 | G85: 0 | H85: 0 | I85: 0 | L85: 0 | M85: 0
D86: १०ख. वाहतूक नियंत्रण विभाग | E86: 0 | F86: 0 | G86: 0 | H86: 0 | I86: 0 | L86: 0 | M86: 0
A87: CE20B101# | B87: _ | C87: _ | D87: शहरामधील चौकांची सुधारणा / विकासकामे करणे | E87: 0 | F87: 663958501 | G87: 663958501 | H87: 258329522 | I87: 405628979 | L87: 0 | M87: 0
A88: CE20B102# | B88: T2- | C88: ST2- | D88: शहरामधील चौकांची सुधारणा / विकासकामे करणे, वाहतूक सुधारण्यासाठी विविध विकास कामे करणे | E88: 0 | F88: 5044532484 | G88: 5044532484 | H88: 2712369161 | I88: 2332163323 | L88: 1875700000 | M88: 1875700000
A89: CE20B107# | B89: _ | D89: रस्त्यांवरील टी जंक्शनचा विकास व सुधारणा व वाहनतळ निर्माण करणे | E89: 0 | F89: 60384542 | G89: 60384542 | H89: 46384542 | I89: 14000000 | L89: 0 | M89: 0
A90: CE20B108# | B90: _ | C90: ST7- | D90: शहरातील वाहनतळांचा जागा विकसित करणे / वाहनतळ निर्माण करणे | E90: 0 | F90: 908499575 | G90: 908499575 | H90: 103822869 | I90: 804676706 | L90: 19000000 | M90: 19000000
A91: CE20B251 | B91: G | C91: P | D91: पुणे शहरातील रिक्षांना CNG Kit बसविणेसाठी अनुदान देणे | E91: 0 | F91: 112136941 | G91: 112136941 | H91: 95760941 | I91: 16376000 | L91: 0 | M91: 0
E92: 0 | F92: 0 | G92: 0 | H92: 0 | I92: 0 | L92: 0 | M92: 0
D93: १०ख. वाहतूक नियंत्रण विभाग एकूण बेरीज | E93: 0 | F93: 6790327184 | G93: 6790327184 | H93: 3217482176 | I93: 3572845008 | L93: 1894700000 | M93: 1894700000
E94: 0 | F94: 0 | G94: 0 | H94: 0 | I94: 0 | L94: 0 | M94: 0
E95: 0 | F95: 0 | G95: 0 | H95: 0 | I95: 0 | L95: 0 | M95: 0
D96: १०ग. विद्युत विभाग | E96: 0 | F96: 0 | G96: 0 | H96: 0 | I96: 0 | L96: 0 | M96: 0
A97: CE20C352# | B97: B5- | C97: SB5- | D97: शहरातील विविध ठिकाणी प्रकाश व्यवस्था करणे | E97: 0 | F97: 6337878164 | G97: 6337878164 | H97: 5143400215 | I97: 1194477949 | L97: 891400000 | M97: 891400000
A98: CE20C550# | B98: _ | C98: SB7- | D98: शहरामध्ये भूमिगत केबल टाकणे | E98: 0 | F98: 913663224 | G98: 913663224 | H98: 616424655 | I98: 297238569 | L98: 145000000 | M98: 145000000
A99: CE20C551# | B99: B8- | C99: _ | D99: शहरामधील विविध भवनांमध्ये विद्युतविषयक कामे करणे | E99: 0 | F99: 213878621 | G99: 213878621 | H99: 165158621 | I99: 48720000 | L99: 15120000 | M99: 15120000
E100: 0 | F100: 0 | G100: 0 | H100: 0 | I100: 0 | L100: 0 | M100: 0
D101: १०ग. विद्युत विभाग एकूण बेरीज | E101: 0 | F101: 7465420009 | G101: 7465420009 | H101: 5924983491 | I101: 1540436518 | L101: 1051520000 | M101: 1051520000
E102: 0 | F102: 0 | G102: 0 | H102: 0 | I102: 0 | L102: 0 | M102: 0
D103: १०घ. पूल व नदी सुधारणा (विकास योजना) | E103: 0 | F103: 0 | G103: 0 | H103: 0 | I103: 0 | L103: 0 | M103: 0
A104: CE20D170# | B104: L1- | C104: SL1- | D104: शहरात विविध ठिकाणी पूल बांधणे / उड्डाणपूल बांधणे / भुयारी मार्ग करणे | E104: 0 | F104: 4224486989 | G104: 4224486989 | H104: 901068252 | I104: 3323418737 | L104: 1262800000 | M104: 1262800000
A105: CE20D219# | B105: L2- | C105: _ | D105: शहरातील नदी सुधारणा कामे करणे व तद्‌नुषंगिक कामे करणे | E105: 0 | F105: 227869568 | G105: 227869568 | H105: 70321033 | I105: 157548535 | L105: 1.05e+09 | M105: 1.05e+09
E106: 0 | F106: 0 | G106: 0 | H106: 0 | I106: 0 | L106: 0 | M106: 0
D107: १०घ. पूल व नदी सुधारणा (विकास योजना) एकूण बेरीज | E107: 0 | F107: 4452356557 | G107: 4452356557 | H107: 971389285 | I107: 3480967272 | L107: 2312800000 | M107: 2312800000
E108: 0 | F108: 0 | G108: 0 | H108: 0 | I108: 0 | L108: 0 | M108: 0
D109: १०च. स्ट्रॉम वॉटर ड्रेन प्रकल्प | E109: 0 | F109: 0 | G109: 0 | H109: 0 | I109: 0 | L109: 0 | M109: 0
A110: CE20E101# | B110: F1- | C110: SF1- | D110: पुणे शहरातील पावसाळी पाण्याच्या व्यवस्थापनासाठी नाला सुधारणा कामे, कल्व्हर्टस व पावसाळी लाईन टाकणे | E110: 0 | F110: 4875332848 | G110: 4875332848 | H110: 4339956303 | I110: 535376545 | L110: 1164500000 | M110: 1164500000
E111: 0 | F111: 0 | G111: 0 | H111: 0 | I111: 0 | L111: 0 | M111: 0
D112: १०च. स्ट्रॉम वॉटर ड्रेन प्रकल्प एकूण बेरीज | E112: 0 | F112: 4875332848 | G112: 4875332848 | H112: 4339956303 | I112: 535376545 | L112: 1164500000 | M112: 1164500000
E113: 0 | F113: 0 | G113: 0 | H113: 0 | I113: 0 | L113: 0 | M113: 0
D114: १२. भवने, भूमी व मनपा वसाहती यांची व्यवस्था | E114: 0 | F114: 0 | G114: 0 | H114: 0 | I114: 0 | L114: 0 | M114: 0
...

Sheet A_Land_Acquisition
A1: सन 2021-22 चे अंदाजपत्रक - खास निधीतून करावयाची योजनांतर्गत कामे
A2: अनुक्रमांक | C2: कामाचे नाव | D2: मान्य अंदाज 2020-21 | E2: नवीन अंदाज 2021-22
A7: (अ) | C7: भूमी संपादन निधीतून करावयाचा खर्च | D7: 0 | E7: 0
D8: 0 | E8: 0
A9: 1 | B9: FE11A101 | C9: भूमी संपादन विशेष अधिकारी यांचा कार्यालयीन खर्च - | D9: 16000000 | E9: 14000000
A10: 2 | C10: कोर्टाच्या निकालानुसार वाढीव नुकसानभरपाई कोर्ट खर्च, वकील फी, जॉइन्ट जज्ज यांचा खर्च वगैरे | D10: 0 | E10: 0
A11: 3 | C11: भूमी संपादन अधिनियमात नव्याने केलेल्या दुरुस्तीमुळे यापूर्वी जाहीर झालेल्या योजनापोटी ावयाच्या वाढीव रकमेचा खर्च | D11: 0 | E11: 0
A12: 4 | C12: परचेस नोटीसांमुळे (नवीन) पाठवावयाच्या भूमी संपादन योजनांसाठी तरतूद | D12: 0 | E12: 0
A13: 5 | C13: ताब्यात घेतलेल्या मिळकती पाडणे, ड्रेनेज, वॉटर, इलेक्ट्रीक टेलिफोन वगैरे कनेक्शन्स हलविणे, जोडणे व इतर तद्‌नुषंगिक कामे करणे. | D13: 0 | E13: 0
A14: 6 | C14: कार्यालयीन कामासाठी साधने, डेडस्टॉक वस्तू खरेदी करणे, हत्यारे खरेदी करणे, कार्यालय व कोठीची दुरुस्ती करणे, आवश्यक सुधारणा करणे, प्रकटन खर्च, प्रवास खर्च वगैर | D14: 0 | E14: 0
A15: 7 | C15: मुंबई प्रांतिक मनपा अधिनियम १९४९ च्या कलम २१३ अन्वये रस्तारूंदीसाठी ताब्यात घेतलेल्या मोकळ्या जागा व त्याप्रित्यर्थ ावयाची नुकसानभरपाईची रक्कम | D15: 0 | E15: 0
A16: 8 | C16: इतर योजनांमधील मोजणी फी व इतर तद्‌नुषंगिक रक्कम | D16: 0 | E16: 0
A17: 9 | C17: भूमी संपादन अधिकारी ह्यांचेकडील खालील नमूद केलेल्या ज्या जागांचे निवाडे जाहीर करतील त्यासाठी रक्कम | D17: 0 | E17: 0
A18: 10 | C18: संगणक दुरूस्ती व आवश्यक साहित्य | D18: 0 | E18: 0
D19: 0 | E19: 0
C20: (अ) बेरीज | D20: 16000000 | E20: 14000000
D21: 0 | E21: 0
D22: 0 | E22: 0
B23: FE11A102 | C23: भूसंपादनासाठी आवश्यक जागांची यादी :- | D23: 224000000 | E23: 161000000
D24: 0 | E24: 0
C25: सी.वाय.जी अंतर्गत रस्ते : | D25: 0 | E25: 0
C26: बाणेर मुख्य रस्ता २६१ ते १०५ | D26: 0 | E26: 0
C27: बाणेर स.क्र. १३३ ते बालेवाडी स.क्र. १० बालेवाडीकडे जाणारा रस्ता मुख्य रस्ता (बालेवाडी) | D27: 0 | E27: 0
C28: बालेवाडी स.क्र. ३४, ३५ जी१ गार्डनचे आरक्षण | D28: 0 | E28: 0
C29: बाणेर स.क्र. २८, २९० जी२ गार्डनचे आरक्षण व बाणेर स.क्र. ३५ जी३ गार्डनचे आरक्षण | D29: 0 | E29: 0
C30: कल्याणीनगर जंक्शन ते आळंदी रोड | D30: 0 | E30: 0
C31: बाणेर स.क्र. १०५, १०६, ११०, १११ पीएमटी१ | D31: 0 | E31: 0
C32: बाणेर स.क्र. ३३ पी.३ | D32: 0 | E32: 0
C33: बाणेर स.क्र. १०० पी.४ | D33: 0 | E33: 0
C34: बाणेर स.क्र. १७४ पी.४ | D34: 0 | E34: 0
C35: बाणेर स.क्र. ७९ पी.६ | D35: 0 | E35: 0
C36: बाणेर स.क्र. १०५, १०६ पी.७ पार्किंगचे आरक्षण | D36: 0 | E36: 0
... C42: एअरपोर्ट रोड ते डेक्कन कॉलेज व्हाया हॉटमिक्स प्लँट | D42: 0 | E42: 0
D43: 0 | E43: 0
C44: जेएनएनयुआरएम / बीआरटी अंतर्गत रस्ते : | D44: 0 | E44: 0
C45: बाणेर स.क्र. १०७, १०८ व ११० मधून जाणारा १८ मी. रस्ता. | D45: 0 | E45: 0
C46: मौजे खराडी ता. हवेली, संगमवाडी ते खराडी २४ मी. नदीकाठचा डी.पी. रस्ता | D46: 0 | E46: 0
C47: मौजे वडगांव शेरी ता. हवेली, संगमवाडी ते खराडी २४ मी. नदीकाठचा डी.पी. रस्ता | D47: 0 | E47: 0
C48: सिंहगड रस्ता महानगरपालिका हद्द दरम्यान नियोजनाते विकसीत करणे (वडगांव बुद्रुक) | D48: 0 | E48: 0
C49: सिंहगड रस्ता महानगरपालिका हद्द दरम्यान नियोजनाते विकसीत करणे (वडगांव खुर्द) | D49: 0 | E49: 0
C50: विश्रांतवाडी ते धानोरी | D50: 0 | E50: 0
C51: संचेती हॉस्पिटल ते गव्हर्नमेंट पोल्ट्री फार्म | D51: 0 | E51: 0
C52: पुणे स्टेशन ते मनपा रोड (कॅनॉट रोड) | D52: 0 | E52: 0
D53: 0 | E53: 0
C54: आरआरडीपी अंतर्गत रस्ते : | D54: 0 | E54: 0
C55: मुळा नदिवरील पिंपळे निलेख यांना जोडणारा पुल रस्त्याचे भुसंपाद (बाणेर) | D55: 0 | E55: 0
C56: सुतारवाडी रस्ता २४ मी. (जुना) | D56: 0 | E56: 0
C57: कोथरूड एकलव्य कॉलेज ते हायवेपर्यंत मुख्य रस्ता (१५ मी. नवीन) | D57: 0 | E57: 0
C58: कोथरूड महात्मा सोसायटी एकलव्य कॉलेज ते हायवे परिसरातील डी.पी. रस्ते (१५ मी.) व ( १८ मी.) | D58: 0 | E58: 0
C59: बालभारती ते पौड फाटा रस्ता | D59: 0 | E59: 0
C60: वारजे जकातनाका ते नवीन अहिरे हद्द एन.डी.ए. रोड जुना जकातनाका ते हायवे व वारजे माळवाडी टेकडीपर्यंत | D60: 0 | E60: 0
C61: जे.पी. नाईक इन्स्टिटयुट ते गणंजय सोसायटी | D61: 0 | E61: 0
C62: अलंकार पोलीस चौकी गिरीजा शंकर सोसायटी पश्चिमानगरी ते नाईक पूल डी.पी. रस्ता | D62: 0 | E62: 0
C63: चांदणी चौक ते सुस चौक | D63: 0 | E63: 0
C64: सिंहगड रोड दोन्ही कॅनॉलवरील प्रस्तावित पुलासह (वडगांव बुद्रुक) | D64: 0 | E64: 0
C65: सुस रस्ता ते बाणेर रस्ता रामनदी कडेचा रस्ता (बाणेर) | D65: 0 | E65: 0
... C67: सुस रस्ता ते बाणेर रस्ता रामनदी कडेचा रस्ता या रस्त्याचे भूसंपादन करणेबाबत (पाषाण) | D67: 0 | E67: 0
D68: 0 | E68: 0
C69: भूसंपादनाची इतर प्रकरणे : | D69: 0 | E69: 0
C70: पुणेमुंबई रस्ता हॅरीस ब्रिज ते खडकी कॅन्टोन्मेंट | D70: 0 | E70: 0
C71: हडपसर स.नं. २२६, २२४, २६६, २११, २१०, २०९, २०८, २०७ पोस्ट ऑफीस बाजूने जाणारा १८ मी. डी. पी. रस्ता | D71: 0 | E71: 0
C72: हडपसर स. नं. ८७, ८९, ९२, ९३, १०६, ३१२, ३१४, ३१ पैकी डी. पी. रस्त्यासाठी | D72: 0 | E72: 0
C73: हडपसर स.नं. २५ ईडब्ल्यूएस पैकी जागा संपादन करणेबाबत | D73: 0 | E73: 0
C74: घोरपडी गाव अनंत टॉकीज ते श्रीवस्ती नगर १२ मी डी.पी. रस्ता | D74: 0 | E74: 0
C75: कोंढवा खु.॥ स.नं. ५अ, ५ ब हायस्कूलसाठी संपादन | D75: 0 | E75: 0
C76: कोंढवा खु.॥ स.नं. १७ पै. मुलांचे खेळाचे मैदानासाठी | D76: 0 | E76: 0
C77: पुणे, पेठ पाषाण स.नं. ११० (पै.) पार्क (उान) साठी संपादन | D77: 0 | E77: 0
C78: हडपसर स.नं. ८४ पैकी प्ले ग्राऊंड साठी संपादन | D78: 0 | E78: 0
C79: वानवडी स.नं. ४९, ५८, ५९ | D79: 0 | E79: 0
C80: नाना पेठ, सि.सं. नं. ४०५ पै. उानासाठी आरक्षित जागा संपादन करणे | D80: 0 | E80: 0
... C95: हिंगणे / कर्वेनगर स.नं. ४० हायस्कूलसाठी | D95: 0 | E95: 0
D96: 0 | E96: 0
D97: 0 | E97: 0
C98: जाहीर झालेल्या निवाड्यापोटी भरण्याची रक्कम | D98: 0 | E98: 0
A99: 1 | C99: कर्वे रस्तारूंद जाहीर झालेल्या निवाड्यापोटी राहीलेली भरावयाची रक्कम | D99: 0 | E99: 0
A100: 2 | C100: सदाशिव पेठ घरांक ४६८ पार्किंगसाठी संपादन करणे | D100: 0 | E100: 0
D101: 0 | E101: 0
D102: 0 | E102: 0
C103: भूमिप्रापण खाते :- | D103: 0 | E103: 0
A104: 1 | C104: केळकर रस्ता (मंदार लॉज ते नारायण पेठ पोलीस चौकी) | D104: 0 | E104: 0
A105: 2 | C105: म्हात्रे पूल ते छत्रपती राजाराम पूल दरम्यानच्या नदीकाठचा १००'' डी.पी. रस्ता | D105: 0 | E105: 0
A106: 3 | C106: सातारा रस्ता | D106: 0 | E106: 0
A107: 4 | C107: सिंहगड रस्ता | D107: 0 | E107: 0
A108: 5 | C108: जंगली महाराज रस्ता | D108: 0 | E108: 0
A109: 6 | C109: पवित्र मंगल कार्यालया, पर्वती (सातारा रस्ता) | D109: 0 | E109: 0
A110: 7 | C110: नेहरू रस्ता, रास्ता पेठ पॉवर हाऊस ते लक्ष्मी रस्ता | D110: 0 | E110: 0
A111: 8 | C111: कर्वे रस्ता (खंडूजीबाबा चौक ते एस.एन.डी.टी.) | D111: 0 | E111: 0
A112: 9 | C112: शंकरशेठ रस्ता | D112: 0 | E112: 0
A113: 10 | C113: सेनापती बापट रस्ता | D113: 0 | E113: 0
A114: 11 | C114: उंबर्‍या गणपती चौक ते खुन्या मुरलीधर रस्ता | D114: 0 | E114: 0
A115: 12 | C115: भाऊ महाराज बोळ | D115: 0 | E115: 0
... A121: 18 | C121: रामवाडी जकातनाका ते लोहगाव विमानतळ | D121: 0 | E121: 0
D122: 0 | E122: 0
C123: जकात नाका :- | D123: 0 | E123: 0
A124: 1 | C124: शिंदेवाडी, स.नं. १०० ते १०६ (पैकी) | D124: 0 | E124: 0
A125: 2 | C125: फुरसुंगी, स.नं. १७५ पैकी | D125: 0 | E125: 0
A126: 3 | C126: वाघोली, गट नं. २३७८, २३७९ | D126: 0 | E126: 0
A127: 4 | C127: बावधन खुर्द, स.नं. ६४ | D127: 0 | E127: 0
A128: 5 | C128: हडपसर, स.नं. ६३ पैकी | D128: 0 | E128: 0
A129: 6 | C129: उंड्री, स.नं. ५४ पैकी | D129: 0 | E129: 0
...

Sheet A_Fund_Expenditure
H1: योजनांतर्गत खर्चाबाबतचे अंदाजपत्रक
A2: मान्यतेचा ठराव क्र. दिनांक (कोड) | B2: प्रभाग क्रमांक | C2: BPL | D2: कामाचे नाव अगर वर्णन | E2: दि. 31 मार्च 2021 अखेरपर्यंत केलेली तरतूद | H2: दि. 31 मार्च 2019 पर्यंतचा खर्चाचा नक्‍की आकडा | I2: 2019-20 मधील खर्चाचा नक्‍की आकडा | J2: 2020-21 मधील खर्चाची अंदाजी रक्‍कम | K2: 2021-22 साठी अधिक तरतूद | M2: 2021-22 साठी एकूण तरतूद | N2: शेरा
E3: कर्जातून | F3: महसूल निधीतून | G3: एकूण | K3: कर्जातून | L3: महसूल निधी व इतर निधी
D8: ४. झोपडपट्टी निर्मूलन व पुनर्वसन निधी | E8: 0 | F8: 0 | G8: 0 | H8: 0 | I8: 0 | J8: 0 | L8: 0 | M8: 0
A9: FE14A101# | B9: _ | C9: SG1- | D9: निरनिराळ्या झोपडपट्टींमध्ये विविध विकासाची कामे करणे | E9: 33377000 | F9: 1532737821 | G9: 1566114821 | H9: 1474114821 | I9: 30158533 | J9: 61841467 | L9: 155800000 | M9: 155800000
A10: FE14A104 | C10: B | D10: झो.नि.पु. अंतर्गत करावयाची कामे | E10: 0 | F10: 234359610 | G10: 234359610 | H10: 202859610 | I10: 6281375 | J10: 25218625 | L10: 15800000 | M10: 15800000
A11: FE14A105# | B11: _ | C11: SG2- | D11: शहरामध्ये शौच्छालये / मुताऱ्या बांधणे | E11: 0 | F11: 1769487157 | G11: 1769487157 | H11: 1307987157 | I11: 223856472 | J11: 237643528 | L11: 266600000 | M11: 266600000
A12: FE14A107 | C12: B | D12: दलित वस्ती सुधारणा अंतर्गत कामे करणे | E12: 0 | F12: 201505383 | G12: 201505383 | H12: 201505383 | I12: 23191253 | J12: -23191253 | L12: 0 | M12: 0
A13: FE14A129 | C13: PL | D13: सार्वजनिक ठिकाणी शौचालय बांधणे | E13: 0 | F13: 77291383 | G13: 77291383 | H13: 45791383 | I13: 9368615 | J13: 22131385 | L13: 15750000 | M13: 15750000
A14: FE14A130 | C14: PL | D14: सार्वजनिक ठिकाणी मुतार्‍या बांधणे | E14: 0 | F14: 56026158 | G14: 56026158 | H14: 24526158 | I14: 6090590 | J14: 25409410 | L14: 15750000 | M14: 15750000
A15: FE14A135 | D15: प्रभाग क्र.14ब, मधील बाबासाहेब आंबेडकर हॉस्टेल विकसित करणेकरिता अहवाल तयार करणे | E15: 0 | F15: 2000000 | G15: 2000000 | H15: 0 | I15: 0 | J15: 2000000 | L15: 0 | M15: 0
E16: 0 | F16: 0 | G16: 0 | H16: 0 | I16: 0 | J16: 0 | L16: 0 | M16: 0
D17: ४. झोपडपट्टी निर्मूलन व पुनर्वसन निधी एकूण बेरीज | E17: 33377000 | F17: 3873407512 | G17: 3906784512 | H17: 3256784512 | I17: 298946838 | J17: 351053162 | L17: 469700000 | M17: 469700000
E18: 0 | F18: 0 | G18: 0 | H18: 0 | I18: 0 | J18: 0 | L18: 0 | M18: 0
D19: क्षेत्रिय कार्यालयाने करावयाची कामे | E19: 0 | F19: 0 | G19: 0 | H19: 0 | I19: 0 | J19: 0 | L19: 0 | M19: 0
E20: 0 | F20: 0 | G20: 0 | H20: 0 | I20: 0 | J20: 0 | L20: 0 | M20: 0
A21: FE14A118# | B21: W5 | C21: B | D21: क्षेत्रिय कार्यालय : झो.नि.पु. विभागाने करावयाची कामे | E21: 0 | F21: 256689792 | G21: 256689792 | H21: 238453792 | I21: 2847704 | J21: 15388296 | L21: 8250000 | M21: 8250000
A22: FE14A121# | B22: C5 | C22: B | D22: क्षेत्रिय कार्यालय : नागरिकांच्या सहभाग योजनेतून झो.नि.पु. विभागाने करावयाची कामे | E22: 0 | F22: 142298136 | G22: 142298136 | H22: 138134136 | I22: 1773068 | J22: 2390932 | L22: 5500000 | M22: 5500000
E23: 0 | F23: 0 | G23: 0 | H23: 0 | I23: 0 | J23: 0 | L23: 0 | M23: 0
D24: क्षेत्रिय कार्यालयाने करावयाची कामे एकूण बेरीज | E24: 0 | F24: 398987928 | G24: 398987928 | H24: 376587928 | I24: 4620772 | J24: 17779228 | L24: 13750000 | M24: 13750000
E25: 0 | F25: 0 | G25: 0 | H25: 0 | I25: 0 | J25: 0 | L25: 0 | M25: 0
D26: ४. झोपडपट्टी निर्मूलन व पुनर्वसन निधीतून करावयाची कामे + क्षेत्रिय कार्यालयाने करावयाची कामे एकूण बेरीज | E26: 33377000 | F26: 4272395440 | G26: 4305772440 | H26: 3633372440 | I26: 303567610 | J26: 368832390 | L26: 483450000 | M26: 483450000
E27: 0 | F27: 0 | G27: 0 | H27: 0 | I27: 0 | J27: 0 | L27: 0 | M27: 0
D28: ४अ. मागासवर्गीय कल्याणकारी योजना निधी | E28: 0 | F28: 0 | G28: 0 | H28: 0 | I28: 0 | J28: 0 | L28: 0 | M28: 0
A29: FE14B101 | C29: B-FA | D29: समाज विकास विभाग अंतर्गत मागासवर्गीय योजना | E29: 0 | F29: 520654616 | G29: 520654616 | H29: 445654616 | I29: 29154934 | J29: 45845066 | L29: 35000000 | M29: 35000000
A30: FE14B112 | C30: B-FA | D30: लोकशाहीर अण्णाभाऊ साठे शैक्षणिक मदत योजना | E30: 0 | F30: 219867082 | G30: 219867082 | H30: 147867082 | I30: 22525000 | J30: 49475000 | L30: 45000000 | M30: 45000000
A31: FE14B113 | C31: B-FA | D31: मौ. अबुल कलाम आझाद शैक्षणिक मदत योजना | E31: 0 | F31: 454758546 | G31: 454758546 | H31: 332758546 | I31: 33800000 | J31: 88200000 | L31: 75000000 | M31: 75000000
A32: FE14B121 | C32: B-T | D32: मागासवर्गीय विद्यार्थ्यांना स्पर्धा परिक्षा मार्गदर्शन केंद्र चालविणे | E32: 0 | F32: 11843896 | G32: 11843896 | H32: 5843896 | I32: 0 | J32: 6000000 | L32: 3000000 | M32: 3000000
A33: FE14B122 | C33: B-T | D33: बालविकास केंद्र व वस्ती रिसोर्स सेंटर सुरू करणे | E33: 0 | F33: 14929939 | G33: 14929939 | H33: 10929939 | I33: 1868243 | J33: 2131757 | L33: 1500000 | M33: 1500000
A34: FE14B123 | C34: B | D34: मागासवर्गीय कल्याणकारी योजनेअंतर्गत विविध योजना राबविणेसाठी मानधन तत्वावरील सेवकांचा मानधन खर्च | E34: 0 | F34: 36002659 | G34: 36002659 | H34: 31002659 | I34: 0 | J34: 5000000 | L34: 5000000 | M34: 5000000
A35: FE14B127 | C35: B | D35: माता रमार्इ भिमराव आंबेडकर योजनेअंतर्गत गवनि घोषीत व शहरी गरीब योजनेतील पात्र ठरणाऱ्या विधवा, निराधार महिलांसाठी दरमहा रू.1,000/- अर्थसहाय्य करणे (मागासवर्गीय कल्याणकारी योजना) | E35: 0 | F35: 23002788 | G35: 23002788 | H35: 1002788 | I35: 2400000 | J35: 19600000 | L35: 17000000 | M35: 17000000
A36: FE14B128 | C36: B-FA | D36: डॉ. बाबासाहेब आंबेडकर विद्यार्थी वसतिगृह, घोले रोड येथील खाणावळीचा खर्च | E36: 0 | F36: 17136257 | G36: 17136257 | H36: 7136257 | I36: 2310794 | J36: 7689206 | L36: 5000000 | M36: 5000000
A37: FE14B129 | C37: B-I | D37: शहरात आदिवासी विद्यार्थ्यांसाठी वसतिगृहे उभारणे | E37: 0 | F37: 53885336 | G37: 53885336 | H37: 3885336 | I37: 13860473 | J37: 36139527 | L37: 30000000 | M37: 30000000
A38: FE14B130 | D38: बार्टी संस्थेच्या मदतीने विविध व्यावसायिक प्रशिक्षण देणे | E38: 0 | F38: 0 | G38: 0 | H38: 0 | I38: 0 | J38: 0 | L38: 0 | M38: 0
A39: FE14B131 | C39: B-T | D39: विविध व्यावसायिक प्रशिक्षण देणे | E39: 0 | F39: 2795454 | G39: 2795454 | H39: 795454 | I39: 1999989 | J39: 11 | L39: 0 | M39: 0
A40: FE14B132 | C40: B-S | D40: मागासवर्गीय कल्याणकारी योजनेचा अभ्यास, ऑडिट व सर्वेक्षण करणे | E40: 0 | F40: 0 | G40: 0 | H40: 0 | I40: 0 | J40: 0 | L40: 0 | M40: 0
A41: FE14B133 | C41: B | D41: लोकशाहिर अण्णा भाऊ साठे यांच्या जन्मशताब्दी वर्षानिमित्त विविध कार्यक्रमाचे आयोजन करणे | E41: 0 | F41: 10000000 | G41: 10000000 | H41: 0 | I41: 0 | J41: 10000000 | L41: 0 | M41: 0
E42: 0 | F42: 0 | G42: 0 | H42: 0 | I42: 0 | J42: 0 | L42: 0 | M42: 0
D43: ४अ. मागासवर्गीय कल्याणकारी योजना निधी एकूण बेरीज | E43: 0 | F43: 1364876573 | G43: 1364876573 | H43: 986876573 | I43: 107919433 | J43: 270080567 | L43: 216500000 | M43: 216500000
E44: 0 | F44: 0 | G44: 0 | H44: 0 | I44: 0 | J44: 0 | L44: 0 | M44: 0
D45: ४ब. महिलाबालकल्याण योजना निधी | E45: 0 | F45: 0 | G45: 0 | H45: 0 | I45: 0 | J45: 0 | L45: 0 | M45: 0
A46: FE14C101 | C46: PL-FA | D46: महिलाबालकल्याण योजना | E46: 0 | F46: 459937791 | G46: 459937791 | H46: 384937791 | I46: 39911058 | J46: 35088942 | L46: 35000000 | M46: 35000000
A47: FE14C108 | C47: PL-FA | D47: महिला सक्षमिकरणासाठी अनुदानाची योजना | E47: 0 | F47: 226903428 | G47: 226903428 | H47: 171903428 | I47: 14626750 | J47: 40373250 | L47: 25000000 | M47: 25000000
A48: FE14C118 | C48: PL | D48: नागरवस्तीच्या वापरातील समाजमंदिरे / इतर वास्तूंच्या विद्युत बिलांसाठी | E48: 0 | F48: 9038740 | G48: 9038740 | H48: 5888740 | I48: 1499959 | J48: 1650041 | L48: 4500000 | M48: 4500000
A49: FE14C125# | B49: M1- | C49: SM1- | D49: महिलाबाल कल्याण योजना अंतर्गत करावयाची कामे | E49: 0 | F49: 339656112 | G49: 339656112 | H49: 86556112 | I49: 54230765 | J49: 198869235 | L49: 129900000 | M49: 129900000
A50: FE14C134 | C50: PL-FA | D50: रस्त्यांवरील मुलांसाठी घरटे प्रकल्प | E50: 0 | F50: 110948260 | G50: 110948260 | H50: 70948260 | I50: 9115400 | J50: 30884600 | L50: 20000000 | M50: 20000000
A51: FE14C135 | C51: PL-FA | D51: कन्यारत्न योजना | E51: 0 | F51: 750000 | G51: 750000 | H51: 750000 | I51: 0 | J51: 0 | K51: 0 | L51: 0 | M51: 0
A52: FE14C139 | C52: PL-T | D52: UCD मार्फत राबविल्या जाणार्‍या निरनिराळया उपक्रमासाठी लागणारा खर्च स्वयंरोजगार, प्रशिक्षण, साहित्य खरेदी इ. | E52: 0 | F52: 20504900 | G52: 20504900 | H52: 12504900 | I52: 3342845 | J52: 4657155 | L52: 4000000 | M52: 4000000
A53: FE14C140 | C53: PL-I | D53: पाळणाघर | E53: 0 | F53: 13120770 | G53: 13120770 | H53: 1120770 | I53: 166052 | J53: 11833948 | L53: 10000000 | M53: 10000000
A54: FE14C140A | D54: असंघटित / संघटीत क्षेत्रात काम करणाऱ्या स्त्रियांच्या सोयीसाठी पाळणाघर सुरू करणे | E54: 0 | F54: 20000000 | G54: 20000000 | H54: 0 | I54: 0 | J54: 20000000 | L54: 0 | M54: 0
A55: FE14C142 | C55: PL-T | D55: शेजार समुहगट व इतर महिलांसाठी विविध स्पर्धा, उपक्रम घेणे | E55: 0 | F55: 5949784 | G55: 5949784 | H55: 3949784 | I55: 28671 | J55: 1971329 | L55: 0 | M55: 0
A56: FE14C143 | C56: PL | D56: महिला व बाल कल्याण योजनेअंतर्गत विविध योजना राबविणेसाठी मानधन तत्वावरील सेवकांचा मानधन खर्च | E56: 0 | F56: 22807805 | G56: 22807805 | H56: 12807805 | I56: 556886 | J56: 9443114 | L56: 5000000 | M56: 5000000
A57: FE14C156 | C57: PL | D57: युवतींसाठी विविध ठिकाणी स्वसंरक्षणाचे प्रशिक्षण देणे | E57: 0 | F57: 6851799 | G57: 6851799 | H57: 1851799 | I57: 72600 | J57: 4927400 | L57: 2500000 | M57: 2500000
A58: FE14C160 | C58: PL-FA | D58: मुलगी दत्तक योजना | E58: 0 | F58: 45267000 | G58: 45267000 | H58: 15267000 | I58: 2060000 | J58: 27940000 | L58: 20000000 | M58: 20000000
A59: FE14C191 | C59: PL-I | D59: बचत गटातील उत्पादित केलेल्या मालाचे प्रदर्शन आयोजित करणे | E59: 0 | F59: 35062840 | G59: 35062840 | H59: 15062840 | I59: 4966366 | J59: 15033634 | L59: 10000000 | M59: 10000000
A60: FE14C208 | C60: PL-I | D60: पुणे शहरातील रस्त्यांवरील मुलांकरिता विविध उपक्रम राबविणे | E60: 0 | F60: 100000000 | G60: 100000000 | H60: 0 | I60: 0 | J60: 100000000 | L60: 50000000 | M60: 50000000
A61: FE14C209 | C61: PL-T | D61: राणी लक्ष्मीबाई महिला सक्षमीकरण योजना | E61: 0 | F61: 60000000 | G61: 60000000 | H61: 0 | I61: 0 | J61: 60000000 | L61: 30000000 | M61: 30000000
A62: FE14C210 | C62: PL-I | D62: बेघर महिलांसाठी रात्र निवारा प्रकल्प सुरू करणे | E62: 0 | F62: 13000000 | G62: 13000000 | H62: 0 | I62: 0 | J62: 13000000 | L62: 8000000 | M62: 8000000
A63: FE14C211 | C63: L-I | D63: १५ क्षेत्रिय कार्यालय येथे हिरकणी कक्ष सुरू करणे | E63: 0 | F63: 6328922 | G63: 6328922 | H63: 328922 | I63: 277213 | J63: 5722787 | L63: 3000000 | M63: 3000000
A64: FE14C212 | D64: महिला बचत गटांना रोजगार निर्मितीसाठी e-marketing साठी संकेतस्थळ सुरू करणे. | E64: 0 | F64: 7500000 | G64: 7500000 | H64: 0 | I64: 0 | J64: 7500000 | L64: 2500000 | M64: 2500000
A65: FE14C213 | C65: PL-FA | D65: महिला मालमत्ता धारकांना सर्वसाधारण करामध्ये प्रोत्साहन म्हणून र.रू. ५००/- पर्यंत सुट देणे तसेच स्व कमाईतून उभारलेली मालमत्तेचा महिलेच्या अथवा मुलांच्या नावे समान हिस्सा दिल्यास १% अथवा जास्तीत जास्त ५०००/- पर्यंत मालमत्ता करामध्ये सवलत देणे | E65: 0 | F65: 0 | G65: 0 | H65: 0 | I65: 0 | J65: 0 | K65: 0 | L65: 0 | M65: 0
A66: FE14C214 | C66: PL-FA | D66: ज्या कंपनीमध्ये संचालक मंडळासह सर्व कर्मचारी १००% महिला असल्यास कंपनीच्या मालमत्ता करामध्ये १% जास्तीत जास्त अथवा रक्कम रू. १००००/- पर्यंत सवलत देणे | E66: 0 | F66: 0 | G66: 0 | H66: 0 | I66: 0 | J66: 0 | K66: 0 | L66: 0 | M66: 0
A67: FE14C215 | C67: PL-FA | D67: PMPML मार्फत चालविल्या जाणार्‍या महिलांसाठीच्या बसचा प्रवास महिन्यातून एकदा मोफत उपलब्ध करून देणे | E67: 0 | F67: 0 | G67: 0 | H67: 0 | I67: 0 | J67: 0 | K67: 0 | L67: 0 | M67: 0
A68: FE14C216 | C68: PL-S | D68: महिला बालकल्याण योजनेचा अभ्यास ऑडिट आणि सर्वेक्षण करणे | E68: 0 | F68: 0 | G68: 0 | H68: 0 | I68: 0 | J68: 0 | K68: 0 | L68: 0 | M68: 0
A69: FE14C217 | C69: L | D69: राणी लक्ष्मीबाई दत्तक योजना | E69: 0 | F69: 15000000 | G69: 15000000 | H69: 0 | I69: 0 | J69: 15000000 | L69: 0 | M69: 0
A70: FE14C218 | C70: L | D70: अनाथ मुलांना शैक्षणिक सुविधा पुरविणे | E70: 0 | F70: 22000000 | G70: 22000000 | H70: 0 | I70: 0 | J70: 22000000 | L70: 21000000 | M70: 21000000
A71: FE14C219 | C71: L | D71: स्वच्छ झोपडपट्टी स्पर्धा, झोपडीत घनकचरा व्यवस्थापनाचे उत्कृष्ट काम करणाऱ्या व्यक्तीं व संस्था यांना परितोषिक देणे | E71: 0 | F71: 7000000 | G71: 7000000 | H71: 0 | I71: 0 | J71: 7000000 | L71: 5000000 | M71: 5000000
A72: FE14C220 | C72: L | D72: महिला व बालके यांचेसाठी स्पर्धा घेणे | E72: 0 | F72: 2000000 | G72: 2000000 | H72: 0 | I72: 0 | J72: 2000000 | L72: 0 | M72: 0
A73: FE14C221 | C73: L | D73: स्त्री संसाधन केंद्र (सक्षमा कक्ष) चालविणे | E73: 0 | F73: 20000000 | G73: 20000000 | H73: 0 | I73: 2238090 | J73: 17761910 | L73: 10000000 | M73: 10000000
A74: FE14C222 | C74: L | D74: Gender Responsibility अभ्यासगट तयार करणे व शहर पातळीवर महिलांच्या सुरक्षिततेसाठी उपाययोजना करणे | E74: 0 | F74: 10000000 | G74: 10000000 | H74: 0 | I74: 0 | J74: 10000000 | L74: 5000000 | M74: 5000000
A75: FE14C223 | C75: L | D75: सार्वजनिक ठिकाणी महिलांच्या सुरक्षिततेसाठी safety mapping व safety audit करणे | E75: 0 | F75: 10000000 | G75: 10000000 | H75: 0 | I75: 0 | J75: 10000000 | L75: 5000000 | M75: 5000000
E76: 0 | F76: 0 | G76: 0 | H76: 0 | I76: 0 | J76: 0 | L76: 0 | M76: 0
D77: ४ब. महिलाबालकल्याण योजना निधी एकूण बेरीज | E77: 0 | F77: 1701107655 | G77: 1701107655 | H77: 895357655 | I77: 133092655 | J77: 672657345 | L77: 405400000 | M77: 405400000
E78: 0 | F78: 0 | G78: 0 | H78: 0 | I78: 0 | J78: 0 | L78: 0 | M78: 0
D79: ४क. युवक कल्याणकारी योजना निधी (नागरवस्ती विकास योजना) | E79: 0 | F79: 0 | G79: 0 | H79: 0 | I79: 0 | J79: 0 | L79: 0 | M79: 0
A80: FE14D101 | C80: P-FA | D80: शहरातील तरुणांसाठी स्वयंरोजगार व प्रशिक्षणासाठी अनुदान देणे | E80: 0 | F80: 144661457 | G80: 144661457 | H80: 123411457 | I80: 10599467 | J80: 10650533 | L80: 15000000 | M80: 15000000
A81: FE14D118 | C81: P-FA | D81: लोकशाहीर अण्णाभाऊ साठे शैक्षणिक मदत योजना व मौ. अब्दुल कलाम आझाद शैक्षणिक मदत योजना | E81: 0 | F81: 1217045588 | G81: 1217045588 | H81: 1002545588 | I81: 94475000 | J81: 120025000 | L81: 130000000 | M81: 130000000
A82: FE14D122 | C82: P-I | D82: शहरात विविध ठिकाणी नाईट शेल्टर योजना राबविणे | E82: 0 | F82: 37468158 | G82: 37468158 | H82: 10468158 | I82: 6885452 | J82: 20114548 | L82: 20000000 | M82: 20000000
A83: FE14D123 | C83: P | D83: प्रशिक्षण संस्थांतील शिक्षक व इतर कर्मचार्‍यांचे मानधन देणे | E83: 0 | F83: 25958147 | G83: 25958147 | H83: 8958147 | I83: 1565729 | J83: 15434271 | L83: 10000000 | M83: 10000000
A84: FE14D125 | C84: P-I | D84: हॅलो माय फ्रेड योजना राबविणे,युवकांसाठी कॉल सेंटर सुरू करणे (मानसिक आरोग्य) | E84: 0 | F84: 3309807 | G84: 3309807 | H84: 409807 | I84: 0 | J84: 2900000 | L84: 1500000 | M84: 1500000
A85: FE14D126 | C85: P-I | D85: नागरवस्ती विकास योजना विभागाच्या ताब्यात असणार्‍या जागेपोटी PMPML प्रशासनास भाडे देणे | E85: 0 | F85: 6050000 | G85: 6050000 | H85: 0 | I85: 0 | J85: 6050000 | L85: 5000000 | M85: 5000000
A86: FE14D129 | C86: P-T | D86: स्पर्धा परिक्षा मार्गदर्शन केंद्र चालविणे | E86: 0 | F86: 3984000 | G86: 3984000 | H86: 884000 | I86: 0 | J86: 3100000 | L86: 1000000 | M86: 1000000
A87: FE14D136 | C87: P-I | D87: पुणे शहरात Light House प्रकल्प सुरू करणे | E87: 0 | F87: 50000000 | G87: 50000000 | H87: 0 | I87: 1977667 | J87: 48022333 | L87: 35000000 | M87: 35000000
A88: FE14D137 | C88: P-I | D88: समाज विकास केंद्रात अभ्यासिका सुरू करणे. | E88: 0 | F88: 987000 | G88: 987000 | H88: 987000 | I88: 0 | J88: 0 | K88: 0 | L88: 0 | M88: 0
A89: FE14D138 | D89: Digital Locker सुविधा उपलब्ध करणे | E89: 0 | F89: 0 | G89: 0 | H89: 0 | I89: 0 | J89: 0 | K89: 0 | L89: 0 | M89: 0
A90: FE14D140 | C90: PL-FA | D90: अभियांत्रिकी शिक्षणानंतर पुढील गुणवत्ता वाढीसाठी Certified Course घेणार्‍या विद्यार्थ्यांना र.रू २५,००० पर्यंत फी साठी आर्थिक सहाय्य करणे | E90: 0 | F90: 0 | G90: 0 | H90: 0 | I90: 0 | J90: 0 | K90: 0 | L90: 0 | M90: 0
A91: FE14D141 | D91: डॉ. बाबासाहेब आंबेडकर विद्यार्थी वसतीगृह, घोले रोड येथील विद्यार्थ्यांचा खानावळीचा खर्च देणे | E91: 0 | F91: 12321488 | G91: 12321488 | H91: 3321488 | I91: 2206421 | J91: 6793579 | L91: 5500000 | M91: 5500000
A92: FE14D142 | C92: P-S | D92: युवक कल्याणकारी योजनेचे अभ्यास ऑडिट आणि सर्वेक्षण करणे | E92: 0 | F92: 0 | G92: 0 | H92: 0 | I92: 0 | J92: 0 | K92: 0 | L92: 0 | M92: 0
A93: FE14D144 | D93: MPSC, UPSC पुर्व परिक्षेत उत्तीर्ण होऊन मुख्य परिक्षेला पात्र होणा-या गुणानुक्रमे प्रत्येकी 100 विद्यार्थ्यांना पुस्तके खेरदीसाठी अर्थसहाय्य करणे | E93: 0 | F93: 2000000 | G93: 2000000 | H93: 0 | I93: 0 | J93: 2000000 | L93: 1000000 | M93: 1000000
A94: FE14D145 | D94: खादी ग्रामोद्योग आयोगाच्या नोडल एजन्सी असणा-या राष्ट्रीय कुंभारी प्रशिक्षण संस्थेबरोबर स्वयंरोजगार कार्यक्रम राबविणे. | E94: 0 | F94: 20000000 | G94: 20000000 | H94: 0 | I94: 0 | J94: 20000000 | L94: 10000000 | M94: 10000000
A95: FE14D146 | D95: प्रभाग क्र.35क, मध्ये कै.वि.स.खांडेकर प्रशिक्षण केंद्रामार्फत स्पर्धा परिक्षांचे प्रशिक्षण घेण्यासाठी सर्व सुविधा पुरविणे. | E95: 0 | F95: 500000 | G95: 500000 | H95: 0 | I95: 0 | J95: 500000 | L95: 0 | M95: 0
A96: FE14D148 | D96: प्रभाग क्र.14ब, मध्ये अभ्यासिका वर्गामध्ये पुस्तके पुरविणे. | E96: 0 | F96: 1000000 | G96: 1000000 | H96: 0 | I96: 0 | J96: 1000000 | L96: 0 | M96: 0
A97: FE14D149 | D97: प्रभाग क्र.29क येथे स्वयंरोजगार व स्टार्टअप प्रोत्साहन करण्यासाठी विविध योजना राबविणे | E97: 0 | F97: 1000000 | G97: 1000000 | H97: 0 | I97: 0 | J97: 1000000 | L97: 0 | M97: 0
A98: FE14D150 | D98: प्रभाग क्र.15 अ, मध्ये मुले व तरूणांमध्ये विज्ञांनाचा उलगडा होणेसाठी प्रशिक्षण शिबीर राबविणे. | E98: 0 | F98: 1000000 | G98: 1000000 | H98: 0 | I98: 0 | J98: 1000000 | L98: 0 | M98: 0
A99: FE14D151 | D99: पुणे शहरात PPP तत्त्वावर कौशल्य विकास केंद्र (Skill Development Centre) सुरू करणे | E99: 0 | F99: 0 | G99: 0 | H99: 0 | I99: 0 | J99: 0 | L99: 300000000 | M99: 300000000
A100: FE14D152 | D100: शायकीय मान्यताप्राप्त व्यवसायभिमुख प्रमाणपत्र अभ्यासक्रमांसाठी अर्थसहाय्य | E100: 0 | F100: 0 | G100: 0 | H100: 0 | I100: 0 | J100: 0 | L100: 20000000 | M100: 20000000
A101: FE14D153 | D101: स्टार्ट अप, मुद्रा, कौशल्य विकास योजनांच्या जनजागृसाठी कार्यक्रमांचे आयोजन | E101: 0 | F101: 0 | G101: 0 | H101: 0 | I101: 0 | J101: 0 | L101: 20000000 | M101: 20000000
A102: FE14D154 | D102: राष्ट्रीय विचारांच्या संवर्धनासाठी स्वामी विवेवकानंद परिषदेचे आयोजन करणे. | E102: 0 | F102: 0 | G102: 0 | H102: 0 | I102: 0 | J102: 0 | L102: 5000000 | M102: 5000000
A103: FE14D155 | D103: पुणे मनपा विविध विभाग, योजनांचे संशोधन करणा-यांना शिष्यवृत्ती देणे. | E103: 0 | F103: 0 | G103: 0 | H103: 0 | I103: 0 | J103: 0 | L103: 1000000 | M103: 1000000
A104: FE14D156 | D104: स्वयंसेवी संस्था, गणेशोत्सव मंडळाचे सहआयोजनातून मनपाचे कार्यक्रम राबविणे. | E104: 0 | F104: 0 | G104: 0 | H104: 0 | I104: 0 | J104: 0 | L104: 10000000 | M104: 10000000
...

Sheet A_DPDC_Machinery_Tree
A1: विवरण | C1: नक्की आकडा | F1: मान्य अंदाज 2020-21 | G1: नवीन अंदाज 2021-22
C2: 2017-18 | D2: 2018-19 | E2: 2019-20
B6: ५. पुणे जिल्हा नियोजन व विकास मंडळ निधीतून करावयाची कामे
B7: ५अ. मा. आमदारांनी सुचविल्याप्रमाणे करावयाची विकासाची कामे
A8: FE15A101 | B8: बोपोडी मतदार संघ क्र. २४६ | C8: 0 | D8: 0 | E8: 0 | F8: 5000000 | G8: 5000000
A9: FE15A102 | B9: शिवाजीनगर मतदार संघ क्र. २४७ | C9: 8245720 | D9: 7569383 | E9: 5663108 | F9: 5000000 | G9: 5000000
A10: FE15A103 | B10: पर्वती मतदार संघ क्र. २४८ | C10: 7741474 | D10: 4049517 | E10: 20538895 | F10: 5000000 | G10: 5000000
A11: FE15A104 | B11: कसबा पेठ मतदार संघ क्र. २४९ | C11: 19590563 | D11: 17250785 | E11: 7008244 | F11: 5000000 | G11: 5000000
A12: FE15A105 | B12: भवानी पेठ मतदार संघ क्र. २५० | C12: 2233120 | D12: 0 | E12: 0 | F12: 5000000 | G12: 5000000
A13: FE15A106 | B13: पुणे (कॅन्टोन्मेंट) मतदार संघ क्र. २५१ | C13: 6010802 | D13: 6022891 | E13: 928911 | F13: 5000000 | G13: 5000000
A14: FE15A107 | B14: विधान परिषद सदस्य | C14: 2598815 | D14: 1627378 | E14: 1348324 | F14: 2500000 | G14: 2500000
C15: 0 | D15: 0 | E15: 0 | F15: 0 | G15: 0
A16: FE15A108 | B16: ५ब. मा. खासदारांनी सुचविल्याप्रमाणे करावयाची विकासाची कामे | C16: 12299310 | D16: 48067028 | E16: 39082990 | F16: 20000000 | G16: 20000000
C17: 0 | D17: 0 | E17: 0 | F17: 0 | G17: 0
A18: FE15A110 | B18: महानगरपालिका क्षेत्रात मुलभूत सोईसुविधांसाठी विशेष अनुदान | C18: 43052096 | D18: 8971934 | E18: 20903967 | F18: 0 | G18: 0
A19: FE15A111 | B19: मुळशी मतदार संघ | C19: 0 | D19: 0 | E19: 0 | F19: 2500000 | G19: 2500000
A20: FE15A112 | B20: कोथरूड विधानसभा मतदार संघ | C20: 4660732 | D20: 2487968 | E20: 0 | F20: 5000000 | G20: 5000000
A21: FE15A113 | B21: हडपसर विधानसभा मतदार संघ | C21: 950400 | D21: 1486525 | E21: 338906 | F21: 5000000 | G21: 5000000
A22: FE15A114 | B22: वडगांवशेरी विधानसभा मतदार संघ | C22: 0 | D22: 0 | E22: 0 | F22: 5000000 | G22: 5000000
A23: FE15A115 | B23: खडकवासला विधानसभा मतदार संघ | C23: 2531383 | D23: 0 | E23: 0 | F23: 5000000 | G23: 5000000
A24: FE15A117 | B24: सर्वसाधारण जिल्हा वार्षिक योजना अंतर्गत नाविन्यपूर्ण योजनांचा निधी | C24: 2499811 | D24: 0 | E24: 0 | F24: 0 | G24: 0
B25: ५. पुणे जिल्हा नियोजन व विकास मंडळ निधीतून करावयाची कामे बेरीज | C25: 112414226 | D25: 97533409 | E25: 95813345 | F25: 75000000 | G25: 75000000
C26: 0 | D26: 0 | E26: 0 | F26: 0 | G26: 0
C27: 0 | D27: 0 | E27: 0 | F27: 0 | G27: 0
B28: ७. यंत्रसामुग्री घसारा निधीतून विकत घ्याववयाची नवीन सामुग्री | C28: 0 | D28: 0 | E28: 0 | F28: 0 | G28: 0
B29: अग्निशामक दलासाठी यंत्रसामुग्री :- | C29: 0 | D29: 0 | E29: 0 | F29: 0 | G29: 0
A30: FE17A103-1 | B30: वॉटर टँकर पंपासह (2 नग) | C30: 9299998 | D30: 11680000 | E30: 0 | F30: 0 | G30: 29400000
A31: FE17A103-2 | B31: फायर इंजिन गाडी (7 नग) | C31: 9300000 | D31: 29199998 | E31: 26292205 | F31: 56000000 | G31: 36820000
A32: FE17A103-4 | B32: हायड्रोलिक प्लॅटफॉर्म | C32: 12798069 | D32: 0 | E32: 0 | F32: 0 | G32: 0
A33: FE17A103-12 | B33: रेस्क्यू इक्वीपमेंट व लाईट मास्ट | C33: 7388960 | D33: 0 | E33: 1460426 | F33: 44000000 | G33: 0
A34: FE17A107-23 | B34: आरोग्य विभागाकडील सरासरी आयुर्मान संपलेल्या आर्टीक्युलेटेड क्रेन निरस्त करून नवीन वाहने खरेदी करणे | C34: 0 | D34: 0 | E34: 0 | F34: 5600000 | G34: 0
A35: FE17A113-6 | B35: विद्युत विभाग :- हायड्रॉलिक प्लॅटफॉर्म (2 नग) | C35: 0 | D35: 0 | E35: 0 | F35: 0 | G35: 2800000
A36: FE17A114-6 | B36: बॅकहो लोडर खरेदी करणे | C36: 0 | D36: 4000200 | E36: 9840186 | F36: 0 | G36: 0
A37: FE17A114-9 | B37: पथ विभागासाठी टिपर खरेदी करणे | C37: 0 | D37: 13749120 | E37: 0 | F37: 8000000 | G37: 0
A38: FE17A114-10 | B38: पथ विभागाकडील कोठ्यांसाठी रोलर्स, मिक्‍सर्स, पेव्हर अन्य यंत्रसामुग्री खरेदी करणे | C38: 18701411 | D38: 0 | E38: 0 | F38: 0 | G38: 0
A39: FE17A124 | B39: मोटार वाहन विभाग मशिनरी | C39: 124045 | D39: 81895 | E39: 631216 | F39: 1600000 | G39: 1330000
A40: FE17A146 | B40: मनपा पदाधिकारी व अधिकार्‍यांसाठी मोटारकार खरेदी करणे | C40: 9660473 | D40: 3145700 | E40: 6706341 | F40: 8000000 | G40: 6510000
A41: FE17A149-3 | B41: कंटेनर दुरुस्ती व रंगवणे | C41: 1844372 | D41: 1973896 | E41: 999989 | F41: 2000000 | G41: 1680000
... A56: FE17A277# | B56: यंत्रसामुग्री घसारा निधीतून विकत घ्याववयाची सामुग्री (यादी Y1) | C56: 40925716 | D56: 40881598 | E56: 135664718 | F56: 106000000 | G56: 165500000
C57: 0 | D57: 0 | E57: 0 | F57: 0 | G57: 0
B58: ७. यंत्रसामुग्री घसारा निधी बेरीज | C58: 211333544 | D58: 244736988 | E58: 281442161 | F58: 384320000 | G58: 408470000
C59: 0 | D59: 0 | E59: 0 | F59: 0 | G59: 0
B60: १०. वृक्ष संरक्षण व संवर्धन प्राधिकारी निधीतून करावयाचा खर्च | C60: 0 | D60: 0 | E60: 0 | F60: 0 | G60: 0
B61: १०क. वृक्ष संवर्धन व संरक्षण कार्यालयाकडील खर्च :- | C61: 0 | D61: 0 | E61: 0 | F61: 0 | G61: 0
A62: FE20A101A | B62: १. कायम सेवकवर्ग वेतन | C62: 32171322 | D62: 31913916 | E62: 38835322 | F62: 57750000 | G62: 63525000
A63: FE20A102A | B63: २. हंगामी सेवकवर्ग | C63: 0 | D63: 0 | E63: 0 | F63: 1050000 | G63: 1155000
C64: 0 | D64: 0 | E64: 0 | F64: 0 | G64: 0
B65: १०क. बेरीज | C65: 32171322 | D65: 31913916 | E65: 38835322 | F65: 58800000 | G65: 64680000
C66: 0 | D66: 0 | E66: 0 | F66: 0 | G66: 0
B67: १०ग. संकीर्ण :- | C67: 0 | D67: 0 | E67: 0 | F67: 0 | G67: 0
A68: FE20C101 | B68: १. मुद्रण | C68: 245100 | D68: 416140 | E68: 59375 | F68: 438900 | G68: 500000
A69: FE20C102 | B69: २. लेखन व साहित्य | C69: 10242 | D69: 264514 | E69: 89702 | F69: 577500 | G69: 750000
A70: FE20C103 | B70: ३. प्रकटन खर्च | C70: 0 | D70: 0 | E70: 0 | F70: 1155000 | G70: 1200000
A71: FE20C104 | B71: ४. टपालखर्च व पावती तिकिटे | C71: 9960 | D71: 0 | E71: 0 | F71: 115500 | G71: 115000
A72: FE20C105 | B72: ५. गणवेष | C72: 0 | D72: 0 | E72: 0 | F72: 231000 | G72: 250000
A73: FE20C106 | B73: ६. पुस्तके व शिलकी साहित्य | C73: 0 | D73: 0 | E73: 0 | F73: 115500 | G73: 120000
A74: FE20C107 | B74: ७. मुलांसाठी मनोरंजन व इतर खर्च | C74: 252267 | D74: 216769 | E74: 213167 | F74: 635250 | G74: 700000
A75: FE20C108 | B75: ८. ट्री अ‍ॅथॉरिटी सभा चहापान खर्च (न.स.) | C75: 12188 | D75: 0 | E75: 0 | F75: 121000 | G75: 125000
C76: 0 | D76: 0 | E76: 0 | F76: 0 | G76: 0
B77: १०ग. बेरीज | C77: 529757 | D77: 897423 | E77: 362244 | F77: 3389650 | G77: 3760000
C78: 0 | D78: 0 | E78: 0 | F78: 0 | G78: 0
A79: FE20D101 | B79: नर्सरीच्या वाढीसाठी रोपे, उपकरणे, खते, साहित्य खरेदी व दुरुस्ती देखभाल | C79: 1136351 | D79: 1544104 | E79: 1422176 | F79: 2200000 | G79: 2000000
A80: FE20Q101 | B80: पुणे शहरात शालेय विार्थ्यांसाठी पर्यावरणावर आधारित विविध उपक्रम राबविणे | C80: 0 | D80: 0 | E80: 0 | F80: 200000 | G80: 200000
A81: FE20E101 | B81: ड. मनपातर्फे फळाफुलांचे प्रदर्शन | C81: 1212805 | D81: 1725000 | E81: 252594 | F81: 1970000 | G81: 2000000
A82: FE20G101 | B82: छ. वृक्ष लागवडीसाठी ३ ते ४ वर्षे वयाची व १० ते १५ फूट उंचीची रोपे, झाडांचे संरक्षणासाठी ट्री गार्ड खरेदी व जुने ट्री गार्ड दुरुस्ती | C82: 2527071 | D82: 2653704 | E82: 57800 | F82: 4000000 | G82: 4000000
A83: FE20H101 | B83: ज. झाडांची हालवाहलव | C83: 0 | D83: 931460 | E83: 0 | F83: 1300000 | G83: 1300000
A84: FE20I101 | B84: ञ. मनपा सार्वजनिक जागेवरील वृक्षारोपण, संरक्षण देखभाल व तद्‌नुषंगिक खर्च | C84: 8203519 | D84: 4573903 | E84: 10027625 | F84: 20000000 | G84: 15000000
A85: FE20K101 | B85: फ. ट्री अ‍ॅथॉरिटीस निरनिराळ्या ठिकाणी भेट देण्यासाठी खर्च | C85: 0 | D85: 0 | E85: 0 | F85: 1518000 | G85: 1250000
A86: FE20L101 | B86: १०ब. वृक्षारोपण उत्तेजनार्थ बक्षिसे | C86: 332750 | D86: 0 | E86: 0 | F86: 1265000 | G86: 1000000
A87: FE20M101 | B87: १०भ. कामगार नुकसान भरपाई कायाखाली नुकसानभरपाई | C87: 0 | D87: 0 | E87: 0 | F87: 189750 | G87: 150000
A88: FE20N101 | B88: १०क्ष. वृक्षगणना व अनुषंगिक कामे | C88: 38817000 | D88: 28484982 | E88: 0 | F88: 30000000 | G88: 30000000
A89: FE20P101 | B89: झाडांना पाणी घालण्यासाठी टँकर खरेदी करणे | C89: 0 | D89: 0 | E89: 6124375 | F89: 1200000 | G89: 1320000
A90: FE20P103 | B90: टायर्स सुटे भाग व देखभाल | C90: 7989237 | D90: 7556692 | E90: 4937109 | F90: 12500000 | G90: 12500000
... A111: FE20P129 | B111: पुणे शहरातील महत्त्वाचा रस्ता असणाऱ्या लोहगाव विमानतळ रस्त्यावर मीयावक पद्धतीने वृक्ष लागवड करून जाळीचे कुंपण घालणे | C111: 0 | D111: 0 | E111: 0 | F111: 500000 | G111: 500000
C112: 0 | D112: 0 | E112: 0 | F112: 0 | G112: 0
B113: १०. वृक्ष संरक्षण व संवर्धन प्राधिकारी निधीतून करावयाचा खर्च एकूण बेरीज | C113: 103597963 | D113: 95235512 | E113: 81771029 | F113: 197238900 | G113: 160035000
C114: 0 | D114: 0 | E114: 0 | F114: 0 | G114: 0
A115: FE31A101 | B115: १९. संकल्प निधी | C115: 12952518 | D115: 8912638 | E115: 1421517 | F115: 0 | G115: 0
C116: 0 | D116: 0 | E116: 0 | F116: 0 | G116: 0
B117: १९. संकल्प निधी बेरीज | C117: 12952518 | D117: 8912638 | E117: 1421517 | F117: 0 | G117: 0

Sheet C_Revenue_Income
A1: पाणीपुरवठा व जलोत्सारण प्रकल्पांतर्गत | G1: खास निधी 'क' चा जमेचा गोषवारा व तपशील
A2: विवरण | C2: नक्की आकडा | H2: 2020-21 वर्षाचा अंदाज | J2: 2021-22 वर्षाचा अंदाज | M2: 2020-21 वर्षाच्या मान्य अंदाजाशी तुलना केलेला 2021-22 वर्षाचा मा. स्थायी समितीने मान्यता दिलेला अंदाज
C3: 2017-18 | D3: 2018-19 | E3: 2019-20 | F3: 2019-20 शेवटची सहामाही | G3: 2020-21 पहिली सहामाही | H3: मान्य अंदाज | I3: दुरूस्त अंदाज | J3: मा. महापालिका आयुक्त यांनी सुचविलेला | K3: मा. स्थायी समितीने मान्यता दिलेला | L3: मा. महानगर- पालिकेने संमत केलेला
M5: अधिक | N5: कमी
A7: अधिनियमाप्रमाणे कमीत कमी रोख शिल्लक ठेवण्याची रक्कम जमेस धरून वर्षारंभीची शिल्लक | C7: 100000 | D7: 100000 | E7: 100000 | F7: 100000 | G7: 0 | H7: 100000 | I7: 100000 | J7: 100000 | K7: 100000 | L7: 0 | M7: 0 | N7: 0
C8: 0 | D8: 0 | E8: 0 | F8: 0 | G8: 0 | H8: 0 | I8: 0 | J8: 0 | K8: 0 | L8: 0 | M8: 0 | N8: 0
A9: १. पाणीपुरवठा (अति. न.अ.) | C9: 0 | D9: 0 | E9: 0 | F9: 0 | G9: 0 | H9: 0 | I9: 0 | J9: 0 | K9: 0 | L9: 0 | M9: 0 | N9: 0
A10: क. पाणीपट्टी साधारण पाणीपट्टी (कआकसंप्र) | B10: XI12A101 | C10: 1147803539 | D10: 1337732647 | E10: 1606183124 | F10: 280361192 | G10: 1328408721 | H10: 2610000000 | I10: 2610000000 | J10: 2900000000 | K10: 2900000000 | L10: 0 | M10: 290000000 | N10: 0
A11: ख. शासनाकडून (कआकसंप्र) | B11: XI12B101 | C11: 0 | D11: 0 | E11: 0 | F11: 0 | G11: 0 | H11: 100000 | I11: 100000 | J11: 100000 | K11: 100000 | L11: 0 | M11: 0 | N11: 0
A12: च. PMPML कडील मिळकतीवरील पाणीपट्टी (कआकसंप्र) | B12: XI12F101 | C12: 0 | D12: 0 | E12: 0 | F12: 0 | G12: 0 | H12: 100000 | I12: 100000 | J12: 100000 | K12: 100000 | L12: 0 | M12: 0 | N12: 0
A13: छ. जललाभ कर (Water Benefit Tax) (कआकसंप्र) | B13: XI12G101 | C13: 519828924 | D13: 558386876 | E13: 579046635 | F13: 145239422 | G13: 400453285 | H13: 1180000000 | I13: 1180000000 | J13: 1180000000 | K13: 1180000000 | L13: 0 | M13: 0 | N13: 0
A14: ग. पाणीपट्टी पाणीमापकानुसार (अति.न.अ.) | B14: XI12C101 | C14: 545850894 | D14: 884181735 | E14: 529584384 | F14: 289521361 | G14: 217956046 | H14: 1650000000 | I14: 1650000000 | J14: 1650000000 | K14: 1650000000 | L14: 0 | M14: 0 | N14: 0
A15: ग१. मीटर पाणीपट्टी थकबाकीपोटी जमा | B15: XI12C101A | C15: 0 | D15: 0 | E15: 0 | F15: 0 | G15: 0 | H15: 50000000 | I15: 50000000 | J15: 50000000 | K15: 1750000000 | L15: 0 | M15: 1700000000 | N15: 0
A16: ग२. गवनि खात्याअंतर्गत होणारी पाणीपट्टी जमा | B16: XI12C101B | C16: 8191908 | D16: 14631177 | E16: 9411692 | F16: 796322 | G16: 0 | H16: 25000000 | I16: 25000000 | J16: 25000000 | K16: 25000000 | L16: 0 | M16: 0 | N16: 0
A17: अनधिकृत कनेक्शन नियमित करण्यापोटी जमा | B17: XI12S101 | C17: 3067 | D17: 0 | E17: 3087 | F17: 0 | G17: 0 | H17: 5000000 | I17: 5000000 | J17: 5000000 | K17: 5000000 | L17: 0 | M17: 0 | N17: 0
A18: घ. पाणीमापक भाडे | B18: XI12D101 | C18: 13202 | D18: 2741759 | E18: 0 | F18: 0 | G18: 0 | H18: 2500000 | I18: 2500000 | J18: 2500000 | K18: 2500000 | L18: 0 | M18: 0 | N18: 0
A19: ड. नवीन नळ आकार नळदुरुस्ती व साफसफी (परतजमा) | B19: XI12E101 | C19: 15447884 | D19: 6506111 | E19: 4606709 | F19: 1588209 | G19: 1773867 | H19: 2500000 | I19: 2500000 | J19: 2500000 | K19: 2500000 | L19: 0 | M19: 0 | N19: 0
A20: ठ. कॉलनी रस्त्यावर पाईप टाकणे कामापोटी सुपरव्हिजन स्क्रुटीनी फी व अन्य जमा होणार | B20: XI12K101 | C20: 10956334 | D20: 17461303 | E20: 710997 | F20: 360180 | G20: 0 | H20: 32500000 | I20: 32500000 | J20: 30000000 | K20: 30000000 | L20: 0 | M20: 0 | N20: 2500000
A21: ढ. जलकेंद्राच्या आवारांतील निवास स्थानापोटी जमा होणारे भाडे | B21: XI12L101 | C21: 1412457 | D21: 0 | E21: 0 | F21: 0 | G21: 0 | H21: 2000000 | I21: 2000000 | J21: 1500000 | K21: 1500000 | L21: 0 | M21: 0 | N21: 500000
... A28: ण. अंदाजपत्रक 'अ' कडून वर्ग | B28: XI12M101 | C28: -696342303 | D28: 1955095785 | E28: -574449956 | F28: -574449956 | G28: 0 | H28: 1243100000 | I28: 1243100000 | J28: 781550000 | K28: -1025900000 | L28: 0 | M28: 0 | N28: 2269000000
C29: 0 | D29: 0 | E29: 0 | F29: 0 | G29: 0 | H29: 0 | I29: 0 | J29: 0 | K29: 0 | L29: 0 | M29: 0 | N29: 0
A30: १. बेरीज | C30: 1619170660 | D30: 4860707869 | E30: 2227088474 | F30: 184320717 | G30: 1963807173 | H30: 6975000000 | I30: 6975000000 | J30: 6800450000 | K30: 6693000000 | L30: 0 | M30: 1990000000 | N30: 2272000000
C31: 0 | D31: 0 | E31: 0 | F31: 0 | G31: 0 | H31: 0 | I31: 0 | J31: 0 | K31: 0 | L31: 0 | M31: 0 | N31: 0
A32: १अ. पुणे कॅन्टोन्मेंट पाणीपुरवठा जमा (अति.न.अ.) | C32: 0 | D32: 0 | E32: 0 | F32: 0 | G32: 0 | H32: 0 | I32: 0 | J32: 0 | K32: 0 | L32: 0 | M32: 0 | N32: 0
A33: (१) पाणीमापकानुसार पाणीपट्टी | B33: XI12Q101 | C33: 74930244 | D33: 164167267 | E33: 280745047 | F33: 167223310 | G33: 31168960 | H33: 210000000 | I33: 210000000 | J33: 210000000 | K33: 210000000 | L33: 0 | M33: 0 | N33: 0
A34: (२) H.E. Factory कडून येणारी जमा | B34: XI12Q102 | C34: 156399237 | D34: 50889083 | E34: 75708335 | F34: 59943068 | G34: 46045247 | H34: 85000000 | I34: 85000000 | J34: 85000000 | K34: 85000000 | L34: 0 | M34: 0 | N34: 0
C35: 0 | D35: 0 | E35: 0 | F35: 0 | G35: 0 | H35: 0 | I35: 0 | J35: 0 | K35: 0 | L35: 0 | M35: 0 | N35: 0
A36: १अ. बेरीज | C36: 231329481 | D36: 215056350 | E36: 356453382 | F36: 227166378 | G36: 77214207 | H36: 295000000 | I36: 295000000 | J36: 295000000 | K36: 295000000 | L36: 0 | M36: 0 | N36: 0
C37: 0 | D37: 0 | E37: 0 | F37: 0 | G37: 0 | H37: 0 | I37: 0 | J37: 0 | K37: 0 | L37: 0 | M37: 0 | N37: 0
A38: पुणे शहरात तंत्रशुध्द पध्दतीने पाणीपुरवठा (24x7 समान पाणीपुरवठा योजना) योजनेंतर्गत टाक्या बांधणेसाठी अनुदान (AMRUT) | B38: ZI12A111A | C38: 399000000 | D38: 308700000 | E38: 236100000 | F38: 236100000 | G38: 0 | H38: 310000000 | I38: 310000000 | J38: 235900000 | K38: 235900000 | L38: 0 | M38: 0 | N38: 74100000
A39: पुणे शहरात तंत्रशुध्द पध्दतीने पाणीपुरवठा करण्याची योजना (24x7 समान पाणीपुरवठा योजना) कर्जरोखे विक्री | B39: ZI12A112 | C39: 2000000000 | D39: 0 | E39: 0 | F39: 0 | G39: 0 | H39: 2000000000 | I39: 2000000000 | J39: 2000000000 | K39: 2000000000 | L39: 0 | M39: 0 | N39: 0
C40: 0 | D40: 0 | E40: 0 | F40: 0 | G40: 0 | H40: 0 | I40: 0 | J40: 0 | K40: 0 | L40: 0 | M40: 0 | N40: 0
A41: राष्ट्रीय नदीसुधारणा प्रकल्पातंर्गत (JICA) केंद्र सरकारकडून अनुदान | B41: ZI12A102 | C41: 0 | D41: 317500000 | E41: 0 | F41: 0 | G41: 0 | H41: 250000000 | I41: 250000000 | J41: 1258000000 | K41: 1258000000 | L41: 0 | M41: 1008000000 | N41: 0
C42: 0 | D42: 0 | E42: 0 | F42: 0 | G42: 0 | H42: 0 | I42: 0 | J42: 0 | K42: 0 | L42: 0 | M42: 0 | N42: 0
A43: १. एकूण बेरीज | C43: 4249500141 | D43: 5701964219 | E43: 2819641856 | F43: 647587095 | G43: 2041021380 | H43: 9830000000 | I43: 9830000000 | J43: 10589350000 | K43: 10481900000 | L43: 0 | M43: 2998000000 | N43: 2346100000
C44: 0 | D44: 0 | E44: 0 | F44: 0 | G44: 0 | H44: 0 | I44: 0 | J44: 0 | K44: 0 | L44: 0 | M44: 0 | N44: 0
A45: २. गटारे व नाले सुधारणा (अति.न.अ.) | C45: 0 | D45: 0 | E45: 0 | F45: 0 | G45: 0 | H45: 0 | I45: 0 | J45: 0 | K45: 0 | L45: 0 | M45: 0 | N45: 0
A46: क. सफाईपट्टी (कआकसंप्र) | B46: XI23A101 | C46: 1941205852 | D46: 2085529792 | E46: 2141634540 | F46: 543520498 | G46: 1457481380 | H46: 3400000000 | I46: 3400000000 | J46: 4350000000 | K46: 4350000000 | L46: 0 | M46: 950000000 | N46: 0
A47: घ. सुअरेज बेनिफीट टॅक्स (कआकसंप्र) | B47: XI23D101 | C47: 896401311 | D47: 961744905 | E47: 999407213 | F47: 254328108 | G47: 689728636 | H47: 2280000000 | I47: 2280000000 | J47: 2260000000 | K47: 2260000000 | L47: 0 | M47: 0 | N47: 20000000
A48: ग. ड्रेनेज / सलेज कनेक्शन व सेवावाढ आकार नियोजित बांधकाम क्षेत्रफळावर रु. ११ चौ. मि. | B48: XI23C101 | C48: 7945543 | D48: 9453661 | E48: 5410009 | F48: 1669980 | G48: 818585 | H48: 0 | I48: 0 | J48: 0 | K48: 0 | L48: 0 | M48: 0 | N48: 0
C49: 0 | D49: 0 | E49: 0 | F49: 0 | G49: 0 | H49: 0 | I49: 0 | J49: 0 | K49: 0 | L49: 0 | M49: 0 | N49: 0
A50: २. बेरीज | C50: 2845552706 | D50: 3056728358 | E50: 3146451762 | F50: 799518586 | G50: 2148028601 | H50: 5680000000 | I50: 5680000000 | J50: 6610000000 | K50: 6610000000 | L50: 0 | M50: 950000000 | N50: 20000000
C51: 0 | D51: 0 | E51: 0 | F51: 0 | G51: 0 | H51: 0 | I51: 0 | J51: 0 | K51: 0 | L51: 0 | M51: 0 | N51: 0
A52: ३. डेव्हलपमेंट निधीकडून जमा Development Charges (बांधकाम नियोजन) | B52: XI23F101 | C52: 1155272716 | D52: 1022164378 | E52: 1264181557 | F52: 1264181557 | G52: 0 | H52: 540000000 | I52: 540000000 | J52: 1025000000 | K52: 1025000000 | L52: 0 | M52: 485000000 | N52: 0
C53: 0 | D53: 0 | E53: 0 | F53: 0 | G53: 0 | H53: 0 | I53: 0 | J53: 0 | K53: 0 | L53: 0 | M53: 0 | N53: 0
A54: १. + २. + ३. एकूण बेरीज | C54: 8250325563 | D54: 9780856955 | E54: 7230275175 | F54: 2711287238 | G54: 4189049981 | H54: 16050000000 | I54: 16050000000 | J54: 18224350000 | K54: 18116900000 | L54: 0 | M54: 4433000000 | N54: 2366100000
C55: 0 | D55: 0 | E55: 0 | F55: 0 | G55: 0 | H55: 0 | I55: 0 | J55: 0 | K55: 0 | L55: 0 | M55: 0 | N55: 0
A56: वर्षारंभीच्या शिलकेसह एकूण जमा | C56: 8250425563 | D56: 9780956955 | E56: 7230375175 | F56: 2711387238 | G56: 4189049981 | H56: 16050100000 | I56: 16050100000 | J56: 18224450000 | K56: 18117000000 | L56: 0 | M56: 4433000000 | N56: 2366100000
C57: 0 | D57: 0 | E57: 0 | F57: 0 | G57: 0 | H57: 0 | I57: 0 | J57: 0 | K57: 0 | L57: 0 | M57: 0 | N57: 0
C58: 0 | D58: 0 | E58: 0 | F58: 0 | G58: 0 | H58: 0 | I58: 0 | J58: 0 | K58: 0 | L58: 0 | M58: 0 | N58: 0
A59: वजा : अंदाजपत्रक 'अ' कडून वर्ग | C59: -696342303 | D59: 1955095785 | E59: -574449956 | F59: -574449956 | G59: 0 | H59: 1243100000 | I59: 1243100000 | J59: 781550000 | K59: -1025900000 | L59: 0 | M59: 0 | N59: 2269000000
C60: 0 | D60: 0 | E60: 0 | F60: 0 | G60: 0 | H60: 0 | I60: 0 | J60: 0 | K60: 0 | L60: 0 | M60: 0 | N60: 0
A61: अंदाजपत्रक 'क' एकूण जमा | C61: 8946767866 | D61: 7825861170 | E61: 7804825131 | F61: 3285837194 | G61: 4189049981 | H61: 14807000000 | I61: 14807000000 | J61: 17442900000 | K61: 19142900000 | L61: 0 | M61: 4433000000 | N61: 97100000

Sheet C_Revenue_Expenditure
A1: योजनेतर खर्च तपशील
A2: विवरण | D2: नक्‍की आकडा | G2: मान्य अंदाज 2020-21 | H2: नवीन अंदाज
D3: 2017-18 | E3: 2018-19 | F3: 2019-20 | H3: 2021-22
A5: १. पाणीपुरवठा | D5: 0 | E5: 0 | F5: 0 | G5: 0 | H5: 0
A6: क. पाणीपुरवठा | D6: 0 | E6: 0 | F6: 0 | G6: 0 | H6: 0
A7: १. मध्यवर्ती कार्यालय, कायम सेवकवर्ग वेतन | B7: XE12A101A | D7: 23580337 | E7: 21639240 | F7: 22930820 | G7: 23300000 | H7: 27500000
A8: २अ. कायम सेवकवर्ग वेतन | B8: XE12A101B | D8: 144923511 | E8: 133028605 | F8: 143995350 | G8: 140000000 | H8: 160000000
A9: २ब. कायम सेवकवर्ग वेतन (वि.का.) | B9: XE12A###A | D9: 9860217 | E9: 8092170 | F9: 4911867 | G9: 15000000 | H9: 7000000
A10: ३. संकीर्ण | B10: XE12A103 | D10: 650931 | E10: 446243 | F10: 241045 | G10: 900000 | H10: 600000
A11: ४. पाण्याची किंमत (पर्वती पंपिंग स्टेशन) | B11: XE12A104 | D11: 319936464 | E11: 793046040 | F11: 714875404 | G11: 729000000 | H11: 790000000
A12: ५. पाणी शुद्ध करणे व तद्‌नुषंगिक कामे करणे | B12: XE12A105 | D12: 58867962 | E12: 50205650 | F12: 67013632 | G12: 64800000 | H12: 67500000
A13: ६. प्रयोगशाळा देखभाल खर्च | B13: XE12A106 | D13: 227793 | E13: 0 | F13: 881357 | G13: 1080000 | H13: 1500000
A14: ७-अ. पंपिंग वीज खर्च | B14: XE12A107 | D14: 601043722 | E14: 693640000 | F14: 778342594 | G14: 792000000 | H14: 801200000
A15: ९. कोठी इतर साहित्य खर्च | B15: XE12A109 | D15: 1189931 | E15: 340813 | F15: 697066 | G15: 2250000 | H15: 1500000
A16: १२. पर्वती जलकेंद्रातील यंत्रसामुग्रीवरील घसारा (मु.ले.) | B16: XE12A112 | D16: 190000 | E16: 215000 | F16: 0 | G16: 0 | H16: 0
A17: १४. जलप्रदूषण प्रतिबंधक खर्च | B17: XE12A115 | D17: 2007642 | E17: 0 | F17: 0 | G17: 2700000 | H17: 2500000
A18: १८. जलकेंद्र पाण्याच्या टाक्या येथे प्रकाश व्यवस्था व दूरध्वनी व्यवस्था | B18: XE12A120 | D18: 0 | E18: 0 | F18: 0 | G18: 900000 | H18: 500000
... A38: पर्वती जलकेंद्र प्रयोगशाळा येथे पाणी तपासणीसाठी लागणारी विविध उपकरणे व तद्‌नुषंगिक साहित्य खरेदी करणे | B38: XE12A146 | D38: 359999 | E38: 0 | F38: 328798 | G38: 0 | H38: 0
A39: क. बेरीज | D39: 1278265818 | E39: 1799104371 | F39: 1835097980 | G39: 1981945000 | H39: 1994500000
D40: 0 | E40: 0 | F40: 0 | G40: 0 | H40: 0
A41: ख१. नळ खाते (स्वारगेट विभाग) | D41: 0 | E41: 0 | F41: 0 | G41: 0 | H41: 0
A42: १. कायम सेवक वर्ग वेतन | B42: XE12B101A | D42: 215760319 | E42: 221769160 | F42: 228669863 | G42: 244000000 | H42: 270000000
A43: २. संकीर्ण | B43: XE12B102 | D43: 652480 | E43: 463550 | F43: 323698 | G43: 648000 | H43: 300000
A44: ४. शहरांतील / नव्याने समाविष्ट गावांतील सर्व व्हॉल्व्हज्‌ चालू व बंद करणे | B44: XE12B107 | D44: 36455792 | E44: 39585979 | F44: 61215355 | G44: 47250000 | H44: 60000000
A45: ८. टँकरने पाणीपुरवठा करणे | B45: XE12B111 | D45: 9305117 | E45: 14825987 | F45: 26968695 | G45: 19800000 | H45: 22000000
A46: ९. कोठी व इतर साहित्य खरेदी | B46: XE12B112 | D46: 20282433 | E46: 17886533 | F46: 19658619 | G46: 27000000 | H46: 20000000
A47: १०. देखभाल दुरुस्ती : नळदुरुस्ती व स्वच्छता तातडीच्या दुरुस्त्या चेंबर करणे, आर.सी.सी, कव्हर बसविणे व तदनुषंगिक कामे करणे | B47: XE12B113 | D47: 45376228 | E47: 47904841 | F47: 45727778 | G47: 50400000 | H47: 52000000
A48: ११. टाक्‍यांची दुरुस्ती | B48: XE12B114 | D48: 719282 | E48: 0 | F48: 0 | G48: 926100 | H48: 0
A49: पाणीपुरवठा विभागाकडील देखभाल दुरूस्तीची कामे (यादी X1) | B49: XE12B115# | D49: 9880350 | E49: 2634964 | F49: 0 | G49: 30700000 | H49: 36000000
D50: 0 | E50: 0 | F50: 0 | G50: 0 | H50: 0
A51: ख१. बेरीज | D51: 338432001 | E51: 345071014 | F51: 382564008 | G51: 420724100 | H51: 460300000
D52: 0 | E52: 0 | F52: 0 | G52: 0 | H52: 0
A53: ख२. नळ खाते (विभागीय कार्यालय) | D53: 0 | E53: 0 | F53: 0 | G53: 0 | H53: 0
A54: १. कायम सेवकवर्ग वेतन | B54: XE12B###A | D54: 31495599 | E54: 23964490 | F54: 22633204 | G54: 40000000 | H54: 27000000
A55: क्षेत्रीय कार्यालयाने करावयाची योजनेतर कामे | B55: XE12B301/W6-# | D55: 0 | E55: 943661 | F55: 2313036 | G55: 0 | H55: 1000000
A56: क्षेत्रीय कार्यालयाने नागरिकांच्या सहभागातून करावयाची योजनेतर कामे | B56: XE12B302/C6-# | D56: 2161144 | E56: 2817441 | F56: 4296733 | G56: 10300000 | H56: 4300000
D57: 0 | E57: 0 | F57: 0 | G57: 0 | H57: 0
A58: ख२. बेरीज | D58: 33656743 | E58: 27725592 | F58: 29242973 | G58: 50300000 | H58: 32300000
D59: 0 | E59: 0 | F59: 0 | G59: 0 | H59: 0
A60: ख. एकूण बेरीज | D60: 372088744 | E60: 372796606 | F60: 411806981 | G60: 471024100 | H60: 492600000
D61: 0 | E61: 0 | F61: 0 | G61: 0 | H61: 0
A62: ग. पाणीमापके | D62: 0 | E62: 0 | F62: 0 | G62: 0 | H62: 0
A63: १. पाणीमापके दुरुस्ती | B63: XE12C101 | D63: 0 | E63: 0 | F63: 0 | G63: 216000 | H63: 250000
A64: ३. संगणक यंत्रासाठी तयार करावयाच्या फॉर्मचा मुशाहिरा | B64: XE12C103 | D64: 151380 | E64: 0 | F64: 0 | G64: 360000 | H64: 400000
A65: ४. मीटर बीले वाटप करणे | B65: XE12C104 | D65: 0 | E65: 0 | F65: 0 | G65: 288000 | H65: 350000
D66: 0 | E66: 0 | F66: 0 | G66: 0 | H66: 0
A67: ग. बेरीज | D67: 151380 | E67: 0 | F67: 0 | G67: 864000 | H67: 1000000
D68: 0 | E68: 0 | F68: 0 | G68: 0 | H68: 0
A69: च. मनपा सेवकांना द्यावयाचा महागाईभत्ता | B69: XE12F101 | D69: 2318349 | E69: 1822664 | F69: 0 | G69: 20000000 | H69: 20000000
A70: 7व्या वेतनआयोगापोटी द्यावयाच्या फरकाची रक्कम | B70: XE12G101 | D70: 0 | E70: 0 | F70: 0 | G70: 50000000 | H70: 100000000
A71: ज. सानुग्रह अनुदान | B71: XE12H101 | D71: 38967247 | E71: 39452188 | F71: 4326522 | G71: 60000000 | H71: 90000000
A72: झ. मनपा सेवकांना प्रवासभत्ता सवलतीसाठी द्यावयाची रक्कम | B72: XE12I101 | D72: 86000 | E72: 317000 | F72: 422500 | G72: 20000000 | H72: 20000000
A73: थ. सेवानिवृत्ती वेतन व तोषदान | B73: XE12K101 | D73: 200000000 | E73: 184000000 | F73: 200000000 | G73: 300000000 | H73: 400000000
A74: प. पेट्रोल, डिझेल, टायर्स, सुटे भाग, देखभाल, दुरुस्ती | B74: XE12M101 | D74: 4987489 | E74: 4593077 | F74: 3914914 | G74: 9000000 | H74: 4000000
A75: ज्ञ१. कर्ज उभारण्याचा खर्च, कर्जाचे हप्ते व व्याज (मु.ले.) | B75: XE12Z101 | D75: 100656190 | E75: 152047800 | F75: 152047800 | G75: 751800000 | H75: 731800000
D76: 0 | E76: 0 | F76: 0 | G76: 0 | H76: 0
A77: १. पाणीपुरवठा एकूण बेरीज | D77: 1997521217 | E77: 2554133706 | F77: 2607616697 | G77: 3664633100 | H77: 3853900000
D78: 0 | E78: 0 | F78: 0 | G78: 0 | H78: 0
A79: १अ. पुणे लष्कर व खडकी पाणीपुरवठा | D79: 0 | E79: 0 | F79: 0 | G79: 0 | H79: 0
A80: क१. लष्कर पाणीपुरवठा | D80: 0 | E80: 0 | F80: 0 | G80: 0 | H80: 0
A81: १. कायम सेवकवर्ग वेतन | B81: XE12N101A | D81: 171815479 | E81: 164571931 | F81: 167040544 | G81: 184100000 | H81: 203000000
A82: २. संकीर्ण | B82: XE12N102 | D82: 570212 | E82: 339066 | F82: 437157 | G82: 900000 | H82: 600000
A83: ३. पाण्याची किंमत | B83: XE12N103 | D83: 47175046 | E83: 500000000 | F83: 100000000 | G83: 58500000 | H83: 63500000
A84: ४. पाणी शुद्ध करणे, तद्‌नुषंगिक कामे करणे | B84: XE12N104 | D84: 6120000 | E84: 9199955 | F84: 8461451 | G84: 10800000 | H84: 11000000
A85: ५. प्रयोगशाळा सँपल टेस्टींगसाठी होणारा खर्च | B85: XE12N105 | D85: 720000 | E85: 0 | F85: 0 | G85: 620000 | H85: 700000
A86: ६. पंपिंग वीज खर्च | B86: XE12N106 | D86: 179699445 | E86: 250891228 | F86: 199528930 | G86: 220500000 | H86: 230000000
A87: ८. कोठी व इतर साहित्य खर्च | B87: XE12N108 | D87: 422 | E87: 452573 | F87: 615580 | G87: 900000 | H87: 0
A88: ९. पंपाचे डिझेल इंजिनसाठी व इतर इंजिनसाठी लागणारे तेल | B88: XE12N109 | D88: 330100 | E88: 0 | F88: 0 | G88: 360000 | H88: 500000
A89: १३. पाणीपुरवठा केंद्र भवनाची देखभाल व दुरुस्ती | B89: XE12N117 | D89: 0 | E89: 0 | F89: 400000 | G89: 1800000 | H89: 2000000
A90: १६. पुणे लष्कर पाणीपुरवठा हद्दीतील व्हॉल्व्ह चालू करणे व बंद करणे | B90: XE12N120 | D90: 21234286 | E90: 27371424 | F90: 31291384 | G90: 36000000 | H90: 40000000
A91: १७. टँकरने पाणीपुरवठा करणे | B91: XE12N121 | D91: 13382460 | E91: 23044690 | F91: 25299474 | G91: 26100000 | H91: 30000000
A92: १९. देखभाल दुरुस्ती (यंत्रसामुग्री सुटे भाग, ट्रान्सफॉर्मर ऑईल, सर्किट ब्रेकर्स, विुत उपकरणांची देखभाल दुरूस्ती, बागकाम, भवनांची देखभाल दुरूस्ती, दिवाबत्ती, नळदुरूस्त्या व इतर दुरूस्त्या) | B92: XE12N123 | D92: 35381571 | E92: 21084056 | F92: 27888464 | G92: 27000000 | H92: 30000000
... A97: पुणे मनपा लष्कर जलकेंद्र ते कोंढवा बकरी हिल टाकी पर्यंत नवजलनालिका टाकण्यासाठी संरक्षक विभाग पुणे लष्कर बोर्डाची लायसेन्स फी व अनामत भरणे | B97: XE12N128 | D97: 0 | E97: 0 | F97: 11669156 | G97: 0 | H97: 0
D98: 0 | E98: 0 | F98: 0 | G98: 0 | H98: 0
A99: क१. लष्कर पाणीपुरवठा बेरीज | D99: 485206153 | E99: 1015240125 | F99: 595180181 | G99: 589180000 | H99: 634950000
D100: 0 | E100: 0 | F100: 0 | G100: 0 | H100: 0
A101: क२. लष्कर पाणीपुरवठा (विभागीय कार्यालय) | D101: 0 | E101: 0 | F101: 0 | G101: 0 | H101: 0
A102: १. कायम सेवक वर्ग वेतन | B102: XE12N###A | D102: 5087378 | E102: 5709141 | F102: 5324501 | G102: 10000000 | H102: 6500000
D103: 0 | E103: 0 | F103: 0 | G103: 0 | H103: 0
A104: क२. बेरीज | D104: 5087378 | E104: 5709141 | F104: 5324501 | G104: 10000000 | H104: 6500000
D105: 0 | E105: 0 | F105: 0 | G105: 0 | H105: 0
A106: क. एकूण बेरीज | D106: 490293531 | E106: 1020949266 | F106: 600504682 | G106: 599180000 | H106: 641450000
D107: 0 | E107: 0 | F107: 0 | G107: 0 | H107: 0
A108: ख१. खडकी व SNDT चतुःश्रृंगी पाणीपुरवठा | D108: 0 | E108: 0 | F108: 0 | G108: 0 | H108: 0
A109: १. कायम सेवकवर्ग वेतन | B109: XE12P101A | D109: 18694524 | E109: 16102534 | F109: 20391226 | G109: 19000000 | H109: 23500000
A110: २. संकीर्ण | B110: XE12P102 | D110: 96474 | E110: 25737 | F110: 40175 | G110: 216000 | H110: 300000
A111: ३. पाण्याची किंमत | B111: XE12P103 | D111: 24942539 | E111: 18145010 | F111: 0 | G111: 31500000 | H111: 33000000
A112: ४. पाणी शुद्ध करणे व तद्‌नुषंगिक कामे करणे | B112: XE12P104 | D112: 239250 | E112: 588800 | F112: 2080000 | G112: 2700000 | H112: 3000000
A113: ६. पंपिंग वीज खर्च | B113: XE12P106 | D113: 12275180 | E113: 13798530 | F113: 16990087 | G113: 17550000 | H113: 20000000
A114: १०. कोठी व इतर साहित्य खर्च | B114: XE12P110 | D114: 7562 | E114: 1523759 | F114: 1214404 | G114: 2700000 | H114: 0
A115: १७. टाक्‍यांची दुरुस्ती | B115: XE12P119 | D115: 674254 | E115: 897502 | F115: 0 | G115: 900000 | H115: 1000000
A116: १८. देखभाल दुरुस्त्या : नळदुरुस्ती व तातडीच्या दुरुस्त्या इत्यादी | B116: XE12P120 | D116: 28996371 | E116: 38291485 | F116: 32071152 | G116: 48600000 | H116: 49000000
A117: १९. व्हॉल्व्ह सोड बंद करणे | B117: XE12P121 | D117: 11458654 | E117: 15013778 | F117: 25083299 | G117: 18000000 | H117: 20000000
A118: २०. टँकरने पाणीपुरवठा करणे | B118: XE12P122 | D118: 21662258 | E118: 20543132 | F118: 25359127 | G118: 21600000 | H118: 21500000
D119: 0 | E119: 0 | F119: 0 | G119: 0 | H119: 0
A120: ख. एकूण बेरीज | D120: 119047066 | E120: 124930267 | F120: 123229470 | G120: 162766000 | H120: 171300000
D121: 0 | E121: 0 | F121: 0 | G121: 0 | H121: 0
A122: 7व्या वेतनआयोगापोटी द्यावयाच्या फरकाची रक्कम | B122: XE12P118C | D122: 0 | E122: 0 | F122: 0 | G122: 50000000 | H122: 100000000
A123: ज सानुग्रह अनुदान | B123: XE12P118D | D123: 11817540 | E123: 12052729 | F123: 48704528 | G123: 70000000 | H123: 90000000
A124: च मनपा सेवकांना द्यावयाचा महागाई भत्ता | B124: XE12P118E | D124: 2071765 | E124: 1146221 | F124: 4020692 | G124: 10000000 | H124: 10000000
...

Sheet WO_Work21_MC
A1: उप आयुक्त विभाग क्र. : | B1: 1 | C1: 1 | D1: 1 | E1: 2 | F1: 2 | G1: 2 | H1: 3 | I1: 3 | J1: 3 | K1: 4 | L1: 4 | M1: 4 | N1: 5 | O1: 5 | P1: 5
A2: विवरण | B2: नगररोड - वडगावशेरी | C2: येरवडा - कळस - धानोरी | D2: ढोलेपाटील | E2: औंध - बाणेर | F2: शिवाजीनगर - घोले रोड | G2: कोथरूड - बावधन | H2: धनकवडी - सहकारनगर | I2: सिंहगड रोड | J2: वारजे - कर्वेनगर | K2: हडपसर - मुंढवा | L2: वानवडी - रामटेकडी | M2: कोंढवा - येवलेवाडी | N2: कसबा - विश्रामबागवाडा | O2: भवानी पेठ | P2: बिबवेवाडी | Q2: एकूण
A4: अंदाजपत्रकातील तरतुदींचा विभागवार वाटप तक्ता - अंदाजपत्रक 'अ'
A6: १. मुख्य देखरेख वसुली
A7: र. विभागीय कार्यालये | B7: RE11W111A | C7: RE11W114A | D7: RE11W110A | E7: RE11W112A | F7: RE11W103A | G7: RE11W104A | H7: RE11W115A | I7: RE11W105A | J7: RE11W113A | K7: RE11W109A | L7: RE11W116A | M7: RE11W106A | N7: RE11W102A | O7: RE11W108A | P7: RE11W107A
A8: ३. क्षेत्रीय कार्यालये कायम सेवकवर्ग वेतन | B8: 64247000 | C8: 22276000 | D8: 30743000 | E8: 42872000 | F8: 28581000 | G8: 28581000 | H8: 35546000 | I8: 49957000 | J8: 46354000 | K8: 35546000 | L8: 35546000 | M8: 35546000 | N8: 42872000 | O8: 42872000 | P8: 28461000 | Q8: 570000000
B9: RE11W111B | C9: RE11W114B | D9: RE11W110B | E9: RE11W112B | F9: RE11W103B | G9: RE11W104B | H9: RE11W115B | I9: RE11W105B | J9: RE11W113B | K9: RE11W109B | L9: RE11W116B | M9: RE11W106B | N9: RE11W102B | O9: RE11W108B | P9: RE11W107B
A10: ४. क्षेत्रीय कार्यालये संकीर्ण | B10: 432000 | C10: 432000 | D10: 432000 | E10: 432000 | F10: 432000 | G10: 432000 | H10: 432000 | I10: 432000 | J10: 432000 | K10: 432000 | L10: 432000 | M10: 432000 | N10: 432000 | O10: 432000 | P10: 432000 | Q10: 6480000
B11: RE11W111E | C11: RE11W114E | D11: RE11W110E | E11: RE11W112E | F11: RE11W103E | G11: RE11W104E | H11: RE11W115E | I11: RE11W105E | J11: RE11W113E | K11: RE11W109E | L11: RE11W116E | M11: RE11W106E | N11: RE11W102E | O11: RE11W108E | P11: RE11W107E
A12: ५. प्रभाग समिती चहापान खर्च | B12: 45000 | C12: 45000 | D12: 45000 | E12: 45000 | F12: 45000 | G12: 45000 | H12: 45000 | I12: 45000 | J12: 45000 | K12: 45000 | L12: 45000 | M12: 45000 | N12: 45000 | O12: 45000 | P12: 45000 | Q12: 675000
B13: RE11W111G | C13: RE11W114G | D13: RE11W110G | E13: RE11W112G | F13: RE11W103G | G13: RE11W104G | H13: RE11W115G | I13: RE11W105G | J13: RE11W113G | K13: RE11W109G | L13: RE11W116G | M13: RE11W106G | N13: RE11W102G | O13: RE11W108G | P13: RE11W107G
A14: समाविष्ट गावांमध्ये देखभाल दुरूस्तीची कामे करणे (पथ, विद्युत, भवन, पाणीपुरवठा, मलनिःसारण इ.) | B14: 3600000 | H14: 7200000 | I14: 3600000 | J14: 7200000 | K14: 14400000 | M14: 3600000 | Q14: 39600000
A16: ४. झोपडपट्टी निर्मूलन व पुनर्वसन
A17: ख२. सबइंजिनियर (हेल्थ) (वि.का.) | B17: RE14B211A | C17: RE14B214A | D17: RE14B210A | E17: RE14B212A | F17: RE14B203A | G17: RE14B204A | H17: RE14B215A | I17: RE14B205A | J17: RE14B213A | K17: RE14B209A | L17: RE14B216A | M17: RE14B206A | N17: RE14B202A | O17: RE14B208A | P17: RE14B207A
A18: सार्वजनिक/सुलभ शौचालय दुरूस्ती, मुतार्‍या दुरूस्ती कामे करणे | B18: 1800000 | C18: 1800000 | D18: 1800000 | E18: 1800000 | F18: 1800000 | G18: 1800000 | H18: 1800000 | I18: 1800000 | J18: 1800000 | K18: 1800000 | L18: 1800000 | M18: 1800000 | N18: 1800000 | O18: 1800000 | P18: 1800000 | Q18: 27000000
B19: RE14B211B | C19: RE14B214B | D19: RE14B210B | E19: RE14B212B | F19: RE14B203B | G19: RE14B204B | H19: RE14B215B | I19: RE14B205B | J19: RE14B213B | K19: RE14B209B | L19: RE14B216B | M19: RE14B206B | N19: RE14B202B | O19: RE14B208B | P19: RE14B207B
A20: काँक्रीटीकरणाची व फरशीची कामे / पेव्हींगची कामे व देखभाल दुरूस्ती करणे | B20: 972000 | C20: 954000 | D20: 954000 | E20: 936000 | F20: 936000 | G20: 1008000 | H20: 936000 | I20: 1008000 | J20: 936000 | K20: 936000 | L20: 1008000 | M20: 936000 | N20: 972000 | O20: 954000 | P20: 954000 | Q20: 14400000
B21: RE14B211C | C21: RE14B214C | D21: RE14B210C | E21: RE14B212C | F21: RE14B203C | G21: RE14B204C | H21: RE14B215C | I21: RE14B205C | J21: RE14B213C | K21: RE14B209C | L21: RE14B216C | M21: RE14B206C | N21: RE14B202C | O21: RE14B208C | P21: RE14B207C
A22: जुन्या ड्रेनेज लाईन बदलणे व दुरूस्ती करणे | B22: 972000 | C22: 954000 | D22: 954000 | E22: 936000 | F22: 936000 | G22: 1008000 | H22: 936000 | I22: 1008000 | J22: 936000 | K22: 936000 | L22: 1008000 | M22: 936000 | N22: 972000 | O22: 954000 | P22: 954000 | Q22: 14400000
B23: RE14B211D | C23: RE14B214D | D23: RE14B210D | E23: RE14B212D | F23: RE14B203D | G23: RE14B204D | H23: RE14B215D | I23: RE14B205D | J23: RE14B213D | K23: RE14B209D | L23: RE14B216D | M23: RE14B206D | N23: RE14B202D | O23: RE14B208D | P23: RE14B207D
A24: ड्रेनेज लाईन व चेंबर साफसफाई करणे | B24: 1044000 | C24: 1044000 | D24: 1067040 | E24: 1008000 | F24: 1008000 | G24: 1139040 | H24: 1008000 | I24: 1139040 | J24: 1008000 | K24: 1296000 | L24: 1008000 | M24: 851040 | N24: 1044000 | O24: 1044000 | P24: 1067040 | Q24: 15775200
B25: RE14B211E | C25: RE14B214E | D25: RE14B210E | E25: RE14B212E | F25: RE14B203E | G25: RE14B204E | H25: RE14B215E | I25: RE14B205E | J25: RE14B213E | K25: RE14B209E | L25: RE14B216E | M25: RE14B206E | N25: RE14B202E | O25: RE14B208E | P25: RE14B207E
A26: देखभाल दुरुस्तीसाठी साहित्य खरेदी - पुरविणे व बसविणे | B26: 288000 | C26: 288000 | D26: 288000 | E26: 288000 | F26: 288000 | G26: 288000 | H26: 288000 | I26: 288000 | J26: 288000 | K26: 288000 | L26: 288000 | M26: 288000 | N26: 288000 | O26: 288000 | P26: 288000 | Q26: 4320000
A28: ७. आरोग्य
A29: लोकारोग्य (विभागीय कार्यालय) | B29: RE17F211A | C29: RE17F214A | D29: RE17F210A | E29: RE17F212A | F29: RE17F203A | G29: RE17F204A | H29: RE17F215A | I29: RE17F205A | J29: RE17F213A | K29: RE17F209A | L29: RE17F216A | M29: RE17F206A | N29: RE17F202A | O29: RE17F208A | P29: RE17F207A
A30: १. कायम सेवकवर्ग वेतन | B30: 12740000 | C30: 6712000 | D30: 9726000 | E30: 4521000 | F30: 8219000 | G30: 3014000 | H30: 4795000 | I30: 9041000 | J30: 3014000 | K30: 7534000 | L30: 10548000 | M30: 6712000 | N30: 22603000 | O30: 5205000 | P30: 5616000 | Q30: 120000000
A32: ९. पथांची झाडलोट, कचरावाहतूक इ.
A33: क२. पथांची झाडलोट (विभा. कार्या.) | B33: RE19A211A | C33: RE19A214A | D33: RE19A210A | E33: RE19A212A | F33: RE19A203A | G33: RE19A204A | H33: RE19A215A | I33: RE19A205A | J33: RE19A213A | K33: RE19A209A | L33: RE19A216A | M33: RE19A206A | N33: RE19A202A | O33: RE19A208A | P33: RE19A207A
A34: १. कायम सेवकवर्ग वेतन | B34: 80000000 | C34: 80000000 | D34: 80000000 | E34: 80000000 | F34: 80000000 | G34: 80000000 | H34: 80000000 | I34: 80000000 | J34: 80000000 | K34: 80000000 | L34: 80000000 | M34: 80000000 | N34: 80000000 | O34: 80000000 | P34: 80000000 | Q34: 1200000000
B35: RE19A211C | C35: RE19A214C | D35: RE19A210C | E35: RE19A212C | F35: RE19A203C | G35: RE19A204C | H35: RE19A215C | I35: RE19A205C | J35: RE19A213C | K35: RE19A209C | L35: RE19A216C | M35: RE19A206C | N35: RE19A202C | O35: RE19A208C | P35: RE19A207C
A36: घंटागाड्या,सायकल रिक्षा पुरविणे व दुरूस्ती,बकेट खरेदी करणे, आरोग्यकोठ्या दुरूस्त करणे | B36: 504000 | C36: 504000 | D36: 432000 | E36: 468000 | F36: 468000 | G36: 504000 | H36: 468000 | I36: 504000 | J36: 468000 | K36: 504000 | L36: 468000 | M36: 468000 | N36: 504000 | O36: 504000 | P36: 432000 | Q36: 7200000
B37: RE19A211D | C37: RE19A214D | D37: RE19A210D | E37: RE19A212D | F37: RE19A203D | G37: RE19A204D | H37: RE19A215D | I37: RE19A205D | J37: RE19A213D | K37: RE19A209D | L37: RE19A216D | M37: RE19A206D | N37: RE19A202D | O37: RE19A208D | P37: RE19A207D
A38: आऊटसोर्सिंगने कचरा संदर्भात कामे करून घेणे | B38: 102500000 | C38: 80700000 | D38: 48800000 | E38: 94900000 | F38: 32200000 | G38: 56400000 | H38: 75000000 | I38: 68000000 | J38: 76200000 | K38: 102500000 | L38: 70500000 | M38: 59200000 | N38: 14200000 | O38: 0 | P38: 51200000 | Q38: 932300000
B39: RE19A211F | C39: RE19A214F | D39: RE19A210F | E39: RE19A212F | F39: RE19A203F | G39: RE19A204F | H39: RE19A215F | I39: RE19A205F | J39: RE19A213F | K39: RE19A209F | L39: RE19A216F | M39: RE19A206F | N39: RE19A202F | O39: RE19A208F | P39: RE19A207F
A40: स्वच्छ सर्वेक्षण संबंधित कामे करणे | B40: 1080000 | C40: 1080000 | D40: 1080000 | E40: 1080000 | F40: 1080000 | G40: 1080000 | H40: 1080000 | I40: 1080000 | J40: 1080000 | K40: 1080000 | L40: 1080000 | M40: 1080000 | N40: 1080000 | O40: 1080000 | P40: 1080000 | Q40: 16200000
B41: RE19A211G | C41: RE19A214G | D41: RE19A210G | E41: RE19A212G | F41: RE19A203G | G41: RE19A204G | H41: RE19A215G | I41: RE19A205G | J41: RE19A213G | K41: RE19A209G | L41: RE19A216G | M41: RE19A206G | N41: RE19A202G | O41: RE19A208G | P41: RE19A207G
A42: Third Party Quality Aasurance करिता सल्लागार फी देणे | B42: 665000 | C42: 665000 | D42: 670000 | E42: 670000 | F42: 665000 | G42: 665000 | H42: 665000 | I42: 670000 | J42: 665000 | K42: 670000 | L42: 665000 | M42: 665000 | N42: 670000 | O42: 665000 | P42: 665000 | Q42: 10000000
A44: ख२. कचरा वाहतूक (विभा. कार्या.) | B44: RE19B211A | C44: RE19B214A | D44: RE19B210A | E44: RE19B212A | F44: RE19B203A | G44: RE19B204A | H44: RE19B215A | I44: RE19B205A | J44: RE19B213A | K44: RE19B209A | L44: RE19B216A | M44: RE19B206A | N44: RE19B202A | O44: RE19B208A | P44: RE19B207A
A45: १. कायम सेवकवर्ग वेतन | B45: 58036000 | C45: 57928000 | D45: 58036000 | E45: 58036000 | F45: 57928000 | G45: 58036000 | H45: 58036000 | I45: 58036000 | J45: 57928000 | K45: 58036000 | L45: 57928000 | M45: 58036000 | N45: 58036000 | O45: 58036000 | P45: 57928000 | Q45: 870000000
A46: ग२. मैला व मैलापाणी वाहतूक (आ.प्र.) | B46: RE19C211A | C46: RE19C214A | D46: RE19C210A | E46: RE19C212A | F46: RE19C203A | G46: RE19C204A | H46: RE19C215A | I46: RE19C205A | J46: RE19C213A | K46: RE19C209A | L46: RE19C216A | M46: RE19C206A | N46: RE19C202A | O46: RE19C208A | P46: RE19C207A
A47: १. कायम सेवकवर्ग वेतन | B47: 27392000 | C47: 27282000 | D47: 27282000 | E47: 27282000 | F47: 27282000 | G47: 27392000 | H47: 27282000 | I47: 27392000 | J47: 27282000 | K47: 27392000 | L47: 27282000 | M47: 27392000 | N47: 27392000 | O47: 27392000 | P47: 27282000 | Q47: 410000000
A49: घ२. भुयारी गटारे, कुंड्या व चेंबर्स स्वच्छता | B49: RE19D211A | C49: RE19D214A | D49: RE19D210A | E49: RE19D212A | F49: RE19D203A | G49: RE19D204A | H49: RE19D215A | I49: RE19D205A | J49: RE19D213A | K49: RE19D209A | L49: RE19D216A | M49: RE19D206A | N49: RE19D202A | O49: RE19D208A | P49: RE19D207A
A50: १. कायम सेवकवर्ग वेतन | B50: 9705000 | C50: 9705000 | D50: 9590000 | E50: 9705000 | F50: 9590000 | G50: 9705000 | H50: 9590000 | I50: 9705000 | J50: 9705000 | K50: 9705000 | L50: 9590000 | M50: 9705000 | N50: 9705000 | O50: 9705000 | P50: 9590000 | Q50: 145000000
A52: च२. झोपडपट्टी वस्त्यांची स्वच्छता व साफसफाईची कामे (विभा.कार्या.)
B53: RE19E211A | C53: RE19E214A | D53: RE19E210A | E53: RE19E212A | F53: RE19E203A | G53: RE19E204A | H53: RE19E215A | I53: RE19E205A | J53: RE19E213A | K53: RE19E209A | L53: RE19E216A | M53: RE19E206A | N53: RE19E202A | O53: RE19E208A | P53: RE19E207A
A54: १. कायम सेवकवर्ग वेतन | B54: 18813000 | C54: 18594000 | D54: 18593000 | E54: 18594000 | F54: 18593000 | G54: 18813000 | H54: 18593000 | I54: 18594000 | J54: 18813000 | K54: 18813000 | L54: 18593000 | M54: 18594000 | N54: 18594000 | O54: 18813000 | P54: 18593000 | Q54: 280000000
A56: १०. पथ सुधारणा (विशेष कार्याधिकारी)
A57: क२. पथ सुधारणा (विशेष कार्याधिकारी) | B57: RE20A211A | C57: RE20A214A | D57: RE20A210A | E57: RE20A212A | F57: RE20A203A | G57: RE20A204A | H57: RE20A215A | I57: RE20A205A | J57: RE20A213A | K57: RE20A209A | L57: RE20A216A | M57: RE20A206A | N57: RE20A202A | O57: RE20A208A | P57: RE20A207A
A58: १. कायम सेवकवर्ग वेतन | B58: 6667000 | C58: 6667000 | D58: 6666000 | E58: 6666000 | F58: 6667000 | G58: 6667000 | H58: 6667000 | I58: 6666000 | J58: 6667000 | K58: 6666000 | L58: 6667000 | M58: 6667000 | N58: 6666000 | O58: 6667000 | P58: 6667000 | Q58: 100000000
A59: ख२. पथ दुरुस्ती (विभागीय कार्यालय) | B59: RE20B211A | C59: RE20B214A | D59: RE20B210A | E59: RE20B212A | F59: RE20B203A | G59: RE20B204A | H59: RE20B215A | I59: RE20B205A | J59: RE20B213A | K59: RE20B209A | L59: RE20B216A | M59: RE20B206A | N59: RE20B202A | O59: RE20B208A | P59: RE20B207A
A60: पथांवरील राडारोडा उचलणे | B60: 1080000 | C60: 1080000 | D60: 1080000 | E60: 1080000 | F60: 1080000 | G60: 1080000 | H60: 1080000 | I60: 1080000 | J60: 1080000 | K60: 1080000 | L60: 1080000 | M60: 1080000 | N60: 1080000 | O60: 1080000 | P60: 1080000 | Q60: 16200000
B61: RE20B211B | C61: RE20B214B | D61: RE20B210B | E61: RE20B212B | F61: RE20B203B | G61: RE20B204B | H61: RE20B215B | I61: RE20B205B | J61: RE20B213B | K61: RE20B209B | L61: RE20B216B | M61: RE20B206B | N61: RE20B202B | O61: RE20B208B | P61: RE20B207B
A62: निरनिराळ्या पथावरील खड्‌डे दुरुस्ती करणे | B62: 1058400 | C62: 1058400 | D62: 1058400 | E62: 1058400 | F62: 1058400 | G62: 1058400 | H62: 1044000 | I62: 1087200 | J62: 1044000 | K62: 1296000 | L62: 1008000 | M62: 871200 | N62: 1058400 | O62: 1058400 | P62: 1058400 | Q62: 15876000
B63: RE20B211D | C63: RE20B214D | D63: RE20B210D | E63: RE20B212D | F63: RE20B203D | G63: RE20B204D | H63: RE20B215D | I63: RE20B205D | J63: RE20B213D | K63: RE20B209D | L63: RE20B216D | M63: RE20B206D | N63: RE20B202D | O63: RE20B208D | P63: RE20B207D
A64: पथावरील पुतळ्यांची स्वच्छता व दुरूस्ती करणे | B64: 142560 | C64: 216000 | D64: 216000 | E64: 180000 | F64: 180000 | G64: 214560 | H64: 190800 | I64: 192960 | J64: 190800 | K64: 215280 | L64: 144000 | M64: 215280 | N64: 216000 | O64: 216000 | P64: 142560 | Q64: 2872800
B65: RE20B211E | C65: RE20B214E | D65: RE20B210E | E65: RE20B212E | F65: RE20B203E | G65: RE20B204E | H65: RE20B215E | I65: RE20B205E | J65: RE20B213E | K65: RE20B209E | L65: RE20B216E | M65: RE20B206E | N65: RE20B202E | O65: RE20B208E | P65: RE20B207E
A66: साईन बोर्डस्‌ रंगविणे, रंगरंगोटी, रेलींगची कामे व डिव्हायडरची कामे करणे | B66: 1584000 | C66: 1548000 | D66: 1548000 | E66: 1548000 | F66: 1548000 | G66: 1584000 | H66: 1548000 | I66: 1584000 | J66: 1548000 | K66: 1800000 | L66: 1440000 | M66: 1440000 | N66: 1584000 | O66: 1548000 | P66: 1548000 | Q66: 23400000
B67: RE20B211F | C67: RE20B214F | D67: RE20B210F | E67: RE20B212F | F67: RE20B203F | G67: RE20B204F | H67: RE20B215F | I67: RE20B205F | J67: RE20B213F | K67: RE20B209F | L67: RE20B216F | M67: RE20B206F | N67: RE20B202F | O67: RE20B208F | P67: RE20B207F
A68: फूटपाथ दुरूस्ती करणे | B68: 1052640 | C68: 1051200 | D68: 1051200 | E68: 1044000 | F68: 1044000 | G68: 1067040 | H68: 1044000 | I68: 1067040 | J68: 1044000 | K68: 1296000 | L68: 1008000 | M68: 851040 | N68: 1051200 | O68: 1051200 | P68: 1052640 | Q68: 15775200
B69: RE20B211G | C69: RE20B214G | D69: RE20B210G | E69: RE20B212G | F69: RE20B203G | G69: RE20B204G | H69: RE20B215G | I69: RE20B205G | J69: RE20B213G | K69: RE20B209G | L69: RE20B216G | M69: RE20B206G | N69: RE20B202G | O69: RE20B208G | P69: RE20B207G
A70: पेव्हींग ब्लॉकची दुरूस्ती / कामे करणे | B70: 645120 | C70: 645120 | D70: 645120 | E70: 612000 | F70: 612000 | G70: 711360 | H70: 645120 | I70: 645120 | J70: 645120 | K70: 720000 | L70: 607680 | M70: 607680 | N70: 645120 | O70: 645120 | P70: 645120 | Q70: 9676800
B71: RE20B211J | C71: RE20B214J | D71: RE20B210J | E71: RE20B212J | F71: RE20B203J | G71: RE20B204J | H71: RE20B215J | I71: RE20B205J | J71: RE20B213J | K71: RE20B209J | L71: RE20B216J | M71: RE20B206J | N71: RE20B202J | O71: RE20B208J | P71: RE20B207J
A72: कोठीसाठी आवश्यक साहित्य पुरविणे व खरेदी करणे | B72: 273600 | C72: 279360 | D72: 273600 | E72: 252000 | F72: 252000 | G72: 322560 | H72: 275040 | I72: 276480 | J72: 275040 | K72: 275040 | L72: 276480 | M72: 275040 | N72: 273600 | O72: 279360 | P72: 273600 | Q72: 4132800
B73: RE20B211K | C73: RE20B214K | D73: RE20B210K | E73: RE20B212K | F73: RE20B203K | G73: RE20B204K | H73: RE20B215K | I73: RE20B205K | J73: RE20B213K | K73: RE20B209K | L73: RE20B216K | M73: RE20B206K | N73: RE20B202K | O73: RE20B208K | P73: RE20B207K
A74: किरकोळ दुरुस्तीची कामे मजुरांमार्फत करून घेणे | B74: 676800 | C74: 676800 | D74: 682560 | E74: 676800 | F74: 676800 | G74: 682560 | H74: 676800 | I74: 682560 | J74: 676800 | K74: 864000 | L74: 596160 | M74: 576000 | N74: 676800 | O74: 676800 | P74: 682560 | Q74: 10180800
B75: RE20B211L | C75: RE20B214L | D75: RE20B210L | E75: RE20B212L | F75: RE20B203L | G75: RE20B204L | H75: RE20B215L | I75: RE20B205L | J75: RE20B213L | K75: RE20B209L | L75: RE20B216L | M75: RE20B206L | N75: RE20B202L | O75: RE20B208L | P75: RE20B207L
A76: पावसाळी लाईन ६०० मि.मि.पर्यंत पाईप टाकणे/दुरूस्ती करणे व इतर अनुषंगिक कामे करणे | B76: 792000 | C76: 788400 | D76: 788400 | E76: 720000 | F76: 720000 | G76: 928800 | H76: 788400 | I76: 792000 | J76: 788400 | K76: 864000 | L76: 784800 | M76: 720000 | N76: 792000 | O76: 788400 | P76: 788400 | Q76: 11844000
B77: RE20B211M | C77: RE20B214M | D77: RE20B210M | E77: RE20B212M | F77: RE20B203M | G77: RE20B204M | H77: RE20B215M | I77: RE20B205M | J77: RE20B213M | K77: RE20B209M | L77: RE20B216M | M77: RE20B206M | N77: RE20B202M | O77: RE20B208M | P77: RE20B207M
A78: पावसाळी जाळ्या पुरविणे, बसविणे व दुरूस्ती करणे | B78: 648000 | C78: 648000 | D78: 659520 | E78: 648000 | F78: 648000 | G78: 659520 | H78: 648000 | I78: 659520 | J78: 648000 | K78: 648000 | L78: 659520 | M78: 648000 | N78: 648000 | O78: 648000 | P78: 659520 | Q78: 9777600
B79: RE20B211N | C79: RE20B214N | D79: RE20B210N | E79: RE20B212N | F79: RE20B203N | G79: RE20B204N | H79: RE20B215N | I79: RE20B205N | J79: RE20B213N | K79: RE20B209N | L79: RE20B216N | M79: RE20B206N | N79: RE20B202N | O79: RE20B208N | P79: RE20B207N
A80: काँक्रीटीकरण करणे / फरशी बसविणे व दुरूस्ती करणे | B80: 550800 | C80: 550800 | D80: 551520 | E80: 540000 | F80: 540000 | G80: 573120 | H80: 550800 | I80: 551520 | J80: 550800 | K80: 550800 | L80: 551520 | M80: 550800 | N80: 550800 | O80: 551520 | P80: 550800 | Q80: 8265600
B81: RE20B211P | C81: RE20B214P | D81: RE20B210P | E81: RE20B212P | F81: RE20B203P | G81: RE20B204P | H81: RE20B215P | I81: RE20B205P | J81: RE20B213P | K81: RE20B209P | L81: RE20B216P | M81: RE20B206P | N81: RE20B202P | O81: RE20B208P | P81: RE20B207P
A82: मुरूम पुरविणे व रस्ता दुरूस्त करणे | B82: 576000 | C82: 432000 | D82: 432000 | E82: 576000 | F82: 288000 | G82: 576000 | H82: 478800 | I82: 482400 | J82: 478800 | K82: 576000 | L82: 432000 | M82: 432000 | N82: 432000 | O82: 432000 | P82: 576000 | Q82: 7200000
A84: ग२. पथांवरील दिवाबत्ती (वि.कार्या.) | B84: RE20C211A | C84: RE20C214A | D84: RE20C210A | E84: RE20C212A | F84: RE20C203A | G84: RE20C204A | H84: RE20C215A | I84: RE20C205A | J84: RE20C213A | K84: RE20C209A | L84: RE20C216A | M84: RE20C206A | N84: RE20C202A | O84: RE20C208A | P84: RE20C207A
A85: कायम सेवकवर्ग वेतन | B85: 8031000 | C85: 8031000 | D85: 7938000 | E85: 8031000 | F85: 8031000 | G85: 7938000 | H85: 8031000 | I85: 8031000 | J85: 7938000 | K85: 8031000 | L85: 8031000 | M85: 7938000 | N85: 8031000 | O85: 8031000 | P85: 7938000 | Q85: 120000000
B86: RE20C211C | C86: RE20C214C | D86: RE20C210C | E86: RE20C212C | F86: RE20C203C | G86: RE20C204C | H86: RE20C215C | I86: RE20C205C | J86: RE20C213C | K86: RE20C209C | L86: RE20C216C | M86: RE20C206C | N86: RE20C202C | O86: RE20C208C | P86: RE20C207C
A87: रस्त्यावरील दिवे, देखभाल दुरूस्ती तसेच विद्युत विषयक आवश्यक कामे करणे | B87: 2700000 | C87: 2700000 | D87: 2700000 | E87: 2430000 | F87: 2430000 | G87: 3240000 | H87: 2700000 | I87: 2700000 | J87: 2700000 | K87: 3240000 | L87: 2700000 | M87: 2160000 | N87: 2700000 | O87: 2700000 | P87: 2700000 | Q87: 40500000
B88: RE20C211D | C88: RE20C214D | D88: RE20C210D | E88: RE20C212D | F88: RE20C203D | G88: RE20C204D | H88: RE20C215D | I88: RE20C205D | J88: RE20C213D | K88: RE20C209D | L88: RE20C216D | M88: RE20C206D | N88: RE20C202D | O88: RE20C208D | P88: RE20C207D
A89: किरकोळ दुरुस्तीची कामे मजुरांमार्फत करून घेणे | B89: 385200 | C89: 385200 | D89: 391680 | E89: 360000 | F89: 360000 | G89: 442080 | H89: 387360 | I89: 387360 | J89: 387360 | K89: 504000 | L89: 360000 | M89: 298080 | N89: 385200 | O89: 385200 | P89: 391680 | Q89: 5810400
A92: १२. भवने, भूमी व मनपा वसाहती यांची व्यवस्था
B93: RE22C211B | C93: RE22C214B | D93: RE22C210B | E93: RE22C212B | F93: RE22C203B | G93: RE22C204B | H93: RE22C215B | I93: RE22C205B | J93: RE22C213B | K93: RE22C209B | L93: RE22C216B | M93: RE22C206B | N93: RE22C202B | O93: RE22C208B | P93: RE22C207B
A94: भवन दुरुस्ती (शाळा, दवाखाने, मार्केट, क्षेत्रिय कार्यालय, मनपा वसाहती इ.) | B94: 1512000 | C94: 1296000 | D94: 1254240 | E94: 1332000 | F94: 1332000 | G94: 1398300 | H94: 1353600 | I94: 1355060 | J94: 1353600 | K94: 1902300 | L94: 1296000 | M94: 864000 | N94: 1512000 | O94: 1296000 | P94: 1254300 | Q94: 20311400
B95: RE22C211C | C95: RE22C214C | D95: RE22C210C | E95: RE22C212C | F95: RE22C203C | G95: RE22C204C | H95: RE22C215C | I95: RE22C205C | J95: RE22C213C | K95: RE22C209C | L95: RE22C216C | M95: RE22C206C | N95: RE22C202C | O95: RE22C208C | P95: RE22C207C
A96: इतर भवन दुरुस्ती (घाट, स्मशानभूमी, विसर्जन हौद इ.) | B96: 1296000 | C96: 1008000 | D96: 961920 | E96: 1088640 | F96: 1088640 | G96: 1088640 | H96: 1088640 | I96: 1088640 | J96: 1088640 | K96: 1440000 | L96: 1008000 | M96: 817920 | N96: 1296000 | O96: 1008000 | P96: 961920 | Q96: 16329600
B97: RE22C211D | C97: RE22C214D | D97: RE22C210D | E97: RE22C212D | F97: RE22C203D | G97: RE22C204D | H97: RE22C215D | I97: RE22C205D | J97: RE22C213D | K97: RE22C209D | L97: RE22C216D | M97: RE22C206D | N97: RE22C202D | O97: RE22C208D | P97: RE22C207D
A98: उत्सवानिमित्त (पालखी, जयंती, गणेशोत्सव इ.) नागरिकांच्या सुरक्षिततेच्या दृष्टीने आवश्यक कामे करणे | B98: 756000 | C98: 1008000 | D98: 1260000 | E98: 856800 | F98: 1008000 | G98: 756000 | H98: 1008000 | I98: 604800 | J98: 756000 | K98: 1260000 | L98: 604800 | M98: 504000 | N98: 3088800 | O98: 7624800 | P98: 504000 | Q98: 21600000
B99: RE22C211E | C99: RE22C214E | D99: RE22C210E | E99: RE22C212E | F99: RE22C203E | G99: RE22C204E | H99: RE22C215E | I99: RE22C205E | J99: RE22C213E | K99: RE22C209E | L99: RE22C216E | M99: RE22C206E | N99: RE22C202E | O99: RE22C208E | P99: RE22C207E
A100: किरकोळ दुरुस्तीसाठी कोठीस साहित्य पुरविणे | B100: 250000 | C100: 250000 | D100: 300000 | E100: 250000 | F100: 250000 | G100: 300000 | H100: 265000 | I100: 270000 | J100: 265000 | K100: 350000 | L100: 250000 | M100: 200000 | N100: 250000 | O100: 250000 | P100: 300000 | Q100: 4000000
A102: १३. बांधकाम नियोजन, नगर रचना इ.
A103: छ२. भवन विभाग (विभागीय कार्या.)
B104: RE23G211A | C104: RE23G214A | D104: RE23G210A | E104: RE23G212A | F104: RE23G203A | G104: RE23G204A | H104: RE23G215A | I104: RE23G205A | J104: RE23G213A | K104: RE23G209A | L104: RE23G216A | M104: RE23G206A | N104: RE23G202A | O104: RE23G208A | P104: RE23G207A
A105: १. कायम सेवकवर्ग वेतन | B105: 3000000 | C105: 6000000 | D105: 4000000 | E105: 2000000 | F105: 3000000 | G105: 5000000 | H105: 4000000 | I105: 4000000 | J105: 2000000 | K105: 5000000 | L105: 4000000 | M105: 2000000 | N105: 2000000 | O105: 3000000 | P105: 1000000 | Q105: 50000000
A107: १५. अनुज्ञापत्र व आकाशचिन्हे
B108: RE25B211B | C108: RE25B214B | D108: RE25B210B | E108: RE25B212B | F108: RE25B203B | G108: RE25B204B | H108: RE25B215B | I108: RE25B205B | J108: RE25B213B | K108: RE25B209B | L108: RE25B216B | M108: RE25B206B | N108: RE25B202B | O108: RE25B208B | P108: RE25B207B
A109: किरकोळ दुरुस्तीची कामे मजुरांमार्फत करून घेणे | B109: 167000 | C109: 167000 | D109: 167000 | E109: 167000 | F109: 167000 | G109: 167000 | H109: 167000 | I109: 167000 | J109: 167000 | K109: 200000 | L109: 167000 | M109: 129000 | N109: 167000 | O109: 167000 | P109: 167000 | Q109: 2500000
A111: अंदाजपत्रक 'अ' एकूण बेरीज | B111: 95854120 | C111: 86660280 | D111: 58166200 | E111: 98483640 | F111: 52046840 | G111: 81746980 | H111: 100309960 | I111: 76557500 | J111: 86457960 | K111: 106552420 | L111: 79681960 | M111: 65591080 | N111: 44614920 | O111: 36077800 | P111: 72581540 | Q111: 5263103200
A114: अंदाजपत्रकातील तरतुदींचा विभागवार वाटप तक्ता - अंदाजपत्रक 'क'
A116: १. पाणीपुरवठा
B117: XE12A211A | C117: XE12A214A | D117: XE12A210A | E117: XE12A212A | F117: XE12A203A | G117: XE12A204A | H117: XE12A215A | I117: XE12A205A | J117: XE12A213A | K117: XE12A209A | L117: XE12A216A | M117: XE12A206A | N117: XE12A202A | O117: XE12A208A | P117: XE12A207A
A118: २ब. कायम सेवक वर्ग वेतन (वि. का.) | B118: 327000 | C118: 280000 | D118: 980000 | E118: 397000 | F118: 1563000 | G118: 401000 | H118: 327000 | I118: 513000 | J118: 0 | K118: 0 | L118: 0 | M118: 0 | N118: 1820000 | O118: 392000 | P118: 0 | Q118: 7000000
...

Sheet list21
A2: यादी क्र. R1
A3: थोर व्यक्तींच्या जयंती / पुण्यतिथी साजरी करणे (यादी R1)
A4: RE11A274/R1-
A6: code | B6: ward | C6: कामाचे नाव | D6: प्रकल्पीय रक्कम | E6: तरतूद
A8: RE11A274/R1-1 | C8: महात्मा फुले जयंती | E8: 100000
A9: RE11A274/R1-2 | C9: डॉ. बाबासाहेब आंबेडकर जयंती | E9: 150000
A10: RE11A274/R1-3 | C10: लोकशाहीर अण्णाभाऊ साठे जयंती | E10: 200000
A11: RE11A274/R1-4 | C11: ईद-ए-मिलाद (पैगंबर जयंती) | E11: 150000
A12: RE11A274/R1-5 | C12: शहरातील शिवजयंती साजरी करणे, रोषणाई करणे | E12: 200000
A13: RE11A274/R1-6 | C13: महात्मा फुले यांची पुण्यतिथी साजरी करणे (दि. 28 नोव्हेंबर) | E13: 500000
A14: RE11A274/R1-7 | C14: मौलाना अब्दुल कलाम आझाद जयंती व पुण्यतिथी साजरी करणे | E14: 600000
A15: RE11A274/R1-8 | C15: लहुजी वस्ताद साळवे जयंती महोत्सव गंज पेठ व संगमवाडी येथे साजरा करणे | E15: 500000
A16: RE11A274/R1-9 | C16: नेताजी सुभाषचंद्र बोस यांची जयंती साजरी करणे | E16: 10000
A17: RE11A274/R1-10 | C17: येरवडा येथे लोकशाहिर अण्णाभाऊ साठे जयंती महोत्सव साजरा करणे | E17: 100000
A18: RE11A274/R1-11 | C18: श्री संत रोहिदास महाराज जयंती, पुण्यतिथी साजरी करणे | E18: 50000
A19: RE11A274/R1-13 | C19: मौलाना अबुल कलाम आझाद जयंती महोत्सव | E19: 500000
A20: RE11A274/R1-14 | C20: महावीर जयंती | E20: 100000
C22: यादी क्र. R1 एकूण | D22: 0 | E22: 3160000
A25: यादी क्र. R2
A26: शहरामध्ये विविध कार्यक्रम, उत्सव, महोत्सव, संमेलन/ सहप्रायोजक तत्वावर कार्यक्रम साजरे करणे (यादी R2)
A27: RE11A275/R2-
A29: code | B29: ward | C29: कामाचे नाव | D29: प्रकल्पीय रक्कम | E29: तरतूद
A31: RE11A275/R2-1 | C31: महानगरपालिका वर्धापन दिन / सुवर्ण महोत्सव साजरा करणे | E31: 700000
A32: RE11A275/R2-2 | C32: वर्षातील महत्त्वपूर्ण दिन | E32: 600000
A33: RE11A275/R2-3 | C33: शिवाजीमहाराज आग्र्‍याहून सुटून परत आले तो स्मृती दिन साजरा करणे | E33: 515000
A34: RE11A275/R2-4 | C34: शनिवारवाडा सांस्कृतिक महोत्सव | E34: 2000000
A35: RE11A275/R2-5 | C35: भारतरत्न डॉ. बाबासाहेब आंबेडकर सांस्कृतिक महोत्सव साजरा करणे/ भिम फेस्टिवल (शनिवारवाडा पटांगण) / फुले आंबेडकर फेस्टिवल (समताभूमी) | E35: 2000000
A36: RE11A275/R2-6 | C36: शिवमहोत्सव साजरा करणे (१४ ते २० फेब्रुवारी) | E36: 2000000
A37: RE11A275/R2-7 | C37: अण्णाभाऊ साठे महोत्सव | E37: 2000000
A38: RE11A275/R2-8 | C38: जागतिक आदिवासी दिन | E38: 500000
A39: RE11A275/R2-11 | C39: प्रभाग क्र.३९ क धनकवडी आंबेगाव पठार मध्ये सांस्कृतिक व क्रीडा महोत्सव आयोजन करणे. | E39: 2000000
C41: यादी क्र. R2 एकूण | D41: 0 | E41: 12315000
A44: यादी क्र. R3
A45: सत्कार, अभिनंदन, पुरस्कार, बक्षिसे यासारखे कार्यक्रम साजरे करणे (यादी R3)
A46: RE11A276/R3-
A48: code | B48: ward | C48: कामाचे नाव | D48: प्रकल्पीय रक्कम | E48: तरतूद
A50: RE11A276/R3-1 | C50: गणेशोत्सव प्रशस्तिपत्रके वितरण | E50: 1000000
A51: RE11A276/R3-2 | C51: श्री संत ज्ञानेश्वर व तुकाराम महाराज पालखी स्वागत व दिंडी प्रमुखांचा स्मृतीचिन्ह देऊन सत्कार | E51: 1000000
A52: RE11A276/R3-3 | C52: प्रतिवर्षी पुणे शहरातील इयत्ता १० वी, १२ वी परिक्षेत गुणवत्ता यादीत येणार्‍या विद्यार्थ्यांचे अभिनंदन | E52: 60000
A53: RE11A276/R3-4 | C53: बालगंधर्व पुरस्कार प्रदानकरिता | E53: 500000
A54: RE11A276/R3-5 | C54: पठ्ठे बापूराव पुरस्कारकरिता | E54: 500000
A55: RE11A276/R3-6 | C55: आचार्य अत्रे पुरस्कारकरिता | E55: 300000
A56: RE11A276/R3-8 | C56: महर्षि वाल्मिकी पुरस्कार | E56: 500000
A57: RE11A276/R3-9 | C57: सावित्रीबाई फुले पुरस्कार | E57: 500000
A58: RE11A276/R3-10 | C58: मौलाना अब्दुल कलाम आझाद पुरस्कार | E58: 500000
A59: RE11A276/R3-11 | C59: जयंतराव टिळक पुरस्कार | E59: 500000
A60: RE11A276/R3-12 | C60: १ ऑक्टोंबर - जागतिक ज्येष्ठ नागरिक दिनाच्या मेळाव्याकरता आच्छादित मंडप टाकणे व स्मृतिचिन्हे देणे | E60: 100000
A61: RE11A276/R3-13 | C61: कै.यशवंतराव चव्हाण यांचे स्मरणार्थ कोथरुड पुणे येथे कै. यशवंतराव चव्हाण पुरस्कार देणे | E61: 175000
... A75: RE11A276/R3-30 | C75: लोकमान्य टिळक शैक्षणिक गुणवत्ता पुरस्कार | E75: 5000000
C77: यादी क्र. R3 एकूण | D77: 0 | E77: 16435000
A80: यादी क्र. R9
A81: ERP, Software Development, Data Entry, सेवकांना प्रशिक्षण खर्च, GIS, Works Management System, Kiosk व तद्‌नुषंगिक कामे (यादी R9)
A82: RE11N103/R9-
A84: code | B84: ward | C84: कामाचे नाव | D84: प्रकल्पीय रक्कम | E84: तरतूद
A86: RE11N103/R9-1 | C86: पुणे मनपाकरिता ई.आर.पी.सोल्युशन घेणे | E86: 30000000
A87: RE11N103/R9-2 | C87: विविध विभागांसाठी डॅशबोर्ड विकसित करणे. | E87: 20000000
A88: RE11N103/R9-3 | C88: जीआयएस व ईआरपी एकमेकांना जोडण्याची प्रणाली विकसित करणे | E88: 30000000
A89: RE11N103/R9-4 | C89: पुणे मनपासाठी क्‍लाउड सर्व्हिस घेणे | E89: 40000000
A90: RE11N103/R9-5 | C90: मनपाच्य विविध कार्यालयांमध्ये नवीन समाविष्ट गावे यांच्यासाठी BSNL इंटरनेट लीज लाईन घेणे. | E90: 7500000
A91: RE11N103/R9-6 | C91: तांत्रिक सल्लागार यांची पुणे मनपासाठी नियुक्‍ती करणे | E91: 11000000
A92: RE11N103/R9-7 | C92: पुणे मनपातील नागरी सुविधा केंद्र चालविणे. | E92: 22800000
A93: RE11N103/R9-8 | C93: आर्टीफिशल इंटलिजनसचा वापर करून विश्लेषणात्मक माहिती व्दारे कर संकलन वाढविणे | E93: 20000000
A94: RE11N103/R9-9 | C94: पुणे मनपातील सर्व्हर्स, हार्डवेअर, नेटवर्क व प्रिंटर्सची देखभाल व दुरुस्ती करणे | E94: 12500000
A95: RE11N103/R9-10 | C95: मनपा मुख्य भवन येथे प्रायमरी व सेकंडरी इंटरनेट १०० एमबीपीएसची लिज लाईन पुरविणे | E95: 5000000
A96: RE11N103/R9-11 | C96: पुणे मनपाकरिता कॉल सेंटर चालविणे | E96: 3000000
A97: RE11N103/R9-12 | C97: बल्क एस.एम.एस./ बल्क ई-मेल गेटवे पुरविणे | E97: 5000000
... A104: RE11N103/R9-19 | C104: स्टार्ट-अप हब करणे | E104: 150000000
C106: यादी क्र. R9 एकूण | D106: 0 | E106: 434300000
A109: यादी क्र. SR9
A110: ERP, Software Development, Data Entry, सेवकांना प्रशिक्षण खर्च, GIS, Works Management System, Kiosk व तद्‌नुषंगिक कामे (यादी R9)
A111: RE11N122/SR9-
A113: code | B113: ward | C113: कामाचे नाव | D113: प्रकल्पीय रक्कम | E113: तरतूद
A115: RE11N122/SR9-81 | B115: 14A | C115: प्रभाग क्र. 14 अ, मध्ये सीटीएस सॉफ्टवेअरसह टॅब पुरविणे | E115: 1000000
A116: RE11N122/SR9-82 | B116: 19C | C116: प्रभाग क्र.19 क,मधील मनपा इमारतींमध्ये तसेच मनपा शाळांमध्ये संगणक वर्ग सुरू करणे करिता संगणक पुरविणे व तदनुषंगिक कामे करणे | E116: 2000000
A117: RE11N122/SR9-83 | B117: 25A | C117: प्रभाग क्र.25 अ मध्ये सावित्रीबाई शिवरकर बहुउद्देशीय हॉल येथे ई-लायब्ररी विकसित करणेकरिता संगणक पुरविणे व उर्वरित कामे पूर्ण करणे. | E117: 5000000
A118: RE11N122/SR9-84 | B118: 25B | C118: प्रभाग क्र.25 ब मधील सर्व महानगरपालिकेच्या शाळांना संगणक व प्रिंटर पुरविणे. | E118: 2000000
A119: RE11N122/SR9-85 | B119: 35D | C119: प्रभाग क्र. 35 ड मध्ये शाळेच्या मुलांना Tab (CTS Software सह) पुरविणे. | E119: 1000000
A120: RE11N122/SR9-86 | B120: 40B | C120: प्रभाग क्र.40ब,मध्ये शाळांना संगणक व प्रिंटर पुरविणे | E120: 2000000
A121: RE11N122/SR9-87 | B121: 7B | C121: प्रभाग क्र. 7 ब मधील पुणे महानगरपालिकेच्या प्राथमिक शाळेमध्ये विद्यार्थ्यांकरीता टॅब (सीटीएस सॉफ्टवेअरसह) पुरविणे. | E121: 1000000
A122: RE11N122/SR9-88 | B122: 5B | C122: प्रभाग क्र.5ब,मध्ये मनपाच्या शाळेमध्ये विद्यार्थ्यांसाठी टॅब (सीटीएस सॉफ्टवेअर) सह पुरविणे | E122: 2000000
A123: RE11N122/SR9-89 | B123: 37S | C123: प्रभाग क्र.37 (स्विकृत),पुणे शहरातील मनपाच्या शाळेतील विद्यार्थ्यांकरिता सी.टी.एस.सॉफ्टवेअर पुरविणे | E123: 5000000
A124: RE11N122/SR9-90 | B124: 37S | C124: प्रभाग क्र.37 (स्विकृत),पुणे शहरातील मनपाच्या शाळांमध्ये संगणक पुरविणे | E124: 5000000
A125: RE11N122/SR9-91 | B125: 16S | C125: प्रभाग क्र.१६ (स्वीकृत नगरसेवक) मध्ये पुणे शहरातील शाळांमध्ये विद्यार्थ्यांकरिता टॅब (सीटीएस सॉ टवेअर सह) पुरविणे. | E125: 5000000
A126: RE11N122/SR9-92 | B126: 16S | C126: प्रभाग क्र.१६ (स्वीकृत नगरसेवक) मध्ये पुणे शहरातील शाळांमध्ये संगणक पुरविणे. | E126: 5000000
... A133: RE11N122/SR9-99 | B133: 19B | C133: प्रभाग क्र.19ब,मध्ये मनपा शाळा व क्षेत्रिय कार्यालय व विविध ठिकाणी संगणक पुरविणे व तदनुषंगिक कामे कऱणे | E133: 1000000
A134: RE11N122/SR9-100 | C134: औषध वितरण व्यवस्थेसाठी सॉफ्टवेअर विकसित करणे. | E134: 4000000
A135: RE11N122/SR9-101 | C135: क्षेत्रिय कार्यालयात महा ई-सेवा केंद्र (शासकीय दाखले 50% सवलतीत) | E135: 10000000
A136: RE11N122/SR9-102 | C136: पुणे शहरासाठी इनव्हेस्टर फॅसिलिटेशन सेल उभारणे. | E136: 500000
A137: RE11N122/SR9-103 | C137: पुणे महानगरपालिकेच्या कार्यालयांमध्ये S.D. Van Solustion सह पुरविणे | E137: 5000000
A138: RE11N122/SR9-104 | C138: प्र.क्र. 19ब मध्ये मनपा शाळा, क्षेत्रीय कार्यालय व विविध ठिकाणी संगणक पुरविणे व इतर तदनुषंगिक कामे करणे | E138: 1000000
C140: यादी क्र. SR9 एकूण | D140: 0 | E140: 64000000
A143: यादी क्र. R4
A144: शहरातील विविध स्मशानभूमी, दफनभूमीमध्ये देखभालदुरूस्तीची कामे करणे (यादी R4)
A145: RE17F169/R4-
A147: code | B147: ward | C147: कामाचे नाव | D147: प्रकल्पीय रक्कम | E147: तरतूद
A149: RE17F169/R4-1 | C149: वैकुंठ स्मशानभूमी येथे सुधारणा कामे करणे | E149: 6000000
A150: RE17F169/R4-2 | C150: शहरातील हिंदू स्मशानभूमी येथे सुधारणा कामे करणे | E150: 12000000
A151: RE17F169/R4-3 | C151: शहरातील मुस्लिम कब्रस्तान येथे सुधारणा कामे करणे | E151: 6000000
A152: RE17F169/R4-4 | C152: शहरातील ख्रिश्चन दफनभूमी येथे सुधारणा कामे करणे | E152: 4000000
A153: RE17F169/R4-5 | C153: लिंगायत स्मशानभूमी येथे विविध सुधारणा कामे करणे | E153: 6000000
...

Sheet JNNURM
A1: • | B1: • | C1: • | D1: • | E1: code | F1: AMRUT, JNNURM (वाढीव कालावधी) व Smart City आभियान | G1: सुधारित मंजूर तरतूद | H1: 2122 स्थायी | I1: H
H2: 0
H3: 0
A4: 6 | F4: शहरी गरिबांसाठी मुलभूत सुविधा (BSUP) : | H4: 0
B5: 8 | E5: FE38A108 | F5: इनसिटू रिहॅबिलीटेशन | G5: 1404200000 | H5: 10500000
H6: 0
F7: शहरी गरिबांसाठी मुलभूत सुविधा (BSUP) : एकूण | H7: 10500000
H8: 0
H9: 0
A10: 14 | E10: FE48A101 | F10: केंद्र शासन पुरस्कृत विविध योजनांसाठी (JNNURM, AMRUT व Smart City आभियान इत्यादी) प्रकल्पासंबधित केंद्रशासन व राज्यशासनाशी समन्वय साधणेसाठी व अन्य विशेष इतर कामांसाठी PIU Cell | G10: 5400000 | H10: 12600000
H11: 0
E12: FE49A104 | F12: JUUNRM वाढीव कालावधी मध्ये मंजूर झालेले तसेच AMRUT अभियानामध्ये समावेश झालेल्या भामा आसखेड पाणी पुरवठा प्रकल्पासाठी तरतूद | H12: 371000000
E13: FE49A105 | F13: JNNURM वाढीव कालावधी मध्ये मंजूर झालेले तसेच AMRUT अभियानामध्ये समावेश झालेल्या वडगाव बुद्रुक प्रकल्पासाठी तरतूद | H13: 14000000
H14: 0
A15: 17 | F15: अमृत अभियानांतर्गत नव्याने सुरु होणाऱ्या प्रकल्पांसाठी तरतूद | H15: 0
E16: FE50A103A | F16: अमृत अभियानांतर्गत पुणे हरित क्षेत्र विकास प्रकल्प २०१५-१६ | H16: 700000
E17: FE50A103B | F17: अमृत अभियानांतर्गत पुणे हरित क्षेत्र विकास प्रकल्प २०१६-१७ | H17: 5740000
E18: FE50A103D | F18: अमृत अभियानांतर्गत पुणे हरित क्षेत्र विकास प्रकल्प २०१७-१८ | H18: 9400000
E19: FE50A104 | F19: स्मार्ट सिटी अभियान अंतर्गत नव्याने सुरु होणाऱ्या प्रकल्पांसाठी तरतूद (केंद्रशासन व राज्यशासन अनुदानासहित) | H19: 500000000
H20: 0
A21: • | B21: • | C21: • | D21: • | E21: • | F21: AMRUT, JNNURM (वाढीव कालावधी) व Smart City आभियान एकूण | H21: 923940000
H22: 0
F23: ( टीप 1 :- जवाहरलाल नेहरू नागरी पुनर्निर्माण योजना निधीतून काम पूर्ण होण्यासाठी आवश्यक असलेल्या रकमेपर्यंत खर्च करण्यात येईल.) | H23: 0
F24: ( टीप 2 :- केंद्र शासनाकडून प्रकल्प मान्य होऊन पहिला हप्ता प्राप्त झाल्यानंतरच खर्च करण्यात येईल.) | H24: 0
A25: • | B25: • | C25: • | D25: • | E25: • | F25: ज.ने.रा.श.पु.अ., अमृत व स्मार्ट सिटी आभियान - फेज 2 एकूण | H25: 923940000

Sheet SPV
C1: code | F1: प्रकल्पीय रक्कम | G1: 2122 स्थायी | H1: H
E2: सार्वजनिक वाहतूक सुधारणा व विशेष प्रकल्प विभागामार्फत करावयाची कामे : | G2: 0
G3: 0
G4: 0
A5: 13 | C5: FE61A118# | E5: सार्वजनिक वाहतूक सुधारणा कामे :- (Comprehensive Mobility Plan) | G5: 0
C6: FE61A118/A-135 | D6: 35 | E6: विविध प्रकारच्या प्रकल्पांच्या अभ्यासासाठी तरतूद (feasibility report, techno-economical report, environmental report & other reports) | G6: 7000000
G7: 0
A8: 14 | E8: पुणे शहरात आवश्यक तेथे भुयारी मार्ग / उड्डाणपूल रेल्वे बांधकाम करणे :- (Non Comprehensive Mobility Plan) | G8: 0
C9: FE61A118/B-110 | E9: घोरपडी पुणे येथे पुणे सोलापूर व पुणे -मिरज रेल्वे लाईनवर उड्‌डाणपूल बांधणे. | F9: 1250000000 | G9: 2.45e+08
C10: FE61A118/B-113 | E10: भूसंपादन, संरक्षण खाते / अन्य खात्यांच्या परवानग्या अथवा अन्य स्वरुपाच्या तांत्रिक अडचणी / प्रश्न मार्गी लागल्यानंतर बंद असलेले / रखडलेले प्रकल्प सुरु करणेसाठी करावयाची तरतूद | G10: 350000000
C11: FE61A118/B-114 | E11: सेव्हन लव्हज चौक ते वखार महामंडळ चौक उड्‌डाणपूल बांधणे | F11: 320000000 | G11: 70000000
C12: FE61A118/B-116 | E12: नव्याने समाविष्ट 23 गावांमध्ये विविध स्वरुपाची कामे करण्यासाठी | G12: 700000000
C13: FE61A118/B-117 | E13: अम्ब्रोसिया रिसॉर्ट ते बावधन उड्डाणपूल / ग्रेडसेपरेटर बांधणे | F13: 200000000 | G13: 35000000
G14: 0
G15: 0
A16: 15 | E16: Signal Free Roads | G16: 0
G17: 0
A18: 16 | C18: FE61A119 | E18: पुणे मेट्रो रेल्वे प्रकल्प | F18: 73000000000 | G18: 35000000
A19: 27 | C19: FE61A129 | E19: औंध-सांगवी जोडणा-या मुळा नदीवर पुल बांधणे | F19: 300000000 | G19: 70000000
A20: 31 | C20: FE61A133 | E20: शासकीय अभियांत्रिकी महाविद्यालय शिवाजीनगर येथे उड्‌डाणपूल बांधणे अंतर्गत, उड्‌डाणपूलांवर ध्वनीरोधक बसविणे व अभियांत्रिकी कॉलेज हॉस्टेल ते कॉलेज मैदान यांना जोडणारा पादचारी पूल बांधणे व इतर तद्‌नुषंगिक कामे करणे. | F20: 50000000 | G20: 84000000
G21: 0
E22: एकूण बेरीज | G22: 1596000000
E24: ( टीप :- आर्थिक वर्षात सार्वजनिक वाहतूक सुधारणा व विशेष प्रकल्पासाठी अतिरिक्त निधीची गरज भासल्यास जागतिक बँक, जपान बँक व वित्त संस्थांकडून कर्ज घेऊन तरतूद उपलब्ध करता येईल. )

Sheet PMAY
F1: प्रकल्पीय रक्कम | G1: 2122 स्थायी | H1: H
E2: प्रधानमंत्री आवास योजना | G2: 0
G3: 0
A4: 1 | C4: FE62A101 | E4: प्रधानमंत्री आवास योजनेअंतर्गत विविध योजना राबविणे | G4: 700000000
G5: 0
E6: एकूण बेरीज | G6: 700000000

Sheet SMRY-2122
A1: code | B1: ward | C1: * | D1: क्षेत्रीय कार्यालयाने करावयाची कामे : सन 2021-22 | E1: पथ | F1: विद्युत | G1: भवन | H1: झोनिपु | I1: पाणीपुरवठा | J1: मलनिःसारण | K1: एकूण | L1: 0
D4: (आकडे लाखात) | E4: 2 | F4: 1 | G4: 4 | H4: 5 | I4: 6 | J4: 7 | K4: Total
A6: code | B6: Sr. | C6: Wards | D6: =D1 -> क्षेत्रीय कार्यालयाने करावयाची कामे : सन 2021-22 | E6: 2 | F6: 1 | G6: 4 | H6: 5 | I6: 6 | J6: 7 | K6: Total
B8: =WardOfficeNonPlan2122!B8 -> 1 | C8: =WardOfficeNonPlan2122!C8 -> 3, 4, 5 | D8: =WardOfficeNonPlan2122!D8 -> नगररोड - वडगावशेरी क्षेत्रीय कार्यालय एकूण बेरीज | E8: =WardOfficeNonPlan2122!E8+WardOfficePlan2122!E8+CitizensNonPlan2122!E8+CitizensPlan2122!E8 -> 312 | F8: =WardOfficeNonPlan2122!F8+WardOfficePlan2122!F8+CitizensNonPlan2122!F8+CitizensPlan2122!F8 -> 170 | G8: =WardOfficeNonPlan2122!G8+WardOfficePlan2122!G8+CitizensNonPlan2122!G8+CitizensPlan2122!G8 -> 72.5 | H8: =WardOfficeNonPlan2122!H8+WardOfficePlan2122!H8+CitizensNonPlan2122!H8+CitizensPlan2122!H8 -> 13 | I8: =WardOfficeNonPlan2122!I8+WardOfficePlan2122!I8+CitizensNonPlan2122!I8+CitizensPlan2122!I8 -> 5 | J8: =WardOfficeNonPlan2122!J8+WardOfficePlan2122!J8+CitizensNonPlan2122!J8+CitizensPlan2122!J8 -> 177.5 | K8: =SUM(E8:J8) -> 750
B9: =WardOfficeNonPlan2122!B9 -> 2 | C9: =WardOfficeNonPlan2122!C9 -> 1, 2, 6 | D9: =WardOfficeNonPlan2122!D9 -> येरवडा - कळस - धानोरी क्षेत्रीय कार्यालय एकूण बेरीज | E9: =WardOfficeNonPlan2122!E9+WardOfficePlan2122!E9+CitizensNonPlan2122!E9+CitizensPlan2122!E9 -> 245 | F9: =WardOfficeNonPlan2122!F9+WardOfficePlan2122!F9+CitizensNonPlan2122!F9+CitizensPlan2122!F9 -> 67.5 | G9: =WardOfficeNonPlan2122!G9+WardOfficePlan2122!G9+CitizensNonPlan2122!G9+CitizensPlan2122!G9 -> 99 | H9: =WardOfficeNonPlan2122!H9+WardOfficePlan2122!H9+CitizensNonPlan2122!H9+CitizensPlan2122!H9 -> 82.5 | I9: =WardOfficeNonPlan2122!I9+WardOfficePlan2122!I9+CitizensNonPlan2122!I9+CitizensPlan2122!I9 -> 0 | J9: =WardOfficeNonPlan2122!J9+WardOfficePlan2122!J9+CitizensNonPlan2122!J9+CitizensPlan2122!J9 -> 256 | K9: =SUM(E9:J9) -> 750
B10: =WardOfficeNonPlan2122!B10 -> 3 | C10: =WardOfficeNonPlan2122!C10 -> 20, 21 | D10: =WardOfficeNonPlan2122!D10 -> ढोलेपाटील क्षेत्रीय कार्यालय एकूण बेरीज | E10: =WardOfficeNonPlan2122!E10+WardOfficePlan2122!E10+CitizensNonPlan2122!E10+CitizensPlan2122!E10 -> 116.5 | F10: =WardOfficeNonPlan2122!F10+WardOfficePlan2122!F10+CitizensNonPlan2122!F10+CitizensPlan2122!F10 -> 31.5 | G10: =WardOfficeNonPlan2122!G10+WardOfficePlan2122!G10+CitizensNonPlan2122!G10+CitizensPlan2122!G10 -> 72 | H10: =WardOfficeNonPlan2122!H10+WardOfficePlan2122!H10+CitizensNonPlan2122!H10+CitizensPlan2122!H10 -> 165 | I10: =WardOfficeNonPlan2122!I10+WardOfficePlan2122!I10+CitizensNonPlan2122!I10+CitizensPlan2122!I10 -> 2.5 | J10: =WardOfficeNonPlan2122!J10+WardOfficePlan2122!J10+CitizensNonPlan2122!J10+CitizensPlan2122!J10 -> 112.5 | K10: =SUM(E10:J10) -> 500
B11: =WardOfficeNonPlan2122!B11 -> 4 | C11: =WardOfficeNonPlan2122!C11 -> 8, 9 | D11: =WardOfficeNonPlan2122!D11 -> औंध - बाणेर क्षेत्रीय कार्यालय एकूण बेरीज | E11: =WardOfficeNonPlan2122!E11+WardOfficePlan2122!E11+CitizensNonPlan2122!E11+CitizensPlan2122!E11 -> 115 | F11: =WardOfficeNonPlan2122!F11+WardOfficePlan2122!F11+CitizensNonPlan2122!F11+CitizensPlan2122!F11 -> 110 | G11: =WardOfficeNonPlan2122!G11+WardOfficePlan2122!G11+CitizensNonPlan2122!G11+CitizensPlan2122!G11 -> 75 | H11: =WardOfficeNonPlan2122!H11+WardOfficePlan2122!H11+CitizensNonPlan2122!H11+CitizensPlan2122!H11 -> 125 | I11: =WardOfficeNonPlan2122!I11+WardOfficePlan2122!I11+CitizensNonPlan2122!I11+CitizensPlan2122!I11 -> 0 | J11: =WardOfficeNonPlan2122!J11+WardOfficePlan2122!J11+CitizensNonPlan2122!J11+CitizensPlan2122!J11 -> 75 | K11: =SUM(E11:J11) -> 500
B12: =WardOfficeNonPlan2122!B12 -> 5 | C12: =WardOfficeNonPlan2122!C12 -> 7, 14 | D12: =WardOfficeNonPlan2122!D12 -> शिवाजीनगर - घोले रोड क्षेत्रीय कार्यालय एकूण बेरीज | E12: =WardOfficeNonPlan2122!E12+WardOfficePlan2122!E12+CitizensNonPlan2122!E12+CitizensPlan2122!E12 -> 91.5 | F12: =WardOfficeNonPlan2122!F12+WardOfficePlan2122!F12+CitizensNonPlan2122!F12+CitizensPlan2122!F12 -> 62 | G12: =WardOfficeNonPlan2122!G12+WardOfficePlan2122!G12+CitizensNonPlan2122!G12+CitizensPlan2122!G12 -> 89 | H12: =WardOfficeNonPlan2122!H12+WardOfficePlan2122!H12+CitizensNonPlan2122!H12+CitizensPlan2122!H12 -> 141 | I12: =WardOfficeNonPlan2122!I12+WardOfficePlan2122!I12+CitizensNonPlan2122!I12+CitizensPlan2122!I12 -> 3 | J12: =WardOfficeNonPlan2122!J12+WardOfficePlan2122!J12+CitizensNonPlan2122!J12+CitizensPlan2122!J12 -> 113.5 | K12: =SUM(E12:J12) -> 500
B13: =WardOfficeNonPlan2122!B13 -> 6 | C13: =WardOfficeNonPlan2122!C13 -> 10, 11, 12 | D13: =WardOfficeNonPlan2122!D13 -> कोथरूड - बावधन क्षेत्रीय कार्यालय एकूण बेरीज | E13: =WardOfficeNonPlan2122!E13+WardOfficePlan2122!E13+CitizensNonPlan2122!E13+CitizensPlan2122!E13 -> 275 | F13: =WardOfficeNonPlan2122!F13+WardOfficePlan2122!F13+CitizensNonPlan2122!F13+CitizensPlan2122!F13 -> 41.5 | G13: =WardOfficeNonPlan2122!G13+WardOfficePlan2122!G13+CitizensNonPlan2122!G13+CitizensPlan2122!G13 -> 112.5 | H13: =WardOfficeNonPlan2122!H13+WardOfficePlan2122!H13+CitizensNonPlan2122!H13+CitizensPlan2122!H13 -> 140.5 | I13: =WardOfficeNonPlan2122!I13+WardOfficePlan2122!I13+CitizensNonPlan2122!I13+CitizensPlan2122!I13 -> 5 | J13: =WardOfficeNonPlan2122!J13+WardOfficePlan2122!J13+CitizensNonPlan2122!J13+CitizensPlan2122!J13 -> 175.5 | K13: =SUM(E13:J13) -> 750
B14: =WardOfficeNonPlan2122!B14 -> 7 | C14: =WardOfficeNonPlan2122!C14 -> 35, 39, 40 | D14: =WardOfficeNonPlan2122!D14 -> धनकवडी - सहकारनगर क्षेत्रीय कार्यालय एकूण बेरीज | E14: =WardOfficeNonPlan2122!E14+WardOfficePlan2122!E14+CitizensNonPlan2122!E14+CitizensPlan2122!E14 -> 265 | F14: =WardOfficeNonPlan2122!F14+WardOfficePlan2122!F14+CitizensNonPlan2122!F14+CitizensPlan2122!F14 -> 72 | G14: =WardOfficeNonPlan2122!G14+WardOfficePlan2122!G14+CitizensNonPlan2122!G14+CitizensPlan2122!G14 -> 110 | H14: =WardOfficeNonPlan2122!H14+WardOfficePlan2122!H14+CitizensNonPlan2122!H14+CitizensPlan2122!H14 -> 66 | I14: =WardOfficeNonPlan2122!I14+WardOfficePlan2122!I14+CitizensNonPlan2122!I14+CitizensPlan2122!I14 -> 5 | J14: =WardOfficeNonPlan2122!J14+WardOfficePlan2122!J14+CitizensNonPlan2122!J14+CitizensPlan2122!J14 -> 232 | K14: =SUM(E14:J14) -> 750
B15: =WardOfficeNonPlan2122!B15 -> 8 | C15: =WardOfficeNonPlan2122!C15 -> 30, 33, 34 | D15: =WardOfficeNonPlan2122!D15 -> सिंहगड रोड क्षेत्रीय कार्यालय एकूण बेरीज | E15: =WardOfficeNonPlan2122!E15+WardOfficePlan2122!E15+CitizensNonPlan2122!E15+CitizensPlan2122!E15 -> 301.45 | F15: =WardOfficeNonPlan2122!F15+WardOfficePlan2122!F15+CitizensNonPlan2122!F15+CitizensPlan2122!F15 -> 97.5 | G15: =WardOfficeNonPlan2122!G15+WardOfficePlan2122!G15+CitizensNonPlan2122!G15+CitizensPlan2122!G15 -> 60.05 | H15: =WardOfficeNonPlan2122!H15+WardOfficePlan2122!H15+CitizensNonPlan2122!H15+CitizensPlan2122!H15 -> 100 | I15: =WardOfficeNonPlan2122!I15+WardOfficePlan2122!I15+CitizensNonPlan2122!I15+CitizensPlan2122!I15 -> 0 | J15: =WardOfficeNonPlan2122!J15+WardOfficePlan2122!J15+CitizensNonPlan2122!J15+CitizensPlan2122!J15 -> 191 | K15: =SUM(E15:J15) -> 750
B16: =WardOfficeNonPlan2122!B16 -> 9 | C16: =WardOfficeNonPlan2122!C16 -> 13, 31, 32 | D16: =WardOfficeNonPlan2122!D16 -> वारजे - कर्वेनगर क्षेत्रीय कार्यालय एकूण बेरीज | E16: =WardOfficeNonPlan2122!E16+WardOfficePlan2122!E16+CitizensNonPlan2122!E16+CitizensPlan2122!E16 -> 247.5 | F16: =WardOfficeNonPlan2122!F16+WardOfficePlan2122!F16+CitizensNonPlan2122!F16+CitizensPlan2122!F16 -> 125 | G16: =WardOfficeNonPlan2122!G16+WardOfficePlan2122!G16+CitizensNonPlan2122!G16+CitizensPlan2122!G16 -> 110 | H16: =WardOfficeNonPlan2122!H16+WardOfficePlan2122!H16+CitizensNonPlan2122!H16+CitizensPlan2122!H16 -> 95 | I16: =WardOfficeNonPlan2122!I16+WardOfficePlan2122!I16+CitizensNonPlan2122!I16+CitizensPlan2122!I16 -> 0 | J16: =WardOfficeNonPlan2122!J16+WardOfficePlan2122!J16+CitizensNonPlan2122!J16+CitizensPlan2122!J16 -> 172.5 | K16: =SUM(E16:J16) -> 750
B17: =WardOfficeNonPlan2122!B17 -> 10 | C17: =WardOfficeNonPlan2122!C17 -> 22, 23, 26 | D17: =WardOfficeNonPlan2122!D17 -> हडपसर - मुंढवा क्षेत्रीय कार्यालय एकूण बेरीज | E17: =WardOfficeNonPlan2122!E17+WardOfficePlan2122!E17+CitizensNonPlan2122!E17+CitizensPlan2122!E17 -> 313.5 | F17: =WardOfficeNonPlan2122!F17+WardOfficePlan2122!F17+CitizensNonPlan2122!F17+CitizensPlan2122!F17 -> 97.5 | G17: =WardOfficeNonPlan2122!G17+WardOfficePlan2122!G17+CitizensNonPlan2122!G17+CitizensPlan2122!G17 -> 102.5 | H17: =WardOfficeNonPlan2122!H17+WardOfficePlan2122!H17+CitizensNonPlan2122!H17+CitizensPlan2122!H17 -> 17.5 | I17: =WardOfficeNonPlan2122!I17+WardOfficePlan2122!I17+CitizensNonPlan2122!I17+CitizensPlan2122!I17 -> 15 | J17: =WardOfficeNonPlan2122!J17+WardOfficePlan2122!J17+CitizensNonPlan2122!J17+CitizensPlan2122!J17 -> 204 | K17: =SUM(E17:J17) -> 750
B18: =WardOfficeNonPlan2122!B18 -> 11 | C18: =WardOfficeNonPlan2122!C18 -> 24, 25, 27 | D18: =WardOfficeNonPlan2122!D18 -> वानवडी - रामटेकडी क्षेत्रीय कार्यालय एकूण बेरीज | E18: =WardOfficeNonPlan2122!E18+WardOfficePlan2122!E18+CitizensNonPlan2122!E18+CitizensPlan2122!E18 -> 285 | F18: =WardOfficeNonPlan2122!F18+WardOfficePlan2122!F18+CitizensNonPlan2122!F18+CitizensPlan2122!F18 -> 110 | G18: =WardOfficeNonPlan2122!G18+WardOfficePlan2122!G18+CitizensNonPlan2122!G18+CitizensPlan2122!G18 -> 58.5 | H18: =WardOfficeNonPlan2122!H18+WardOfficePlan2122!H18+CitizensNonPlan2122!H18+CitizensPlan2122!H18 -> 25 | I18: =WardOfficeNonPlan2122!I18+WardOfficePlan2122!I18+CitizensNonPlan2122!I18+CitizensPlan2122!I18 -> 0 | J18: =WardOfficeNonPlan2122!J18+WardOfficePlan2122!J18+CitizensNonPlan2122!J18+CitizensPlan2122!J18 -> 209 | K18: =SUM(E18:J18) -> 687.5
B19: =WardOfficeNonPlan2122!B19 -> 12 | C19: =WardOfficeNonPlan2122!C19 -> 38, 41 | D19: =WardOfficeNonPlan2122!D19 -> कोंढवा - येवलेवाडी क्षेत्रीय कार्यालय एकूण बेरीज | E19: =WardOfficeNonPlan2122!E19+WardOfficePlan2122!E19+CitizensNonPlan2122!E19+CitizensPlan2122!E19 -> 191.5 | F19: =WardOfficeNonPlan2122!F19+WardOfficePlan2122!F19+CitizensNonPlan2122!F19+CitizensPlan2122!F19 -> 85.5 | G19: =WardOfficeNonPlan2122!G19+WardOfficePlan2122!G19+CitizensNonPlan2122!G19+CitizensPlan2122!G19 -> 40.5 | H19: =WardOfficeNonPlan2122!H19+WardOfficePlan2122!H19+CitizensNonPlan2122!H19+CitizensPlan2122!H19 -> 5 | I19: =WardOfficeNonPlan2122!I19+WardOfficePlan2122!I19+CitizensNonPlan2122!I19+CitizensPlan2122!I19 -> 0 | J19: =WardOfficeNonPlan2122!J19+WardOfficePlan2122!J19+CitizensNonPlan2122!J19+CitizensPlan2122!J19 -> 177.5 | K19: =SUM(E19:J19) -> 500
... B23: =WardOfficeNonPlan2122!B23 -> 16 | C23: =WardOfficeNonPlan2122!C23 -> 42 | D23: =WardOfficeNonPlan2122!D23 -> नव्याने समाविष्ट झालेली गावे एकूण बेरीज | E23: =WardOfficeNonPlan2122!E23+WardOfficePlan2122!E23+CitizensNonPlan2122!E23+CitizensPlan2122!E23 -> 37.5 | F23: =WardOfficeNonPlan2122!F23+WardOfficePlan2122!F23+CitizensNonPlan2122!F23+CitizensPlan2122!F23 -> 25 | G23: =WardOfficeNonPlan2122!G23+WardOfficePlan2122!G23+CitizensNonPlan2122!G23+CitizensPlan2122!G23 -> 35 | H23: =WardOfficeNonPlan2122!H23+WardOfficePlan2122!H23+CitizensNonPlan2122!H23+CitizensPlan2122!H23 -> 5 | I23: =WardOfficeNonPlan2122!I23+WardOfficePlan2122!I23+CitizensNonPlan2122!I23+CitizensPlan2122!I23 -> 0 | J23: =WardOfficeNonPlan2122!J23+WardOfficePlan2122!J23+CitizensNonPlan2122!J23+CitizensPlan2122!J23 -> 22.5 | K23: =SUM(E23:J23) -> 125
C25: =SUM(C8:C24) -> 42 | D25: =""&TEXT(D6,"0")&" एकूण बेरीज" -> क्षेत्रीय कार्यालयाने करावयाची कामे : सन 2021-22 एकूण बेरीज | E25: =SUM(E8:E24) -> 3427.95 | F25: =SUM(F8:F24) -> 1413.5 | G25: =SUM(G8:G24) -> 1319.55 | H25: =SUM(H8:H24) -> 1266 | I25: =SUM(I8:I24) -> 60.5 | J25: =SUM(J8:J24) -> 2762.5 | K25: =SUM(K8:K24) -> 10250

Sheet WardOfficeNonPlan2122
A1: code | B1: ward | C1: * | D1: क्षेत्रीय कार्यालयाने करावयाची योजनेतर कामे : सन 2021-22 | E1: पथ | F1: विद्युत | G1: भवन | H1: झोनिपु | I1: पाणीपुरवठा | J1: मलनिःसारण | K1: एकूण | L1: H
D4: (आकडे लाखात) | E4: W2 | F4: W1 | G4: W4 | H4: W5 | I4: W6 | J4: W7
A6: code | B6: Sr. | C6: Wards | D6: =D1 -> क्षेत्रीय कार्यालयाने करावयाची योजनेतर कामे : सन 2021-22 | E6: RE20A301/W2- | F6: RE20C301/W1- | G6: RE22C301/W4- | H6: RE14B301/W5- | I6: XE12B301/W6- | J6: XE23A301/W7- | K6: Total
B8: 1 | C8: 3, 4, 5 | D8: =D289 -> नगररोड - वडगावशेरी क्षेत्रीय कार्यालय एकूण बेरीज | E8: =E289 -> 125 | F8: =F289 -> 100 | G8: =G289 -> 12.5 | H8: =H289 -> 0 | I8: =I289 -> 0 | J8: =J289 -> 62.5 | K8: =SUM(E8:J8) -> 300
B9: 2 | C9: 1, 2, 6 | D9: =D544 -> येरवडा - कळस - धानोरी क्षेत्रीय कार्यालय एकूण बेरीज | E9: =E544 -> 140 | F9: =F544 -> 37.5 | G9: =G544 -> 74 | H9: =H544 -> 47.5 | I9: =I544 -> 0 | J9: =J544 -> 151 | K9: =SUM(E9:J9) -> 450
B10: 3 | C10: 20, 21 | D10: =D716 -> ढोलेपाटील क्षेत्रीय कार्यालय एकूण बेरीज | E10: =E716 -> 82.5 | F10: =F716 -> 20 | G10: =G716 -> 42.5 | H10: =H716 -> 87.5 | I10: =I716 -> 2.5 | J10: =J716 -> 65 | K10: =SUM(E10:J10) -> 300
B11: 4 | C11: 8, 9 | D11: =D888 -> औंध - बाणेर क्षेत्रीय कार्यालय एकूण बेरीज | E11: =E888 -> 60 | F11: =F888 -> 60 | G11: =G888 -> 60 | H11: =H888 -> 60 | I11: =I888 -> 0 | J11: =J888 -> 60 | K11: =SUM(E11:J11) -> 300
B12: 5 | C12: 7, 14 | D12: =D1060 -> शिवाजीनगर - घोले रोड क्षेत्रीय कार्यालय एकूण बेरीज | E12: =E1060 -> 67.5 | F12: =F1060 -> 45 | G12: =G1060 -> 56 | H12: =H1060 -> 64 | I12: =I1060 -> 0 | J12: =J1060 -> 67.5 | K12: =SUM(E12:J12) -> 300
B13: 6 | C13: 10, 11, 12 | D13: =D1315 -> कोथरूड - बावधन क्षेत्रीय कार्यालय एकूण बेरीज | E13: =E1315 -> 132 | F13: =F1315 -> 20.5 | G13: =G1315 -> 87.5 | H13: =H1315 -> 97.5 | I13: =I1315 -> 0 | J13: =J1315 -> 82.5 | K13: =SUM(E13:J13) -> 420
B14: 7 | C14: 35, 39, 40 | D14: =D1570 -> धनकवडी - सहकारनगर क्षेत्रीय कार्यालय एकूण बेरीज | E14: =E1570 -> 145.5 | F14: =F1570 -> 39.5 | G14: =G1570 -> 20.5 | H14: =H1570 -> 46 | I14: =I1570 -> 2.5 | J14: =J1570 -> 119 | K14: =SUM(E14:J14) -> 373
B15: 8 | C15: 30, 33, 34 | D15: =D1825 -> सिंहगड रोड क्षेत्रीय कार्यालय एकूण बेरीज | E15: =E1825 -> 0 | F15: =F1825 -> 0 | G15: =G1825 -> 0 | H15: =H1825 -> 0 | I15: =I1825 -> 0 | J15: =J1825 -> 0 | K15: =SUM(E15:J15) -> 0
B16: 9 | C16: 13, 31, 32 | D16: =D2080 -> वारजे - कर्वेनगर क्षेत्रीय कार्यालय एकूण बेरीज | E16: =E2080 -> 112.5 | F16: =F2080 -> 105 | G16: =G2080 -> 32.5 | H16: =H2080 -> 57.5 | I16: =I2080 -> 0 | J16: =J2080 -> 90 | K16: =SUM(E16:J16) -> 397.5
B17: 10 | C17: 22, 23, 26 | D17: =D2335 -> हडपसर - मुंढवा क्षेत्रीय कार्यालय एकूण बेरीज | E17: =E2335 -> 127 | F17: =F2335 -> 62.5 | G17: =G2335 -> 57.5 | H17: =H2335 -> 17.5 | I17: =I2335 -> 5 | J17: =J2335 -> 44 | K17: =SUM(E17:J17) -> 313.5
B18: 11 | C18: 24, 25, 27 | D18: =D2590 -> वानवडी - रामटेकडी क्षेत्रीय कार्यालय एकूण बेरीज | E18: =E2590 -> 80 | F18: =F2590 -> 30 | G18: =G2590 -> 23.5 | H18: =H2590 -> 20 | I18: =I2590 -> 0 | J18: =J2590 -> 117.5 | K18: =SUM(E18:J18) -> 271
B19: 12 | C19: 38, 41 | D19: =D2762 -> कोंढवा - येवलेवाडी क्षेत्रीय कार्यालय एकूण बेरीज | E19: =E2762 -> 50 | F19: =F2762 -> 0 | G19: =G2762 -> 35.5 | H19: =H2762 -> 0 | I19: =I2762 -> 0 | J19: =J2762 -> 87.5 | K19: =SUM(E19:J19) -> 173
B20: 13 | C20: 15, 16, 29 | D20: =D3017 -> कसबा - विश्रामबागवाडा क्षेत्रीय कार्यालय एकूण बेरीज | E20: =E3017 -> 152.5 | F20: =F3017 -> 60 | G20: =G3017 -> 75 | H20: =H3017 -> 82.5 | I20: =I3017 -> 0 | J20: =J3017 -> 80 | K20: =SUM(E20:J20) -> 450
B21: 14 | C21: 17, 18, 19 | D21: =D3272 -> भवानी पेठ क्षेत्रीय कार्यालय एकूण बेरीज | E21: =E3272 -> 115 | F21: =F3272 -> 60 | G21: =G3272 -> 80 | H21: =H3272 -> 70 | I21: =I3272 -> 0 | J21: =J3272 -> 125 | K21: =SUM(E21:J21) -> 450
B22: 15 | C22: 28, 36, 37 | D22: =D3527 -> बिबवेवाडी क्षेत्रीय कार्यालय एकूण बेरीज | E22: =E3527 -> 75 | F22: =F3527 -> 62.5 | G22: =G3527 -> 50 | H22: =H3527 -> 30 | I22: =I3527 -> 0 | J22: =J3527 -> 45 | K22: =SUM(E22:J22) -> 262.5
B23: 16 | C23: 42 | D23: =D3699 -> नव्याने समाविष्ट झालेली गावे एकूण बेरीज | E23: =E3699 -> 5 | F23: =F3699 -> 5 | G23: =G3699 -> 10 | H23: =H3699 -> 5 | I23: =I3699 -> 0 | J23: =J3699 -> 12.5 | K23: =SUM(E23:J23) -> 37.5
C25: =SUM(C8:C24) -> 42 | D25: =""&TEXT(D6,"0")&" एकूण बेरीज" -> क्षेत्रीय कार्यालयाने करावयाची योजनेतर कामे : सन 2021-22 एकूण बेरीज | E25: =SUM(E8:E24) -> 1469.5 | F25: =SUM(F8:F24) -> 707.5 | G25: =SUM(G8:G24) -> 717 | H25: =SUM(H8:H24) -> 685 | I25: =SUM(I8:I24) -> 10 | J25: =SUM(J8:J24) -> 1209 | K25: =SUM(K8:K24) -> 4798
E27: =E25*100000 -> 146950000 | F27: =F25*100000 -> 70750000 | G27: =G25*100000 -> 71700000 | H27: =H25*100000 -> 68500000 | I27: =I25*100000 -> 1000000 | J27: =J25*100000 -> 120900000 | K27: =K25*100000 -> 479800000 | L27: 0
L28: 0
L29: 0
L30: 0
L31: 0
L32: 0
L33: 0
L34: 0
L35: 0
L36: 0
D37: नगररोड - वडगावशेरी क्षेत्रीय कार्यालय | K37: =SUM(E37:J37) -> 0
K38: =SUM(E38:J38) -> 0
A39: XE23A301/W7-801 | B39: 3 | D39: प्रभाग क्र. 3 मध्ये विविध ठिकाणी ड्रेनेज लाईन टाकणे व कॉक्रीट करणे | E39: 0 | F39: 0 | G39: 0 | H39: 0 | I39: 0 | J39: 10 | K39: =SUM(E39:J39) -> 10
A40: RE20A301/W2-901 | B40: 3 | D40: प्रभाग क्र. 3 मध्ये विविध ठिकाणी रस्त्याची कामे करणे | E40: 5 | F40: 0 | G40: 0 | H40: 0 | I40: 0 | J40: 0 | K40: =SUM(E40:J40) -> 5
A41: RE20C301/W1-501 | B41: 3 | D41: प्रभाग क्र. 3 मध्ये यमुनानगर जवळील परिसरात प्रकाश व्यवस्था करणे | E41: 0 | F41: 5 | G41: 0 | H41: 0 | I41: 0 | J41: 0 | K41: =SUM(E41:J41) -> 5
A42: RE20C301/W1-502 | B42: 3 | D42: प्रभाग क्र. 3 मध्ये तक्षशिला क्रिटिंग क्रिडानगरी येथे विविध विकास कामे करणे | E42: 0 | F42: 5 | G42: 0 | H42: 0 | I42: 0 | J42: 0 | K42: =SUM(E42:J42) -> 5
A43: RE20C301/W1-503 | B43: 3 | D43: प्रभाग क्र. 3 मधील सोपाननगर येथे तारा भुमिगत करणे | E43: 0 | F43: 5 | G43: 0 | H43: 0 | I43: 0 | J43: 0 | K43: =SUM(E43:J43) -> 5
A44: RE20C301/W1-504 | B44: 3 | D44: प्रभाग क्र. 3 मध्ये संजयपार्क येथे धोकादायक जंक्शन बॉक्स बदलणे | E44: 0 | F44: 5 | G44: 0 | H44: 0 | I44: 0 | J44: 0 | K44: =SUM(E44:J44) -> 5
A45: RE20A301/W2-902 | B45: 3 | D45: प्रभाग क्र. 3 विविध भागात रस्ते विकसित करणे | E45: 7.5 | F45: 0 | G45: 0 | H45: 0 | I45: 0 | J45: 0 | K45: =SUM(E45:J45) -> 7.5
A46: RE20A301/W2-903 | B46: 3 | D46: प्रभाग क्र. 3 विविध भागात रस्ते विषयक कामे करणे | E46: 5 | F46: 0 | G46: 0 | H46: 0 | I46: 0 | J46: 0 | K46: =SUM(E46:J46) -> 5
A47: RE20C301/W1-505 | B47: 3 | D47: प्रभाग क्र. 3 मध्ये राजीवनगर विमाननगर येथील नविन रस्त्यांवर पोल बसविणे | E47: 0 | F47: 5 | G47: 0 | H47: 0 | I47: 0 | J47: 0 | K47: =SUM(E47:J47) -> 5
A48: RE20C301/W1-506 | B48: 3 | D48: प्रभाग क्र. 3 विमाननगर परिसरात भुमिगत केबल टाकणे | E48: 0 | F48: 5 | G48: 0 | H48: 0 | I48: 0 | J48: 0 | K48: =SUM(E48:J48) -> 5
A49: RE20A301/W2-904 | B49: 3 | D49: प्रभाग क्र. 3 मधील विमाननगर व संजयपार्क येथील रस्ते विकसित करणे | E49: 7.5 | F49: 0 | G49: 0 | H49: 0 | I49: 0 | J49: 0 | K49: =SUM(E49:J49) -> 7.5
A50: XE23A301/W7-802 | B50: 3 | D50: प्रभाग क्र. 3 मध्ये विविध ठिकाणी ड्रेनेज दुरुस्ती विषयक कामे करणे | E50: 0 | F50: 0 | G50: 0 | H50: 0 | I50: 0 | J50: 5 | K50: =SUM(E50:J50) -> 5
... A55: RE20A301/W2-906 | B55: 3 | D55: प्रभाग क्र. 3 मधील विविध ठिकाणी रोड दुरुस्तीची कामे करणे | E55: 7.5 | F55: 0 | G55: 0 | H55: 0 | I55: 0 | J55: 0 | K55: =SUM(E55:J55) -> 7.5
B56: 3 | D56: 0 | E56: 0 | F56: 0 | G56: 0 | H56: 0 | I56: 0 | J56: 0 | K56: =SUM(E56:J56) -> 0 | L56: 0
B57: 3 | D57: 0 | E57: 0 | F57: 0 | G57: 0 | H57: 0 | I57: 0 | J57: 0 | K57: =SUM(E57:J57) -> 0 | L57: 0
B58: 3 | D58: 0 | E58: 0 | F58: 0 | G58: 0 | H58: 0 | I58: 0 | J58: 0 | K58: =SUM(E58:J58) -> 0 | L58: 0
B59: 3 | D59: 0 | E59: 0 | F59: 0 | G59: 0 | H59: 0 | I59: 0 | J59: 0 | K59: =SUM(E59:J59) -> 0 | L59: 0
B60: 3 | D60: 0 | E60: 0 | F60: 0 | G60: 0 | H60: 0 | I60: 0 | J60: 0 | K60: =SUM(E60:J60) -> 0 | L60: 0
B61: 3 | D61: 0 | E61: 0 | F61: 0 | G61: 0 | H61: 0 | I61: 0 | J61: 0 | K61: =SUM(E61:J61) -> 0 | L61: 0
B62: 3 | D62: 0 | E62: 0 | F62: 0 | G62: 0 | H62: 0 | I62: 0 | J62: 0 | K62: =SUM(E62:J62) -> 0 | L62: 0
B63: 3 | D63: 0 | E63: 0 | F63: 0 | G63: 0 | H63: 0 | I63: 0 | J63: 0 | K63: =SUM(E63:J63) -> 0 | L63: 0
B64: 3 | D64: 0 | E64: 0 | F64: 0 | G64: 0 | H64: 0 | I64: 0 | J64: 0 | K64: =SUM(E64:J64) -> 0 | L64: 0
B65: 3 | D65: 0 | E65: 0 | F65: 0 | G65: 0 | H65: 0 | I65: 0 | J65: 0 | K65: =SUM(E65:J65) -> 0 | L65: 0
B66: 3 | D66: 0 | E66: 0 | F66: 0 | G66: 0 | H66: 0 | I66: 0 | J66: 0 | K66: =SUM(E66:J66) -> 0 | L66: 0
B67: 3 | D67: 0 | E67: 0 | F67: 0 | G67: 0 | H67: 0 | I67: 0 | J67: 0 | K67: =SUM(E67:J67) -> 0 | L67: 0
... B118: 3 | D118: 0 | E118: 0 | F118: 0 | G118: 0 | H118: 0 | I118: 0 | J118: 0 | K118: =SUM(E118:J118) -> 0 | L118: 0
B119: 3 | K119: =SUM(E119:J119) -> 0
B120: 3 | D120: एकूण बेरीज | E120: =SUM(E39:E119) -> 37.5 | F120: =SUM(F39:F119) -> 37.5 | G120: =SUM(G39:G119) -> 0 | H120: =SUM(H39:H119) -> 0 | I120: =SUM(I39:I119) -> 0 | J120: =SUM(J39:J119) -> 25 | K120: =SUM(E120:J120) -> 100
K121: =SUM(E121:J121) -> 0
A122: XE23A301/W7-805 | B122: 4 | D122: प्रभाग क्र. 4 मध्ये विविध ठिकाणी ड्रेनेज दुरुस्ती विषयक कामे करणे | E122: 0 | F122: 0 | G122: 0 | H122: 0 | I122: 0 | J122: 7.5 | K122: =SUM(E122:J122) -> 7.5
A123: RE20A301/W2-907 | B123: 4 | D123: प्रभाग क्र. 4 मध्ये रस्ते विषयक कामे करणे | E123: 5 | F123: 0 | G123: 0 | H123: 0 | I123: 0 | J123: 0 | K123: =SUM(E123:J123) -> 5
A124: RE20C301/W1-508 | B124: 4 | D124: प्रभाग क्र. 4 मध्ये विविध ठिकाणी प्रकाश व्यवस्था करणे | E124: 0 | F124: 5 | G124: 0 | H124: 0 | I124: 0 | J124: 0 | K124: =SUM(E124:J124) -> 5
A125: RE20C301/W1-509 | B125: 4 | D125: प्रभाग क्र. 4 मध्ये विविध ठिकाणी विदयुत तारा भुमीगत करणे | E125: 0 | F125: 5 | G125: 0 | H125: 0 | I125: 0 | J125: 0 | K125: =SUM(E125:J125) -> 5
A126: RE20A301/W2-908 | B126: 4 | D126: प्रभाग क्र. 4 मध्ये फुटपाथ दुरुस्ती विषयक कामे करणे | E126: 2.5 | F126: 0 | G126: 0 | H126: 0 | I126: 0 | J126: 0 | K126: =SUM(E126:J126) -> 2.5
A127: RE20A301/W2-909 | B127: 4 | D127: प्रभाग क्र. 4 मध्ये विविध ठिकाणी रस्ते डांबरीकरण करणे | E127: 10 | F127: 0 | G127: 0 | H127: 0 | I127: 0 | J127: 0 | K127: =SUM(E127:J127) -> 10
A128: RE22C301/W4-701 | B128: 4 | D128: प्रभाग क्र. 4 मध्ये मनपा शाळेत विविध कामे करणे | E128: 0 | F128: 0 | G128: 5 | H128: 0 | I128: 0 | J128: 0 | K128: =SUM(E128:J128) -> 5
A129: RE20C301/W1-510 | B129: 4 | D129: प्रभाग क्र. 4 मध्ये वायरिंग विषयक कामे करणे | E129: 0 | F129: 5 | G129: 0 | H129: 0 | I129: 0 | J129: 0 | K129: =SUM(E129:J129) -> 5
A130: XE23A301/W7-806 | B130: 4 | D130: प्रभाग क्र. 4 मध्ये विविध ठिकाणी ड्रेनेज लाईन टाकणे | E130: 0 | F130: 0 | G130: 0 | H130: 0 | I130: 0 | J130: 5 | K130: =SUM(E130:J130) -> 5
A131: RE20A301/W2-910 | B131: 4 | D131: प्रभाग क्र. 4 मध्ये विविध ठिकाणी कॉक्रीटीकरण करणे | E131: 7.5 | F131: 0 | G131: 0 | H131: 0 | I131: 0 | J131: 0 | K131: =SUM(E131:J131) -> 7.5
A132: XE23A301/W7-807 | B132: 4 | D132: प्रभाग क्र. 4 मध्ये विविध ठिकाणी ड्रेनेज लाईन टाकणे | E132: 0 | F132: 0 | G132: 0 | H132: 0 | I132: 0 | J132: 5 | K132: =SUM(E132:J132) -> 5
A133: RE20C301/W1-511 | B133: 4 | D133: प्रभाग क्र. 4 मध्ये खराडी परिसरात विदयुत विषयक कामे करणे | E133: 0 | F133: 7.5 | G133: 0 | H133: 0 | I133: 0 | J133: 0 | K133: =SUM(E133:J133) -> 7.5
... A138: RE20A301/W2-913 | B138: 4 | D138: प्रभाग क्र. 4 मध्ये चंदननगर येथील गल्लीबोळ कॉक्रीटीकरण करणे | E138: 5 | F138: 0 | G138: 0 | H138: 0 | I138: 0 | J138: 0 | K138: =SUM(E138:J138) -> 5
B139: 4 | D139: 0 | E139: 0 | F139: 0 | G139: 0 | H139: 0 | I139: 0 | J139: 0 | K139: =SUM(E139:J139) -> 0 | L139: 0
B140: 4 | D140: 0 | E140: 0 | F140: 0 | G140: 0 | H140: 0 | I140: 0 | J140: 0 | K140: =SUM(E140:J140) -> 0 | L140: 0
B141: 4 | D141: 0 | E141: 0 | F141: 0 | G141: 0 | H141: 0 | I141: 0 | J141: 0 | K141: =SUM(E141:J141) -> 0 | L141: 0
B142: 4 | D142: 0 | E142: 0 | F142: 0 | G142: 0 | H142: 0 | I142: 0 | J142: 0 | K142: =SUM(E142:J142) -> 0 | L142: 0
B143: 4 | D143: 0 | E143: 0 | F143: 0 | G143: 0 | H143: 0 | I143: 0 | J143: 0 | K143: =SUM(E143:J143) -> 0 | L143: 0
B144: 4 | D144: 0 | E144: 0 | F144: 0 | G144: 0 | H144: 0 | I144: 0 | J144: 0 | K144: =SUM(E144:J144) -> 0 | L144: 0
B145: 4 | D145: 0 | E145: 0 | F145: 0 | G145: 0 | H145: 0 | I145: 0 | J145: 0 | K145: =SUM(E145:J145) -> 0 | L145: 0
B146: 4 | D146: 0 | E146: 0 | F146: 0 | G146: 0 | H146: 0 | I146: 0 | J146: 0 | K146: =SUM(E146:J146) -> 0 | L146: 0
B147: 4 | D147: 0 | E147: 0 | F147: 0 | G147: 0 | H147: 0 | I147: 0 | J147: 0 | K147: =SUM(E147:J147) -> 0 | L147: 0
B148: 4 | D148: 0 | E148: 0 | F148: 0 | G148: 0 | H148: 0 | I148: 0 | J148: 0 | K148: =SUM(E148:J148) -> 0 | L148: 0
B149: 4 | D149: 0 | E149: 0 | F149: 0 | G149: 0 | H149: 0 | I149: 0 | J149: 0 | K149: =SUM(E149:J149) -> 0 | L149: 0
B150: 4 | D150: 0 | E150: 0 | F150: 0 | G150: 0 | H150: 0 | I150: 0 | J150: 0 | K150: =SUM(E150:J150) -> 0 | L150: 0
... B201: 4 | D201: 0 | E201: 0 | F201: 0 | G201: 0 | H201: 0 | I201: 0 | J201: 0 | K201: =SUM(E201:J201) -> 0 | L201: 0
B202: 4 | K202: =SUM(E202:J202) -> 0
B203: 4 | D203: एकूण बेरीज | E203: =SUM(E122:E202) -> 45 | F203: =SUM(F122:F202) -> 27.5 | G203: =SUM(G122:G202) -> 5 | H203: =SUM(H122:H202) -> 0 | I203: =SUM(I122:I202) -> 0 | J203: =SUM(J122:J202) -> 22.5 | K203: =SUM(E203:J203) -> 100
K204: =SUM(E204:J204) -> 0
A205: RE20A301/W2-914 | B205: 5 | D205: प्रभाग क्र. 5 मध्ये वडगांवशेरी - कल्याणीनगर परिसरात व विविध ठिकाणी रस्ते डांबरीकरण करणे | E205: 10 | F205: 0 | G205: 0 | H205: 0 | I205: 0 | J205: 0 | K205: =SUM(E205:J205) -> 10
A206: XE23A301/W7-809 | B206: 5 | D206: प्रभाग क्र. 5 मध्ये वडगांवशेरी परिसरात ड्रेनेज लाईन टाकणे | E206: 0 | F206: 0 | G206: 0 | H206: 0 | I206: 0 | J206: 7.5 | K206: =SUM(E206:J206) -> 7.5
A207: RE20C301/W1-513 | B207: 5 | D207: प्रभाग क्र. 5 मध्ये वडगांवशेरी परिसरात नविन पोल उभे करणे | E207: 0 | F207: 5 | G207: 0 | H207: 0 | I207: 0 | J207: 0 | K207: =SUM(E207:J207) -> 5
A208: RE20C301/W1-514 | B208: 5 | D208: प्रभाग क्र. 5 मध्ये कल्याणीनगर येथे प्रकाश व्यवस्था करणे | E208: 0 | F208: 5 | G208: 0 | H208: 0 | I208: 0 | J208: 0 | K208: =SUM(E208:J208) -> 5
A209: RE20A301/W2-915 | B209: 5 | D209: प्रभाग क्र. 5 मध्ये रस्ते विकसित करणे | E209: 10 | F209: 0 | G209: 0 | H209: 0 | I209: 0 | J209: 0 | K209: =SUM(E209:J209) -> 10
A210: RE22C301/W4-702 | B210: 5 | D210: प्रभाग क्र. 5 मध्ये विविध सुधारणा कामे करणे | E210: 0 | F210: 0 | G210: 5 | H210: 0 | I210: 0 | J210: 0 | K210: =SUM(E210:J210) -> 5
A211: RE20C301/W1-515 | B211: 5 | D211: प्रभाग क्र. 5 मध्ये विविध ठिकाणी पोल उभे करणे | E211: 0 | F211: 5 | G211: 0 | H211: 0 | I211: 0 | J211: 0 | K211: =SUM(E211:J211) -> 5
A212: RE20C301/W1-516 | B212: 5 | D212: प्रभाग क्र. 5 मध्ये जुना मुंढवा रोड येथे पोल उभे लावणे | E212: 0 | F212: 5 | G212: 0 | H212: 0 | I212: 0 | J212: 0 | K212: =SUM(E212:J212) -> 5
A213: RE20A301/W2-916 | B213: 5 | D213: प्रभाग क्र. 5 मध्ये आदर्शनगर त्रिंबकेश्वर सोसायटी व परिसरात रस्ते विकसित करणे | E213: 10 | F213: 0 | G213: 0 | H213: 0 | I213: 0 | J213: 0 | K213: =SUM(E213:J213) -> 10
A214: RE22C301/W4-703 | B214: 5 | D214: प्रभाग क्र. 5 मध्ये विविध विकास कामे करणे | E214: 0 | F214: 0 | G214: 2.5 | H214: 0 | I214: 0 | J214: 0 | K214: =SUM(E214:J214) -> 2.5
...

Sheet WardOfficePlan2122
A1: code | B1: ward | C1: * | D1: क्षेत्रीय कार्यालयाने करावयाची योजनांतर्गत कामे : सन 2021-22 | E1: पथ | F1: विद्युत | G1: भवन | H1: झोनिपु | I1: पाणीपुरवठा | J1: मलनिःसारण | K1: एकूण | L1: H
D4: (आकडे लाखात) | E4: W2 | F4: W1 | G4: W4 | H4: W5 | I4: W6 | J4: W7
A6: code | B6: Sr. | C6: Wards | D6: =D1 -> क्षेत्रीय कार्यालयाने करावयाची योजनांतर्गत कामे : सन 2021-22 | E6: CE20A176/W2- | F6: CE20C118/W1- | G6: CE22A114/W4- | H6: FE14A118/W5- | I6: ZE16A115/W6- | J6: ZE16B113/W7- | K6: Total
B8: 1 | C8: 3, 4, 5 | D8: =D289 -> नगररोड - वडगावशेरी क्षेत्रीय कार्यालय एकूण बेरीज | E8: =E289 -> 45 | F8: =F289 -> 50 | G8: =G289 -> 25 | H8: =H289 -> 0 | I8: =I289 -> 0 | J8: =J289 -> 30 | K8: =SUM(E8:J8) -> 150
B9: 2 | C9: 1, 2, 6 | D9: =D544 -> येरवडा - कळस - धानोरी क्षेत्रीय कार्यालय एकूण बेरीज | E9: =E544 -> 0 | F9: =F544 -> 0 | G9: =G544 -> 0 | H9: =H544 -> 0 | I9: =I544 -> 0 | J9: =J544 -> 0 | K9: =SUM(E9:J9) -> 0
B10: 3 | C10: 20, 21 | D10: =D716 -> ढोलेपाटील क्षेत्रीय कार्यालय एकूण बेरीज | E10: =E716 -> 0 | F10: =F716 -> 0 | G10: =G716 -> 0 | H10: =H716 -> 0 | I10: =I716 -> 0 | J10: =J716 -> 0 | K10: =SUM(E10:J10) -> 0
B11: 4 | C11: 8, 9 | D11: =D888 -> औंध - बाणेर क्षेत्रीय कार्यालय एकूण बेरीज | E11: =E888 -> 0 | F11: =F888 -> 0 | G11: =G888 -> 0 | H11: =H888 -> 0 | I11: =I888 -> 0 | J11: =J888 -> 0 | K11: =SUM(E11:J11) -> 0
B12: 5 | C12: 7, 14 | D12: =D1060 -> शिवाजीनगर - घोले रोड क्षेत्रीय कार्यालय एकूण बेरीज | E12: =E1060 -> 0 | F12: =F1060 -> 0 | G12: =G1060 -> 0 | H12: =H1060 -> 0 | I12: =I1060 -> 0 | J12: =J1060 -> 0 | K12: =SUM(E12:J12) -> 0
B13: 6 | C13: 10, 11, 12 | D13: =D1315 -> कोथरूड - बावधन क्षेत्रीय कार्यालय एकूण बेरीज | E13: =E1315 -> 10 | F13: =F1315 -> 10 | G13: =G1315 -> 10 | H13: =H1315 -> 0 | I13: =I1315 -> 0 | J13: =J1315 -> 0 | K13: =SUM(E13:J13) -> 30
B14: 7 | C14: 35, 39, 40 | D14: =D1570 -> धनकवडी - सहकारनगर क्षेत्रीय कार्यालय एकूण बेरीज | E14: =E1570 -> 23.5 | F14: =F1570 -> 2.5 | G14: =G1570 -> 38.5 | H14: =H1570 -> 0 | I14: =I1570 -> 2.5 | J14: =J1570 -> 10 | K14: =SUM(E14:J14) -> 77
B15: 8 | C15: 30, 33, 34 | D15: =D1825 -> सिंहगड रोड क्षेत्रीय कार्यालय एकूण बेरीज | E15: =E1825 -> 171.45 | F15: =F1825 -> 32.5 | G15: =G1825 -> 60.05 | H15: =H1825 -> 60 | I15: =I1825 -> 0 | J15: =J1825 -> 126 | K15: =SUM(E15:J15) -> 450
B16: 9 | C16: 13, 31, 32 | D16: =D2080 -> वारजे - कर्वेनगर क्षेत्रीय कार्यालय एकूण बेरीज | E16: =E2080 -> 5 | F16: =F2080 -> 0 | G16: =G2080 -> 17.5 | H16: =H2080 -> 22.5 | I16: =I2080 -> 0 | J16: =J2080 -> 7.5 | K16: =SUM(E16:J16) -> 52.5
B17: 10 | C17: 22, 23, 26 | D17: =D2335 -> हडपसर - मुंढवा क्षेत्रीय कार्यालय एकूण बेरीज | E17: =E2335 -> 76.5 | F17: =F2335 -> 5 | G17: =G2335 -> 25 | H17: =H2335 -> 0 | I17: =I2335 -> 0 | J17: =J2335 -> 30 | K17: =SUM(E17:J17) -> 136.5
B18: 11 | C18: 24, 25, 27 | D18: =D2590 -> वानवडी - रामटेकडी क्षेत्रीय कार्यालय एकूण बेरीज | E18: =E2590 -> 69 | F18: =F2590 -> 40 | G18: =G2590 -> 10 | H18: =H2590 -> 0 | I18: =I2590 -> 0 | J18: =J2590 -> 22.5 | K18: =SUM(E18:J18) -> 141.5
B19: 12 | C19: 38, 41 | D19: =D2762 -> कोंढवा - येवलेवाडी क्षेत्रीय कार्यालय एकूण बेरीज | E19: =E2762 -> 42.5 | F19: =F2762 -> 59.5 | G19: =G2762 -> 0 | H19: =H2762 -> 0 | I19: =I2762 -> 0 | J19: =J2762 -> 25 | K19: =SUM(E19:J19) -> 127
B20: 13 | C20: 15, 16, 29 | D20: =D3017 -> कसबा - विश्रामबागवाडा क्षेत्रीय कार्यालय एकूण बेरीज | E20: =E3017 -> 0 | F20: =F3017 -> 0 | G20: =G3017 -> 0 | H20: =H3017 -> 0 | I20: =I3017 -> 0 | J20: =J3017 -> 0 | K20: =SUM(E20:J20) -> 0
B21: 14 | C21: 17, 18, 19 | D21: =D3272 -> भवानी पेठ क्षेत्रीय कार्यालय एकूण बेरीज | E21: =E3272 -> 0 | F21: =F3272 -> 0 | G21: =G3272 -> 0 | H21: =H3272 -> 0 | I21: =I3272 -> 0 | J21: =J3272 -> 0 | K21: =SUM(E21:J21) -> 0
B22: 15 | C22: 28, 36, 37 | D22: =D3527 -> बिबवेवाडी क्षेत्रीय कार्यालय एकूण बेरीज | E22: =E3527 -> 25 | F22: =F3527 -> 20 | G22: =G3527 -> 0 | H22: =H3527 -> 0 | I22: =I3527 -> 0 | J22: =J3527 -> 105 | K22: =SUM(E22:J22) -> 150
B23: 16 | C23: 42 | D23: =D3699 -> नव्याने समाविष्ट झालेली गावे एकूण बेरीज | E23: =E3699 -> 7.5 | F23: =F3699 -> 5 | G23: =G3699 -> 15 | H23: =H3699 -> 0 | I23: =I3699 -> 0 | J23: =J3699 -> 10 | K23: =SUM(E23:J23) -> 37.5
C25: =SUM(C8:C24) -> 42 | D25: =""&TEXT(D6,"0")&" एकूण बेरीज" -> क्षेत्रीय कार्यालयाने करावयाची योजनांतर्गत कामे : सन 2021-22 एकूण बेरीज | E25: =SUM(E8:E24) -> 475.45 | F25: =SUM(F8:F24) -> 224.5 | G25: =SUM(G8:G24) -> 201.05 | H25: =SUM(H8:H24) -> 82.5 | I25: =SUM(I8:I24) -> 2.5 | J25: =SUM(J8:J24) -> 366 | K25: =SUM(K8:K24) -> 1352
E27: =E25*100000 -> 47545000 | F27: =F25*100000 -> 22450000 | G27: =G25*100000 -> 20105000 | H27: =H25*100000 -> 8250000 | I27: =I25*100000 -> 250000 | J27: =J25*100000 -> 36600000 | K27: =K25*100000 -> 135200000 | L27: 0
L28: 0
L29: 0
L30: 0
L31: 0
L32: 0
L33: 0
L34: 0
L35: 0
L36: 0
D37: नगररोड - वडगावशेरी क्षेत्रीय कार्यालय | K37: =SUM(E37:J37) -> 0
K38: =SUM(E38:J38) -> 0
A39: CE20A176/W2-401 | B39: 3 | D39: प्रभाग क्र. 3 मध्ये विविध भागातील फुटपाथची कामे करणे | E39: 5 | F39: 0 | G39: 0 | H39: 0 | I39: 0 | J39: 0 | K39: =SUM(E39:J39) -> 5
A40: CE20C118/W1-301 | B40: 3 | D40: प्रभाग क्र. 3 संजयपार्क येथे विदयुत पुरवठा करणे | E40: 0 | F40: 5 | G40: 0 | H40: 0 | I40: 0 | J40: 0 | K40: =SUM(E40:J40) -> 5
A41: CE20C118/W1-302 | B41: 3 | D41: प्रभाग क्र. 3 मध्ये कलवड या ठिकाणी पोल टाकुन प्रकाश व्यवस्था करणे | E41: 0 | F41: 2.5 | G41: 0 | H41: 0 | I41: 0 | J41: 0 | K41: =SUM(E41:J41) -> 2.5
A42: CE20A176/W2-402 | B42: 3 | D42: प्रभाग क्र. 3 मध्ये विविध ठिकाणी फुटपाथ दुरुस्ती विषयक कामे करणे | E42: 5 | F42: 0 | G42: 0 | H42: 0 | I42: 0 | J42: 0 | K42: =SUM(E42:J42) -> 5
A43: ZE16B113/W7-401 | B43: 3 | D43: प्रभाग क्र. 3 मध्ये ड्रेनेज दुरुस्ती विषयक कामे करणे | E43: 0 | F43: 0 | G43: 0 | H43: 0 | I43: 0 | J43: 2.5 | K43: =SUM(E43:J43) -> 2.5
A44: ZE16B113/W7-402 | B44: 3 | D44: प्रभाग क्र. 3 मध्ये विविध भागात ड्रेनेज लाईन टाकणे | E44: 0 | F44: 0 | G44: 0 | H44: 0 | I44: 0 | J44: 5 | K44: =SUM(E44:J44) -> 5
A45: CE20C118/W1-303 | B45: 3 | D45: प्रभाग क्र. 3 मध्‍ये विविध ठिकाणी पोल बसविणे | E45: 0 | F45: 2.5 | G45: 0 | H45: 0 | I45: 0 | J45: 0 | K45: =SUM(E45:J45) -> 2.5
A46: CE20A176/W2-403 | B46: 3 | D46: प्रभाग क्र. 3 मध्ये विविध ठिकाणी रस्ते विकसित करणे | E46: 5 | F46: 0 | G46: 0 | H46: 0 | I46: 0 | J46: 0 | K46: =SUM(E46:J46) -> 5
A47: CE22A114/W4-301 | B47: 3 | D47: प्रभाग क्र. 3 मधील शौचालय दुरुस्ती करणे | E47: 0 | F47: 0 | G47: 5 | H47: 0 | I47: 0 | J47: 0 | K47: =SUM(E47:J47) -> 5
A48: CE20C118/W1-304 | B48: 3 | D48: प्रभाग क्र. 3 मध्ये कलवड इंदिरानगर व बर्माशेल भागात विदयुत विषयक कामे करणे | E48: 0 | F48: 5 | G48: 0 | H48: 0 | I48: 0 | J48: 0 | K48: =SUM(E48:J48) -> 5
A49: CE22A114/W4-302 | B49: 3 | D49: प्रभाग क्र. 3 म.गांधीनगर व जयप्रकाशनगर मधील शौचालयाच्या संपुर्ण दुरुस्त्या करणे | E49: 0 | F49: 0 | G49: 5 | H49: 0 | I49: 0 | J49: 0 | K49: =SUM(E49:J49) -> 5
A50: ZE16B113/W7-403 | B50: 3 | D50: प्रभाग क्र. 3 मधील गरजेची कामे कव मेंन्टन्सची कामे करणे | E50: 0 | F50: 0 | G50: 0 | H50: 0 | I50: 0 | J50: 2.5 | K50: =SUM(E50:J50) -> 2.5
B51: 3 | D51: 0 | E51: 0 | F51: 0 | G51: 0 | H51: 0 | I51: 0 | J51: 0 | K51: =SUM(E51:J51) -> 0 | L51: 0
B52: 3 | D52: 0 | E52: 0 | F52: 0 | G52: 0 | H52: 0 | I52: 0 | J52: 0 | K52: =SUM(E52:J52) -> 0 | L52: 0
B53: 3 | D53: 0 | E53: 0 | F53: 0 | G53: 0 | H53: 0 | I53: 0 | J53: 0 | K53: =SUM(E53:J53) -> 0 | L53: 0
B54: 3 | D54: 0 | E54: 0 | F54: 0 | G54: 0 | H54: 0 | I54: 0 | J54: 0 | K54: =SUM(E54:J54) -> 0 | L54: 0
B55: 3 | D55: 0 | E55: 0 | F55: 0 | G55: 0 | H55: 0 | I55: 0 | J55: 0 | K55: =SUM(E55:J55) -> 0 | L55: 0
B56: 3 | D56: 0 | E56: 0 | F56: 0 | G56: 0 | H56: 0 | I56: 0 | J56: 0 | K56: =SUM(E56:J56) -> 0 | L56: 0
B57: 3 | D57: 0 | E57: 0 | F57: 0 | G57: 0 | H57: 0 | I57: 0 | J57: 0 | K57: =SUM(E57:J57) -> 0 | L57: 0
B58: 3 | D58: 0 | E58: 0 | F58: 0 | G58: 0 | H58: 0 | I58: 0 | J58: 0 | K58: =SUM(E58:J58) -> 0 | L58: 0
B59: 3 | D59: 0 | E59: 0 | F59: 0 | G59: 0 | H59: 0 | I59: 0 | J59: 0 | K59: =SUM(E59:J59) -> 0 | L59: 0
B60: 3 | D60: 0 | E60: 0 | F60: 0 | G60: 0 | H60: 0 | I60: 0 | J60: 0 | K60: =SUM(E60:J60) -> 0 | L60: 0
B61: 3 | D61: 0 | E61: 0 | F61: 0 | G61: 0 | H61: 0 | I61: 0 | J61: 0 | K61: =SUM(E61:J61) -> 0 | L61: 0
B62: 3 | D62: 0 | E62: 0 | F62: 0 | G62: 0 | H62: 0 | I62: 0 | J62: 0 | K62: =SUM(E62:J62) -> 0 | L62: 0
... B118: 3 | D118: 0 | E118: 0 | F118: 0 | G118: 0 | H118: 0 | I118: 0 | J118: 0 | K118: =SUM(E118:J118) -> 0 | L118: 0
B119: 3 | K119: =SUM(E119:J119) -> 0
B120: 3 | D120: एकूण बेरीज | E120: =SUM(E39:E119) -> 15 | F120: =SUM(F39:F119) -> 15 | G120: =SUM(G39:G119) -> 10 | H120: =SUM(H39:H119) -> 0 | I120: =SUM(I39:I119) -> 0 | J120: =SUM(J39:J119) -> 10 | K120: =SUM(E120:J120) -> 50
K121: =SUM(E121:J121) -> 0
A122: CE20A176/W2-404 | B122: 4 | D122: प्रभाग क्र. 4 मध्ये विविध ठिकाणी डांबरीकरण करणे | E122: 2.5 | F122: 0 | G122: 0 | H122: 0 | I122: 0 | J122: 0 | K122: =SUM(E122:J122) -> 2.5
A123: CE22A114/W4-303 | B123: 4 | D123: प्रभाग क्र. 4 मध्ये शौचालय दुरुस्तीची कामे करणे | E123: 0 | F123: 0 | G123: 5 | H123: 0 | I123: 0 | J123: 0 | K123: =SUM(E123:J123) -> 5
A124: CE20A176/W2-405 | B124: 4 | D124: प्रभाग क्र. 4 मध्ये फुटपाथ दुरुस्ती विषयक कामे करणे | E124: 2.5 | F124: 0 | G124: 0 | H124: 0 | I124: 0 | J124: 0 | K124: =SUM(E124:J124) -> 2.5
A125: CE20A176/W2-406 | B125: 4 | D125: प्रभाग क्र. 4 मध्ये विविध ठिकाणी कॉक्रीट करणे | E125: 2.5 | F125: 0 | G125: 0 | H125: 0 | I125: 0 | J125: 0 | K125: =SUM(E125:J125) -> 2.5
A126: ZE16B113/W7-404 | B126: 4 | D126: प्रभाग क्र. 4 मध्ये विविध ठिकाणी ड्रेनेज दुरुस्ती विषयक कामे करणे | E126: 0 | F126: 0 | G126: 0 | H126: 0 | I126: 0 | J126: 2.5 | K126: =SUM(E126:J126) -> 2.5
A127: CE22A114/W4-304 | B127: 4 | D127: प्रभाग क्र. 4 मध्ये शौचालय दुरुस्ती विषयक कामे करणे | E127: 0 | F127: 0 | G127: 2.5 | H127: 0 | I127: 0 | J127: 0 | K127: =SUM(E127:J127) -> 2.5
A128: CE20C118/W1-305 | B128: 4 | D128: प्रभाग क्र. 4 मध्ये थिटे वस्ती परिसरात विदयुत विषयक कामे करणे | E128: 0 | F128: 5 | G128: 0 | H128: 0 | I128: 0 | J128: 0 | K128: =SUM(E128:J128) -> 5
A129: CE20C118/W1-306 | B129: 4 | D129: प्रभाग क्र. 4 मध्ये खराडी परिसरात प्रकाश व्यवस्था करणे | E129: 0 | F129: 2.5 | G129: 0 | H129: 0 | I129: 0 | J129: 0 | K129: =SUM(E129:J129) -> 2.5
A130: ZE16B113/W7-405 | B130: 4 | D130: प्रभाग क्र. 4 मध्ये ड्रेनेज चेंबर दुरुस्ती व तदनुषगिंक कामे करणे | E130: 0 | F130: 0 | G130: 0 | H130: 0 | I130: 0 | J130: 5 | K130: =SUM(E130:J130) -> 5
A131: CE20A176/W2-407 | B131: 4 | D131: प्रभाग क्र. 4 मध्ये विविध विकास कामे करणे | E131: 2.5 | F131: 0 | G131: 0 | H131: 0 | I131: 0 | J131: 0 | K131: =SUM(E131:J131) -> 2.5
A132: CE20C118/W1-307 | B132: 4 | D132: प्रभाग क्र. 4 मध्ये राजाराम पाटील नगर येथे विदयुत तारा भुमिगत करणे | E132: 0 | F132: 5 | G132: 0 | H132: 0 | I132: 0 | J132: 0 | K132: =SUM(E132:J132) -> 5
A133: CE20C118/W1-308 | B133: 4 | D133: प्रभाग क्र. 4 मध्ये नविन रस्त्यांवर पथदिवे बसविणे | E133: 0 | F133: 5 | G133: 0 | H133: 0 | I133: 0 | J133: 0 | K133: =SUM(E133:J133) -> 5
... A136: CE22A114/W4-306 | B136: 4 | D136: प्रभाग क्र. 4 मध्ये येथील शैाचालय दुरुस्ती विषयक कामे करणे | E136: 0 | F136: 0 | G136: 2.5 | H136: 0 | I136: 0 | J136: 0 | K136: =SUM(E136:J136) -> 2.5
B137: 4 | D137: 0 | E137: 0 | F137: 0 | G137: 0 | H137: 0 | I137: 0 | J137: 0 | K137: =SUM(E137:J137) -> 0 | L137: 0
B138: 4 | D138: 0 | E138: 0 | F138: 0 | G138: 0 | H138: 0 | I138: 0 | J138: 0 | K138: =SUM(E138:J138) -> 0 | L138: 0
B139: 4 | D139: 0 | E139: 0 | F139: 0 | G139: 0 | H139: 0 | I139: 0 | J139: 0 | K139: =SUM(E139:J139) -> 0 | L139: 0
B140: 4 | D140: 0 | E140: 0 | F140: 0 | G140: 0 | H140: 0 | I140: 0 | J140: 0 | K140: =SUM(E140:J140) -> 0 | L140: 0
B141: 4 | D141: 0 | E141: 0 | F141: 0 | G141: 0 | H141: 0 | I141: 0 | J141: 0 | K141: =SUM(E141:J141) -> 0 | L141: 0
B142: 4 | D142: 0 | E142: 0 | F142: 0 | G142: 0 | H142: 0 | I142: 0 | J142: 0 | K142: =SUM(E142:J142) -> 0 | L142: 0
B143: 4 | D143: 0 | E143: 0 | F143: 0 | G143: 0 | H143: 0 | I143: 0 | J143: 0 | K143: =SUM(E143:J143) -> 0 | L143: 0
B144: 4 | D144: 0 | E144: 0 | F144: 0 | G144: 0 | H144: 0 | I144: 0 | J144: 0 | K144: =SUM(E144:J144) -> 0 | L144: 0
B145: 4 | D145: 0 | E145: 0 | F145: 0 | G145: 0 | H145: 0 | I145: 0 | J145: 0 | K145: =SUM(E145:J145) -> 0 | L145: 0
B146: 4 | D146: 0 | E146: 0 | F146: 0 | G146: 0 | H146: 0 | I146: 0 | J146: 0 | K146: =SUM(E146:J146) -> 0 | L146: 0
B147: 4 | D147: 0 | E147: 0 | F147: 0 | G147: 0 | H147: 0 | I147: 0 | J147: 0 | K147: =SUM(E147:J147) -> 0 | L147: 0
B148: 4 | D148: 0 | E148: 0 | F148: 0 | G148: 0 | H148: 0 | I148: 0 | J148: 0 | K148: =SUM(E148:J148) -> 0 | L148: 0
... B201: 4 | D201: 0 | E201: 0 | F201: 0 | G201: 0 | H201: 0 | I201: 0 | J201: 0 | K201: =SUM(E201:J201) -> 0 | L201: 0
B202: 4 | K202: =SUM(E202:J202) -> 0
B203: 4 | D203: एकूण बेरीज | E203: =SUM(E122:E202) -> 10 | F203: =SUM(F122:F202) -> 20 | G203: =SUM(G122:G202) -> 12.5 | H203: =SUM(H122:H202) -> 0 | I203: =SUM(I122:I202) -> 0 | J203: =SUM(J122:J202) -> 7.5 | K203: =SUM(E203:J203) -> 50
K204: =SUM(E204:J204) -> 0
A205: ZE16B113/W7-406 | B205: 5 | D205: प्रभाग क्र. 5 मध्ये वडगांवशेरी कल्याणीनगर विविध ठिकाणी ड्रेनेज लाईन देखभाल दुरुस्ती विषयक कामे करणे | E205: 0 | F205: 0 | G205: 0 | H205: 0 | I205: 0 | J205: 5 | K205: =SUM(E205:J205) -> 5
A206: CE20A176/W2-408 | B206: 5 | D206: प्रभाग क्र. 5 मध्ये वडगांवशेरी व परिसरात रस्ते कॉक्रीटीकरण करणे | E206: 5 | F206: 0 | G206: 0 | H206: 0 | I206: 0 | J206: 0 | K206: =SUM(E206:J206) -> 5
A207: CE20C118/W1-310 | B207: 5 | D207: प्रभाग क्र. 5 मध्ये वडगांवशेरी गावठाण येथे विदयुत विषयक कामे करणे | E207: 0 | F207: 2.5 | G207: 0 | H207: 0 | I207: 0 | J207: 0 | K207: =SUM(E207:J207) -> 2.5
A208: ZE16B113/W7-407 | B208: 5 | D208: प्रभाग क्र. 5 मध्ये ड्रेनेज विषयक कामे करणे | E208: 0 | F208: 0 | G208: 0 | H208: 0 | I208: 0 | J208: 5 | K208: =SUM(E208:J208) -> 5
A209: CE20A176/W2-409 | B209: 5 | D209: प्रभाग क्र. 5 मध्ये फुटपाथ करणे ब्लॉक दुरुस्ती करणे | E209: 5 | F209: 0 | G209: 0 | H209: 0 | I209: 0 | J209: 0 | K209: =SUM(E209:J209) -> 5
A210: CE20C118/W1-311 | B210: 5 | D210: प्रभाग क्र. 5 मध्ये साईनाथ नगर येथे प्रकाश व्यवस्था करणे | E210: 0 | F210: 2.5 | G210: 0 | H210: 0 | I210: 0 | J210: 0 | K210: =SUM(E210:J210) -> 2.5
A211: CE20A176/W2-410 | B211: 5 | D211: प्रभाग क्र. 5 मध्ये सैनिकवाडी आदर्शनगर वडगावंशेरी परिसरात रस्ते विकसित करणे | E211: 5 | F211: 0 | G211: 0 | H211: 0 | I211: 0 | J211: 0 | K211: =SUM(E211:J211) -> 5
A212: CE20C118/W1-312 | B212: 5 | D212: प्रभाग क्र. 5 मध्ये नविन रस्त्यांवर पोल लावणे | E212: 0 | F212: 5 | G212: 0 | H212: 0 | I212: 0 | J212: 0 | K212: =SUM(E212:J212) -> 5
A213: CE22A114/W4-307 | B213: 5 | D213: प्रभाग क्र. 5 मध्ये शौचालय दुरुस्ती विषयक कामे करणे | E213: 0 | F213: 0 | G213: 2.5 | H213: 0 | I213: 0 | J213: 0 | K213: =SUM(E213:J213) -> 2.5
A214: CE20C118/W1-313 | B214: 5 | D214: प्रभाग क्र. 5 मध्ये माळवाडी व गलांडे नगर येथे विदयुत विषयक कामे करणे | E214: 0 | F214: 5 | G214: 0 | H214: 0 | I214: 0 | J214: 0 | K214: =SUM(E214:J214) -> 5
A215: CE20A176/W2-411 | B215: 5 | D215: प्रभाग क्र. 5 मध्ये रस्ते कॉक्रीट करणे | E215: 5 | F215: 0 | G215: 0 | H215: 0 | I215: 0 | J215: 0 | K215: =SUM(E215:J215) -> 5
...

Sheet CitizensNonPlan2122
A1: code | B1: ward | C1: * | D1: क्षेत्रीय कार्यालयाने नागरिकांच्या सहभागातून करावयाची योजनेतर कामे : सन 2021-22 | E1: पथ | F1: विद्युत | G1: भवन | H1: झोनिपु | I1: पाणीपुरवठा | J1: मलनिःसारण | K1: एकूण | L1: H
D4: (आकडे लाखात) | E4: C2 | F4: C1 | G4: C4 | H4: C5 | I4: C6 | J4: C7
A6: code | B6: Sr. | C6: Wards | D6: =D1 -> क्षेत्रीय कार्यालयाने नागरिकांच्या सहभागातून करावयाची योजनेतर कामे : सन 2021-22 | E6: RE20A302/C2- | F6: RE20C302/C1- | G6: RE22C302/C4- | H6: RE14B302/C5- | I6: XE12B302/C6- | J6: XE23A302/C7- | K6: Total
B8: 1 | C8: 3, 4, 5 | D8: =D289 -> नगररोड - वडगावशेरी क्षेत्रीय कार्यालय एकूण बेरीज | E8: =E289 -> 142 | F8: =F289 -> 20 | G8: =G289 -> 35 | H8: =H289 -> 13 | I8: =I289 -> 5 | J8: =J289 -> 85 | K8: =SUM(E8:J8) -> 300
B9: 2 | C9: 1, 2, 6 | D9: =D544 -> येरवडा - कळस - धानोरी क्षेत्रीय कार्यालय एकूण बेरीज | E9: =E544 -> 105 | F9: =F544 -> 30 | G9: =G544 -> 25 | H9: =H544 -> 35 | I9: =I544 -> 0 | J9: =J544 -> 105 | K9: =SUM(E9:J9) -> 300
B10: 3 | C10: 20, 21 | D10: =D716 -> ढोलेपाटील क्षेत्रीय कार्यालय एकूण बेरीज | E10: =E716 -> 34 | F10: =F716 -> 11.5 | G10: =G716 -> 29.5 | H10: =H716 -> 77.5 | I10: =I716 -> 0 | J10: =J716 -> 47.5 | K10: =SUM(E10:J10) -> 200
B11: 4 | C11: 8, 9 | D11: =D888 -> औंध - बाणेर क्षेत्रीय कार्यालय एकूण बेरीज | E11: =E888 -> 55 | F11: =F888 -> 50 | G11: =G888 -> 15 | H11: =H888 -> 65 | I11: =I888 -> 0 | J11: =J888 -> 15 | K11: =SUM(E11:J11) -> 200
B12: 5 | C12: 7, 14 | D12: =D1060 -> शिवाजीनगर - घोले रोड क्षेत्रीय कार्यालय एकूण बेरीज | E12: =E1060 -> 24 | F12: =F1060 -> 17 | G12: =G1060 -> 33 | H12: =H1060 -> 77 | I12: =I1060 -> 3 | J12: =J1060 -> 46 | K12: =SUM(E12:J12) -> 200
B13: 6 | C13: 10, 11, 12 | D13: =D1315 -> कोथरूड - बावधन क्षेत्रीय कार्यालय एकूण बेरीज | E13: =E1315 -> 100 | F13: =F1315 -> 2 | G13: =G1315 -> 15 | H13: =H1315 -> 43 | I13: =I1315 -> 0 | J13: =J1315 -> 88 | K13: =SUM(E13:J13) -> 248
B14: 7 | C14: 35, 39, 40 | D14: =D1570 -> धनकवडी - सहकारनगर क्षेत्रीय कार्यालय एकूण बेरीज | E14: =E1570 -> 76 | F14: =F1570 -> 30 | G14: =G1570 -> 33 | H14: =H1570 -> 20 | I14: =I1570 -> 0 | J14: =J1570 -> 103 | K14: =SUM(E14:J14) -> 262
B15: 8 | C15: 30, 33, 34 | D15: =D1825 -> सिंहगड रोड क्षेत्रीय कार्यालय एकूण बेरीज | E15: =E1825 -> 0 | F15: =F1825 -> 0 | G15: =G1825 -> 0 | H15: =H1825 -> 0 | I15: =I1825 -> 0 | J15: =J1825 -> 0 | K15: =SUM(E15:J15) -> 0
B16: 9 | C16: 13, 31, 32 | D16: =D2080 -> वारजे - कर्वेनगर क्षेत्रीय कार्यालय एकूण बेरीज | E16: =E2080 -> 60 | F16: =F2080 -> 0 | G16: =G2080 -> 0 | H16: =H2080 -> 0 | I16: =I2080 -> 0 | J16: =J2080 -> 60 | K16: =SUM(E16:J16) -> 120
B17: 10 | C17: 22, 23, 26 | D17: =D2335 -> हडपसर - मुंढवा क्षेत्रीय कार्यालय एकूण बेरीज | E17: =E2335 -> 105 | F17: =F2335 -> 25 | G17: =G2335 -> 20 | H17: =H2335 -> 0 | I17: =I2335 -> 10 | J17: =J2335 -> 125 | K17: =SUM(E17:J17) -> 285
B18: 11 | C18: 24, 25, 27 | D18: =D2590 -> वानवडी - रामटेकडी क्षेत्रीय कार्यालय एकूण बेरीज | E18: =E2590 -> 136 | F18: =F2590 -> 40 | G18: =G2590 -> 25 | H18: =H2590 -> 5 | I18: =I2590 -> 0 | J18: =J2590 -> 69 | K18: =SUM(E18:J18) -> 275
B19: 12 | C19: 38, 41 | D19: =D2762 -> कोंढवा - येवलेवाडी क्षेत्रीय कार्यालय एकूण बेरीज | E19: =E2762 -> 33 | F19: =F2762 -> 0 | G19: =G2762 -> 5 | H19: =H2762 -> 5 | I19: =I2762 -> 0 | J19: =J2762 -> 42 | K19: =SUM(E19:J19) -> 85
B20: 13 | C20: 15, 16, 29 | D20: =D3017 -> कसबा - विश्रामबागवाडा क्षेत्रीय कार्यालय एकूण बेरीज | E20: =E3017 -> 100 | F20: =F3017 -> 53 | G20: =G3017 -> 38 | H20: =H3017 -> 30 | I20: =I3017 -> 10 | J20: =J3017 -> 69 | K20: =SUM(E20:J20) -> 300
B21: 14 | C21: 17, 18, 19 | D21: =D3272 -> भवानी पेठ क्षेत्रीय कार्यालय एकूण बेरीज | E21: =E3272 -> 74 | F21: =F3272 -> 13 | G21: =G3272 -> 10 | H21: =H3272 -> 53 | I21: =I3272 -> 15 | J21: =J3272 -> 135 | K21: =SUM(E21:J21) -> 300
B22: 15 | C22: 28, 36, 37 | D22: =D3527 -> बिबवेवाडी क्षेत्रीय कार्यालय एकूण बेरीज | E22: =E3527 -> 45 | F22: =F3527 -> 35 | G22: =G3527 -> 15 | H22: =H3527 -> 20 | I22: =I3527 -> 0 | J22: =J3527 -> 70 | K22: =SUM(E22:J22) -> 185
B23: 16 | C23: 42 | D23: =D3699 -> नव्याने समाविष्ट झालेली गावे एकूण बेरीज | E23: =E3699 -> 15 | F23: =F3699 -> 10 | G23: =G3699 -> 0 | H23: =H3699 -> 0 | I23: =I3699 -> 0 | J23: =J3699 -> 0 | K23: =SUM(E23:J23) -> 25
C25: =SUM(C8:C24) -> 42 | D25: =""&TEXT(D6,"0")&" एकूण बेरीज" -> क्षेत्रीय कार्यालयाने नागरिकांच्या सहभागातून करावयाची योजनेतर कामे : सन 2021-22 एकूण बेरीज | E25: =SUM(E8:E24) -> 1104 | F25: =SUM(F8:F24) -> 336.5 | G25: =SUM(G8:G24) -> 298.5 | H25: =SUM(H8:H24) -> 443.5 | I25: =SUM(I8:I24) -> 43 | J25: =SUM(J8:J24) -> 1059.5 | K25: =SUM(K8:K24) -> 3285
E27: =E25*100000 -> 110400000 | F27: =F25*100000 -> 33650000 | G27: =G25*100000 -> 29850000 | H27: =H25*100000 -> 44350000 | I27: =I25*100000 -> 4300000 | J27: =J25*100000 -> 105950000 | K27: =K25*100000 -> 328500000 | L27: 0
L28: 0
L29: 0
L30: 0
L31: 0
L32: 0
L33: 0
L34: 0
L35: 0
L36: 0
D37: नगररोड - वडगावशेरी क्षेत्रीय कार्यालय | K37: =SUM(E37:J37) -> 0
K38: =SUM(E38:J38) -> 0
A39: RE20A302/C2-701 | B39: 3 | D39: प्रभाग क्र.३ मध्ये नविन विकसित रोडला साईटपटटी मारणे | E39: 5 | F39: 0 | G39: 0 | H39: 0 | I39: 0 | J39: 0 | K39: =SUM(E39:J39) -> 5
A40: RE20A302/C2-702 | B40: 3 | D40: प्रभाग क्र.३ धनलक्ष्मी सोसायटी येथील लेन मध्‍ये ब्लॉक बसविणे | E40: 5 | F40: 0 | G40: 0 | H40: 0 | I40: 0 | J40: 0 | K40: =SUM(E40:J40) -> 5
A41: RE22C302/C4-721 | B41: 3 | D41: प्रभाग क्र.३ मधील समाज मंदिरामध्‍ये विविध विकास कामे करणे | E41: 0 | F41: 0 | G41: 5 | H41: 0 | I41: 0 | J41: 0 | K41: =SUM(E41:J41) -> 5
A42: RE20A302/C2-703 | B42: 3 | D42: प्रभाग क्र.३ बॉम्बे सैपर्स कॉलनी येथे रस्ता ग्राउंटींग करुन डांबरीकरण करणे | E42: 5 | F42: 0 | G42: 0 | H42: 0 | I42: 0 | J42: 0 | K42: =SUM(E42:J42) -> 5
A43: XE23A302/C7-1101 | B43: 3 | D43: प्रभाग क्र.३ जंगदबा सोसायटी येथील लेन मध्‍ये ड्रेनेज लाईन टाकणे | E43: 0 | F43: 0 | G43: 0 | H43: 0 | I43: 0 | J43: 5 | K43: =SUM(E43:J43) -> 5
A44: XE12B302/C6-301 | B44: 3 | D44: प्रभाग क्र.३ मध्‍ये सर्वे नं.199 यमुनानगर (वस्ती) विमाननगर,पुणे -14 यमुनानगर वस्ती मध्‍ये 2 शौचालय उपलब्ध असुन त्याची देखभाल व स्वच्छता राखणे | E44: 0 | F44: 0 | G44: 0 | H44: 0 | I44: 5 | J44: 0 | K44: =SUM(E44:J44) -> 5
A45: RE20A302/C2-704 | B45: 3 | D45: प्रभाग क्र.३ मध्‍ये बॉम्बे सैपर्स कॉलनी येथे फुटपाथ विकसित करणे | E45: 5 | F45: 0 | G45: 0 | H45: 0 | I45: 0 | J45: 0 | K45: =SUM(E45:J45) -> 5
A46: RE22C302/C4-722 | B46: 3 | D46: प्रभाग क्र.३ मध्‍ये सर्वे नं.199 यमुनानगर (वस्ती) विमाननगर मधील सम्राट चौक पासुन दोन्ही बाजुने रस्तेच्या बाजुची भिंत रंगकाम करुन चित्रीकरण करणे | E46: 0 | F46: 0 | G46: 5 | H46: 0 | I46: 0 | J46: 0 | K46: =SUM(E46:J46) -> 5
A47: XE23A302/C7-1102 | B47: 3 | D47: प्रभाग क्र.३ विमाननगर, साकोरेनगर ड्रेनेज लाईन साफ करणे | E47: 0 | F47: 0 | G47: 0 | H47: 0 | I47: 0 | J47: 5 | K47: =SUM(E47:J47) -> 5
A48: RE20C302/C1-601 | B48: 3 | D48: प्रभाग क्र.३ ऑपईस सोसा ते कोवीड केअर सेंटर पर्यंत स्ट्रीट लाईट दुरुस्त करणे | E48: 0 | F48: 5 | G48: 0 | H48: 0 | I48: 0 | J48: 0 | K48: =SUM(E48:J48) -> 5
A49: RE20A302/C2-705 | B49: 3 | D49: प्रभाग क्र.३ गांधीनगर मजिद गल्लीत खोदलेले रस्ते व चेंबरची दुरस्ती करणे | E49: 5 | F49: 0 | G49: 0 | H49: 0 | I49: 0 | J49: 0 | K49: =SUM(E49:J49) -> 5
A50: RE14B302/C5-601 | B50: 3 | D50: प्र.क्र.३ गांधीनगर व जयप्रकाशनगर मधील शौचालयत मुतारीमध्‍ये नळ बसविणे व दरवाजे बसविणे, गरजेच्या दुरुस्त्या करणे | E50: 0 | F50: 0 | G50: 0 | H50: 3 | I50: 0 | J50: 0 | K50: =SUM(E50:J50) -> 3
... A59: XE23A302/C7-1104 | B59: 3 | D59: प्रभाग क्र.३ संजयपार्क परिसरात विविध ठिकाणी ड्रेनेज लाईन टाकणे व साफसफाई करणे | E59: 0 | F59: 0 | G59: 0 | H59: 0 | I59: 0 | J59: 5 | K59: =SUM(E59:J59) -> 5
B60: 3 | D60: 0 | E60: 0 | F60: 0 | G60: 0 | H60: 0 | I60: 0 | J60: 0 | K60: =SUM(E60:J60) -> 0 | L60: 0
B61: 3 | D61: 0 | E61: 0 | F61: 0 | G61: 0 | H61: 0 | I61: 0 | J61: 0 | K61: =SUM(E61:J61) -> 0 | L61: 0
B62: 3 | D62: 0 | E62: 0 | F62: 0 | G62: 0 | H62: 0 | I62: 0 | J62: 0 | K62: =SUM(E62:J62) -> 0 | L62: 0
B63: 3 | D63: 0 | E63: 0 | F63: 0 | G63: 0 | H63: 0 | I63: 0 | J63: 0 | K63: =SUM(E63:J63) -> 0 | L63: 0
B64: 3 | D64: 0 | E64: 0 | F64: 0 | G64: 0 | H64: 0 | I64: 0 | J64: 0 | K64: =SUM(E64:J64) -> 0 | L64: 0
B65: 3 | D65: 0 | E65: 0 | F65: 0 | G65: 0 | H65: 0 | I65: 0 | J65: 0 | K65: =SUM(E65:J65) -> 0 | L65: 0
B66: 3 | D66: 0 | E66: 0 | F66: 0 | G66: 0 | H66: 0 | I66: 0 | J66: 0 | K66: =SUM(E66:J66) -> 0 | L66: 0
B67: 3 | D67: 0 | E67: 0 | F67: 0 | G67: 0 | H67: 0 | I67: 0 | J67: 0 | K67: =SUM(E67:J67) -> 0 | L67: 0
B68: 3 | D68: 0 | E68: 0 | F68: 0 | G68: 0 | H68: 0 | I68: 0 | J68: 0 | K68: =SUM(E68:J68) -> 0 | L68: 0
B69: 3 | D69: 0 | E69: 0 | F69: 0 | G69: 0 | H69: 0 | I69: 0 | J69: 0 | K69: =SUM(E69:J69) -> 0 | L69: 0
B70: 3 | D70: 0 | E70: 0 | F70: 0 | G70: 0 | H70: 0 | I70: 0 | J70: 0 | K70: =SUM(E70:J70) -> 0 | L70: 0
B71: 3 | D71: 0 | E71: 0 | F71: 0 | G71: 0 | H71: 0 | I71: 0 | J71: 0 | K71: =SUM(E71:J71) -> 0 | L71: 0
... B118: 3 | D118: 0 | E118: 0 | F118: 0 | G118: 0 | H118: 0 | I118: 0 | J118: 0 | K118: =SUM(E118:J118) -> 0 | L118: 0
B119: 3 | K119: =SUM(E119:J119) -> 0
B120: 3 | D120: एकूण बेरीज | E120: =SUM(E39:E119) -> 47 | F120: =SUM(F39:F119) -> 5 | G120: =SUM(G39:G119) -> 15 | H120: =SUM(H39:H119) -> 8 | I120: =SUM(I39:I119) -> 5 | J120: =SUM(J39:J119) -> 20 | K120: =SUM(E120:J120) -> 100
K121: =SUM(E121:J121) -> 0
A122: RE20A302/C2-711 | B122: 4 | D122: प्रभाग क्र. ४ खराडी,चंदननगर,गणेशनगर परिसरातील राडारोडा उचलणे | E122: 5 | F122: 0 | G122: 0 | H122: 0 | I122: 0 | J122: 0 | K122: =SUM(E122:J122) -> 5
A123: RE20A302/C2-712 | B123: 4 | D123: प्रभाग क्र. ४ खुळेवाडी परिसरात गल्लीबोळ कॉक्रीटीकरण करणे | E123: 5 | F123: 0 | G123: 0 | H123: 0 | I123: 0 | J123: 0 | K123: =SUM(E123:J123) -> 5
A124: XE23A302/C7-1105 | B124: 4 | D124: प्रभाग क्र. ४ बिडीकामगार वसाहत ,खराडी येथे ड्रेनेज लाईन | E124: 0 | F124: 0 | G124: 0 | H124: 0 | I124: 0 | J124: 5 | K124: =SUM(E124:J124) -> 5
A125: RE20A302/C2-713 | B125: 4 | D125: थिटेवस्ती चंदननगर, खराडी परिसरात खोदलेल्या रस्त्याचे डांबरीकरण करणे | E125: 5 | F125: 0 | G125: 0 | H125: 0 | I125: 0 | J125: 0 | K125: =SUM(E125:J125) -> 5
A126: RE14B302/C5-603 | B126: 4 | D126: प्रभाग क्र 4 खराडी चंदननगर,परिसरातील सार्वजनिक शौचालयांची दुरस्ती करणे | E126: 0 | F126: 0 | G126: 0 | H126: 5 | I126: 0 | J126: 0 | K126: =SUM(E126:J126) -> 5
A127: XE23A302/C7-1106 | B127: 4 | D127: प्रभाग क्र. ४ मधील थिटेवस्ती गल्ली नं.10,11 मधील खराब झालेली ड्रेनेज चेंबर दुरस्ती करणे | E127: 0 | F127: 0 | G127: 0 | H127: 0 | I127: 0 | J127: 5 | K127: =SUM(E127:J127) -> 5
A128: RE20A302/C2-714 | B128: 4 | D128: प्रभाग क्र. ४ गल्ली नं.11 राजाराम पाटील येथील रस्ता डांबरीकरण करणे | E128: 5 | F128: 0 | G128: 0 | H128: 0 | I128: 0 | J128: 0 | K128: =SUM(E128:J128) -> 5
A129: RE20A302/C2-715 | B129: 4 | D129: प्रभाग क्र. ४ श्री मकाजी माशाब यांच्या घराजवळील गल्ली काँक्रीटीकरण करणे | E129: 5 | F129: 0 | G129: 0 | H129: 0 | I129: 0 | J129: 0 | K129: =SUM(E129:J129) -> 5
A130: XE23A302/C7-1107 | B130: 4 | D130: प्रभाग क्र. ४ सर्व्हे नं.10/11 संभाजीनगर येथील झीरमिरे यांच्या घरासमोरील ड्रेनेज लाईन टाकणे | E130: 0 | F130: 0 | G130: 0 | H130: 0 | I130: 0 | J130: 5 | K130: =SUM(E130:J130) -> 5
A131: RE20C302/C1-602 | B131: 4 | D131: प्र.क्र. ४ सर्व्हे नं.10/11 सर्व परिसरातील पथदिवे (एल ई डी)चेंज करणे (नविन टाकणे) व विदयुत विषयक कामे करणे | E131: 0 | F131: 7 | G131: 0 | H131: 0 | I131: 0 | J131: 0 | K131: =SUM(E131:J131) -> 7
A132: XE23A302/C7-1108 | B132: 4 | D132: प्रभाग क्र. ४ ड्रेनेज लाईन तुंबत असुन तेथे ड्रेनेज लाईन नाही लाईट खांब नाही व डांबरीकरण करणे | E132: 0 | F132: 0 | G132: 0 | H132: 0 | I132: 0 | J132: 5 | K132: =SUM(E132:J132) -> 5
A133: XE23A302/C7-1109 | B133: 4 | D133: प्रभाग क्र. ४ परिसरातील सर्व ड्रेनेज लाईन दुरुस्त करणे | E133: 0 | F133: 0 | G133: 0 | H133: 0 | I133: 0 | J133: 5 | K133: =SUM(E133:J133) -> 5
... A140: XE23A302/C7-1112 | B140: 4 | D140: प्रभाग क्र. ४ खराडी,चंदननगर,परिसरात ड्रेनेज दुरस्तीविषयक कामे करणे | E140: 0 | F140: 0 | G140: 0 | H140: 0 | I140: 0 | J140: 5 | K140: =SUM(E140:J140) -> 5
B141: 4 | D141: 0 | E141: 0 | F141: 0 | G141: 0 | H141: 0 | I141: 0 | J141: 0 | K141: =SUM(E141:J141) -> 0 | L141: 0
B142: 4 | D142: 0 | E142: 0 | F142: 0 | G142: 0 | H142: 0 | I142: 0 | J142: 0 | K142: =SUM(E142:J142) -> 0 | L142: 0
B143: 4 | D143: 0 | E143: 0 | F143: 0 | G143: 0 | H143: 0 | I143: 0 | J143: 0 | K143: =SUM(E143:J143) -> 0 | L143: 0
B144: 4 | D144: 0 | E144: 0 | F144: 0 | G144: 0 | H144: 0 | I144: 0 | J144: 0 | K144: =SUM(E144:J144) -> 0 | L144: 0
B145: 4 | D145: 0 | E145: 0 | F145: 0 | G145: 0 | H145: 0 | I145: 0 | J145: 0 | K145: =SUM(E145:J145) -> 0 | L145: 0
B146: 4 | D146: 0 | E146: 0 | F146: 0 | G146: 0 | H146: 0 | I146: 0 | J146: 0 | K146: =SUM(E146:J146) -> 0 | L146: 0
B147: 4 | D147: 0 | E147: 0 | F147: 0 | G147: 0 | H147: 0 | I147: 0 | J147: 0 | K147: =SUM(E147:J147) -> 0 | L147: 0
B148: 4 | D148: 0 | E148: 0 | F148: 0 | G148: 0 | H148: 0 | I148: 0 | J148: 0 | K148: =SUM(E148:J148) -> 0 | L148: 0
B149: 4 | D149: 0 | E149: 0 | F149: 0 | G149: 0 | H149: 0 | I149: 0 | J149: 0 | K149: =SUM(E149:J149) -> 0 | L149: 0
B150: 4 | D150: 0 | E150: 0 | F150: 0 | G150: 0 | H150: 0 | I150: 0 | J150: 0 | K150: =SUM(E150:J150) -> 0 | L150: 0
B151: 4 | D151: 0 | E151: 0 | F151: 0 | G151: 0 | H151: 0 | I151: 0 | J151: 0 | K151: =SUM(E151:J151) -> 0 | L151: 0
B152: 4 | D152: 0 | E152: 0 | F152: 0 | G152: 0 | H152: 0 | I152: 0 | J152: 0 | K152: =SUM(E152:J152) -> 0 | L152: 0
... B201: 4 | D201: 0 | E201: 0 | F201: 0 | G201: 0 | H201: 0 | I201: 0 | J201: 0 | K201: =SUM(E201:J201) -> 0 | L201: 0
B202: 4 | K202: =SUM(E202:J202) -> 0
B203: 4 | D203: एकूण बेरीज | E203: =SUM(E122:E202) -> 40 | F203: =SUM(F122:F202) -> 15 | G203: =SUM(G122:G202) -> 0 | H203: =SUM(H122:H202) -> 5 | I203: =SUM(I122:I202) -> 0 | J203: =SUM(J122:J202) -> 40 | K203: =SUM(E203:J203) -> 100
K204: =SUM(E204:J204) -> 0
A205: RE20A302/C2-719 | B205: 5 | D205: प्रभाग क्र.५ मध्‍ये विविध ठिकाणी गल्लीबोळ काँक्रीट करणे | E205: 5 | F205: 0 | G205: 0 | H205: 0 | I205: 0 | J205: 0 | K205: =SUM(E205:J205) -> 5
A206: RE20A302/C2-720 | B206: 5 | D206: प्रभाग क्र.५ मधील विविध ठिकाणी सिमेंट काँक्रीट रस्त्याच्या मधील खचलेले पेव्हिंग ब्लॉक दुरस्त करणे | E206: 5 | F206: 0 | G206: 0 | H206: 0 | I206: 0 | J206: 0 | K206: =SUM(E206:J206) -> 5
A207: XE23A302/C7-1113 | B207: 5 | D207: प्रभाग क्र.५ मध्‍ये विविध ठिकाणी ड्रेनेज दुरस्ती व साफसफाई करणे | E207: 0 | F207: 0 | G207: 0 | H207: 0 | I207: 0 | J207: 5 | K207: =SUM(E207:J207) -> 5
A208: RE22C302/C4-724 | B208: 5 | D208: प्रभाग क्र.५ मधील ज्येष्ठ नागरिक संघ यांचे हॉलमध्ये विविध सुधारणा कामे करणे | E208: 0 | F208: 0 | G208: 5 | H208: 0 | I208: 0 | J208: 0 | K208: =SUM(E208:J208) -> 5
A209: RE20A302/C2-721 | B209: 5 | D209: प्रभाग क्र.५ मध्ये विविध ठिकाणी राडारोडा उचलणे | E209: 5 | F209: 0 | G209: 0 | H209: 0 | I209: 0 | J209: 0 | K209: =SUM(E209:J209) -> 5
A210: RE22C302/C4-725 | B210: 5 | D210: प्रभाग क्र.५ बौध्द विहारात सुधारणा कामे करणे | E210: 0 | F210: 0 | G210: 5 | H210: 0 | I210: 0 | J210: 0 | K210: =SUM(E210:J210) -> 5
A211: RE20A302/C2-722 | B211: 5 | D211: प्रभाग क्र.५ च्या ठिकाणी विविध ठिकाणी रस्ते कॉक्रीटीकरण करणे | E211: 5 | F211: 0 | G211: 0 | H211: 0 | I211: 0 | J211: 0 | K211: =SUM(E211:J211) -> 5
A212: RE20A302/C2-723 | B212: 5 | D212: प्रभाग क्र.५ च्या ठिकाणी विविध ठिकाणी ब्लॉक दुरस्त करणे | E212: 5 | F212: 0 | G212: 0 | H212: 0 | I212: 0 | J212: 0 | K212: =SUM(E212:J212) -> 5
A213: RE20A302/C2-724 | B213: 5 | D213: प्रभाग क्र.५ मध्से संत जोसेफ कॉलनी या ठिकाणी रस्ते डांबरीकरण करणे | E213: 5 | F213: 0 | G213: 0 | H213: 0 | I213: 0 | J213: 0 | K213: =SUM(E213:J213) -> 5
A214: RE20A302/C2-725 | B214: 5 | D214: प्रभाग क्र.५ मध्ये विविध ठिकाणी रेलिंग बसविणे | E214: 5 | F214: 0 | G214: 0 | H214: 0 | I214: 0 | J214: 0 | K214: =SUM(E214:J214) -> 5
...

Sheet CitizensPlan2122
A1: code | B1: ward | C1: * | D1: क्षेत्रीय कार्यालयाने नागरिकांच्या सहभागातून करावयाची योजनांतर्गत कामे : सन 2021-22 | E1: पथ | F1: विद्युत | G1: भवन | H1: झोनिपु | I1: पाणीपुरवठा | J1: मलनिःसारण | K1: एकूण | L1: H
D4: (आकडे लाखात) | E4: C2 | F4: C1 | G4: C4 | H4: C5 | I4: C6 | J4: C7
A6: code | B6: Sr. | C6: Wards | D6: =D1 -> क्षेत्रीय कार्यालयाने नागरिकांच्या सहभागातून करावयाची योजनांतर्गत कामे : सन 2021-22 | E6: CE20A1196/C2- | F6: CE20C406/C1- | G6: CE22A547/C4- | H6: FE14A121/C5- | I6: ZE16A117/C6- | J6: ZE16B130/C7- | K6: Total
B8: 1 | C8: 3, 4, 5 | D8: =D289 -> नगररोड - वडगावशेरी क्षेत्रीय कार्यालय एकूण बेरीज | E8: =E289 -> 0 | F8: =F289 -> 0 | G8: =G289 -> 0 | H8: =H289 -> 0 | I8: =I289 -> 0 | J8: =J289 -> 0 | K8: =SUM(E8:J8) -> 0
B9: 2 | C9: 1, 2, 6 | D9: =D544 -> येरवडा - कळस - धानोरी क्षेत्रीय कार्यालय एकूण बेरीज | E9: =E544 -> 0 | F9: =F544 -> 0 | G9: =G544 -> 0 | H9: =H544 -> 0 | I9: =I544 -> 0 | J9: =J544 -> 0 | K9: =SUM(E9:J9) -> 0
B10: 3 | C10: 20, 21 | D10: =D716 -> ढोलेपाटील क्षेत्रीय कार्यालय एकूण बेरीज | E10: =E716 -> 0 | F10: =F716 -> 0 | G10: =G716 -> 0 | H10: =H716 -> 0 | I10: =I716 -> 0 | J10: =J716 -> 0 | K10: =SUM(E10:J10) -> 0
B11: 4 | C11: 8, 9 | D11: =D888 -> औंध - बाणेर क्षेत्रीय कार्यालय एकूण बेरीज | E11: =E888 -> 0 | F11: =F888 -> 0 | G11: =G888 -> 0 | H11: =H888 -> 0 | I11: =I888 -> 0 | J11: =J888 -> 0 | K11: =SUM(E11:J11) -> 0
B12: 5 | C12: 7, 14 | D12: =D1060 -> शिवाजीनगर - घोले रोड क्षेत्रीय कार्यालय एकूण बेरीज | E12: =E1060 -> 0 | F12: =F1060 -> 0 | G12: =G1060 -> 0 | H12: =H1060 -> 0 | I12: =I1060 -> 0 | J12: =J1060 -> 0 | K12: =SUM(E12:J12) -> 0
B13: 6 | C13: 10, 11, 12 | D13: =D1315 -> कोथरूड - बावधन क्षेत्रीय कार्यालय एकूण बेरीज | E13: =E1315 -> 33 | F13: =F1315 -> 9 | G13: =G1315 -> 0 | H13: =H1315 -> 0 | I13: =I1315 -> 5 | J13: =J1315 -> 5 | K13: =SUM(E13:J13) -> 52
B14: 7 | C14: 35, 39, 40 | D14: =D1570 -> धनकवडी - सहकारनगर क्षेत्रीय कार्यालय एकूण बेरीज | E14: =E1570 -> 20 | F14: =F1570 -> 0 | G14: =G1570 -> 18 | H14: =H1570 -> 0 | I14: =I1570 -> 0 | J14: =J1570 -> 0 | K14: =SUM(E14:J14) -> 38
B15: 8 | C15: 30, 33, 34 | D15: =D1825 -> सिंहगड रोड क्षेत्रीय कार्यालय एकूण बेरीज | E15: =E1825 -> 130 | F15: =F1825 -> 65 | G15: =G1825 -> 0 | H15: =H1825 -> 40 | I15: =I1825 -> 0 | J15: =J1825 -> 65 | K15: =SUM(E15:J15) -> 300
B16: 9 | C16: 13, 31, 32 | D16: =D2080 -> वारजे - कर्वेनगर क्षेत्रीय कार्यालय एकूण बेरीज | E16: =E2080 -> 70 | F16: =F2080 -> 20 | G16: =G2080 -> 60 | H16: =H2080 -> 15 | I16: =I2080 -> 0 | J16: =J2080 -> 15 | K16: =SUM(E16:J16) -> 180
B17: 10 | C17: 22, 23, 26 | D17: =D2335 -> हडपसर - मुंढवा क्षेत्रीय कार्यालय एकूण बेरीज | E17: =E2335 -> 5 | F17: =F2335 -> 5 | G17: =G2335 -> 0 | H17: =H2335 -> 0 | I17: =I2335 -> 0 | J17: =J2335 -> 5 | K17: =SUM(E17:J17) -> 15
B18: 11 | C18: 24, 25, 27 | D18: =D2590 -> वानवडी - रामटेकडी क्षेत्रीय कार्यालय एकूण बेरीज | E18: =E2590 -> 0 | F18: =F2590 -> 0 | G18: =G2590 -> 0 | H18: =H2590 -> 0 | I18: =I2590 -> 0 | J18: =J2590 -> 0 | K18: =SUM(E18:J18) -> 0
B19: 12 | C19: 38, 41 | D19: =D2762 -> कोंढवा - येवलेवाडी क्षेत्रीय कार्यालय एकूण बेरीज | E19: =E2762 -> 66 | F19: =F2762 -> 26 | G19: =G2762 -> 0 | H19: =H2762 -> 0 | I19: =I2762 -> 0 | J19: =J2762 -> 23 | K19: =SUM(E19:J19) -> 115
B20: 13 | C20: 15, 16, 29 | D20: =D3017 -> कसबा - विश्रामबागवाडा क्षेत्रीय कार्यालय एकूण बेरीज | E20: =E3017 -> 0 | F20: =F3017 -> 0 | G20: =G3017 -> 0 | H20: =H3017 -> 0 | I20: =I3017 -> 0 | J20: =J3017 -> 0 | K20: =SUM(E20:J20) -> 0
B21: 14 | C21: 17, 18, 19 | D21: =D3272 -> भवानी पेठ क्षेत्रीय कार्यालय एकूण बेरीज | E21: =E3272 -> 0 | F21: =F3272 -> 0 | G21: =G3272 -> 0 | H21: =H3272 -> 0 | I21: =I3272 -> 0 | J21: =J3272 -> 0 | K21: =SUM(E21:J21) -> 0
B22: 15 | C22: 28, 36, 37 | D22: =D3527 -> बिबवेवाडी क्षेत्रीय कार्यालय एकूण बेरीज | E22: =E3527 -> 45 | F22: =F3527 -> 15 | G22: =G3527 -> 15 | H22: =H3527 -> 0 | I22: =I3527 -> 0 | J22: =J3527 -> 15 | K22: =SUM(E22:J22) -> 90
B23: 16 | C23: 42 | D23: =D3699 -> नव्याने समाविष्ट झालेली गावे एकूण बेरीज | E23: =E3699 -> 10 | F23: =F3699 -> 5 | G23: =G3699 -> 10 | H23: =H3699 -> 0 | I23: =I3699 -> 0 | J23: =J3699 -> 0 | K23: =SUM(E23:J23) -> 25
