Workbook
Name BdgtNo: #REF!
Name BdgtYear: #REF!
Name CurrentYear: #REF!
Name Description: "P_A_C_Ex"
Name Head: #REF!
Name Last2Yr: #REF!
Name Last3Yr: #REF!
Name Last4Yr: #REF!
Name Last5Yr: #REF!
Name List_Smry_0: A_List!#REF!
Name List_Smry_0: C_List!#REF!
Name List_Smry_1: A_List!#REF!
Name List_Smry_1: C_List!#REF!
Name List_Smry_2: A_List!#REF!
Name List_Smry_2: C_List!#REF!
Name NextYear: #REF!
Name P_A_A_Ex: #REF!
Name P_A_A01: #REF!
Name P_A_A02: #REF!
Name P_A_A03: A_Revenue_Income!$A$7:$N$540
Name P_A_A04: #REF!
Name P_A_A05: A_Revenue_Expenditure!$A$4:$H$1634
Name P_A_A08: #REF!
Name P_A_A09: #REF!
Name P_A_A10: #REF!,#REF!,#REF!
Name P_A_A11: #REF!
Name P_A_A12: A_Capital_Expenditure!$A$7:$N$215
Name P_A_A13: #REF!
Name P_A_A14: A_Land_Acquisition!$A$4:$E$386
Name P_A_A15: A_Fund_Expenditure!$A$6:$N$137
Name P_A_A16: A_DPDC_Machinery_Tree!$A$6:$G$115
Name P_A_AC_In1: #REF!
Name P_A_APP: #REF!
Name P_A_Bdgt: A_DPDC_Machinery_Tree!$A$6:$G$115
Name P_A_Bdgt: A_Fund_Expenditure!$A$6:$N$137
Name P_A_Bdgt: A_Land_Acquisition!$A$4:$E$386
Name P_A_Bdgt: A_Revenue_Income!$A$7:$N$540
Name P_A_Bdgt: C_Capital_Expenditure!$A$6:$N$63
Name P_A_Bdgt: C_Revenue_Expenditure!$A$4:$H$397
Name P_A_Bdgt: WO_Work22_MC!$A$4:$Q$145
Name P_A_C_Ex: #REF!
Name P_A_C01: #REF!
Name P_A_C02: C_Revenue_Income!$A$7:$N$62
Name P_A_C02A: #REF!
Name P_A_C03: C_Revenue_Expenditure!$A$4:$H$397
Name P_A_C05: #REF!
Name P_A_C07: C_Capital_Expenditure!$A$6:$N$63
Name P_A_Doller_MC: #REF!,#REF!,#REF!
Name P_A_Doller_SC: #REF!,#REF!,#REF!
Name P_A_dvdr: #REF!
Name P_A_Fnl_Rec: #REF!
Name P_A_Info: #REF!
Name P_A_Info1: #REF!
Name P_A_Info2: #REF!
Name P_A_jnnurm: JNNURM!$A$1:$D$26
Name P_A_ListA: A_List!$A$1:$F$433
Name P_A_ListA: C_List!#REF!
Name P_A_ListC: A_List!$A$434:$F$434
Name P_A_ListC: C_List!$A$1:$F$72
Name P_A_S_Wtr: #REF!

Sheet A_Revenue_Income
A1: जमेचा | G1: तपशील
A2: विवरण | C2: नक्की आकडा | H2: 2021-22 वर्षाचा अंदाज | J2: 2022-23 वर्षाचा अंदाज | M2: 2021-22 वर्षाच्या मान्य अंदाजाशी तुलना केलेला 2022-23 वर्षाचा मा. महा. आयुक्त यांनी सुचविलेला अंदाज
C3: 2018-19 | D3: 2019-20 | E3: 2020-21 | F3: 2020-21 शेवटची सहामाही | G3: 2021-22 पहिली सहामाही | H3: मान्य अंदाज | I3: दुरूस्त अंदाज | J3: मा. महापालिका आयुक्त यांनी सुचविलेला | K3: मा. स्थायी समितीने मान्यता दिलेला | L3: मा. महानगर- पालिकेने संमत केलेला
M5: अधिक | N5: कमी
A7: अधिनियमाप्रमाणे कमीत कमी रोख शिल्लक ठेवण्याची रक्कम जमेस धरून वर्षारंभीची शिल्लक | B7: 0 | C7: 100000 | D7: 100000 | E7: 100000 | F7: 100000 | G7: 0 | H7: 100000 | I7: 100000 | J7: 100000 | K7: 0 | L7: 0 | M7: 0 | N7: 0
C8: 0 | D8: 0 | E8: 0 | F8: 0 | G8: 0 | H8: 0 | I8: 0 | J8: 0 | K8: 0 | L8: 0 | M8: 0 | N8: 0
A9: १. सर्वसाधारण कर, अप्रत्यक्ष कर व इतर जमा | C9: 0 | D9: 0 | E9: 0 | F9: 0 | G9: 0 | H9: 0 | I9: 0 | J9: 0 | K9: 0 | L9: 0 | M9: 0 | N9: 0
A10: क. सर्वसाधारण पट्टी | C10: 0 | D10: 0 | E10: 0 | F10: 0 | G10: 0 | H10: 0 | I10: 0 | J10: 0 | K10: 0 | L10: 0 | M10: 0 | N10: 0
A11: १. नागरिकांकडून (कआकसंप्र) | B11: RI11A101 | C11: 3361147014 | D11: 3613696720 | E11: 5001213963 | F11: 2469739845 | G11: 3367138173 | H11: 11050000000 | I11: 11050000000 | J11: 8370000000 | K11: 0 | L11: 0 | M11: 0 | N11: 2680000000
A12: लोहगाव (उर्वरित) | B12: RI11AA101 | C12: 37675 | D12: 646073 | E12: 1565320 | F12: 1374270 | G12: 509585 | H12: 0 | I12: 0 | J12: 0 | K12: 0 | L12: 0 | M12: 0 | N12: 0
A13: मुंढवा (उर्वरित केशवनगर) | B13: RI11AB101 | C13: 8185 | D13: 1067975 | E13: 964210 | F13: 893215 | G13: 323820 | H13: 0 | I13: 0 | J13: 0 | K13: 0 | L13: 0 | M13: 0 | N13: 0
A14: हडपसर (संपूर्ण साडेसतरानळी) | B14: RI11AC101 | C14: 3735 | D14: 85825 | E14: 1300405 | F14: 1291605 | G14: 176780 | H14: 0 | I14: 0 | J14: 0 | K14: 0 | L14: 0 | M14: 0 | N14: 0
A15: शिवणे (संपूर्ण उत्तमनगर) | B15: RI11AD101 | C15: 13465 | D15: 387130 | E15: 226850 | F15: 141645 | G15: 578520 | H15: 0 | I15: 0 | J15: 0 | K15: 0 | L15: 0 | M15: 0 | N15: 0
A16: शिवणे | B16: RI11AE101 | C16: 9565 | D16: 2103535 | E16: 1492950 | F16: 1354400 | G16: 0 | H16: 0 | I16: 0 | J16: 0 | K16: 0 | L16: 0 | M16: 0 | N16: 0
A17: आंबेगाव खुर्द | B17: RI11AF101 | C17: 6810 | D17: 1974340 | E17: 1087355 | F17: 1001085 | G17: 599315 | H17: 0 | I17: 0 | J17: 0 | K17: 0 | L17: 0 | M17: 0 | N17: 0
A18: उंड्री | B18: RI11AG101 | C18: 3755 | D18: 1132345 | E18: 2069140 | F18: 1242295 | G18: 728795 | H18: 0 | I18: 0 | J18: 0 | K18: 0 | L18: 0 | M18: 0 | N18: 0
A19: धायरी | B19: RI11AH101 | C19: 32565 | D19: 24150 | E19: 895530 | F19: 770995 | G19: 253455 | H19: 0 | I19: 0 | J19: 0 | K19: 0 | L19: 0 | M19: 0 | N19: 0
A20: आंबेगाव बुद्रुक | B20: RI11AJ101 | C20: 19645 | D20: 2560515 | E20: 1698345 | F20: 1482600 | G20: 793320 | H20: 0 | I20: 0 | J20: 0 | K20: 0 | L20: 0 | M20: 0 | N20: 0
A21: फुरसुंगी | B21: RI11AK101 | C21: 110450 | D21: 2070710 | E21: 1818395 | F21: 1524885 | G21: 588400 | H21: 0 | I21: 0 | J21: 0 | K21: 0 | L21: 0 | M21: 0 | N21: 0
A22: उरुळी देवाची | B22: RI11AL101 | C22: 33235 | D22: 101150 | E22: 127750 | F22: 86980 | G22: 164735 | H22: 0 | I22: 0 | J22: 0 | K22: 0 | L22: 0 | M22: 0 | N22: 0
... A49: पुणे मनपा हद्दीमध्ये नव्याने समाविष्ट होणारी 23 गावे (कआकसंप्र) | B49: RI11A107 | C49: 0 | D49: 0 | E49: 0 | F49: 0 | G49: 0 | H49: 2300000000 | I49: 2300000000 | J49: 0 | K49: 0 | L49: 0 | M49: 0 | N49: 2300000000
C50: 0 | D50: 0 | E50: 0 | F50: 0 | G50: 0 | H50: 0 | I50: 0 | J50: 0 | K50: 0 | L50: 0 | M50: 0 | N50: 0
A51: क. सर्वसाधारण कर बेरीज | C51: 3525303066 | D51: 3803991790 | E51: 5157049218 | F51: 2561038231 | G51: 3498218178 | H51: 13516500000 | I51: 13516500000 | J51: 10026200000 | K51: 0 | L51: 0 | M51: 0 | N51: 3490300000
C52: 0 | D52: 0 | E52: 0 | F52: 0 | G52: 0 | H52: 0 | I52: 0 | J52: 0 | K52: 0 | L52: 0 | M52: 0 | N52: 0
A53: ख. आयातकर | C53: 0 | D53: 0 | E53: 0 | F53: 0 | G53: 0 | H53: 0 | I53: 0 | J53: 0 | K53: 0 | L53: 0 | M53: 0 | N53: 0
A54: १. पक्की जमा (आ.क.प्र.) | B54: RI11B101 | C54: -5618500 | D54: -4881548 | E54: 0 | F54: 0 | G54: 0 | H54: 0 | I54: 0 | J54: 0 | K54: 0 | L54: 0 | M54: 0 | N54: 0
C55: 0 | D55: 0 | E55: 0 | F55: 0 | G55: 0 | H55: 0 | I55: 0 | J55: 0 | K55: 0 | L55: 0 | M55: 0 | N55: 0
A56: ख. निव्वळ आयातकर एकूण बेरीज | C56: -5618500 | D56: -4881548 | E56: 0 | F56: 0 | G56: 0 | H56: 0 | I56: 0 | J56: 0 | K56: 0 | L56: 0 | M56: 0 | N56: 0
C57: 0 | D57: 0 | E57: 0 | F57: 0 | G57: 0 | H57: 0 | I57: 0 | J57: 0 | K57: 0 | L57: 0 | M57: 0 | N57: 0
A58: ख-१. स्थानिक संस्था कर | C58: 0 | D58: 0 | E58: 0 | F58: 0 | G58: 0 | H58: 0 | I58: 0 | J58: 0 | K58: 0 | L58: 0 | M58: 0 | N58: 0
A59: स्थानिक संस्था कर नोंदणी शुल्क | B59: RI11B201 | C59: 300 | D59: 0 | E59: 0 | F59: 0 | G59: 0 | H59: 0 | I59: 0 | J59: 0 | K59: 0 | L59: 0 | M59: 0 | N59: 0
A60: स्थानिक संस्था कर | B60: RI11B202 | C60: 14074585 | D60: 1120093 | E60: 0 | F60: 0 | G60: 0 | H60: 5000000 | I60: 5000000 | J60: 5000000 | K60: 0 | L60: 0 | M60: 0 | N60: 0
A61: चौरस मीटर बांधकामाप्रमाणे भरावयाची ठोक रक्कम | B61: RI11B202B | C61: 3832035 | D61: 5510120 | E61: 1442790 | F61: 1442790 | G61: 29226 | H61: 200000 | I61: 200000 | J61: 300000 | K61: 0 | L61: 0 | M61: 100000 | N61: 0
A62: इतर जमा - स्थानिक संस्था कर | B62: RI11B202E | C62: 25232 | D62: 1780 | E62: 0 | F62: 0 | G62: 0 | H62: 0 | I62: 0 | J62: 0 | K62: 0 | L62: 0 | M62: 0 | N62: 0
A63: स्थानिक संस्था करापोटी व्याज | B63: RI11B203 | C63: 6911393 | D63: 821243 | E63: 0 | F63: 0 | G63: 0 | H63: 500000 | I63: 500000 | J63: 1400000 | K63: 0 | L63: 0 | M63: 900000 | N63: 0
A64: स्थानिक संस्था कर शास्ती (दंड) | B64: RI11B204 | C64: 80000 | D64: 25000 | E64: 35000 | F64: 30000 | G64: 25000 | H64: 0 | I64: 0 | J64: 0 | K64: 0 | L64: 0 | M64: 0 | N64: 0
A65: राज्य शासनाकडून मुद्रांक शुल्क अधिभारापोटी मिळालेली रक्कम (१%) | B65: RI11B206 | C65: 2758200420 | D65: 1749317051 | E65: 247275393 | F65: 0 | G65: 0 | H65: 1700000000 | I65: 1700000000 | J65: 3353000000 | K65: 0 | L65: 0 | M65: 1653000000 | N65: 0
A66: मनपा ठेकेदारांच्या बिलांमधून LBT वसुली | B66: RI11B207 | C66: 92301 | D66: 889 | E66: 16326 | F66: 10244 | G66: 0 | H66: 0 | I66: 0 | J66: 0 | K66: 0 | L66: 0 | M66: 0 | N66: 0
C67: 0 | D67: 0 | E67: 0 | F67: 0 | G67: 0 | H67: 0 | I67: 0 | J67: 0 | K67: 0 | L67: 0 | M67: 0 | N67: 0
A68: ख-१. स्थानिक संस्था कर बेरीज | C68: 2783216266 | D68: 1756796176 | E68: 248769509 | F68: 1483034 | G68: 54226 | H68: 1705700000 | I68: 1705700000 | J68: 3359700000 | K68: 0 | L68: 0 | M68: 1654000000 | N68: 0
C69: 0 | D69: 0 | E69: 0 | F69: 0 | G69: 0 | H69: 0 | I69: 0 | J69: 0 | K69: 0 | L69: 0 | M69: 0 | N69: 0
A70: वजा :- स्थानिक संस्था कर रिफंड | B70: RI11B251 | C70: 24998 | D70: 17276886 | E70: 0 | F70: 0 | G70: 0 | H70: 0 | I70: 0 | J70: 50000000 | K70: 0 | L70: 0 | M70: 50000000 | N70: 0
C71: 0 | D71: 0 | E71: 0 | F71: 0 | G71: 0 | H71: 0 | I71: 0 | J71: 0 | K71: 0 | L71: 0 | M71: 0 | N71: 0
A72: ख-१. स्थानिक संस्था कर एकूण बेरीज | C72: 2783191268 | D72: 1739519290 | E72: 248769509 | F72: 1483034 | G72: 54226 | H72: 1705700000 | I72: 1705700000 | J72: 3309700000 | K72: 0 | L72: 0 | M72: 1604000000 | N72: 0
C73: 0 | D73: 0 | E73: 0 | F73: 0 | G73: 0 | H73: 0 | I73: 0 | J73: 0 | K73: 0 | L73: 0 | M73: 0 | N73: 0
A74: राज्यशासनाकडून महाराष्ट्र वस्तू व सेवा कर अंतर्गत अनुदान (GST) | B74: RI11B209 | C74: 15728200000 | D74: 17025600000 | E74: 17621450000 | F74: 8427650000 | G74: 10695550000 | H74: 19858800000 | I74: 19858800000 | J74: 21447500000 | K74: 0 | L74: 0 | M74: 1588700000 | N74: 0
C75: 0 | D75: 0 | E75: 0 | F75: 0 | G75: 0 | H75: 0 | I75: 0 | J75: 0 | K75: 0 | L75: 0 | M75: 0 | N75: 0
A76: ग. इतर कर | C76: 0 | D76: 0 | E76: 0 | F76: 0 | G76: 0 | H76: 0 | I76: 0 | J76: 0 | K76: 0 | L76: 0 | M76: 0 | N76: 0
A77: १. करमणूककर (कआकसंप्र) | B77: RI11C101 | C77: 18144020 | D77: 17587320 | E77: 2536470 | F77: 974340 | G77: 785410 | H77: 22500000 | I77: 22500000 | J77: 22500000 | K77: 0 | L77: 0 | M77: 0 | N77: 0
A78: २. व्यवसायकर (कआकसंप्र) शासनाकडून व्यवसाय करापोटी मिळणारी नुकसान भरपाई | B78: RI11C102 | C78: 0 | D78: 0 | E78: 0 | F78: 0 | G78: 0 | H78: 3500000 | I78: 3500000 | J78: 3500000 | K78: 0 | L78: 0 | M78: 0 | N78: 0
C79: 0 | D79: 0 | E79: 0 | F79: 0 | G79: 0 | H79: 0 | I79: 0 | J79: 0 | K79: 0 | L79: 0 | M79: 0 | N79: 0
A80: ग. बेरीज | C80: 18144020 | D80: 17587320 | E80: 2536470 | F80: 974340 | G80: 785410 | H80: 26000000 | I80: 26000000 | J80: 26000000 | K80: 0 | L80: 0 | M80: 0 | N80: 0
C81: 0 | D81: 0 | E81: 0 | F81: 0 | G81: 0 | H81: 0 | I81: 0 | J81: 0 | K81: 0 | L81: 0 | M81: 0 | N81: 0
A82: घ. महानगरपालिका अधिनियमाखाली दंडाबाबत शासकीय सहाय्य (वि. सल्लागार) | B82: RI11D101 | C82: 733050 | D82: 1316400 | E82: 0 | F82: 0 | G82: 0 | H82: 0 | I82: 0 | J82: 0 | K82: 0 | L82: 0 | M82: 0 | N82: 0
C83: 0 | D83: 0 | E83: 0 | F83: 0 | G83: 0 | H83: 0 | I83: 0 | J83: 0 | K83: 0 | L83: 0 | M83: 0 | N83: 0
A84: गुंतविलेल्या रकमांवरील व्याज (मु.ले.) | B84: RI11E101 | C84: 1622335365 | D84: 1603520711 | E84: 1277693995 | F84: 952438974 | G84: 351389701 | H84: 470000000 | I84: 470000000 | J84: 600000000 | K84: 0 | L84: 0 | M84: 130000000 | N84: 0
A85: विविध खात्यांच्या ऑडिट अहवालातून वसुली | B85: RI11E107 | C85: 710465 | D85: 333042 | E85: 229620 | F85: 224009 | G85: 58898 | H85: 0 | I85: 0 | J85: 0 | K85: 0 | L85: 0 | M85: 0 | N85: 0
A86: ज्यादा आकार वसुली (मु.ले.) | B86: RI11E109 | C86: 0 | D86: 2434560 | E86: 1121869 | F86: 435568 | G86: 26425 | H86: 0 | I86: 0 | J86: 0 | K86: 0 | L86: 0 | M86: 0 | N86: 0
A87: इतर जमा (मु.ले.) | B87: RI11E110 | C87: 0 | D87: 0 | E87: 0 | F87: 0 | G87: 1027559 | H87: 0 | I87: 0 | J87: 0 | K87: 0 | L87: 0 | M87: 0 | N87: 0
A88: सेवकांसाठी सेवापुस्तक शुल्क | B88: RI11E123 | C88: 8405 | D88: 4440 | E88: 0 | F88: 0 | G88: 490 | H88: 0 | I88: 0 | J88: 0 | K88: 0 | L88: 0 | M88: 0 | N88: 0
A89: पुणे मनपाच्या हद्दीत नव्याने समाविष्ट झालेल्या 11 गावातील इतर जमा (मु.ले.) | B89: RI11E124 | C89: 99689170 | D89: 9061000 | E89: 0 | F89: 0 | G89: 0 | H89: 0 | I89: 0 | J89: 0 | K89: 0 | L89: 0 | M89: 0 | N89: 0
C90: 0 | D90: 0 | E90: 0 | F90: 0 | G90: 0 | H90: 0 | I90: 0 | J90: 0 | K90: 0 | L90: 0 | M90: 0 | N90: 0
A91: ज. इतर जमा | C91: 0 | D91: 0 | E91: 0 | F91: 0 | G91: 0 | H91: 0 | I91: 0 | J91: 0 | K91: 0 | L91: 0 | M91: 0 | N91: 0
A92: ज१. जुनी रद्दी विक्री (मसआ.जिंघ.) | B92: RI11H101 | C92: 191635 | D92: 72394 | E92: 454031 | F92: 418648 | G92: 0 | H92: 0 | I92: 0 | J92: 0 | K92: 0 | L92: 0 | M92: 0 | N92: 0
C93: 0 | D93: 0 | E93: 0 | F93: 0 | G93: 0 | H93: 0 | I93: 0 | J93: 0 | K93: 0 | L93: 0 | M93: 0 | N93: 0
A94: ज२. शुल्काचे उत्पन्न | C94: 0 | D94: 0 | E94: 0 | F94: 0 | G94: 0 | H94: 0 | I94: 0 | J94: 0 | K94: 0 | L94: 0 | M94: 0 | N94: 0
A95: अ. मसुदा शुल्क (वि. सल्लागार) | B95: RI11H102A | C95: 5721837 | D95: 5185432 | E95: 3511744 | F95: 2760396 | G95: 2818284 | H95: 5000000 | I95: 5000000 | J95: 5000000 | K95: 0 | L95: 0 | M95: 0 | N95: 0
A96: ब. दाव्याचा खर्च व प्रोसेस शुल्क (वि. सल्लागार) | B96: RI11H102B | C96: 7750 | D96: 0 | E96: 0 | F96: 0 | G96: 0 | H96: 0 | I96: 0 | J96: 100000 | K96: 0 | L96: 0 | M96: 100000 | N96: 0
A97: क. नक्कल शुल्क (झोनिपु) | B97: RI11H102C | C97: 103721 | D97: 115549 | E97: 47538 | F97: 33346 | G97: 32582 | H97: 300000 | I97: 300000 | J97: 300000 | K97: 0 | L97: 0 | M97: 0 | N97: 0
A98: ड. अधिपत्र (Warrant) शुल्क (कआकसंप्र) | B98: RI11H102D | C98: 11012968 | D98: 8291369 | E98: 20957076 | F98: 18730466 | G98: 4874815 | H98: 20000000 | I98: 20000000 | J98: 20000000 | K98: 0 | L98: 0 | M98: 0 | N98: 0
A99: ई. सूचनापत्र (Notice) शुल्क (कआकसंप्र) | B99: RI11H102E | C99: 995201 | D99: 707417 | E99: 2187793 | F99: 2113960 | G99: 55209 | H99: 500000 | I99: 500000 | J99: 500000 | K99: 0 | L99: 0 | M99: 0 | N99: 0
A100: फ. मिळकतीच्या मालकी हक्काबद्दल शुल्क (कआकसंप्र) | B100: RI11H102F | C100: 129719220 | D100: 90083435 | E100: 116093095 | F100: 104021125 | G100: 90302356 | H100: 90000000 | I100: 90000000 | J100: 95000000 | K100: 0 | L100: 0 | M100: 5000000 | N100: 0
A101: ग. मिळकतकर थकबाकी शास्ती (२%) (कआकसंप्र) | B101: RI11H102G | C101: 772687238 | D101: 694859495 | E101: 981672788 | F101: 821887606 | G101: 298058958 | H101: 1750000000 | I101: 1750000000 | J101: 1750000000 | K101: 0 | L101: 0 | M101: 0 | N101: 0
C102: 0 | D102: 0 | E102: 0 | F102: 0 | G102: 0 | H102: 0 | I102: 0 | J102: 0 | K102: 0 | L102: 0 | M102: 0 | N102: 0
A103: ज२. बेरीज | C103: 920247935 | D103: 799242697 | E103: 1124470034 | F103: 949546899 | G103: 396142204 | H103: 1865800000 | I103: 1865800000 | J103: 1870900000 | K103: 0 | L103: 0 | M103: 5100000 | N103: 0
C104: 0 | D104: 0 | E104: 0 | F104: 0 | G104: 0 | H104: 0 | I104: 0 | J104: 0 | K104: 0 | L104: 0 | M104: 0 | N104: 0
A105: ज३. किरकोळ जमा | C105: 0 | D105: 0 | E105: 0 | F105: 0 | G105: 0 | H105: 0 | I105: 0 | J105: 0 | K105: 0 | L105: 0 | M105: 0 | N105: 0
A106: न नेलेली व जप्त केलेली अनामत पक्की जमा (मु.ले.) | B106: RI11H103A | C106: 36948 | D106: 433965 | E106: 0 | F106: 0 | G106: 556108 | H106: 0 | I106: 0 | J106: 0 | K106: 0 | L106: 0 | M106: 0 | N106: 0
A107: मतदार याद्या विक्री (निवडणूक) | B107: RI11H103C | C107: 0 | D107: 0 | E107: 4609 | F107: 4609 | G107: 0 | H107: 17125000 | I107: 17125000 | J107: 20158000 | K107: 0 | L107: 0 | M107: 3033000 | N107: 0
A108: इतर किरकोळ जमा (निवडणूक) | B108: RI11H103D | C108: 6175 | D108: 8972 | E108: 0 | F108: 0 | G108: 0 | H108: 10000 | I108: 10000 | J108: 10000 | K108: 0 | L108: 0 | M108: 0 | N108: 0
A109: इतर खात्यांकडील पुस्तके, मॅन्युअल्स्‌, नकाशे इ. (मसआ.जिंघ.) | B109: RI11H103E | C109: 9497 | D109: 13582 | E109: 47358 | F109: 46018 | G109: 11240 | H109: 0 | I109: 0 | J109: 0 | K109: 0 | L109: 0 | M109: 0 | N109: 0
A110: भांडार खात्याकडील जुने साहित्य विक्री (म.स.आ.) | B110: RI11H103F | C110: 1442300 | D110: 1933256 | E110: 6447300 | F110: 6021300 | G110: 14923699 | H110: 40000000 | I110: 40000000 | J110: 40000000 | K110: 0 | L110: 0 | M110: 0 | N110: 0
A111: घरबांधणी कर्ज फॉर्म विक्री (मसआ.जिंघ.) | B111: RI11H103K | C111: 3100 | D111: 1700 | E111: 945 | F111: 945 | G111: 0 | H111: 0 | I111: 0 | J111: 0 | K111: 0 | L111: 0 | M111: 0 | N111: 0
A112: खानेसुमारीपोटी शासनाकडून मिळणारी रक्कम (जिं.घ.) | B112: RI11H103L | C112: 0 | D112: 0 | E112: 2701800 | F112: 2701800 | G112: 0 | H112: 0 | I112: 0 | J112: 0 | K112: 0 | L112: 0 | M112: 0 | N112: 0
A113: सेवकवर्ग विभाग इतर जमा | B113: RI11H103N | C113: 40640 | D113: 7400 | E113: 380816 | F113: 374616 | G113: 750 | H113: 0 | I113: 0 | J113: 0 | K113: 0 | L113: 0 | M113: 0 | N113: 0
A114: सुरक्षा विभाग इतर जमा | B114: RI11H103P | C114: 117856 | D114: 1350 | E114: 23931 | F114: 23931 | G114: 0 | H114: 0 | I114: 0 | J114: 0 | K114: 0 | L114: 0 | M114: 0 | N114: 0
A115: महाराष्ट्र माहितीचा अधिकार अधिनियम | B115: RI11H103R | C115: 761562 | D115: 425054 | E115: 237813 | F115: 190479 | G115: 164682 | H115: 3000 | I115: 3000 | J115: 4000 | K115: 0 | L115: 0 | M115: 1000 | N115: 0
A116: CFC अंतर्गत जमा होणारी रक्कम | B116: RI11H103S | C116: 1515652 | D116: 998055 | E116: 809425 | F116: 690055 | G116: 445375 | H116: 0 | I116: 0 | J116: 0 | K116: 0 | L116: 0 | M116: 0 | N116: 0
C117: 0 | D117: 0 | E117: 0 | F117: 0 | G117: 0 | H117: 0 | I117: 0 | J117: 0 | K117: 0 | L117: 0 | M117: 0 | N117: 0
A118: ज३. बेरीज | C118: 3933730 | D118: 3823334 | E118: 10653997 | F118: 10053753 | G118: 16101854 | H118: 57138000 | I118: 57138000 | J118: 60172000 | K118: 0 | L118: 0 | M118: 3034000 | N118: 0
C119: 0 | D119: 0 | E119: 0 | F119: 0 | G119: 0 | H119: 0 | I119: 0 | J119: 0 | K119: 0 | L119: 0 | M119: 0 | N119: 0
A120: ज. इतर जमा एकूण बेरीज | C120: 924373300 | D120: 803138425 | E120: 1135578062 | F120: 960019300 | G120: 412244058 | H120: 1922938000 | I120: 1922938000 | J120: 1931072000 | K120: 0 | L120: 0 | M120: 8134000 | N120: 0
C121: 0 | D121: 0 | E121: 0 | F121: 0 | G121: 0 | H121: 0 | I121: 0 | J121: 0 | K121: 0 | L121: 0 | M121: 0 | N121: 0
A122: १. सर्वसाधारणकर, अप्रत्यक्षकर व इतर जमा एकूण बेरीज | C122: 24697069609 | D122: 25001625430 | E122: 25444428743 | F122: 12904263456 | G122: 14959354945 | H122: 37499938000 | I122: 37499938000 | J122: 37340472000 | K122: 0 | L122: 0 | M122: 0 | N122: 159466000
C123: 0 | D123: 0 | E123: 0 | F123: 0 | G123: 0 | H123: 0 | I123: 0 | J123: 0 | K123: 0 | L123: 0 | M123: 0 | N123: 0
A124: २. प्राथमिक शिक्षण | C124: 0 | D124: 0 | E124: 0 | F124: 0 | G124: 0 | H124: 0 | I124: 0 | J124: 0 | K124: 0 | L124: 0 | M124: 0 | N124: 0
A125: शासकीय अनुदान - प्राथमिक शिक्षण | B125: RI12A101 | C125: 830367728 | D125: 883423008 | E125: 758054000 | F125: 350609000 | G125: 599730456 | H125: 1210000000 | I125: 1210000000 | J125: 1210000000 | K125: 0 | L125: 0 | M125: 0 | N125: 0
A126: प्राथमिक शिक्षण विभाग – शाळा भाडे | B126: RI12A103 | C126: 4574741 | D126: 896883 | E126: 216274 | F126: 59095 | G126: 130402 | H126: 900000 | I126: 900000 | J126: 100000 | K126: 0 | L126: 0 | M126: 0 | N126: 800000
A127: दंड, साक्षी, भत्ता इत्यादी | B127: RI12A104 | C127: 0 | D127: 0 | E127: 0 | F127: 0 | G127: 0 | H127: 10000 | I127: 10000 | J127: 5000 | K127: 0 | L127: 0 | M127: 0 | N127: 5000
A128: बालवाडी शुल्क | B128: RI12A105 | C128: 0 | D128: 0 | E128: 0 | F128: 0 | G128: 0 | H128: 5000 | I128: 5000 | J128: 5000 | K128: 0 | L128: 0 | M128: 0 | N128: 0
...

Sheet A_Revenue_Expenditure
A1: योजनेतर खर्च तपशील
A2: विवरण | D2: नक्‍की आकडा | G2: मान्य अंदाज 2021-22 | H2: नवीन अंदाज 2022-23
D3: 2018-19 | E3: 2019-20 | F3: 2020-21
A4: १. मुख्य देखरेख, वसुली वगैरे | D4: 0 | E4: 0 | F4: 0 | G4: 0 | H4: 0
A5: क. महानगरपालिका व स्थायी समिती | D5: 0 | E5: 0 | F5: 0 | G5: 0 | H5: 0
A6: १ नगरसचिव यांचे कार्यालय | D6: 0 | E6: 0 | F6: 0 | G6: 0 | H6: 0
A7: १. नगरसचिव (म्युनिसिपल सेक्रेटरी) (मुं.प्रां. मनपा अधिनियम, कलम४५(३) प्रमाणे) वेतन | B7: RE11A101A | D7: 1357957 | E7: 1343918 | F7: 1757440 | G7: 1500000 | H7: 2500000
A8: २. कायम सेवकवर्ग वेतन | B8: RE11A102A | D8: 38537287 | E8: 37739899 | F8: 40716333 | G8: 45000000 | H8: 51100000
A9: ३. संकीर्ण (न.स.) | B9: RE11A103 | D9: 4967904 | E9: 727424 | F9: 3701446 | G9: 10000000 | H9: 10000000
A10: ३अ. मागील बिले देण्यासाठी (न.स.) | B10: RE11A103A | D10: 2886671 | E10: 1251212 | F10: 2627800 | G10: 4000000 | H10: 4000000
A11: ४. प्रवास खर्च (न.स.) | B11: RE11A104 | D11: 35207 | E11: 133002 | F11: 26355 | G11: 2000000 | H11: 2000000
A12: ५. ग्रंथालय व वाचनालय | B12: RE11A105 | D12: 172716 | E12: 189625 | F12: 188737 | G12: 250000 | H12: 250000
A13: ६. समारंभ खर्च (न.स. व वि.अ.) | B13: RE11A106 | D13: 68200 | E13: 0 | F13: 0 | G13: 500000 | H13: 500000
A14: १०. अखिल भारतीय/महाराष्ट्र महापौर परिषद व अखिल भारतीय स्थानिक स्वराज्य संस्था प्रतिनिधी अधिवेशन | B14: RE11A110 | D14: 0 | E14: 0 | F14: 0 | G14: 300000 | H14: 300000
A15: ११. मनपा व शासकीय निवृत्त सेवकांना द्यावयाचा चहापान खर्च | B15: RE11A111 | D15: 3000 | E15: 0 | F15: 0 | G15: 300000 | H15: 300000
A16: १३. महाराष्ट्र राज्य महानगरपालिका स्थायी समिती अध्यक्ष परिषद वर्गणी व तद्‌नुषंगिक खर्च | B16: RE11A113 | D16: 0 | E16: 0 | F16: 0 | G16: 1000 | H16: 1000
A17: १४. मा. महापौर यांचा व्ययनियमन (सम्प्च्युअरी) भत्ता | B17: RE11A114 | D17: 0 | E17: 0 | F17: 0 | G17: 5000 | H17: 5000
A18: १५. मा. महापौर यांचा ऐच्छिक खर्च | B18: RE11A115 | D18: 95427 | E18: 57402 | F18: 122823 | G18: 200000 | H18: 200000
... A53: नगरसचिव विभागामार्फत आवश्यक सेवक भरती करणे (कंत्राटी) | B53: RE11A280 | D53: 0 | E53: 0 | F53: 0 | G53: 10000000 | H53: 0
D54: 0 | E54: 0 | F54: 0 | G54: 0 | H54: 0
A55: क. मनपा व स्थायी समिती बेरीज | D55: 87211238 | E55: 94077423 | F55: 98581149 | G55: 173656000 | H55: 176990000
D56: 0 | E56: 0 | F56: 0 | G56: 0 | H56: 0
A57: ख. मुख्य लेखापरिक्षक यांचे कार्यालय | D57: 0 | E57: 0 | F57: 0 | G57: 0 | H57: 0
A58: १. मुख्य लेखापरिक्षक (म्युनिसिपल चीफ ऑडिटर) (मु.प्रां. मनपा अधिनियम, कलम ४५ (३) प्रमाणे) यांचे वेतन | B58: RE11B101A | D58: 2623589 | E58: 2390291 | F58: 2617074 | G58: 2500000 | H58: 3773000
A59: २. कायम सेवकवर्ग वेतन | B59: RE11B102A | D59: 29232284 | E59: 26552946 | F59: 22830016 | G59: 29000000 | H59: 41220000
A60: ३. संकीर्ण | B60: RE11B103 | D60: 115189 | E60: 66256 | F60: 82905 | G60: 225000 | H60: 200000
D61: 0 | E61: 0 | F61: 0 | G61: 0 | H61: 0
A62: ख. मुख्यलेखापरिक्षक यांचे कार्या. बेरीज | D62: 31971062 | E62: 29009493 | F62: 25529995 | G62: 31725000 | H62: 45193000
D63: 0 | E63: 0 | F63: 0 | G63: 0 | H63: 0
A64: ग१. महापालिका आयुक्त यांचे कार्यालय | D64: 0 | E64: 0 | F64: 0 | G64: 0 | H64: 0
A65: १. महापालिका आयुक्त (म्युनिसिपल कमिशनर) (मु. प्रां. मनपा अधिनियम, कलम ३७ (१) प्रमाणे) यांचे वेतन | B65: RE11C101A | D65: 2531394 | E65: 2816569 | F65: 2971037 | G65: 3000000 | H65: 3000000
A66: २. उपआयुक्त (जनरल) (मुं. प्रां. मनपा अधिनियम, कलम ४५(३) प्रमाणे) यांचे वेतन | B66: RE11C102A | D66: 1175614 | E66: 1635153 | F66: 1378496 | G66: 2500000 | H66: 2500000
A67: ३. कायम सेवकवर्ग वेतन | B67: RE11C103A | D67: 29549463 | E67: 28289154 | F67: 24591421 | G67: 29500000 | H67: 41754000
A68: ४. संकीर्ण | B68: RE11C104 | D68: 1356556 | E68: 1450875 | F68: 1191416 | G68: 2000000 | H68: 2200000
A69: ६. मा. महापालिका आयुक्त यांचा ऐच्छिक खर्च (म.स.आ.) | B69: RE11C106 | D69: 50003 | E69: 139240 | F69: 164482 | G69: 850000 | H69: 800000
D70: 0 | E70: 0 | F70: 0 | G70: 0 | H70: 0
A71: ग१. महापालिका आयुक्त कार्यालय बेरीज | D71: 34663030 | E71: 34330991 | F71: 30296852 | G71: 37850000 | H71: 50254000
D72: 0 | E72: 0 | F72: 0 | G72: 0 | H72: 0
A73: ग२. अतिरिक्त महापालिका आयुक्त (विशेष) यांचे कार्यालय | D73: 0 | E73: 0 | F73: 0 | G73: 0 | H73: 0
A74: १. अतिरिक्त महापालिका आयुक्त (विशेष) यांचे वेतन | B74: RE11C126A | D74: 2041368 | E74: 1390901 | F74: 1407008 | G74: 3000000 | H74: 3000000
A75: २. कायम सेवकवर्ग वेतन | B75: RE11C127A | D75: 13598908 | E75: 14067805 | F75: 18077610 | G75: 15000000 | H75: 19272000
A76: ३. संकीर्ण | B76: RE11C128 | D76: 295033 | E76: 145323 | F76: 73458 | G76: 800000 | H76: 900000
A77: ४. मनपा सेवकांस विविध सेमिनर, कॉन्फरन्स, प्रशिक्षण इ. साठी हजर राहण्यासाठी खर्च | B77: RE11C129 | D77: 33097 | E77: 48945 | F77: 0 | G77: 300000 | H77: 400000
A78: 5. अतिरिक्त महापालिका आयुक्त (विशेष) यांचेकडे येणार्‍या पाहुण्यांचा आतिथ्याकरिता होणारा खर्च | B78: RE11C129C | D78: 9570 | E78: 0 | F78: 0 | G78: 300000 | H78: 400000
A79: ग२. अतिरिक्त महापालिका आयुक्त (विशेष) यांचे कार्यालय बेरीज | D79: 15977976 | E79: 15652974 | F79: 19558076 | G79: 19400000 | H79: 23972000
D80: 0 | E80: 0 | F80: 0 | G80: 0 | H80: 0
A81: ग३. अतिरिक्त महापालिका आयुक्त (जनरल) यांचे कार्यालय | D81: 0 | E81: 0 | F81: 0 | G81: 0 | H81: 0
A82: १. मा. अतिरिक्त महापालिका आयुक्त (जनरल) यांचे वेतन | B82: RE11C131A | D82: 570358 | E82: 1508356 | F82: 1723134 | G82: 3000000 | H82: 3000000
A83: २. कायम सेवकवर्ग वेतन | B83: RE11C132A | D83: 11585239 | E83: 10819677 | F83: 10142425 | G83: 13500000 | H83: 17749000
A84: ३. संकीर्ण | B84: RE11C133 | D84: 169434 | E84: 102866 | F84: 95372 | G84: 800000 | H84: 900000
A85: ४.अतिरिक्त महापालिका आयुक्त (जनरल) यांचेकडे येणार्‍या पाहुण्यांचा आतिथ्याकरिता होणारा खर्च | B85: RE11C134 | D85: 4633 | E85: 15818 | F85: 23088 | G85: 300000 | H85: 400000
A86: ५. अधिकारी / सेवक प्रशिक्षण वर्ग / कार्यशाळेस उपस्थित राहण्याचा प्रवासखर्च, कार्यशाळा शुल्क, प्रशिक्षण शुल्क वगैरे | B86: RE11C135 | D86: 66363 | E86: 79157 | F86: 34714 | G86: 200000 | H86: 400000
D87: 0 | E87: 0 | F87: 0 | G87: 0 | H87: 0
A88: ग३. अतिरिक्त महापालिका आयुक्त (जनरल) यांचे कार्यालय बेरीज | D88: 12396027 | E88: 12525874 | F88: 12018733 | G88: 17800000 | H88: 22449000
D89: 0 | E89: 0 | F89: 0 | G89: 0 | H89: 0
A90: ग४. अतिरिक्त महापालिका आयुक्त (इस्टेट) यांचे कार्यालय | D90: 0 | E90: 0 | F90: 0 | G90: 0 | H90: 0
A91: १. मा. अतिरिक्त महापालिका आयुक्त (इस्टेट) यांचे वेतन | B91: RE11C141 | D91: 881779 | E91: 2297535 | F91: 1599389 | G91: 3000000 | H91: 3000000
A92: २. कायम सेवकवर्ग वेतन | B92: RE11C142 | D92: 7129521 | E92: 8690113 | F92: 8316126 | G92: 10000000 | H92: 19270000
A93: ३. संकीर्ण | B93: RE11C143 | D93: 418716 | E93: 139447 | F93: 192893 | G93: 800000 | H93: 900000
A94: ४.अतिरिक्त महापालिका आयुक्त (इस्टेट) यांचेकडे येणार्‍या पाहुण्यांचा आतिथ्याकरिता होणारा खर्च | B94: RE11C144 | D94: 0 | E94: 6374 | F94: 0 | G94: 300000 | H94: 400000
A95: 6. प्रशिक्षण वर्ग / कार्यशाळेस उपस्थित राहण्याचा प्रवासखर्च | B95: RE11C146 | D95: 167071 | E95: 217849 | F95: 50071 | G95: 300000 | H95: 400000
A96: ग४. अतिरिक्त महापालिका आयुक्त (इस्टेट) यांचे कार्यालय बेरीज | D96: 8597087 | E96: 11351318 | F96: 10158479 | G96: 14400000 | H96: 23970000
A97: ग५. दक्षता विभाग | D97: 0 | E97: 0 | F97: 0 | G97: 0 | H97: 0
A98: १. कायम सेवकवर्ग वेतन | B98: RE11C151 | D98: 9473049 | E98: 9733412 | F98: 11349940 | G98: 12000000 | H98: 20782000
A99: २. संकीर्ण | B99: RE11C152 | D99: 79462 | E99: 49286 | F99: 97901 | G99: 200000 | H99: 200000
A100: ग५. दक्षता विभाग बेरीज | D100: 9552511 | E100: 9782698 | F100: 11447841 | G100: 12200000 | H100: 20982000
D101: 0 | E101: 0 | F101: 0 | G101: 0 | H101: 0
A102: ग१+ग२+ग३+ग४+ग५ एकूण बेरीज | D102: 81186631 | E102: 83643855 | F102: 83479981 | G102: 101650000 | H102: 141627000
D103: 0 | E103: 0 | F103: 0 | G103: 0 | H103: 0
A104: घ१. उपआयुक्त (विशेष) यांचे कार्यालय | D104: 0 | E104: 0 | F104: 0 | G104: 0 | H104: 0
A105: १. उपआयुक्त (विशेष) (मुं. प्रां. मनपा अधिनियम, कलम ४५(३) प्रमाणे) यांचे वेतन | B105: RE11D101A | D105: 0 | E105: 1171262 | F105: 1060949 | G105: 2300000 | H105: 2500000
A106: २. कायम सेवकवर्ग वेतन | B106: RE11D102A | D106: 8214909 | E106: 7634116 | F106: 7541229 | G106: 9500000 | H106: 11394000
A107: ३. संकीर्ण | B107: RE11D103 | D107: 31644 | E107: 38712 | F107: 32284 | G107: 100000 | H107: 100000
D108: 0 | E108: 0 | F108: 0 | G108: 0 | H108: 0
A109: घ१. उपआयुक्त (विशेष) कार्यालय बेरीज | D109: 8246553 | E109: 8844090 | F109: 8634462 | G109: 11900000 | H109: 13994000
A110: घ२. सेवकवर्ग विभाग | D110: 0 | E110: 0 | F110: 0 | G110: 0 | H110: 0
A111: १. कायम सेवकवर्ग वेतन | B111: RE11D126A | D111: 30921722 | E111: 32741529 | F111: 29864437 | G111: 36000000 | H111: 49388000
A112: २. संकीर्ण | B112: RE11D127 | D112: 214222 | E112: 82917 | F112: 286732 | G112: 400000 | H112: 400000
A113: ५. प्रशिक्षण प्रबोधिनीसाठी फर्निचर व तद्‌नुषंगिक कामे करणे व साहित्य घेणे | B113: RE11D127C | D113: 55555 | E113: 0 | F113: 0 | G113: 500000 | H113: 500000
A114: ६. अधिकारी / कर्मचार्‍यांसाठी प्रशिक्षण आयोजन करणेसाठी खर्च | B114: RE11D127D | D114: 138226 | E114: 31555 | F114: 0 | G114: 1500000 | H114: 1500000
A115: ७. पुणे मनपामध्ये बायोमॅट्रिक अटेंडन्स प्रणाली कार्यान्वीत करणे | B115: RE11D127E | D115: 0 | E115: 0 | F115: 674960 | G115: 500000 | H115: 4000000
A116: ८. सेवकवर्ग विभागासाठी फर्निचर करणे | B116: RE11D127F | D116: 0 | E116: 0 | F116: 720000 | G116: 500000 | H116: 800000
A117: समाविष्ट गावांतील सेवकांच्या वेतनासाठी | B117: RE11D127H | D117: 66257402 | E117: 106962499 | F117: 19264911 | G117: 0 | H117: 21953000
A118: मनपा पदाधिकारी, अधिकारी, नगरसेवक, कर्मचारी यांना प्रशिक्षणासाठी वसंतराव भागवत प्रबोधिनी स्थापन करणे. | B118: RE11D127K | D118: 299000 | E118: 0 | F118: 0 | G118: 0 | H118: 0
A119: पत्रकार डी.आर.कुलकर्णी गृहनिर्माण संस्था प्रशिक्षण | B119: RE11D127L | D119: 0 | E119: 0 | F119: 0 | G119: 10000000 | H119: 0
D120: 0 | E120: 0 | F120: 0 | G120: 0 | H120: 0
A121: घ२. सेवकवर्ग विभाग बेरीज | D121: 97886127 | E121: 139818500 | F121: 50811040 | G121: 49400000 | H121: 78541000
D122: 0 | E122: 0 | F122: 0 | G122: 0 | H122: 0
A123: घ२अ. सेवाभरती व परीक्षा नियंत्रण विभाग | D123: 0 | E123: 0 | F123: 0 | G123: 0 | H123: 0
A124: 3. विविध रिक्त पदे भरण्यासाठी आयोजित करण्यात येणार्‍या परीक्षांसाठी खर्च | B124: RE11D153 | D124: 0 | E124: 0 | F124: 0 | G124: 2000000 | H124: 2000000
D125: 0 | E125: 0 | F125: 0 | G125: 0 | H125: 0
A126: घ२अ. सेवाभरती व परीक्षा नियंत्रण विभाग बेरीज | D126: 0 | E126: 0 | F126: 0 | G126: 2000000 | H126: 2000000
D127: 0 | E127: 0 | F127: 0 | G127: 0 | H127: 0
A128: घ२ब. मागासवर्ग विभाग | D128: 0 | E128: 0 | F128: 0 | G128: 0 | H128: 0
A129: १. कायम सेवकवर्ग वेतन | B129: RE11D161 | D129: 0 | E129: 220446 | F129: 454796 | G129: 500000 | H129: 1467000
D130: 0 | E130: 0 | F130: 0 | G130: 0 | H130: 0
A131: घ२ब. मागासवर्ग विभाग बेरीज | D131: 0 | E131: 220446 | F131: 454796 | G131: 500000 | H131: 1467000
D132: 0 | E132: 0 | F132: 0 | G132: 0 | H132: 0
A133: घ३. सुरक्षा विभाग | D133: 0 | E133: 0 | F133: 0 | G133: 0 | H133: 0
A134: १. कायम सेवकवर्ग वेतन | B134: RE11D128A | D134: 176225158 | E134: 174932722 | F134: 171374741 | G134: 190000000 | H134: 221508000
...

Sheet A_Capital_Expenditure
A1: सन 2022-23 चे योजनांतर्गत | H1: खर्चाबाबतचे अंदाजपत्रक
A2: मान्यतेचा ठराव क्र. दिनांक (Code) | B2: प्रभाग क्रमांक | C2: BPL | D2: कामाचे नाव अगर वर्णन | E2: दि. 31 मार्च 2022 अखेरपर्यंत केलेली तरतूद | H2: दि. 31 मार्च 2021 पर्यंतचा खर्चाचा नक्‍की आकडा | I2: 2021-22 मधील खर्चाची अंदाजी रक्कम | K2: 2022-23 साठी अधिक तरतूद | M2: 2022-23 साठी एकूण तरतूद | N2: प्रकल्पीय रक्कम
E3: कर्जातून | F3: महसूल निधीतून | G3: एकूण | I3: प्रत्यक्ष उपलब्ध तरतूद | J3: कर्जातून तरतूद | K3: कर्जातून | L3: महसूल निधी व इतर निधी
D7: १. मनपा भवन व मनपा इमारती | E7: 0 | F7: 0 | G7: 0 | H7: 0 | I7: 0 | L7: 0 | M7: 0
A8: CE11A129# | B8: J1- | C8: _ | D8: शहरात विविध ठिकाणी मनपासाठी इमारती बांधणे व विकास कामे करणे | E8: 0 | F8: 808496291 | G8: 808496291 | H8: 691071262 | I8: 117425029 | L8: 195000000 | M8: 195000000
E9: 0 | F9: 0 | G9: 0 | H9: 0 | I9: 0 | L9: 0 | M9: 0
D10: १. मनपा भवन व मनपा इमारती एकूण बेरीज | E10: 0 | F10: 808496291 | G10: 808496291 | H10: 691071262 | I10: 117425029 | L10: 195000000 | M10: 195000000
E11: 0 | F11: 0 | G11: 0 | H11: 0 | I11: 0 | L11: 0 | M11: 0
D12: २. प्राथमिक शिक्षण | E12: 0 | F12: 0 | G12: 0 | H12: 0 | I12: 0 | L12: 0 | M12: 0
A13: CE12A381# | B13: _ | C13: _ | D13: प्राथमिक शाळेमध्ये मुलभूत सोयी सुविधांसाठी विविध विकासकामे करणे | E13: 0 | F13: 1301502862 | G13: 1301502862 | H13: 1301502862 | I13: 0 | L13: 0 | M13: 0
A14: CE12A422# | B14: J2- | C14: _ | D14: प्राथमिक शाळेसाठी नवीन इमारत बांधणे / वर्गखोल्या बांधणे / मैदाने विकसित करणे व मुलभूत सोयी सुविधांसाठी विविध विकासकामे करणे | E14: 0 | F14: 1325472139 | G14: 1325472139 | H14: 1093094755 | I14: 232377384 | L14: 315500000 | M14: 315500000
E15: 0 | F15: 0 | G15: 0 | H15: 0 | I15: 0 | L15: 0 | M15: 0
C16: B | D16: २. प्राथमिक शिक्षण एकूण बेरीज | E16: 0 | F16: 2686415818 | G16: 2686415818 | H16: 2454038434 | I16: 232377384 | L16: 315500000 | M16: 315500000
E17: 0 | F17: 0 | G17: 0 | H17: 0 | I17: 0 | L17: 0 | M17: 0
D18: ३. दुय्यम शिक्षण | E18: 0 | F18: 0 | G18: 0 | H18: 0 | I18: 0 | L18: 0 | M18: 0
A19: CE13A128# | B19: J5- | C19: _ | D19: माध्यमिक शाळांमध्ये मुलभूत सोयी सुविधांसाठी विविध विकासकामे करणे | E19: 0 | F19: 68490996 | G19: 68490996 | H19: 60693416 | I19: 7797580 | L19: 3500000 | M19: 3500000
E20: 0 | F20: 0 | G20: 0 | H20: 0 | I20: 0 | L20: 0 | M20: 0
C21: B | D21: ३. दुय्यम शिक्षण एकूण बेरीज | E21: 0 | F21: 68490996 | G21: 68490996 | H21: 60693416 | I21: 7797580 | L21: 3500000 | M21: 3500000
E22: 0 | F22: 0 | G22: 0 | H22: 0 | I22: 0 | L22: 0 | M22: 0
D23: ७. आरोग्य विभाग | E23: 0 | F23: 0 | G23: 0 | H23: 0 | I23: 0 | L23: 0 | M23: 0
A24: CE17A192# | B24: _ | C24: _ | D24: दवाखान्यातील मुलभूत सोयी सुविधांसाठी विविध विकासकामे करणे | E24: 0 | F24: 583746804 | G24: 583746804 | H24: 583746804 | I24: 0 | L24: 0 | M24: 0
A25: CE17A227# | B25: J12- | C25: _ | D25: शहरामध्ये विविध ठिकाणी स्मशानभूमी / दफनभूमी विकसित करणे / दशक्रीया विधीसाठी घाट बांधणे व विविध विकासकामे करणे | E25: 0 | F25: 789005778 | G25: 789005778 | H25: 661059560 | I25: 127946218 | L25: 63000000 | M25: 63000000
A26: CE17A242# | B26: J6- | C26: _ | D26: शहरामध्ये दवाखाने / प्रसुतिगृह बांधणे / दवाखान्यांसाठी विविध उपकरणे खरेदी करणे / दवाखान्यातील मुलभूत सोयी सुविधांसाठी विविध विकासकामे करणे | E26: 0 | F26: 1104500955 | G26: 1104500955 | H26: 667053162 | I26: 437447793 | L26: 1202500000 | M26: 1202500000
A27: CE17A244# | B27: _ | C27: _ | D27: शहरातील दवाखान्यांसाठी विविध उपकरणे खरेदी करणे | E27: 0 | F27: 153267558 | G27: 153267558 | H27: 153267558 | I27: 0 | L27: 0 | M27: 0
E28: 0 | F28: 0 | G28: 0 | H28: 0 | I28: 0 | L28: 0 | M28: 0
C29: B | D29: ७. आरोग्य विभाग एकूण बेरीज | E29: 0 | F29: 2658568233 | G29: 2658568233 | H29: 2093174222 | I29: 565394011 | L29: 1265500000 | M29: 1265500000
E30: 0 | F30: 0 | G30: 0 | H30: 0 | I30: 0 | L30: 0 | M30: 0
D31: ९. पथांची झाडलोट / घनकचरा व्यवस्थापन विभाग | E31: 0 | F31: 0 | G31: 0 | H31: 0 | I31: 0 | L31: 0 | M31: 0
A32: CE19A116 | D32: उरूळी देवाची/फुरसंगी डेपो परिसर कचरा डेपोवरील उर्वरित कचर्‍याचे नॉर्म्सप्रमाणे कॅपिंग करणे व तद्‌नुषंगिक कामे करणे | E32: 0 | F32: 828238528 | G32: 828238528 | H32: 811712664 | I32: 16525864 | L32: 9000000 | M32: 9000000
A33: CE19A117 | D33: उरुळी देवाची/फुरसुंगी येथील कचरा डेपोच्या भोवती सिमाभिंत बांधणे. | E33: 0 | F33: 58029046 | G33: 58029046 | H33: 48245253 | I33: 9783793 | L33: 4500000 | M33: 4500000
A34: CE19A120 | D34: व्हर्मीकंपोस्ट पध्दतीचे प्रक्रिया प्रकल्प उभारणे. | E34: 0 | F34: 153449062 | G34: 153449062 | H34: 153449062 | I34: 0 | L34: 0 | M34: 0
A35: CE19A122 | D35: कचरा प्रक्रिया प्रकल्पासाठी जागा ताब्यात घेणे, कंपाउंड करणे, रस्ते करणे व तदनुषंगिक कामे करणे. | E35: 0 | F35: 80797347 | G35: 80797347 | H35: 70039173 | I35: 10758174 | L35: 9000000 | M35: 9000000
A36: CE19A123 | D36: ताब्यात येणार्‍या जागांवर प्रक्रिया प्रकल्प उभारणे, प्रकल्पांसाठी आवश्यक सुविधा विषयक कामे करणे इत्यादी. | E36: 0 | F36: 319085651 | G36: 319085651 | H36: 245750959 | I36: 73334692 | L36: 129150000 | M36: 129150000
A37: CE19A139 | D37: उरुळी देवाची/फुरसंगी येथील गावांमध्ये विविध विकास कामे करणे | E37: 0 | F37: 518198479 | G37: 518198479 | H37: 510456552 | I37: 7741927 | L37: 9000000 | M37: 9000000
A38: CE19A141 | D38: घनकचरा व्यवस्थापनकडील कचरागाडया, बंदिस्त करणे विविध रॅम्प बंदिस्त करणे व कॉक्रीट करणे. | E38: 0 | F38: 131705349 | G38: 131705349 | H38: 117603119 | I38: 14102230 | L38: 13500000 | M38: 13500000
A39: CE19A143 | D39: गार्डन वेस्टसाठी विविध ठिकाणी पुणे मनपा हद्दीत श्रेडर मशिन बसविणे | E39: 0 | F39: 8198533 | G39: 8198533 | H39: 6357180 | I39: 1841353 | L39: 900000 | M39: 900000
A40: CE19A153 | D40: प्लास्टिक व इलेक्ट्रॉनिक वस्तू विभाजीत करणेकरीता शेड बांधणे | E40: 0 | F40: 19528393 | G40: 19528393 | H40: 16028393 | I40: 3500000 | L40: 2250000 | M40: 2250000
A41: CE19A154# | C41: _ | D41: शहरात घनकचरा संदर्भात विविध विकास कामे करणे | E41: 0 | F41: 289378553 | G41: 289378553 | H41: 254278545 | I41: 35100008 | L41: 0 | M41: 0
A42: CE19A155 | D42: e-waste जमा करणे व प्रक्रिया करणे | E42: 0 | F42: 4350000 | G42: 4350000 | H42: 850000 | I42: 3500000 | L42: 3150000 | M42: 3150000
A43: CE19A156 | D43: कचरा वाहतुकीसाठी नव्याने उपनगरांमध्ये रॅम्पचे आधुनिकीकरण, विकासकामे करणे, यंत्रसामग्री | E43: 0 | F43: 89889926 | G43: 89889926 | H43: 61791166 | I43: 28098760 | L43: 144000000 | M43: 144000000
A44: CE19A157 | D44: उरळी देवाची / फुरसुंगी येथे इनर्ट / रिजेक्ट मटेरीयलसाठी नव्याने शास्त्रोक्त लॅण्डफील विकसीत करणे व त्याची देखभाल दुरुस्ती करणे | E44: 0 | F44: 325123460 | G44: 325123460 | H44: 248123438 | I44: 77000022 | L44: 90000000 | M44: 90000000
A45: CE19A158 | D45: पुणे महानगरपालिकाच्या नव्याने समाविष्ट होणाऱ्या गावामध्ये घनकचरा व्यवस्थापनाशी संबधीत कामे करणे | E45: 0 | F45: 29305818 | G45: 29305818 | H45: 15305818 | I45: 14000000 | L45: 72000000 | M45: 72000000
A46: CE19A163 | D46: घनकचरा व्यवस्थापनाअंतर्गत विकेंद्रीत पध्दतीने प्रभाग व वॉर्डनिहाय कचरा प्रकिया केंद्र उभारणे व तद्‌नुषंगिक कामे करणे | E46: 0 | F46: 512424317 | G46: 512424317 | H46: 406905632 | I46: 105518685 | L46: 54000000 | M46: 54000000
A47: CE19A168 | D47: पुणे मनपाच्या अस्तित्वातील कचरा हस्तांतर केंद्र व हजेरीकोठ्‌या व विविध प्रकल्प याठिकाणी सेवकांसाठी सुविधा पुरविणे व बांधकामासाठी देखभाल दुरूस्ती करणे | E47: 0 | F47: 23768891 | G47: 23768891 | H47: 16723185 | I47: 7045706 | L47: 5400000 | M47: 5400000
A48: CE19A169 | D48: स्वच्छ भारत अभियान अंतर्गत मनपाचा हिस्सा | E48: 0 | F48: 211133993 | G48: 211133993 | H48: 206833993 | I48: 4300000 | L48: 450000 | M48: 450000
A49: CE19A171 | D49: समग्रसाठी मनपाचा हिस्सा | E49: 0 | F49: 16177027 | G49: 16177027 | H49: 16177027 | I49: 0 | L49: 0 | M49: 0
A50: CE19A173 | D50: सार्वजनीक स्वच्छतागृह बांधणे | E50: 0 | F50: 56916137 | G50: 56916137 | H50: 47838679 | I50: 9077458 | L50: 18000000 | M50: 18000000
A51: CE19A174 | D51: e-toilet करणे, जुन्या बसचे स्वच्छतागृहामध्ये रूपांतर करणे | E51: 0 | F51: 4000851 | G51: 4000851 | H51: 4000851 | I51: 0 | L51: 0 | M51: 0
A52: CE19A178 | D52: उरूळी देवाची/फुरसंगी डेपो येथील साठलेल्या कचऱ्यावर बायोमायनिंग प्रक्रिया करणे | E52: 0 | F52: 473564507 | G52: 473564507 | H52: 309060336 | I52: 164504171 | L52: 272000000 | M52: 272000000
A53: CE19A179 | D53: उरूळी देवाची/फुरसंगी डेपो येथील साठलेल्या कचऱ्यावर बायोमायनिंग प्रक्रिया करण्यासाठीच्या ठिकाणी रस्ता करणे, R.O. Plant बसविणे | E53: 0 | F53: 71254250 | G53: 71254250 | H53: 41739372 | I53: 29514878 | L53: 9000000 | M53: 9000000
... A67: CE19A194 | D67: पुणे शहरातील उद्यानांमधील कचऱ्यावर प्रक्रिया करण्यासाठी | E67: 0 | F67: 0 | G67: 0 | H67: 0 | I67: 0 | L67: 2500000 | M67: 2500000
E68: 0 | F68: 0 | G68: 0 | H68: 0 | I68: 0 | L68: 0 | M68: 0
D69: ९. पथांची झाडलोट / घनकचरा व्यवस्थापन विभाग एकूण बेरीज | E69: 0 | F69: 5262564941 | G69: 5262564941 | H69: 4085466066 | I69: 1177098875 | L69: 1280000000 | M69: 1280000000
E70: 0 | F70: 0 | G70: 0 | H70: 0 | I70: 0 | L70: 0 | M70: 0
D71: १०क. पथ सुधारणा विभाग | E71: 0 | F71: 0 | G71: 0 | H71: 0 | I71: 0 | L71: 0 | M71: 0
A72: CE20A102# | B72: A2- | C72: _ | D72: शहरामधील रस्ते विकसित करणे आणि डांबरीकरण करणे | E72: 11538000 | F72: 10858850779 | G72: 10870388779 | H72: 9317394237 | I72: 1552994542 | L72: 2921400000 | M72: 2921400000
A73: CE20A103# | B73: A13- | C73: _ | D73: Pedestrian Policy नुसार शहरातील फूटपाथ विकसित करणे | E73: 0 | F73: 3500588562 | G73: 3500588562 | H73: 3199452105 | I73: 301136457 | L73: 130700000 | M73: 130700000
A74: CE20A104# | B74: _ | C74: _ | D74: शहरात पेव्हिंग ब्लॉक, इंटरलॉकिंग ब्लॉक बसविणे | E74: 0 | F74: 226512603 | G74: 226512603 | H74: 226512603 | I74: 0 | L74: 0 | M74: 0
A75: CE20A884# | B75: A10- | C75: _ | D75: शहरात विविध विकासाची कामे करणे | E75: 0 | F75: 2100564974 | G75: 2100564974 | H75: 1827142377 | I75: 273422597 | L75: 16500000 | M75: 16500000
A76: CE20A1248# | B76: A5- | D76: शहरातील प्रमुख डी.पी. रस्त्यांचे भूसंपादन करणे | E76: 0 | F76: 0 | G76: 0 | H76: 0 | I76: 0 | L76: 345000000 | M76: 345000000
A77: CE20A1249# | B77: A6- | C77: _ | D77: शहरामधील रस्ते विकसित करणे | E77: 0 | F77: 3863793091 | G77: 3863793091 | H77: 3355056510 | I77: 508736581 | L77: 933900000 | M77: 933900000
A78: CE20A1250# | B78: _ | C78: _ | D78: पुणे शहरात CMP आराखड्यानुसार (PPP / Development TDR / Deffered payment / Premium charges) अन्वये प्रशासकीय मुल्यमापनानुसार प्रत्यक्ष अंमलबजावणी करून कामे करणे | E78: 0 | F78: 310594176 | G78: 310594176 | H78: 310594176 | I78: 0 | L78: 0 | M78: 0
A79: CE20A1259# | B79: A9- | D79: शहरातील रस्ते पुनर्डांबरीकरण करणे | E79: 0 | F79: 1096400594 | G79: 1096400594 | H79: 1083697681 | I79: 12702913 | L79: 560200000 | M79: 560200000
A80: CE20A1262# | B80: A15- | C80: _ | D80: शहरातील रस्ते काँक्रीटने विकसित करणे | E80: 0 | F80: 5142029082 | G80: 5142029082 | H80: 4561280556 | I80: 580748526 | L80: 75000000 | M80: 75000000
A81: CE20A1263# | B81: A16- | C81: _ | D81: शहरामध्ये BRT मार्ग विकसित करणे | E81: 0 | F81: 2228657527 | G81: 2228657527 | H81: 2220905816 | I81: 7751711 | L81: 60000000 | M81: 60000000
A82: CE20A1264# | B82: A17- | D82: शहरामध्ये सायकल ट्रॅक विकसित करणे | E82: 0 | F82: 228272597 | G82: 228272597 | H82: 149121876 | I82: 79150721 | L82: 101500000 | M82: 101500000
A83: CE20A1266# | B83: A18- | D83: नविन समाविष्ट गावांमध्ये रस्ते विकसित करणे | E83: 0 | F83: 381790609 | G83: 381790609 | H83: 374411239 | I83: 7379370 | L83: 1000000 | M83: 1000000
E84: 0 | F84: 0 | G84: 0 | H84: 0 | I84: 0 | L84: 0 | M84: 0
D85: १०क. पथ सुधारणा विभाग एकूण बेरीज | E85: 11538000 | F85: 29938054594 | G85: 29949592594 | H85: 26625569176 | I85: 3324023418 | L85: 5145200000 | M85: 5145200000
E86: 0 | F86: 0 | G86: 0 | H86: 0 | I86: 0 | L86: 0 | M86: 0
E87: 0 | F87: 0 | G87: 0 | H87: 0 | I87: 0 | L87: 0 | M87: 0
D88: १०ख. वाहतूक नियंत्रण विभाग | E88: 0 | F88: 0 | G88: 0 | H88: 0 | I88: 0 | L88: 0 | M88: 0
A89: CE20B101# | B89: _ | C89: _ | D89: शहरामधील चौकांची सुधारणा / विकासकामे करणे | E89: 0 | F89: 340521100 | G89: 340521100 | H89: 322135413 | I89: 18385687 | L89: 0 | M89: 0
A90: CE20B102# | B90: T2- | C90: _ | D90: शहरामधील चौकांची सुधारणा / विकासकामे करणे, वाहतूक सुधारण्यासाठी विविध विकास कामे करणे | E90: 0 | F90: 3277526920 | G90: 3277526920 | H90: 2956137130 | I90: 321389790 | L90: 1162000000 | M90: 1162000000
A91: CE20B107# | B91: _ | D91: रस्त्यांवरील टी जंक्शनचा विकास व सुधारणा व वाहनतळ निर्माण करणे | E91: 0 | F91: 46384542 | G91: 46384542 | H91: 46384542 | I91: 0 | L91: 0 | M91: 0
A92: CE20B108# | B92: T7- | C92: _ | D92: शहरातील वाहनतळांचा जागा विकसित करणे / वाहनतळ निर्माण करणे | E92: 0 | F92: 367012939 | G92: 367012939 | H92: 154637150 | I92: 212375789 | L92: 6000000 | M92: 6000000
A93: CE20B251 | B93: G | C93: P | D93: पुणे शहरातील रिक्षांना CNG Kit बसविणेसाठी अनुदान देणे | E93: 0 | F93: 104760941 | G93: 104760941 | H93: 95760941 | I93: 9000000 | L93: 0 | M93: 0
E94: 0 | F94: 0 | G94: 0 | H94: 0 | I94: 0 | L94: 0 | M94: 0
D95: १०ख. वाहतूक नियंत्रण विभाग एकूण बेरीज | E95: 0 | F95: 4137021583 | G95: 4137021583 | H95: 3575870317 | I95: 561151266 | L95: 1168000000 | M95: 1168000000
D96: १०ग. विद्युत विभाग | E96: 0 | F96: 0 | G96: 0 | H96: 0 | I96: 0 | L96: 0 | M96: 0
A97: CE20C352# | B97: B5- | C97: _ | D97: शहरातील विविध ठिकाणी प्रकाश व्यवस्था करणे | E97: 0 | F97: 6175004297 | G97: 6175004297 | H97: 5822168039 | I97: 352836258 | L97: 141100000 | M97: 141100000
A98: CE20C550# | B98: _ | C98: _ | D98: शहरामध्ये भूमिगत केबल टाकणे | E98: 0 | F98: 865129721 | G98: 865129721 | H98: 737266831 | I98: 127862890 | L98: 0 | M98: 0
A99: CE20C551# | B99: B8- | C99: _ | D99: शहरामधील विविध भवनांमध्ये विद्युतविषयक कामे करणे | E99: 0 | F99: 209006621 | G99: 209006621 | H99: 203484857 | I99: 5521764 | L99: 21000000 | M99: 21000000
E100: 0 | F100: 0 | G100: 0 | H100: 0 | I100: 0 | L100: 0 | M100: 0
D101: १०ग. विद्युत विभाग एकूण बेरीज | E101: 0 | F101: 7249140639 | G101: 7249140639 | H101: 6762919727 | I101: 486220912 | L101: 162100000 | M101: 162100000
E102: 0 | F102: 0 | G102: 0 | H102: 0 | I102: 0 | L102: 0 | M102: 0
D103: १०घ. पूल व नदी सुधारणा (विकास योजना) | E103: 0 | F103: 0 | G103: 0 | H103: 0 | I103: 0 | L103: 0 | M103: 0
A104: CE20D170# | B104: L1- | C104: _ | D104: शहरात विविध ठिकाणी पूल बांधणे / उड्डाणपूल बांधणे / भुयारी मार्ग करणे | E104: 0 | F104: 1774917217 | G104: 1774917217 | H104: 1227599849 | I104: 547317368 | L104: 1645000000 | M104: 1645000000
A105: CE20D219# | B105: L2- | C105: _ | D105: शहरातील नदी सुधारणा कामे करणे व तद्‌नुषंगिक कामे करणे | E105: 0 | F105: 152062969 | G105: 152062969 | H105: 76186742 | I105: 75876227 | L105: 2750000000 | M105: 2750000000
E106: 0 | F106: 0 | G106: 0 | H106: 0 | I106: 0 | L106: 0 | M106: 0
D107: १०घ. पूल व नदी सुधारणा (विकास योजना) एकूण बेरीज | E107: 0 | F107: 1926980186 | G107: 1926980186 | H107: 1303786591 | I107: 623193595 | L107: 4395000000 | M107: 4395000000
E108: 0 | F108: 0 | G108: 0 | H108: 0 | I108: 0 | L108: 0 | M108: 0
D109: १०च. स्ट्रॉम वॉटर ड्रेन प्रकल्प | E109: 0 | F109: 0 | G109: 0 | H109: 0 | I109: 0 | L109: 0 | M109: 0
A110: CE20E101# | B110: F1- | C110: _ | D110: पुणे शहरातील पावसाळी पाण्याच्या व्यवस्थापनासाठी नाला सुधारणा कामे, कल्व्हर्टस व पावसाळी लाईन टाकणे | E110: 0 | F110: 4797404365 | G110: 4797404365 | H110: 4702204188 | I110: 95200177 | L110: 507500000 | M110: 507500000
E111: 0 | F111: 0 | G111: 0 | H111: 0 | I111: 0 | L111: 0 | M111: 0
D112: १०च. स्ट्रॉम वॉटर ड्रेन प्रकल्प एकूण बेरीज | E112: 0 | F112: 4797404365 | G112: 4797404365 | H112: 4702204188 | I112: 95200177 | L112: 507500000 | M112: 507500000
E113: 0 | F113: 0 | G113: 0 | H113: 0 | I113: 0 | L113: 0 | M113: 0
D114: १२. भवने, भूमी व मनपा वसाहती यांची व्यवस्था | E114: 0 | F114: 0 | G114: 0 | H114: 0 | I114: 0 | L114: 0 | M114: 0
A115: CE22A370# | B115: _ | C115: _ | D115: शहरात विविध ठिकाणी व्यायाम शाळा बांधणे | E115: 0 | F115: 268874714 | G115: 268874714 | H115: 268874714 | I115: 0 | L115: 0 | M115: 0
A116: CE22A458# | B116: _ | C116: _ | D116: शहरामध्ये समाजमंदिर, ग्रंथालय, वाचनालय, अभ्यासिका, एमपीएसी/ युपीएससी केंद्रे उभारणे | E116: 0 | F116: 468043007 | G116: 468043007 | H116: 468043007 | I116: 0 | L116: 0 | M116: 0
...

Sheet A_Land_Acquisition
A1: सन 2022-23 चे अंदाजपत्रक - खास निधीतून करावयाची योजनांतर्गत कामे
A2: अनुक्रमांक | C2: कामाचे नाव | D2: मान्य अंदाज 2021-22 | E2: नवीन अंदाज 2022-23
A5: (अ) | C5: भूमी संपादन निधीतून करावयाचा खर्च | D5: 0 | E5: 0
D6: 0 | E6: 0
A7: 1 | B7: FE11A101 | C7: भूमी संपादन विशेष अधिकारी यांचा कार्यालयीन खर्च - | D7: 14000000 | E7: 50000000
A8: 2 | C8: कोर्टाच्या निकालानुसार वाढीव नुकसानभरपाई कोर्ट खर्च, वकील फी, जॉइन्ट जज्ज यांचा खर्च वगैरे | D8: 0 | E8: 0
A9: 3 | C9: भूमी संपादन अधिनियमात नव्याने केलेल्या दुरुस्तीमुळे यापूर्वी जाहीर झालेल्या योजनापोटी ावयाच्या वाढीव रकमेचा खर्च | D9: 0 | E9: 0
A10: 4 | C10: परचेस नोटीसांमुळे (नवीन) पाठवावयाच्या भूमी संपादन योजनांसाठी तरतूद | D10: 0 | E10: 0
A11: 5 | C11: ताब्यात घेतलेल्या मिळकती पाडणे, ड्रेनेज, वॉटर, इलेक्ट्रीक टेलिफोन वगैरे कनेक्शन्स हलविणे, जोडणे व इतर तद्‌नुषंगिक कामे करणे. | D11: 0 | E11: 0
A12: 6 | C12: कार्यालयीन कामासाठी साधने, डेडस्टॉक वस्तू खरेदी करणे, हत्यारे खरेदी करणे, कार्यालय व कोठीची दुरुस्ती करणे, आवश्यक सुधारणा करणे, प्रकटन खर्च, प्रवास खर्च वगैर | D12: 0 | E12: 0
A13: 7 | C13: मुंबई प्रांतिक मनपा अधिनियम १९४९ च्या कलम २१३ अन्वये रस्तारूंदीसाठी ताब्यात घेतलेल्या मोकळ्या जागा व त्याप्रित्यर्थ ावयाची नुकसानभरपाईची रक्कम | D13: 0 | E13: 0
A14: 8 | C14: इतर योजनांमधील मोजणी फी व इतर तद्‌नुषंगिक रक्कम | D14: 0 | E14: 0
A15: 9 | C15: भूमी संपादन अधिकारी ह्यांचेकडील खालील नमूद केलेल्या ज्या जागांचे निवाडे जाहीर करतील त्यासाठी रक्कम | D15: 0 | E15: 0
A16: 10 | C16: संगणक दुरूस्ती व आवश्यक साहित्य | D16: 0 | E16: 0
D17: 0 | E17: 0
C18: (अ) बेरीज | D18: 14000000 | E18: 50000000
D19: 0 | E19: 0
D20: 0 | E20: 0
B21: FE11A102 | C21: भूसंपादनासाठी आवश्यक जागांची यादी :- | D21: 161000000 | E21: 250000000
D22: 0 | E22: 0
C23: सी.वाय.जी अंतर्गत रस्ते : | D23: 0 | E23: 0
C24: बाणेर मुख्य रस्ता २६१ ते १०५ | D24: 0 | E24: 0
C25: बाणेर स.क्र. १३३ ते बालेवाडी स.क्र. १० बालेवाडीकडे जाणारा रस्ता मुख्य रस्ता (बालेवाडी) | D25: 0 | E25: 0
C26: बालेवाडी स.क्र. ३४, ३५ जी१ गार्डनचे आरक्षण | D26: 0 | E26: 0
C27: बाणेर स.क्र. २८, २९० जी२ गार्डनचे आरक्षण व बाणेर स.क्र. ३५ जी३ गार्डनचे आरक्षण | D27: 0 | E27: 0
C28: कल्याणीनगर जंक्शन ते आळंदी रोड | D28: 0 | E28: 0
C29: बाणेर स.क्र. १०५, १०६, ११०, १११ पीएमटी१ | D29: 0 | E29: 0
C30: बाणेर स.क्र. ३३ पी.३ | D30: 0 | E30: 0
C31: बाणेर स.क्र. १०० पी.४ | D31: 0 | E31: 0
C32: बाणेर स.क्र. १७४ पी.४ | D32: 0 | E32: 0
C33: बाणेर स.क्र. ७९ पी.६ | D33: 0 | E33: 0
C34: बाणेर स.क्र. १०५, १०६ पी.७ पार्किंगचे आरक्षण | D34: 0 | E34: 0
... C40: एअरपोर्ट रोड ते डेक्कन कॉलेज व्हाया हॉटमिक्स प्लँट | D40: 0 | E40: 0
D41: 0 | E41: 0
C42: जेएनएनयुआरएम / बीआरटी अंतर्गत रस्ते : | D42: 0 | E42: 0
C43: बाणेर स.क्र. १०७, १०८ व ११० मधून जाणारा १८ मी. रस्ता. | D43: 0 | E43: 0
C44: मौजे खराडी ता. हवेली, संगमवाडी ते खराडी २४ मी. नदीकाठचा डी.पी. रस्ता | D44: 0 | E44: 0
C45: मौजे वडगांव शेरी ता. हवेली, संगमवाडी ते खराडी २४ मी. नदीकाठचा डी.पी. रस्ता | D45: 0 | E45: 0
C46: सिंहगड रस्ता महानगरपालिका हद्द दरम्यान नियोजनाते विकसीत करणे (वडगांव बुद्रुक) | D46: 0 | E46: 0
C47: सिंहगड रस्ता महानगरपालिका हद्द दरम्यान नियोजनाते विकसीत करणे (वडगांव खुर्द) | D47: 0 | E47: 0
C48: विश्रांतवाडी ते धानोरी | D48: 0 | E48: 0
C49: संचेती हॉस्पिटल ते गव्हर्नमेंट पोल्ट्री फार्म | D49: 0 | E49: 0
C50: पुणे स्टेशन ते मनपा रोड (कॅनॉट रोड) | D50: 0 | E50: 0
D51: 0 | E51: 0
C52: आरआरडीपी अंतर्गत रस्ते : | D52: 0 | E52: 0
C53: मुळा नदिवरील पिंपळे निलेख यांना जोडणारा पुल रस्त्याचे भुसंपाद (बाणेर) | D53: 0 | E53: 0
C54: सुतारवाडी रस्ता २४ मी. (जुना) | D54: 0 | E54: 0
C55: कोथरूड एकलव्य कॉलेज ते हायवेपर्यंत मुख्य रस्ता (१५ मी. नवीन) | D55: 0 | E55: 0
C56: कोथरूड महात्मा सोसायटी एकलव्य कॉलेज ते हायवे परिसरातील डी.पी. रस्ते (१५ मी.) व ( १८ मी.) | D56: 0 | E56: 0
C57: बालभारती ते पौड फाटा रस्ता | D57: 0 | E57: 0
C58: वारजे जकातनाका ते नवीन अहिरे हद्द एन.डी.ए. रोड जुना जकातनाका ते हायवे व वारजे माळवाडी टेकडीपर्यंत | D58: 0 | E58: 0
C59: जे.पी. नाईक इन्स्टिटयुट ते गणंजय सोसायटी | D59: 0 | E59: 0
C60: अलंकार पोलीस चौकी गिरीजा शंकर सोसायटी पश्चिमानगरी ते नाईक पूल डी.पी. रस्ता | D60: 0 | E60: 0
C61: चांदणी चौक ते सुस चौक | D61: 0 | E61: 0
C62: सिंहगड रोड दोन्ही कॅनॉलवरील प्रस्तावित पुलासह (वडगांव बुद्रुक) | D62: 0 | E62: 0
C63: सुस रस्ता ते बाणेर रस्ता रामनदी कडेचा रस्ता (बाणेर) | D63: 0 | E63: 0
... C65: सुस रस्ता ते बाणेर रस्ता रामनदी कडेचा रस्ता या रस्त्याचे भूसंपादन करणेबाबत (पाषाण) | D65: 0 | E65: 0
D66: 0 | E66: 0
C67: भूसंपादनाची इतर प्रकरणे : | D67: 0 | E67: 0
C68: पुणेमुंबई रस्ता हॅरीस ब्रिज ते खडकी कॅन्टोन्मेंट | D68: 0 | E68: 0
C69: हडपसर स.नं. २२६, २२४, २६६, २११, २१०, २०९, २०८, २०७ पोस्ट ऑफीस बाजूने जाणारा १८ मी. डी. पी. रस्ता | D69: 0 | E69: 0
C70: हडपसर स. नं. ८७, ८९, ९२, ९३, १०६, ३१२, ३१४, ३१ पैकी डी. पी. रस्त्यासाठी | D70: 0 | E70: 0
C71: हडपसर स.नं. २५ ईडब्ल्यूएस पैकी जागा संपादन करणेबाबत | D71: 0 | E71: 0
C72: घोरपडी गाव अनंत टॉकीज ते श्रीवस्ती नगर १२ मी डी.पी. रस्ता | D72: 0 | E72: 0
C73: कोंढवा खु.॥ स.नं. ५अ, ५ ब हायस्कूलसाठी संपादन | D73: 0 | E73: 0
C74: कोंढवा खु.॥ स.नं. १७ पै. मुलांचे खेळाचे मैदानासाठी | D74: 0 | E74: 0
C75: पुणे, पेठ पाषाण स.नं. ११० (पै.) पार्क (उान) साठी संपादन | D75: 0 | E75: 0
C76: हडपसर स.नं. ८४ पैकी प्ले ग्राऊंड साठी संपादन | D76: 0 | E76: 0
C77: वानवडी स.नं. ४९, ५८, ५९ | D77: 0 | E77: 0
C78: नाना पेठ, सि.सं. नं. ४०५ पै. उानासाठी आरक्षित जागा संपादन करणे | D78: 0 | E78: 0
... C93: हिंगणे / कर्वेनगर स.नं. ४० हायस्कूलसाठी | D93: 0 | E93: 0
D94: 0 | E94: 0
D95: 0 | E95: 0
C96: जाहीर झालेल्या निवाड्यापोटी भरण्याची रक्कम | D96: 0 | E96: 0
A97: 1 | C97: कर्वे रस्तारूंद जाहीर झालेल्या निवाड्यापोटी राहीलेली भरावयाची रक्कम | D97: 0 | E97: 0
A98: 2 | C98: सदाशिव पेठ घरांक ४६८ पार्किंगसाठी संपादन करणे | D98: 0 | E98: 0
D99: 0 | E99: 0
D100: 0 | E100: 0
C101: भूमिप्रापण खाते :- | D101: 0 | E101: 0
A102: 1 | C102: केळकर रस्ता (मंदार लॉज ते नारायण पेठ पोलीस चौकी) | D102: 0 | E102: 0
A103: 2 | C103: म्हात्रे पूल ते छत्रपती राजाराम पूल दरम्यानच्या नदीकाठचा १००'' डी.पी. रस्ता | D103: 0 | E103: 0
A104: 3 | C104: सातारा रस्ता | D104: 0 | E104: 0
A105: 4 | C105: सिंहगड रस्ता | D105: 0 | E105: 0
A106: 5 | C106: जंगली महाराज रस्ता | D106: 0 | E106: 0
A107: 6 | C107: पवित्र मंगल कार्यालया, पर्वती (सातारा रस्ता) | D107: 0 | E107: 0
A108: 7 | C108: नेहरू रस्ता, रास्ता पेठ पॉवर हाऊस ते लक्ष्मी रस्ता | D108: 0 | E108: 0
A109: 8 | C109: कर्वे रस्ता (खंडूजीबाबा चौक ते एस.एन.डी.टी.) | D109: 0 | E109: 0
A110: 9 | C110: शंकरशेठ रस्ता | D110: 0 | E110: 0
A111: 10 | C111: सेनापती बापट रस्ता | D111: 0 | E111: 0
A112: 11 | C112: उंबर्‍या गणपती चौक ते खुन्या मुरलीधर रस्ता | D112: 0 | E112: 0
A113: 12 | C113: भाऊ महाराज बोळ | D113: 0 | E113: 0
... A119: 18 | C119: रामवाडी जकातनाका ते लोहगाव विमानतळ | D119: 0 | E119: 0
D120: 0 | E120: 0
C121: जकात नाका :- | D121: 0 | E121: 0
A122: 1 | C122: शिंदेवाडी, स.नं. १०० ते १०६ (पैकी) | D122: 0 | E122: 0
A123: 2 | C123: फुरसुंगी, स.नं. १७५ पैकी | D123: 0 | E123: 0
A124: 3 | C124: वाघोली, गट नं. २३७८, २३७९ | D124: 0 | E124: 0
A125: 4 | C125: बावधन खुर्द, स.नं. ६४ | D125: 0 | E125: 0
A126: 5 | C126: हडपसर, स.नं. ६३ पैकी | D126: 0 | E126: 0
A127: 6 | C127: उंड्री, स.नं. ५४ पैकी | D127: 0 | E127: 0
...

Sheet A_Fund_Expenditure
A1: सन 2022-23 चे उपनगरे विकास निधीचे | H1: योजनांतर्गत खर्चाबाबतचे अंदाजपत्रक
A2: मान्यतेचा ठराव क्र. दिनांक (कोड) | B2: प्रभाग क्रमांक | C2: BPL | D2: कामाचे नाव अगर वर्णन | E2: दि. 31 मार्च 2022 अखेरपर्यंत केलेली तरतूद | H2: दि. 31 मार्च 2020 पर्यंतचा खर्चाचा नक्‍की आकडा | I2: 2020-21 मधील खर्चाचा नक्‍की आकडा | J2: 2021-22 मधील खर्चाची अंदाजी रक्‍कम | K2: 2022-23 साठी अधिक तरतूद | M2: 2022-23 साठी एकूण तरतूद | N2: शेरा
E3: कर्जातून | F3: महसूल निधीतून | G3: एकूण | K3: कर्जातून | L3: महसूल निधी व इतर निधी
D7: ४. झोपडपट्टी निर्मूलन व पुनर्वसन निधी | E7: 0 | F7: 0 | G7: 0 | H7: 0 | I7: 0 | J7: 0 | L7: 0 | M7: 0
A8: FE14A101# | B8: _ | C8: _ | D8: निरनिराळ्या झोपडपट्टींमध्ये विविध विकासाची कामे करणे | E8: 33377000 | F8: 1670472010 | G8: 1703849010 | H8: 1504273354 | I8: 39139701 | J8: 160435955 | L8: 0 | M8: 0
A9: FE14A104 | C9: B | D9: झो.नि.पु. अंतर्गत करावयाची कामे | E9: 0 | F9: 250159611 | G9: 250159611 | H9: 209140985 | I9: 23992261 | J9: 17026365 | L9: 15800000 | M9: 15800000
A10: FE14A105# | B10: _ | C10: _ | D10: शहरामध्ये शौच्छालये / मुताऱ्या बांधणे | E10: 0 | F10: 1921763843 | G10: 1921763843 | H10: 1531843629 | I10: 110695897 | J10: 279224317 | L10: 0 | M10: 0
A11: FE14A107 | C11: B | D11: दलित वस्ती सुधारणा अंतर्गत कामे करणे | E11: 0 | F11: 224696636 | G11: 224696636 | H11: 224696636 | I11: 14720804 | J11: -14720804 | L11: 0 | M11: 0
A12: FE14A129 | C12: PL | D12: सार्वजनिक ठिकाणी शौचालय बांधणे | E12: 0 | F12: 92709466 | G12: 92709466 | H12: 55159998 | I12: 20109765 | J12: 17439703 | L12: 15750000 | M12: 15750000
A13: FE14A130 | C13: PL | D13: सार्वजनिक ठिकाणी मुतार्‍या बांधणे | E13: 0 | F13: 70678303 | G13: 70678303 | H13: 30616748 | I13: 21862549 | J13: 18199006 | L13: 15750000 | M13: 15750000
A14: FE14A135 | D14: प्रभाग क्र.14ब, मधील बाबासाहेब आंबेडकर हॉस्टेल विकसित करणेकरिता अहवाल तयार करणे | E14: 0 | F14: 0 | G14: 0 | H14: 0 | I14: 0 | J14: 0 | L14: 0 | M14: 0
E15: 0 | F15: 0 | G15: 0 | H15: 0 | I15: 0 | J15: 0 | L15: 0 | M15: 0
D16: ४. झोपडपट्टी निर्मूलन व पुनर्वसन निधी एकूण बेरीज | E16: 33377000 | F16: 4230479869 | G16: 4263856869 | H16: 3555731350 | I16: 230520977 | J16: 477604542 | L16: 47300000 | M16: 47300000
E17: 0 | F17: 0 | G17: 0 | H17: 0 | I17: 0 | J17: 0 | L17: 0 | M17: 0
D18: क्षेत्रिय कार्यालयाने करावयाची कामे | E18: 0 | F18: 0 | G18: 0 | H18: 0 | I18: 0 | J18: 0 | L18: 0 | M18: 0
E19: 0 | F19: 0 | G19: 0 | H19: 0 | I19: 0 | J19: 0 | L19: 0 | M19: 0
A20: FE14A118# | B20: W5 | C20: B | D20: क्षेत्रिय कार्यालय : झो.नि.पु. विभागाने करावयाची कामे | E20: 0 | F20: 263527952 | G20: 263527952 | H20: 241301496 | I20: 1740454 | J20: 20486002 | L20: 3750000 | M20: 3750000
A21: FE14A121# | B21: C5 | C21: B | D21: क्षेत्रिय कार्यालय : नागरिकांच्या सहभाग योजनेतून झो.नि.पु. विभागाने करावयाची कामे | E21: 0 | F21: 146137357 | G21: 146137357 | H21: 139907204 | I21: 566153 | J21: 5664000 | L21: 5550000 | M21: 5550000
E22: 0 | F22: 0 | G22: 0 | H22: 0 | I22: 0 | J22: 0 | L22: 0 | M22: 0
D23: क्षेत्रिय कार्यालयाने करावयाची कामे एकूण बेरीज | E23: 0 | F23: 409665309 | G23: 409665309 | H23: 381208700 | I23: 2306607 | J23: 26150002 | L23: 9300000 | M23: 9300000
E24: 0 | F24: 0 | G24: 0 | H24: 0 | I24: 0 | J24: 0 | L24: 0 | M24: 0
D25: ४. झोपडपट्टी निर्मूलन व पुनर्वसन निधीतून करावयाची कामे + क्षेत्रिय कार्यालयाने करावयाची कामे एकूण बेरीज | E25: 33377000 | F25: 4640145178 | G25: 4673522178 | H25: 3936940050 | I25: 232827584 | J25: 503754544 | L25: 56600000 | M25: 56600000
E26: 0 | F26: 0 | G26: 0 | H26: 0 | I26: 0 | J26: 0 | L26: 0 | M26: 0
D27: ४अ. मागासवर्गीय कल्याणकारी योजना निधी | E27: 0 | F27: 0 | G27: 0 | H27: 0 | I27: 0 | J27: 0 | L27: 0 | M27: 0
A28: FE14B101 | C28: B-FA | D28: समाज विकास विभाग अंतर्गत मागासवर्गीय योजना | E28: 0 | F28: 544809550 | G28: 544809550 | H28: 474809550 | I28: 23433297 | J28: 46566703 | L28: 35000000 | M28: 35000000
A29: FE14B112 | C29: B-FA | D29: लोकशाहीर अण्णाभाऊ साठे शैक्षणिक मदत योजना | E29: 0 | F29: 256392082 | G29: 256392082 | H29: 170392082 | I29: 25625000 | J29: 60375000 | L29: 50000000 | M29: 50000000
A30: FE14B113 | C30: B-FA | D30: मौ. अबुल कलाम आझाद शैक्षणिक मदत योजना | E30: 0 | F30: 512558546 | G30: 512558546 | H30: 366558546 | I30: 46875000 | J30: 99125000 | L30: 80000000 | M30: 80000000
A31: FE14B121 | C31: B-T | D31: मागासवर्गीय विद्यार्थ्यांना स्पर्धा परिक्षा मार्गदर्शन केंद्र चालविणे | E31: 0 | F31: 11843896 | G31: 11843896 | H31: 5843896 | I31: 1020000 | J31: 4980000 | L31: 3000000 | M31: 3000000
A32: FE14B122 | C32: B-T | D32: बालविकास केंद्र व वस्ती रिसोर्स सेंटर सुरू करणे | E32: 0 | F32: 16298182 | G32: 16298182 | H32: 12798182 | I32: 130680 | J32: 3369320 | L32: 1500000 | M32: 1500000
A33: FE14B123 | C33: B | D33: मागासवर्गीय कल्याणकारी योजनेअंतर्गत विविध योजना राबविणेसाठी मानधन तत्वावरील सेवकांचा मानधन खर्च | E33: 0 | F33: 41002659 | G33: 41002659 | H33: 31002659 | I33: 3388892 | J33: 6611108 | L33: 6000000 | M33: 6000000
A34: FE14B127 | C34: B | D34: माता रमार्इ भिमराव आंबेडकर योजनेअंतर्गत गवनि घोषीत व शहरी गरीब योजनेतील पात्र ठरणाऱ्या विधवा, निराधार महिलांसाठी दरमहा रू.1,000/- अर्थसहाय्य करणे (मागासवर्गीय कल्याणकारी योजना) | E34: 0 | F34: 37402788 | G34: 37402788 | H34: 3402788 | I34: 1613000 | J34: 32387000 | L34: 17000000 | M34: 17000000
A35: FE14B128 | C35: B-FA | D35: डॉ. बाबासाहेब आंबेडकर विद्यार्थी वसतिगृह, घोले रोड येथील खाणावळीचा खर्च | E35: 0 | F35: 19447051 | G35: 19447051 | H35: 9447051 | I35: 172229 | J35: 9827771 | L35: 5000000 | M35: 5000000
A36: FE14B129 | C36: B-I | D36: शहरात आदिवासी विद्यार्थ्यांसाठी वसतिगृहे उभारणे | E36: 0 | F36: 77745809 | G36: 77745809 | H36: 17745809 | I36: 24825240 | J36: 35174760 | L36: 50000000 | M36: 50000000
A37: FE14B131 | C37: B-T | D37: विविध व्यावसायिक प्रशिक्षण देणे | E37: 0 | F37: 2795443 | G37: 2795443 | H37: 2795443 | I37: 0 | J37: 0 | L37: 0 | M37: 0
A38: FE14B133 | C38: B | D38: लोकशाहिर अण्णा भाऊ साठे यांच्या जन्मशताब्दी वर्षानिमित्त विविध कार्यक्रमाचे आयोजन करणे | E38: 0 | F38: 10000000 | G38: 10000000 | H38: 0 | I38: 0 | J38: 10000000 | L38: 0 | M38: 0
E39: 0 | F39: 0 | G39: 0 | H39: 0 | I39: 0 | J39: 0 | L39: 0 | M39: 0
D40: ४अ. मागासवर्गीय कल्याणकारी योजना निधी एकूण बेरीज | E40: 0 | F40: 1530296006 | G40: 1530296006 | H40: 1094796006 | I40: 127083338 | J40: 308416662 | L40: 247500000 | M40: 247500000
E41: 0 | F41: 0 | G41: 0 | H41: 0 | I41: 0 | J41: 0 | L41: 0 | M41: 0
D42: ४ब. महिलाबालकल्याण योजना निधी | E42: 0 | F42: 0 | G42: 0 | H42: 0 | I42: 0 | J42: 0 | L42: 0 | M42: 0
A43: FE14C101 | C43: PL-FA | D43: महिलाबालकल्याण योजना | E43: 0 | F43: 495419703 | G43: 495419703 | H43: 424848849 | I43: 15814293 | J43: 54756561 | L43: 35000000 | M43: 35000000
A44: FE14C108 | C44: PL-FA | D44: महिला सक्षमिकरणासाठी अनुदानाची योजना | E44: 0 | F44: 239030178 | G44: 239030178 | H44: 186530178 | I44: 20715000 | J44: 31785000 | L44: 25000000 | M44: 25000000
A45: FE14C118 | C45: PL | D45: नागरवस्तीच्या वापरातील समाजमंदिरे / इतर वास्तूंच्या विद्युत बिलांसाठी | E45: 0 | F45: 13538699 | G45: 13538699 | H45: 7388699 | I45: 1650000 | J45: 4500000 | L45: 5200000 | M45: 5200000
A46: FE14C125# | B46: M1- | C46: _ | D46: महिलाबाल कल्याण योजना अंतर्गत करावयाची कामे | E46: 0 | F46: 313306838 | G46: 313306838 | H46: 140786877 | I46: 33287991 | J46: 139231970 | L46: 17500000 | M46: 17500000
A47: FE14C134 | C47: PL-FA | D47: रस्त्यांवरील मुलांसाठी घरटे प्रकल्प | E47: 0 | F47: 120063660 | G47: 120063660 | H47: 80063660 | I47: 7482961 | J47: 32517039 | L47: 20000000 | M47: 20000000
A48: FE14C139 | C48: PL-T | D48: UCD मार्फत राबविल्या जाणार्‍या निरनिराळया उपक्रमासाठी लागणारा खर्च स्वयंरोजगार, प्रशिक्षण, साहित्य खरेदी इ. | E48: 0 | F48: 23847745 | G48: 23847745 | H48: 15847745 | I48: 0 | J48: 8000000 | L48: 4000000 | M48: 4000000
A49: FE14C140 | C49: PL-I | D49: पाळणाघर | E49: 0 | F49: 21286822 | G49: 21286822 | H49: 1286822 | I49: 581 | J49: 19999419 | L49: 10000000 | M49: 10000000
A50: FE14C140A | D50: असंघटित / संघटीत क्षेत्रात काम करणाऱ्या स्त्रियांच्या सोयीसाठी पाळणाघर सुरू करणे | E50: 0 | F50: 0 | G50: 0 | H50: 0 | I50: 0 | J50: 0 | L50: 0 | M50: 0
A51: FE14C142 | C51: PL-T | D51: शेजार समुहगट व इतर महिलांसाठी विविध स्पर्धा, उपक्रम घेणे | E51: 0 | F51: 3978455 | G51: 3978455 | H51: 3978455 | I51: 0 | J51: 0 | L51: 0 | M51: 0
A52: FE14C143 | C52: PL | D52: महिला व बाल कल्याण योजनेअंतर्गत विविध योजना राबविणेसाठी मानधन तत्वावरील सेवकांचा मानधन खर्च | E52: 0 | F52: 23364691 | G52: 23364691 | H52: 13364691 | I52: 3771201 | J52: 6228799 | L52: 6000000 | M52: 6000000
A53: FE14C156 | C53: PL | D53: युवतींसाठी विविध ठिकाणी स्वसंरक्षणाचे प्रशिक्षण देणे | E53: 0 | F53: 6924399 | G53: 6924399 | H53: 1924399 | I53: 148500 | J53: 4851500 | L53: 2500000 | M53: 2500000
A54: FE14C160 | C54: PL-FA | D54: मुलगी दत्तक योजना | E54: 0 | F54: 57327000 | G54: 57327000 | H54: 17327000 | I54: 500000 | J54: 39500000 | L54: 20000000 | M54: 20000000
A55: FE14C191 | C55: PL-I | D55: बचत गटातील उत्पादित केलेल्या मालाचे प्रदर्शन आयोजित करणे | E55: 0 | F55: 40029206 | G55: 40029206 | H55: 20029206 | I55: 19618 | J55: 19980382 | L55: 10000000 | M55: 10000000
A56: FE14C208 | C56: PL-I | D56: पुणे शहरातील रस्त्यांवरील मुलांकरिता विविध उपक्रम राबविणे | E56: 0 | F56: 100000000 | G56: 100000000 | H56: 0 | I56: 11187707 | J56: 88812293 | L56: 40000000 | M56: 40000000
A57: FE14C209 | C57: PL-T | D57: राणी लक्ष्मीबाई महिला सक्षमीकरण योजना | E57: 0 | F57: 60594060 | G57: 60594060 | H57: 0 | I57: 594060 | J57: 60000000 | L57: 30000000 | M57: 30000000
A58: FE14C210 | C58: PL-I | D58: बेघर महिलांसाठी रात्र निवारा प्रकल्प सुरू करणे | E58: 0 | F58: 16000000 | G58: 16000000 | H58: 0 | I58: 0 | J58: 16000000 | L58: 8000000 | M58: 8000000
A59: FE14C211 | C59: L-I | D59: १५ क्षेत्रिय कार्यालय येथे हिरकणी कक्ष सुरू करणे | E59: 0 | F59: 6861939 | G59: 6861939 | H59: 606135 | I59: 655616 | J59: 5600188 | L59: 3000000 | M59: 3000000
A60: FE14C212 | D60: महिला बचत गटांना रोजगार निर्मितीसाठी e-marketing साठी संकेतस्थळ सुरू करणे. | E60: 0 | F60: 5000000 | G60: 5000000 | H60: 0 | I60: 0 | J60: 5000000 | L60: 2500000 | M60: 2500000
A61: FE14C217 | C61: L | D61: राणी लक्ष्मीबाई दत्तक योजना | E61: 0 | F61: 15000000 | G61: 15000000 | H61: 0 | I61: 0 | J61: 15000000 | L61: 0 | M61: 0
A62: FE14C218 | C62: L | D62: अनाथ मुलांना शैक्षणिक सुविधा पुरविणे | E62: 0 | F62: 42000000 | G62: 42000000 | H62: 0 | I62: 0 | J62: 42000000 | L62: 1100000 | M62: 1100000
A63: FE14C219 | C63: L | D63: स्वच्छ झोपडपट्टी स्पर्धा, झोपडीत घनकचरा व्यवस्थापनाचे उत्कृष्ट काम करणाऱ्या व्यक्तीं व संस्था यांना परितोषिक देणे | E63: 0 | F63: 10000000 | G63: 10000000 | H63: 0 | I63: 804200 | J63: 9195800 | L63: 5000000 | M63: 5000000
A64: FE14C220 | C64: L | D64: महिला व बालके यांचेसाठी स्पर्धा घेणे | E64: 0 | F64: 0 | G64: 0 | H64: 0 | I64: 0 | J64: 0 | L64: 0 | M64: 0
A65: FE14C221 | C65: L | D65: स्त्री संसाधन केंद्र (सक्षमा कक्ष) चालविणे | E65: 0 | F65: 22238090 | G65: 22238090 | H65: 2238090 | I65: 4855253 | J65: 15144747 | L65: 10000000 | M65: 10000000
A66: FE14C222 | C66: L | D66: Gender Responsibility अभ्यासगट तयार करणे व शहर पातळीवर महिलांच्या सुरक्षिततेसाठी उपाययोजना करणे | E66: 0 | F66: 10000000 | G66: 10000000 | H66: 0 | I66: 0 | J66: 10000000 | L66: 5000000 | M66: 5000000
A67: FE14C223 | C67: L | D67: सार्वजनिक ठिकाणी महिलांच्या सुरक्षिततेसाठी safety mapping व safety audit करणे | E67: 0 | F67: 10000000 | G67: 10000000 | H67: 0 | I67: 0 | J67: 10000000 | L67: 5000000 | M67: 5000000
E68: 0 | F68: 0 | G68: 0 | H68: 0 | I68: 0 | J68: 0 | L68: 0 | M68: 0
D69: ४ब. महिलाबालकल्याण योजना निधी एकूण बेरीज | E69: 0 | F69: 1768040989 | G69: 1768040989 | H69: 1028450310 | I69: 101486981 | J69: 638103698 | L69: 264800000 | M69: 264800000
E70: 0 | F70: 0 | G70: 0 | H70: 0 | I70: 0 | J70: 0 | L70: 0 | M70: 0
D71: ४क. युवक कल्याणकारी योजना निधी (नागरवस्ती विकास योजना) | E71: 0 | F71: 0 | G71: 0 | H71: 0 | I71: 0 | J71: 0 | L71: 0 | M71: 0
A72: FE14D101 | C72: P-FA | D72: शहरातील तरुणांसाठी स्वयंरोजगार व प्रशिक्षणासाठी अनुदान देणे | E72: 0 | F72: 159010924 | G72: 159010924 | H72: 134010924 | I72: 5071434 | J72: 19928566 | L72: 20000000 | M72: 20000000
A73: FE14D118 | C73: P-FA | D73: लोकशाहीर अण्णाभाऊ साठे शैक्षणिक मदत योजना व मौ. अब्दुल कलाम आझाद शैक्षणिक मदत योजना | E73: 0 | F73: 1347020588 | G73: 1347020588 | H73: 1097020588 | I73: 107625000 | J73: 142375000 | L73: 150000000 | M73: 150000000
A74: FE14D122 | C74: P-I | D74: शहरात विविध ठिकाणी नाईट शेल्टर योजना राबविणे | E74: 0 | F74: 57353610 | G74: 57353610 | H74: 17353610 | I74: 670798 | J74: 39329202 | L74: 20000000 | M74: 20000000
A75: FE14D123 | C75: P | D75: प्रशिक्षण संस्थांतील शिक्षक व इतर कर्मचार्‍यांचे मानधन देणे | E75: 0 | F75: 30523876 | G75: 30523876 | H75: 10523876 | I75: 1187293 | J75: 18812707 | L75: 10000000 | M75: 10000000
A76: FE14D125 | C76: P-I | D76: हॅलो माय फ्रेड योजना राबविणे,युवकांसाठी कॉल सेंटर सुरू करणे (मानसिक आरोग्य) | E76: 0 | F76: 3409807 | G76: 3409807 | H76: 409807 | I76: 0 | J76: 3000000 | L76: 1500000 | M76: 1500000
A77: FE14D126 | C77: P-I | D77: नागरवस्ती विकास योजना विभागाच्या ताब्यात असणार्‍या जागेपोटी PMPML प्रशासनास भाडे देणे | E77: 0 | F77: 10000000 | G77: 10000000 | H77: 0 | I77: 5000000 | J77: 5000000 | L77: 60000000 | M77: 60000000
A78: FE14D129 | C78: P-T | D78: स्पर्धा परिक्षा मार्गदर्शन केंद्र चालविणे | E78: 0 | F78: 2884000 | G78: 2884000 | H78: 884000 | I78: 306000 | J78: 1694000 | L78: 2000000 | M78: 2000000
A79: FE14D136 | C79: P-I | D79: पुणे शहरात Light House प्रकल्प सुरू करणे | E79: 0 | F79: 71977667 | G79: 71977667 | H79: 1977667 | I79: 0 | J79: 70000000 | L79: 35000000 | M79: 35000000
A80: FE14D137 | C80: P-I | D80: समाज विकास केंद्रात अभ्यासिका सुरू करणे. | E80: 0 | F80: 987000 | G80: 987000 | H80: 987000 | I80: 0 | J80: 0 | K80: 0 | L80: 0 | M80: 0
A81: FE14D141 | D81: डॉ. बाबासाहेब आंबेडकर विद्यार्थी वसतीगृह, घोले रोड येथील विद्यार्थ्यांचा खानावळीचा खर्च देणे | E81: 0 | F81: 16527909 | G81: 16527909 | H81: 5527909 | I81: 0 | J81: 11000000 | L81: 5500000 | M81: 5500000
A82: FE14D144 | D82: MPSC, UPSC पुर्व परिक्षेत उत्तीर्ण होऊन मुख्य परिक्षेला पात्र होणा-या गुणानुक्रमे प्रत्येकी 100 विद्यार्थ्यांना पुस्तके खेरदीसाठी अर्थसहाय्य करणे | E82: 0 | F82: 2000000 | G82: 2000000 | H82: 0 | I82: 0 | J82: 2000000 | L82: 1000000 | M82: 1000000
A83: FE14D145 | D83: खादी ग्रामोद्योग आयोगाच्या नोडल एजन्सी असणा-या राष्ट्रीय कुंभारी प्रशिक्षण संस्थेबरोबर स्वयंरोजगार कार्यक्रम राबविणे. | E83: 0 | F83: 20000000 | G83: 20000000 | H83: 0 | I83: 0 | J83: 20000000 | L83: 0 | M83: 0
A84: FE14D149 | D84: प्रभाग क्र.29क येथे स्वयंरोजगार व स्टार्टअप प्रोत्साहन करण्यासाठी विविध योजना राबविणे | E84: 0 | F84: 1000000 | G84: 1000000 | H84: 0 | I84: 0 | J84: 1000000 | L84: 0 | M84: 0
A85: FE14D150 | D85: प्रभाग क्र.15 अ, मध्ये मुले व तरूणांमध्ये विज्ञांनाचा उलगडा होणेसाठी प्रशिक्षण शिबीर राबविणे. | E85: 0 | F85: 1000000 | G85: 1000000 | H85: 0 | I85: 0 | J85: 1000000 | L85: 0 | M85: 0
A86: FE14D151 | D86: पुणे शहरात PPP तत्त्वावर कौशल्य विकास केंद्र (Skill Development Centre) सुरू करणे | E86: 0 | F86: 300000000 | G86: 300000000 | H86: 0 | I86: 0 | J86: 300000000 | L86: 100000000 | M86: 100000000
A87: FE14D152 | D87: शायकीय मान्यताप्राप्त व्यवसायभिमुख प्रमाणपत्र अभ्यासक्रमांसाठी अर्थसहाय्य | E87: 0 | F87: 20000000 | G87: 20000000 | H87: 0 | I87: 0 | J87: 20000000 | L87: 5000000 | M87: 5000000
A88: FE14D153 | D88: स्टार्ट अप, मुद्रा, कौशल्य विकास योजनांच्या जनजागृसाठी कार्यक्रमांचे आयोजन | E88: 0 | F88: 20000000 | G88: 20000000 | H88: 0 | I88: 0 | J88: 20000000 | L88: 5000000 | M88: 5000000
A89: FE14D154 | D89: राष्ट्रीय विचारांच्या संवर्धनासाठी स्वामी विवेवकानंद परिषदेचे आयोजन करणे. | E89: 0 | F89: 5000000 | G89: 5000000 | H89: 0 | I89: 0 | J89: 5000000 | L89: 0 | M89: 0
A90: FE14D155 | D90: पुणे मनपा विविध विभाग, योजनांचे संशोधन करणा-यांना शिष्यवृत्ती देणे. | E90: 0 | F90: 1000000 | G90: 1000000 | H90: 0 | I90: 0 | J90: 1000000 | L90: 0 | M90: 0
A91: FE14D156 | D91: स्वयंसेवी संस्था, गणेशोत्सव मंडळाचे सहआयोजनातून मनपाचे कार्यक्रम राबविणे. | E91: 0 | F91: 10000000 | G91: 10000000 | H91: 0 | I91: 0 | J91: 10000000 | L91: 0 | M91: 0
A92: FE14D157 | D92: विविध शासकीय योजनांबाबत जनजागृती करण्यासाठी पुस्तिका तयार करणे. | E92: 0 | F92: 10000000 | G92: 10000000 | H92: 0 | I92: 0 | J92: 10000000 | L92: 1000000 | M92: 1000000
E93: 0 | F93: 0 | G93: 0 | H93: 0 | I93: 0 | J93: 0 | L93: 0 | M93: 0
D94: ४क. युवक कल्याणकारी योजना निधी (नागरवस्ती विकास योजना) एकूण बेरीज | E94: 0 | F94: 2092193846 | G94: 2092193846 | H94: 1271193846 | I94: 119860525 | J94: 701139475 | L94: 416000000 | M94: 416000000
E95: 0 | F95: 0 | G95: 0 | H95: 0 | I95: 0 | J95: 0 | L95: 0 | M95: 0
D96: ४ड. दिव्यांग कल्याणकारी योजना निधी | E96: 0 | F96: 0 | G96: 0 | H96: 0 | I96: 0 | J96: 0 | L96: 0 | M96: 0
A97: FE14E101 | D97: दिव्यांग कल्याणकारी योजना | E97: 0 | F97: 712313399 | G97: 712313399 | H97: 439813399 | I97: 51853183 | J97: 220646817 | L97: 150000000 | M97: 150000000
A98: FE14E101A | C98: H-FA | D98: अपंगांना (दिव्यांग) स्वयंरोजगारासाठी अर्थसहाय्य | E98: 0 | F98: 4295833 | G98: 4295833 | H98: 4295833 | I98: 0 | J98: 0 | K98: 0 | L98: 0 | M98: 0
A99: FE14E101B | C99: H-FA | D99: उध शिक्षणासाठी अर्थसहाय्य | E99: 0 | F99: 2923041 | G99: 2923041 | H99: 2923041 | I99: 0 | J99: 0 | K99: 0 | L99: 0 | M99: 0
A100: FE14E101C | C100: H-FA | D100: पुणे महानगरपालिका हद्दीतील अंध व अपंग, मुकबधिर व्यक्ति यांचेसाठी पुणे महानगरपालिकेमार्फत मोफत PMPML बस पास देणे | E100: 0 | F100: 155000000 | G100: 155000000 | H100: 60000000 | I100: 0 | J100: 95000000 | L100: 100000000 | M100: 100000000
A101: FE14E101D | C101: H-FA | D101: अंध, अपंग (दिव्यांग), विकलांग, मुकबधिर व्यक्तिंना कृत्रिम अवयव घेणेसाठी योजना | E101: 0 | F101: 5149721 | G101: 5149721 | H101: 4149721 | I101: 769412 | J101: 230588 | L101: 0 | M101: 0
A102: FE14E101E | C102: H-FA | D102: महापालिका क्षेत्रातील १८ वर्षापुढील मतिमंद व्यक्तींचा सांभाळ करणार्‍या महापालिका हद्दीतील नोंदणीकृत स्वयंसेवी संस्थेस अथवा मतिमंद व्यक्तीच्या पालकांस अर्थसहाय्य | E102: 0 | F102: 20600000 | G102: 20600000 | H102: 600000 | I102: 1293000 | J102: 18707000 | L102: 0 | M102: 0
A103: FE14E101F | C103: H-FA | D103: कुष्ठ पिडीत व १००% अतितीव्र अपंग (दिव्यांग) व्यक्तीकरिता वार्षिक अर्थसहाय्य योजना | E103: 0 | F103: 16027000 | G103: 16027000 | H103: 1027000 | I103: 482000 | J103: 14518000 | L103: 0 | M103: 0
...

Sheet A_DPDC_Machinery_Tree
A1: सन 2022-23 चे अंदाजपत्रक – खास निधीतून करावयाची योजनांतर्गत कामे
A2: विवरण | C2: नक्की आकडा | F2: मान्य अंदाज 2021-22 | G2: नवीन अंदाज 2022-23
C4: 2018-19 | D4: 2019-20 | E4: 2020-21
B6: ५. पुणे जिल्हा नियोजन व विकास मंडळ निधीतून करावयाची कामे
B7: ५अ. मा. आमदारांनी सुचविल्याप्रमाणे करावयाची विकासाची कामे
A8: FE15A101 | B8: बोपोडी मतदार संघ क्र. २४६ | C8: 0 | D8: 0 | E8: 0 | F8: 5000000 | G8: 5000000
A9: FE15A102 | B9: शिवाजीनगर मतदार संघ क्र. २४७ | C9: 7569383 | D9: 5663108 | E9: 5222480 | F9: 5000000 | G9: 5000000
A10: FE15A103 | B10: पर्वती मतदार संघ क्र. २४८ | C10: 4049517 | D10: 20538895 | E10: 8224490 | F10: 5000000 | G10: 5000000
A11: FE15A104 | B11: कसबा पेठ मतदार संघ क्र. २४९ | C11: 17250785 | D11: 7008244 | E11: 9752843 | F11: 5000000 | G11: 5000000
A12: FE15A105 | B12: भवानी पेठ मतदार संघ क्र. २५० | C12: 0 | D12: 0 | E12: 0 | F12: 5000000 | G12: 5000000
A13: FE15A106 | B13: पुणे (कॅन्टोन्मेंट) मतदार संघ क्र. २५१ | C13: 6022891 | D13: 928911 | E13: 424631 | F13: 5000000 | G13: 5000000
A14: FE15A107 | B14: विधान परिषद सदस्य | C14: 1627378 | D14: 1348324 | E14: 20726398 | F14: 2500000 | G14: 2500000
C15: 0 | D15: 0 | E15: 0 | F15: 0 | G15: 0
A16: FE15A108 | B16: ५ब. मा. खासदारांनी सुचविल्याप्रमाणे करावयाची विकासाची कामे | C16: 48067028 | D16: 39082990 | E16: 17265839 | F16: 20000000 | G16: 20000000
C17: 0 | D17: 0 | E17: 0 | F17: 0 | G17: 0
A18: FE15A110 | B18: महानगरपालिका क्षेत्रात मुलभूत सोईसुविधांसाठी विशेष अनुदान | C18: 8971934 | D18: 20903967 | E18: 48163144 | F18: 0 | G18: 0
A19: FE15A111 | B19: मुळशी मतदार संघ | C19: 0 | D19: 0 | E19: 0 | F19: 2500000 | G19: 2500000
A20: FE15A112 | B20: कोथरूड विधानसभा मतदार संघ | C20: 2487968 | D20: 0 | E20: 0 | F20: 5000000 | G20: 5000000
A21: FE15A113 | B21: हडपसर विधानसभा मतदार संघ | C21: 1486525 | D21: 338906 | E21: 0 | F21: 5000000 | G21: 5000000
A22: FE15A114 | B22: वडगांवशेरी विधानसभा मतदार संघ | C22: 0 | D22: 0 | E22: 273673 | F22: 5000000 | G22: 5000000
A23: FE15A115 | B23: खडकवासला विधानसभा मतदार संघ | C23: 0 | D23: 0 | E23: 2366999 | F23: 5000000 | G23: 5000000
A24: RE53A101 | B24: ५. पुणे जिल्हा नियोजन व विकास मंडळ निधीतून करावयाची कामे बेरीज | C24: 97533409 | D24: 95813345 | E24: 112420497 | F24: 75000000 | G24: 75000000
C25: 0 | D25: 0 | E25: 0 | F25: 0 | G25: 0
C26: 0 | D26: 0 | E26: 0 | F26: 0 | G26: 0
B27: ७. यंत्रसामुग्री घसारा निधीतून विकत घ्याववयाची नवीन सामुग्री | C27: 0 | D27: 0 | E27: 0 | F27: 0 | G27: 0
B28: अग्निशामक दलासाठी यंत्रसामुग्री :- | C28: 0 | D28: 0 | E28: 0 | F28: 0 | G28: 0
A29: FE17A103-1 | B29: वॉटर टँकर पंपासह | C29: 11680000 | D29: 0 | E29: 0 | F29: 29400000 | G29: 21000000
A30: FE17A103-2 | B30: फायर इंजिन गाडी | C30: 29199998 | D30: 26292205 | E30: 0 | F30: 36820000 | G30: 80000000
A31: FE17A103-12 | B31: रेस्क्यू इक्वीपमेंट व लाईट मास्ट | C31: 0 | D31: 1460426 | E31: 16276396 | F31: 0 | G31: 0
A32: FE17A113-6 | B32: विद्युत विभाग :- हायड्रॉलिक प्लॅटफॉर्म (2 नग) | C32: 0 | D32: 0 | E32: 0 | F32: 2800000 | G32: 0
A33: FE17A114-6 | B33: बॅकहो लोडर खरेदी करणे | C33: 4000200 | D33: 9840186 | E33: 0 | F33: 0 | G33: 5000000
A34: FE17A114-9 | B34: पथ विभागासाठी टिपर खरेदी करणे | C34: 13749120 | D34: 0 | E34: 0 | F34: 0 | G34: 8000000
A35: FE17A114-10 | B35: पथ विभागाकडील कोठ्यांसाठी रोलर्स, मिक्‍सर्स, पेव्हर अन्य यंत्रसामुग्री खरेदी करणे | C35: 0 | D35: 0 | E35: 0 | F35: 0 | G35: 9000000
A36: FE17A124 | B36: मोटार वाहन विभाग मशिनरी | C36: 81895 | D36: 631216 | E36: 496687 | F36: 1330000 | G36: 1500000
A37: FE17A146 | B37: मनपा पदाधिकारी व अधिकार्‍यांसाठी मोटारकार खरेदी करणे | C37: 3145700 | D37: 6706341 | E37: 0 | F37: 6510000 | G37: 500000
A38: FE17A149-3 | B38: कंटेनर दुरुस्ती व रंगवणे | C38: 1973896 | D38: 999989 | E38: 930424 | F38: 1680000 | G38: 2000000
A39: FE17A149-4 | B39: कचरा निर्मूलन विषयक यंत्रसामुग्री | C39: 179900 | D39: 996545 | E39: 0 | F39: 980000 | G39: 500000
A40: FE17A149-13 | B40: आयुर्मान संपलेली वाहणे बदलणे | C40: 2228582 | D40: 9907998 | E40: 9601015 | F40: 0 | G40: 30000000
... A53: FE17A277# | B53: यंत्रसामुग्री घसारा निधीतून विकत घ्याववयाची सामुग्री (यादी Y1) | C53: 40881598 | D53: 135664718 | E53: 13294690 | F53: 165500000 | G53: 6000000
C54: 0 | D54: 0 | E54: 0 | F54: 0 | G54: 0
A55: RE51A101 | B55: ७. यंत्रसामुग्री घसारा निधी बेरीज | C55: 244736988 | D55: 281442161 | E55: 125644293 | F55: 408470000 | G55: 276400000
C56: 0 | D56: 0 | E56: 0 | F56: 0 | G56: 0
B57: १०. वृक्ष संरक्षण व संवर्धन प्राधिकारी निधीतून करावयाचा खर्च | C57: 0 | D57: 0 | E57: 0 | F57: 0 | G57: 0
B58: १०क. वृक्ष संवर्धन व संरक्षण कार्यालयाकडील खर्च :- | C58: 0 | D58: 0 | E58: 0 | F58: 0 | G58: 0
A59: FE20A101A | B59: १. कायम सेवकवर्ग वेतन | C59: 31913916 | D59: 38835322 | E59: 57638337 | F59: 63525000 | G59: 70000000
A60: FE20A102A | B60: २. हंगामी सेवकवर्ग | C60: 0 | D60: 0 | E60: 0 | F60: 1155000 | G60: 1155000
C61: 0 | D61: 0 | E61: 0 | F61: 0 | G61: 0
B62: १०क. बेरीज | C62: 31913916 | D62: 38835322 | E62: 57638337 | F62: 64680000 | G62: 71155000
C63: 0 | D63: 0 | E63: 0 | F63: 0 | G63: 0
B64: १०ग. संकीर्ण :- | C64: 0 | D64: 0 | E64: 0 | F64: 0 | G64: 0
A65: FE20C101 | B65: १. मुद्रण | C65: 416140 | D65: 59375 | E65: 0 | F65: 500000 | G65: 550000
A66: FE20C102 | B66: २. लेखन व साहित्य | C66: 264514 | D66: 89702 | E66: 0 | F66: 750000 | G66: 750000
A67: FE20C103 | B67: ३. प्रकटन खर्च | C67: 0 | D67: 0 | E67: 0 | F67: 1200000 | G67: 1300000
A68: FE20C104 | B68: ४. टपालखर्च व पावती तिकिटे | C68: 0 | D68: 0 | E68: 0 | F68: 115000 | G68: 115000
A69: FE20C105 | B69: ५. गणवेष | C69: 0 | D69: 0 | E69: 0 | F69: 250000 | G69: 275000
A70: FE20C106 | B70: ६. पुस्तके व शिलकी साहित्य | C70: 0 | D70: 0 | E70: 0 | F70: 120000 | G70: 120000
A71: FE20C107 | B71: ७. मुलांसाठी मनोरंजन व इतर खर्च | C71: 216769 | D71: 213167 | E71: 0 | F71: 700000 | G71: 800000
A72: FE20C108 | B72: ८. ट्री अ‍ॅथॉरिटी सभा चहापान खर्च (न.स.) | C72: 0 | D72: 0 | E72: 0 | F72: 125000 | G72: 125000
C73: 0 | D73: 0 | E73: 0 | F73: 0 | G73: 0
B74: १०ग. बेरीज | C74: 897423 | D74: 362244 | E74: 0 | F74: 3760000 | G74: 4035000
C75: 0 | D75: 0 | E75: 0 | F75: 0 | G75: 0
A76: FE20D101 | B76: नर्सरीच्या वाढीसाठी रोपे, उपकरणे, खते, साहित्य खरेदी व दुरुस्ती देखभाल | C76: 1544104 | D76: 1422176 | E76: 0 | F76: 2000000 | G76: 2200000
A77: FE20Q101 | B77: पुणे शहरात शालेय विार्थ्यांसाठी पर्यावरणावर आधारित विविध उपक्रम राबविणे | C77: 0 | D77: 0 | E77: 0 | F77: 200000 | G77: 200000
A78: FE20E101 | B78: ड. मनपातर्फे फळाफुलांचे प्रदर्शन | C78: 1725000 | D78: 252594 | E78: 1479222 | F78: 2000000 | G78: 2000000
A79: FE20G101 | B79: छ. वृक्ष लागवडीसाठी ३ ते ४ वर्षे वयाची व १० ते १५ फूट उंचीची रोपे, झाडांचे संरक्षणासाठी ट्री गार्ड खरेदी व जुने ट्री गार्ड दुरुस्ती | C79: 2653704 | D79: 57800 | E79: 2724776 | F79: 4000000 | G79: 4400000
A80: FE20H101 | B80: ज. झाडांची हालवाहलव | C80: 931460 | D80: 0 | E80: 900391 | F80: 1300000 | G80: 1300000
A81: FE20I101 | B81: ञ. मनपा सार्वजनिक जागेवरील वृक्षारोपण, संरक्षण देखभाल व तद्‌नुषंगिक खर्च | C81: 4573903 | D81: 10027625 | E81: 6267314 | F81: 15000000 | G81: 20000000
A82: FE20K101 | B82: फ. ट्री अ‍ॅथॉरिटीस निरनिराळ्या ठिकाणी भेट देण्यासाठी खर्च | C82: 0 | D82: 0 | E82: 0 | F82: 1250000 | G82: 100000
A83: FE20L101 | B83: १०ब. वृक्षारोपण उत्तेजनार्थ बक्षिसे | C83: 0 | D83: 0 | E83: 0 | F83: 1000000 | G83: 1000000
A84: FE20M101 | B84: १०भ. कामगार नुकसान भरपाई कायाखाली नुकसानभरपाई | C84: 0 | D84: 0 | E84: 0 | F84: 150000 | G84: 150000
A85: FE20N101 | B85: १०क्ष. वृक्षगणना व अनुषंगिक कामे | C85: 28484982 | D85: 0 | E85: 2724000 | F85: 30000000 | G85: 30000000
A86: FE20P101 | B86: झाडांना पाणी घालण्यासाठी टँकर खरेदी करणे | C86: 0 | D86: 6124375 | E86: 0 | F86: 1320000 | G86: 1320000
A87: FE20P103 | B87: टायर्स सुटे भाग व देखभाल | C87: 7556692 | D87: 4937109 | E87: 9135611 | F87: 12500000 | G87: 14000000
... A109: FE20P133 | B109: स.नं. ३७,३८ पंचवटी पाषाण येथील वृक्ष लागवड, संवर्धन व इतर तदनुषंगिक कामे करणे | C109: 0 | D109: 0 | E109: 0 | F109: 0 | G109: 2500000
C110: 0 | D110: 0 | E110: 0 | F110: 0 | G110: 0
B111: १०. वृक्ष संरक्षण व संवर्धन प्राधिकारी निधीतून करावयाचा खर्च एकूण बेरीज | C111: 95235512 | D111: 81771029 | E111: 80869651 | F111: 160035000 | G111: 223385000
C112: 0 | D112: 0 | E112: 0 | F112: 0 | G112: 0
A113: FE31A101 | B113: १९. संकल्प निधी | C113: 8912638 | D113: 1421517 | E113: 55823 | F113: 0 | G113: 0
C114: 0 | D114: 0 | E114: 0 | F114: 0 | G114: 0
B115: १९. संकल्प निधी बेरीज | C115: 8912638 | D115: 1421517 | E115: 55823 | F115: 0 | G115: 0

Sheet A_List
D1: यादी क्र. R1
D2: थोर व्यक्तींच्या जयंती / पुण्यतिथी साजरी करणे (यादी R1)
D3: RE11A274/R1-
A5: code | B5: ward | D5: कामाचे नाव | E5: प्रकल्पीय रक्कम | F5: तरतूद
A7: RE11A274/R1-1 | D7: महात्मा फुले जयंती | F7: 100000
A8: RE11A274/R1-2 | D8: डॉ. बाबासाहेब आंबेडकर जयंती | F8: 150000
A9: RE11A274/R1-3 | D9: लोकशाहीर अण्णाभाऊ साठे जयंती | F9: 200000
A10: RE11A274/R1-4 | D10: ईद-ए-मिलाद (पैगंबर जयंती) | F10: 150000
A11: RE11A274/R1-5 | D11: शहरातील शिवजयंती साजरी करणे, रोषणाई करणे | F11: 200000
A12: RE11A274/R1-6 | D12: महात्मा फुले यांची पुण्यतिथी साजरी करणे (दि. 28 नोव्हेंबर) | F12: 500000
A13: RE11A274/R1-7 | D13: मौलाना अब्दुल कलाम आझाद जयंती व पुण्यतिथी साजरी करणे | F13: 600000
A14: RE11A274/R1-8 | D14: लहुजी वस्ताद साळवे जयंती महोत्सव गंज पेठ व संगमवाडी येथे साजरा करणे | F14: 500000
A15: RE11A274/R1-9 | D15: नेताजी सुभाषचंद्र बोस यांची जयंती साजरी करणे | F15: 10000
A16: RE11A274/R1-10 | D16: येरवडा येथे लोकशाहिर अण्णाभाऊ साठे जयंती महोत्सव साजरा करणे | F16: 100000
A17: RE11A274/R1-11 | D17: श्री संत रोहिदास महाराज जयंती, पुण्यतिथी साजरी करणे | F17: 50000
A18: RE11A274/R1-13 | D18: मौलाना अबुल कलाम आझाद जयंती महोत्सव | F18: 500000
A19: RE11A274/R1-14 | D19: महावीर जयंती | F19: 100000
D21: यादी क्र. R1 एकूण | E21: 0 | F21: 3160000
D24: यादी क्र. R2
D25: शहरामध्ये विविध कार्यक्रम, उत्सव, महोत्सव, संमेलन/ सहप्रायोजक तत्वावर कार्यक्रम साजरे करणे (यादी R2)
D26: RE11A275/R2-
A28: code | B28: ward | D28: कामाचे नाव | E28: प्रकल्पीय रक्कम | F28: तरतूद
A30: RE11A275/R2-1 | D30: महानगरपालिका वर्धापन दिन / सुवर्ण महोत्सव साजरा करणे | F30: 700000
A31: RE11A275/R2-2 | D31: वर्षातील महत्त्वपूर्ण दिन | F31: 600000
A32: RE11A275/R2-3 | D32: शिवाजीमहाराज आग्र्‍याहून सुटून परत आले तो स्मृती दिन साजरा करणे | F32: 515000
A33: RE11A275/R2-4 | D33: शनिवारवाडा सांस्कृतिक महोत्सव | F33: 2000000
A34: RE11A275/R2-5 | D34: भारतरत्न डॉ. बाबासाहेब आंबेडकर सांस्कृतिक महोत्सव साजरा करणे/ भिम फेस्टिवल (शनिवारवाडा पटांगण) / फुले आंबेडकर फेस्टिवल (समताभूमी) | F34: 2000000
A35: RE11A275/R2-6 | D35: शिवमहोत्सव साजरा करणे (१४ ते २० फेब्रुवारी) | F35: 2000000
A36: RE11A275/R2-7 | D36: अण्णाभाऊ साठे महोत्सव | F36: 2000000
A37: RE11A275/R2-8 | D37: जागतिक आदिवासी दिन | F37: 500000
A38: RE11A275/R2-11 | D38: प्रभाग क्र.३९ क धनकवडी आंबेगाव पठार मध्ये सांस्कृतिक व क्रीडा महोत्सव आयोजन करणे. | F38: 2000000
D40: यादी क्र. R2 एकूण | E40: 0 | F40: 12315000
D43: यादी क्र. R3
D44: सत्कार, अभिनंदन, पुरस्कार, बक्षिसे यासारखे कार्यक्रम साजरे करणे (यादी R3)
D45: RE11A276/R3-
A47: code | B47: ward | D47: कामाचे नाव | E47: प्रकल्पीय रक्कम | F47: तरतूद
A49: RE11A276/R3-1 | D49: गणेशोत्सव प्रशस्तिपत्रके वितरण | F49: 1000000
A50: RE11A276/R3-2 | D50: श्री संत ज्ञानेश्वर व तुकाराम महाराज पालखी स्वागत व दिंडी प्रमुखांचा स्मृतीचिन्ह देऊन सत्कार | F50: 1000000
A51: RE11A276/R3-3 | D51: प्रतिवर्षी पुणे शहरातील इयत्ता १० वी, १२ वी परिक्षेत गुणवत्ता यादीत येणार्‍या विद्यार्थ्यांचे अभिनंदन | F51: 60000
A52: RE11A276/R3-4 | D52: बालगंधर्व पुरस्कार प्रदानकरिता | F52: 500000
A53: RE11A276/R3-5 | D53: पठ्ठे बापूराव पुरस्कारकरिता | F53: 500000
A54: RE11A276/R3-6 | D54: आचार्य अत्रे पुरस्कारकरिता | F54: 300000
A55: RE11A276/R3-8 | D55: महर्षि वाल्मिकी पुरस्कार | F55: 500000
A56: RE11A276/R3-9 | D56: सावित्रीबाई फुले पुरस्कार | F56: 500000
A57: RE11A276/R3-10 | D57: मौलाना अब्दुल कलाम आझाद पुरस्कार | F57: 500000
A58: RE11A276/R3-11 | D58: जयंतराव टिळक पुरस्कार | F58: 500000
A59: RE11A276/R3-12 | D59: १ ऑक्टोंबर - जागतिक ज्येष्ठ नागरिक दिनाच्या मेळाव्याकरता आच्छादित मंडप टाकणे व स्मृतिचिन्हे देणे | F59: 100000
A60: RE11A276/R3-13 | D60: कै.यशवंतराव चव्हाण यांचे स्मरणार्थ कोथरुड पुणे येथे कै. यशवंतराव चव्हाण पुरस्कार देणे | F60: 175000
... A74: RE11A276/R3-30 | D74: लोकमान्य टिळक शैक्षणिक गुणवत्ता पुरस्कार | F74: 5000000
D76: यादी क्र. R3 एकूण | E76: 0 | F76: 16435000
D79: यादी क्र. R9
D80: ERP, Software Development, Data Entry, सेवकांना प्रशिक्षण खर्च, GIS, Works Management System, Kiosk व तद्‌नुषंगिक कामे (यादी R9)
D81: RE11N103/R9-
A83: code | B83: ward | D83: कामाचे नाव | E83: प्रकल्पीय रक्कम | F83: तरतूद
A85: RE11N103/R9-1 | D85: पुणे मनपाकरिता ई.आर.पी.सोल्युशन घेणे | F85: 36000000
A86: RE11N103/R9-2 | D86: विविध विभागांसाठी डॅशबोर्ड विकसित करणे. | F86: 12000000
A87: RE11N103/R9-3 | D87: जीआयएस व ईआरपी एकमेकांना जोडण्याची प्रणाली विकसित करणे | F87: 18000000
A88: RE11N103/R9-4 | D88: पुणे मनपासाठी क्‍लाउड सर्व्हिस घेणे | F88: 27000000
A89: RE11N103/R9-5 | D89: मनपाच्य विविध कार्यालयांमध्ये नवीन समाविष्ट गावे यांच्यासाठी BSNL इंटरनेट लीज लाईन घेणे. | F89: 4500000
A90: RE11N103/R9-6 | D90: तांत्रिक सल्लागार यांची पुणे मनपासाठी नियुक्‍ती करणे | F90: 12000000
A91: RE11N103/R9-7 | D91: पुणे मनपातील नागरी सुविधा केंद्र चालविणे. | F91: 24000000
A92: RE11N103/R9-8 | D92: आर्टीफिशल इंटलिजनसचा वापर करून विश्लेषणात्मक माहिती व्दारे कर संकलन वाढविणे | F92: 12000000
A93: RE11N103/R9-9 | D93: पुणे मनपातील सर्व्हर्स, हार्डवेअर, नेटवर्क व प्रिंटर्सची देखभाल व दुरुस्ती करणे | F93: 10500000
A94: RE11N103/R9-10 | D94: मनपा मुख्य भवन येथे प्रायमरी व सेकंडरी इंटरनेट १०० एमबीपीएसची लिज लाईन पुरविणे | F94: 3000000
A95: RE11N103/R9-11 | D95: पुणे मनपाकरिता कॉल सेंटर चालविणे | F95: 2400000
A96: RE11N103/R9-12 | D96: बल्क एस.एम.एस./ बल्क ई-मेल गेटवे पुरविणे | F96: 3000000
... A104: RE11N103/R9-20 | D104: पुणे मनपाचे विविध विभागांमध्ये Networking, Cabling विकसन व देखभाल दुरुस्ती करणे | F104: 6000000
D106: यादी क्र. R9 एकूण | E106: 0 | F106: 350000000
D109: यादी क्र. R4
D110: शहरातील विविध स्मशानभूमी, दफनभूमीमध्ये देखभालदुरूस्तीची कामे करणे (यादी R4)
D111: RE17F169/R4-
A113: code | B113: ward | D113: कामाचे नाव | E113: प्रकल्पीय रक्कम | F113: तरतूद
A115: RE17F169/R4-1 | D115: वैकुंठ स्मशानभूमी येथे सुधारणा कामे करणे | F115: 7500000
A116: RE17F169/R4-2 | D116: शहरातील हिंदू स्मशानभूमी येथे सुधारणा कामे करणे | F116: 20000000
A117: RE17F169/R4-3 | D117: शहरातील मुस्लिम कब्रस्तान येथे सुधारणा कामे करणे | F117: 10000000
A118: RE17F169/R4-4 | D118: शहरातील ख्रिश्चन दफनभूमी येथे सुधारणा कामे करणे | F118: 7500000
A119: RE17F169/R4-5 | D119: लिंगायत स्मशानभूमी येथे विविध सुधारणा कामे करणे | F119: 7500000
A120: RE17F169/R4-6 | D120: लिंगायत ख्रिश्चन मुस्लिम स्मशानभूमीमध्ये माती टाकणे | F120: 7500000
A121: RE17F169/R4-7 | D121: नव्याने समाविष्ट झालेल्या गावांतील स्मशानभूमी, कब्रस्तान, दफनभूमी येथे दुरुस्ती व सुधारणा कामे करणे | F121: 40000000
D123: यादी क्र. R4 एकूण | E123: 0 | F123: 100000000
D124: यादी क्र. R15
D125: रस्त्यांवरील चेंबर्स समपातळीत करणे, RCC चेंबर्स करणे, क्षेत्रीय कार्यालयनिहाय मोबाईल मेंटेनन्स युनिटद्वारे देखभालदुरूस्तीची कामे करणे व तद्‌नुषंगिक इतर कामे करणे (यादी R15)
D126: RE20B115/R15-
A128: code | B128: ward | D128: कामाचे नाव | E128: प्रकल्पीय रक्कम | F128: तरतूद
A130: RE20B115/R15-1 | D130: औंध - बाणेर क्षेत्रीय कार्यालयाचे कार्यक्षेत्रातील रस्त्यांवरील चेंबर्स समपातळीत करणे, RCC चेंबर्स करणे, क्षेत्रीय कार्यालय निहाय मोबाईल मेंटेनन्स युनिटद्वारे देखभाल दुरूस्तीची कामे करणे व तद्‌नुषंगिक इतर कामे करणे. | F130: 11250000
A131: RE20B115/R15-2 | D131: शिवाजीनगर - घोले रोड क्षेत्रीय कार्यालयाचे कार्यक्षेत्रातील रस्त्यांवरील चेंबर्स समपातळीत करणे, RCC चेंबर्स करणे, क्षेत्रीय कार्यालय निहाय मोबाईल मेंटेनन्स युनिटद्वारे देखभाल दुरूस्तीची कामे करणे व तद्‌नुषंगिक इतर कामे करणे. | F131: 11250000
A132: RE20B115/R15-3 | D132: सिंहगड रोड क्षेत्रीय कार्यालयाचे कार्यक्षेत्रातील रस्त्यांवरील चेंबर्स समपातळीत करणे, RCC चेंबर्स करणे, क्षेत्रीय कार्यालय निहाय मोबाईल मेंटेनन्स युनिटद्वारे देखभाल दुरूस्तीची कामे करणे व तद्‌नुषंगिक इतर कामे करणे. | F132: 11250000
A133: RE20B115/R15-4 | D133: वानवडी - रामटेकडी क्षेत्रीय कार्यालयाचे कार्यक्षेत्रातील रस्त्यांवरील चेंबर्स समपातळीत करणे, RCC चेंबर्स करणे, क्षेत्रीय कार्यालय निहाय मोबाईल मेंटेनन्स युनिटद्वारे देखभाल दुरूस्तीची कामे करणे व तद्‌नुषंगिक इतर कामे करणे. | F133: 11250000
A134: RE20B115/R15-5 | D134: कोंढवा - येवलेवाडी क्षेत्रीय कार्यालयाचे कार्यक्षेत्रातील रस्त्यांवरील चेंबर्स समपातळीत करणे, RCC चेंबर्स करणे, क्षेत्रीय कार्यालय निहाय मोबाईल मेंटेनन्स युनिटद्वारे देखभाल दुरूस्तीची कामे करणे व तद्‌नुषंगिक इतर कामे करणे. | F134: 11250000
A135: RE20B115/R15-6 | D135: कसबा - विश्रामबागवाडा क्षेत्रीय कार्यालयाचे कार्यक्षेत्रातील रस्त्यांवरील चेंबर्स समपातळीत करणे, RCC चेंबर्स करणे, क्षेत्रीय कार्यालय निहाय मोबाईल मेंटेनन्स युनिटद्वारे देखभाल दुरूस्तीची कामे करणे व तद्‌नुषंगिक इतर कामे करणे. | F135: 11250000
A136: RE20B115/R15-7 | D136: बिबवेवाडी क्षेत्रीय कार्यालयाचे कार्यक्षेत्रातील रस्त्यांवरील चेंबर्स समपातळीत करणे, RCC चेंबर्स करणे, क्षेत्रीय कार्यालय निहाय मोबाईल मेंटेनन्स युनिटद्वारे देखभाल दुरूस्तीची कामे करणे व तद्‌नुषंगिक इतर कामे करणे. | F136: 11250000
A137: RE20B115/R15-8 | D137: नगररोड - वडगांव शेरी क्षेत्रीय कार्यालयाचे कार्यक्षेत्रातील रस्त्यांवरील चेंबर्स समपातळीत करणे, RCC चेंबर्स करणे, क्षेत्रीय कार्यालय निहाय मोबाईल मेंटेनन्स युनिटद्वारे देखभाल दुरूस्तीची कामे करणे व तद्‌नुषंगिक इतर कामे करणे. | F137: 11250000
A138: RE20B115/R15-9 | D138: येरवडा कळस - धानोरी क्षेत्रीय कार्यालयाचे कार्यक्षेत्रातील रस्त्यांवरील चेंबर्स समपातळीत करणे, RCC चेंबर्स करणे, क्षेत्रीय कार्यालय निहाय मोबाईल मेंटेनन्स युनिटद्वारे देखभाल दुरूस्तीची कामे करणे व तद्‌नुषंगिक इतर कामे करणे. | F138: 11250000
A139: RE20B115/R15-10 | D139: ढोले पाटील क्षेत्रीय कार्यालयाचे कार्यक्षेत्रातील रस्त्यांवरील चेंबर्स समपातळीत करणे, RCC चेंबर्स करणे, क्षेत्रीय कार्यालय निहाय मोबाईल मेंटेनन्स युनिटद्वारे देखभाल दुरूस्तीची कामे करणे व तद्‌नुषंगिक इतर कामे करणे. | F139: 11250000
A140: RE20B115/R15-11 | D140: कोथरूड - बावधन क्षेत्रीय कार्यालयाचे कार्यक्षेत्रातील रस्त्यांवरील चेंबर्स समपातळीत करणे, RCC चेंबर्स करणे, क्षेत्रीय कार्यालय निहाय मोबाईल मेंटेनन्स युनिटद्वारे देखभाल दुरूस्तीची कामे करणे व तद्‌नुषंगिक इतर कामे करणे. | F140: 11250000
A141: RE20B115/R15-12 | D141: धनकवडी - सहकारनगर क्षेत्रीय कार्यालयाचे कार्यक्षेत्रातील रस्त्यांवरील चेंबर्स समपातळीत करणे, RCC चेंबर्स करणे, क्षेत्रीय कार्यालय निहाय मोबाईल मेंटेनन्स युनिटद्वारे देखभाल दुरूस्तीची कामे करणे व तद्‌नुषंगिक इतर कामे करणे. | F141: 11250000
... A145: RE20B115/R15-16 | D145: नव्याने समाविष्ठ गावांचे कार्यक्षेत्रातील रस्त्यांवरील चेंबर्स समपातळीत करणे, RCC चेंबर्स करणे, क्षेत्रीय कार्यालय निहाय मोबाईल मेंटेनन्स युनिटद्वारे देखभाल दुरूस्तीची कामे करणे व तद्‌नुषंगिक इतर कामे करणे. | F145: 11250000
D147: यादी क्र. R15 एकूण | E147: 0 | F147: 180000000
D150: यादी क्र. R12
D151: पथ विभागाकडील योजनेतर कामे (यादी R12)
...

Sheet C_Revenue_Income
A1: पाणीपुरवठा व जलोत्सारण प्रकल्पांतर्गत | G1: खास निधी 'क' चा जमेचा गोषवारा व तपशील
A2: विवरण | C2: नक्की आकडा | H2: 2021-22 वर्षाचा अंदाज | J2: 2022-23 वर्षाचा अंदाज | M2: 2021-22 वर्षाच्या मान्य अंदाजाशी तुलना केलेला 2022-23 वर्षाचा मा. महा. आयुक्त यांनी सुचविलेला अंदाज
C3: 2018-19 | D3: 2019-20 | E3: 2020-21 | F3: 2020-21 शेवटची सहामाही | G3: 2021-22 पहिली सहामाही | H3: मान्य अंदाज | I3: दुरूस्त अंदाज | J3: मा. महापालिका आयुक्त यांनी सुचविलेला | K3: मा. स्थायी समितीने मान्यता दिलेला | L3: मा. महानगर- पालिकेने संमत केलेला
M5: अधिक | N5: कमी
A7: अधिनियमाप्रमाणे कमीत कमी रोख शिल्लक ठेवण्याची रक्कम जमेस धरून वर्षारंभीची शिल्लक | C7: 100000 | D7: 100000 | E7: 100000 | F7: 100000 | G7: 0 | H7: 100000 | I7: 100000 | J7: 100000 | K7: 0 | L7: 0 | M7: 0 | N7: 0
C8: 0 | D8: 0 | E8: 0 | F8: 0 | G8: 0 | H8: 0 | I8: 0 | J8: 0 | K8: 0 | L8: 0 | M8: 0 | N8: 0
A9: १. पाणीपुरवठा (अति. न.अ.) | C9: 0 | D9: 0 | E9: 0 | F9: 0 | G9: 0 | H9: 0 | I9: 0 | J9: 0 | K9: 0 | L9: 0 | M9: 0 | N9: 0
A10: क. पाणीपट्टी साधारण पाणीपट्टी (कआकसंप्र) | B10: XI12A101 | C10: 1337732647 | D10: 1606183124 | E10: 2058845761 | F10: 730437040 | G10: 1465395040 | H10: 2900000000 | I10: 2900000000 | J10: 2940000000 | K10: 0 | L10: 0 | M10: 40000000 | N10: 0
A11: ख. शासनाकडून (कआकसंप्र) | B11: XI12B101 | C11: 0 | D11: 0 | E11: 0 | F11: 0 | G11: 0 | H11: 100000 | I11: 100000 | J11: 100000 | K11: 0 | L11: 0 | M11: 0 | N11: 0
A12: च. PMPML कडील मिळकतीवरील पाणीपट्टी (कआकसंप्र) | B12: XI12F101 | C12: 0 | D12: 0 | E12: 0 | F12: 0 | G12: 0 | H12: 100000 | I12: 100000 | J12: 100000 | K12: 0 | L12: 0 | M12: 0 | N12: 0
A13: छ. जललाभ कर (Water Benefit Tax) (कआकसंप्र) | B13: XI12G101 | C13: 558386876 | D13: 579046635 | E13: 758285451 | F13: 357832166 | G13: 531045484 | H13: 1180000000 | I13: 1180000000 | J13: 965000000 | K13: 0 | L13: 0 | M13: 0 | N13: 215000000
A14: ग. पाणीपट्टी पाणीमापकानुसार (अति.न.अ.) | B14: XI12C101 | C14: 884181735 | D14: 529584384 | E14: 753359388 | F14: 535403342 | G14: 327782319 | H14: 1650000000 | I14: 1650000000 | J14: 1690000000 | K14: 0 | L14: 0 | M14: 40000000 | N14: 0
A15: ग१. मीटर पाणीपट्टी थकबाकीपोटी जमा | B15: XI12C101A | C15: 0 | D15: 0 | E15: 0 | F15: 0 | G15: 0 | H15: 1750000000 | I15: 1750000000 | J15: 70000000 | K15: 0 | L15: 0 | M15: 0 | N15: 1680000000
A16: ग२. गवनि खात्याअंतर्गत होणारी पाणीपट्टी जमा | B16: XI12C101B | C16: 14631177 | D16: 9411692 | E16: 0 | F16: 0 | G16: 0 | H16: 25000000 | I16: 25000000 | J16: 35000000 | K16: 0 | L16: 0 | M16: 10000000 | N16: 0
A17: अनधिकृत कनेक्शन नियमित करण्यापोटी जमा | B17: XI12S101 | C17: 0 | D17: 3087 | E17: 6900 | F17: 6900 | G17: 622000 | H17: 5000000 | I17: 5000000 | J17: 5000000 | K17: 0 | L17: 0 | M17: 0 | N17: 0
A18: घ. पाणीमापक भाडे | B18: XI12D101 | C18: 2741759 | D18: 0 | E18: 0 | F18: 0 | G18: 0 | H18: 2500000 | I18: 2500000 | J18: 2500000 | K18: 0 | L18: 0 | M18: 0 | N18: 0
A19: ड. नवीन नळ आकार नळदुरुस्ती व साफसफी (परतजमा) | B19: XI12E101 | C19: 6506111 | D19: 4606709 | E19: 16279484 | F19: 14505617 | G19: 28837561 | H19: 2500000 | I19: 2500000 | J19: 5000000 | K19: 0 | L19: 0 | M19: 2500000 | N19: 0
A20: ठ. कॉलनी रस्त्यावर पाईप टाकणे कामापोटी सुपरव्हिजन स्क्रुटीनी फी व अन्य जमा होणार | B20: XI12K101 | C20: 17461303 | D20: 710997 | E20: 0 | F20: 0 | G20: 23400 | H20: 30000000 | I20: 30000000 | J20: 32500000 | K20: 0 | L20: 0 | M20: 2500000 | N20: 0
A21: ढ. जलकेंद्राच्या आवारांतील निवास स्थानापोटी जमा होणारे भाडे | B21: XI12L101 | C21: 0 | D21: 0 | E21: 0 | F21: 0 | G21: 0 | H21: 1500000 | I21: 1500000 | J21: 2000000 | K21: 0 | L21: 0 | M21: 500000 | N21: 0
... A28: ण. अंदाजपत्रक 'अ' कडून वर्ग | B28: XI12M101 | C28: 1955095785 | D28: -574449956 | E28: 394235273 | F28: 394235273 | G28: 0 | H28: -1025900000 | I28: -1025900000 | J28: 3972040000 | K28: 0 | L28: 0 | M28: 4997940000 | N28: 0
C29: 0 | D29: 0 | E29: 0 | F29: 0 | G29: 0 | H29: 0 | I29: 0 | J29: 0 | K29: 0 | L29: 0 | M29: 0 | N29: 0
A30: १. बेरीज | C30: 4860707869 | D30: 2227088474 | E30: 4037494219 | F30: 2073687046 | G30: 2371937089 | H30: 6693000000 | I30: 6693000000 | J30: 9901740000 | K30: 0 | L30: 0 | M30: 3208740000 | N30: 0
C31: 0 | D31: 0 | E31: 0 | F31: 0 | G31: 0 | H31: 0 | I31: 0 | J31: 0 | K31: 0 | L31: 0 | M31: 0 | N31: 0
A32: १अ. पुणे कॅन्टोन्मेंट पाणीपुरवठा जमा (अति.न.अ.) | C32: 0 | D32: 0 | E32: 0 | F32: 0 | G32: 0 | H32: 0 | I32: 0 | J32: 0 | K32: 0 | L32: 0 | M32: 0 | N32: 0
A33: (१) पाणीमापकानुसार पाणीपट्टी | B33: XI12Q101 | C33: 164167267 | D33: 280745047 | E33: 132107578 | F33: 100938618 | G33: 110455073 | H33: 210000000 | I33: 210000000 | J33: 230000000 | K33: 0 | L33: 0 | M33: 20000000 | N33: 0
A34: (२) H.E. Factory कडून येणारी जमा | B34: XI12Q102 | C34: 50889083 | D34: 75708335 | E34: 65743017 | F34: 19697770 | G34: 29136474 | H34: 85000000 | I34: 85000000 | J34: 95000000 | K34: 0 | L34: 0 | M34: 10000000 | N34: 0
C35: 0 | D35: 0 | E35: 0 | F35: 0 | G35: 0 | H35: 0 | I35: 0 | J35: 0 | K35: 0 | L35: 0 | M35: 0 | N35: 0
A36: १अ. बेरीज | C36: 215056350 | D36: 356453382 | E36: 197850595 | F36: 120636388 | G36: 139591547 | H36: 295000000 | I36: 295000000 | J36: 325000000 | K36: 0 | L36: 0 | M36: 30000000 | N36: 0
C37: 0 | D37: 0 | E37: 0 | F37: 0 | G37: 0 | H37: 0 | I37: 0 | J37: 0 | K37: 0 | L37: 0 | M37: 0 | N37: 0
A38: पुणे शहरात तंत्रशुध्द पध्दतीने पाणीपुरवठा (24x7 समान पाणीपुरवठा योजना) योजनेंतर्गत टाक्या बांधणेसाठी अनुदान (AMRUT) | B38: ZI12A111A | C38: 308700000 | D38: 236100000 | E38: 0 | F38: 0 | G38: 0 | H38: 235900000 | I38: 235900000 | J38: 234200000 | K38: 0 | L38: 0 | M38: 0 | N38: 1700000
A39: पुणे शहरात तंत्रशुध्द पध्दतीने पाणीपुरवठा करण्याची योजना (24x7 समान पाणीपुरवठा योजना) कर्जरोखे विक्री | B39: ZI12A112 | C39: 0 | D39: 0 | E39: 0 | F39: 0 | G39: 0 | H39: 2000000000 | I39: 2000000000 | J39: 4000000000 | K39: 0 | L39: 0 | M39: 2000000000 | N39: 0
A40: पुणे शहरात तंत्रशुध्द पध्दतीने पाणीपुरवठा (24x7 समान पाणीपुरवठा योजना) योजनेंतर्गत केलेल्या कामासाठी पुणे स्मार्ट सिटीकडून प्राप्त झालेली रक्कम | B40: ZI12A113 | C40: 0 | D40: 0 | E40: 346600000 | F40: 346600000 | G40: 0 | H40: 0 | I40: 0 | J40: 0 | K40: 0 | L40: 0 | M40: 0 | N40: 0
C41: 0 | D41: 0 | E41: 0 | F41: 0 | G41: 0 | H41: 0 | I41: 0 | J41: 0 | K41: 0 | L41: 0 | M41: 0 | N41: 0
A42: राष्ट्रीय नदीसुधारणा प्रकल्पातंर्गत (JICA) केंद्र सरकारकडून अनुदान | B42: ZI12A102 | C42: 317500000 | D42: 0 | E42: 0 | F42: 0 | G42: 0 | H42: 1258000000 | I42: 1258000000 | J42: 2500000000 | K42: 0 | L42: 0 | M42: 1242000000 | N42: 0
C43: 0 | D43: 0 | E43: 0 | F43: 0 | G43: 0 | H43: 0 | I43: 0 | J43: 0 | K43: 0 | L43: 0 | M43: 0 | N43: 0
A44: १. एकूण बेरीज | C44: 5701964219 | D44: 2819641856 | E44: 4581944814 | F44: 2540923434 | G44: 2511528636 | H44: 10481900000 | I44: 10481900000 | J44: 16960940000 | K44: 0 | L44: 0 | M44: 6479040000 | N44: 0
C45: 0 | D45: 0 | E45: 0 | F45: 0 | G45: 0 | H45: 0 | I45: 0 | J45: 0 | K45: 0 | L45: 0 | M45: 0 | N45: 0
A46: २. गटारे व नाले सुधारणा (अति.न.अ.) | C46: 0 | D46: 0 | E46: 0 | F46: 0 | G46: 0 | H46: 0 | I46: 0 | J46: 0 | K46: 0 | L46: 0 | M46: 0 | N46: 0
A47: क. सफाईपट्टी (कआकसंप्र) | B47: XI23A101 | C47: 2085529792 | D47: 2141634540 | E47: 2774526408 | F47: 1317045028 | G47: 1862246673 | H47: 4350000000 | I47: 4350000000 | J47: 4020000000 | K47: 0 | L47: 0 | M47: 0 | N47: 330000000
A48: घ. सुअरेज बेनिफीट टॅक्स (कआकसंप्र) | B48: XI23D101 | C48: 961744905 | D48: 999407213 | E48: 1310741121 | F48: 621012485 | G48: 888524732 | H48: 2260000000 | I48: 2260000000 | J48: 1220000000 | K48: 0 | L48: 0 | M48: 0 | N48: 1040000000
A49: ग. ड्रेनेज / सलेज कनेक्शन व सेवावाढ आकार नियोजित बांधकाम क्षेत्रफळावर रु. ११ चौ. मि. | B49: XI23C101 | C49: 9453661 | D49: 5410009 | E49: 2638068 | F49: 1819483 | G49: 1451275 | H49: 0 | I49: 0 | J49: 0 | K49: 0 | L49: 0 | M49: 0 | N49: 0
C50: 0 | D50: 0 | E50: 0 | F50: 0 | G50: 0 | H50: 0 | I50: 0 | J50: 0 | K50: 0 | L50: 0 | M50: 0 | N50: 0
A51: २. बेरीज | C51: 3056728358 | D51: 3146451762 | E51: 4087905597 | F51: 1939876996 | G51: 2752222680 | H51: 6610000000 | I51: 6610000000 | J51: 5240000000 | K51: 0 | L51: 0 | M51: 0 | N51: 1370000000
C52: 0 | D52: 0 | E52: 0 | F52: 0 | G52: 0 | H52: 0 | I52: 0 | J52: 0 | K52: 0 | L52: 0 | M52: 0 | N52: 0
A53: 3. डेव्हलपमेंट निधीकडून जमा Development Charges (बांधकाम नियोजन) | B53: XI23F101 | C53: 1022164378 | D53: 1264181557 | E53: 824193001 | F53: 824193001 | G53: 0 | H53: 1025000000 | I53: 1025000000 | J53: 1211000000 | K53: 0 | L53: 0 | M53: 186000000 | N53: 0
C54: 0 | D54: 0 | E54: 0 | F54: 0 | G54: 0 | H54: 0 | I54: 0 | J54: 0 | K54: 0 | L54: 0 | M54: 0 | N54: 0
A55: १. + २. + ३. एकूण बेरीज | C55: 9780856955 | D55: 7230275175 | E55: 9494043412 | F55: 5304993431 | G55: 5263751316 | H55: 18116900000 | I55: 18116900000 | J55: 23411940000 | K55: 0 | L55: 0 | M55: 5295040000 | N55: 0
C56: 0 | D56: 0 | E56: 0 | F56: 0 | G56: 0 | H56: 0 | I56: 0 | J56: 0 | K56: 0 | L56: 0 | M56: 0 | N56: 0
A57: वर्षारंभीच्या शिलकेसह एकूण जमा | C57: 9780956955 | D57: 7230375175 | E57: 9494143412 | F57: 5305093431 | G57: 5263751316 | H57: 18117000000 | I57: 18117000000 | J57: 23412040000 | K57: 0 | L57: 0 | M57: 5295040000 | N57: 0
C58: 0 | D58: 0 | E58: 0 | F58: 0 | G58: 0 | H58: 0 | I58: 0 | J58: 0 | K58: 0 | L58: 0 | M58: 0 | N58: 0
C59: 0 | D59: 0 | E59: 0 | F59: 0 | G59: 0 | H59: 0 | I59: 0 | J59: 0 | K59: 0 | L59: 0 | M59: 0 | N59: 0
A60: वजा : अंदाजपत्रक 'अ' कडून वर्ग | C60: 1955095785 | D60: -574449956 | E60: 394235273 | F60: 394235273 | G60: 0 | H60: -1025900000 | I60: -1025900000 | J60: 3972040000 | K60: 0 | L60: 0 | M60: 4997940000 | N60: 0
C61: 0 | D61: 0 | E61: 0 | F61: 0 | G61: 0 | H61: 0 | I61: 0 | J61: 0 | K61: 0 | L61: 0 | M61: 0 | N61: 0
A62: अंदाजपत्रक 'क' एकूण जमा | C62: 7825861170 | D62: 7804825131 | E62: 9099908139 | F62: 4910858158 | G62: 5263751316 | H62: 19142900000 | I62: 19142900000 | J62: 19440000000 | K62: 0 | L62: 0 | M62: 297100000 | N62: 0

Sheet C_Revenue_Expenditure
A1: योजनेतर खर्च तपशील
A2: विवरण | D2: नक्‍की आकडा | G2: मान्य अंदाज 2021-22 | H2: नवीन अंदाज 2022-23
D3: 2018-19 | E3: 2019-20 | F3: 2020-21
A5: १. पाणीपुरवठा | D5: 0 | E5: 0 | F5: 0 | G5: 0 | H5: 0
A6: क. पाणीपुरवठा | D6: 0 | E6: 0 | F6: 0 | G6: 0 | H6: 0
A7: १. मध्यवर्ती कार्यालय, कायम सेवकवर्ग वेतन | B7: XE12A101A | D7: 21639240 | E7: 22930820 | F7: 22379238 | G7: 27500000 | H7: 33990000
A8: २अ. कायम सेवकवर्ग वेतन | B8: XE12A101B | D8: 133028605 | E8: 143995350 | F8: 135107365 | G8: 160000000 | H8: 189160000
A9: २ब. कायम सेवकवर्ग वेतन (वि.का.) | B9: XE12A###A | D9: 8092170 | E9: 4911867 | F9: 6390031 | G9: 7000000 | H9: 7000000
A10: ३. संकीर्ण | B10: XE12A103 | D10: 446243 | E10: 241045 | F10: 345090 | G10: 600000 | H10: 700000
A11: ४. पाण्याची किंमत (पर्वती पंपिंग स्टेशन) | B11: XE12A104 | D11: 793046040 | E11: 714875404 | F11: 478919198 | G11: 790000000 | H11: 808500000
A12: ५. पाणी शुद्ध करणे व तद्‌नुषंगिक कामे करणे | B12: XE12A105 | D12: 50205650 | E12: 67013632 | F12: 58328083 | G12: 67500000 | H12: 85200000
A13: ६. प्रयोगशाळा देखभाल खर्च | B13: XE12A106 | D13: 0 | E13: 881357 | F13: 811793 | G13: 1500000 | H13: 1500000
A14: ७-अ. पंपिंग वीज खर्च | B14: XE12A107 | D14: 693640000 | E14: 778342594 | F14: 806361533 | G14: 801200000 | H14: 800000000
A15: ९. कोठी इतर साहित्य खर्च | B15: XE12A109 | D15: 340813 | E15: 697066 | F15: 460849 | G15: 1500000 | H15: 1000000
A16: १२. पर्वती जलकेंद्रातील यंत्रसामुग्रीवरील घसारा (मु.ले.) | B16: XE12A112 | D16: 215000 | E16: 0 | F16: 0 | G16: 0 | H16: 0
A17: १४. जलप्रदूषण प्रतिबंधक खर्च | B17: XE12A115 | D17: 0 | E17: 0 | F17: 734191 | G17: 2500000 | H17: 2500000
A18: १८. जलकेंद्र पाण्याच्या टाक्या येथे प्रकाश व्यवस्था व दूरध्वनी व्यवस्था | B18: XE12A120 | D18: 0 | E18: 0 | F18: 0 | G18: 500000 | H18: 500000
... A38: पर्वती जलकेंद्र प्रयोगशाळा येथे पाणी तपासणीसाठी लागणारी विविध उपकरणे व तद्‌नुषंगिक साहित्य खरेदी करणे | B38: XE12A146 | D38: 0 | E38: 328798 | F38: 0 | G38: 0 | H38: 0
A39: क. बेरीज | D39: 1799104371 | E39: 1835097980 | F39: 1625140673 | G39: 1994500000 | H39: 2051750000
D40: 0 | E40: 0 | F40: 0 | G40: 0 | H40: 0
A41: ख१. नळ खाते (स्वारगेट विभाग) | D41: 0 | E41: 0 | F41: 0 | G41: 0 | H41: 0
A42: १. कायम सेवक वर्ग वेतन | B42: XE12B101A | D42: 221769160 | E42: 228669863 | F42: 226930999 | G42: 270000000 | H42: 314807000
A43: २. संकीर्ण | B43: XE12B102 | D43: 463550 | E43: 323698 | F43: 353403 | G43: 300000 | H43: 300000
A44: ४. शहरांतील / नव्याने समाविष्ट गावांतील सर्व व्हॉल्व्हज्‌ चालू व बंद करणे | B44: XE12B107 | D44: 39585979 | E44: 61215355 | F44: 95825633 | G44: 60000000 | H44: 70000000
A45: ८. टँकरने पाणीपुरवठा करणे | B45: XE12B111 | D45: 14825987 | E45: 26968695 | F45: 26948995 | G45: 22000000 | H45: 22000000
A46: ९. कोठी व इतर साहित्य खरेदी | B46: XE12B112 | D46: 17886533 | E46: 19658619 | F46: 12586142 | G46: 20000000 | H46: 20000000
A47: १०. देखभाल दुरुस्ती : नळदुरुस्ती व स्वच्छता तातडीच्या दुरुस्त्या चेंबर करणे, आर.सी.सी, कव्हर बसविणे व तदनुषंगिक कामे करणे | B47: XE12B113 | D47: 47904841 | E47: 45727778 | F47: 77831942 | G47: 52000000 | H47: 60000000
A48: पाणीपुरवठा विभागाकडील देखभाल दुरूस्तीची कामे (यादी X1) | B48: XE12B115# | D48: 2634964 | E48: 0 | F48: 0 | G48: 36000000 | H48: 0
D49: 0 | E49: 0 | F49: 0 | G49: 0 | H49: 0
A50: ख१. बेरीज | D50: 345071014 | E50: 382564008 | F50: 440477114 | G50: 460300000 | H50: 487107000
D51: 0 | E51: 0 | F51: 0 | G51: 0 | H51: 0
A52: ख२. नळ खाते (विभागीय कार्यालय) | D52: 0 | E52: 0 | F52: 0 | G52: 0 | H52: 0
A53: १. कायम सेवकवर्ग वेतन | B53: XE12B###A | D53: 23964490 | E53: 22633204 | F53: 20941786 | G53: 27000000 | H53: 30993000
A54: क्षेत्रीय कार्यालयाने करावयाची योजनेतर कामे | B54: XE12B301/W6-# | D54: 943661 | E54: 2313036 | F54: 0 | G54: 1000000 | H54: 2000000
A55: क्षेत्रीय कार्यालयाने नागरिकांच्या सहभागातून करावयाची योजनेतर कामे | B55: XE12B302/C6-# | D55: 2817441 | E55: 4296733 | F55: 0 | G55: 4300000 | H55: 6550000
D56: 0 | E56: 0 | F56: 0 | G56: 0 | H56: 0
A57: ख२. बेरीज | D57: 27725592 | E57: 29242973 | F57: 20941786 | G57: 32300000 | H57: 39543000
D58: 0 | E58: 0 | F58: 0 | G58: 0 | H58: 0
A59: ख. एकूण बेरीज | D59: 372796606 | E59: 411806981 | F59: 461418900 | G59: 492600000 | H59: 526650000
D60: 0 | E60: 0 | F60: 0 | G60: 0 | H60: 0
A61: ग. पाणीमापके | D61: 0 | E61: 0 | F61: 0 | G61: 0 | H61: 0
A62: १. पाणीमापके दुरुस्ती | B62: XE12C101 | D62: 0 | E62: 0 | F62: 0 | G62: 250000 | H62: 280000
A63: ३. संगणक यंत्रासाठी तयार करावयाच्या फॉर्मचा मुशाहिरा | B63: XE12C103 | D63: 0 | E63: 0 | F63: 0 | G63: 400000 | H63: 400000
A64: ४. मीटर बीले वाटप करणे | B64: XE12C104 | D64: 0 | E64: 0 | F64: 0 | G64: 350000 | H64: 420000
D65: 0 | E65: 0 | F65: 0 | G65: 0 | H65: 0
A66: ग. बेरीज | D66: 0 | E66: 0 | F66: 0 | G66: 1000000 | H66: 1100000
D67: 0 | E67: 0 | F67: 0 | G67: 0 | H67: 0
A68: च. मनपा सेवकांना द्यावयाचा महागाईभत्ता | B68: XE12F101 | D68: 1822664 | E68: 0 | F68: 0 | G68: 20000000 | H68: 20000000
A69: 7व्या वेतनआयोगापोटी द्यावयाच्या फरकाची रक्कम | B69: XE12G101 | D69: 0 | E69: 0 | F69: 0 | G69: 100000000 | H69: 100000000
A70: ज. सानुग्रह अनुदान | B70: XE12H101 | D70: 39452188 | E70: 4326522 | F70: 5098645 | G70: 90000000 | H70: 50000000
A71: झ. मनपा सेवकांना प्रवासभत्ता सवलतीसाठी द्यावयाची रक्कम | B71: XE12I101 | D71: 317000 | E71: 422500 | F71: 368500 | G71: 20000000 | H71: 20000000
A72: थ. सेवानिवृत्ती वेतन व तोषदान | B72: XE12K101 | D72: 184000000 | E72: 200000000 | F72: 300000000 | G72: 400000000 | H72: 400000000
A73: प. पेट्रोल, डिझेल, टायर्स, सुटे भाग, देखभाल, दुरुस्ती | B73: XE12M101 | D73: 4593077 | E73: 3914914 | F73: 8305994 | G73: 4000000 | H73: 5000000
A74: ज्ञ१. कर्ज उभारण्याचा खर्च, कर्जाचे हप्ते व व्याज (मु.ले.) | B74: XE12Z101 | D74: 152047800 | E74: 152047800 | F74: 152047800 | G74: 731800000 | H74: 1111800000
D75: 0 | E75: 0 | F75: 0 | G75: 0 | H75: 0
A76: १. पाणीपुरवठा एकूण बेरीज | D76: 2554133706 | E76: 2607616697 | F76: 2552380512 | G76: 3853900000 | H76: 4286300000
D77: 0 | E77: 0 | F77: 0 | G77: 0 | H77: 0
A78: १अ. पुणे लष्कर व खडकी पाणीपुरवठा | D78: 0 | E78: 0 | F78: 0 | G78: 0 | H78: 0
A79: क१. लष्कर पाणीपुरवठा | D79: 0 | E79: 0 | F79: 0 | G79: 0 | H79: 0
A80: १. कायम सेवकवर्ग वेतन | B80: XE12N101A | D80: 164571931 | E80: 167040544 | F80: 179552896 | G80: 203000000 | H80: 237900000
A81: २. संकीर्ण | B81: XE12N102 | D81: 339066 | E81: 437157 | F81: 769422 | G81: 600000 | H81: 600000
A82: ३. पाण्याची किंमत | B82: XE12N103 | D82: 500000000 | E82: 100000000 | F82: 58500000 | G82: 63500000 | H82: 73000000
A83: ४. पाणी शुद्ध करणे, तद्‌नुषंगिक कामे करणे | B83: XE12N104 | D83: 9199955 | E83: 8461451 | F83: 10576102 | G83: 11000000 | H83: 12100000
A84: ५. प्रयोगशाळा सँपल टेस्टींगसाठी होणारा खर्च | B84: XE12N105 | D84: 0 | E84: 0 | F84: 0 | G84: 700000 | H84: 700000
A85: ६. पंपिंग वीज खर्च | B85: XE12N106 | D85: 250891228 | E85: 199528930 | F85: 220155328 | G85: 230000000 | H85: 245500000
A86: ८. कोठी व इतर साहित्य खर्च | B86: XE12N108 | D86: 452573 | E86: 615580 | F86: 0 | G86: 0 | H86: 0
A87: ९. पंपाचे डिझेल इंजिनसाठी व इतर इंजिनसाठी लागणारे तेल | B87: XE12N109 | D87: 0 | E87: 0 | F87: 331801 | G87: 500000 | H87: 500000
A88: १३. पाणीपुरवठा केंद्र भवनाची देखभाल व दुरुस्ती | B88: XE12N117 | D88: 0 | E88: 400000 | F88: 1799966 | G88: 2000000 | H88: 2200000
A89: १६. पुणे लष्कर पाणीपुरवठा हद्दीतील व्हॉल्व्ह चालू करणे व बंद करणे | B89: XE12N120 | D89: 27371424 | E89: 31291384 | F89: 46161444 | G89: 40000000 | H89: 50000000
A90: १७. टँकरने पाणीपुरवठा करणे | B90: XE12N121 | D90: 23044690 | E90: 25299474 | F90: 27053449 | G90: 30000000 | H90: 35000000
A91: १९. देखभाल दुरुस्ती (यंत्रसामुग्री सुटे भाग, ट्रान्सफॉर्मर ऑईल, सर्किट ब्रेकर्स, विुत उपकरणांची देखभाल दुरूस्ती, बागकाम, भवनांची देखभाल दुरूस्ती, दिवाबत्ती, नळदुरूस्त्या व इतर दुरूस्त्या) | B91: XE12N123 | D91: 21084056 | E91: 27888464 | F91: 41175497 | G91: 30000000 | H91: 35000000
... A96: पुणे मनपा लष्कर जलकेंद्र ते कोंढवा बकरी हिल टाकी पर्यंत नवजलनालिका टाकण्यासाठी संरक्षक विभाग पुणे लष्कर बोर्डाची लायसेन्स फी व अनामत भरणे | B96: XE12N128 | D96: 0 | E96: 11669156 | F96: 0 | G96: 0 | H96: 0
D97: 0 | E97: 0 | F97: 0 | G97: 0 | H97: 0
A98: क१. लष्कर पाणीपुरवठा बेरीज | D98: 1015240125 | E98: 595180181 | F98: 606933193 | G98: 634950000 | H98: 717000000
D99: 0 | E99: 0 | F99: 0 | G99: 0 | H99: 0
A100: क२. लष्कर पाणीपुरवठा (विभागीय कार्यालय) | D100: 0 | E100: 0 | F100: 0 | G100: 0 | H100: 0
A101: १. कायम सेवक वर्ग वेतन | B101: XE12N###A | D101: 5709141 | E101: 5324501 | F101: 4702696 | G101: 6500000 | H101: 6812000
D102: 0 | E102: 0 | F102: 0 | G102: 0 | H102: 0
A103: क२. बेरीज | D103: 5709141 | E103: 5324501 | F103: 4702696 | G103: 6500000 | H103: 6812000
D104: 0 | E104: 0 | F104: 0 | G104: 0 | H104: 0
A105: क. एकूण बेरीज | D105: 1020949266 | E105: 600504682 | F105: 611635889 | G105: 641450000 | H105: 723812000
D106: 0 | E106: 0 | F106: 0 | G106: 0 | H106: 0
A107: ख१. खडकी व SNDT चतुःश्रृंगी पाणीपुरवठा | D107: 0 | E107: 0 | F107: 0 | G107: 0 | H107: 0
A108: १. कायम सेवकवर्ग वेतन | B108: XE12P101A | D108: 16102534 | E108: 20391226 | F108: 17807045 | G108: 23500000 | H108: 22038000
A109: २. संकीर्ण | B109: XE12P102 | D109: 25737 | E109: 40175 | F109: 83542 | G109: 300000 | H109: 300000
A110: ३. पाण्याची किंमत | B110: XE12P103 | D110: 18145010 | E110: 0 | F110: 0 | G110: 33000000 | H110: 37900000
A111: ४. पाणी शुद्ध करणे व तद्‌नुषंगिक कामे करणे | B111: XE12P104 | D111: 588800 | E111: 2080000 | F111: 2169240 | G111: 3000000 | H111: 3300000
A112: ६. पंपिंग वीज खर्च | B112: XE12P106 | D112: 13798530 | E112: 16990087 | F112: 17549640 | G112: 20000000 | H112: 20000000
A113: १०. कोठी व इतर साहित्य खर्च | B113: XE12P110 | D113: 1523759 | E113: 1214404 | F113: 600210 | G113: 0 | H113: 0
A114: १७. टाक्‍यांची दुरुस्ती | B114: XE12P119 | D114: 897502 | E114: 0 | F114: 0 | G114: 1000000 | H114: 1000000
A115: १८. देखभाल दुरुस्त्या : नळदुरुस्ती व तातडीच्या दुरुस्त्या इत्यादी | B115: XE12P120 | D115: 38291485 | E115: 32071152 | F115: 45286103 | G115: 49000000 | H115: 44800000
A116: १९. व्हॉल्व्ह सोड बंद करणे | B116: XE12P121 | D116: 15013778 | E116: 25083299 | F116: 24131515 | G116: 20000000 | H116: 30000000
A117: २०. टँकरने पाणीपुरवठा करणे | B117: XE12P122 | D117: 20543132 | E117: 25359127 | F117: 43269063 | G117: 21500000 | H117: 30000000
D118: 0 | E118: 0 | F118: 0 | G118: 0 | H118: 0
A119: ख. एकूण बेरीज | D119: 124930267 | E119: 123229470 | F119: 150896358 | G119: 171300000 | H119: 189338000
D120: 0 | E120: 0 | F120: 0 | G120: 0 | H120: 0
A121: 7व्या वेतनआयोगापोटी द्यावयाच्या फरकाची रक्कम | B121: XE12P118C | D121: 0 | E121: 0 | F121: 0 | G121: 100000000 | H121: 100000000
A122: ज सानुग्रह अनुदान | B122: XE12P118D | D122: 12052729 | E122: 48704528 | F122: 50730167 | G122: 90000000 | H122: 50000000
A123: च मनपा सेवकांना द्यावयाचा महागाई भत्ता | B123: XE12P118E | D123: 1146221 | E123: 4020692 | F123: 0 | G123: 10000000 | H123: 10000000
A124: झ मनपा सेवकांना प्रवासभत्ता सवलतीसाठी द्यावयाची रक्कम | B124: XE12P118F | D124: 274500 | E124: 216000 | F124: 148000 | G124: 10000000 | H124: 10000000
...

Sheet C_Capital_Expenditure
A1: सन 2022-23 चे योजनांतर्गत | H1: खर्चाबाबतचे अंदाजपत्रक
A2: मान्यतेचा ठराव क्र. दिनांक (कोड) | B2: प्रभाग क्रमांक | C2: BPL | D2: कामाचे नाव अगर वर्णन | E2: दि. 31 मार्च 2022 अखेरपर्यंत केलेली तरतूद | H2: दि. 31 मार्च 2021 पर्यंतचा खर्चाचा नक्‍की आकडा | I2: 2021-22 मधील खर्चाची अंदाजी रक्कम | K2: 2022-23 साठी अधिक तरतूद | M2: 2022-23 साठी एकूण तरतूद | N2: प्रकल्पीय रक्कम
E3: कर्जातून | F3: महसूल निधीतून | G3: एकूण | I3: प्रत्यक्ष उपलब्ध तरतूद | J3: कर्जातून तरतूद | K3: कर्जातून | L3: महसूल निधी व इतर निधी
D7: 1. पाणीपुरवठा विभाग | F7: 0 | G7: 0 | H7: 0 | I7: 0 | L7: 0 | M7: 0
F8: 0 | G8: 0 | H8: 0 | I8: 0 | L8: 0 | M8: 0
A9: ZE16A103# | B9: P1- | C9: _ | D9: शहरामध्ये पाण्याच्या टाक्या बांधणे / बोअरवेल घेणे / जलशुध्दीकरण केंद्रे बांधणे आणि विद्युत / स्थापत्य / यांत्रिकीविषयक कामे करणे | F9: 557991260 | G9: 557991260 | H9: 98616001 | I9: 459375259 | L9: 384600000 | M9: 384600000
A10: ZE16A104# | B10: P2- | C10: _ | D10: शहरामध्ये पाण्याच्या लाईन टाकणे | F10: 7252192595 | G10: 7252192595 | H10: 6502125477 | I10: 750067118 | L10: 198400000 | M10: 198400000
A11: ZE16A106# | B11: _ | C11: _ | D11: शहरामध्ये पाण्याच्या टाक्या बांधणे / बोअरवेल घेणे | F11: 346015472 | G11: 346015472 | H11: 346015469 | I11: 3 | L11: 0 | M11: 0
A12: ZE16A107# | B12: _ | C12: _ | D12: शहरामध्ये जलशुध्दीकरण केंद्रे बांधणे आणि विद्युत विषयक, स्थापत्य विषयक, यांत्रिकीविषयक कामे करणे | F12: 670330361 | G12: 670330361 | H12: 598580359 | I12: 71750002 | L12: 0 | M12: 0
F13: 0 | G13: 0 | H13: 0 | I13: 0 | L13: 0 | M13: 0
D14: 1. पाणीपुरवठा विभाग एकूण बेरीज | F14: 8826529688 | G14: 8826529688 | H14: 7545337306 | I14: 1281192382 | L14: 583000000 | M14: 583000000
F15: 0 | G15: 0 | H15: 0 | I15: 0 | L15: 0 | M15: 0
F16: 0 | G16: 0 | H16: 0 | I16: 0 | L16: 0 | M16: 0
D17: 2. मलनिःसारण विभाग | F17: 0 | G17: 0 | H17: 0 | I17: 0 | L17: 0 | M17: 0
F18: 0 | G18: 0 | H18: 0 | I18: 0 | L18: 0 | M18: 0
A19: ZE16B102# | B19: D2- | C19: _ | D19: शहरामध्ये मलवाहिन्या विकसित करणे | F19: 11908710881 | G19: 11908710881 | H19: 8140284953 | I19: 3768425928 | L19: 3553600000 | M19: 3553600000
A20: ZE16B103# | B20: D3- | C20: _ | D20: शहरामध्ये नाला चॅनलायझेशन करणे / नाल्याला सिमाभिंत बांधणे व तदनुषंगिक कामे करणे | F20: 947709603 | G20: 947709603 | H20: 439631714 | I20: 508077889 | L20: 37000000 | M20: 37000000
A21: ZE16B105# | B21: D5- | C21: _ | D21: शहरामध्ये मैलापाणी शुध्दीकरण केंद्रे बांधणे आणि विद्युत / स्थापत्य / यांत्रिकीविषयक कामे करणे | F21: 333115622 | G21: 333115622 | H21: 267922800 | I21: 65192822 | L21: 16200000 | M21: 16200000
F22: 0 | G22: 0 | H22: 0 | I22: 0 | L22: 0 | M22: 0
D23: 2. मलनिःसारण विभाग एकूण बेरीज | F23: 13189536106 | G23: 13189536106 | H23: 8847839467 | I23: 4341696639 | L23: 3606800000 | M23: 3606800000
F24: 0 | G24: 0 | H24: 0 | I24: 0 | L24: 0 | M24: 0
D25: 3. पाणीपुरवठा प्रकल्प | F25: 0 | G25: 0 | H25: 0 | I25: 0 | L25: 0 | M25: 0
F26: 0 | G26: 0 | H26: 0 | I26: 0 | L26: 0 | M26: 0
A27: ZE16C101# | B27: PR1- | D27: शहरामध्ये पाणीपुरवठा प्रकल्प अंतर्गत कामे करणे | F27: 7873341271 | G27: 7873341271 | H27: 6837141228 | I27: 1036200043 | L27: 625500000 | M27: 625500000
A28: ZE16C102# | B28: _ | D28: राष्ट्रीय नदी सुधारणा योजना (JICA) | F28: 1115946204 | G28: 1115946204 | H28: 373167055 | I28: 742779149 | L28: 0 | M28: 0
A29: ZE16C103# | B29: PR3- | D29: पुणे शहरात तंत्रशुध्द पध्दतीने पाणीपुरवठा करण्याची योजना (24x7 समान पाणीपुरवठा योजना) | F29: 10293750854 | G29: 10293750854 | H29: 5420776679 | I29: 4872974175 | L29: 6000000000 | M29: 6000000000
F30: 0 | G30: 0 | H30: 0 | I30: 0 | L30: 0 | M30: 0
D31: 3. पाणीपुरवठा प्रकल्प एकूण बेरीज | F31: 19283038329 | G31: 19283038329 | H31: 12631084962 | I31: 6651953367 | L31: 6625500000 | M31: 6625500000
F32: 0 | G32: 0 | H32: 0 | I32: 0 | L32: 0 | M32: 0
D33: 4. मलनिःसारण प्रकल्प | F33: 0 | G33: 0 | H33: 0 | I33: 0 | L33: 0 | M33: 0
F34: 0 | G34: 0 | H34: 0 | I34: 0 | L34: 0 | M34: 0
A35: ZE16D102# | B35: _ | C35: _ | D35: शहरामध्ये मोठ्या व्यासाच्या मलवाहिन्या विकसित करणे | F35: 1166380684 | G35: 1166380684 | H35: 936022100 | I35: 230358584 | L35: 0 | M35: 0
A36: ZE16D103# | B36: MP3- | C36: _ | D36: शहरामध्ये मैलापाणी शुध्दीकरण केंद्र उभारणे / पंपिंग स्टेशन उभारणे | F36: 107106864 | G36: 107106864 | H36: 6106864 | I36: 101000000 | L36: 120000000 | M36: 120000000
A37: ZE16D104# | B37: MP4- | C37: _ | D37: राष्ट्रीय नदी सुधारणा योजना (JICA) | F37: 1200000000 | G37: 1200000000 | H37: 0 | I37: 1200000000 | L37: 2950000000 | M37: 2950000000
F38: 0 | G38: 0 | H38: 0 | I38: 0 | L38: 0 | M38: 0
D39: 4. मलनिःसारण प्रकल्प एकूण बेरीज | F39: 2473487548 | G39: 2473487548 | H39: 942128964 | I39: 1531358584 | L39: 3070000000 | M39: 3070000000
F40: 0 | G40: 0 | H40: 0 | I40: 0 | L40: 0 | M40: 0
D41: क्षेत्रिय कार्यालयाने करावयाची कामे | F41: 0 | G41: 0 | H41: 0 | I41: 0 | L41: 0 | M41: 0
F42: 0 | G42: 0 | H42: 0 | I42: 0 | L42: 0 | M42: 0
A43: ZE16A115# | B43: W6 | D43: क्षेत्रिय कार्यालय : पाणीपुरवठा विभागाने करावयाची कामे | F43: 111742587 | G43: 111742587 | H43: 111492587 | I43: 250000 | L43: 2750000 | M43: 2750000
A44: ZE16A117# | B44: C6 | D44: क्षेत्रिय कार्यालय : नागरिकांच्या सहभाग योजनेतून पाणीपुरवठा विभागाने करावयाची कामे | F44: 60858052 | G44: 60858052 | H44: 55858051 | I44: 5000001 | L44: 1500000 | M44: 1500000
F45: 0 | G45: 0 | H45: 0 | I45: 0 | L45: 0 | M45: 0
A46: ZE16B113# | B46: W7 | D46: क्षेत्रिय कार्यालय : मलनिःसारण विभागाने करावयाची कामे | F46: 519910697 | G46: 519910697 | H46: 446954682 | I46: 72956015 | L46: 36000000 | M46: 36000000
A47: ZE16B130# | B47: C7 | D47: क्षेत्रिय कार्यालय : नागरिकांच्या सहभाग योजनेतून मलनिःसारण विभागाने करावयाची कामे | F47: 194370286 | G47: 194370286 | H47: 171676283 | I47: 22694003 | L47: 16950000 | M47: 16950000
F48: 0 | G48: 0 | H48: 0 | I48: 0 | L48: 0 | M48: 0
D49: क्षेत्रिय कार्यालयाने करावयाची कामे एकूण बेरीज | F49: 886881622 | G49: 886881622 | H49: 785981603 | I49: 100900019 | L49: 57200000 | M49: 57200000
A51: • | B51: • | C51: • | D51: 1. पाणीपुरवठा विभाग | E51: 0 | F51: 8826529688 | G51: 8826529688 | H51: 7545337306 | I51: 1281192382 | J51: 0 | K51: 0 | L51: 583000000 | M51: 583000000
A52: • | B52: • | C52: • | D52: क्षेत्रिय कार्यालय : पाणीपुरवठा विभागाने करावयाची कामे | E52: 0 | F52: 172600639 | G52: 172600639 | H52: 167350638 | I52: 5250001 | J52: 0 | K52: 0 | L52: 4250000 | M52: 4250000
A53: ZE16A | B53: XE12X101 | D53: 1. पाणीपुरवठा विभाग एकूण बेरीज | E53: 0 | F53: 8999130327 | G53: 8999130327 | H53: 7712687944 | I53: 1286442383 | J53: 0 | K53: 0 | L53: 587250000 | M53: 587250000
A54: • | B54: • | C54: •
A55: • | B55: • | C55: • | D55: 2. मलनिःसारण विभाग | E55: 0 | F55: 13189536106 | G55: 13189536106 | H55: 8847839467 | I55: 4341696639 | J55: 0 | K55: 0 | L55: 3606800000 | M55: 3606800000
A56: • | B56: • | C56: • | D56: क्षेत्रिय कार्यालय : मलनिःसारण विभागाने करावयाची कामे | E56: 0 | F56: 714280983 | G56: 714280983 | H56: 618630965 | I56: 95650018 | J56: 0 | K56: 0 | L56: 52950000 | M56: 52950000
A57: ZE16B | B57: XE23X101 | D57: 2. मलनिःसारण विभाग एकूण बेरीज | E57: 0 | F57: 13903817089 | G57: 13903817089 | H57: 9466470432 | I57: 4437346657 | J57: 0 | K57: 0 | L57: 3659750000 | M57: 3659750000
A58: • | B58: • | C58: •
A59: ZE16C | B59: XE41X101 | D59: 3. पाणीपुरवठा प्रकल्प एकूण बेरीज | E59: 0 | F59: 19283038329 | G59: 19283038329 | H59: 12631084962 | I59: 6651953367 | J59: 0 | K59: 0 | L59: 6625500000 | M59: 6625500000
A60: ZE16D | B60: XE41X102 | D60: 4. मलनिःसारण प्रकल्प एकूण बेरीज | E60: 0 | F60: 2473487548 | G60: 2473487548 | H60: 942128964 | I60: 1531358584 | J60: 0 | K60: 0 | L60: 3070000000 | M60: 3070000000
A61: • | B61: • | C61: •
A62: ZE Total | B62: • | C62: • | D62: पाणीपुरवठा + मलनिःसारण + पाणीपुरवठा प्रकल्प + मलनिःसारण प्रकल्प : एकूण बेरीज | E62: 0 | F62: 44659473293 | G62: 44659473293 | H62: 30752372302 | I62: 13907100991 | J62: 0 | K62: 0 | L62: 13942500000 | M62: 13942500000

Sheet C_List
D1: यादी क्र. X2
D2: मलनिःस्सारण विभागाकडील देखभाल दुरूस्तीची कामे
D3: XE23A117/X2-
A5: code | B5: ward | D5: कामाचे नाव | E5: प्रकल्पीय रक्कम | F5: तरतूद
A7: XE23A117/X2-386 | D7: मलनि:सारण विभागाची मागील वर्षाची पेंडिंग बिले देणे | F7: 20000000
A8: XE23A117/X2-387 | D8: मलनि:सारण विभागाची अचानक उद्भवणारी कामे करणे | F8: 20000000
A9: XE23A117/X2-401 | D9: येरवडा कळस धानोरी क्षेञिय कार्यालयाच्‍या अखत्‍यारीतील पावसाळी गटाराची साफसफाई व तद्नुषंगिक कामे करणे | F9: 5000000
A10: XE23A117/X2-402 | D10: नगररोड वडगाव शेरी क्षेञिय कार्यालयाच्‍या अखत्‍यारीतील पावसाळी गटाराची साफसफाई व तद्नुषंगिक कामे करणे | F10: 5000000
A11: XE23A117/X2-403 | D11: ढोले पाटील क्षेञिय कार्यालयाच्‍या अखत्‍यारीतील पावसाळी गटाराची साफसफाई व तद्नुषंगिक कामे करणे | F11: 5000000
A12: XE23A117/X2-404 | D12: औंध बाणेर क्षेञिय कार्यालयाच्‍या अखत्‍यारीतील पावसाळी गटाराची साफसफाई व तद्नुषंगिक कामे करणे | F12: 5000000
A13: XE23A117/X2-405 | D13: शिवाजीनगर घोले रोड क्षेञिय कार्यालयाच्‍या अखत्‍यारीतील पावसाळी गटाराची व तद्नुषंगिक कामे करणे | F13: 5000000
A14: XE23A117/X2-406 | D14: कोथरूड बावधन क्षेञिय कार्यालयाच्‍या अखत्‍यारीतील पावसाळी गटाराची साफसफाई व तद्नुषंगिक कामे करणे | F14: 5000000
A15: XE23A117/X2-407 | D15: धनकवडी सहकारनगर क्षेञिय कार्यालयाच्‍या अखत्‍यारीतील पावसाळी गटाराची साफसफाई व तद्नुषंगिक कामे करणे | F15: 5000000
A16: XE23A117/X2-408 | D16: वारजे कर्वेनगर रोड क्षेञिय कार्यालयाच्‍या अखत्‍यारीतील पावसाळी गटाराची साफसफाई व तद्नुषंगिक कामे करणे | F16: 5000000
A17: XE23A117/X2-409 | D17: सिंहगड रोड क्षेञिय कार्यालयाच्‍या अखत्‍यारीतील पावसाळी गटाराची साफसफाई व तद्नुषंगिक कामे करणे | F17: 5000000
A18: XE23A117/X2-410 | D18: कोंढवा येवलेवाडी क्षेञिय कार्यालयाच्‍या अखत्‍यारीतील पावसाळी गटाराची साफसफाई व तद्नुषंगिक कामे करणे | F18: 5000000
... A69: XE23A117/X2-461 | D69: बिबवेवाडी क्षेञिय कार्यालयाच्‍या अखत्‍यारितील ओढ्या नाल्‍यातील मलवाहिन्‍यांची देखभाल व दुरुस्‍तीची कामे करणे. | F69: 6500000
D71: यादी क्र. X2 एकूण | E71: 0 | F71: 425000000
A73: पाणीपुरवठा विभागाकडील कामाच्या याद्या
D75: यादी क्र. P1
D76: शहरामध्ये पाण्याच्या टाक्या बांधणे / बोअरवेल घेणे / जलशुध्दीकरण केंद्रे बांधणे आणि विद्युत / स्थापत्य / यांत्रिकीविषयक कामे करणे
D77: ZE16A103/P1-
A79: code | B79: ward | D79: कामाचे नाव | E79: प्रकल्पीय रक्कम | F79: तरतूद
A81: ZE16A103/P1-81 | D81: राष्ट्रीय पेयजेल कार्यक्रमाअंतर्गत महाराष्ट्र जीवन प्राधिकरणामार्फत फुरसुंगी व उरुळी देवाची येथे सुरु असलेल्या योजनेसाठी उर्वरित रक्कम देणे | F81: 62500000
A82: ZE16A103/P1-82 | D82: गांधीभवन येथे २ एम एल डी पाण्याची टाकी बांधणे | F82: 20000000
A83: ZE16A103/P1-83 | D83: लष्कर जलशुद्धीकरण केंद्राची नव्याने उभारणी करणे | F83: 20000000
A84: ZE16A103/P1-84 | D84: पर्वती येथे रॉ वॉटर पंपिंग स्टेशन उभारणे | F84: 7500000
A85: ZE16A103/P1-85 | D85: पाण्याच्या साठवण टाक्यांना आतील बाजूनी क्लोरीन प्रतिबंधक कोटिंग करणे | F85: 50000000
A86: ZE16A103/P1-86 | D86: पर्वती जलकेंद्र अंतर्गत रॉ वाटर पंपींग स्टेशन मधील जुने 3.3 केव्ही क्षमतेचे व्हीसीबी पॅनल काढून त्या जागी नवीन पॅनल बसविणे व तदनुषंगीक कामे करणे | F86: 3500000
A87: ZE16A103/P1-87 | D87: पर्वती जलकेंद्र अंतर्गत नवीन बुस्टर पंपींग यंत्रणेसाठी 10 ठिकाणी फ्लोमीटर पुरविणे व बसविणे. | F87: 2500000
A88: ZE16A103/P1-88 | D88: खोराड वस्ती येथील बुस्टर पंपींग यंत्रणा सुधारणा करणे. | F88: 2500000
A89: ZE16A103/P1-89 | D89: साईनगर येथील बुस्टर पंपींग यंत्रणा स्थलांतरीत करणे | F89: 3000000
A90: ZE16A103/P1-90 | D90: पर्वती जलकेंद्र येथील टप्पा क्र - २ फिल्टर बेंड रिग्रेडशन करणे. | F90: 5000000
A91: ZE16A103/P1-91 | D91: पर्वती जलकेंद्रामधील फिल्टरबेड मधील पाण्याची गळती थांबविणे. | F91: 2000000
A92: ZE16A103/P1-92 | D92: पर्वती जलकेंद्र मधील स्टिलिंग चेंबरची देखभाल दुरूस्ती करणे. | F92: 1000000
... A124: ZE16A103/P1-124 | D124: लष्कर जलकेंद्र अंतर्गत येणार्‍या चिखली व फुरसुंगी जलकेंद्राच्या प्रयोगशाळेसाठी विविध साहित्य पुरविणे. | F124: 2500000
D126: सन 2021-22 मधील अपूर्ण कामांसाठी सन 2022-23 मध्ये उपलब्ध केलेली तरतूद
A127: ZE16A103/P1-9 | D127: पर्वती जलकेंद्र येथे पंप हाऊस क्र.१,२ व ३ साठी ए.पी.एफ.सी. युनिट पुरविणे व बसविणे. | F127: 2000000
A128: ZE16A103/P1-12 | D128: पर्वती जलकेंद्र येथील सेकंड स्टेजकडील बेड वॉशिंगकरीता ७.५ एच.पी. क्षमतेचा कॉम्प्रेसर पुरविणे व बसविणे | F128: 1000000
A129: ZE16A103/P1-13 | D129: पर्वती जलकेंद्र येथील सेंकंड स्टेजकडील क्लॅरिफायर क्र.३ चे क्लॅरिफॉक्युलेटर, गिअर असेंब्ली पुरविणे व बसविणे | F129: 1500000
A130: ZE16A103/P1-32 | D130: पद्‌मावती पपिंग स्टेशन येथील सेमिनरी पंपासाठी नविन क्रेन पुरविणे, बसविणे. | F130: 800000
A131: ZE16A103/P1-33 | D131: पर्वती जलकेंद्रांतर्गत रॉ वॉटर पंपिंग स्टेशन येथे संपवेलच्या ओव्हरफलो ड्रेनसाठी तद्‌नुषंगिक कामे करणे. | F131: 2500000
A132: ZE16A103/P1-48 | D132: पाषाण पंपींग येथील एचटी सप्लाय आउट डोअर स्विचयार्ड इनडोअर करणे व तदनुषंगीक कामे करणे. | F132: 2500000
A133: ZE16A103/P1-47 | D133: एसएनडीटी पंपींग येथे व्हॉल्व्ह नवीन बसविणे | F133: 800000
A134: ZE16A103/P1-101 | D134: नव्याने समाविष्ठ 11 गावांमध्ये पाणीपुरवठा विषयक व इतर विकास कामे करणे | F134: 35000000
A135: ZE16A103/P1-102 | D135: कोथरूड बावधन क्षेत्रीय कार्यालय अंतर्गत दुषित पाण्याच्या तक्रारीची निवारण करणे झोपडपट्टी, गुंठेवारी व इतर भागांनमध्ये पाण्याच्या लाईन बदलणे, कुपनलीका देखभाल दुरुस्तीची व इतर कामे करणे | F135: 2000000
A136: ZE16A103/P1-103 | D136: वारजे कर्वेनगर क्षेत्रीय कार्यालय अंतर्गत दुषित पाण्याच्या तक्रारीची निवारण करणे झोपडपट्टी, गुंठेवारी व इतर भागांनमध्ये पाण्याच्या लाईन बदलणे, कुपनलीका देखभाल दुरुस्तीची व इतर कामे करणे | F136: 2000000
A137: ZE16A103/P1-106 | D137: भवानी पेठ क्षेत्रीय कार्यालय अंतर्गत दुषित पाण्याच्या तक्रारीची निवारण करणे झोपडपट्टी, गुंठेवारी व इतर भागांनमध्ये पाण्याच्या लाईन बदलणे, कुपनलीका देखभाल दुरुस्तीची व इतर कामे करणे | F137: 2500000
A138: ZE16A103/P1-107 | D138: धनकवडी - सहकारनगर क्षेत्रीय कार्यालय अंतर्गत दुषित पाण्याच्या तक्रारीची निवारण करणे झोपडपट्टी, गुंठेवारी व इतर भागांनमध्ये पाण्याच्या लाईन बदलणे, कुपनलीका देखभाल दुरुस्तीची व इतर कामे करणे | F138: 2000000
... A140: ZE16A103/P1-118 | D140: पर्वती HLR टाकी ४५० मि.मी पंपींग जुनी लाईन बदलून नवीन लाईन टाकणे | F140: 20000000
D142: यादी क्र. P1 एकूण | E142: 0 | F142: 384600000
D145: यादी क्र. P2
D146: शहरामध्ये पाण्याच्या लाईन टाकणे
D147: ZE16A104/P2-
A149: code | B149: ward | D149: कामाचे नाव | E149: प्रकल्पीय रक्कम | F149: तरतूद
A151: ZE16A104/P2-271 | D151: पर्वती रॉ वॉटर पंपिंग स्टेशन ते लष्कर जलकेंद्र रॉ वॉटर रायझिंग मेन लाईन टाकणे. | F151: 150000000
A152: ZE16A104/P2-272 | D152: लष्कर जलकेंद्र ते बकरी हिल टाकी पर्यंत १००० मिमी व्यासाची नवीन रायझिंग मेन जलनलिका टाकणे | E152: 150000000 | F152: 10000000
A153: ZE16A104/P2-273 | D153: पदमावती पंपींग स्टेशन मधील बिबवेवाडी झोनची जुनी रायझींग मेन पाईप लाईन बदलणे | F153: 2000000
A154: ZE16A104/P2-274 | D154: पदमावती पंपींग स्टेशन मधील पंपहाउस मधील पाणी ड्रेन करणेसाठी नवीन वॉश आउट लाईन टाकणे. | F154: 3000000
D156: सन 2021-22 मधील अपूर्ण कामांसाठी सन 2022-23 मध्ये उपलब्ध केलेली तरतूद
A157: ZE16A104/P2-111+ | D157: स्वारगेट पाणीपुरवठा विभागा अंतर्गतची मागील बिले अदा करणे (कॉमन) | F157: 5000000
A158: ZE16A104A/P2-1355+ | D158: चतृःश्रृंगी पाणीपुरवठा विभागाअंतगतची मागील बिले अदा करणे (कॉमन) समान | F158: 2500000
A159: ZE16A104A/P2-312+ | D159: लष्कर जलकेद्र वितरण व्यवस्थे मागिल बिले देण्यासाठी आवश्यक तरतुद | F159: 10000000
A160: ZE16A104/P2-212 | B160: 40 | D160: प्रभाग क्र. ४० मध्ये विविध ठिकाणी पाण्याची लार्इन टाकणे व इतर कामे करणे . | F160: 3000000
A161: ZE16A104/P2-218 | D161: नवीन व जुने लष्कर जलकेंद्र कार्यालय मधील स्थापत्य विषयक विविध कामे व ड्रेनेज विषयक कामे करणे. | F161: 1500000
A162: ZE16A104/P2-234 | D162: लष्कर जलकेंद्र गेट पासून मम्मादेवी चौक,बिशप चर्च दरम्यान ४०० मिमी व्यासाची एम.एस.लाईन टाकणे. | F162: 4000000
A163: ZE16A104/P2-216 | D163: नवीन लष्कर जल केंद्र आवारातील सर्च टॉवर शिफ्ट करणे. | F163: 1200000
A164: ZE16A104/P2-237 | D164: वानवडी प्र.क्र.२५ मध्ये एस.आर.पी.एफ.ग्रुप १ व २ चे मधील हद्दीपासून ते एस.आर.पी.एफ. गेट क्र.१ पर्यंत ५०० मिमी व्यासाची जुनी पी.एस.सी.जलनलिका बदलून नव्याने ५०० मिमी व्यासाची एम.एस.जलनलिका टाकणे. | F164: 3000000
A165: ZE16A104/P2-63 | D165: उंड्री गाव येथे विविध ठिकाणी नव्याने जलवाहिनी विकसित करणे. | F165: 700000
A166: ZE16A104/P2-69 | D166: कात्रज उरूळी बायपास रस्त्याने बालाजी हॉटेल ते उंड्री चौक दरम्यान 10 इंची व्यासाची मुख्य जलवाहिनी विकसित करणे. | F166: 2500000
D168: यादी क्र. P2 एकूण | E168: 150000000 | F168: 198400000
A170: पाणीपुरवठा प्रकल्प टप्पा क्र. १ - प्रकल्पांतर्गत कामे
D173: यादी क्र. PR1
D174: शहरामध्ये पाणीपुरवठा प्रकल्प अंतर्गत कामे करणे
D175: ZE16C101/PR1-
A177: code | B177: ward | D177: कामाचे नाव | E177: प्रकल्पीय रक्कम | F177: तरतूद
D179: सन 2021-22 मधील अपूर्ण कामांसाठी सन 2022-23 मध्ये उपलब्ध केलेली तरतूद
A180: ZE16A103/P1-125+ | D180: पर्वती जलकेद्र येथे नवीन 500 MLD क्षमतेचे जलशुध्दी करण केंद्र बांधणे. | F180: 40000000
A181: ZE16A103/P1-126+ | D181: खडकवासला येथे नविन जॅकवेल बांधणे, पुणे शहरातील नविन बंद पाईपलाईन टाकणे (खडकवासला- पर्वती- लष्कर) | F181: 23500000
A182: ZE16C101/PR1-131 | D182: JNNURM भामा आसखेड पाणीपुरवठा योजने अंतर्गत पाणी आरक्षणापोटी पाटबंधारे विभागाकडे सिंचन पुनर्स्थापना खर्चापोटी/ पुनर्वसनाची रक्कम अदा करणे | F182: 300000000
A183: ZE16C101/PR1-151 | D183: खडकवासला ते पर्वती (३००० MM) लाईन ची दुरुस्ती करणे | F183: 200000000
A184: ZE16C101/PR1-154 | D184: समान पाणीपुरवठा प्रकल्प व्यतिरिक्त पाण्याच्या टाक्यांना विविध ठिकाणी सीमाभिंत व संरक्षक भिंती बांधणे. | F184: 50000000
A185: ZE16C101/PR1-161 | D185: सुतारदरा येथे 1 MLD पाण्याची टाकी बांधणे | F185: 12000000
D187: यादी क्र. PR1 एकूण | E187: 0 | F187: 625500000
D190: यादी क्र. PR3
D191: पुणे शहरात तंत्रशुध्द पध्दतीने पाणीपुरवठा करण्याची योजना (24x7 समान पाणीपुरवठा योजना)
D192: ZE16C103/PR3-
A194: code | B194: ward | D194: कामाचे नाव | E194: प्रकल्पीय रक्कम | F194: तरतूद
A196: ZE16C103/PR3-5 | D196: पुणे मनपा हद्दीमध्ये नव्याने समाविष्ठ 11 गावे व 23 गावांमध्ये Master Plan नुसार पाणीपुरवठा करण्याची योजना | F196: 1500000000
D198: सन 2021-22 मधील अपूर्ण कामांसाठी सन 2022-23 मध्ये उपलब्ध केलेली तरतूद
A199: ZE16C103/PR3-1 | D199: पुणे शहरात तंत्रशुध्द पध्दतीने पाणीपुरवठा करण्याची योजना (24x7 समान पाणीपुरवठा योजना) अंतर्गत जलवाहिन्या टाकणे | F199: 3000000000
A200: ZE16C103/PR3-2 | D200: पुणे शहरात तंत्रशुध्द पध्दतीने पाणीपुरवठा करण्याची योजना (24x7 समान पाणीपुरवठा योजना) अंतर्गत भूसंपादनासाठी | F200: 20000000
A201: ZE16C103/PR3-3 | D201: अमृत अभियानांतर्गत पुणे शहरात तंत्रशुध्द पद्धतीने पाणीपुरवठा करण्याची योजना (24x7 समान पाणीपुरवठा योजना) अंतर्गत विविध ठिकाणी पाण्याच्या टाक्या बांधणे | F201: 600000000
A202: ZE16C103/PR3-4 | D202: पुणे शहरात तंत्रशुध्द पध्दतीने पाणीपुरवठा करण्याची योजना (24x7 समान पाणीपुरवठा योजना) अंतर्गत पाण्याचे मीटर बसविणे | F202: 880000000
D204: यादी क्र. PR3 एकूण | E204: 0 | F204: 6000000000
A207: जलोत्सारण विभागाकडील कामाच्या याद्या
D209: यादी क्र. D2
D210: शहरामध्ये मलवाहिन्या विकसित करणे
D211: ZE16B102/D2-
A213: code | B213: ward | D213: कामाचे नाव | E213: प्रकल्पीय रक्कम | F213: तरतूद
...

Sheet SMRY-2223
A1: code | B1: ward | C1: * | D1: क्षेत्रीय कार्यालयाने करावयाची कामे : सन 2022-23 | E1: पथ | F1: विद्युत | G1: भवन | H1: झोनिपु | I1: पाणीपुरवठा | J1: मलनिःसारण | K1: एकूण
D4: (आकडे लाखात) | E4: 2 | F4: 1 | G4: 4 | H4: 5 | I4: 6 | J4: 7 | K4: Total
A6: code | B6: Sr. | C6: Wards | D6: क्षेत्रीय कार्यालयाने करावयाची कामे : सन 2022-23 | E6: 2 | F6: 1 | G6: 4 | H6: 5 | I6: 6 | J6: 7 | K6: Total
B8: =WardOfficeNonPlan2223!B8 -> 1 | C8: =WardOfficeNonPlan2223!C8 -> 3, 4, 5 | D8: =WardOfficeNonPlan2223!D8 -> नगररोड - वडगावशेरी क्षेत्रीय कार्यालय एकूण बेरीज | E8: =WardOfficeNonPlan2223!E8+WardOfficePlan2223!E8+CitizensNonPlan2223!E8+CitizensPlan2223!E8 -> 237 | F8: =WardOfficeNonPlan2223!F8+WardOfficePlan2223!F8+CitizensNonPlan2223!F8+CitizensPlan2223!F8 -> 130 | G8: =WardOfficeNonPlan2223!G8+WardOfficePlan2223!G8+CitizensNonPlan2223!G8+CitizensPlan2223!G8 -> 92.5 | H8: =WardOfficeNonPlan2223!H8+WardOfficePlan2223!H8+CitizensNonPlan2223!H8+CitizensPlan2223!H8 -> 5 | I8: =WardOfficeNonPlan2223!I8+WardOfficePlan2223!I8+CitizensNonPlan2223!I8+CitizensPlan2223!I8 -> 42.5 | J8: =WardOfficeNonPlan2223!J8+WardOfficePlan2223!J8+CitizensNonPlan2223!J8+CitizensPlan2223!J8 -> 242.5 | K8: =SUM(E8:J8) -> 749.5
B9: =WardOfficeNonPlan2223!B9 -> 2 | C9: =WardOfficeNonPlan2223!C9 -> 1, 2, 6 | D9: =WardOfficeNonPlan2223!D9 -> येरवडा - कळस - धानोरी क्षेत्रीय कार्यालय एकूण बेरीज | E9: =WardOfficeNonPlan2223!E9+WardOfficePlan2223!E9+CitizensNonPlan2223!E9+CitizensPlan2223!E9 -> 211.5 | F9: =WardOfficeNonPlan2223!F9+WardOfficePlan2223!F9+CitizensNonPlan2223!F9+CitizensPlan2223!F9 -> 82.5 | G9: =WardOfficeNonPlan2223!G9+WardOfficePlan2223!G9+CitizensNonPlan2223!G9+CitizensPlan2223!G9 -> 115 | H9: =WardOfficeNonPlan2223!H9+WardOfficePlan2223!H9+CitizensNonPlan2223!H9+CitizensPlan2223!H9 -> 102.5 | I9: =WardOfficeNonPlan2223!I9+WardOfficePlan2223!I9+CitizensNonPlan2223!I9+CitizensPlan2223!I9 -> 0 | J9: =WardOfficeNonPlan2223!J9+WardOfficePlan2223!J9+CitizensNonPlan2223!J9+CitizensPlan2223!J9 -> 238.5 | K9: =SUM(E9:J9) -> 750
B10: =WardOfficeNonPlan2223!B10 -> 3 | C10: =WardOfficeNonPlan2223!C10 -> 20, 21 | D10: =WardOfficeNonPlan2223!D10 -> ढोलेपाटील क्षेत्रीय कार्यालय एकूण बेरीज | E10: =WardOfficeNonPlan2223!E10+WardOfficePlan2223!E10+CitizensNonPlan2223!E10+CitizensPlan2223!E10 -> 82.5 | F10: =WardOfficeNonPlan2223!F10+WardOfficePlan2223!F10+CitizensNonPlan2223!F10+CitizensPlan2223!F10 -> 32 | G10: =WardOfficeNonPlan2223!G10+WardOfficePlan2223!G10+CitizensNonPlan2223!G10+CitizensPlan2223!G10 -> 48 | H10: =WardOfficeNonPlan2223!H10+WardOfficePlan2223!H10+CitizensNonPlan2223!H10+CitizensPlan2223!H10 -> 160 | I10: =WardOfficeNonPlan2223!I10+WardOfficePlan2223!I10+CitizensNonPlan2223!I10+CitizensPlan2223!I10 -> 12.5 | J10: =WardOfficeNonPlan2223!J10+WardOfficePlan2223!J10+CitizensNonPlan2223!J10+CitizensPlan2223!J10 -> 90 | K10: =SUM(E10:J10) -> 425
B11: =WardOfficeNonPlan2223!B11 -> 4 | C11: =WardOfficeNonPlan2223!C11 -> 8, 9 | D11: =WardOfficeNonPlan2223!D11 -> औंध - बाणेर क्षेत्रीय कार्यालय एकूण बेरीज | E11: =WardOfficeNonPlan2223!E11+WardOfficePlan2223!E11+CitizensNonPlan2223!E11+CitizensPlan2223!E11 -> 105 | F11: =WardOfficeNonPlan2223!F11+WardOfficePlan2223!F11+CitizensNonPlan2223!F11+CitizensPlan2223!F11 -> 107 | G11: =WardOfficeNonPlan2223!G11+WardOfficePlan2223!G11+CitizensNonPlan2223!G11+CitizensPlan2223!G11 -> 143 | H11: =WardOfficeNonPlan2223!H11+WardOfficePlan2223!H11+CitizensNonPlan2223!H11+CitizensPlan2223!H11 -> 70 | I11: =WardOfficeNonPlan2223!I11+WardOfficePlan2223!I11+CitizensNonPlan2223!I11+CitizensPlan2223!I11 -> 0 | J11: =WardOfficeNonPlan2223!J11+WardOfficePlan2223!J11+CitizensNonPlan2223!J11+CitizensPlan2223!J11 -> 75 | K11: =SUM(E11:J11) -> 500
B12: =WardOfficeNonPlan2223!B12 -> 5 | C12: =WardOfficeNonPlan2223!C12 -> 7, 14 | D12: =WardOfficeNonPlan2223!D12 -> शिवाजीनगर - घोले रोड क्षेत्रीय कार्यालय एकूण बेरीज | E12: =WardOfficeNonPlan2223!E12+WardOfficePlan2223!E12+CitizensNonPlan2223!E12+CitizensPlan2223!E12 -> 82.5 | F12: =WardOfficeNonPlan2223!F12+WardOfficePlan2223!F12+CitizensNonPlan2223!F12+CitizensPlan2223!F12 -> 65 | G12: =WardOfficeNonPlan2223!G12+WardOfficePlan2223!G12+CitizensNonPlan2223!G12+CitizensPlan2223!G12 -> 91 | H12: =WardOfficeNonPlan2223!H12+WardOfficePlan2223!H12+CitizensNonPlan2223!H12+CitizensPlan2223!H12 -> 104 | I12: =WardOfficeNonPlan2223!I12+WardOfficePlan2223!I12+CitizensNonPlan2223!I12+CitizensPlan2223!I12 -> 15 | J12: =WardOfficeNonPlan2223!J12+WardOfficePlan2223!J12+CitizensNonPlan2223!J12+CitizensPlan2223!J12 -> 142.5 | K12: =SUM(E12:J12) -> 500
B13: =WardOfficeNonPlan2223!B13 -> 6 | C13: =WardOfficeNonPlan2223!C13 -> 10, 11, 12 | D13: =WardOfficeNonPlan2223!D13 -> कोथरूड - बावधन क्षेत्रीय कार्यालय एकूण बेरीज | E13: =WardOfficeNonPlan2223!E13+WardOfficePlan2223!E13+CitizensNonPlan2223!E13+CitizensPlan2223!E13 -> 267.5 | F13: =WardOfficeNonPlan2223!F13+WardOfficePlan2223!F13+CitizensNonPlan2223!F13+CitizensPlan2223!F13 -> 62.5 | G13: =WardOfficeNonPlan2223!G13+WardOfficePlan2223!G13+CitizensNonPlan2223!G13+CitizensPlan2223!G13 -> 98 | H13: =WardOfficeNonPlan2223!H13+WardOfficePlan2223!H13+CitizensNonPlan2223!H13+CitizensPlan2223!H13 -> 145 | I13: =WardOfficeNonPlan2223!I13+WardOfficePlan2223!I13+CitizensNonPlan2223!I13+CitizensPlan2223!I13 -> 15 | J13: =WardOfficeNonPlan2223!J13+WardOfficePlan2223!J13+CitizensNonPlan2223!J13+CitizensPlan2223!J13 -> 162 | K13: =SUM(E13:J13) -> 750
B14: =WardOfficeNonPlan2223!B14 -> 7 | C14: =WardOfficeNonPlan2223!C14 -> 35, 39, 40 | D14: =WardOfficeNonPlan2223!D14 -> धनकवडी - सहकारनगर क्षेत्रीय कार्यालय एकूण बेरीज | E14: =WardOfficeNonPlan2223!E14+WardOfficePlan2223!E14+CitizensNonPlan2223!E14+CitizensPlan2223!E14 -> 235.5 | F14: =WardOfficeNonPlan2223!F14+WardOfficePlan2223!F14+CitizensNonPlan2223!F14+CitizensPlan2223!F14 -> 67 | G14: =WardOfficeNonPlan2223!G14+WardOfficePlan2223!G14+CitizensNonPlan2223!G14+CitizensPlan2223!G14 -> 79.5 | H14: =WardOfficeNonPlan2223!H14+WardOfficePlan2223!H14+CitizensNonPlan2223!H14+CitizensPlan2223!H14 -> 89 | I14: =WardOfficeNonPlan2223!I14+WardOfficePlan2223!I14+CitizensNonPlan2223!I14+CitizensPlan2223!I14 -> 15 | J14: =WardOfficeNonPlan2223!J14+WardOfficePlan2223!J14+CitizensNonPlan2223!J14+CitizensPlan2223!J14 -> 264 | K14: =SUM(E14:J14) -> 750
B15: =WardOfficeNonPlan2223!B15 -> 8 | C15: =WardOfficeNonPlan2223!C15 -> 30, 33, 34 | D15: =WardOfficeNonPlan2223!D15 -> सिंहगड रोड क्षेत्रीय कार्यालय एकूण बेरीज | E15: =WardOfficeNonPlan2223!E15+WardOfficePlan2223!E15+CitizensNonPlan2223!E15+CitizensPlan2223!E15 -> 301.45 | F15: =WardOfficeNonPlan2223!F15+WardOfficePlan2223!F15+CitizensNonPlan2223!F15+CitizensPlan2223!F15 -> 97.5 | G15: =WardOfficeNonPlan2223!G15+WardOfficePlan2223!G15+CitizensNonPlan2223!G15+CitizensPlan2223!G15 -> 60.05 | H15: =WardOfficeNonPlan2223!H15+WardOfficePlan2223!H15+CitizensNonPlan2223!H15+CitizensPlan2223!H15 -> 100 | I15: =WardOfficeNonPlan2223!I15+WardOfficePlan2223!I15+CitizensNonPlan2223!I15+CitizensPlan2223!I15 -> 0 | J15: =WardOfficeNonPlan2223!J15+WardOfficePlan2223!J15+CitizensNonPlan2223!J15+CitizensPlan2223!J15 -> 191 | K15: =SUM(E15:J15) -> 750
B16: =WardOfficeNonPlan2223!B16 -> 9 | C16: =WardOfficeNonPlan2223!C16 -> 13, 31, 32 | D16: =WardOfficeNonPlan2223!D16 -> वारजे - कर्वेनगर क्षेत्रीय कार्यालय एकूण बेरीज | E16: =WardOfficeNonPlan2223!E16+WardOfficePlan2223!E16+CitizensNonPlan2223!E16+CitizensPlan2223!E16 -> 241.5 | F16: =WardOfficeNonPlan2223!F16+WardOfficePlan2223!F16+CitizensNonPlan2223!F16+CitizensPlan2223!F16 -> 128.5 | G16: =WardOfficeNonPlan2223!G16+WardOfficePlan2223!G16+CitizensNonPlan2223!G16+CitizensPlan2223!G16 -> 121.5 | H16: =WardOfficeNonPlan2223!H16+WardOfficePlan2223!H16+CitizensNonPlan2223!H16+CitizensPlan2223!H16 -> 107.5 | I16: =WardOfficeNonPlan2223!I16+WardOfficePlan2223!I16+CitizensNonPlan2223!I16+CitizensPlan2223!I16 -> 0 | J16: =WardOfficeNonPlan2223!J16+WardOfficePlan2223!J16+CitizensNonPlan2223!J16+CitizensPlan2223!J16 -> 151 | K16: =SUM(E16:J16) -> 750
B17: =WardOfficeNonPlan2223!B17 -> 10 | C17: =WardOfficeNonPlan2223!C17 -> 22, 23, 26 | D17: =WardOfficeNonPlan2223!D17 -> हडपसर - मुंढवा क्षेत्रीय कार्यालय एकूण बेरीज | E17: =WardOfficeNonPlan2223!E17+WardOfficePlan2223!E17+CitizensNonPlan2223!E17+CitizensPlan2223!E17 -> 340 | F17: =WardOfficeNonPlan2223!F17+WardOfficePlan2223!F17+CitizensNonPlan2223!F17+CitizensPlan2223!F17 -> 107.5 | G17: =WardOfficeNonPlan2223!G17+WardOfficePlan2223!G17+CitizensNonPlan2223!G17+CitizensPlan2223!G17 -> 62.5 | H17: =WardOfficeNonPlan2223!H17+WardOfficePlan2223!H17+CitizensNonPlan2223!H17+CitizensPlan2223!H17 -> 10 | I17: =WardOfficeNonPlan2223!I17+WardOfficePlan2223!I17+CitizensNonPlan2223!I17+CitizensPlan2223!I17 -> 10 | J17: =WardOfficeNonPlan2223!J17+WardOfficePlan2223!J17+CitizensNonPlan2223!J17+CitizensPlan2223!J17 -> 220 | K17: =SUM(E17:J17) -> 750
B18: =WardOfficeNonPlan2223!B18 -> 11 | C18: =WardOfficeNonPlan2223!C18 -> 24, 25, 27 | D18: =WardOfficeNonPlan2223!D18 -> वानवडी - रामटेकडी क्षेत्रीय कार्यालय एकूण बेरीज | E18: =WardOfficeNonPlan2223!E18+WardOfficePlan2223!E18+CitizensNonPlan2223!E18+CitizensPlan2223!E18 -> 252.5 | F18: =WardOfficeNonPlan2223!F18+WardOfficePlan2223!F18+CitizensNonPlan2223!F18+CitizensPlan2223!F18 -> 92.5 | G18: =WardOfficeNonPlan2223!G18+WardOfficePlan2223!G18+CitizensNonPlan2223!G18+CitizensPlan2223!G18 -> 42.5 | H18: =WardOfficeNonPlan2223!H18+WardOfficePlan2223!H18+CitizensNonPlan2223!H18+CitizensPlan2223!H18 -> 30 | I18: =WardOfficeNonPlan2223!I18+WardOfficePlan2223!I18+CitizensNonPlan2223!I18+CitizensPlan2223!I18 -> 5 | J18: =WardOfficeNonPlan2223!J18+WardOfficePlan2223!J18+CitizensNonPlan2223!J18+CitizensPlan2223!J18 -> 265.5 | K18: =SUM(E18:J18) -> 688
B19: =WardOfficeNonPlan2223!B19 -> 12 | C19: =WardOfficeNonPlan2223!C19 -> 38, 41 | D19: =WardOfficeNonPlan2223!D19 -> कोंढवा - येवलेवाडी क्षेत्रीय कार्यालय एकूण बेरीज | E19: =WardOfficeNonPlan2223!E19+WardOfficePlan2223!E19+CitizensNonPlan2223!E19+CitizensPlan2223!E19 -> 210.5 | F19: =WardOfficeNonPlan2223!F19+WardOfficePlan2223!F19+CitizensNonPlan2223!F19+CitizensPlan2223!F19 -> 88.5 | G19: =WardOfficeNonPlan2223!G19+WardOfficePlan2223!G19+CitizensNonPlan2223!G19+CitizensPlan2223!G19 -> 40.5 | H19: =WardOfficeNonPlan2223!H19+WardOfficePlan2223!H19+CitizensNonPlan2223!H19+CitizensPlan2223!H19 -> 0 | I19: =WardOfficeNonPlan2223!I19+WardOfficePlan2223!I19+CitizensNonPlan2223!I19+CitizensPlan2223!I19 -> 0 | J19: =WardOfficeNonPlan2223!J19+WardOfficePlan2223!J19+CitizensNonPlan2223!J19+CitizensPlan2223!J19 -> 160.5 | K19: =SUM(E19:J19) -> 500
... B23: =WardOfficeNonPlan2223!B23 -> 16 | C23: =WardOfficeNonPlan2223!C23 -> 42 | D23: =WardOfficeNonPlan2223!D23 -> नव्याने समाविष्ट झालेली गावे एकूण बेरीज | E23: =WardOfficeNonPlan2223!E23+WardOfficePlan2223!E23+CitizensNonPlan2223!E23+CitizensPlan2223!E23 -> 32.5 | F23: =WardOfficeNonPlan2223!F23+WardOfficePlan2223!F23+CitizensNonPlan2223!F23+CitizensPlan2223!F23 -> 30 | G23: =WardOfficeNonPlan2223!G23+WardOfficePlan2223!G23+CitizensNonPlan2223!G23+CitizensPlan2223!G23 -> 25 | H23: =WardOfficeNonPlan2223!H23+WardOfficePlan2223!H23+CitizensNonPlan2223!H23+CitizensPlan2223!H23 -> 0 | I23: =WardOfficeNonPlan2223!I23+WardOfficePlan2223!I23+CitizensNonPlan2223!I23+CitizensPlan2223!I23 -> 0 | J23: =WardOfficeNonPlan2223!J23+WardOfficePlan2223!J23+CitizensNonPlan2223!J23+CitizensPlan2223!J23 -> 37.5 | K23: =SUM(E23:J23) -> 125
C25: =SUM(C8:C24) -> 42 | D25: =""&TEXT(D6,"0")&" एकूण बेरीज" -> क्षेत्रीय कार्यालयाने करावयाची कामे : सन 2022-23 एकूण बेरीज | E25: =SUM(E8:E24) -> 3257.95 | F25: =SUM(F8:F24) -> 1391.5 | G25: =SUM(G8:G24) -> 1336.55 | H25: =SUM(H8:H24) -> 1260 | I25: =SUM(I8:I24) -> 128 | J25: =SUM(J8:J24) -> 2798 | K25: =SUM(K8:K24) -> 10172

Sheet WardOfficeNonPlan2223
A1: code | B1: ward | C1: * | D1: क्षेत्रीय कार्यालयाने करावयाची योजनेतर कामे : सन 2022-23 | E1: पथ | F1: विद्युत | G1: भवन | H1: झोनिपु | I1: पाणीपुरवठा | J1: मलनिःसारण | K1: एकूण | L1: H
D4: (आकडे लाखात) | E4: W2 | F4: W1 | G4: W4 | H4: W5 | I4: W6 | J4: W7
A6: code | B6: Sr. | C6: Wards | D6: क्षेत्रीय कार्यालयाने करावयाची योजनेतर कामे : सन 2022-23 | E6: RE20A301/W2- | F6: RE20C301/W1- | G6: RE22C301/W4- | H6: RE14B301/W5- | I6: XE12B301/W6- | J6: XE23A301/W7- | K6: Total
B8: 1 | C8: 3, 4, 5 | D8: =D289 -> नगररोड - वडगावशेरी क्षेत्रीय कार्यालय एकूण बेरीज | E8: =E289 -> 52 | F8: =F289 -> 27.5 | G8: =G289 -> 15 | H8: =H289 -> 0 | I8: =I289 -> 7.5 | J8: =J289 -> 47.5 | K8: =SUM(E8:J8) -> 149.5
B9: 2 | C9: 1, 2, 6 | D9: =D544 -> येरवडा - कळस - धानोरी क्षेत्रीय कार्यालय एकूण बेरीज | E9: =E544 -> 106.5 | F9: =F544 -> 57.5 | G9: =G544 -> 85 | H9: =H544 -> 47.5 | I9: =I544 -> 0 | J9: =J544 -> 153.5 | K9: =SUM(E9:J9) -> 450
B10: 3 | C10: 20, 21 | D10: =D716 -> ढोलेपाटील क्षेत्रीय कार्यालय एकूण बेरीज | E10: =E716 -> 75 | F10: =F716 -> 22.5 | G10: =G716 -> 40 | H10: =H716 -> 90 | I10: =I716 -> 5 | J10: =J716 -> 67.5 | K10: =SUM(E10:J10) -> 300
B11: 4 | C11: 8, 9 | D11: =D888 -> औंध - बाणेर क्षेत्रीय कार्यालय एकूण बेरीज | E11: =E888 -> 60 | F11: =F888 -> 60 | G11: =G888 -> 60 | H11: =H888 -> 60 | I11: =I888 -> 0 | J11: =J888 -> 60 | K11: =SUM(E11:J11) -> 300
B12: 5 | C12: 7, 14 | D12: =D1060 -> शिवाजीनगर - घोले रोड क्षेत्रीय कार्यालय एकूण बेरीज | E12: =E1060 -> 57.5 | F12: =F1060 -> 45 | G12: =G1060 -> 66 | H12: =H1060 -> 64 | I12: =I1060 -> 0 | J12: =J1060 -> 67.5 | K12: =SUM(E12:J12) -> 300
B13: 6 | C13: 10, 11, 12 | D13: =D1315 -> कोथरूड - बावधन क्षेत्रीय कार्यालय एकूण बेरीज | E13: =E1315 -> 134 | F13: =F1315 -> 20.5 | G13: =G1315 -> 88 | H13: =H1315 -> 98 | I13: =I1315 -> 0 | J13: =J1315 -> 79.5 | K13: =SUM(E13:J13) -> 420
B14: 7 | C14: 35, 39, 40 | D14: =D1570 -> धनकवडी - सहकारनगर क्षेत्रीय कार्यालय एकूण बेरीज | E14: =E1570 -> 102.5 | F14: =F1570 -> 17.5 | G14: =G1570 -> 25 | H14: =H1570 -> 55 | I14: =I1570 -> 7.5 | J14: =J1570 -> 150 | K14: =SUM(E14:J14) -> 357.5
B15: 8 | C15: 30, 33, 34 | D15: =D1825 -> सिंहगड रोड क्षेत्रीय कार्यालय एकूण बेरीज | E15: =E1825 -> 36.5 | F15: =F1825 -> 5 | G15: =G1825 -> 5 | H15: =H1825 -> 45 | I15: =I1825 -> 0 | J15: =J1825 -> 61 | K15: =SUM(E15:J15) -> 152.5
B16: 9 | C16: 13, 31, 32 | D16: =D2080 -> वारजे - कर्वेनगर क्षेत्रीय कार्यालय एकूण बेरीज | E16: =E2080 -> 114 | F16: =F2080 -> 68.5 | G16: =G2080 -> 27.5 | H16: =H2080 -> 37.5 | I16: =I2080 -> 0 | J16: =J2080 -> 81 | K16: =SUM(E16:J16) -> 328.5
B17: 10 | C17: 22, 23, 26 | D17: =D2335 -> हडपसर - मुंढवा क्षेत्रीय कार्यालय एकूण बेरीज | E17: =E2335 -> 200 | F17: =F2335 -> 62.5 | G17: =G2335 -> 37.5 | H17: =H2335 -> 10 | I17: =I2335 -> 0 | J17: =J2335 -> 140 | K17: =SUM(E17:J17) -> 450
B18: 11 | C18: 24, 25, 27 | D18: =D2590 -> वानवडी - रामटेकडी क्षेत्रीय कार्यालय एकूण बेरीज | E18: =E2590 -> 75 | F18: =F2590 -> 20 | G18: =G2590 -> 17.5 | H18: =H2590 -> 15 | I18: =I2590 -> 0 | J18: =J2590 -> 117.5 | K18: =SUM(E18:J18) -> 245
B19: 12 | C19: 38, 41 | D19: =D2762 -> कोंढवा - येवलेवाडी क्षेत्रीय कार्यालय एकूण बेरीज | E19: =E2762 -> 50 | F19: =F2762 -> 0 | G19: =G2762 -> 35.5 | H19: =H2762 -> 0 | I19: =I2762 -> 0 | J19: =J2762 -> 87.5 | K19: =SUM(E19:J19) -> 173
B20: 13 | C20: 15, 16, 29 | D20: =D3017 -> कसबा - विश्रामबागवाडा क्षेत्रीय कार्यालय एकूण बेरीज | E20: =E3017 -> 160 | F20: =F3017 -> 62.5 | G20: =G3017 -> 72.5 | H20: =H3017 -> 85 | I20: =I3017 -> 0 | J20: =J3017 -> 70 | K20: =SUM(E20:J20) -> 450
B21: 14 | C21: 17, 18, 19 | D21: =D3272 -> भवानी पेठ क्षेत्रीय कार्यालय एकूण बेरीज | E21: =E3272 -> 120 | F21: =F3272 -> 70 | G21: =G3272 -> 80 | H21: =H3272 -> 70 | I21: =I3272 -> 0 | J21: =J3272 -> 110 | K21: =SUM(E21:J21) -> 450
B22: 15 | C22: 28, 36, 37 | D22: =D3527 -> बिबवेवाडी क्षेत्रीय कार्यालय एकूण बेरीज | E22: =E3527 -> 75 | F22: =F3527 -> 62.5 | G22: =G3527 -> 50 | H22: =H3527 -> 30 | I22: =I3527 -> 0 | J22: =J3527 -> 45 | K22: =SUM(E22:J22) -> 262.5
B23: 16 | C23: 42 | D23: =D3699 -> नव्याने समाविष्ट झालेली गावे एकूण बेरीज | E23: =E3699 -> 10 | F23: =F3699 -> 5 | G23: =G3699 -> 10 | H23: =H3699 -> 0 | I23: =I3699 -> 0 | J23: =J3699 -> 27.5 | K23: =SUM(E23:J23) -> 52.5
C25: =SUM(C8:C24) -> 42 | D25: =""&TEXT(D6,"0")&" एकूण बेरीज" -> क्षेत्रीय कार्यालयाने करावयाची योजनेतर कामे : सन 2022-23 एकूण बेरीज | E25: =SUM(E8:E24) -> 1428 | F25: =SUM(F8:F24) -> 606.5 | G25: =SUM(G8:G24) -> 714.5 | H25: =SUM(H8:H24) -> 707 | I25: =SUM(I8:I24) -> 20 | J25: =SUM(J8:J24) -> 1365 | K25: =SUM(K8:K24) -> 4841
E27: =E25*100000 -> 142800000 | F27: =F25*100000 -> 60650000 | G27: =G25*100000 -> 71450000 | H27: =H25*100000 -> 70700000 | I27: =I25*100000 -> 2000000 | J27: =J25*100000 -> 136500000 | K27: =K25*100000 -> 484100000 | L27: 0
D37: नगररोड - वडगावशेरी क्षेत्रीय कार्यालय | K37: =SUM(E37:J37) -> 0
K38: =SUM(E38:J38) -> 0
A39: RE20A301/W2-1281 | B39: 3 | D39: प्रभाग क्र. 3 अ मध्ये विविध ठिकाणी फुटपाथ दुरुस्ती विषयक कामे करणे | E39: 2.5 | F39: 0 | G39: 0 | H39: 0 | I39: 0 | J39: 0 | K39: =SUM(E39:J39) -> 2.5
A40: XE23A301/W7-1111 | B40: 3 | D40: प्रभाग क्र. 3 अ मध्ये विविध ठिकाणी ड्रेनेज लाईन व चेंबर दुरुस्ती विषयक कामे करणे | E40: 0 | F40: 0 | G40: 0 | H40: 0 | I40: 0 | J40: 5 | K40: =SUM(E40:J40) -> 5
A41: RE20A301/W2-1282 | B41: 3 | D41: प्रभाग क्र. 3 अ मध्ये विविध ठिकाणी डांबरीकरण करणे | E41: 5 | F41: 0 | G41: 0 | H41: 0 | I41: 0 | J41: 0 | K41: =SUM(E41:J41) -> 5
A42: RE20A301/W2-1283 | B42: 3 | D42: प्रभाग क्र. 3 ब मध्ये विविध ठिकाणी फुटपाथ दुरुस्ती विषयक कामे करणे | E42: 2.5 | F42: 0 | G42: 0 | H42: 0 | I42: 0 | J42: 0 | K42: =SUM(E42:J42) -> 2.5
A43: XE23A301/W7-1112 | B43: 3 | D43: प्रभाग क्र. 3 ब मध्ये ड्रेनेज दुरुस्ती विषयक कामे करणे | E43: 0 | F43: 0 | G43: 0 | H43: 0 | I43: 0 | J43: 5 | K43: =SUM(E43:J43) -> 5
A44: XE23A301/W7-1113 | B44: 3 | D44: प्रभाग क्र. 3 क मध्ये विविध भागात ड्रेनेज लाईन टाकणे | E44: 0 | F44: 0 | G44: 0 | H44: 0 | I44: 0 | J44: 5 | K44: =SUM(E44:J44) -> 5
A45: RE20C301/W1-681 | B45: 3 | D45: प्रभाग क्र. 3 क मध्‍ये विविध ठिकाणी पोल बसविणे | E45: 0 | F45: 2.5 | G45: 0 | H45: 0 | I45: 0 | J45: 0 | K45: =SUM(E45:J45) -> 2.5
A46: RE20A301/W2-1284 | B46: 3 | D46: प्रभाग क्र. 3 क मध्ये विविध ठिकाणी डांबरीकरण करणे | E46: 5 | F46: 0 | G46: 0 | H46: 0 | I46: 0 | J46: 0 | K46: =SUM(E46:J46) -> 5
A47: RE20A301/W2-1285 | B47: 3 | D47: प्रभाग क्र. 3 ब मध्ये विविध ठिकाणी रस्ते विकसित करणे | E47: 5 | F47: 0 | G47: 0 | H47: 0 | I47: 0 | J47: 0 | K47: =SUM(E47:J47) -> 5
A48: RE20C301/W1-682 | B48: 3 | D48: प्रभाग क्र. 3 ड मध्ये विविध ठिकाणी विदयुत विषयक कामे करणे | E48: 0 | F48: 5 | G48: 0 | H48: 0 | I48: 0 | J48: 0 | K48: =SUM(E48:J48) -> 5
A49: XE12B301/W6-211 | B49: 3 | D49: प्रभाग क्र. 3 ड मध्ये विविध ठिकाणी पाणी पुरवठा विषयक कामे करणे | E49: 0 | F49: 0 | G49: 0 | H49: 0 | I49: 2.5 | J49: 0 | K49: =SUM(E49:J49) -> 2.5
A50: XE23A301/W7-1114 | B50: 3 | D50: प्रभाग क्र. 3 ड शांतीरक्षक येथे.विविध विकास कामे करणे | E50: 0 | F50: 0 | G50: 0 | H50: 0 | I50: 0 | J50: 5 | K50: =SUM(E50:J50) -> 5
B51: 3 | D51: 0 | E51: 0 | F51: 0 | G51: 0 | H51: 0 | I51: 0 | J51: 0 | K51: =SUM(E51:J51) -> 0 | L51: 0
B52: 3 | D52: 0 | E52: 0 | F52: 0 | G52: 0 | H52: 0 | I52: 0 | J52: 0 | K52: =SUM(E52:J52) -> 0 | L52: 0
B53: 3 | D53: 0 | E53: 0 | F53: 0 | G53: 0 | H53: 0 | I53: 0 | J53: 0 | K53: =SUM(E53:J53) -> 0 | L53: 0
B54: 3 | D54: 0 | E54: 0 | F54: 0 | G54: 0 | H54: 0 | I54: 0 | J54: 0 | K54: =SUM(E54:J54) -> 0 | L54: 0
B55: 3 | D55: 0 | E55: 0 | F55: 0 | G55: 0 | H55: 0 | I55: 0 | J55: 0 | K55: =SUM(E55:J55) -> 0 | L55: 0
B56: 3 | D56: 0 | E56: 0 | F56: 0 | G56: 0 | H56: 0 | I56: 0 | J56: 0 | K56: =SUM(E56:J56) -> 0 | L56: 0
B57: 3 | D57: 0 | E57: 0 | F57: 0 | G57: 0 | H57: 0 | I57: 0 | J57: 0 | K57: =SUM(E57:J57) -> 0 | L57: 0
B58: 3 | D58: 0 | E58: 0 | F58: 0 | G58: 0 | H58: 0 | I58: 0 | J58: 0 | K58: =SUM(E58:J58) -> 0 | L58: 0
B59: 3 | D59: 0 | E59: 0 | F59: 0 | G59: 0 | H59: 0 | I59: 0 | J59: 0 | K59: =SUM(E59:J59) -> 0 | L59: 0
B60: 3 | D60: 0 | E60: 0 | F60: 0 | G60: 0 | H60: 0 | I60: 0 | J60: 0 | K60: =SUM(E60:J60) -> 0 | L60: 0
B61: 3 | D61: 0 | E61: 0 | F61: 0 | G61: 0 | H61: 0 | I61: 0 | J61: 0 | K61: =SUM(E61:J61) -> 0 | L61: 0
B62: 3 | D62: 0 | E62: 0 | F62: 0 | G62: 0 | H62: 0 | I62: 0 | J62: 0 | K62: =SUM(E62:J62) -> 0 | L62: 0
... B118: 3 | D118: 0 | E118: 0 | F118: 0 | G118: 0 | H118: 0 | I118: 0 | J118: 0 | K118: =SUM(E118:J118) -> 0 | L118: 0
B119: 3 | K119: =SUM(E119:J119) -> 0
B120: 3 | D120: एकूण बेरीज | E120: =SUM(E39:E119) -> 20 | F120: =SUM(F39:F119) -> 7.5 | G120: =SUM(G39:G119) -> 0 | H120: =SUM(H39:H119) -> 0 | I120: =SUM(I39:I119) -> 2.5 | J120: =SUM(J39:J119) -> 20 | K120: =SUM(E120:J120) -> 50
K121: =SUM(E121:J121) -> 0
A122: RE20A301/W2-1286 | B122: 4 | D122: प्रभाग क्र. 4 अ मध्ये विविध ठिकाणी डांबरीकरण करणे | E122: 2.5 | F122: 0 | G122: 0 | H122: 0 | I122: 0 | J122: 0 | K122: =SUM(E122:J122) -> 2.5
A123: RE22C301/W4-901 | B123: 4 | D123: प्रभाग क्र. 4 अ मध्ये शौचालय दुरुस्तीची कामे करणे | E123: 0 | F123: 0 | G123: 5 | H123: 0 | I123: 0 | J123: 0 | K123: =SUM(E123:J123) -> 5
A124: RE20A301/W2-1287 | B124: 4 | D124: प्रभाग क्र. 4 अ मध्ये फुटपाथ दुरुस्ती विषयक कामे करणे | E124: 2.5 | F124: 0 | G124: 0 | H124: 0 | I124: 0 | J124: 0 | K124: =SUM(E124:J124) -> 2.5
A125: RE20A301/W2-1288 | B125: 4 | D125: प्रभाग क्र. 4 अ मध्ये विविध ठिकाणी कॉक्रीट करणे | E125: 2.5 | F125: 0 | G125: 0 | H125: 0 | I125: 0 | J125: 0 | K125: =SUM(E125:J125) -> 2.5
A126: XE23A301/W7-1115 | B126: 4 | D126: प्रभाग क्र. 4 ब मध्ये विविध ठिकाणी ड्रेनेज दुरुस्ती विषयक कामे करणे | E126: 0 | F126: 0 | G126: 0 | H126: 0 | I126: 0 | J126: 2.5 | K126: =SUM(E126:J126) -> 2.5
A127: RE22C301/W4-902 | B127: 4 | D127: प्रभाग क्र. 4 ब मध्ये शौचालय दुरुस्ती विषयक कामे करणे | E127: 0 | F127: 0 | G127: 2.5 | H127: 0 | I127: 0 | J127: 0 | K127: =SUM(E127:J127) -> 2.5
A128: RE20C301/W1-683 | B128: 4 | D128: प्रभाग क्र. 4 ब मध्ये थिटे वस्ती परिसरात विदयुत विषयक कामे करणे | E128: 0 | F128: 5 | G128: 0 | H128: 0 | I128: 0 | J128: 0 | K128: =SUM(E128:J128) -> 5
A129: RE20C301/W1-684 | B129: 4 | D129: प्रभाग क्र. 4 ब मध्ये खराडी परिसरात प्रकाश व्यवस्था करणे | E129: 0 | F129: 2.5 | G129: 0 | H129: 0 | I129: 0 | J129: 0 | K129: =SUM(E129:J129) -> 2.5
A130: XE23A301/W7-1116 | B130: 4 | D130: प्रभाग क्र. 4क मध्ये ड्रेनेज चेंबर दुरुस्ती व तदनुषगिंक कामे करणे | E130: 0 | F130: 0 | G130: 0 | H130: 0 | I130: 0 | J130: 5 | K130: =SUM(E130:J130) -> 5
A131: RE20A301/W2-1289 | B131: 4 | D131: प्रभाग क्र. 4 क मध्ये विविध विकास कामे करणे | E131: 2.5 | F131: 0 | G131: 0 | H131: 0 | I131: 0 | J131: 0 | K131: =SUM(E131:J131) -> 2.5
A132: RE20C301/W1-685 | B132: 4 | D132: प्रभाग क्र. 4 क मध्ये राजाराम पाटील नगर येथे विदयुत तारा भुमिगत करणे | E132: 0 | F132: 5 | G132: 0 | H132: 0 | I132: 0 | J132: 0 | K132: =SUM(E132:J132) -> 5
A133: XE23A301/W7-1117 | B133: 4 | D133: प्रभाग क्र. 4 ड मध्ये विविध ठिकाणी ड्रेनेज दुरुस्ती विषयक कामे करणे | E133: 0 | F133: 0 | G133: 0 | H133: 0 | I133: 0 | J133: 5 | K133: =SUM(E133:J133) -> 5
... A135: RE22C301/W4-903 | B135: 4 | D135: प्रभाग क्र. 4 ड मध्ये येथील शैाचालय दुरुस्ती विषयक कामे करणे | E135: 0 | F135: 0 | G135: 2.5 | H135: 0 | I135: 0 | J135: 0 | K135: =SUM(E135:J135) -> 2.5
B136: 4 | D136: 0 | E136: 0 | F136: 0 | G136: 0 | H136: 0 | I136: 0 | J136: 0 | K136: =SUM(E136:J136) -> 0 | L136: 0
B137: 4 | D137: 0 | E137: 0 | F137: 0 | G137: 0 | H137: 0 | I137: 0 | J137: 0 | K137: =SUM(E137:J137) -> 0 | L137: 0
B138: 4 | D138: 0 | E138: 0 | F138: 0 | G138: 0 | H138: 0 | I138: 0 | J138: 0 | K138: =SUM(E138:J138) -> 0 | L138: 0
B139: 4 | D139: 0 | E139: 0 | F139: 0 | G139: 0 | H139: 0 | I139: 0 | J139: 0 | K139: =SUM(E139:J139) -> 0 | L139: 0
B140: 4 | D140: 0 | E140: 0 | F140: 0 | G140: 0 | H140: 0 | I140: 0 | J140: 0 | K140: =SUM(E140:J140) -> 0 | L140: 0
B141: 4 | D141: 0 | E141: 0 | F141: 0 | G141: 0 | H141: 0 | I141: 0 | J141: 0 | K141: =SUM(E141:J141) -> 0 | L141: 0
B142: 4 | D142: 0 | E142: 0 | F142: 0 | G142: 0 | H142: 0 | I142: 0 | J142: 0 | K142: =SUM(E142:J142) -> 0 | L142: 0
B143: 4 | D143: 0 | E143: 0 | F143: 0 | G143: 0 | H143: 0 | I143: 0 | J143: 0 | K143: =SUM(E143:J143) -> 0 | L143: 0
B144: 4 | D144: 0 | E144: 0 | F144: 0 | G144: 0 | H144: 0 | I144: 0 | J144: 0 | K144: =SUM(E144:J144) -> 0 | L144: 0
B145: 4 | D145: 0 | E145: 0 | F145: 0 | G145: 0 | H145: 0 | I145: 0 | J145: 0 | K145: =SUM(E145:J145) -> 0 | L145: 0
B146: 4 | D146: 0 | E146: 0 | F146: 0 | G146: 0 | H146: 0 | I146: 0 | J146: 0 | K146: =SUM(E146:J146) -> 0 | L146: 0
B147: 4 | D147: 0 | E147: 0 | F147: 0 | G147: 0 | H147: 0 | I147: 0 | J147: 0 | K147: =SUM(E147:J147) -> 0 | L147: 0
... B201: 4 | D201: 0 | E201: 0 | F201: 0 | G201: 0 | H201: 0 | I201: 0 | J201: 0 | K201: =SUM(E201:J201) -> 0 | L201: 0
B202: 4 | K202: =SUM(E202:J202) -> 0 | L202: 0
B203: 4 | D203: एकूण बेरीज | E203: =SUM(E122:E202) -> 15 | F203: =SUM(F122:F202) -> 12.5 | G203: =SUM(G122:G202) -> 10 | H203: =SUM(H122:H202) -> 0 | I203: =SUM(I122:I202) -> 0 | J203: =SUM(J122:J202) -> 12.5 | K203: =SUM(E203:J203) -> 50
K204: =SUM(E204:J204) -> 0 | L204: 0
A205: RE20A301/W2-1291 | B205: 5 | D205: प्रभाग क्र. 5 अ वडगांवशेरी कल्‍याणीनगर परिसरात रस्‍ते विकसित करणे | E205: 5 | F205: 0 | G205: 0 | H205: 0 | I205: 0 | J205: 0 | K205: =SUM(E205:J205) -> 5
A206: XE23A301/W7-1118 | B206: 5 | D206: प्रभाग क्र. 5 अ वडगांवशेरी कल्‍याणीनगर ड्रेनेज लाईन टाकणे व दुरुस्‍ती विषयक कामे करणे | E206: 0 | F206: 0 | G206: 0 | H206: 0 | I206: 0 | J206: 5 | K206: =SUM(E206:J206) -> 5
A207: RE22C301/W4-904 | B207: 5 | D207: प्रभाग क्र. 5 अ वडगांवशेरी मध्ये मनपा इमारती मध्ये विविध विकास कामे करणे | E207: 0 | F207: 0 | G207: 2.5 | H207: 0 | I207: 0 | J207: 0 | K207: =SUM(E207:J207) -> 2.5
A208: RE20A301/W2-1292 | B208: 5 | D208: प्रभाग क्र. 5 ब मध्ये विविध विकास कामे करणे | E208: 2 | F208: 0 | G208: 0 | H208: 0 | I208: 0 | J208: 0 | K208: =SUM(E208:J208) -> 2
A209: XE23A301/W7-1119 | B209: 5 | D209: प्रभाग क्र. 5 ब मध्ये विविध ठिकाणी ड्रेनेज दुरुस्ती विषयक कामे करणे | E209: 0 | F209: 0 | G209: 0 | H209: 0 | I209: 0 | J209: 5 | K209: =SUM(E209:J209) -> 5
A210: RE20C301/W1-686 | B210: 5 | D210: प्रभाग क्र. 5 ब मध्ये परिसरात प्रकाश व्यवस्था करणे | E210: 0 | F210: 5 | G210: 0 | H210: 0 | I210: 0 | J210: 0 | K210: =SUM(E210:J210) -> 5
A211: RE20A301/W2-1293 | B211: 5 | D211: प्रभाग क्र. 5 क वडगांवशेरी कल्‍याणीनगर भागात रस्‍ते विकसित करणे | E211: 5 | F211: 0 | G211: 0 | H211: 0 | I211: 0 | J211: 0 | K211: =SUM(E211:J211) -> 5
A212: XE23A301/W7-1120 | B212: 5 | D212: प्रभाग क्र. 5 क वडगांवशेरी कल्‍याणीनगर ड्रेनेज लाईन टाकणे व देखभाल दुरुस्‍ती विषयक कामे करणे | E212: 0 | F212: 0 | G212: 0 | H212: 0 | I212: 0 | J212: 5 | K212: =SUM(E212:J212) -> 5
A213: RE20C301/W1-687 | B213: 5 | D213: प्रभाग क्र. 5 क वडगांवशेरी मध्ये मनपा इमारती मध्ये देखभाल दुरुस्‍ती विषयक कामे करणे | E213: 0 | F213: 2.5 | G213: 0 | H213: 0 | I213: 0 | J213: 0 | K213: =SUM(E213:J213) -> 2.5
A214: RE22C301/W4-905 | B214: 5 | D214: प्रभाग क्र. 5 ड मध्ये शौचालय दुरुस्ती विषयक कामे करणे | E214: 0 | F214: 0 | G214: 2.5 | H214: 0 | I214: 0 | J214: 0 | K214: =SUM(E214:J214) -> 2.5
A215: RE20A301/W2-1294 | B215: 5 | D215: प्रभाग क्र. 5 ड मध्ये विविध ठिकाणी डांबरीकरण करणे | E215: 5 | F215: 0 | G215: 0 | H215: 0 | I215: 0 | J215: 0 | K215: =SUM(E215:J215) -> 5
A216: XE12B301/W6-212 | B216: 5 | D216: प्रभाग क्र. 5 ड वडगांवशेरी कल्‍याणीनगर पाणी पुरवठा विषयक करणे | E216: 0 | F216: 0 | G216: 0 | H216: 0 | I216: 5 | J216: 0 | K216: =SUM(E216:J216) -> 5
B217: 5 | D217: 0 | E217: 0 | F217: 0 | G217: 0 | H217: 0 | I217: 0 | J217: 0 | K217: =SUM(E217:J217) -> 0 | L217: 0
B218: 5 | D218: 0 | E218: 0 | F218: 0 | G218: 0 | H218: 0 | I218: 0 | J218: 0 | K218: =SUM(E218:J218) -> 0 | L218: 0
B219: 5 | D219: 0 | E219: 0 | F219: 0 | G219: 0 | H219: 0 | I219: 0 | J219: 0 | K219: =SUM(E219:J219) -> 0 | L219: 0
B220: 5 | D220: 0 | E220: 0 | F220: 0 | G220: 0 | H220: 0 | I220: 0 | J220: 0 | K220: =SUM(E220:J220) -> 0 | L220: 0
B221: 5 | D221: 0 | E221: 0 | F221: 0 | G221: 0 | H221: 0 | I221: 0 | J221: 0 | K221: =SUM(E221:J221) -> 0 | L221: 0
B222: 5 | D222: 0 | E222: 0 | F222: 0 | G222: 0 | H222: 0 | I222: 0 | J222: 0 | K222: =SUM(E222:J222) -> 0 | L222: 0
B223: 5 | D223: 0 | E223: 0 | F223: 0 | G223: 0 | H223: 0 | I223: 0 | J223: 0 | K223: =SUM(E223:J223) -> 0 | L223: 0
B224: 5 | D224: 0 | E224: 0 | F224: 0 | G224: 0 | H224: 0 | I224: 0 | J224: 0 | K224: =SUM(E224:J224) -> 0 | L224: 0
...

Sheet WardOfficePlan2223
A1: code | B1: ward | C1: * | D1: क्षेत्रीय कार्यालयाने करावयाची योजनांतर्गत कामे : सन 2022-23 | E1: पथ | F1: विद्युत | G1: भवन | H1: झोनिपु | I1: पाणीपुरवठा | J1: मलनिःसारण | K1: एकूण | L1: H
D4: (आकडे लाखात) | E4: W2 | F4: W1 | G4: W4 | H4: W5 | I4: W6 | J4: W7
A6: code | B6: Sr. | C6: Wards | D6: क्षेत्रीय कार्यालयाने करावयाची योजनांतर्गत कामे : सन 2022-23 | E6: CE20A176/W2- | F6: CE20C118/W1- | G6: CE22A114/W4- | H6: FE14A118/W5- | I6: ZE16A115/W6- | J6: ZE16B113/W7- | K6: Total
B8: 1 | C8: 3, 4, 5 | D8: =D289 -> नगररोड - वडगावशेरी क्षेत्रीय कार्यालय एकूण बेरीज | E8: =E289 -> 80 | F8: =F289 -> 67.5 | G8: =G289 -> 17.5 | H8: =H289 -> 5 | I8: =I289 -> 25 | J8: =J289 -> 105 | K8: =SUM(E8:J8) -> 300
B9: 2 | C9: 1, 2, 6 | D9: =D544 -> येरवडा - कळस - धानोरी क्षेत्रीय कार्यालय एकूण बेरीज | E9: =E544 -> 0 | F9: =F544 -> 0 | G9: =G544 -> 0 | H9: =H544 -> 0 | I9: =I544 -> 0 | J9: =J544 -> 0 | K9: =SUM(E9:J9) -> 0
B10: 3 | C10: 20, 21 | D10: =D716 -> ढोलेपाटील क्षेत्रीय कार्यालय एकूण बेरीज | E10: =E716 -> 0 | F10: =F716 -> 0 | G10: =G716 -> 0 | H10: =H716 -> 0 | I10: =I716 -> 0 | J10: =J716 -> 0 | K10: =SUM(E10:J10) -> 0
B11: 4 | C11: 8, 9 | D11: =D888 -> औंध - बाणेर क्षेत्रीय कार्यालय एकूण बेरीज | E11: =E888 -> 0 | F11: =F888 -> 0 | G11: =G888 -> 0 | H11: =H888 -> 0 | I11: =I888 -> 0 | J11: =J888 -> 0 | K11: =SUM(E11:J11) -> 0
B12: 5 | C12: 7, 14 | D12: =D1060 -> शिवाजीनगर - घोले रोड क्षेत्रीय कार्यालय एकूण बेरीज | E12: =E1060 -> 0 | F12: =F1060 -> 0 | G12: =G1060 -> 0 | H12: =H1060 -> 0 | I12: =I1060 -> 0 | J12: =J1060 -> 0 | K12: =SUM(E12:J12) -> 0
B13: 6 | C13: 10, 11, 12 | D13: =D1315 -> कोथरूड - बावधन क्षेत्रीय कार्यालय एकूण बेरीज | E13: =E1315 -> 10 | F13: =F1315 -> 10 | G13: =G1315 -> 10 | H13: =H1315 -> 0 | I13: =I1315 -> 0 | J13: =J1315 -> 0 | K13: =SUM(E13:J13) -> 30
B14: 7 | C14: 35, 39, 40 | D14: =D1570 -> धनकवडी - सहकारनगर क्षेत्रीय कार्यालय एकूण बेरीज | E14: =E1570 -> 60 | F14: =F1570 -> 17.5 | G14: =G1570 -> 7.5 | H14: =H1570 -> 5 | I14: =I1570 -> 2.5 | J14: =J1570 -> 0 | K14: =SUM(E14:J14) -> 92.5
B15: 8 | C15: 30, 33, 34 | D15: =D1825 -> सिंहगड रोड क्षेत्रीय कार्यालय एकूण बेरीज | E15: =E1825 -> 134.95 | F15: =F1825 -> 27.5 | G15: =G1825 -> 55.05 | H15: =H1825 -> 15 | I15: =I1825 -> 0 | J15: =J1825 -> 65 | K15: =SUM(E15:J15) -> 297.5
B16: 9 | C16: 13, 31, 32 | D16: =D2080 -> वारजे - कर्वेनगर क्षेत्रीय कार्यालय एकूण बेरीज | E16: =E2080 -> 42 | F16: =F2080 -> 5 | G16: =G2080 -> 45 | H16: =H2080 -> 12.5 | I16: =I2080 -> 0 | J16: =J2080 -> 17 | K16: =SUM(E16:J16) -> 121.5
B17: 10 | C17: 22, 23, 26 | D17: =D2335 -> हडपसर - मुंढवा क्षेत्रीय कार्यालय एकूण बेरीज | E17: =E2335 -> 0 | F17: =F2335 -> 0 | G17: =G2335 -> 0 | H17: =H2335 -> 0 | I17: =I2335 -> 0 | J17: =J2335 -> 0 | K17: =SUM(E17:J17) -> 0
B18: 11 | C18: 24, 25, 27 | D18: =D2590 -> वानवडी - रामटेकडी क्षेत्रीय कार्यालय एकूण बेरीज | E18: =E2590 -> 77.5 | F18: =F2590 -> 47.5 | G18: =G2590 -> 5 | H18: =H2590 -> 0 | I18: =I2590 -> 0 | J18: =J2590 -> 38 | K18: =SUM(E18:J18) -> 168
B19: 12 | C19: 38, 41 | D19: =D2762 -> कोंढवा - येवलेवाडी क्षेत्रीय कार्यालय एकूण बेरीज | E19: =E2762 -> 42.5 | F19: =F2762 -> 59.5 | G19: =G2762 -> 0 | H19: =H2762 -> 0 | I19: =I2762 -> 0 | J19: =J2762 -> 25 | K19: =SUM(E19:J19) -> 127
B20: 13 | C20: 15, 16, 29 | D20: =D3017 -> कसबा - विश्रामबागवाडा क्षेत्रीय कार्यालय एकूण बेरीज | E20: =E3017 -> 0 | F20: =F3017 -> 0 | G20: =G3017 -> 0 | H20: =H3017 -> 0 | I20: =I3017 -> 0 | J20: =J3017 -> 0 | K20: =SUM(E20:J20) -> 0
B21: 14 | C21: 17, 18, 19 | D21: =D3272 -> भवानी पेठ क्षेत्रीय कार्यालय एकूण बेरीज | E21: =E3272 -> 0 | F21: =F3272 -> 0 | G21: =G3272 -> 0 | H21: =H3272 -> 0 | I21: =I3272 -> 0 | J21: =J3272 -> 0 | K21: =SUM(E21:J21) -> 0
B22: 15 | C22: 28, 36, 37 | D22: =D3527 -> बिबवेवाडी क्षेत्रीय कार्यालय एकूण बेरीज | E22: =E3527 -> 25 | F22: =F3527 -> 20 | G22: =G3527 -> 0 | H22: =H3527 -> 0 | I22: =I3527 -> 0 | J22: =J3527 -> 105 | K22: =SUM(E22:J22) -> 150
B23: 16 | C23: 42 | D23: =D3699 -> नव्याने समाविष्ट झालेली गावे एकूण बेरीज | E23: =E3699 -> 7.5 | F23: =F3699 -> 5 | G23: =G3699 -> 5 | H23: =H3699 -> 0 | I23: =I3699 -> 0 | J23: =J3699 -> 5 | K23: =SUM(E23:J23) -> 22.5
C25: =SUM(C8:C24) -> 42 | D25: =""&TEXT(D6,"0")&" एकूण बेरीज" -> क्षेत्रीय कार्यालयाने करावयाची योजनांतर्गत कामे : सन 2022-23 एकूण बेरीज | E25: =SUM(E8:E24) -> 479.45 | F25: =SUM(F8:F24) -> 259.5 | G25: =SUM(G8:G24) -> 145.05 | H25: =SUM(H8:H24) -> 37.5 | I25: =SUM(I8:I24) -> 27.5 | J25: =SUM(J8:J24) -> 360 | K25: =SUM(K8:K24) -> 1309
E27: =E25*100000 -> 47945000 | F27: =F25*100000 -> 25950000 | G27: =G25*100000 -> 14505000 | H27: =H25*100000 -> 3750000 | I27: =I25*100000 -> 2750000 | J27: =J25*100000 -> 36000000 | K27: =K25*100000 -> 130900000 | L27: 0
D37: नगररोड - वडगावशेरी क्षेत्रीय कार्यालय | K37: =SUM(E37:J37) -> 0
K38: =SUM(E38:J38) -> 0
A39: CE20A176/W2-521 | B39: 3 | D39: प्रभाग क्र. 3 अ मध्ये विविध ठिकाणी ब्लॉक दुरुस्ती विषयक कामे करणे | E39: 5 | F39: 0 | G39: 0 | H39: 0 | I39: 0 | J39: 0 | K39: =SUM(E39:J39) -> 5
A40: ZE16B113/W7-481 | B40: 3 | D40: प्रभाग क्र. 3 अ मध्ये परिसरातील ड्रेनेज लाईन साफसफाई व दुरुस्ती करणे | E40: 0 | F40: 0 | G40: 0 | H40: 0 | I40: 0 | J40: 5 | K40: =SUM(E40:J40) -> 5
A41: CE20C118/W1-421 | B41: 3 | D41: प्रभाग क्र. 3 अ मध्ये विदयुत विषयक दुरुस्‍तीची कामे करणे | E41: 0 | F41: 7.5 | G41: 0 | H41: 0 | I41: 0 | J41: 0 | K41: =SUM(E41:J41) -> 7.5
A42: CE22A114/W4-351 | B42: 3 | D42: प्रभाग क्र. 3 अ मध्ये विविध ठिकाणी शौचालय दुरुस्‍ती विषयक कामे करणे | E42: 0 | F42: 0 | G42: 5 | H42: 0 | I42: 0 | J42: 0 | K42: =SUM(E42:J42) -> 5
A43: ZE16A115/W6-131 | B43: 3 | D43: प्रभाग क्र. 3 अ विविध ठिकाणी पाणी पुरवठा दुरुस्‍ती विषयक करणे | E43: 0 | F43: 0 | G43: 0 | H43: 0 | I43: 2.5 | J43: 0 | K43: =SUM(E43:J43) -> 2.5
A44: ZE16B113/W7-482 | B44: 3 | D44: प्रभाग क्र. 3 ब मध्ये विविध ठिकाणी कॉक्रीट करणे | E44: 0 | F44: 0 | G44: 0 | H44: 0 | I44: 0 | J44: 7.5 | K44: =SUM(E44:J44) -> 7.5
A45: CE20A176/W2-522 | B45: 3 | D45: प्रभाग क्र. 3 ब मध्ये विविध ठिकाणी रस्त्याची कामे करणे | E45: 5 | F45: 0 | G45: 0 | H45: 0 | I45: 0 | J45: 0 | K45: =SUM(E45:J45) -> 5
A46: ZE16B113/W7-483 | B46: 3 | D46: प्रभाग क्र. 3 .ब मध्ये विविध ठिकाणी ड्रेनेज लाईन दुरुस्‍ती विषयक कामे करणे | E46: 0 | F46: 0 | G46: 0 | H46: 0 | I46: 0 | J46: 5 | K46: =SUM(E46:J46) -> 5
A47: CE20C118/W1-422 | B47: 3 | D47: प्रभाग क्र. 3 ब मधील सोपाननगर सोमनाथनगर येथे पोल टाकणे | E47: 0 | F47: 5 | G47: 0 | H47: 0 | I47: 0 | J47: 0 | K47: =SUM(E47:J47) -> 5
A48: CE20A176/W2-523 | B48: 3 | D48: प्रभाग क्र. 3 ब मधील सोपाननगर सोमनाथनगर येथे ब्‍लॉक दुरुस्‍ती करणे | E48: 2.5 | F48: 0 | G48: 0 | H48: 0 | I48: 0 | J48: 0 | K48: =SUM(E48:J48) -> 2.5
A49: CE20C118/W1-423 | B49: 3 | D49: प्रभाग क्र. 3 क मध्ये विमाननगर येथे विदुयत विषयक कामे करणे | E49: 0 | F49: 5 | G49: 0 | H49: 0 | I49: 0 | J49: 0 | K49: =SUM(E49:J49) -> 5
A50: CE20A176/W2-524 | B50: 3 | D50: प्रभाग क्र. 3 क विविध भागात रस्ते विकसित करणे | E50: 7.5 | F50: 0 | G50: 0 | H50: 0 | I50: 0 | J50: 0 | K50: =SUM(E50:J50) -> 7.5
... A57: ZE16B113/W7-487 | B57: 3 | D57: प्रभाग क्र. 3 ड गोल्फ चौक ते डॉन बास्को शाळेपर्यंत ड्रेनेज लाईन बदलणे | E57: 0 | F57: 0 | G57: 0 | H57: 0 | I57: 0 | J57: 5 | K57: =SUM(E57:J57) -> 5
B58: 3 | D58: 0 | E58: 0 | F58: 0 | G58: 0 | H58: 0 | I58: 0 | J58: 0 | K58: =SUM(E58:J58) -> 0 | L58: 0
B59: 3 | D59: 0 | E59: 0 | F59: 0 | G59: 0 | H59: 0 | I59: 0 | J59: 0 | K59: =SUM(E59:J59) -> 0 | L59: 0
B60: 3 | D60: 0 | E60: 0 | F60: 0 | G60: 0 | H60: 0 | I60: 0 | J60: 0 | K60: =SUM(E60:J60) -> 0 | L60: 0
B61: 3 | D61: 0 | E61: 0 | F61: 0 | G61: 0 | H61: 0 | I61: 0 | J61: 0 | K61: =SUM(E61:J61) -> 0 | L61: 0
B62: 3 | D62: 0 | E62: 0 | F62: 0 | G62: 0 | H62: 0 | I62: 0 | J62: 0 | K62: =SUM(E62:J62) -> 0 | L62: 0
B63: 3 | D63: 0 | E63: 0 | F63: 0 | G63: 0 | H63: 0 | I63: 0 | J63: 0 | K63: =SUM(E63:J63) -> 0 | L63: 0
B64: 3 | D64: 0 | E64: 0 | F64: 0 | G64: 0 | H64: 0 | I64: 0 | J64: 0 | K64: =SUM(E64:J64) -> 0 | L64: 0
B65: 3 | D65: 0 | E65: 0 | F65: 0 | G65: 0 | H65: 0 | I65: 0 | J65: 0 | K65: =SUM(E65:J65) -> 0 | L65: 0
B66: 3 | D66: 0 | E66: 0 | F66: 0 | G66: 0 | H66: 0 | I66: 0 | J66: 0 | K66: =SUM(E66:J66) -> 0 | L66: 0
B67: 3 | D67: 0 | E67: 0 | F67: 0 | G67: 0 | H67: 0 | I67: 0 | J67: 0 | K67: =SUM(E67:J67) -> 0 | L67: 0
B68: 3 | D68: 0 | E68: 0 | F68: 0 | G68: 0 | H68: 0 | I68: 0 | J68: 0 | K68: =SUM(E68:J68) -> 0 | L68: 0
B69: 3 | D69: 0 | E69: 0 | F69: 0 | G69: 0 | H69: 0 | I69: 0 | J69: 0 | K69: =SUM(E69:J69) -> 0 | L69: 0
... B118: 3 | D118: 0 | E118: 0 | F118: 0 | G118: 0 | H118: 0 | I118: 0 | J118: 0 | K118: =SUM(E118:J118) -> 0 | L118: 0
B119: 3 | K119: =SUM(E119:J119) -> 0 | L119: 0
B120: 3 | D120: एकूण बेरीज | E120: =SUM(E39:E119) -> 20 | F120: =SUM(F39:F119) -> 22.5 | G120: =SUM(G39:G119) -> 5 | H120: =SUM(H39:H119) -> 5 | I120: =SUM(I39:I119) -> 5 | J120: =SUM(J39:J119) -> 42.5 | K120: =SUM(E120:J120) -> 100
K121: =SUM(E121:J121) -> 0
A122: ZE16B113/W7-488 | B122: 4 | D122: प्रभाग क्र. 4 अ मध्ये विविध ठिकाणी ड्रेनेज दुरुस्ती विषयक कामे करणे | E122: 0 | F122: 0 | G122: 0 | H122: 0 | I122: 0 | J122: 7.5 | K122: =SUM(E122:J122) -> 7.5
A123: CE20A176/W2-525 | B123: 4 | D123: प्रभाग क्र. 4 अ मध्ये रस्ते विषयक कामे करणे | E123: 5 | F123: 0 | G123: 0 | H123: 0 | I123: 0 | J123: 0 | K123: =SUM(E123:J123) -> 5
A124: CE20C118/W1-359 | B124: 4 | D124: प्रभाग क्र. 4 अ मध्ये विविध ठिकाणी प्रकाश व्यवस्था करणे | E124: 0 | F124: 5 | G124: 0 | H124: 0 | I124: 0 | J124: 0 | K124: =SUM(E124:J124) -> 5
A125: CE20C118/W1-360 | B125: 4 | D125: प्रभाग क्र. 4अ मध्ये विविध ठिकाणी विदयुत तारा भुमीगत करणे | E125: 0 | F125: 5 | G125: 0 | H125: 0 | I125: 0 | J125: 0 | K125: =SUM(E125:J125) -> 5
A126: ZE16A115/W6-133 | B126: 4 | D126: प्रभाग क्र. 4अ मध्ये विविध ठिकाणी पाणी पुरवठा दुरुस्ती विषयक कामे करणे | E126: 0 | F126: 0 | G126: 0 | H126: 0 | I126: 2.5 | J126: 0 | K126: =SUM(E126:J126) -> 2.5
A127: CE20A176/W2-526 | B127: 4 | D127: प्रभाग क्र. 4ब मध्ये विविध ठिकाणी ब्‍लॉक दुरुस्ती विषयक कामे करणे | E127: 5 | F127: 0 | G127: 0 | H127: 0 | I127: 0 | J127: 0 | K127: =SUM(E127:J127) -> 5
A128: CE20A176/W2-527 | B128: 4 | D128: प्रभाग क्र. 4 ब मध्ये विविध ठिकाणी रस्ते डांबरीकरण करणे | E128: 7.5 | F128: 0 | G128: 0 | H128: 0 | I128: 0 | J128: 0 | K128: =SUM(E128:J128) -> 7.5
A129: CE22A114/W4-352 | B129: 4 | D129: प्रभाग क्र. 4 ब मध्ये मनपा शाळेत दुरुस्‍ती विषयक कामे करणे | E129: 0 | F129: 0 | G129: 5 | H129: 0 | I129: 0 | J129: 0 | K129: =SUM(E129:J129) -> 5
A130: CE20C118/W1-361 | B130: 4 | D130: प्रभाग क्र. 4 ब मध्ये वायरिंग विषयक कामे करणे | E130: 0 | F130: 2.5 | G130: 0 | H130: 0 | I130: 0 | J130: 0 | K130: =SUM(E130:J130) -> 2.5
A131: CE20C118/W1-362 | B131: 4 | D131: प्रभाग क्र. 4 ब मध्ये विविध शाळामधील दुरुस्ती विषयक कामे करणे | E131: 0 | F131: 5 | G131: 0 | H131: 0 | I131: 0 | J131: 0 | K131: =SUM(E131:J131) -> 5
A132: ZE16B113/W7-489 | B132: 4 | D132: प्रभाग क्र. 4 क मध्ये विविध ठिकाणी ड्रेनेज लाईन टाकणे व कॉक्रीट करणे | E132: 0 | F132: 0 | G132: 0 | H132: 0 | I132: 0 | J132: 5 | K132: =SUM(E132:J132) -> 5
A133: CE20A176/W2-528 | B133: 4 | D133: प्रभाग क्र. 4 क मध्ये विविध ठिकाणी डांबरीकरण करणे | E133: 5 | F133: 0 | G133: 0 | H133: 0 | I133: 0 | J133: 0 | K133: =SUM(E133:J133) -> 5
... A141: CE22A114/W4-353 | B141: 4 | D141: प्रभाग क्र. 4 ड मध्ये विविध शौचालयाची दुरुस्‍ती करणे | E141: 0 | F141: 0 | G141: 2.5 | H141: 0 | I141: 0 | J141: 0 | K141: =SUM(E141:J141) -> 2.5
B142: 4 | D142: 0 | E142: 0 | F142: 0 | G142: 0 | H142: 0 | I142: 0 | J142: 0 | K142: =SUM(E142:J142) -> 0 | L142: 0
B143: 4 | D143: 0 | E143: 0 | F143: 0 | G143: 0 | H143: 0 | I143: 0 | J143: 0 | K143: =SUM(E143:J143) -> 0 | L143: 0
B144: 4 | D144: 0 | E144: 0 | F144: 0 | G144: 0 | H144: 0 | I144: 0 | J144: 0 | K144: =SUM(E144:J144) -> 0 | L144: 0
B145: 4 | D145: 0 | E145: 0 | F145: 0 | G145: 0 | H145: 0 | I145: 0 | J145: 0 | K145: =SUM(E145:J145) -> 0 | L145: 0
B146: 4 | D146: 0 | E146: 0 | F146: 0 | G146: 0 | H146: 0 | I146: 0 | J146: 0 | K146: =SUM(E146:J146) -> 0 | L146: 0
B147: 4 | D147: 0 | E147: 0 | F147: 0 | G147: 0 | H147: 0 | I147: 0 | J147: 0 | K147: =SUM(E147:J147) -> 0 | L147: 0
B148: 4 | D148: 0 | E148: 0 | F148: 0 | G148: 0 | H148: 0 | I148: 0 | J148: 0 | K148: =SUM(E148:J148) -> 0 | L148: 0
B149: 4 | D149: 0 | E149: 0 | F149: 0 | G149: 0 | H149: 0 | I149: 0 | J149: 0 | K149: =SUM(E149:J149) -> 0 | L149: 0
B150: 4 | D150: 0 | E150: 0 | F150: 0 | G150: 0 | H150: 0 | I150: 0 | J150: 0 | K150: =SUM(E150:J150) -> 0 | L150: 0
B151: 4 | D151: 0 | E151: 0 | F151: 0 | G151: 0 | H151: 0 | I151: 0 | J151: 0 | K151: =SUM(E151:J151) -> 0 | L151: 0
B152: 4 | D152: 0 | E152: 0 | F152: 0 | G152: 0 | H152: 0 | I152: 0 | J152: 0 | K152: =SUM(E152:J152) -> 0 | L152: 0
B153: 4 | D153: 0 | E153: 0 | F153: 0 | G153: 0 | H153: 0 | I153: 0 | J153: 0 | K153: =SUM(E153:J153) -> 0 | L153: 0
... B201: 4 | D201: 0 | E201: 0 | F201: 0 | G201: 0 | H201: 0 | I201: 0 | J201: 0 | K201: =SUM(E201:J201) -> 0 | L201: 0
B202: 4 | K202: =SUM(E202:J202) -> 0 | L202: 0
B203: 4 | D203: एकूण बेरीज | E203: =SUM(E122:E202) -> 35 | F203: =SUM(F122:F202) -> 30 | G203: =SUM(G122:G202) -> 7.5 | H203: =SUM(H122:H202) -> 0 | I203: =SUM(I122:I202) -> 2.5 | J203: =SUM(J122:J202) -> 25 | K203: =SUM(E203:J203) -> 100
K204: =SUM(E204:J204) -> 0
A205: ZE16B113/W7-493 | B205: 5 | D205: प्रभाग क्र. 5 अ वडगांवशेरी व परिसरात ड्रेनेज लाईन टाकणे | E205: 0 | F205: 0 | G205: 0 | H205: 0 | I205: 0 | J205: 7.5 | K205: =SUM(E205:J205) -> 7.5
A206: CE20A176/W2-531 | B206: 5 | D206: प्रभाग क्र. 5 अ वडगांवशेरी व परिसरात रस्‍ते विकसित करणे | E206: 7.5 | F206: 0 | G206: 0 | H206: 0 | I206: 0 | J206: 0 | K206: =SUM(E206:J206) -> 7.5
A207: ZE16A115/W6-134 | B207: 5 | D207: प्रभाग क्र. 5 अ वडगांवशेरी मध्ये पाणीपुरवठा व दुरुस्‍ती विषयक कामे करणे | E207: 0 | F207: 0 | G207: 0 | H207: 0 | I207: 5 | J207: 0 | K207: =SUM(E207:J207) -> 5
A208: CE20C118/W1-365 | B208: 5 | D208: प्रभाग क्र. 5 अ वडगांवशेरी मध्ये विदयुत विषयक कामे करणे | E208: 0 | F208: 5 | G208: 0 | H208: 0 | I208: 0 | J208: 0 | K208: =SUM(E208:J208) -> 5
A209: ZE16B113/W7-494 | B209: 5 | D209: प्रभाग क्र. 5 ब वडगांवशेरी व परिसरात ड्रेनेज लाईन टाकणे | E209: 0 | F209: 0 | G209: 0 | H209: 0 | I209: 0 | J209: 7.5 | K209: =SUM(E209:J209) -> 7.5
A210: CE20C118/W1-366 | B210: 5 | D210: प्रभाग क्र. 5 ब मध्ये वडगांवशेरी येथे विदयुत विषयक कामे करणे | E210: 0 | F210: 5 | G210: 0 | H210: 0 | I210: 0 | J210: 0 | K210: =SUM(E210:J210) -> 5
A211: CE22A114/W4-354 | B211: 5 | D211: प्रभाग क्र. 5 ब मध्ये विविध शौचालयाची दुरुस्‍ती करणे | E211: 0 | F211: 0 | G211: 5 | H211: 0 | I211: 0 | J211: 0 | K211: =SUM(E211:J211) -> 5
A212: ZE16A115/W6-135 | B212: 5 | D212: प्रभाग क्र. 5 ब विविध ठिकाणी पाणी पुरवठा दुरुस्‍ती विषयक करणे | E212: 0 | F212: 0 | G212: 0 | H212: 0 | I212: 7.5 | J212: 0 | K212: =SUM(E212:J212) -> 7.5
A213: ZE16B113/W7-495 | B213: 5 | D213: प्रभाग क्र. 5 क वडगांवशेरी व परिसरात ड्रेनेज लाईन टाकणे व तदनुषगिंक कामे करणे | E213: 0 | F213: 0 | G213: 0 | H213: 0 | I213: 0 | J213: 7.5 | K213: =SUM(E213:J213) -> 7.5
A214: CE20A176/W2-532 | B214: 5 | D214: प्रभाग क्र. 5 क वडगांवशेरी भागात रस्‍ते विकसित करणे | E214: 7.5 | F214: 0 | G214: 0 | H214: 0 | I214: 0 | J214: 0 | K214: =SUM(E214:J214) -> 7.5
A215: ZE16A115/W6-136 | B215: 5 | D215: प्रभाग क्र. 5 क वडगांवशेरी मध्ये पाण्याची लाईन टाकणे व दुरुस्‍ती विषयक कामे करणे | E215: 0 | F215: 0 | G215: 0 | H215: 0 | I215: 5 | J215: 0 | K215: =SUM(E215:J215) -> 5
A216: CE20C118/W1-367 | B216: 5 | D216: प्रभाग क्र. 5 क वडगांवशेरी मध्ये प्रकाश व्‍यवस्‍था करणे | E216: 0 | F216: 5 | G216: 0 | H216: 0 | I216: 0 | J216: 0 | K216: =SUM(E216:J216) -> 5
... A220: CE20A176/W2-534 | B220: 5 | D220: प्रभाग क्र. 5 ड वडगांवशेरी मध्ये विदयुत विषयक कामे करणे | E220: 5 | F220: 0 | G220: 0 | H220: 0 | I220: 0 | J220: 0 | K220: =SUM(E220:J220) -> 5
B221: 5 | D221: 0 | E221: 0 | F221: 0 | G221: 0 | H221: 0 | I221: 0 | J221: 0 | K221: =SUM(E221:J221) -> 0 | L221: 0
B222: 5 | D222: 0 | E222: 0 | F222: 0 | G222: 0 | H222: 0 | I222: 0 | J222: 0 | K222: =SUM(E222:J222) -> 0 | L222: 0
B223: 5 | D223: 0 | E223: 0 | F223: 0 | G223: 0 | H223: 0 | I223: 0 | J223: 0 | K223: =SUM(E223:J223) -> 0 | L223: 0
B224: 5 | D224: 0 | E224: 0 | F224: 0 | G224: 0 | H224: 0 | I224: 0 | J224: 0 | K224: =SUM(E224:J224) -> 0 | L224: 0
B225: 5 | D225: 0 | E225: 0 | F225: 0 | G225: 0 | H225: 0 | I225: 0 | J225: 0 | K225: =SUM(E225:J225) -> 0 | L225: 0
B226: 5 | D226: 0 | E226: 0 | F226: 0 | G226: 0 | H226: 0 | I226: 0 | J226: 0 | K226: =SUM(E226:J226) -> 0 | L226: 0
...

Sheet CitizensNonPlan2223
A1: code | B1: ward | C1: * | D1: क्षेत्रीय कार्यालयाने नागरिकांच्या सहभागातून करावयाची योजनेतर कामे : सन 2022-23 | E1: पथ | F1: विद्युत | G1: भवन | H1: झोनिपु | I1: पाणीपुरवठा | J1: मलनिःसारण | K1: एकूण | L1: H
D4: (आकडे लाखात) | E4: C2 | F4: C1 | G4: C4 | H4: C5 | I4: C6 | J4: C7
A6: code | B6: Sr. | C6: Wards | D6: क्षेत्रीय कार्यालयाने नागरिकांच्या सहभागातून करावयाची योजनेतर कामे : सन 2022-23 | E6: RE20A302/C2- | F6: RE20C302/C1- | G6: RE22C302/C4- | H6: RE14B302/C5- | I6: XE12B302/C6- | J6: XE23A302/C7- | K6: Total
B8: 1 | C8: 3, 4, 5 | D8: =D289 -> नगररोड - वडगावशेरी क्षेत्रीय कार्यालय एकूण बेरीज | E8: =E289 -> 105 | F8: =F289 -> 35 | G8: =G289 -> 60 | H8: =H289 -> 0 | I8: =I289 -> 10 | J8: =J289 -> 90 | K8: =SUM(E8:J8) -> 300
B9: 2 | C9: 1, 2, 6 | D9: =D544 -> येरवडा - कळस - धानोरी क्षेत्रीय कार्यालय एकूण बेरीज | E9: =E544 -> 105 | F9: =F544 -> 25 | G9: =G544 -> 30 | H9: =H544 -> 55 | I9: =I544 -> 0 | J9: =J544 -> 85 | K9: =SUM(E9:J9) -> 300
B10: 3 | C10: 20, 21 | D10: =D716 -> ढोलेपाटील क्षेत्रीय कार्यालय एकूण बेरीज | E10: =E716 -> 7.5 | F10: =F716 -> 9.5 | G10: =G716 -> 8 | H10: =H716 -> 70 | I10: =I716 -> 7.5 | J10: =J716 -> 22.5 | K10: =SUM(E10:J10) -> 125
B11: 4 | C11: 8, 9 | D11: =D888 -> औंध - बाणेर क्षेत्रीय कार्यालय एकूण बेरीज | E11: =E888 -> 45 | F11: =F888 -> 47 | G11: =G888 -> 83 | H11: =H888 -> 10 | I11: =I888 -> 0 | J11: =J888 -> 15 | K11: =SUM(E11:J11) -> 200
B12: 5 | C12: 7, 14 | D12: =D1060 -> शिवाजीनगर - घोले रोड क्षेत्रीय कार्यालय एकूण बेरीज | E12: =E1060 -> 25 | F12: =F1060 -> 20 | G12: =G1060 -> 25 | H12: =H1060 -> 40 | I12: =I1060 -> 15 | J12: =J1060 -> 75 | K12: =SUM(E12:J12) -> 200
B13: 6 | C13: 10, 11, 12 | D13: =D1315 -> कोथरूड - बावधन क्षेत्रीय कार्यालय एकूण बेरीज | E13: =E1315 -> 77 | F13: =F1315 -> 7 | G13: =G1315 -> 0 | H13: =H1315 -> 47 | I13: =I1315 -> 10 | J13: =J1315 -> 45 | K13: =SUM(E13:J13) -> 186
B14: 7 | C14: 35, 39, 40 | D14: =D1570 -> धनकवडी - सहकारनगर क्षेत्रीय कार्यालय एकूण बेरीज | E14: =E1570 -> 42 | F14: =F1570 -> 8 | G14: =G1570 -> 16 | H14: =H1570 -> 29 | I14: =I1570 -> 0 | J14: =J1570 -> 90 | K14: =SUM(E14:J14) -> 185
B15: 8 | C15: 30, 33, 34 | D15: =D1825 -> सिंहगड रोड क्षेत्रीय कार्यालय एकूण बेरीज | E15: =E1825 -> 25 | F15: =F1825 -> 25 | G15: =G1825 -> 0 | H15: =H1825 -> 35 | I15: =I1825 -> 0 | J15: =J1825 -> 35 | K15: =SUM(E15:J15) -> 120
B16: 9 | C16: 13, 31, 32 | D16: =D2080 -> वारजे - कर्वेनगर क्षेत्रीय कार्यालय एकूण बेरीज | E16: =E2080 -> 43 | F16: =F2080 -> 40 | G16: =G2080 -> 9 | H16: =H2080 -> 10 | I16: =I2080 -> 0 | J16: =J2080 -> 29 | K16: =SUM(E16:J16) -> 131
B17: 10 | C17: 22, 23, 26 | D17: =D2335 -> हडपसर - मुंढवा क्षेत्रीय कार्यालय एकूण बेरीज | E17: =E2335 -> 140 | F17: =F2335 -> 45 | G17: =G2335 -> 25 | H17: =H2335 -> 0 | I17: =I2335 -> 10 | J17: =J2335 -> 80 | K17: =SUM(E17:J17) -> 300
B18: 11 | C18: 24, 25, 27 | D18: =D2590 -> वानवडी - रामटेकडी क्षेत्रीय कार्यालय एकूण बेरीज | E18: =E2590 -> 100 | F18: =F2590 -> 25 | G18: =G2590 -> 20 | H18: =H2590 -> 15 | I18: =I2590 -> 0 | J18: =J2590 -> 110 | K18: =SUM(E18:J18) -> 270
B19: 12 | C19: 38, 41 | D19: =D2762 -> कोंढवा - येवलेवाडी क्षेत्रीय कार्यालय एकूण बेरीज | E19: =E2762 -> 15 | F19: =F2762 -> 5 | G19: =G2762 -> 5 | H19: =H2762 -> 0 | I19: =I2762 -> 0 | J19: =J2762 -> 27 | K19: =SUM(E19:J19) -> 52
B20: 13 | C20: 15, 16, 29 | D20: =D3017 -> कसबा - विश्रामबागवाडा क्षेत्रीय कार्यालय एकूण बेरीज | E20: =E3017 -> 85 | F20: =F3017 -> 30 | G20: =G3017 -> 55 | H20: =H3017 -> 70 | I20: =I3017 -> 10 | J20: =J3017 -> 50 | K20: =SUM(E20:J20) -> 300
B21: 14 | C21: 17, 18, 19 | D21: =D3272 -> भवानी पेठ क्षेत्रीय कार्यालय एकूण बेरीज | E21: =E3272 -> 94 | F21: =F3272 -> 15 | G21: =G3272 -> 17 | H21: =H3272 -> 66 | I21: =I3272 -> 3 | J21: =J3272 -> 105 | K21: =SUM(E21:J21) -> 300
B22: 15 | C22: 28, 36, 37 | D22: =D3527 -> बिबवेवाडी क्षेत्रीय कार्यालय एकूण बेरीज | E22: =E3527 -> 58 | F22: =F3527 -> 18 | G22: =G3527 -> 33 | H22: =H3527 -> 13 | I22: =I3527 -> 0 | J22: =J3527 -> 40 | K22: =SUM(E22:J22) -> 162
B23: 16 | C23: 42 | D23: =D3699 -> नव्याने समाविष्ट झालेली गावे एकूण बेरीज | E23: =E3699 -> 5 | F23: =F3699 -> 15 | G23: =G3699 -> 5 | H23: =H3699 -> 0 | I23: =I3699 -> 0 | J23: =J3699 -> 5 | K23: =SUM(E23:J23) -> 30
C25: =SUM(C8:C24) -> 42 | D25: =""&TEXT(D6,"0")&" एकूण बेरीज" -> क्षेत्रीय कार्यालयाने नागरिकांच्या सहभागातून करावयाची योजनेतर कामे : सन 2022-23 एकूण बेरीज | E25: =SUM(E8:E24) -> 971.5 | F25: =SUM(F8:F24) -> 369.5 | G25: =SUM(G8:G24) -> 391 | H25: =SUM(H8:H24) -> 460 | I25: =SUM(I8:I24) -> 65.5 | J25: =SUM(J8:J24) -> 903.5 | K25: =SUM(K8:K24) -> 3161
E27: =E25*100000 -> 97150000 | F27: =F25*100000 -> 36950000 | G27: =G25*100000 -> 39100000 | H27: =H25*100000 -> 46000000 | I27: =I25*100000 -> 6550000 | J27: =J25*100000 -> 90350000 | K27: =K25*100000 -> 316100000 | L27: 0
D37: नगररोड - वडगावशेरी क्षेत्रीय कार्यालय | K37: =SUM(E37:J37) -> 0
K38: =SUM(E38:J38) -> 0
A39: XE23A302/C7-1331 | B39: 3 | D39: प्रभाग क्र.३अ मधील वैकफिल्ड व सिध्दार्थनगर येथील ड्रेनेज लाईन चेंबर दुरुस्‍त करणे | J39: 5 | K39: =SUM(E39:J39) -> 5
A40: XE23A302/C7-1332 | B40: 3 | D40: प्रभाग क्र.३अ मधील संजयपार्क व यमुनानगर मधील ड्रेनेज लाईन चेंबर दुरुस्‍त करणे | J40: 5 | K40: =SUM(E40:J40) -> 5
A41: XE23A302/C7-1333 | B41: 3 | D41: प्रभाग क्र.३अ विमाननगर परिसरातील ड्रेनेज विषयक देखभाल दुरुस्‍ती करणे | J41: 5 | K41: =SUM(E41:J41) -> 5
A42: RE22C302/C4-791 | B42: 3 | D42: प्रभाग क्र.३अ वैकफिल्ड, संजयपार्क यमुनानगर येथील शौचालयाची दुरुस्‍ती करणे | G42: 5 | K42: =SUM(E42:J42) -> 5
A43: RE20A302/C2-951 | B43: 3 | D43: प्रभाग क्र.३अ विमाननगर परिसरातील फुटपाथ दुरुस्‍ती करणे | E43: 5 | K43: =SUM(E43:J43) -> 5
A44: RE20A302/C2-952 | B44: 3 | D44: प्रभाग क्र.३ फुटपाथ् दुरुस्ती करणे | E44: 5 | K44: =SUM(E44:J44) -> 5
A45: RE20A302/C2-953 | B45: 3 | D45: प्रभाग क्र.३ स्‍वच्‍छ विषयी कचरा ढकलगाडी पुरविणे | E45: 5 | K45: =SUM(E45:J45) -> 5
A46: XE12B302/C6-331 | B46: 3 | D46: प्रभाग क्र.३ प्रभागामध्ये विविध ठिकाणी पाण्याच्‍या लाईन दुरुस्‍ती विषयक कामे करणे | I46: 5 | K46: =SUM(E46:J46) -> 5
A47: XE23A302/C7-1334 | B47: 3 | D47: प्रभाग क्र.३ ड्रेनेज दुरुस्‍ती विषयक कामे करणे | J47: 5 | K47: =SUM(E47:J47) -> 5
A48: RE20C302/C1-681 | B48: 3 | D48: प्रभाग क्र.३ विदयुत विषयक कामे करणे | F48: 5 | K48: =SUM(E48:J48) -> 5
A49: RE20C302/C1-682 | B49: 3 | D49: प्रभाग क्र.३ म्‍हाडा कॉलनी व रोहन मिथिला जवळ पथदिप कामे करणे | F49: 5 | K49: =SUM(E49:J49) -> 5
A50: RE20A302/C2-954 | B50: 3 | D50: प्रभाग क्र.३ क मध्ये विविध ठिकाणी फुटपाथ दुरुस्‍ती विषयक कामे करणे | E50: 5 | K50: =SUM(E50:J50) -> 5
A51: XE23A302/C7-1335 | B51: 3 | D51: प्रभाग क्र.३ क मध्ये विमानगर मधील यमुनानगर येथे ड्रेनेज विषयक कामे करणे | J51: 5 | K51: =SUM(E51:J51) -> 5
A52: RE22C302/C4-792 | B52: 3 | D52: प्रभाग क्र.३ मोकळया जागेत भवन व गार्डन बसविणे | G52: 5 | K52: =SUM(E52:J52) -> 5
A53: RE22C302/C4-793 | B53: 3 | D53: प्रभाग क्र.3 मध्ये भिंतीचित्र रंगविणे | G53: 5 | K53: =SUM(E53:J53) -> 5
A54: XE12B302/C6-332 | B54: 3 | D54: प्रभाग क्र.3 ड स.नं.103 गांधीनगर व जयप्रकाशनगर येथे पाण्याची लाईन टाकणे व कॉक्रीट करणे | I54: 5 | K54: =SUM(E54:J54) -> 5
A55: RE20C302/C1-683 | B55: 3 | D55: प्रभाग क्र.3 ड स.नं.103 गांधीनगर व जयप्रकाशनगर येथे प्रकाश व्‍यवस्‍था करणे | F55: 5 | K55: =SUM(E55:J55) -> 5
A56: RE22C302/C4-794 | B56: 3 | D56: प्रभाग क्र.3 ड गांधीनगर व जयप्रकाशनगर येथील सार्वजनिक शौचालय दुरुस्‍त करणे | G56: 5 | K56: =SUM(E56:J56) -> 5
A57: XE23A302/C7-1336 | B57: 3 | D57: प्रभाग क्र.3 ड स.नं.103 गांधीनगर गल्‍लीबोळातील ड्रेनेज चेंबर दुरुस्‍ती करणे व जाळया बसविणे व नविन ड्रेनेज लाईन टाकणे | J57: 5 | K57: =SUM(E57:J57) -> 5
A58: XE23A302/C7-1337 | B58: 3 | D58: प्रभाग क्र.3 ड जयप्रकाशनगर येथील गल्‍लीबोळातील ड्रेनेज चेंबर दुरुस्‍ती करणे व जाळया बसविणे व नविन ड्रेनेज लाईन टाकणे | J58: 5 | K58: =SUM(E58:J58) -> 5
B59: 3 | D59: 0 | E59: 0 | F59: 0 | G59: 0 | H59: 0 | I59: 0 | J59: 0 | K59: =SUM(E59:J59) -> 0 | L59: 0
B60: 3 | D60: 0 | E60: 0 | F60: 0 | G60: 0 | H60: 0 | I60: 0 | J60: 0 | K60: =SUM(E60:J60) -> 0 | L60: 0
B61: 3 | D61: 0 | E61: 0 | F61: 0 | G61: 0 | H61: 0 | I61: 0 | J61: 0 | K61: =SUM(E61:J61) -> 0 | L61: 0
B62: 3 | D62: 0 | E62: 0 | F62: 0 | G62: 0 | H62: 0 | I62: 0 | J62: 0 | K62: =SUM(E62:J62) -> 0 | L62: 0
B63: 3 | D63: 0 | E63: 0 | F63: 0 | G63: 0 | H63: 0 | I63: 0 | J63: 0 | K63: =SUM(E63:J63) -> 0 | L63: 0
B64: 3 | D64: 0 | E64: 0 | F64: 0 | G64: 0 | H64: 0 | I64: 0 | J64: 0 | K64: =SUM(E64:J64) -> 0 | L64: 0
B65: 3 | D65: 0 | E65: 0 | F65: 0 | G65: 0 | H65: 0 | I65: 0 | J65: 0 | K65: =SUM(E65:J65) -> 0 | L65: 0
B66: 3 | D66: 0 | E66: 0 | F66: 0 | G66: 0 | H66: 0 | I66: 0 | J66: 0 | K66: =SUM(E66:J66) -> 0 | L66: 0
B67: 3 | D67: 0 | E67: 0 | F67: 0 | G67: 0 | H67: 0 | I67: 0 | J67: 0 | K67: =SUM(E67:J67) -> 0 | L67: 0
B68: 3 | D68: 0 | E68: 0 | F68: 0 | G68: 0 | H68: 0 | I68: 0 | J68: 0 | K68: =SUM(E68:J68) -> 0 | L68: 0
B69: 3 | D69: 0 | E69: 0 | F69: 0 | G69: 0 | H69: 0 | I69: 0 | J69: 0 | K69: =SUM(E69:J69) -> 0 | L69: 0
B70: 3 | D70: 0 | E70: 0 | F70: 0 | G70: 0 | H70: 0 | I70: 0 | J70: 0 | K70: =SUM(E70:J70) -> 0 | L70: 0
... B118: 3 | D118: 0 | E118: 0 | F118: 0 | G118: 0 | H118: 0 | I118: 0 | J118: 0 | K118: =SUM(E118:J118) -> 0 | L118: 0
B119: 3 | K119: =SUM(E119:J119) -> 0
B120: 3 | D120: एकूण बेरीज | E120: =SUM(E39:E119) -> 20 | F120: =SUM(F39:F119) -> 15 | G120: =SUM(G39:G119) -> 20 | H120: =SUM(H39:H119) -> 0 | I120: =SUM(I39:I119) -> 10 | J120: =SUM(J39:J119) -> 35 | K120: =SUM(E120:J120) -> 100
K121: =SUM(E121:J121) -> 0
A122: RE20A302/C2-955 | B122: 4 | D122: प्रभाग क्र. ४ अ मध्ये खराडी,चंदननगर,डांबरीकरण करणे | E122: 5 | K122: =SUM(E122:J122) -> 5
A123: RE20A302/C2-956 | B123: 4 | D123: प्रभाग क्र. ४ अ मध्ये गणेशनगर चंदननगर परिसरात परिसरात फुटपाथ दुरुस्‍त करणे | E123: 5 | K123: =SUM(E123:J123) -> 5
A124: RE20C302/C1-684 | B124: 4 | D124: प्रभाग क्र. ४ अ मध्ये विविध ठिकाणी विदयुत विषयक कामे करणे | F124: 5 | K124: =SUM(E124:J124) -> 5
A125: XE23A302/C7-1338 | B125: 4 | D125: प्रभाग क्र. ४ अ मधील गणेशनगर येथील ड्रेनेज दुरुस्‍ती विषयक कामे करणे | J125: 5 | K125: =SUM(E125:J125) -> 5
A126: RE20A302/C2-957 | B126: 4 | D126: प्र.क्र.४अ मध्ये काळुबाईनगर येथे लक्ष्मी सकट यांच्‍या घरापासुन सुधाकर काटे यांच्‍या घरापर्यंत रस्‍ता डांबरीकरण करणे | E126: 5 | K126: =SUM(E126:J126) -> 5
A127: XE23A302/C7-1339 | B127: 4 | D127: प्रभाग क्र. ४ ब मध्ये स.नं.37/2अ,2ब बिडीकामगार वसाहत खराडी संपुर्ण ड्रेनेज लाईन बदलणे | J127: 5 | K127: =SUM(E127:J127) -> 5
A128: RE20A302/C2-958 | B128: 4 | D128: प्रभाग क्र. ४ ब साईनगरी सोसायटी समोरचा कमानीपासुन चा रस्‍ता ते लेन नंदननगर पर्यंत डांबरीकरण करणे | E128: 5 | K128: =SUM(E128:J128) -> 5
A129: XE23A302/C7-1340 | B129: 4 | D129: प्रभाग क्र. ४ ब साईनगरी सोसायटी स.नं.47/5 अ लेन नं.15 चंदननगर पावसाळी पाण्याची लाईन टाकणे | J129: 5 | K129: =SUM(E129:J129) -> 5
A130: RE20A302/C2-959 | B130: 4 | D130: प्रभाग क्र. ४ ब पाराशर सोसायटी लेन नं.6 बालाजी हॉस्‍पिटलच्‍या मागे संपुर्ण रस्‍ता करणे | E130: 5 | K130: =SUM(E130:J130) -> 5
A131: RE20A302/C2-960 | B131: 4 | D131: प्रभाग क्र. ४ ब जुना मुंढवा रोड द्वारका गार्डन ते सुंदराबाई शाळा पर्यंत डिव्‍हायडरची उंची वाढविणे | E131: 5 | K131: =SUM(E131:J131) -> 5
A132: RE22C302/C4-795 | B132: 4 | D132: प्रभाग क्र. ४ क मधील शौचालयाची दुरुस्‍ती करणे | G132: 5 | K132: =SUM(E132:J132) -> 5
A133: XE23A302/C7-1341 | B133: 4 | D133: प्रभाग क्र. ४ क मध्ये चंदननगर खराडी परिसरात ड्रेनेज लाईन व चेंबर साफसफाई करणे | J133: 5 | K133: =SUM(E133:J133) -> 5
A134: XE23A302/C7-1342 | B134: 4 | D134: प्रभाग क्र. ४ क तुकारामनगर, आपले घर, थिटेवस्‍ती, राजाराम पाटील नगर येथील ड्रेनेज दुरुस्‍ती विषयक कामे करणे | J134: 5 | K134: =SUM(E134:J134) -> 5
A135: RE20C302/C1-685 | B135: 4 | D135: प्रभाग क्र. ४ क मध्ये विदयुत विषयक कामे करणे | F135: 5 | K135: =SUM(E135:J135) -> 5
A136: XE23A302/C7-1343 | B136: 4 | D136: प्रभाग क्र. ४ क मधील बोराटे वस्‍ती व परिसरातील ड्रेनेज चेंबर दुरुस्‍ती करणे | J136: 5 | K136: =SUM(E136:J136) -> 5
A137: RE20C302/C1-686 | B137: 4 | D137: प्रभाग क्र. ४ ड मध्ये पथदिवे दुरुस्‍त करणे | F137: 5 | K137: =SUM(E137:J137) -> 5
A138: RE22C302/C4-796 | B138: 4 | D138: प्रभाग क्र. ४ ड मध्ये शौचालय दुरुस्‍ती विषयक कामे करणे | G138: 5 | K138: =SUM(E138:J138) -> 5
A139: XE23A302/C7-1344 | B139: 4 | D139: प्रभाग क्र. ४ ड मध्ये ड्रेनेज विषयक कामे करणे. | J139: 5 | K139: =SUM(E139:J139) -> 5
A140: XE23A302/C7-1345 | B140: 4 | D140: प्रभाग क्र. ४ ड मध्ये खराडी चंदननगर परिसरात चेंबर दुरुस्‍ती करणे | J140: 5 | K140: =SUM(E140:J140) -> 5
A141: RE20A302/C2-961 | B141: 4 | D141: प्रभाग क्र. ४ ड मध्ये खराडी चंदननगर परिसरात डांबरीकरण करणे | E141: 5 | K141: =SUM(E141:J141) -> 5
B142: 4 | D142: 0 | E142: 0 | F142: 0 | G142: 0 | H142: 0 | I142: 0 | J142: 0 | K142: =SUM(E142:J142) -> 0 | L142: 0
B143: 4 | D143: 0 | E143: 0 | F143: 0 | G143: 0 | H143: 0 | I143: 0 | J143: 0 | K143: =SUM(E143:J143) -> 0 | L143: 0
B144: 4 | D144: 0 | E144: 0 | F144: 0 | G144: 0 | H144: 0 | I144: 0 | J144: 0 | K144: =SUM(E144:J144) -> 0 | L144: 0
B145: 4 | D145: 0 | E145: 0 | F145: 0 | G145: 0 | H145: 0 | I145: 0 | J145: 0 | K145: =SUM(E145:J145) -> 0 | L145: 0
B146: 4 | D146: 0 | E146: 0 | F146: 0 | G146: 0 | H146: 0 | I146: 0 | J146: 0 | K146: =SUM(E146:J146) -> 0 | L146: 0
B147: 4 | D147: 0 | E147: 0 | F147: 0 | G147: 0 | H147: 0 | I147: 0 | J147: 0 | K147: =SUM(E147:J147) -> 0 | L147: 0
B148: 4 | D148: 0 | E148: 0 | F148: 0 | G148: 0 | H148: 0 | I148: 0 | J148: 0 | K148: =SUM(E148:J148) -> 0 | L148: 0
B149: 4 | D149: 0 | E149: 0 | F149: 0 | G149: 0 | H149: 0 | I149: 0 | J149: 0 | K149: =SUM(E149:J149) -> 0 | L149: 0
B150: 4 | D150: 0 | E150: 0 | F150: 0 | G150: 0 | H150: 0 | I150: 0 | J150: 0 | K150: =SUM(E150:J150) -> 0 | L150: 0
B151: 4 | D151: 0 | E151: 0 | F151: 0 | G151: 0 | H151: 0 | I151: 0 | J151: 0 | K151: =SUM(E151:J151) -> 0 | L151: 0
B152: 4 | D152: 0 | E152: 0 | F152: 0 | G152: 0 | H152: 0 | I152: 0 | J152: 0 | K152: =SUM(E152:J152) -> 0 | L152: 0
B153: 4 | D153: 0 | E153: 0 | F153: 0 | G153: 0 | H153: 0 | I153: 0 | J153: 0 | K153: =SUM(E153:J153) -> 0 | L153: 0
... B201: 4 | D201: 0 | E201: 0 | F201: 0 | G201: 0 | H201: 0 | I201: 0 | J201: 0 | K201: =SUM(E201:J201) -> 0 | L201: 0
B202: 4 | K202: =SUM(E202:J202) -> 0
B203: 4 | D203: एकूण बेरीज | E203: =SUM(E122:E202) -> 35 | F203: =SUM(F122:F202) -> 15 | G203: =SUM(G122:G202) -> 10 | H203: =SUM(H122:H202) -> 0 | I203: =SUM(I122:I202) -> 0 | J203: =SUM(J122:J202) -> 40 | K203: =SUM(E203:J203) -> 100
K204: =SUM(E204:J204) -> 0
A205: RE20C302/C1-687 | B205: 5 | D205: प्रभाग क्र. 5 अ मध्ये रामवाडी व वडगावंशेरी परिसरात सी सी टी व्‍ही कॅमेरे बसविणे | F205: 5 | K205: =SUM(E205:J205) -> 5
A206: RE22C302/C4-797 | B206: 5 | D206: प्रभाग क्र. 5 अ मध्ये ओपन जिम बसविणे | G206: 5 | K206: =SUM(E206:J206) -> 5
A207: RE20A302/C2-962 | B207: 5 | D207: प्रभाग क्र. 5 अ वडगावंशेरी परिसरात पदपथ करणे व दुरुस्‍ती करणे | E207: 5 | K207: =SUM(E207:J207) -> 5
A208: RE20A302/C2-963 | B208: 5 | D208: प्रभाग क्र. 5 अ वडगावंशेरी परिसरातील रस्‍त्ते दुरुस्‍ती करणे | E208: 5 | K208: =SUM(E208:J208) -> 5
A209: XE23A302/C7-1346 | B209: 5 | D209: प्रभाग क्र. 5 अ वडगावंशेरी मधील विविध ठिकाणच्‍या ड्रेनेज लाईन दुरुस्‍त करणे व साफ करणे | J209: 5 | K209: =SUM(E209:J209) -> 5
...

Sheet CitizensPlan2223
A1: code | B1: ward | C1: * | D1: क्षेत्रीय कार्यालयाने नागरिकांच्या सहभागातून करावयाची योजनांतर्गत कामे : सन 2022-23 | E1: पथ | F1: विद्युत | G1: भवन | H1: झोनिपु | I1: पाणीपुरवठा | J1: मलनिःसारण | K1: एकूण | L1: H
D4: (आकडे लाखात) | E4: C2 | F4: C1 | G4: C4 | H4: C5 | I4: C6 | J4: C7
A6: code | B6: Sr. | C6: Wards | D6: क्षेत्रीय कार्यालयाने नागरिकांच्या सहभागातून करावयाची योजनांतर्गत कामे : सन 2022-23 | E6: CE20A1196/C2- | F6: CE20C406/C1- | G6: CE22A547/C4- | H6: FE14A121/C5- | I6: ZE16A117/C6- | J6: ZE16B130/C7- | K6: Total
B8: 1 | C8: 3, 4, 5 | D8: =D289 -> नगररोड - वडगावशेरी क्षेत्रीय कार्यालय एकूण बेरीज | E8: =E289 -> 0 | F8: =F289 -> 0 | G8: =G289 -> 0 | H8: =H289 -> 0 | I8: =I289 -> 0 | J8: =J289 -> 0 | K8: =SUM(E8:J8) -> 0
B9: 2 | C9: 1, 2, 6 | D9: =D544 -> येरवडा - कळस - धानोरी क्षेत्रीय कार्यालय एकूण बेरीज | E9: =E544 -> 0 | F9: =F544 -> 0 | G9: =G544 -> 0 | H9: =H544 -> 0 | I9: =I544 -> 0 | J9: =J544 -> 0 | K9: =SUM(E9:J9) -> 0
B10: 3 | C10: 20, 21 | D10: =D716 -> ढोलेपाटील क्षेत्रीय कार्यालय एकूण बेरीज | E10: =E716 -> 0 | F10: =F716 -> 0 | G10: =G716 -> 0 | H10: =H716 -> 0 | I10: =I716 -> 0 | J10: =J716 -> 0 | K10: =SUM(E10:J10) -> 0
B11: 4 | C11: 8, 9 | D11: =D888 -> औंध - बाणेर क्षेत्रीय कार्यालय एकूण बेरीज | E11: =E888 -> 0 | F11: =F888 -> 0 | G11: =G888 -> 0 | H11: =H888 -> 0 | I11: =I888 -> 0 | J11: =J888 -> 0 | K11: =SUM(E11:J11) -> 0
B12: 5 | C12: 7, 14 | D12: =D1060 -> शिवाजीनगर - घोले रोड क्षेत्रीय कार्यालय एकूण बेरीज | E12: =E1060 -> 0 | F12: =F1060 -> 0 | G12: =G1060 -> 0 | H12: =H1060 -> 0 | I12: =I1060 -> 0 | J12: =J1060 -> 0 | K12: =SUM(E12:J12) -> 0
B13: 6 | C13: 10, 11, 12 | D13: =D1315 -> कोथरूड - बावधन क्षेत्रीय कार्यालय एकूण बेरीज | E13: =E1315 -> 46.5 | F13: =F1315 -> 25 | G13: =G1315 -> 0 | H13: =H1315 -> 0 | I13: =I1315 -> 5 | J13: =J1315 -> 37.5 | K13: =SUM(E13:J13) -> 114
B14: 7 | C14: 35, 39, 40 | D14: =D1570 -> धनकवडी - सहकारनगर क्षेत्रीय कार्यालय एकूण बेरीज | E14: =E1570 -> 31 | F14: =F1570 -> 24 | G14: =G1570 -> 31 | H14: =H1570 -> 0 | I14: =I1570 -> 5 | J14: =J1570 -> 24 | K14: =SUM(E14:J14) -> 115
B15: 8 | C15: 30, 33, 34 | D15: =D1825 -> सिंहगड रोड क्षेत्रीय कार्यालय एकूण बेरीज | E15: =E1825 -> 105 | F15: =F1825 -> 40 | G15: =G1825 -> 0 | H15: =H1825 -> 5 | I15: =I1825 -> 0 | J15: =J1825 -> 30 | K15: =SUM(E15:J15) -> 180
B16: 9 | C16: 13, 31, 32 | D16: =D2080 -> वारजे - कर्वेनगर क्षेत्रीय कार्यालय एकूण बेरीज | E16: =E2080 -> 42.5 | F16: =F2080 -> 15 | G16: =G2080 -> 40 | H16: =H2080 -> 47.5 | I16: =I2080 -> 0 | J16: =J2080 -> 24 | K16: =SUM(E16:J16) -> 169
B17: 10 | C17: 22, 23, 26 | D17: =D2335 -> हडपसर - मुंढवा क्षेत्रीय कार्यालय एकूण बेरीज | E17: =E2335 -> 0 | F17: =F2335 -> 0 | G17: =G2335 -> 0 | H17: =H2335 -> 0 | I17: =I2335 -> 0 | J17: =J2335 -> 0 | K17: =SUM(E17:J17) -> 0
B18: 11 | C18: 24, 25, 27 | D18: =D2590 -> वानवडी - रामटेकडी क्षेत्रीय कार्यालय एकूण बेरीज | E18: =E2590 -> 0 | F18: =F2590 -> 0 | G18: =G2590 -> 0 | H18: =H2590 -> 0 | I18: =I2590 -> 5 | J18: =J2590 -> 0 | K18: =SUM(E18:J18) -> 5
B19: 12 | C19: 38, 41 | D19: =D2762 -> कोंढवा - येवलेवाडी क्षेत्रीय कार्यालय एकूण बेरीज | E19: =E2762 -> 103 | F19: =F2762 -> 24 | G19: =G2762 -> 0 | H19: =H2762 -> 0 | I19: =I2762 -> 0 | J19: =J2762 -> 21 | K19: =SUM(E19:J19) -> 148
B20: 13 | C20: 15, 16, 29 | D20: =D3017 -> कसबा - विश्रामबागवाडा क्षेत्रीय कार्यालय एकूण बेरीज | E20: =E3017 -> 0 | F20: =F3017 -> 0 | G20: =G3017 -> 0 | H20: =H3017 -> 0 | I20: =I3017 -> 0 | J20: =J3017 -> 0 | K20: =SUM(E20:J20) -> 0
B21: 14 | C21: 17, 18, 19 | D21: =D3272 -> भवानी पेठ क्षेत्रीय कार्यालय एकूण बेरीज | E21: =E3272 -> 0 | F21: =F3272 -> 0 | G21: =G3272 -> 0 | H21: =H3272 -> 0 | I21: =I3272 -> 0 | J21: =J3272 -> 0 | K21: =SUM(E21:J21) -> 0
B22: 15 | C22: 28, 36, 37 | D22: =D3527 -> बिबवेवाडी क्षेत्रीय कार्यालय एकूण बेरीज | E22: =E3527 -> 41 | F22: =F3527 -> 23 | G22: =G3527 -> 10 | H22: =H3527 -> 3 | I22: =I3527 -> 0 | J22: =J3527 -> 33 | K22: =SUM(E22:J22) -> 110
B23: 16 | C23: 42 | D23: =D3699 -> नव्याने समाविष्ट झालेली गावे एकूण बेरीज | E23: =E3699 -> 10 | F23: =F3699 -> 5 | G23: =G3699 -> 5 | H23: =H3699 -> 0 | I23: =I3699 -> 0 | J23: =J3699 -> 0 | K23: =SUM(E23:J23) -> 20
C25: =SUM(C8:C24) -> 42 | D25: =""&TEXT(D6,"0")&" एकूण बेरीज" -> क्षेत्रीय कार्यालयाने नागरिकांच्या सहभागातून करावयाची योजनांतर्गत कामे : सन 2022-23 एकूण बेरीज | E25: =SUM(E8:E24) -> 379 | F25: =SUM(F8:F24) -> 156 | G25: =SUM(G8:G24) -> 86 | H25: =SUM(H8:H24) -> 55.5 | I25: =SUM(I8:I24) -> 15 | J25: =SUM(J8:J24) -> 169.5 | K25: =SUM(K8:K24) -> 861
E27: =E25*100000 -> 37900000 | F27: =F25*100000 -> 15600000 | G27: =G25*100000 -> 8600000 | H27: =H25*100000 -> 5550000 | I27: =I25*100000 -> 1500000 | J27: =J25*100000 -> 16950000 | K27: =K25*100000 -> 86100000 | L27: 0
D37: नगररोड - वडगावशेरी क्षेत्रीय कार्यालय | K37: =SUM(E37:J37) -> 0 | L37: 0
K38: =SUM(E38:J38) -> 0 | L38: 0
B39: 3 | D39: 0 | E39: 0 | F39: 0 | G39: 0 | H39: 0 | I39: 0 | J39: 0 | K39: =SUM(E39:J39) -> 0 | L39: 0
B40: 3 | D40: 0 | E40: 0 | F40: 0 | G40: 0 | H40: 0 | I40: 0 | J40: 0 | K40: =SUM(E40:J40) -> 0 | L40: 0
B41: 3 | D41: 0 | E41: 0 | F41: 0 | G41: 0 | H41: 0 | I41: 0 | J41: 0 | K41: =SUM(E41:J41) -> 0 | L41: 0
B42: 3 | D42: 0 | E42: 0 | F42: 0 | G42: 0 | H42: 0 | I42: 0 | J42: 0 | K42: =SUM(E42:J42) -> 0 | L42: 0
B43: 3 | D43: 0 | E43: 0 | F43: 0 | G43: 0 | H43: 0 | I43: 0 | J43: 0 | K43: =SUM(E43:J43) -> 0 | L43: 0
B44: 3 | D44: 0 | E44: 0 | F44: 0 | G44: 0 | H44: 0 | I44: 0 | J44: 0 | K44: =SUM(E44:J44) -> 0 | L44: 0
B45: 3 | D45: 0 | E45: 0 | F45: 0 | G45: 0 | H45: 0 | I45: 0 | J45: 0 | K45: =SUM(E45:J45) -> 0 | L45: 0
B46: 3 | D46: 0 | E46: 0 | F46: 0 | G46: 0 | H46: 0 | I46: 0 | J46: 0 | K46: =SUM(E46:J46) -> 0 | L46: 0
B47: 3 | D47: 0 | E47: 0 | F47: 0 | G47: 0 | H47: 0 | I47: 0 | J47: 0 | K47: =SUM(E47:J47) -> 0 | L47: 0
B48: 3 | D48: 0 | E48: 0 | F48: 0 | G48: 0 | H48: 0 | I48: 0 | J48: 0 | K48: =SUM(E48:J48) -> 0 | L48: 0
B49: 3 | D49: 0 | E49: 0 | F49: 0 | G49: 0 | H49: 0 | I49: 0 | J49: 0 | K49: =SUM(E49:J49) -> 0 | L49: 0
B50: 3 | D50: 0 | E50: 0 | F50: 0 | G50: 0 | H50: 0 | I50: 0 | J50: 0 | K50: =SUM(E50:J50) -> 0 | L50: 0
... B118: 3 | D118: 0 | E118: 0 | F118: 0 | G118: 0 | H118: 0 | I118: 0 | J118: 0 | K118: =SUM(E118:J118) -> 0 | L118: 0
B119: 3 | K119: =SUM(E119:J119) -> 0 | L119: 0
B120: 3 | D120: एकूण बेरीज | E120: =SUM(E39:E119) -> 0 | F120: =SUM(F39:F119) -> 0 | G120: =SUM(G39:G119) -> 0 | H120: =SUM(H39:H119) -> 0 | I120: =SUM(I39:I119) -> 0 | J120: =SUM(J39:J119) -> 0 | K120: =SUM(E120:J120) -> 0 | L120: 0
K121: =SUM(E121:J121) -> 0 | L121: 0
B122: 4 | D122: 0 | E122: 0 | F122: 0 | G122: 0 | H122: 0 | I122: 0 | J122: 0 | K122: =SUM(E122:J122) -> 0 | L122: 0
B123: 4 | D123: 0 | E123: 0 | F123: 0 | G123: 0 | H123: 0 | I123: 0 | J123: 0 | K123: =SUM(E123:J123) -> 0 | L123: 0
B124: 4 | D124: 0 | E124: 0 | F124: 0 | G124: 0 | H124: 0 | I124: 0 | J124: 0 | K124: =SUM(E124:J124) -> 0 | L124: 0
B125: 4 | D125: 0 | E125: 0 | F125: 0 | G125: 0 | H125: 0 | I125: 0 | J125: 0 | K125: =SUM(E125:J125) -> 0 | L125: 0
B126: 4 | D126: 0 | E126: 0 | F126: 0 | G126: 0 | H126: 0 | I126: 0 | J126: 0 | K126: =SUM(E126:J126) -> 0 | L126: 0
B127: 4 | D127: 0 | E127: 0 | F127: 0 | G127: 0 | H127: 0 | I127: 0 | J127: 0 | K127: =SUM(E127:J127) -> 0 | L127: 0
B128: 4 | D128: 0 | E128: 0 | F128: 0 | G128: 0 | H128: 0 | I128: 0 | J128: 0 | K128: =SUM(E128:J128) -> 0 | L128: 0
B129: 4 | D129: 0 | E129: 0 | F129: 0 | G129: 0 | H129: 0 | I129: 0 | J129: 0 | K129: =SUM(E129:J129) -> 0 | L129: 0
B130: 4 | D130: 0 | E130: 0 | F130: 0 | G130: 0 | H130: 0 | I130: 0 | J130: 0 | K130: =SUM(E130:J130) -> 0 | L130: 0
B131: 4 | D131: 0 | E131: 0 | F131: 0 | G131: 0 | H131: 0 | I131: 0 | J131: 0 | K131: =SUM(E131:J131) -> 0 | L131: 0
B132: 4 | D132: 0 | E132: 0 | F132: 0 | G132: 0 | H132: 0 | I132: 0 | J132: 0 | K132: =SUM(E132:J132) -> 0 | L132: 0
B133: 4 | D133: 0 | E133: 0 | F133: 0 | G133: 0 | H133: 0 | I133: 0 | J133: 0 | K133: =SUM(E133:J133) -> 0 | L133: 0
... B201: 4 | D201: 0 | E201: 0 | F201: 0 | G201: 0 | H201: 0 | I201: 0 | J201: 0 | K201: =SUM(E201:J201) -> 0 | L201: 0
B202: 4 | K202: =SUM(E202:J202) -> 0 | L202: 0
B203: 4 | D203: एकूण बेरीज | E203: =SUM(E122:E202) -> 0 | F203: =SUM(F122:F202) -> 0 | G203: =SUM(G122:G202) -> 0 | H203: =SUM(H122:H202) -> 0 | I203: =SUM(I122:I202) -> 0 | J203: =SUM(J122:J202) -> 0 | K203: =SUM(E203:J203) -> 0 | L203: 0
K204: =SUM(E204:J204) -> 0 | L204: 0
B205: 5 | D205: 0 | E205: 0 | F205: 0 | G205: 0 | H205: 0 | I205: 0 | J205: 0 | K205: =SUM(E205:J205) -> 0 | L205: 0
B206: 5 | D206: 0 | E206: 0 | F206: 0 | G206: 0 | H206: 0 | I206: 0 | J206: 0 | K206: =SUM(E206:J206) -> 0 | L206: 0
B207: 5 | D207: 0 | E207: 0 | F207: 0 | G207: 0 | H207: 0 | I207: 0 | J207: 0 | K207: =SUM(E207:J207) -> 0 | L207: 0
B208: 5 | D208: 0 | E208: 0 | F208: 0 | G208: 0 | H208: 0 | I208: 0 | J208: 0 | K208: =SUM(E208:J208) -> 0 | L208: 0
B209: 5 | D209: 0 | E209: 0 | F209: 0 | G209: 0 | H209: 0 | I209: 0 | J209: 0 | K209: =SUM(E209:J209) -> 0 | L209: 0
B210: 5 | D210: 0 | E210: 0 | F210: 0 | G210: 0 | H210: 0 | I210: 0 | J210: 0 | K210: =SUM(E210:J210) -> 0 | L210: 0
B211: 5 | D211: 0 | E211: 0 | F211: 0 | G211: 0 | H211: 0 | I211: 0 | J211: 0 | K211: =SUM(E211:J211) -> 0 | L211: 0
B212: 5 | D212: 0 | E212: 0 | F212: 0 | G212: 0 | H212: 0 | I212: 0 | J212: 0 | K212: =SUM(E212:J212) -> 0 | L212: 0
B213: 5 | D213: 0 | E213: 0 | F213: 0 | G213: 0 | H213: 0 | I213: 0 | J213: 0 | K213: =SUM(E213:J213) -> 0 | L213: 0
B214: 5 | D214: 0 | E214: 0 | F214: 0 | G214: 0 | H214: 0 | I214: 0 | J214: 0 | K214: =SUM(E214:J214) -> 0 | L214: 0
B215: 5 | D215: 0 | E215: 0 | F215: 0 | G215: 0 | H215: 0 | I215: 0 | J215: 0 | K215: =SUM(E215:J215) -> 0 | L215: 0
B216: 5 | D216: 0 | E216: 0 | F216: 0 | G216: 0 | H216: 0 | I216: 0 | J216: 0 | K216: =SUM(E216:J216) -> 0 | L216: 0
... B284: 5 | D284: 0 | E284: 0 | F284: 0 | G284: 0 | H284: 0 | I284: 0 | J284: 0 | K284: =SUM(E284:J284) -> 0 | L284: 0
B285: 5 | K285: =SUM(E285:J285) -> 0 | L285: 0
B286: 5 | D286: एकूण बेरीज | E286: =SUM(E205:E285) -> 0 | F286: =SUM(F205:F285) -> 0 | G286: =SUM(G205:G285) -> 0 | H286: =SUM(H205:H285) -> 0 | I286: =SUM(I205:I285) -> 0 | J286: =SUM(J205:J285) -> 0 | K286: =SUM(E286:J286) -> 0 | L286: 0
K287: =SUM(E287:J287) -> 0 | L287: 0
K288: =SUM(E288:J288) -> 0 | L288: 0
B289: 0 | D289: =""&TEXT(D37,"0")&" एकूण बेरीज" -> नगररोड - वडगावशेरी क्षेत्रीय कार्यालय एकूण बेरीज | E289: =E120+E203+E286 -> 0 | F289: =F120+F203+F286 -> 0 | G289: =G120+G203+G286 -> 0 | H289: =H120+H203+H286 -> 0 | I289: =I120+I203+I286 -> 0 | J289: =J120+J203+J286 -> 0 | K289: =SUM(E289:J289) -> 0 | L289: 0
K290: =SUM(E290:J290) -> 0 | L290: 0
K291: =SUM(E291:J291) -> 0 | L291: 0
D292: येरवडा - कळस - धानोरी क्षेत्रीय कार्यालय | K292: =SUM(E292:J292) -> 0 | L292: 0
K293: =SUM(E293:J293) -> 0 | L293: 0
B294: 1 | D294: 0 | E294: 0 | F294: 0 | G294: 0 | H294: 0 | I294: 0 | J294: 0 | K294: =SUM(E294:J294) -> 0 | L294: 0
B295: 1 | D295: 0 | E295: 0 | F295: 0 | G295: 0 | H295: 0 | I295: 0 | J295: 0 | K295: =SUM(E295:J295) -> 0 | L295: 0
B296: 1 | D296: 0 | E296: 0 | F296: 0 | G296: 0 | H296: 0 | I296: 0 | J296: 0 | K296: =SUM(E296:J296) -> 0 | L296: 0
B297: 1 | D297: 0 | E297: 0 | F297: 0 | G297: 0 | H297: 0 | I297: 0 | J297: 0 | K297: =SUM(E297:J297) -> 0 | L297: 0
B298: 1 | D298: 0 | E298: 0 | F298: 0 | G298: 0 | H298: 0 | I298: 0 | J298: 0 | K298: =SUM(E298:J298) -> 0 | L298: 0
B299: 1 | D299: 0 | E299: 0 | F299: 0 | G299: 0 | H299: 0 | I299: 0 | J299: 0 | K299: =SUM(E299:J299) -> 0 | L299: 0
B300: 1 | D300: 0 | E300: 0 | F300: 0 | G300: 0 | H300: 0 | I300: 0 | J300: 0 | K300: =SUM(E300:J300) -> 0 | L300: 0
B301: 1 | D301: 0 | E301: 0 | F301: 0 | G301: 0 | H301: 0 | I301: 0 | J301: 0 | K301: =SUM(E301:J301) -> 0 | L301: 0
